package c.a.a.a.a.e;

import java.io.BufferedInputStream;
import java.io.BufferedOutputStream;
import java.io.ByteArrayOutputStream;
import java.io.Closeable;
import java.io.Flushable;
import java.io.IOException;
import java.io.InputStream;
import java.io.OutputStream;
import java.net.HttpURLConnection;
import java.net.InetSocketAddress;
import java.net.MalformedURLException;
import java.net.Proxy;
import java.net.Proxy.Type;
import java.net.URL;
import java.nio.ByteBuffer;
import java.nio.CharBuffer;
import java.nio.charset.Charset;
import java.nio.charset.CharsetEncoder;
import java.util.Iterator;
import java.util.Map;
import java.util.Map.Entry;
import java.util.Set;
import java.util.concurrent.Callable;
import java.util.zip.GZIPInputStream;

public class d
{
  private static final String[] b = new String[0];
  private static b c = b.a;
  public final URL a;
  private HttpURLConnection d = null;
  private final String e;
  private e f;
  private boolean g;
  private boolean h = true;
  private boolean i = false;
  private int j = 8192;
  private String k;
  private int l;

  public d(CharSequence paramCharSequence, String paramString)
    throws d.c
  {
    try
    {
      this.a = new URL(paramCharSequence.toString());
      this.e = paramString;
      return;
    }
    catch (MalformedURLException localMalformedURLException)
    {
      throw new c(localMalformedURLException);
    }
  }

  public static d a(CharSequence paramCharSequence, Map<?, ?> paramMap, boolean paramBoolean)
  {
    String str = a(paramCharSequence, paramMap);
    if (paramBoolean)
      str = a(str);
    return b(str);
  }

  // ERROR //
  public static String a(CharSequence paramCharSequence)
    throws d.c
  {
    // Byte code:
    //   0: new 54	java/net/URL
    //   3: dup
    //   4: aload_0
    //   5: invokeinterface 60 1 0
    //   10: invokespecial 63	java/net/URL:<init>	(Ljava/lang/String;)V
    //   13: astore_1
    //   14: aload_1
    //   15: invokevirtual 88	java/net/URL:getHost	()Ljava/lang/String;
    //   18: astore_2
    //   19: aload_1
    //   20: invokevirtual 92	java/net/URL:getPort	()I
    //   23: istore_3
    //   24: iload_3
    //   25: iconst_m1
    //   26: if_icmpeq +30 -> 56
    //   29: new 94	java/lang/StringBuilder
    //   32: dup
    //   33: invokespecial 95	java/lang/StringBuilder:<init>	()V
    //   36: aload_2
    //   37: invokevirtual 99	java/lang/StringBuilder:append	(Ljava/lang/String;)Ljava/lang/StringBuilder;
    //   40: bipush 58
    //   42: invokevirtual 102	java/lang/StringBuilder:append	(C)Ljava/lang/StringBuilder;
    //   45: iload_3
    //   46: invokestatic 107	java/lang/Integer:toString	(I)Ljava/lang/String;
    //   49: invokevirtual 99	java/lang/StringBuilder:append	(Ljava/lang/String;)Ljava/lang/StringBuilder;
    //   52: invokevirtual 108	java/lang/StringBuilder:toString	()Ljava/lang/String;
    //   55: astore_2
    //   56: new 110	java/net/URI
    //   59: dup
    //   60: aload_1
    //   61: invokevirtual 113	java/net/URL:getProtocol	()Ljava/lang/String;
    //   64: aload_2
    //   65: aload_1
    //   66: invokevirtual 116	java/net/URL:getPath	()Ljava/lang/String;
    //   69: aload_1
    //   70: invokevirtual 119	java/net/URL:getQuery	()Ljava/lang/String;
    //   73: aload_1
    //   74: invokevirtual 122	java/net/URL:getRef	()Ljava/lang/String;
    //   77: invokespecial 125	java/net/URI:<init>	(Ljava/lang/String;Ljava/lang/String;Ljava/lang/String;Ljava/lang/String;Ljava/lang/String;)V
    //   80: invokevirtual 128	java/net/URI:toASCIIString	()Ljava/lang/String;
    //   83: astore 7
    //   85: aload 7
    //   87: bipush 63
    //   89: invokevirtual 132	java/lang/String:indexOf	(I)I
    //   92: istore 8
    //   94: iload 8
    //   96: ifle +70 -> 166
    //   99: iload 8
    //   101: iconst_1
    //   102: iadd
    //   103: aload 7
    //   105: invokevirtual 135	java/lang/String:length	()I
    //   108: if_icmpge +58 -> 166
    //   111: new 94	java/lang/StringBuilder
    //   114: dup
    //   115: invokespecial 95	java/lang/StringBuilder:<init>	()V
    //   118: aload 7
    //   120: iconst_0
    //   121: iload 8
    //   123: iconst_1
    //   124: iadd
    //   125: invokevirtual 139	java/lang/String:substring	(II)Ljava/lang/String;
    //   128: invokevirtual 99	java/lang/StringBuilder:append	(Ljava/lang/String;)Ljava/lang/StringBuilder;
    //   131: aload 7
    //   133: iload 8
    //   135: iconst_1
    //   136: iadd
    //   137: invokevirtual 141	java/lang/String:substring	(I)Ljava/lang/String;
    //   140: ldc 143
    //   142: ldc 145
    //   144: invokevirtual 149	java/lang/String:replace	(Ljava/lang/CharSequence;Ljava/lang/CharSequence;)Ljava/lang/String;
    //   147: ldc 151
    //   149: ldc 153
    //   151: invokevirtual 149	java/lang/String:replace	(Ljava/lang/CharSequence;Ljava/lang/CharSequence;)Ljava/lang/String;
    //   154: invokevirtual 99	java/lang/StringBuilder:append	(Ljava/lang/String;)Ljava/lang/StringBuilder;
    //   157: invokevirtual 108	java/lang/StringBuilder:toString	()Ljava/lang/String;
    //   160: astore 9
    //   162: aload 9
    //   164: astore 7
    //   166: aload 7
    //   168: areturn
    //   169: astore 10
    //   171: new 40	c/a/a/a/a/e/d$c
    //   174: dup
    //   175: aload 10
    //   177: invokespecial 70	c/a/a/a/a/e/d$c:<init>	(Ljava/io/IOException;)V
    //   180: athrow
    //   181: astore 4
    //   183: new 83	java/io/IOException
    //   186: dup
    //   187: ldc 155
    //   189: invokespecial 156	java/io/IOException:<init>	(Ljava/lang/String;)V
    //   192: astore 5
    //   194: aload 5
    //   196: aload 4
    //   198: invokevirtual 160	java/io/IOException:initCause	(Ljava/lang/Throwable;)Ljava/lang/Throwable;
    //   201: pop
    //   202: new 40	c/a/a/a/a/e/d$c
    //   205: dup
    //   206: aload 5
    //   208: invokespecial 70	c/a/a/a/a/e/d$c:<init>	(Ljava/io/IOException;)V
    //   211: athrow
    //
    // Exception table:
    //   from	to	target	type
    //   0	14	169	java/io/IOException
    //   56	94	181	java/net/URISyntaxException
    //   99	162	181	java/net/URISyntaxException
  }

  public static String a(CharSequence paramCharSequence, Map<?, ?> paramMap)
  {
    String str = paramCharSequence.toString();
    if ((paramMap == null) || (paramMap.isEmpty()))
      return str;
    StringBuilder localStringBuilder = new StringBuilder(str);
    a(str, localStringBuilder);
    b(str, localStringBuilder);
    Iterator localIterator = paramMap.entrySet().iterator();
    Map.Entry localEntry1 = (Map.Entry)localIterator.next();
    localStringBuilder.append(localEntry1.getKey().toString());
    localStringBuilder.append('=');
    Object localObject1 = localEntry1.getValue();
    if (localObject1 != null)
      localStringBuilder.append(localObject1);
    while (localIterator.hasNext())
    {
      localStringBuilder.append('&');
      Map.Entry localEntry2 = (Map.Entry)localIterator.next();
      localStringBuilder.append(localEntry2.getKey().toString());
      localStringBuilder.append('=');
      Object localObject2 = localEntry2.getValue();
      if (localObject2 != null)
        localStringBuilder.append(localObject2);
    }
    return localStringBuilder.toString();
  }

  private static StringBuilder a(String paramString, StringBuilder paramStringBuilder)
  {
    if (2 + paramString.indexOf(':') == paramString.lastIndexOf('/'))
      paramStringBuilder.append('/');
    return paramStringBuilder;
  }

  public static d b(CharSequence paramCharSequence)
    throws d.c
  {
    return new d(paramCharSequence, "GET");
  }

  public static d b(CharSequence paramCharSequence, Map<?, ?> paramMap, boolean paramBoolean)
  {
    String str = a(paramCharSequence, paramMap);
    if (paramBoolean)
      str = a(str);
    return c(str);
  }

  private static StringBuilder b(String paramString, StringBuilder paramStringBuilder)
  {
    int m = paramString.indexOf('?');
    int n = -1 + paramStringBuilder.length();
    if (m == -1)
      paramStringBuilder.append('?');
    while ((m >= n) || (paramString.charAt(n) == '&'))
      return paramStringBuilder;
    paramStringBuilder.append('&');
    return paramStringBuilder;
  }

  public static d c(CharSequence paramCharSequence)
    throws d.c
  {
    return new d(paramCharSequence, "POST");
  }

  public static d d(CharSequence paramCharSequence)
    throws d.c
  {
    return new d(paramCharSequence, "PUT");
  }

  public static d e(CharSequence paramCharSequence)
    throws d.c
  {
    return new d(paramCharSequence, "DELETE");
  }

  private static String f(String paramString)
  {
    if ((paramString != null) && (paramString.length() > 0))
      return paramString;
    return "UTF-8";
  }

  private Proxy p()
  {
    return new Proxy(Proxy.Type.HTTP, new InetSocketAddress(this.k, this.l));
  }

  private HttpURLConnection q()
  {
    try
    {
      if (this.k != null);
      HttpURLConnection localHttpURLConnection;
      for (Object localObject = c.a(this.a, p()); ; localObject = localHttpURLConnection)
      {
        ((HttpURLConnection)localObject).setRequestMethod(this.e);
        return localObject;
        localHttpURLConnection = c.a(this.a);
      }
    }
    catch (IOException localIOException)
    {
      throw new c(localIOException);
    }
  }

  public int a(String paramString, int paramInt)
    throws d.c
  {
    k();
    return a().getHeaderFieldInt(paramString, paramInt);
  }

  public d a(int paramInt)
  {
    a().setConnectTimeout(paramInt);
    return this;
  }

  protected d a(final InputStream paramInputStream, final OutputStream paramOutputStream)
    throws IOException
  {
    return (d)new a(paramInputStream, this.h)
    {
      public d a()
        throws IOException
      {
        byte[] arrayOfByte = new byte[d.a(d.this)];
        while (true)
        {
          int i = paramInputStream.read(arrayOfByte);
          if (i == -1)
            break;
          paramOutputStream.write(arrayOfByte, 0, i);
        }
        return d.this;
      }
    }
    .call();
  }

  public d a(String paramString, Number paramNumber)
    throws d.c
  {
    return a(paramString, null, paramNumber);
  }

  public d a(String paramString1, String paramString2)
  {
    a().setRequestProperty(paramString1, paramString2);
    return this;
  }

  public d a(String paramString1, String paramString2, Number paramNumber)
    throws d.c
  {
    if (paramNumber != null);
    for (String str = paramNumber.toString(); ; str = null)
      return b(paramString1, paramString2, str);
  }

  protected d a(String paramString1, String paramString2, String paramString3)
    throws IOException
  {
    StringBuilder localStringBuilder = new StringBuilder();
    localStringBuilder.append("form-data; name=\"").append(paramString1);
    if (paramString2 != null)
      localStringBuilder.append("\"; filename=\"").append(paramString2);
    localStringBuilder.append('"');
    f("Content-Disposition", localStringBuilder.toString());
    if (paramString3 != null)
      f("Content-Type", paramString3);
    return f("\r\n");
  }

  // ERROR //
  public d a(String paramString1, String paramString2, String paramString3, java.io.File paramFile)
    throws d.c
  {
    // Byte code:
    //   0: new 317	java/io/BufferedInputStream
    //   3: dup
    //   4: new 319	java/io/FileInputStream
    //   7: dup
    //   8: aload 4
    //   10: invokespecial 322	java/io/FileInputStream:<init>	(Ljava/io/File;)V
    //   13: invokespecial 325	java/io/BufferedInputStream:<init>	(Ljava/io/InputStream;)V
    //   16: astore 5
    //   18: aload_0
    //   19: aload_1
    //   20: aload_2
    //   21: aload_3
    //   22: aload 5
    //   24: invokevirtual 328	c/a/a/a/a/e/d:a	(Ljava/lang/String;Ljava/lang/String;Ljava/lang/String;Ljava/io/InputStream;)Lc/a/a/a/a/e/d;
    //   27: astore 9
    //   29: aload 5
    //   31: ifnull +8 -> 39
    //   34: aload 5
    //   36: invokevirtual 333	java/io/InputStream:close	()V
    //   39: aload 9
    //   41: areturn
    //   42: astore 6
    //   44: aconst_null
    //   45: astore 5
    //   47: new 40	c/a/a/a/a/e/d$c
    //   50: dup
    //   51: aload 6
    //   53: invokespecial 70	c/a/a/a/a/e/d$c:<init>	(Ljava/io/IOException;)V
    //   56: athrow
    //   57: astore 7
    //   59: aload 5
    //   61: ifnull +8 -> 69
    //   64: aload 5
    //   66: invokevirtual 333	java/io/InputStream:close	()V
    //   69: aload 7
    //   71: athrow
    //   72: astore 10
    //   74: aload 9
    //   76: areturn
    //   77: astore 8
    //   79: goto -10 -> 69
    //   82: astore 7
    //   84: aconst_null
    //   85: astore 5
    //   87: goto -28 -> 59
    //   90: astore 6
    //   92: goto -45 -> 47
    //
    // Exception table:
    //   from	to	target	type
    //   0	18	42	java/io/IOException
    //   18	29	57	finally
    //   47	57	57	finally
    //   34	39	72	java/io/IOException
    //   64	69	77	java/io/IOException
    //   0	18	82	finally
    //   18	29	90	java/io/IOException
  }

  public d a(String paramString1, String paramString2, String paramString3, InputStream paramInputStream)
    throws d.c
  {
    try
    {
      m();
      a(paramString1, paramString2, paramString3);
      a(paramInputStream, this.f);
      return this;
    }
    catch (IOException localIOException)
    {
      throw new c(localIOException);
    }
  }

  public d a(String paramString1, String paramString2, String paramString3, String paramString4)
    throws d.c
  {
    try
    {
      m();
      a(paramString1, paramString2, paramString3);
      this.f.a(paramString4);
      return this;
    }
    catch (IOException localIOException)
    {
      throw new c(localIOException);
    }
  }

  public d a(Map.Entry<String, String> paramEntry)
  {
    return a((String)paramEntry.getKey(), (String)paramEntry.getValue());
  }

  public d a(boolean paramBoolean)
  {
    a().setUseCaches(paramBoolean);
    return this;
  }

  public String a(String paramString)
    throws d.c
  {
    ByteArrayOutputStream localByteArrayOutputStream = c();
    try
    {
      a(e(), localByteArrayOutputStream);
      String str = localByteArrayOutputStream.toString(f(paramString));
      return str;
    }
    catch (IOException localIOException)
    {
      throw new c(localIOException);
    }
  }

  public HttpURLConnection a()
  {
    if (this.d == null)
      this.d = q();
    return this.d;
  }

  public int b()
    throws d.c
  {
    try
    {
      j();
      int m = a().getResponseCode();
      return m;
    }
    catch (IOException localIOException)
    {
      throw new c(localIOException);
    }
  }

  public d b(String paramString1, String paramString2, String paramString3)
    throws d.c
  {
    return a(paramString1, paramString2, null, paramString3);
  }

  public String b(String paramString)
    throws d.c
  {
    k();
    return a().getHeaderField(paramString);
  }

  public String b(String paramString1, String paramString2)
  {
    return c(b(paramString1), paramString2);
  }

  public int c(String paramString)
    throws d.c
  {
    return a(paramString, -1);
  }

  protected ByteArrayOutputStream c()
  {
    int m = i();
    if (m > 0)
      return new ByteArrayOutputStream(m);
    return new ByteArrayOutputStream();
  }

  protected String c(String paramString1, String paramString2)
  {
    String str;
    if ((paramString1 == null) || (paramString1.length() == 0))
    {
      str = null;
      return str;
    }
    int m = paramString1.length();
    int n = 1 + paramString1.indexOf(';');
    if ((n == 0) || (n == m))
      return null;
    int i1 = paramString1.indexOf(';', n);
    int i2;
    int i3;
    if (i1 == -1)
    {
      i2 = n;
      i3 = m;
    }
    while (true)
    {
      if (i2 < i3)
      {
        int i4 = paramString1.indexOf('=', i2);
        if ((i4 != -1) && (i4 < i3) && (paramString2.equals(paramString1.substring(i2, i4).trim())))
        {
          str = paramString1.substring(i4 + 1, i3).trim();
          int i8 = str.length();
          if (i8 != 0)
          {
            if ((i8 <= 2) || ('"' != str.charAt(0)) || ('"' != str.charAt(i8 - 1)))
              break;
            return str.substring(1, i8 - 1);
          }
        }
        int i5 = i3 + 1;
        int i6 = paramString1.indexOf(';', i5);
        if (i6 == -1)
          i6 = m;
        int i7 = i6;
        i2 = i5;
        i3 = i7;
        continue;
      }
      return null;
      i2 = n;
      i3 = i1;
    }
  }

  public d d(String paramString)
  {
    return d(paramString, null);
  }

  public d d(String paramString1, String paramString2)
  {
    if ((paramString2 != null) && (paramString2.length() > 0))
      return a("Content-Type", paramString1 + "; charset=" + paramString2);
    return a("Content-Type", paramString1);
  }

  public String d()
    throws d.c
  {
    return a(g());
  }

  public d e(String paramString1, String paramString2)
  {
    return b(paramString1, null, paramString2);
  }

  public BufferedInputStream e()
    throws d.c
  {
    return new BufferedInputStream(f(), this.j);
  }

  public d f(CharSequence paramCharSequence)
    throws d.c
  {
    try
    {
      l();
      this.f.a(paramCharSequence.toString());
      return this;
    }
    catch (IOException localIOException)
    {
      throw new c(localIOException);
    }
  }

  public d f(String paramString1, String paramString2)
    throws d.c
  {
    return f(paramString1).f(": ").f(paramString2).f("\r\n");
  }

  public InputStream f()
    throws d.c
  {
    if (b() < 400);
    Object localObject;
    while (true)
    {
      try
      {
        InputStream localInputStream2 = a().getInputStream();
        localObject = localInputStream2;
        if ((this.i) && ("gzip".equals(h())))
          break;
        return localObject;
      }
      catch (IOException localIOException3)
      {
        throw new c(localIOException3);
      }
      localObject = a().getErrorStream();
      if (localObject == null)
        try
        {
          InputStream localInputStream1 = a().getInputStream();
          localObject = localInputStream1;
        }
        catch (IOException localIOException1)
        {
          throw new c(localIOException1);
        }
    }
    try
    {
      GZIPInputStream localGZIPInputStream = new GZIPInputStream((InputStream)localObject);
      return localGZIPInputStream;
    }
    catch (IOException localIOException2)
    {
      throw new c(localIOException2);
    }
  }

  public String g()
  {
    return b("Content-Type", "charset");
  }

  public String h()
  {
    return b("Content-Encoding");
  }

  public int i()
  {
    return c("Content-Length");
  }

  protected d j()
    throws IOException
  {
    if (this.f == null)
      return this;
    if (this.g)
      this.f.a("\r\n--00content0boundary00--\r\n");
    if (this.h);
    try
    {
      this.f.close();
      while (true)
      {
        label41: this.f = null;
        return this;
        this.f.close();
      }
    }
    catch (IOException localIOException)
    {
      break label41;
    }
  }

  protected d k()
    throws d.c
  {
    try
    {
      d locald = j();
      return locald;
    }
    catch (IOException localIOException)
    {
      throw new c(localIOException);
    }
  }

  protected d l()
    throws IOException
  {
    if (this.f != null)
      return this;
    a().setDoOutput(true);
    String str = c(a().getRequestProperty("Content-Type"), "charset");
    this.f = new e(a().getOutputStream(), str, this.j);
    return this;
  }

  protected d m()
    throws IOException
  {
    if (!this.g)
    {
      this.g = true;
      d("multipart/form-data; boundary=00content0boundary00").l();
      this.f.a("--00content0boundary00\r\n");
      return this;
    }
    this.f.a("\r\n--00content0boundary00\r\n");
    return this;
  }

  public URL n()
  {
    return a().getURL();
  }

  public String o()
  {
    return a().getRequestMethod();
  }

  public String toString()
  {
    return o() + ' ' + n();
  }

  protected static abstract class a<V> extends d.d<V>
  {
    private final Closeable a;
    private final boolean b;

    protected a(Closeable paramCloseable, boolean paramBoolean)
    {
      this.a = paramCloseable;
      this.b = paramBoolean;
    }

    protected void c()
      throws IOException
    {
      if ((this.a instanceof Flushable))
        ((Flushable)this.a).flush();
      if (this.b);
      try
      {
        this.a.close();
        return;
        this.a.close();
        return;
      }
      catch (IOException localIOException)
      {
      }
    }
  }

  public static abstract interface b
  {
    public static final b a = new b()
    {
      public HttpURLConnection a(URL paramAnonymousURL)
        throws IOException
      {
        return (HttpURLConnection)paramAnonymousURL.openConnection();
      }

      public HttpURLConnection a(URL paramAnonymousURL, Proxy paramAnonymousProxy)
        throws IOException
      {
        return (HttpURLConnection)paramAnonymousURL.openConnection(paramAnonymousProxy);
      }
    };

    public abstract HttpURLConnection a(URL paramURL)
      throws IOException;

    public abstract HttpURLConnection a(URL paramURL, Proxy paramProxy)
      throws IOException;
  }

  public static class c extends RuntimeException
  {
    protected c(IOException paramIOException)
    {
      super();
    }

    public IOException a()
    {
      return (IOException)super.getCause();
    }
  }

  protected static abstract class d<V>
    implements Callable<V>
  {
    protected abstract V b()
      throws d.c, IOException;

    protected abstract void c()
      throws IOException;

    // ERROR //
    public V call()
      throws d.c
    {
      // Byte code:
      //   0: iconst_1
      //   1: istore_1
      //   2: aload_0
      //   3: invokevirtual 21	c/a/a/a/a/e/d$d:b	()Ljava/lang/Object;
      //   6: astore 6
      //   8: aload_0
      //   9: invokevirtual 23	c/a/a/a/a/e/d$d:c	()V
      //   12: aload 6
      //   14: areturn
      //   15: astore 7
      //   17: new 15	c/a/a/a/a/e/d$c
      //   20: dup
      //   21: aload 7
      //   23: invokespecial 26	c/a/a/a/a/e/d$c:<init>	(Ljava/io/IOException;)V
      //   26: athrow
      //   27: astore 5
      //   29: aload 5
      //   31: athrow
      //   32: astore_2
      //   33: aload_0
      //   34: invokevirtual 23	c/a/a/a/a/e/d$d:c	()V
      //   37: aload_2
      //   38: athrow
      //   39: astore 4
      //   41: new 15	c/a/a/a/a/e/d$c
      //   44: dup
      //   45: aload 4
      //   47: invokespecial 26	c/a/a/a/a/e/d$c:<init>	(Ljava/io/IOException;)V
      //   50: athrow
      //   51: astore_3
      //   52: iload_1
      //   53: ifne -16 -> 37
      //   56: new 15	c/a/a/a/a/e/d$c
      //   59: dup
      //   60: aload_3
      //   61: invokespecial 26	c/a/a/a/a/e/d$c:<init>	(Ljava/io/IOException;)V
      //   64: athrow
      //   65: astore_2
      //   66: iconst_0
      //   67: istore_1
      //   68: goto -35 -> 33
      //
      // Exception table:
      //   from	to	target	type
      //   8	12	15	java/io/IOException
      //   2	8	27	c/a/a/a/a/e/d$c
      //   29	32	32	finally
      //   41	51	32	finally
      //   2	8	39	java/io/IOException
      //   33	37	51	java/io/IOException
      //   2	8	65	finally
    }
  }

  public static class e extends BufferedOutputStream
  {
    private final CharsetEncoder a;

    public e(OutputStream paramOutputStream, String paramString, int paramInt)
    {
      super(paramInt);
      this.a = Charset.forName(d.e(paramString)).newEncoder();
    }

    public e a(String paramString)
      throws IOException
    {
      ByteBuffer localByteBuffer = this.a.encode(CharBuffer.wrap(paramString));
      super.write(localByteBuffer.array(), 0, localByteBuffer.limit());
      return this;
    }
  }
}

/* Location:           E:\Study\Tools\apktool2_2\dex2jar-0.0.9.15\classes_viber_dex2jar.jar
 * Qualified Name:     c.a.a.a.a.e.d
 * JD-Core Version:    0.6.2
 */