package com.google.android.gms.internal.ads;

import android.content.Context;
import android.os.Binder;

@zzare
public final class zzaih
  implements zzm
{
  private volatile zzahy zzdax;
  private final Context zzlj;

  public zzaih(Context paramContext)
  {
    this.zzlj = paramContext;
  }

  private final void disconnect()
  {
    if (this.zzdax == null)
      return;
    this.zzdax.disconnect();
    Binder.flushPendingCommands();
  }

  // ERROR //
  public final zzp zzc(zzr<?> paramzzr)
    throws zzaf
  {
    // Byte code:
    //   0: aload_1
    //   1: invokestatic 49	com/google/android/gms/internal/ads/zzahz:zzh	(Lcom/google/android/gms/internal/ads/zzr;)Lcom/google/android/gms/internal/ads/zzahz;
    //   4: astore_2
    //   5: invokestatic 55	com/google/android/gms/ads/internal/zzk:zzln	()Lcom/google/android/gms/common/util/Clock;
    //   8: invokeinterface 61 1 0
    //   13: lstore_3
    //   14: new 63	com/google/android/gms/internal/ads/zzbbs
    //   17: dup
    //   18: invokespecial 64	com/google/android/gms/internal/ads/zzbbs:<init>	()V
    //   21: astore 5
    //   23: new 66	com/google/android/gms/internal/ads/zzail
    //   26: dup
    //   27: aload_0
    //   28: aload 5
    //   30: invokespecial 69	com/google/android/gms/internal/ads/zzail:<init>	(Lcom/google/android/gms/internal/ads/zzaih;Lcom/google/android/gms/internal/ads/zzbbs;)V
    //   33: astore 6
    //   35: new 71	com/google/android/gms/internal/ads/zzaim
    //   38: dup
    //   39: aload_0
    //   40: aload 5
    //   42: invokespecial 72	com/google/android/gms/internal/ads/zzaim:<init>	(Lcom/google/android/gms/internal/ads/zzaih;Lcom/google/android/gms/internal/ads/zzbbs;)V
    //   45: astore 7
    //   47: aload_0
    //   48: new 23	com/google/android/gms/internal/ads/zzahy
    //   51: dup
    //   52: aload_0
    //   53: getfield 18	com/google/android/gms/internal/ads/zzaih:zzlj	Landroid/content/Context;
    //   56: invokestatic 76	com/google/android/gms/ads/internal/zzk:zzlu	()Lcom/google/android/gms/internal/ads/zzazh;
    //   59: invokevirtual 82	com/google/android/gms/internal/ads/zzazh:zzwr	()Landroid/os/Looper;
    //   62: aload 6
    //   64: aload 7
    //   66: invokespecial 85	com/google/android/gms/internal/ads/zzahy:<init>	(Landroid/content/Context;Landroid/os/Looper;Lcom/google/android/gms/common/internal/BaseGmsClient$BaseConnectionCallbacks;Lcom/google/android/gms/common/internal/BaseGmsClient$BaseOnConnectionFailedListener;)V
    //   69: putfield 21	com/google/android/gms/internal/ads/zzaih:zzdax	Lcom/google/android/gms/internal/ads/zzahy;
    //   72: aload_0
    //   73: getfield 21	com/google/android/gms/internal/ads/zzaih:zzdax	Lcom/google/android/gms/internal/ads/zzahy;
    //   76: invokevirtual 88	com/google/android/gms/internal/ads/zzahy:checkAvailabilityAndConnect	()V
    //   79: aload 5
    //   81: new 90	com/google/android/gms/internal/ads/zzaii
    //   84: dup
    //   85: aload_0
    //   86: aload_2
    //   87: invokespecial 93	com/google/android/gms/internal/ads/zzaii:<init>	(Lcom/google/android/gms/internal/ads/zzaih;Lcom/google/android/gms/internal/ads/zzahz;)V
    //   90: getstatic 99	com/google/android/gms/internal/ads/zzaxh:zzdvr	Lcom/google/android/gms/internal/ads/zzbbm;
    //   93: invokestatic 104	com/google/android/gms/internal/ads/zzbas:zza	(Lcom/google/android/gms/internal/ads/zzbbi;Lcom/google/android/gms/internal/ads/zzbam;Ljava/util/concurrent/Executor;)Lcom/google/android/gms/internal/ads/zzbbi;
    //   96: astore 15
    //   98: getstatic 110	com/google/android/gms/internal/ads/zzact:zzcty	Lcom/google/android/gms/internal/ads/zzaci;
    //   101: astore 16
    //   103: aload 15
    //   105: invokestatic 116	com/google/android/gms/internal/ads/zzyr:zzpe	()Lcom/google/android/gms/internal/ads/zzacq;
    //   108: aload 16
    //   110: invokevirtual 122	com/google/android/gms/internal/ads/zzacq:zzd	(Lcom/google/android/gms/internal/ads/zzaci;)Ljava/lang/Object;
    //   113: checkcast 124	java/lang/Integer
    //   116: invokevirtual 128	java/lang/Integer:intValue	()I
    //   119: i2l
    //   120: getstatic 134	java/util/concurrent/TimeUnit:MILLISECONDS	Ljava/util/concurrent/TimeUnit;
    //   123: getstatic 138	com/google/android/gms/internal/ads/zzaxh:zzdvt	Ljava/util/concurrent/ScheduledExecutorService;
    //   126: invokestatic 141	com/google/android/gms/internal/ads/zzbas:zza	(Lcom/google/android/gms/internal/ads/zzbbi;JLjava/util/concurrent/TimeUnit;Ljava/util/concurrent/ScheduledExecutorService;)Lcom/google/android/gms/internal/ads/zzbbi;
    //   129: astore 17
    //   131: aload 17
    //   133: new 143	com/google/android/gms/internal/ads/zzaik
    //   136: dup
    //   137: aload_0
    //   138: invokespecial 145	com/google/android/gms/internal/ads/zzaik:<init>	(Lcom/google/android/gms/internal/ads/zzaih;)V
    //   141: getstatic 99	com/google/android/gms/internal/ads/zzaxh:zzdvr	Lcom/google/android/gms/internal/ads/zzbbm;
    //   144: invokeinterface 150 3 0
    //   149: aload 17
    //   151: invokeinterface 154 1 0
    //   156: checkcast 156	android/os/ParcelFileDescriptor
    //   159: astore 18
    //   161: invokestatic 55	com/google/android/gms/ads/internal/zzk:zzln	()Lcom/google/android/gms/common/util/Clock;
    //   164: invokeinterface 61 1 0
    //   169: lload_3
    //   170: lsub
    //   171: lstore 19
    //   173: new 158	java/lang/StringBuilder
    //   176: dup
    //   177: bipush 52
    //   179: invokespecial 161	java/lang/StringBuilder:<init>	(I)V
    //   182: ldc 163
    //   184: invokevirtual 167	java/lang/StringBuilder:append	(Ljava/lang/String;)Ljava/lang/StringBuilder;
    //   187: lload 19
    //   189: invokevirtual 170	java/lang/StringBuilder:append	(J)Ljava/lang/StringBuilder;
    //   192: ldc 172
    //   194: invokevirtual 167	java/lang/StringBuilder:append	(Ljava/lang/String;)Ljava/lang/StringBuilder;
    //   197: invokevirtual 176	java/lang/StringBuilder:toString	()Ljava/lang/String;
    //   200: invokestatic 182	com/google/android/gms/internal/ads/zzaxa:zzds	(Ljava/lang/String;)V
    //   203: new 184	com/google/android/gms/internal/ads/zzarv
    //   206: dup
    //   207: aload 18
    //   209: invokespecial 187	com/google/android/gms/internal/ads/zzarv:<init>	(Landroid/os/ParcelFileDescriptor;)V
    //   212: getstatic 193	com/google/android/gms/internal/ads/zzaib:CREATOR	Landroid/os/Parcelable$Creator;
    //   215: invokevirtual 196	com/google/android/gms/internal/ads/zzarv:zza	(Landroid/os/Parcelable$Creator;)Lcom/google/android/gms/common/internal/safeparcel/SafeParcelable;
    //   218: checkcast 189	com/google/android/gms/internal/ads/zzaib
    //   221: astore 21
    //   223: aload 21
    //   225: ifnonnull +98 -> 323
    //   228: aconst_null
    //   229: areturn
    //   230: astore 14
    //   232: invokestatic 55	com/google/android/gms/ads/internal/zzk:zzln	()Lcom/google/android/gms/common/util/Clock;
    //   235: invokeinterface 61 1 0
    //   240: lload_3
    //   241: lsub
    //   242: lstore 9
    //   244: new 158	java/lang/StringBuilder
    //   247: dup
    //   248: bipush 52
    //   250: invokespecial 161	java/lang/StringBuilder:<init>	(I)V
    //   253: ldc 163
    //   255: invokevirtual 167	java/lang/StringBuilder:append	(Ljava/lang/String;)Ljava/lang/StringBuilder;
    //   258: lload 9
    //   260: invokevirtual 170	java/lang/StringBuilder:append	(J)Ljava/lang/StringBuilder;
    //   263: ldc 172
    //   265: invokevirtual 167	java/lang/StringBuilder:append	(Ljava/lang/String;)Ljava/lang/StringBuilder;
    //   268: invokevirtual 176	java/lang/StringBuilder:toString	()Ljava/lang/String;
    //   271: invokestatic 182	com/google/android/gms/internal/ads/zzaxa:zzds	(Ljava/lang/String;)V
    //   274: aconst_null
    //   275: areturn
    //   276: astore 11
    //   278: invokestatic 55	com/google/android/gms/ads/internal/zzk:zzln	()Lcom/google/android/gms/common/util/Clock;
    //   281: invokeinterface 61 1 0
    //   286: lload_3
    //   287: lsub
    //   288: lstore 12
    //   290: new 158	java/lang/StringBuilder
    //   293: dup
    //   294: bipush 52
    //   296: invokespecial 161	java/lang/StringBuilder:<init>	(I)V
    //   299: ldc 163
    //   301: invokevirtual 167	java/lang/StringBuilder:append	(Ljava/lang/String;)Ljava/lang/StringBuilder;
    //   304: lload 12
    //   306: invokevirtual 170	java/lang/StringBuilder:append	(J)Ljava/lang/StringBuilder;
    //   309: ldc 172
    //   311: invokevirtual 167	java/lang/StringBuilder:append	(Ljava/lang/String;)Ljava/lang/StringBuilder;
    //   314: invokevirtual 176	java/lang/StringBuilder:toString	()Ljava/lang/String;
    //   317: invokestatic 182	com/google/android/gms/internal/ads/zzaxa:zzds	(Ljava/lang/String;)V
    //   320: aload 11
    //   322: athrow
    //   323: aload 21
    //   325: getfield 200	com/google/android/gms/internal/ads/zzaib:zzdav	Z
    //   328: ifeq +16 -> 344
    //   331: new 39	com/google/android/gms/internal/ads/zzaf
    //   334: dup
    //   335: aload 21
    //   337: getfield 204	com/google/android/gms/internal/ads/zzaib:zzdaw	Ljava/lang/String;
    //   340: invokespecial 206	com/google/android/gms/internal/ads/zzaf:<init>	(Ljava/lang/String;)V
    //   343: athrow
    //   344: aload 21
    //   346: getfield 210	com/google/android/gms/internal/ads/zzaib:zzdat	[Ljava/lang/String;
    //   349: arraylength
    //   350: aload 21
    //   352: getfield 213	com/google/android/gms/internal/ads/zzaib:zzdau	[Ljava/lang/String;
    //   355: arraylength
    //   356: if_icmpne -128 -> 228
    //   359: new 215	java/util/HashMap
    //   362: dup
    //   363: invokespecial 216	java/util/HashMap:<init>	()V
    //   366: astore 22
    //   368: iconst_0
    //   369: istore 23
    //   371: iload 23
    //   373: aload 21
    //   375: getfield 210	com/google/android/gms/internal/ads/zzaib:zzdat	[Ljava/lang/String;
    //   378: arraylength
    //   379: if_icmpge +31 -> 410
    //   382: aload 22
    //   384: aload 21
    //   386: getfield 210	com/google/android/gms/internal/ads/zzaib:zzdat	[Ljava/lang/String;
    //   389: iload 23
    //   391: aaload
    //   392: aload 21
    //   394: getfield 213	com/google/android/gms/internal/ads/zzaib:zzdau	[Ljava/lang/String;
    //   397: iload 23
    //   399: aaload
    //   400: invokevirtual 220	java/util/HashMap:put	(Ljava/lang/Object;Ljava/lang/Object;)Ljava/lang/Object;
    //   403: pop
    //   404: iinc 23 1
    //   407: goto -36 -> 371
    //   410: new 222	com/google/android/gms/internal/ads/zzp
    //   413: dup
    //   414: aload 21
    //   416: getfield 226	com/google/android/gms/internal/ads/zzaib:statusCode	I
    //   419: aload 21
    //   421: getfield 230	com/google/android/gms/internal/ads/zzaib:data	[B
    //   424: aload 22
    //   426: aload 21
    //   428: getfield 233	com/google/android/gms/internal/ads/zzaib:zzac	Z
    //   431: aload 21
    //   433: getfield 237	com/google/android/gms/internal/ads/zzaib:zzad	J
    //   436: invokespecial 240	com/google/android/gms/internal/ads/zzp:<init>	(I[BLjava/util/Map;ZJ)V
    //   439: areturn
    //   440: astore 8
    //   442: goto -210 -> 232
    //
    // Exception table:
    //   from	to	target	type
    //   14	161	230	java/lang/InterruptedException
    //   14	161	276	finally
    //   14	161	440	java/util/concurrent/ExecutionException
  }
}

/* Location:           E:\Study\Tools\apktool2_2\dex2jar-0.0.9.15\classes_viber_2_dex2jar.jar
 * Qualified Name:     com.google.android.gms.internal.ads.zzaih
 * JD-Core Version:    0.6.2
 */