package com.google.android.gms.internal.ads;

import java.io.IOException;
import java.io.InputStream;

public class zzak
  implements zzm
{
  private static final boolean DEBUG = zzag.DEBUG;

  @Deprecated
  private final zzas zzbp;
  private final zzaj zzbq;
  private final zzal zzbr;

  public zzak(zzaj paramzzaj)
  {
    this(paramzzaj, new zzal(4096));
  }

  private zzak(zzaj paramzzaj, zzal paramzzal)
  {
    this.zzbq = paramzzaj;
    this.zzbp = paramzzaj;
    this.zzbr = paramzzal;
  }

  @Deprecated
  public zzak(zzas paramzzas)
  {
    this(paramzzas, new zzal(4096));
  }

  @Deprecated
  private zzak(zzas paramzzas, zzal paramzzal)
  {
    this.zzbp = paramzzas;
    this.zzbq = new zzai(paramzzas);
    this.zzbr = paramzzal;
  }

  private static void zza(String paramString, zzr<?> paramzzr, zzaf paramzzaf)
    throws zzaf
  {
    zzac localzzac = paramzzr.zzj();
    int i = paramzzr.zzi();
    try
    {
      localzzac.zza(paramzzaf);
      Object[] arrayOfObject2 = new Object[2];
      arrayOfObject2[0] = paramString;
      arrayOfObject2[1] = Integer.valueOf(i);
      paramzzr.zzb(String.format("%s-retry [timeout=%s]", arrayOfObject2));
      return;
    }
    catch (zzaf localzzaf)
    {
      Object[] arrayOfObject1 = new Object[2];
      arrayOfObject1[0] = paramString;
      arrayOfObject1[1] = Integer.valueOf(i);
      paramzzr.zzb(String.format("%s-timeout-giveup [timeout=%s]", arrayOfObject1));
      throw localzzaf;
    }
  }

  private final byte[] zza(InputStream paramInputStream, int paramInt)
    throws IOException, zzad
  {
    zzaw localzzaw = new zzaw(this.zzbr, paramInt);
    byte[] arrayOfByte1 = null;
    if (paramInputStream == null)
      try
      {
        throw new zzad();
      }
      finally
      {
        if (paramInputStream == null);
      }
    try
    {
      paramInputStream.close();
      this.zzbr.zza(arrayOfByte1);
      localzzaw.close();
      throw localObject;
      arrayOfByte1 = this.zzbr.zzc(1024);
      while (true)
      {
        int i = paramInputStream.read(arrayOfByte1);
        if (i == -1)
          break;
        localzzaw.write(arrayOfByte1, 0, i);
      }
      byte[] arrayOfByte2 = localzzaw.toByteArray();
      if (paramInputStream != null);
      try
      {
        paramInputStream.close();
        this.zzbr.zza(arrayOfByte1);
        localzzaw.close();
        return arrayOfByte2;
      }
      catch (IOException localIOException2)
      {
        while (true)
          zzag.v("Error occurred when closing InputStream", new Object[0]);
      }
    }
    catch (IOException localIOException1)
    {
      while (true)
        zzag.v("Error occurred when closing InputStream", new Object[0]);
    }
  }

  // ERROR //
  public zzp zzc(zzr<?> paramzzr)
    throws zzaf
  {
    // Byte code:
    //   0: invokestatic 140	android/os/SystemClock:elapsedRealtime	()J
    //   3: lstore_2
    //   4: invokestatic 146	java/util/Collections:emptyList	()Ljava/util/List;
    //   7: astore 4
    //   9: aload_1
    //   10: invokevirtual 150	com/google/android/gms/internal/ads/zzr:zzf	()Lcom/google/android/gms/internal/ads/zzc;
    //   13: astore 15
    //   15: aload 15
    //   17: ifnonnull +77 -> 94
    //   20: invokestatic 154	java/util/Collections:emptyMap	()Ljava/util/Map;
    //   23: astore 16
    //   25: aload_0
    //   26: getfield 36	com/google/android/gms/internal/ads/zzak:zzbq	Lcom/google/android/gms/internal/ads/zzaj;
    //   29: aload_1
    //   30: aload 16
    //   32: invokevirtual 159	com/google/android/gms/internal/ads/zzaj:zza	(Lcom/google/android/gms/internal/ads/zzr;Ljava/util/Map;)Lcom/google/android/gms/internal/ads/zzar;
    //   35: astore 17
    //   37: aload 17
    //   39: invokevirtual 164	com/google/android/gms/internal/ads/zzar:getStatusCode	()I
    //   42: istore 18
    //   44: aload 17
    //   46: invokevirtual 167	com/google/android/gms/internal/ads/zzar:zzq	()Ljava/util/List;
    //   49: astore 4
    //   51: iload 18
    //   53: sipush 304
    //   56: if_icmpne +563 -> 619
    //   59: aload_1
    //   60: invokevirtual 150	com/google/android/gms/internal/ads/zzr:zzf	()Lcom/google/android/gms/internal/ads/zzc;
    //   63: astore 19
    //   65: aload 19
    //   67: ifnonnull +108 -> 175
    //   70: new 169	com/google/android/gms/internal/ads/zzp
    //   73: dup
    //   74: sipush 304
    //   77: aconst_null
    //   78: iconst_1
    //   79: invokestatic 140	android/os/SystemClock:elapsedRealtime	()J
    //   82: lload_2
    //   83: lsub
    //   84: aload 4
    //   86: invokespecial 172	com/google/android/gms/internal/ads/zzp:<init>	(I[BZJLjava/util/List;)V
    //   89: astore 20
    //   91: aload 20
    //   93: areturn
    //   94: new 174	java/util/HashMap
    //   97: dup
    //   98: invokespecial 175	java/util/HashMap:<init>	()V
    //   101: astore 16
    //   103: aload 15
    //   105: getfield 180	com/google/android/gms/internal/ads/zzc:zza	Ljava/lang/String;
    //   108: ifnull +18 -> 126
    //   111: aload 16
    //   113: ldc 182
    //   115: aload 15
    //   117: getfield 180	com/google/android/gms/internal/ads/zzc:zza	Ljava/lang/String;
    //   120: invokeinterface 188 3 0
    //   125: pop
    //   126: aload 15
    //   128: getfield 191	com/google/android/gms/internal/ads/zzc:zzc	J
    //   131: lconst_0
    //   132: lcmp
    //   133: ifle -108 -> 25
    //   136: aload 16
    //   138: ldc 193
    //   140: aload 15
    //   142: getfield 191	com/google/android/gms/internal/ads/zzc:zzc	J
    //   145: invokestatic 198	com/google/android/gms/internal/ads/zzaq:zzb	(J)Ljava/lang/String;
    //   148: invokeinterface 188 3 0
    //   153: pop
    //   154: goto -129 -> 25
    //   157: astore 14
    //   159: ldc 200
    //   161: aload_1
    //   162: new 202	com/google/android/gms/internal/ads/zzae
    //   165: dup
    //   166: invokespecial 203	com/google/android/gms/internal/ads/zzae:<init>	()V
    //   169: invokestatic 205	com/google/android/gms/internal/ads/zzak:zza	(Ljava/lang/String;Lcom/google/android/gms/internal/ads/zzr;Lcom/google/android/gms/internal/ads/zzaf;)V
    //   172: goto -168 -> 4
    //   175: new 207	java/util/TreeSet
    //   178: dup
    //   179: getstatic 211	java/lang/String:CASE_INSENSITIVE_ORDER	Ljava/util/Comparator;
    //   182: invokespecial 214	java/util/TreeSet:<init>	(Ljava/util/Comparator;)V
    //   185: astore 21
    //   187: aload 4
    //   189: invokeinterface 220 1 0
    //   194: ifne +87 -> 281
    //   197: aload 4
    //   199: invokeinterface 224 1 0
    //   204: astore 29
    //   206: aload 29
    //   208: invokeinterface 229 1 0
    //   213: ifeq +68 -> 281
    //   216: aload 21
    //   218: aload 29
    //   220: invokeinterface 233 1 0
    //   225: checkcast 235	com/google/android/gms/internal/ads/zzl
    //   228: invokevirtual 239	com/google/android/gms/internal/ads/zzl:getName	()Ljava/lang/String;
    //   231: invokeinterface 245 2 0
    //   236: pop
    //   237: goto -31 -> 206
    //   240: astore 11
    //   242: aload_1
    //   243: invokevirtual 248	com/google/android/gms/internal/ads/zzr:getUrl	()Ljava/lang/String;
    //   246: invokestatic 251	java/lang/String:valueOf	(Ljava/lang/Object;)Ljava/lang/String;
    //   249: astore 12
    //   251: aload 12
    //   253: invokevirtual 254	java/lang/String:length	()I
    //   256: ifeq +546 -> 802
    //   259: ldc_w 256
    //   262: aload 12
    //   264: invokevirtual 260	java/lang/String:concat	(Ljava/lang/String;)Ljava/lang/String;
    //   267: astore 13
    //   269: new 262	java/lang/RuntimeException
    //   272: dup
    //   273: aload 13
    //   275: aload 11
    //   277: invokespecial 265	java/lang/RuntimeException:<init>	(Ljava/lang/String;Ljava/lang/Throwable;)V
    //   280: athrow
    //   281: new 267	java/util/ArrayList
    //   284: dup
    //   285: aload 4
    //   287: invokespecial 270	java/util/ArrayList:<init>	(Ljava/util/Collection;)V
    //   290: astore 22
    //   292: aload 19
    //   294: getfield 274	com/google/android/gms/internal/ads/zzc:zzg	Ljava/util/List;
    //   297: ifnull +191 -> 488
    //   300: aload 19
    //   302: getfield 274	com/google/android/gms/internal/ads/zzc:zzg	Ljava/util/List;
    //   305: invokeinterface 220 1 0
    //   310: ifne +285 -> 595
    //   313: aload 19
    //   315: getfield 274	com/google/android/gms/internal/ads/zzc:zzg	Ljava/util/List;
    //   318: invokeinterface 224 1 0
    //   323: astore 26
    //   325: aload 26
    //   327: invokeinterface 229 1 0
    //   332: ifeq +263 -> 595
    //   335: aload 26
    //   337: invokeinterface 233 1 0
    //   342: checkcast 235	com/google/android/gms/internal/ads/zzl
    //   345: astore 27
    //   347: aload 21
    //   349: aload 27
    //   351: invokevirtual 239	com/google/android/gms/internal/ads/zzl:getName	()Ljava/lang/String;
    //   354: invokeinterface 277 2 0
    //   359: ifne -34 -> 325
    //   362: aload 22
    //   364: aload 27
    //   366: invokeinterface 278 2 0
    //   371: pop
    //   372: goto -47 -> 325
    //   375: astore 5
    //   377: aconst_null
    //   378: astore 7
    //   380: aload 17
    //   382: astore 6
    //   384: aload 6
    //   386: ifnull +431 -> 817
    //   389: aload 6
    //   391: invokevirtual 164	com/google/android/gms/internal/ads/zzar:getStatusCode	()I
    //   394: istore 8
    //   396: iconst_2
    //   397: anewarray 4	java/lang/Object
    //   400: astore 9
    //   402: aload 9
    //   404: iconst_0
    //   405: iload 8
    //   407: invokestatic 73	java/lang/Integer:valueOf	(I)Ljava/lang/Integer;
    //   410: aastore
    //   411: aload 9
    //   413: iconst_1
    //   414: aload_1
    //   415: invokevirtual 248	com/google/android/gms/internal/ads/zzr:getUrl	()Ljava/lang/String;
    //   418: aastore
    //   419: ldc_w 280
    //   422: aload 9
    //   424: invokestatic 283	com/google/android/gms/internal/ads/zzag:e	(Ljava/lang/String;[Ljava/lang/Object;)V
    //   427: aload 7
    //   429: ifnull +460 -> 889
    //   432: new 169	com/google/android/gms/internal/ads/zzp
    //   435: dup
    //   436: iload 8
    //   438: aload 7
    //   440: iconst_0
    //   441: invokestatic 140	android/os/SystemClock:elapsedRealtime	()J
    //   444: lload_2
    //   445: lsub
    //   446: aload 4
    //   448: invokespecial 172	com/google/android/gms/internal/ads/zzp:<init>	(I[BZJLjava/util/List;)V
    //   451: astore 10
    //   453: iload 8
    //   455: sipush 401
    //   458: if_icmpeq +11 -> 469
    //   461: iload 8
    //   463: sipush 403
    //   466: if_icmpne +361 -> 827
    //   469: ldc_w 285
    //   472: aload_1
    //   473: new 287	com/google/android/gms/internal/ads/zza
    //   476: dup
    //   477: aload 10
    //   479: invokespecial 290	com/google/android/gms/internal/ads/zza:<init>	(Lcom/google/android/gms/internal/ads/zzp;)V
    //   482: invokestatic 205	com/google/android/gms/internal/ads/zzak:zza	(Ljava/lang/String;Lcom/google/android/gms/internal/ads/zzr;Lcom/google/android/gms/internal/ads/zzaf;)V
    //   485: goto -481 -> 4
    //   488: aload 19
    //   490: getfield 293	com/google/android/gms/internal/ads/zzc:zzf	Ljava/util/Map;
    //   493: invokeinterface 294 1 0
    //   498: ifne +97 -> 595
    //   501: aload 19
    //   503: getfield 293	com/google/android/gms/internal/ads/zzc:zzf	Ljava/util/Map;
    //   506: invokeinterface 298 1 0
    //   511: invokeinterface 299 1 0
    //   516: astore 23
    //   518: aload 23
    //   520: invokeinterface 229 1 0
    //   525: ifeq +70 -> 595
    //   528: aload 23
    //   530: invokeinterface 233 1 0
    //   535: checkcast 301	java/util/Map$Entry
    //   538: astore 24
    //   540: aload 21
    //   542: aload 24
    //   544: invokeinterface 304 1 0
    //   549: invokeinterface 277 2 0
    //   554: ifne -36 -> 518
    //   557: aload 22
    //   559: new 235	com/google/android/gms/internal/ads/zzl
    //   562: dup
    //   563: aload 24
    //   565: invokeinterface 304 1 0
    //   570: checkcast 77	java/lang/String
    //   573: aload 24
    //   575: invokeinterface 307 1 0
    //   580: checkcast 77	java/lang/String
    //   583: invokespecial 310	com/google/android/gms/internal/ads/zzl:<init>	(Ljava/lang/String;Ljava/lang/String;)V
    //   586: invokeinterface 278 2 0
    //   591: pop
    //   592: goto -74 -> 518
    //   595: new 169	com/google/android/gms/internal/ads/zzp
    //   598: dup
    //   599: sipush 304
    //   602: aload 19
    //   604: getfield 314	com/google/android/gms/internal/ads/zzc:data	[B
    //   607: iconst_1
    //   608: invokestatic 140	android/os/SystemClock:elapsedRealtime	()J
    //   611: lload_2
    //   612: lsub
    //   613: aload 22
    //   615: invokespecial 172	com/google/android/gms/internal/ads/zzp:<init>	(I[BZJLjava/util/List;)V
    //   618: areturn
    //   619: aload 17
    //   621: invokevirtual 318	com/google/android/gms/internal/ads/zzar:getContent	()Ljava/io/InputStream;
    //   624: astore 31
    //   626: aload 31
    //   628: ifnull +134 -> 762
    //   631: aload_0
    //   632: aload 31
    //   634: aload 17
    //   636: invokevirtual 321	com/google/android/gms/internal/ads/zzar:getContentLength	()I
    //   639: invokespecial 323	com/google/android/gms/internal/ads/zzak:zza	(Ljava/io/InputStream;I)[B
    //   642: astore 32
    //   644: aload 32
    //   646: astore 7
    //   648: invokestatic 140	android/os/SystemClock:elapsedRealtime	()J
    //   651: lload_2
    //   652: lsub
    //   653: lstore 33
    //   655: getstatic 22	com/google/android/gms/internal/ads/zzak:DEBUG	Z
    //   658: ifne +12 -> 670
    //   661: lload 33
    //   663: ldc2_w 324
    //   666: lcmp
    //   667: ifle +250 -> 917
    //   670: iconst_5
    //   671: anewarray 4	java/lang/Object
    //   674: astore 36
    //   676: aload 36
    //   678: iconst_0
    //   679: aload_1
    //   680: aastore
    //   681: aload 36
    //   683: iconst_1
    //   684: lload 33
    //   686: invokestatic 330	java/lang/Long:valueOf	(J)Ljava/lang/Long;
    //   689: aastore
    //   690: aload 7
    //   692: ifnull +78 -> 770
    //   695: aload 7
    //   697: arraylength
    //   698: invokestatic 73	java/lang/Integer:valueOf	(I)Ljava/lang/Integer;
    //   701: astore 37
    //   703: aload 36
    //   705: iconst_2
    //   706: aload 37
    //   708: aastore
    //   709: aload 36
    //   711: iconst_3
    //   712: iload 18
    //   714: invokestatic 73	java/lang/Integer:valueOf	(I)Ljava/lang/Integer;
    //   717: aastore
    //   718: aload 36
    //   720: iconst_4
    //   721: aload_1
    //   722: invokevirtual 58	com/google/android/gms/internal/ads/zzr:zzj	()Lcom/google/android/gms/internal/ads/zzac;
    //   725: invokeinterface 332 1 0
    //   730: invokestatic 73	java/lang/Integer:valueOf	(I)Ljava/lang/Integer;
    //   733: aastore
    //   734: ldc_w 334
    //   737: aload 36
    //   739: invokestatic 337	com/google/android/gms/internal/ads/zzag:d	(Ljava/lang/String;[Ljava/lang/Object;)V
    //   742: goto +175 -> 917
    //   745: new 90	java/io/IOException
    //   748: dup
    //   749: invokespecial 338	java/io/IOException:<init>	()V
    //   752: athrow
    //   753: astore 5
    //   755: aload 17
    //   757: astore 6
    //   759: goto -375 -> 384
    //   762: iconst_0
    //   763: newarray byte
    //   765: astore 7
    //   767: goto -119 -> 648
    //   770: ldc_w 340
    //   773: astore 37
    //   775: goto -72 -> 703
    //   778: new 169	com/google/android/gms/internal/ads/zzp
    //   781: dup
    //   782: iload 18
    //   784: aload 7
    //   786: iconst_0
    //   787: invokestatic 140	android/os/SystemClock:elapsedRealtime	()J
    //   790: lload_2
    //   791: lsub
    //   792: aload 4
    //   794: invokespecial 172	com/google/android/gms/internal/ads/zzp:<init>	(I[BZJLjava/util/List;)V
    //   797: astore 35
    //   799: aload 35
    //   801: areturn
    //   802: new 77	java/lang/String
    //   805: dup
    //   806: ldc_w 256
    //   809: invokespecial 342	java/lang/String:<init>	(Ljava/lang/String;)V
    //   812: astore 13
    //   814: goto -545 -> 269
    //   817: new 344	com/google/android/gms/internal/ads/zzq
    //   820: dup
    //   821: aload 5
    //   823: invokespecial 347	com/google/android/gms/internal/ads/zzq:<init>	(Ljava/lang/Throwable;)V
    //   826: athrow
    //   827: iload 8
    //   829: sipush 400
    //   832: if_icmplt +21 -> 853
    //   835: iload 8
    //   837: sipush 499
    //   840: if_icmpgt +13 -> 853
    //   843: new 349	com/google/android/gms/internal/ads/zzg
    //   846: dup
    //   847: aload 10
    //   849: invokespecial 350	com/google/android/gms/internal/ads/zzg:<init>	(Lcom/google/android/gms/internal/ads/zzp;)V
    //   852: athrow
    //   853: iload 8
    //   855: sipush 500
    //   858: if_icmplt +21 -> 879
    //   861: iload 8
    //   863: sipush 599
    //   866: if_icmpgt +13 -> 879
    //   869: new 92	com/google/android/gms/internal/ads/zzad
    //   872: dup
    //   873: aload 10
    //   875: invokespecial 351	com/google/android/gms/internal/ads/zzad:<init>	(Lcom/google/android/gms/internal/ads/zzp;)V
    //   878: athrow
    //   879: new 92	com/google/android/gms/internal/ads/zzad
    //   882: dup
    //   883: aload 10
    //   885: invokespecial 351	com/google/android/gms/internal/ads/zzad:<init>	(Lcom/google/android/gms/internal/ads/zzp;)V
    //   888: athrow
    //   889: ldc_w 353
    //   892: aload_1
    //   893: new 355	com/google/android/gms/internal/ads/zzo
    //   896: dup
    //   897: invokespecial 356	com/google/android/gms/internal/ads/zzo:<init>	()V
    //   900: invokestatic 205	com/google/android/gms/internal/ads/zzak:zza	(Ljava/lang/String;Lcom/google/android/gms/internal/ads/zzr;Lcom/google/android/gms/internal/ads/zzaf;)V
    //   903: goto -899 -> 4
    //   906: astore 5
    //   908: aconst_null
    //   909: astore 6
    //   911: aconst_null
    //   912: astore 7
    //   914: goto -530 -> 384
    //   917: iload 18
    //   919: sipush 200
    //   922: if_icmplt -177 -> 745
    //   925: iload 18
    //   927: sipush 299
    //   930: if_icmple -152 -> 778
    //   933: goto -188 -> 745
    //
    // Exception table:
    //   from	to	target	type
    //   9	15	157	java/net/SocketTimeoutException
    //   20	25	157	java/net/SocketTimeoutException
    //   25	37	157	java/net/SocketTimeoutException
    //   37	51	157	java/net/SocketTimeoutException
    //   59	65	157	java/net/SocketTimeoutException
    //   70	91	157	java/net/SocketTimeoutException
    //   94	126	157	java/net/SocketTimeoutException
    //   126	154	157	java/net/SocketTimeoutException
    //   175	206	157	java/net/SocketTimeoutException
    //   206	237	157	java/net/SocketTimeoutException
    //   281	325	157	java/net/SocketTimeoutException
    //   325	372	157	java/net/SocketTimeoutException
    //   488	518	157	java/net/SocketTimeoutException
    //   518	592	157	java/net/SocketTimeoutException
    //   595	619	157	java/net/SocketTimeoutException
    //   619	626	157	java/net/SocketTimeoutException
    //   631	644	157	java/net/SocketTimeoutException
    //   648	661	157	java/net/SocketTimeoutException
    //   670	690	157	java/net/SocketTimeoutException
    //   695	703	157	java/net/SocketTimeoutException
    //   703	742	157	java/net/SocketTimeoutException
    //   745	753	157	java/net/SocketTimeoutException
    //   762	767	157	java/net/SocketTimeoutException
    //   778	799	157	java/net/SocketTimeoutException
    //   9	15	240	java/net/MalformedURLException
    //   20	25	240	java/net/MalformedURLException
    //   25	37	240	java/net/MalformedURLException
    //   37	51	240	java/net/MalformedURLException
    //   59	65	240	java/net/MalformedURLException
    //   70	91	240	java/net/MalformedURLException
    //   94	126	240	java/net/MalformedURLException
    //   126	154	240	java/net/MalformedURLException
    //   175	206	240	java/net/MalformedURLException
    //   206	237	240	java/net/MalformedURLException
    //   281	325	240	java/net/MalformedURLException
    //   325	372	240	java/net/MalformedURLException
    //   488	518	240	java/net/MalformedURLException
    //   518	592	240	java/net/MalformedURLException
    //   595	619	240	java/net/MalformedURLException
    //   619	626	240	java/net/MalformedURLException
    //   631	644	240	java/net/MalformedURLException
    //   648	661	240	java/net/MalformedURLException
    //   670	690	240	java/net/MalformedURLException
    //   695	703	240	java/net/MalformedURLException
    //   703	742	240	java/net/MalformedURLException
    //   745	753	240	java/net/MalformedURLException
    //   762	767	240	java/net/MalformedURLException
    //   778	799	240	java/net/MalformedURLException
    //   37	51	375	java/io/IOException
    //   59	65	375	java/io/IOException
    //   70	91	375	java/io/IOException
    //   175	206	375	java/io/IOException
    //   206	237	375	java/io/IOException
    //   281	325	375	java/io/IOException
    //   325	372	375	java/io/IOException
    //   488	518	375	java/io/IOException
    //   518	592	375	java/io/IOException
    //   595	619	375	java/io/IOException
    //   619	626	375	java/io/IOException
    //   631	644	375	java/io/IOException
    //   762	767	375	java/io/IOException
    //   648	661	753	java/io/IOException
    //   670	690	753	java/io/IOException
    //   695	703	753	java/io/IOException
    //   703	742	753	java/io/IOException
    //   745	753	753	java/io/IOException
    //   778	799	753	java/io/IOException
    //   9	15	906	java/io/IOException
    //   20	25	906	java/io/IOException
    //   25	37	906	java/io/IOException
    //   94	126	906	java/io/IOException
    //   126	154	906	java/io/IOException
  }
}

/* Location:           E:\Study\Tools\apktool2_2\dex2jar-0.0.9.15\classes_viber_2_dex2jar.jar
 * Qualified Name:     com.google.android.gms.internal.ads.zzak
 * JD-Core Version:    0.6.2
 */