package com.google.android.gms.internal.ads;

import java.io.OutputStream;

final class zzarw
  implements Runnable
{
  zzarw(zzarv paramzzarv, OutputStream paramOutputStream, byte[] paramArrayOfByte)
  {
  }

  // ERROR //
  public final void run()
  {
    // Byte code:
    //   0: new 24	java/io/DataOutputStream
    //   3: dup
    //   4: aload_0
    //   5: getfield 14	com/google/android/gms/internal/ads/zzarw:zzdot	Ljava/io/OutputStream;
    //   8: invokespecial 27	java/io/DataOutputStream:<init>	(Ljava/io/OutputStream;)V
    //   11: astore_1
    //   12: aload_1
    //   13: aload_0
    //   14: getfield 16	com/google/android/gms/internal/ads/zzarw:zzdou	[B
    //   17: arraylength
    //   18: invokevirtual 31	java/io/DataOutputStream:writeInt	(I)V
    //   21: aload_1
    //   22: aload_0
    //   23: getfield 16	com/google/android/gms/internal/ads/zzarw:zzdou	[B
    //   26: invokevirtual 35	java/io/DataOutputStream:write	([B)V
    //   29: aload_1
    //   30: invokestatic 41	com/google/android/gms/common/util/IOUtils:closeQuietly	(Ljava/io/Closeable;)V
    //   33: return
    //   34: astore_2
    //   35: aconst_null
    //   36: astore_1
    //   37: ldc 43
    //   39: aload_2
    //   40: invokestatic 49	com/google/android/gms/internal/ads/zzaxa:zzc	(Ljava/lang/String;Ljava/lang/Throwable;)V
    //   43: invokestatic 55	com/google/android/gms/ads/internal/zzk:zzlk	()Lcom/google/android/gms/internal/ads/zzawn;
    //   46: aload_2
    //   47: ldc 57
    //   49: invokevirtual 63	com/google/android/gms/internal/ads/zzawn:zza	(Ljava/lang/Throwable;Ljava/lang/String;)V
    //   52: aload_1
    //   53: ifnonnull +11 -> 64
    //   56: aload_0
    //   57: getfield 14	com/google/android/gms/internal/ads/zzarw:zzdot	Ljava/io/OutputStream;
    //   60: invokestatic 41	com/google/android/gms/common/util/IOUtils:closeQuietly	(Ljava/io/Closeable;)V
    //   63: return
    //   64: aload_1
    //   65: invokestatic 41	com/google/android/gms/common/util/IOUtils:closeQuietly	(Ljava/io/Closeable;)V
    //   68: return
    //   69: astore_3
    //   70: aconst_null
    //   71: astore_1
    //   72: aload_1
    //   73: ifnonnull +12 -> 85
    //   76: aload_0
    //   77: getfield 14	com/google/android/gms/internal/ads/zzarw:zzdot	Ljava/io/OutputStream;
    //   80: invokestatic 41	com/google/android/gms/common/util/IOUtils:closeQuietly	(Ljava/io/Closeable;)V
    //   83: aload_3
    //   84: athrow
    //   85: aload_1
    //   86: invokestatic 41	com/google/android/gms/common/util/IOUtils:closeQuietly	(Ljava/io/Closeable;)V
    //   89: goto -6 -> 83
    //   92: astore_3
    //   93: goto -21 -> 72
    //   96: astore_2
    //   97: goto -60 -> 37
    //
    // Exception table:
    //   from	to	target	type
    //   0	12	34	java/io/IOException
    //   0	12	69	finally
    //   12	29	92	finally
    //   37	52	92	finally
    //   12	29	96	java/io/IOException
  }
}

/* Location:           E:\Study\Tools\apktool2_2\dex2jar-0.0.9.15\classes_viber_2_dex2jar.jar
 * Qualified Name:     com.google.android.gms.internal.ads.zzarw
 * JD-Core Version:    0.6.2
 */