package com.google.android.gms.internal.ads;

import android.content.Context;
import java.io.File;
import java.text.DecimalFormat;
import java.util.Collections;
import java.util.HashSet;
import java.util.Set;

@zzare
public final class zzbgf extends zzbfu
{
  private static final Set<String> zzeig = Collections.synchronizedSet(new HashSet());
  private static final DecimalFormat zzeih = new DecimalFormat("#,###");
  private File zzeii;
  private boolean zzeij;

  public zzbgf(zzbdg paramzzbdg)
  {
    super(paramzzbdg);
    File localFile = this.mContext.getCacheDir();
    if (localFile == null)
      zzaxa.zzep("Context.getCacheDir() returned null");
    do
    {
      return;
      this.zzeii = new File(localFile, "admobVideoStreams");
      if ((!this.zzeii.isDirectory()) && (!this.zzeii.mkdirs()))
      {
        String str3 = String.valueOf(this.zzeii.getAbsolutePath());
        if (str3.length() != 0);
        for (String str4 = "Could not create preload cache directory at ".concat(str3); ; str4 = new String("Could not create preload cache directory at "))
        {
          zzaxa.zzep(str4);
          this.zzeii = null;
          return;
        }
      }
    }
    while ((this.zzeii.setReadable(true, false)) && (this.zzeii.setExecutable(true, false)));
    String str1 = String.valueOf(this.zzeii.getAbsolutePath());
    if (str1.length() != 0);
    for (String str2 = "Could not set cache file permissions at ".concat(str1); ; str2 = new String("Could not set cache file permissions at "))
    {
      zzaxa.zzep(str2);
      this.zzeii = null;
      return;
    }
  }

  private final File zzc(File paramFile)
  {
    return new File(this.zzeii, String.valueOf(paramFile.getName()).concat(".done"));
  }

  public final void abort()
  {
    this.zzeij = true;
  }

  // ERROR //
  public final boolean zzex(String paramString)
  {
    // Byte code:
    //   0: aload_0
    //   1: getfield 67	com/google/android/gms/internal/ads/zzbgf:zzeii	Ljava/io/File;
    //   4: ifnonnull +14 -> 18
    //   7: aload_0
    //   8: aload_1
    //   9: aconst_null
    //   10: ldc 124
    //   12: aconst_null
    //   13: invokevirtual 128	com/google/android/gms/internal/ads/zzbfu:zza	(Ljava/lang/String;Ljava/lang/String;Ljava/lang/String;Ljava/lang/String;)V
    //   16: iconst_0
    //   17: ireturn
    //   18: aload_0
    //   19: getfield 67	com/google/android/gms/internal/ads/zzbgf:zzeii	Ljava/io/File;
    //   22: ifnonnull +61 -> 83
    //   25: iconst_0
    //   26: istore 6
    //   28: getstatic 134	com/google/android/gms/internal/ads/zzact:zzclv	Lcom/google/android/gms/internal/ads/zzaci;
    //   31: astore 7
    //   33: iload 6
    //   35: invokestatic 140	com/google/android/gms/internal/ads/zzyr:zzpe	()Lcom/google/android/gms/internal/ads/zzacq;
    //   38: aload 7
    //   40: invokevirtual 146	com/google/android/gms/internal/ads/zzacq:zzd	(Lcom/google/android/gms/internal/ads/zzaci;)Ljava/lang/Object;
    //   43: checkcast 148	java/lang/Integer
    //   46: invokevirtual 151	java/lang/Integer:intValue	()I
    //   49: if_icmple +217 -> 266
    //   52: aload_0
    //   53: getfield 67	com/google/android/gms/internal/ads/zzbgf:zzeii	Ljava/io/File;
    //   56: ifnonnull +81 -> 137
    //   59: iconst_0
    //   60: istore 97
    //   62: iload 97
    //   64: ifne -46 -> 18
    //   67: ldc 153
    //   69: invokestatic 58	com/google/android/gms/internal/ads/zzaxa:zzep	(Ljava/lang/String;)V
    //   72: aload_0
    //   73: aload_1
    //   74: aconst_null
    //   75: ldc 155
    //   77: aconst_null
    //   78: invokevirtual 128	com/google/android/gms/internal/ads/zzbfu:zza	(Ljava/lang/String;Ljava/lang/String;Ljava/lang/String;Ljava/lang/String;)V
    //   81: iconst_0
    //   82: ireturn
    //   83: aload_0
    //   84: getfield 67	com/google/android/gms/internal/ads/zzbgf:zzeii	Ljava/io/File;
    //   87: invokevirtual 159	java/io/File:listFiles	()[Ljava/io/File;
    //   90: astore_2
    //   91: aload_2
    //   92: arraylength
    //   93: istore_3
    //   94: iconst_0
    //   95: istore 4
    //   97: iconst_0
    //   98: istore 5
    //   100: iload 5
    //   102: iload_3
    //   103: if_icmpge +27 -> 130
    //   106: aload_2
    //   107: iload 5
    //   109: aaload
    //   110: invokevirtual 109	java/io/File:getName	()Ljava/lang/String;
    //   113: ldc 111
    //   115: invokevirtual 162	java/lang/String:endsWith	(Ljava/lang/String;)Z
    //   118: ifne +6 -> 124
    //   121: iinc 4 1
    //   124: iinc 5 1
    //   127: goto -27 -> 100
    //   130: iload 4
    //   132: istore 6
    //   134: goto -106 -> 28
    //   137: aconst_null
    //   138: astore 91
    //   140: ldc2_w 163
    //   143: lstore 92
    //   145: aload_0
    //   146: getfield 67	com/google/android/gms/internal/ads/zzbgf:zzeii	Ljava/io/File;
    //   149: invokevirtual 159	java/io/File:listFiles	()[Ljava/io/File;
    //   152: astore 94
    //   154: aload 94
    //   156: arraylength
    //   157: istore 95
    //   159: iconst_0
    //   160: istore 96
    //   162: iload 96
    //   164: iload 95
    //   166: if_icmpge +56 -> 222
    //   169: aload 94
    //   171: iload 96
    //   173: aaload
    //   174: astore 99
    //   176: aload 99
    //   178: invokevirtual 109	java/io/File:getName	()Ljava/lang/String;
    //   181: ldc 111
    //   183: invokevirtual 162	java/lang/String:endsWith	(Ljava/lang/String;)Z
    //   186: ifne +1950 -> 2136
    //   189: aload 99
    //   191: invokevirtual 168	java/io/File:lastModified	()J
    //   194: lstore 100
    //   196: lload 100
    //   198: lload 92
    //   200: lcmp
    //   201: ifge +1935 -> 2136
    //   204: aload 99
    //   206: astore 102
    //   208: iinc 96 1
    //   211: aload 102
    //   213: astore 91
    //   215: lload 100
    //   217: lstore 92
    //   219: goto -57 -> 162
    //   222: iconst_0
    //   223: istore 97
    //   225: aload 91
    //   227: ifnull -165 -> 62
    //   230: aload 91
    //   232: invokevirtual 171	java/io/File:delete	()Z
    //   235: istore 97
    //   237: aload_0
    //   238: aload 91
    //   240: invokespecial 173	com/google/android/gms/internal/ads/zzbgf:zzc	(Ljava/io/File;)Ljava/io/File;
    //   243: astore 98
    //   245: aload 98
    //   247: invokevirtual 176	java/io/File:isFile	()Z
    //   250: ifeq -188 -> 62
    //   253: iload 97
    //   255: aload 98
    //   257: invokevirtual 171	java/io/File:delete	()Z
    //   260: iand
    //   261: istore 97
    //   263: goto -201 -> 62
    //   266: aload_0
    //   267: aload_1
    //   268: invokevirtual 179	com/google/android/gms/internal/ads/zzbfu:zzey	(Ljava/lang/String;)Ljava/lang/String;
    //   271: astore 8
    //   273: new 60	java/io/File
    //   276: dup
    //   277: aload_0
    //   278: getfield 67	com/google/android/gms/internal/ads/zzbgf:zzeii	Ljava/io/File;
    //   281: aload 8
    //   283: invokespecial 65	java/io/File:<init>	(Ljava/io/File;Ljava/lang/String;)V
    //   286: astore 9
    //   288: aload_0
    //   289: aload 9
    //   291: invokespecial 173	com/google/android/gms/internal/ads/zzbgf:zzc	(Ljava/io/File;)Ljava/io/File;
    //   294: astore 10
    //   296: aload 9
    //   298: invokevirtual 176	java/io/File:isFile	()Z
    //   301: ifeq +75 -> 376
    //   304: aload 10
    //   306: invokevirtual 176	java/io/File:isFile	()Z
    //   309: ifeq +67 -> 376
    //   312: aload 9
    //   314: invokevirtual 181	java/io/File:length	()J
    //   317: l2i
    //   318: istore 88
    //   320: aload_1
    //   321: invokestatic 84	java/lang/String:valueOf	(Ljava/lang/Object;)Ljava/lang/String;
    //   324: astore 89
    //   326: aload 89
    //   328: invokevirtual 88	java/lang/String:length	()I
    //   331: ifeq +31 -> 362
    //   334: ldc 183
    //   336: aload 89
    //   338: invokevirtual 94	java/lang/String:concat	(Ljava/lang/String;)Ljava/lang/String;
    //   341: astore 90
    //   343: aload 90
    //   345: invokestatic 186	com/google/android/gms/internal/ads/zzaxa:zzdp	(Ljava/lang/String;)V
    //   348: aload_0
    //   349: aload_1
    //   350: aload 9
    //   352: invokevirtual 78	java/io/File:getAbsolutePath	()Ljava/lang/String;
    //   355: iload 88
    //   357: invokevirtual 189	com/google/android/gms/internal/ads/zzbfu:zza	(Ljava/lang/String;Ljava/lang/String;I)V
    //   360: iconst_1
    //   361: ireturn
    //   362: new 80	java/lang/String
    //   365: dup
    //   366: ldc 183
    //   368: invokespecial 95	java/lang/String:<init>	(Ljava/lang/String;)V
    //   371: astore 90
    //   373: goto -30 -> 343
    //   376: aload_0
    //   377: getfield 67	com/google/android/gms/internal/ads/zzbgf:zzeii	Ljava/io/File;
    //   380: invokevirtual 78	java/io/File:getAbsolutePath	()Ljava/lang/String;
    //   383: invokestatic 84	java/lang/String:valueOf	(Ljava/lang/Object;)Ljava/lang/String;
    //   386: astore 11
    //   388: aload_1
    //   389: invokestatic 84	java/lang/String:valueOf	(Ljava/lang/Object;)Ljava/lang/String;
    //   392: astore 12
    //   394: aload 12
    //   396: invokevirtual 88	java/lang/String:length	()I
    //   399: ifeq +87 -> 486
    //   402: aload 11
    //   404: aload 12
    //   406: invokevirtual 94	java/lang/String:concat	(Ljava/lang/String;)Ljava/lang/String;
    //   409: astore 13
    //   411: getstatic 29	com/google/android/gms/internal/ads/zzbgf:zzeig	Ljava/util/Set;
    //   414: astore 14
    //   416: aload 14
    //   418: monitorenter
    //   419: getstatic 29	com/google/android/gms/internal/ads/zzbgf:zzeig	Ljava/util/Set;
    //   422: aload 13
    //   424: invokeinterface 195 2 0
    //   429: ifeq +85 -> 514
    //   432: aload_1
    //   433: invokestatic 84	java/lang/String:valueOf	(Ljava/lang/Object;)Ljava/lang/String;
    //   436: astore 86
    //   438: aload 86
    //   440: invokevirtual 88	java/lang/String:length	()I
    //   443: ifeq +57 -> 500
    //   446: ldc 197
    //   448: aload 86
    //   450: invokevirtual 94	java/lang/String:concat	(Ljava/lang/String;)Ljava/lang/String;
    //   453: astore 87
    //   455: aload 87
    //   457: invokestatic 58	com/google/android/gms/internal/ads/zzaxa:zzep	(Ljava/lang/String;)V
    //   460: aload_0
    //   461: aload_1
    //   462: aload 9
    //   464: invokevirtual 78	java/io/File:getAbsolutePath	()Ljava/lang/String;
    //   467: ldc 199
    //   469: aconst_null
    //   470: invokevirtual 128	com/google/android/gms/internal/ads/zzbfu:zza	(Ljava/lang/String;Ljava/lang/String;Ljava/lang/String;Ljava/lang/String;)V
    //   473: aload 14
    //   475: monitorexit
    //   476: iconst_0
    //   477: ireturn
    //   478: astore 15
    //   480: aload 14
    //   482: monitorexit
    //   483: aload 15
    //   485: athrow
    //   486: new 80	java/lang/String
    //   489: dup
    //   490: aload 11
    //   492: invokespecial 95	java/lang/String:<init>	(Ljava/lang/String;)V
    //   495: astore 13
    //   497: goto -86 -> 411
    //   500: new 80	java/lang/String
    //   503: dup
    //   504: ldc 197
    //   506: invokespecial 95	java/lang/String:<init>	(Ljava/lang/String;)V
    //   509: astore 87
    //   511: goto -56 -> 455
    //   514: getstatic 29	com/google/android/gms/internal/ads/zzbgf:zzeig	Ljava/util/Set;
    //   517: aload 13
    //   519: invokeinterface 202 2 0
    //   524: pop
    //   525: aload 14
    //   527: monitorexit
    //   528: aconst_null
    //   529: astore 17
    //   531: invokestatic 208	com/google/android/gms/ads/internal/zzk:zzls	()Lcom/google/android/gms/internal/ads/zzbbt;
    //   534: pop
    //   535: getstatic 211	com/google/android/gms/internal/ads/zzact:zzcma	Lcom/google/android/gms/internal/ads/zzaci;
    //   538: astore 27
    //   540: invokestatic 140	com/google/android/gms/internal/ads/zzyr:zzpe	()Lcom/google/android/gms/internal/ads/zzacq;
    //   543: aload 27
    //   545: invokevirtual 146	com/google/android/gms/internal/ads/zzacq:zzd	(Lcom/google/android/gms/internal/ads/zzaci;)Ljava/lang/Object;
    //   548: checkcast 148	java/lang/Integer
    //   551: invokevirtual 151	java/lang/Integer:intValue	()I
    //   554: istore 28
    //   556: new 213	java/net/URL
    //   559: dup
    //   560: aload_1
    //   561: invokespecial 214	java/net/URL:<init>	(Ljava/lang/String;)V
    //   564: astore 29
    //   566: iconst_0
    //   567: istore 30
    //   569: iload 30
    //   571: iconst_1
    //   572: iadd
    //   573: istore 31
    //   575: iload 31
    //   577: bipush 20
    //   579: if_icmpgt +446 -> 1025
    //   582: aload 29
    //   584: invokevirtual 218	java/net/URL:openConnection	()Ljava/net/URLConnection;
    //   587: astore 32
    //   589: aload 32
    //   591: iload 28
    //   593: invokevirtual 224	java/net/URLConnection:setConnectTimeout	(I)V
    //   596: aload 32
    //   598: iload 28
    //   600: invokevirtual 227	java/net/URLConnection:setReadTimeout	(I)V
    //   603: aload 32
    //   605: instanceof 229
    //   608: ifne +167 -> 775
    //   611: new 118	java/io/IOException
    //   614: dup
    //   615: ldc 231
    //   617: invokespecial 232	java/io/IOException:<init>	(Ljava/lang/String;)V
    //   620: athrow
    //   621: astore 18
    //   623: aconst_null
    //   624: astore 20
    //   626: ldc 234
    //   628: astore 19
    //   630: aload 18
    //   632: instanceof 120
    //   635: ifeq +13 -> 648
    //   638: invokestatic 238	com/google/android/gms/ads/internal/zzk:zzlk	()Lcom/google/android/gms/internal/ads/zzawn;
    //   641: aload 18
    //   643: ldc 240
    //   645: invokevirtual 245	com/google/android/gms/internal/ads/zzawn:zza	(Ljava/lang/Throwable;Ljava/lang/String;)V
    //   648: aload 17
    //   650: invokevirtual 250	java/io/FileOutputStream:close	()V
    //   653: aload_0
    //   654: getfield 114	com/google/android/gms/internal/ads/zzbgf:zzeij	Z
    //   657: ifeq +1375 -> 2032
    //   660: new 252	java/lang/StringBuilder
    //   663: dup
    //   664: bipush 26
    //   666: aload_1
    //   667: invokestatic 84	java/lang/String:valueOf	(Ljava/lang/Object;)Ljava/lang/String;
    //   670: invokevirtual 88	java/lang/String:length	()I
    //   673: iadd
    //   674: invokespecial 254	java/lang/StringBuilder:<init>	(I)V
    //   677: ldc_w 256
    //   680: invokevirtual 260	java/lang/StringBuilder:append	(Ljava/lang/String;)Ljava/lang/StringBuilder;
    //   683: aload_1
    //   684: invokevirtual 260	java/lang/StringBuilder:append	(Ljava/lang/String;)Ljava/lang/StringBuilder;
    //   687: ldc_w 262
    //   690: invokevirtual 260	java/lang/StringBuilder:append	(Ljava/lang/String;)Ljava/lang/StringBuilder;
    //   693: invokevirtual 265	java/lang/StringBuilder:toString	()Ljava/lang/String;
    //   696: invokestatic 268	com/google/android/gms/internal/ads/zzaxa:zzeo	(Ljava/lang/String;)V
    //   699: aload 9
    //   701: invokevirtual 271	java/io/File:exists	()Z
    //   704: ifeq +44 -> 748
    //   707: aload 9
    //   709: invokevirtual 171	java/io/File:delete	()Z
    //   712: ifne +36 -> 748
    //   715: aload 9
    //   717: invokevirtual 78	java/io/File:getAbsolutePath	()Ljava/lang/String;
    //   720: invokestatic 84	java/lang/String:valueOf	(Ljava/lang/Object;)Ljava/lang/String;
    //   723: astore 23
    //   725: aload 23
    //   727: invokevirtual 88	java/lang/String:length	()I
    //   730: ifeq +1346 -> 2076
    //   733: ldc_w 273
    //   736: aload 23
    //   738: invokevirtual 94	java/lang/String:concat	(Ljava/lang/String;)Ljava/lang/String;
    //   741: astore 24
    //   743: aload 24
    //   745: invokestatic 58	com/google/android/gms/internal/ads/zzaxa:zzep	(Ljava/lang/String;)V
    //   748: aload_0
    //   749: aload_1
    //   750: aload 9
    //   752: invokevirtual 78	java/io/File:getAbsolutePath	()Ljava/lang/String;
    //   755: aload 19
    //   757: aload 20
    //   759: invokevirtual 128	com/google/android/gms/internal/ads/zzbfu:zza	(Ljava/lang/String;Ljava/lang/String;Ljava/lang/String;Ljava/lang/String;)V
    //   762: getstatic 29	com/google/android/gms/internal/ads/zzbgf:zzeig	Ljava/util/Set;
    //   765: aload 13
    //   767: invokeinterface 276 2 0
    //   772: pop
    //   773: iconst_0
    //   774: ireturn
    //   775: aload 32
    //   777: checkcast 229	java/net/HttpURLConnection
    //   780: astore 33
    //   782: new 278	com/google/android/gms/internal/ads/zzazy
    //   785: dup
    //   786: invokespecial 279	com/google/android/gms/internal/ads/zzazy:<init>	()V
    //   789: astore 34
    //   791: aload 34
    //   793: aload 33
    //   795: aconst_null
    //   796: invokevirtual 282	com/google/android/gms/internal/ads/zzazy:zza	(Ljava/net/HttpURLConnection;[B)V
    //   799: aload 33
    //   801: iconst_0
    //   802: invokevirtual 286	java/net/HttpURLConnection:setInstanceFollowRedirects	(Z)V
    //   805: aload 33
    //   807: invokevirtual 289	java/net/HttpURLConnection:getResponseCode	()I
    //   810: istore 35
    //   812: aload 34
    //   814: aload 33
    //   816: iload 35
    //   818: invokevirtual 292	com/google/android/gms/internal/ads/zzazy:zza	(Ljava/net/HttpURLConnection;I)V
    //   821: iload 35
    //   823: bipush 100
    //   825: idiv
    //   826: iconst_3
    //   827: if_icmpne +209 -> 1036
    //   830: aload 33
    //   832: ldc_w 294
    //   835: invokevirtual 297	java/net/HttpURLConnection:getHeaderField	(Ljava/lang/String;)Ljava/lang/String;
    //   838: astore 79
    //   840: aload 79
    //   842: ifnonnull +14 -> 856
    //   845: new 118	java/io/IOException
    //   848: dup
    //   849: ldc_w 299
    //   852: invokespecial 232	java/io/IOException:<init>	(Ljava/lang/String;)V
    //   855: athrow
    //   856: new 213	java/net/URL
    //   859: dup
    //   860: aload 29
    //   862: aload 79
    //   864: invokespecial 302	java/net/URL:<init>	(Ljava/net/URL;Ljava/lang/String;)V
    //   867: astore 80
    //   869: aload 80
    //   871: invokevirtual 305	java/net/URL:getProtocol	()Ljava/lang/String;
    //   874: astore 81
    //   876: aload 81
    //   878: ifnonnull +14 -> 892
    //   881: new 118	java/io/IOException
    //   884: dup
    //   885: ldc_w 307
    //   888: invokespecial 232	java/io/IOException:<init>	(Ljava/lang/String;)V
    //   891: athrow
    //   892: aload 81
    //   894: ldc_w 309
    //   897: invokevirtual 312	java/lang/String:equals	(Ljava/lang/Object;)Z
    //   900: ifne +64 -> 964
    //   903: aload 81
    //   905: ldc_w 314
    //   908: invokevirtual 312	java/lang/String:equals	(Ljava/lang/Object;)Z
    //   911: ifne +53 -> 964
    //   914: aload 81
    //   916: invokestatic 84	java/lang/String:valueOf	(Ljava/lang/Object;)Ljava/lang/String;
    //   919: astore 84
    //   921: aload 84
    //   923: invokevirtual 88	java/lang/String:length	()I
    //   926: ifeq +23 -> 949
    //   929: ldc_w 316
    //   932: aload 84
    //   934: invokevirtual 94	java/lang/String:concat	(Ljava/lang/String;)Ljava/lang/String;
    //   937: astore 85
    //   939: new 118	java/io/IOException
    //   942: dup
    //   943: aload 85
    //   945: invokespecial 232	java/io/IOException:<init>	(Ljava/lang/String;)V
    //   948: athrow
    //   949: new 80	java/lang/String
    //   952: dup
    //   953: ldc_w 316
    //   956: invokespecial 95	java/lang/String:<init>	(Ljava/lang/String;)V
    //   959: astore 85
    //   961: goto -22 -> 939
    //   964: aload 79
    //   966: invokestatic 84	java/lang/String:valueOf	(Ljava/lang/Object;)Ljava/lang/String;
    //   969: astore 82
    //   971: aload 82
    //   973: invokevirtual 88	java/lang/String:length	()I
    //   976: ifeq +34 -> 1010
    //   979: ldc_w 318
    //   982: aload 82
    //   984: invokevirtual 94	java/lang/String:concat	(Ljava/lang/String;)Ljava/lang/String;
    //   987: astore 83
    //   989: aload 83
    //   991: invokestatic 186	com/google/android/gms/internal/ads/zzaxa:zzdp	(Ljava/lang/String;)V
    //   994: aload 33
    //   996: invokevirtual 321	java/net/HttpURLConnection:disconnect	()V
    //   999: iload 31
    //   1001: istore 30
    //   1003: aload 80
    //   1005: astore 29
    //   1007: goto -438 -> 569
    //   1010: new 80	java/lang/String
    //   1013: dup
    //   1014: ldc_w 318
    //   1017: invokespecial 95	java/lang/String:<init>	(Ljava/lang/String;)V
    //   1020: astore 83
    //   1022: goto -33 -> 989
    //   1025: new 118	java/io/IOException
    //   1028: dup
    //   1029: ldc_w 323
    //   1032: invokespecial 232	java/io/IOException:<init>	(Ljava/lang/String;)V
    //   1035: athrow
    //   1036: aload 33
    //   1038: instanceof 229
    //   1041: ifeq +141 -> 1182
    //   1044: aload 33
    //   1046: checkcast 229	java/net/HttpURLConnection
    //   1049: invokevirtual 289	java/net/HttpURLConnection:getResponseCode	()I
    //   1052: istore 76
    //   1054: iload 76
    //   1056: sipush 400
    //   1059: if_icmplt +123 -> 1182
    //   1062: ldc_w 325
    //   1065: astore 19
    //   1067: iload 76
    //   1069: invokestatic 328	java/lang/Integer:toString	(I)Ljava/lang/String;
    //   1072: invokestatic 84	java/lang/String:valueOf	(Ljava/lang/Object;)Ljava/lang/String;
    //   1075: astore 77
    //   1077: aload 77
    //   1079: invokevirtual 88	java/lang/String:length	()I
    //   1082: ifeq +74 -> 1156
    //   1085: ldc_w 330
    //   1088: aload 77
    //   1090: invokevirtual 94	java/lang/String:concat	(Ljava/lang/String;)Ljava/lang/String;
    //   1093: astore 78
    //   1095: aload 78
    //   1097: astore 20
    //   1099: new 118	java/io/IOException
    //   1102: dup
    //   1103: new 252	java/lang/StringBuilder
    //   1106: dup
    //   1107: bipush 32
    //   1109: aload_1
    //   1110: invokestatic 84	java/lang/String:valueOf	(Ljava/lang/Object;)Ljava/lang/String;
    //   1113: invokevirtual 88	java/lang/String:length	()I
    //   1116: iadd
    //   1117: invokespecial 254	java/lang/StringBuilder:<init>	(I)V
    //   1120: ldc_w 332
    //   1123: invokevirtual 260	java/lang/StringBuilder:append	(Ljava/lang/String;)Ljava/lang/StringBuilder;
    //   1126: iload 76
    //   1128: invokevirtual 335	java/lang/StringBuilder:append	(I)Ljava/lang/StringBuilder;
    //   1131: ldc_w 337
    //   1134: invokevirtual 260	java/lang/StringBuilder:append	(Ljava/lang/String;)Ljava/lang/StringBuilder;
    //   1137: aload_1
    //   1138: invokevirtual 260	java/lang/StringBuilder:append	(Ljava/lang/String;)Ljava/lang/StringBuilder;
    //   1141: invokevirtual 265	java/lang/StringBuilder:toString	()Ljava/lang/String;
    //   1144: invokespecial 232	java/io/IOException:<init>	(Ljava/lang/String;)V
    //   1147: athrow
    //   1148: astore 18
    //   1150: aconst_null
    //   1151: astore 17
    //   1153: goto -523 -> 630
    //   1156: new 80	java/lang/String
    //   1159: dup
    //   1160: ldc_w 330
    //   1163: invokespecial 95	java/lang/String:<init>	(Ljava/lang/String;)V
    //   1166: astore 20
    //   1168: goto -69 -> 1099
    //   1171: astore 18
    //   1173: aconst_null
    //   1174: astore 20
    //   1176: aconst_null
    //   1177: astore 17
    //   1179: goto -549 -> 630
    //   1182: aload 33
    //   1184: invokevirtual 340	java/net/URLConnection:getContentLength	()I
    //   1187: istore 36
    //   1189: iload 36
    //   1191: ifge +74 -> 1265
    //   1194: aload_1
    //   1195: invokestatic 84	java/lang/String:valueOf	(Ljava/lang/Object;)Ljava/lang/String;
    //   1198: astore 37
    //   1200: aload 37
    //   1202: invokevirtual 88	java/lang/String:length	()I
    //   1205: ifeq +45 -> 1250
    //   1208: ldc_w 342
    //   1211: aload 37
    //   1213: invokevirtual 94	java/lang/String:concat	(Ljava/lang/String;)Ljava/lang/String;
    //   1216: astore 38
    //   1218: aload 38
    //   1220: invokestatic 58	com/google/android/gms/internal/ads/zzaxa:zzep	(Ljava/lang/String;)V
    //   1223: aload_0
    //   1224: aload_1
    //   1225: aload 9
    //   1227: invokevirtual 78	java/io/File:getAbsolutePath	()Ljava/lang/String;
    //   1230: ldc_w 344
    //   1233: aconst_null
    //   1234: invokevirtual 128	com/google/android/gms/internal/ads/zzbfu:zza	(Ljava/lang/String;Ljava/lang/String;Ljava/lang/String;Ljava/lang/String;)V
    //   1237: getstatic 29	com/google/android/gms/internal/ads/zzbgf:zzeig	Ljava/util/Set;
    //   1240: aload 13
    //   1242: invokeinterface 276 2 0
    //   1247: pop
    //   1248: iconst_0
    //   1249: ireturn
    //   1250: new 80	java/lang/String
    //   1253: dup
    //   1254: ldc_w 342
    //   1257: invokespecial 95	java/lang/String:<init>	(Ljava/lang/String;)V
    //   1260: astore 38
    //   1262: goto -44 -> 1218
    //   1265: getstatic 38	com/google/android/gms/internal/ads/zzbgf:zzeih	Ljava/text/DecimalFormat;
    //   1268: iload 36
    //   1270: i2l
    //   1271: invokevirtual 348	java/text/DecimalFormat:format	(J)Ljava/lang/String;
    //   1274: astore 40
    //   1276: getstatic 351	com/google/android/gms/internal/ads/zzact:zzclw	Lcom/google/android/gms/internal/ads/zzaci;
    //   1279: astore 41
    //   1281: invokestatic 140	com/google/android/gms/internal/ads/zzyr:zzpe	()Lcom/google/android/gms/internal/ads/zzacq;
    //   1284: aload 41
    //   1286: invokevirtual 146	com/google/android/gms/internal/ads/zzacq:zzd	(Lcom/google/android/gms/internal/ads/zzaci;)Ljava/lang/Object;
    //   1289: checkcast 148	java/lang/Integer
    //   1292: invokevirtual 151	java/lang/Integer:intValue	()I
    //   1295: istore 42
    //   1297: iload 36
    //   1299: iload 42
    //   1301: if_icmple +124 -> 1425
    //   1304: new 252	java/lang/StringBuilder
    //   1307: dup
    //   1308: bipush 33
    //   1310: aload 40
    //   1312: invokestatic 84	java/lang/String:valueOf	(Ljava/lang/Object;)Ljava/lang/String;
    //   1315: invokevirtual 88	java/lang/String:length	()I
    //   1318: iadd
    //   1319: aload_1
    //   1320: invokestatic 84	java/lang/String:valueOf	(Ljava/lang/Object;)Ljava/lang/String;
    //   1323: invokevirtual 88	java/lang/String:length	()I
    //   1326: iadd
    //   1327: invokespecial 254	java/lang/StringBuilder:<init>	(I)V
    //   1330: ldc_w 353
    //   1333: invokevirtual 260	java/lang/StringBuilder:append	(Ljava/lang/String;)Ljava/lang/StringBuilder;
    //   1336: aload 40
    //   1338: invokevirtual 260	java/lang/StringBuilder:append	(Ljava/lang/String;)Ljava/lang/StringBuilder;
    //   1341: ldc_w 355
    //   1344: invokevirtual 260	java/lang/StringBuilder:append	(Ljava/lang/String;)Ljava/lang/StringBuilder;
    //   1347: aload_1
    //   1348: invokevirtual 260	java/lang/StringBuilder:append	(Ljava/lang/String;)Ljava/lang/StringBuilder;
    //   1351: invokevirtual 265	java/lang/StringBuilder:toString	()Ljava/lang/String;
    //   1354: invokestatic 58	com/google/android/gms/internal/ads/zzaxa:zzep	(Ljava/lang/String;)V
    //   1357: aload 40
    //   1359: invokestatic 84	java/lang/String:valueOf	(Ljava/lang/Object;)Ljava/lang/String;
    //   1362: astore 43
    //   1364: aload 43
    //   1366: invokevirtual 88	java/lang/String:length	()I
    //   1369: ifeq +41 -> 1410
    //   1372: ldc_w 357
    //   1375: aload 43
    //   1377: invokevirtual 94	java/lang/String:concat	(Ljava/lang/String;)Ljava/lang/String;
    //   1380: astore 44
    //   1382: aload_0
    //   1383: aload_1
    //   1384: aload 9
    //   1386: invokevirtual 78	java/io/File:getAbsolutePath	()Ljava/lang/String;
    //   1389: ldc_w 359
    //   1392: aload 44
    //   1394: invokevirtual 128	com/google/android/gms/internal/ads/zzbfu:zza	(Ljava/lang/String;Ljava/lang/String;Ljava/lang/String;Ljava/lang/String;)V
    //   1397: getstatic 29	com/google/android/gms/internal/ads/zzbgf:zzeig	Ljava/util/Set;
    //   1400: aload 13
    //   1402: invokeinterface 276 2 0
    //   1407: pop
    //   1408: iconst_0
    //   1409: ireturn
    //   1410: new 80	java/lang/String
    //   1413: dup
    //   1414: ldc_w 357
    //   1417: invokespecial 95	java/lang/String:<init>	(Ljava/lang/String;)V
    //   1420: astore 44
    //   1422: goto -40 -> 1382
    //   1425: new 252	java/lang/StringBuilder
    //   1428: dup
    //   1429: bipush 20
    //   1431: aload 40
    //   1433: invokestatic 84	java/lang/String:valueOf	(Ljava/lang/Object;)Ljava/lang/String;
    //   1436: invokevirtual 88	java/lang/String:length	()I
    //   1439: iadd
    //   1440: aload_1
    //   1441: invokestatic 84	java/lang/String:valueOf	(Ljava/lang/Object;)Ljava/lang/String;
    //   1444: invokevirtual 88	java/lang/String:length	()I
    //   1447: iadd
    //   1448: invokespecial 254	java/lang/StringBuilder:<init>	(I)V
    //   1451: ldc_w 361
    //   1454: invokevirtual 260	java/lang/StringBuilder:append	(Ljava/lang/String;)Ljava/lang/StringBuilder;
    //   1457: aload 40
    //   1459: invokevirtual 260	java/lang/StringBuilder:append	(Ljava/lang/String;)Ljava/lang/StringBuilder;
    //   1462: ldc_w 363
    //   1465: invokevirtual 260	java/lang/StringBuilder:append	(Ljava/lang/String;)Ljava/lang/StringBuilder;
    //   1468: aload_1
    //   1469: invokevirtual 260	java/lang/StringBuilder:append	(Ljava/lang/String;)Ljava/lang/StringBuilder;
    //   1472: invokevirtual 265	java/lang/StringBuilder:toString	()Ljava/lang/String;
    //   1475: invokestatic 186	com/google/android/gms/internal/ads/zzaxa:zzdp	(Ljava/lang/String;)V
    //   1478: aload 33
    //   1480: invokevirtual 367	java/net/URLConnection:getInputStream	()Ljava/io/InputStream;
    //   1483: invokestatic 373	java/nio/channels/Channels:newChannel	(Ljava/io/InputStream;)Ljava/nio/channels/ReadableByteChannel;
    //   1486: astore 46
    //   1488: new 247	java/io/FileOutputStream
    //   1491: dup
    //   1492: aload 9
    //   1494: invokespecial 376	java/io/FileOutputStream:<init>	(Ljava/io/File;)V
    //   1497: astore 47
    //   1499: aload 47
    //   1501: invokevirtual 380	java/io/FileOutputStream:getChannel	()Ljava/nio/channels/FileChannel;
    //   1504: astore 48
    //   1506: ldc_w 381
    //   1509: invokestatic 387	java/nio/ByteBuffer:allocate	(I)Ljava/nio/ByteBuffer;
    //   1512: astore 49
    //   1514: invokestatic 391	com/google/android/gms/ads/internal/zzk:zzln	()Lcom/google/android/gms/common/util/Clock;
    //   1517: astore 50
    //   1519: iconst_0
    //   1520: istore 51
    //   1522: aload 50
    //   1524: invokeinterface 396 1 0
    //   1529: lstore 52
    //   1531: getstatic 399	com/google/android/gms/internal/ads/zzact:zzclz	Lcom/google/android/gms/internal/ads/zzaci;
    //   1534: astore 54
    //   1536: invokestatic 140	com/google/android/gms/internal/ads/zzyr:zzpe	()Lcom/google/android/gms/internal/ads/zzacq;
    //   1539: aload 54
    //   1541: invokevirtual 146	com/google/android/gms/internal/ads/zzacq:zzd	(Lcom/google/android/gms/internal/ads/zzaci;)Ljava/lang/Object;
    //   1544: checkcast 401	java/lang/Long
    //   1547: invokevirtual 404	java/lang/Long:longValue	()J
    //   1550: lstore 55
    //   1552: new 406	com/google/android/gms/internal/ads/zzazk
    //   1555: dup
    //   1556: lload 55
    //   1558: invokespecial 409	com/google/android/gms/internal/ads/zzazk:<init>	(J)V
    //   1561: astore 57
    //   1563: getstatic 412	com/google/android/gms/internal/ads/zzact:zzcly	Lcom/google/android/gms/internal/ads/zzaci;
    //   1566: astore 58
    //   1568: invokestatic 140	com/google/android/gms/internal/ads/zzyr:zzpe	()Lcom/google/android/gms/internal/ads/zzacq;
    //   1571: aload 58
    //   1573: invokevirtual 146	com/google/android/gms/internal/ads/zzacq:zzd	(Lcom/google/android/gms/internal/ads/zzaci;)Ljava/lang/Object;
    //   1576: checkcast 401	java/lang/Long
    //   1579: invokevirtual 404	java/lang/Long:longValue	()J
    //   1582: lstore 59
    //   1584: aload 46
    //   1586: aload 49
    //   1588: invokeinterface 418 2 0
    //   1593: istore 61
    //   1595: iload 61
    //   1597: iflt +295 -> 1892
    //   1600: iload 51
    //   1602: iload 61
    //   1604: iadd
    //   1605: istore 51
    //   1607: iload 51
    //   1609: iload 42
    //   1611: if_icmple +87 -> 1698
    //   1614: ldc_w 359
    //   1617: astore 19
    //   1619: iload 51
    //   1621: invokestatic 328	java/lang/Integer:toString	(I)Ljava/lang/String;
    //   1624: invokestatic 84	java/lang/String:valueOf	(Ljava/lang/Object;)Ljava/lang/String;
    //   1627: astore 74
    //   1629: aload 74
    //   1631: invokevirtual 88	java/lang/String:length	()I
    //   1634: ifeq +37 -> 1671
    //   1637: ldc_w 357
    //   1640: aload 74
    //   1642: invokevirtual 94	java/lang/String:concat	(Ljava/lang/String;)Ljava/lang/String;
    //   1645: astore 75
    //   1647: aload 75
    //   1649: astore 20
    //   1651: new 118	java/io/IOException
    //   1654: dup
    //   1655: ldc_w 420
    //   1658: invokespecial 232	java/io/IOException:<init>	(Ljava/lang/String;)V
    //   1661: athrow
    //   1662: astore 18
    //   1664: aload 47
    //   1666: astore 17
    //   1668: goto -1038 -> 630
    //   1671: new 80	java/lang/String
    //   1674: dup
    //   1675: ldc_w 357
    //   1678: invokespecial 95	java/lang/String:<init>	(Ljava/lang/String;)V
    //   1681: astore 20
    //   1683: goto -32 -> 1651
    //   1686: astore 18
    //   1688: aload 47
    //   1690: astore 17
    //   1692: aconst_null
    //   1693: astore 20
    //   1695: goto -1065 -> 630
    //   1698: aload 49
    //   1700: invokevirtual 424	java/nio/ByteBuffer:flip	()Ljava/nio/Buffer;
    //   1703: pop
    //   1704: aload 48
    //   1706: aload 49
    //   1708: invokevirtual 429	java/nio/channels/FileChannel:write	(Ljava/nio/ByteBuffer;)I
    //   1711: ifgt -7 -> 1704
    //   1714: aload 49
    //   1716: invokevirtual 432	java/nio/ByteBuffer:clear	()Ljava/nio/Buffer;
    //   1719: pop
    //   1720: aload 50
    //   1722: invokeinterface 396 1 0
    //   1727: lload 52
    //   1729: lsub
    //   1730: ldc2_w 433
    //   1733: lload 59
    //   1735: lmul
    //   1736: lcmp
    //   1737: ifle +79 -> 1816
    //   1740: ldc_w 436
    //   1743: astore 19
    //   1745: lload 59
    //   1747: invokestatic 438	java/lang/Long:toString	(J)Ljava/lang/String;
    //   1750: astore 70
    //   1752: new 252	java/lang/StringBuilder
    //   1755: dup
    //   1756: bipush 29
    //   1758: aload 70
    //   1760: invokestatic 84	java/lang/String:valueOf	(Ljava/lang/Object;)Ljava/lang/String;
    //   1763: invokevirtual 88	java/lang/String:length	()I
    //   1766: iadd
    //   1767: invokespecial 254	java/lang/StringBuilder:<init>	(I)V
    //   1770: ldc_w 440
    //   1773: invokevirtual 260	java/lang/StringBuilder:append	(Ljava/lang/String;)Ljava/lang/StringBuilder;
    //   1776: aload 70
    //   1778: invokevirtual 260	java/lang/StringBuilder:append	(Ljava/lang/String;)Ljava/lang/StringBuilder;
    //   1781: ldc_w 442
    //   1784: invokevirtual 260	java/lang/StringBuilder:append	(Ljava/lang/String;)Ljava/lang/StringBuilder;
    //   1787: invokevirtual 265	java/lang/StringBuilder:toString	()Ljava/lang/String;
    //   1790: astore 71
    //   1792: aload 71
    //   1794: astore 20
    //   1796: new 118	java/io/IOException
    //   1799: dup
    //   1800: ldc_w 444
    //   1803: invokespecial 232	java/io/IOException:<init>	(Ljava/lang/String;)V
    //   1806: athrow
    //   1807: astore 18
    //   1809: aload 47
    //   1811: astore 17
    //   1813: goto -1183 -> 630
    //   1816: aload_0
    //   1817: getfield 114	com/google/android/gms/internal/ads/zzbgf:zzeij	Z
    //   1820: ifeq +31 -> 1851
    //   1823: ldc_w 446
    //   1826: astore 19
    //   1828: new 118	java/io/IOException
    //   1831: dup
    //   1832: ldc_w 448
    //   1835: invokespecial 232	java/io/IOException:<init>	(Ljava/lang/String;)V
    //   1838: athrow
    //   1839: astore 18
    //   1841: aload 47
    //   1843: astore 17
    //   1845: aconst_null
    //   1846: astore 20
    //   1848: goto -1218 -> 630
    //   1851: aload 57
    //   1853: invokevirtual 451	com/google/android/gms/internal/ads/zzazk:tryAcquire	()Z
    //   1856: ifeq -272 -> 1584
    //   1859: aload 9
    //   1861: invokevirtual 78	java/io/File:getAbsolutePath	()Ljava/lang/String;
    //   1864: astore 72
    //   1866: getstatic 457	com/google/android/gms/internal/ads/zzazu:zzyr	Landroid/os/Handler;
    //   1869: new 459	com/google/android/gms/internal/ads/zzbfv
    //   1872: dup
    //   1873: aload_0
    //   1874: aload_1
    //   1875: aload 72
    //   1877: iload 51
    //   1879: iload 36
    //   1881: iconst_0
    //   1882: invokespecial 462	com/google/android/gms/internal/ads/zzbfv:<init>	(Lcom/google/android/gms/internal/ads/zzbfu;Ljava/lang/String;Ljava/lang/String;IIZ)V
    //   1885: invokevirtual 468	android/os/Handler:post	(Ljava/lang/Runnable;)Z
    //   1888: pop
    //   1889: goto -305 -> 1584
    //   1892: aload 47
    //   1894: invokevirtual 250	java/io/FileOutputStream:close	()V
    //   1897: iconst_3
    //   1898: invokestatic 472	com/google/android/gms/internal/ads/zzaxa:isLoggable	(I)Z
    //   1901: ifeq +67 -> 1968
    //   1904: getstatic 38	com/google/android/gms/internal/ads/zzbgf:zzeih	Ljava/text/DecimalFormat;
    //   1907: iload 51
    //   1909: i2l
    //   1910: invokevirtual 348	java/text/DecimalFormat:format	(J)Ljava/lang/String;
    //   1913: astore 67
    //   1915: new 252	java/lang/StringBuilder
    //   1918: dup
    //   1919: bipush 22
    //   1921: aload 67
    //   1923: invokestatic 84	java/lang/String:valueOf	(Ljava/lang/Object;)Ljava/lang/String;
    //   1926: invokevirtual 88	java/lang/String:length	()I
    //   1929: iadd
    //   1930: aload_1
    //   1931: invokestatic 84	java/lang/String:valueOf	(Ljava/lang/Object;)Ljava/lang/String;
    //   1934: invokevirtual 88	java/lang/String:length	()I
    //   1937: iadd
    //   1938: invokespecial 254	java/lang/StringBuilder:<init>	(I)V
    //   1941: ldc_w 474
    //   1944: invokevirtual 260	java/lang/StringBuilder:append	(Ljava/lang/String;)Ljava/lang/StringBuilder;
    //   1947: aload 67
    //   1949: invokevirtual 260	java/lang/StringBuilder:append	(Ljava/lang/String;)Ljava/lang/StringBuilder;
    //   1952: ldc_w 363
    //   1955: invokevirtual 260	java/lang/StringBuilder:append	(Ljava/lang/String;)Ljava/lang/StringBuilder;
    //   1958: aload_1
    //   1959: invokevirtual 260	java/lang/StringBuilder:append	(Ljava/lang/String;)Ljava/lang/StringBuilder;
    //   1962: invokevirtual 265	java/lang/StringBuilder:toString	()Ljava/lang/String;
    //   1965: invokestatic 186	com/google/android/gms/internal/ads/zzaxa:zzdp	(Ljava/lang/String;)V
    //   1968: aload 9
    //   1970: iconst_1
    //   1971: iconst_0
    //   1972: invokevirtual 99	java/io/File:setReadable	(ZZ)Z
    //   1975: pop
    //   1976: aload 10
    //   1978: invokevirtual 176	java/io/File:isFile	()Z
    //   1981: ifeq +37 -> 2018
    //   1984: aload 10
    //   1986: invokestatic 477	java/lang/System:currentTimeMillis	()J
    //   1989: invokevirtual 481	java/io/File:setLastModified	(J)Z
    //   1992: pop
    //   1993: aload_0
    //   1994: aload_1
    //   1995: aload 9
    //   1997: invokevirtual 78	java/io/File:getAbsolutePath	()Ljava/lang/String;
    //   2000: iload 51
    //   2002: invokevirtual 189	com/google/android/gms/internal/ads/zzbfu:zza	(Ljava/lang/String;Ljava/lang/String;I)V
    //   2005: getstatic 29	com/google/android/gms/internal/ads/zzbgf:zzeig	Ljava/util/Set;
    //   2008: aload 13
    //   2010: invokeinterface 276 2 0
    //   2015: pop
    //   2016: iconst_1
    //   2017: ireturn
    //   2018: aload 10
    //   2020: invokevirtual 484	java/io/File:createNewFile	()Z
    //   2023: pop
    //   2024: goto -31 -> 1993
    //   2027: astore 63
    //   2029: goto -36 -> 1993
    //   2032: new 252	java/lang/StringBuilder
    //   2035: dup
    //   2036: bipush 25
    //   2038: aload_1
    //   2039: invokestatic 84	java/lang/String:valueOf	(Ljava/lang/Object;)Ljava/lang/String;
    //   2042: invokevirtual 88	java/lang/String:length	()I
    //   2045: iadd
    //   2046: invokespecial 254	java/lang/StringBuilder:<init>	(I)V
    //   2049: ldc_w 486
    //   2052: invokevirtual 260	java/lang/StringBuilder:append	(Ljava/lang/String;)Ljava/lang/StringBuilder;
    //   2055: aload_1
    //   2056: invokevirtual 260	java/lang/StringBuilder:append	(Ljava/lang/String;)Ljava/lang/StringBuilder;
    //   2059: ldc_w 262
    //   2062: invokevirtual 260	java/lang/StringBuilder:append	(Ljava/lang/String;)Ljava/lang/StringBuilder;
    //   2065: invokevirtual 265	java/lang/StringBuilder:toString	()Ljava/lang/String;
    //   2068: aload 18
    //   2070: invokestatic 489	com/google/android/gms/internal/ads/zzaxa:zzd	(Ljava/lang/String;Ljava/lang/Throwable;)V
    //   2073: goto -1374 -> 699
    //   2076: new 80	java/lang/String
    //   2079: dup
    //   2080: ldc_w 273
    //   2083: invokespecial 95	java/lang/String:<init>	(Ljava/lang/String;)V
    //   2086: astore 24
    //   2088: goto -1345 -> 743
    //   2091: astore 25
    //   2093: goto -1440 -> 653
    //   2096: astore 21
    //   2098: goto -1445 -> 653
    //   2101: astore 18
    //   2103: aconst_null
    //   2104: astore 20
    //   2106: aconst_null
    //   2107: astore 17
    //   2109: goto -1479 -> 630
    //   2112: astore 18
    //   2114: aconst_null
    //   2115: astore 17
    //   2117: goto -1487 -> 630
    //   2120: astore 18
    //   2122: ldc 234
    //   2124: astore 19
    //   2126: aload 47
    //   2128: astore 17
    //   2130: aconst_null
    //   2131: astore 20
    //   2133: goto -1503 -> 630
    //   2136: lload 92
    //   2138: lstore 100
    //   2140: aload 91
    //   2142: astore 102
    //   2144: goto -1936 -> 208
    //   2147: astore 18
    //   2149: ldc 234
    //   2151: astore 19
    //   2153: aconst_null
    //   2154: astore 20
    //   2156: aconst_null
    //   2157: astore 17
    //   2159: goto -1529 -> 630
    //   2162: astore 18
    //   2164: ldc 234
    //   2166: astore 19
    //   2168: aload 47
    //   2170: astore 17
    //   2172: aconst_null
    //   2173: astore 20
    //   2175: goto -1545 -> 630
    //
    // Exception table:
    //   from	to	target	type
    //   419	455	478	finally
    //   455	476	478	finally
    //   480	483	478	finally
    //   500	511	478	finally
    //   514	528	478	finally
    //   531	566	621	java/io/IOException
    //   582	621	621	java/io/IOException
    //   775	840	621	java/io/IOException
    //   845	856	621	java/io/IOException
    //   856	876	621	java/io/IOException
    //   881	892	621	java/io/IOException
    //   892	939	621	java/io/IOException
    //   939	949	621	java/io/IOException
    //   949	961	621	java/io/IOException
    //   964	989	621	java/io/IOException
    //   989	999	621	java/io/IOException
    //   1010	1022	621	java/io/IOException
    //   1025	1036	621	java/io/IOException
    //   1036	1054	621	java/io/IOException
    //   1182	1189	621	java/io/IOException
    //   1194	1218	621	java/io/IOException
    //   1218	1248	621	java/io/IOException
    //   1250	1262	621	java/io/IOException
    //   1265	1297	621	java/io/IOException
    //   1304	1382	621	java/io/IOException
    //   1382	1408	621	java/io/IOException
    //   1410	1422	621	java/io/IOException
    //   1425	1499	621	java/io/IOException
    //   1099	1148	1148	java/io/IOException
    //   1067	1095	1171	java/io/IOException
    //   1156	1168	1171	java/io/IOException
    //   1651	1662	1662	java/io/IOException
    //   1796	1807	1662	java/io/IOException
    //   1619	1647	1686	java/io/IOException
    //   1671	1683	1686	java/io/IOException
    //   1745	1792	1686	java/io/IOException
    //   1828	1839	1686	java/io/IOException
    //   1651	1662	1807	java/lang/RuntimeException
    //   1796	1807	1807	java/lang/RuntimeException
    //   1619	1647	1839	java/lang/RuntimeException
    //   1671	1683	1839	java/lang/RuntimeException
    //   1745	1792	1839	java/lang/RuntimeException
    //   1828	1839	1839	java/lang/RuntimeException
    //   2018	2024	2027	java/io/IOException
    //   648	653	2091	java/io/IOException
    //   648	653	2096	java/lang/NullPointerException
    //   1067	1095	2101	java/lang/RuntimeException
    //   1156	1168	2101	java/lang/RuntimeException
    //   1099	1148	2112	java/lang/RuntimeException
    //   1499	1519	2120	java/lang/RuntimeException
    //   1522	1584	2120	java/lang/RuntimeException
    //   1584	1595	2120	java/lang/RuntimeException
    //   1698	1704	2120	java/lang/RuntimeException
    //   1704	1740	2120	java/lang/RuntimeException
    //   1816	1823	2120	java/lang/RuntimeException
    //   1851	1889	2120	java/lang/RuntimeException
    //   1892	1968	2120	java/lang/RuntimeException
    //   1968	1993	2120	java/lang/RuntimeException
    //   1993	2016	2120	java/lang/RuntimeException
    //   2018	2024	2120	java/lang/RuntimeException
    //   531	566	2147	java/lang/RuntimeException
    //   582	621	2147	java/lang/RuntimeException
    //   775	840	2147	java/lang/RuntimeException
    //   845	856	2147	java/lang/RuntimeException
    //   856	876	2147	java/lang/RuntimeException
    //   881	892	2147	java/lang/RuntimeException
    //   892	939	2147	java/lang/RuntimeException
    //   939	949	2147	java/lang/RuntimeException
    //   949	961	2147	java/lang/RuntimeException
    //   964	989	2147	java/lang/RuntimeException
    //   989	999	2147	java/lang/RuntimeException
    //   1010	1022	2147	java/lang/RuntimeException
    //   1025	1036	2147	java/lang/RuntimeException
    //   1036	1054	2147	java/lang/RuntimeException
    //   1182	1189	2147	java/lang/RuntimeException
    //   1194	1218	2147	java/lang/RuntimeException
    //   1218	1248	2147	java/lang/RuntimeException
    //   1250	1262	2147	java/lang/RuntimeException
    //   1265	1297	2147	java/lang/RuntimeException
    //   1304	1382	2147	java/lang/RuntimeException
    //   1382	1408	2147	java/lang/RuntimeException
    //   1410	1422	2147	java/lang/RuntimeException
    //   1425	1499	2147	java/lang/RuntimeException
    //   1499	1519	2162	java/io/IOException
    //   1522	1584	2162	java/io/IOException
    //   1584	1595	2162	java/io/IOException
    //   1698	1704	2162	java/io/IOException
    //   1704	1740	2162	java/io/IOException
    //   1816	1823	2162	java/io/IOException
    //   1851	1889	2162	java/io/IOException
    //   1892	1968	2162	java/io/IOException
    //   1968	1993	2162	java/io/IOException
    //   1993	2016	2162	java/io/IOException
  }
}

/* Location:           E:\Study\Tools\apktool2_2\dex2jar-0.0.9.15\classes_viber_2_dex2jar.jar
 * Qualified Name:     com.google.android.gms.internal.ads.zzbgf
 * JD-Core Version:    0.6.2
 */