package com.google.android.gms.internal.ads;

import android.content.Context;

public final class zzcit
  implements zzczb<zzciu, zzciv>
{
  private final String zzdmk;
  private final zzasn zzfxl;
  private final String zzfxz;
  private final Context zzlj;

  public zzcit(Context paramContext, String paramString1, zzasn paramzzasn, String paramString2)
  {
    this.zzlj = paramContext;
    this.zzfxz = paramString1;
    this.zzfxl = paramzzasn;
    this.zzdmk = paramString2;
  }

  // ERROR //
  private final zzciv zza(String paramString1, zzase paramzzase, org.json.JSONObject paramJSONObject, String paramString2)
    throws zzcie
  {
    // Byte code:
    //   0: new 35	com/google/android/gms/internal/ads/zzciv
    //   3: dup
    //   4: invokespecial 36	com/google/android/gms/internal/ads/zzciv:<init>	()V
    //   7: astore 5
    //   9: aload_0
    //   10: getfield 23	com/google/android/gms/internal/ads/zzcit:zzfxz	Ljava/lang/String;
    //   13: invokestatic 42	java/lang/String:valueOf	(Ljava/lang/Object;)Ljava/lang/String;
    //   16: astore 11
    //   18: aload 11
    //   20: invokevirtual 46	java/lang/String:length	()I
    //   23: ifeq +503 -> 526
    //   26: ldc 48
    //   28: aload 11
    //   30: invokevirtual 52	java/lang/String:concat	(Ljava/lang/String;)Ljava/lang/String;
    //   33: astore 12
    //   35: aload 12
    //   37: invokestatic 58	com/google/android/gms/internal/ads/zzaxa:zzeo	(Ljava/lang/String;)V
    //   40: aload_1
    //   41: invokestatic 42	java/lang/String:valueOf	(Ljava/lang/Object;)Ljava/lang/String;
    //   44: astore 13
    //   46: aload 13
    //   48: invokevirtual 46	java/lang/String:length	()I
    //   51: ifeq +489 -> 540
    //   54: ldc 60
    //   56: aload 13
    //   58: invokevirtual 52	java/lang/String:concat	(Ljava/lang/String;)Ljava/lang/String;
    //   61: astore 14
    //   63: aload 14
    //   65: invokestatic 63	com/google/android/gms/internal/ads/zzaxa:zzdp	(Ljava/lang/String;)V
    //   68: new 65	java/net/URL
    //   71: dup
    //   72: aload_1
    //   73: invokespecial 67	java/net/URL:<init>	(Ljava/lang/String;)V
    //   76: astore 15
    //   78: new 69	java/util/HashMap
    //   81: dup
    //   82: invokespecial 70	java/util/HashMap:<init>	()V
    //   85: astore 16
    //   87: invokestatic 76	com/google/android/gms/ads/internal/zzk:zzln	()Lcom/google/android/gms/common/util/Clock;
    //   90: invokeinterface 82 1 0
    //   95: lstore 17
    //   97: iconst_0
    //   98: istore 19
    //   100: aload 15
    //   102: astore 20
    //   104: aload_0
    //   105: getfield 25	com/google/android/gms/internal/ads/zzcit:zzfxl	Lcom/google/android/gms/internal/ads/zzasn;
    //   108: invokeinterface 87 1 0
    //   113: aload 20
    //   115: invokevirtual 91	java/net/URL:openConnection	()Ljava/net/URLConnection;
    //   118: checkcast 93	java/net/HttpURLConnection
    //   121: astore 21
    //   123: invokestatic 97	com/google/android/gms/ads/internal/zzk:zzlg	()Lcom/google/android/gms/internal/ads/zzaxj;
    //   126: aload_0
    //   127: getfield 21	com/google/android/gms/internal/ads/zzcit:zzlj	Landroid/content/Context;
    //   130: aload_0
    //   131: getfield 23	com/google/android/gms/internal/ads/zzcit:zzfxz	Ljava/lang/String;
    //   134: iconst_0
    //   135: aload 21
    //   137: invokevirtual 102	com/google/android/gms/internal/ads/zzaxj:zza	(Landroid/content/Context;Ljava/lang/String;ZLjava/net/HttpURLConnection;)V
    //   140: aload 4
    //   142: invokestatic 108	android/text/TextUtils:isEmpty	(Ljava/lang/CharSequence;)Z
    //   145: ifne +12 -> 157
    //   148: aload 21
    //   150: ldc 110
    //   152: aload 4
    //   154: invokevirtual 114	java/net/HttpURLConnection:addRequestProperty	(Ljava/lang/String;Ljava/lang/String;)V
    //   157: aload_2
    //   158: invokevirtual 120	com/google/android/gms/internal/ads/zzase:zztw	()Z
    //   161: ifeq +78 -> 239
    //   164: aload_3
    //   165: ldc 122
    //   167: invokevirtual 128	org/json/JSONObject:optJSONObject	(Ljava/lang/String;)Lorg/json/JSONObject;
    //   170: astore 44
    //   172: aload 44
    //   174: ifnull +380 -> 554
    //   177: aload 44
    //   179: ldc 130
    //   181: ldc 132
    //   183: invokevirtual 136	org/json/JSONObject:optString	(Ljava/lang/String;Ljava/lang/String;)Ljava/lang/String;
    //   186: invokestatic 108	android/text/TextUtils:isEmpty	(Ljava/lang/CharSequence;)Z
    //   189: ifne +19 -> 208
    //   192: aload 21
    //   194: ldc 138
    //   196: aload 44
    //   198: ldc 130
    //   200: ldc 132
    //   202: invokevirtual 136	org/json/JSONObject:optString	(Ljava/lang/String;Ljava/lang/String;)Ljava/lang/String;
    //   205: invokevirtual 114	java/net/HttpURLConnection:addRequestProperty	(Ljava/lang/String;Ljava/lang/String;)V
    //   208: aload 44
    //   210: ldc 140
    //   212: ldc 132
    //   214: invokevirtual 136	org/json/JSONObject:optString	(Ljava/lang/String;Ljava/lang/String;)Ljava/lang/String;
    //   217: invokestatic 108	android/text/TextUtils:isEmpty	(Ljava/lang/CharSequence;)Z
    //   220: ifne +19 -> 239
    //   223: aload 21
    //   225: ldc 142
    //   227: aload 44
    //   229: ldc 140
    //   231: ldc 132
    //   233: invokevirtual 136	org/json/JSONObject:optString	(Ljava/lang/String;Ljava/lang/String;)Ljava/lang/String;
    //   236: invokevirtual 114	java/net/HttpURLConnection:addRequestProperty	(Ljava/lang/String;Ljava/lang/String;)V
    //   239: aconst_null
    //   240: astore 23
    //   242: aload_2
    //   243: ifnull +69 -> 312
    //   246: aload_2
    //   247: invokevirtual 146	com/google/android/gms/internal/ads/zzase:zztv	()Ljava/lang/String;
    //   250: invokestatic 108	android/text/TextUtils:isEmpty	(Ljava/lang/CharSequence;)Z
    //   253: istore 24
    //   255: aconst_null
    //   256: astore 23
    //   258: iload 24
    //   260: ifne +52 -> 312
    //   263: aload 21
    //   265: iconst_1
    //   266: invokevirtual 150	java/net/HttpURLConnection:setDoOutput	(Z)V
    //   269: aload_2
    //   270: invokevirtual 146	com/google/android/gms/internal/ads/zzase:zztv	()Ljava/lang/String;
    //   273: invokevirtual 154	java/lang/String:getBytes	()[B
    //   276: astore 23
    //   278: aload 21
    //   280: aload 23
    //   282: arraylength
    //   283: invokevirtual 158	java/net/HttpURLConnection:setFixedLengthStreamingMode	(I)V
    //   286: new 160	java/io/BufferedOutputStream
    //   289: dup
    //   290: aload 21
    //   292: invokevirtual 164	java/net/HttpURLConnection:getOutputStream	()Ljava/io/OutputStream;
    //   295: invokespecial 167	java/io/BufferedOutputStream:<init>	(Ljava/io/OutputStream;)V
    //   298: astore 25
    //   300: aload 25
    //   302: aload 23
    //   304: invokevirtual 171	java/io/BufferedOutputStream:write	([B)V
    //   307: aload 25
    //   309: invokestatic 177	com/google/android/gms/common/util/IOUtils:closeQuietly	(Ljava/io/Closeable;)V
    //   312: new 179	com/google/android/gms/internal/ads/zzazy
    //   315: dup
    //   316: invokespecial 180	com/google/android/gms/internal/ads/zzazy:<init>	()V
    //   319: astore 27
    //   321: aload 27
    //   323: aload 21
    //   325: aload 23
    //   327: invokevirtual 183	com/google/android/gms/internal/ads/zzazy:zza	(Ljava/net/HttpURLConnection;[B)V
    //   330: aload 21
    //   332: invokevirtual 186	java/net/HttpURLConnection:getResponseCode	()I
    //   335: istore 28
    //   337: aload 21
    //   339: invokevirtual 190	java/net/HttpURLConnection:getHeaderFields	()Ljava/util/Map;
    //   342: invokeinterface 196 1 0
    //   347: invokeinterface 202 1 0
    //   352: astore 29
    //   354: aload 29
    //   356: invokeinterface 207 1 0
    //   361: ifeq +231 -> 592
    //   364: aload 29
    //   366: invokeinterface 211 1 0
    //   371: checkcast 213	java/util/Map$Entry
    //   374: astore 39
    //   376: aload 39
    //   378: invokeinterface 216 1 0
    //   383: checkcast 38	java/lang/String
    //   386: astore 40
    //   388: aload 39
    //   390: invokeinterface 219 1 0
    //   395: checkcast 221	java/util/List
    //   398: astore 41
    //   400: aload 16
    //   402: aload 40
    //   404: invokeinterface 225 2 0
    //   409: ifeq +161 -> 570
    //   412: aload 16
    //   414: aload 40
    //   416: invokeinterface 229 2 0
    //   421: checkcast 221	java/util/List
    //   424: aload 41
    //   426: invokeinterface 233 2 0
    //   431: pop
    //   432: goto -78 -> 354
    //   435: astore 22
    //   437: aload 21
    //   439: invokevirtual 236	java/net/HttpURLConnection:disconnect	()V
    //   442: aload_0
    //   443: getfield 25	com/google/android/gms/internal/ads/zzcit:zzfxl	Lcom/google/android/gms/internal/ads/zzasn;
    //   446: invokeinterface 239 1 0
    //   451: aload 22
    //   453: athrow
    //   454: astore 6
    //   456: aload 6
    //   458: invokevirtual 242	java/io/IOException:getMessage	()Ljava/lang/String;
    //   461: invokestatic 42	java/lang/String:valueOf	(Ljava/lang/Object;)Ljava/lang/String;
    //   464: astore 7
    //   466: aload 7
    //   468: invokevirtual 46	java/lang/String:length	()I
    //   471: ifeq +478 -> 949
    //   474: ldc 244
    //   476: aload 7
    //   478: invokevirtual 52	java/lang/String:concat	(Ljava/lang/String;)Ljava/lang/String;
    //   481: astore 8
    //   483: aload 8
    //   485: invokestatic 247	com/google/android/gms/internal/ads/zzaxa:zzep	(Ljava/lang/String;)V
    //   488: aload 6
    //   490: invokevirtual 242	java/io/IOException:getMessage	()Ljava/lang/String;
    //   493: invokestatic 42	java/lang/String:valueOf	(Ljava/lang/Object;)Ljava/lang/String;
    //   496: astore 9
    //   498: aload 9
    //   500: invokevirtual 46	java/lang/String:length	()I
    //   503: ifeq +460 -> 963
    //   506: ldc 249
    //   508: aload 9
    //   510: invokevirtual 52	java/lang/String:concat	(Ljava/lang/String;)Ljava/lang/String;
    //   513: astore 10
    //   515: new 31	com/google/android/gms/internal/ads/zzcie
    //   518: dup
    //   519: aload 10
    //   521: iconst_2
    //   522: invokespecial 252	com/google/android/gms/internal/ads/zzcie:<init>	(Ljava/lang/String;I)V
    //   525: athrow
    //   526: new 38	java/lang/String
    //   529: dup
    //   530: ldc 48
    //   532: invokespecial 253	java/lang/String:<init>	(Ljava/lang/String;)V
    //   535: astore 12
    //   537: goto -502 -> 35
    //   540: new 38	java/lang/String
    //   543: dup
    //   544: ldc 60
    //   546: invokespecial 253	java/lang/String:<init>	(Ljava/lang/String;)V
    //   549: astore 14
    //   551: goto -488 -> 63
    //   554: ldc 255
    //   556: invokestatic 258	com/google/android/gms/internal/ads/zzaxa:zzds	(Ljava/lang/String;)V
    //   559: goto -320 -> 239
    //   562: aload 25
    //   564: invokestatic 177	com/google/android/gms/common/util/IOUtils:closeQuietly	(Ljava/io/Closeable;)V
    //   567: aload 26
    //   569: athrow
    //   570: aload 16
    //   572: aload 40
    //   574: new 260	java/util/ArrayList
    //   577: dup
    //   578: aload 41
    //   580: invokespecial 263	java/util/ArrayList:<init>	(Ljava/util/Collection;)V
    //   583: invokeinterface 267 3 0
    //   588: pop
    //   589: goto -235 -> 354
    //   592: aload 27
    //   594: aload 21
    //   596: iload 28
    //   598: invokevirtual 270	com/google/android/gms/internal/ads/zzazy:zza	(Ljava/net/HttpURLConnection;I)V
    //   601: iload 28
    //   603: sipush 200
    //   606: if_icmplt +152 -> 758
    //   609: iload 28
    //   611: sipush 300
    //   614: if_icmpge +144 -> 758
    //   617: new 272	java/io/InputStreamReader
    //   620: dup
    //   621: aload 21
    //   623: invokevirtual 276	java/net/HttpURLConnection:getInputStream	()Ljava/io/InputStream;
    //   626: invokespecial 279	java/io/InputStreamReader:<init>	(Ljava/io/InputStream;)V
    //   629: astore 34
    //   631: invokestatic 97	com/google/android/gms/ads/internal/zzk:zzlg	()Lcom/google/android/gms/internal/ads/zzaxj;
    //   634: pop
    //   635: aload 34
    //   637: invokestatic 282	com/google/android/gms/internal/ads/zzaxj:zza	(Ljava/io/InputStreamReader;)Ljava/lang/String;
    //   640: astore 37
    //   642: aload 34
    //   644: invokestatic 177	com/google/android/gms/common/util/IOUtils:closeQuietly	(Ljava/io/Closeable;)V
    //   647: aload 27
    //   649: aload 37
    //   651: invokevirtual 285	com/google/android/gms/internal/ads/zzazy:zzek	(Ljava/lang/String;)V
    //   654: aload 5
    //   656: iload 28
    //   658: putfield 289	com/google/android/gms/internal/ads/zzciv:zzfya	I
    //   661: aload 5
    //   663: aload 37
    //   665: putfield 292	com/google/android/gms/internal/ads/zzciv:zzdnj	Ljava/lang/String;
    //   668: aload 5
    //   670: aload 16
    //   672: putfield 296	com/google/android/gms/internal/ads/zzciv:zzab	Ljava/util/Map;
    //   675: aload 37
    //   677: invokestatic 108	android/text/TextUtils:isEmpty	(Ljava/lang/CharSequence;)Z
    //   680: ifeq +45 -> 725
    //   683: getstatic 302	com/google/android/gms/internal/ads/zzact:zzcvl	Lcom/google/android/gms/internal/ads/zzaci;
    //   686: astore 38
    //   688: invokestatic 308	com/google/android/gms/internal/ads/zzyr:zzpe	()Lcom/google/android/gms/internal/ads/zzacq;
    //   691: aload 38
    //   693: invokevirtual 314	com/google/android/gms/internal/ads/zzacq:zzd	(Lcom/google/android/gms/internal/ads/zzaci;)Ljava/lang/Object;
    //   696: checkcast 316	java/lang/Boolean
    //   699: invokevirtual 319	java/lang/Boolean:booleanValue	()Z
    //   702: ifne +23 -> 725
    //   705: new 31	com/google/android/gms/internal/ads/zzcie
    //   708: dup
    //   709: ldc_w 321
    //   712: iconst_3
    //   713: invokespecial 252	com/google/android/gms/internal/ads/zzcie:<init>	(Ljava/lang/String;I)V
    //   716: athrow
    //   717: aload 34
    //   719: invokestatic 177	com/google/android/gms/common/util/IOUtils:closeQuietly	(Ljava/io/Closeable;)V
    //   722: aload 35
    //   724: athrow
    //   725: aload 5
    //   727: invokestatic 76	com/google/android/gms/ads/internal/zzk:zzln	()Lcom/google/android/gms/common/util/Clock;
    //   730: invokeinterface 82 1 0
    //   735: lload 17
    //   737: lsub
    //   738: putfield 325	com/google/android/gms/internal/ads/zzciv:zzfyb	J
    //   741: aload 21
    //   743: invokevirtual 236	java/net/HttpURLConnection:disconnect	()V
    //   746: aload_0
    //   747: getfield 25	com/google/android/gms/internal/ads/zzcit:zzfxl	Lcom/google/android/gms/internal/ads/zzasn;
    //   750: invokeinterface 239 1 0
    //   755: aload 5
    //   757: areturn
    //   758: iload 28
    //   760: sipush 300
    //   763: if_icmplt +104 -> 867
    //   766: iload 28
    //   768: sipush 400
    //   771: if_icmpge +96 -> 867
    //   774: aload 21
    //   776: ldc_w 327
    //   779: invokevirtual 330	java/net/HttpURLConnection:getHeaderField	(Ljava/lang/String;)Ljava/lang/String;
    //   782: astore 30
    //   784: aload 30
    //   786: invokestatic 108	android/text/TextUtils:isEmpty	(Ljava/lang/CharSequence;)Z
    //   789: ifeq +20 -> 809
    //   792: ldc_w 332
    //   795: invokestatic 247	com/google/android/gms/internal/ads/zzaxa:zzep	(Ljava/lang/String;)V
    //   798: new 31	com/google/android/gms/internal/ads/zzcie
    //   801: dup
    //   802: ldc_w 334
    //   805: invokespecial 335	com/google/android/gms/internal/ads/zzcie:<init>	(Ljava/lang/String;)V
    //   808: athrow
    //   809: new 65	java/net/URL
    //   812: dup
    //   813: aload 30
    //   815: invokespecial 67	java/net/URL:<init>	(Ljava/lang/String;)V
    //   818: astore 31
    //   820: iload 19
    //   822: iconst_1
    //   823: iadd
    //   824: istore 32
    //   826: getstatic 338	com/google/android/gms/internal/ads/zzact:zzcuu	Lcom/google/android/gms/internal/ads/zzaci;
    //   829: astore 33
    //   831: iload 32
    //   833: invokestatic 308	com/google/android/gms/internal/ads/zzyr:zzpe	()Lcom/google/android/gms/internal/ads/zzacq;
    //   836: aload 33
    //   838: invokevirtual 314	com/google/android/gms/internal/ads/zzacq:zzd	(Lcom/google/android/gms/internal/ads/zzaci;)Ljava/lang/Object;
    //   841: checkcast 340	java/lang/Integer
    //   844: invokevirtual 343	java/lang/Integer:intValue	()I
    //   847: if_icmple +77 -> 924
    //   850: ldc_w 345
    //   853: invokestatic 247	com/google/android/gms/internal/ads/zzaxa:zzep	(Ljava/lang/String;)V
    //   856: new 31	com/google/android/gms/internal/ads/zzcie
    //   859: dup
    //   860: ldc_w 347
    //   863: invokespecial 335	com/google/android/gms/internal/ads/zzcie:<init>	(Ljava/lang/String;)V
    //   866: athrow
    //   867: new 349	java/lang/StringBuilder
    //   870: dup
    //   871: bipush 46
    //   873: invokespecial 351	java/lang/StringBuilder:<init>	(I)V
    //   876: ldc_w 353
    //   879: invokevirtual 357	java/lang/StringBuilder:append	(Ljava/lang/String;)Ljava/lang/StringBuilder;
    //   882: iload 28
    //   884: invokevirtual 360	java/lang/StringBuilder:append	(I)Ljava/lang/StringBuilder;
    //   887: invokevirtual 363	java/lang/StringBuilder:toString	()Ljava/lang/String;
    //   890: invokestatic 247	com/google/android/gms/internal/ads/zzaxa:zzep	(Ljava/lang/String;)V
    //   893: new 31	com/google/android/gms/internal/ads/zzcie
    //   896: dup
    //   897: new 349	java/lang/StringBuilder
    //   900: dup
    //   901: bipush 46
    //   903: invokespecial 351	java/lang/StringBuilder:<init>	(I)V
    //   906: ldc_w 353
    //   909: invokevirtual 357	java/lang/StringBuilder:append	(Ljava/lang/String;)Ljava/lang/StringBuilder;
    //   912: iload 28
    //   914: invokevirtual 360	java/lang/StringBuilder:append	(I)Ljava/lang/StringBuilder;
    //   917: invokevirtual 363	java/lang/StringBuilder:toString	()Ljava/lang/String;
    //   920: invokespecial 335	com/google/android/gms/internal/ads/zzcie:<init>	(Ljava/lang/String;)V
    //   923: athrow
    //   924: aload 21
    //   926: invokevirtual 236	java/net/HttpURLConnection:disconnect	()V
    //   929: aload_0
    //   930: getfield 25	com/google/android/gms/internal/ads/zzcit:zzfxl	Lcom/google/android/gms/internal/ads/zzasn;
    //   933: invokeinterface 239 1 0
    //   938: iload 32
    //   940: istore 19
    //   942: aload 31
    //   944: astore 20
    //   946: goto -842 -> 104
    //   949: new 38	java/lang/String
    //   952: dup
    //   953: ldc 244
    //   955: invokespecial 253	java/lang/String:<init>	(Ljava/lang/String;)V
    //   958: astore 8
    //   960: goto -477 -> 483
    //   963: new 38	java/lang/String
    //   966: dup
    //   967: ldc 249
    //   969: invokespecial 253	java/lang/String:<init>	(Ljava/lang/String;)V
    //   972: astore 10
    //   974: goto -459 -> 515
    //   977: astore 35
    //   979: goto -262 -> 717
    //   982: astore 26
    //   984: goto -422 -> 562
    //   987: astore 26
    //   989: aconst_null
    //   990: astore 25
    //   992: goto -430 -> 562
    //   995: astore 35
    //   997: aconst_null
    //   998: astore 34
    //   1000: goto -283 -> 717
    //
    // Exception table:
    //   from	to	target	type
    //   123	157	435	finally
    //   157	172	435	finally
    //   177	208	435	finally
    //   208	239	435	finally
    //   246	255	435	finally
    //   263	286	435	finally
    //   307	312	435	finally
    //   312	354	435	finally
    //   354	432	435	finally
    //   554	559	435	finally
    //   562	570	435	finally
    //   570	589	435	finally
    //   592	601	435	finally
    //   642	717	435	finally
    //   717	725	435	finally
    //   725	741	435	finally
    //   774	809	435	finally
    //   809	820	435	finally
    //   826	867	435	finally
    //   867	924	435	finally
    //   0	35	454	java/io/IOException
    //   35	63	454	java/io/IOException
    //   63	97	454	java/io/IOException
    //   104	123	454	java/io/IOException
    //   437	454	454	java/io/IOException
    //   526	537	454	java/io/IOException
    //   540	551	454	java/io/IOException
    //   741	755	454	java/io/IOException
    //   924	938	454	java/io/IOException
    //   631	642	977	finally
    //   300	307	982	finally
    //   286	300	987	finally
    //   617	631	995	finally
  }
}

/* Location:           E:\Study\Tools\apktool2_2\dex2jar-0.0.9.15\classes_viber_2_dex2jar.jar
 * Qualified Name:     com.google.android.gms.internal.ads.zzcit
 * JD-Core Version:    0.6.2
 */