package com.google.android.gms.internal.ads;

final class zzck
  implements Runnable
{
  // ERROR //
  public final void run()
  {
    // Byte code:
    //   0: ldc 17
    //   2: invokestatic 23	java/security/MessageDigest:getInstance	(Ljava/lang/String;)Ljava/security/MessageDigest;
    //   5: invokestatic 29	com/google/android/gms/internal/ads/zzci:zza	(Ljava/security/MessageDigest;)Ljava/security/MessageDigest;
    //   8: pop
    //   9: getstatic 33	com/google/android/gms/internal/ads/zzci:zznn	Ljava/util/concurrent/CountDownLatch;
    //   12: invokevirtual 38	java/util/concurrent/CountDownLatch:countDown	()V
    //   15: return
    //   16: astore_2
    //   17: getstatic 33	com/google/android/gms/internal/ads/zzci:zznn	Ljava/util/concurrent/CountDownLatch;
    //   20: invokevirtual 38	java/util/concurrent/CountDownLatch:countDown	()V
    //   23: return
    //   24: astore_1
    //   25: getstatic 33	com/google/android/gms/internal/ads/zzci:zznn	Ljava/util/concurrent/CountDownLatch;
    //   28: invokevirtual 38	java/util/concurrent/CountDownLatch:countDown	()V
    //   31: aload_1
    //   32: athrow
    //
    // Exception table:
    //   from	to	target	type
    //   0	9	16	java/security/NoSuchAlgorithmException
    //   0	9	24	finally
  }
}

/* Location:           E:\Study\Tools\apktool2_2\dex2jar-0.0.9.15\classes_viber_2_dex2jar.jar
 * Qualified Name:     com.google.android.gms.internal.ads.zzck
 * JD-Core Version:    0.6.2
 */