package com.google.android.gms.internal.ads;

import android.content.BroadcastReceiver;
import android.content.Context;
import android.content.Intent;
import android.content.pm.PackageInfo;
import android.content.pm.PackageManager;
import android.util.Log;
import android.util.Pair;
import com.google.android.gms.ads.identifier.AdvertisingIdClient;
import com.google.android.gms.common.GooglePlayServicesNotAvailableException;
import com.google.android.gms.common.GooglePlayServicesRepairableException;
import dalvik.system.DexClassLoader;
import java.io.File;
import java.io.IOException;
import java.lang.reflect.Method;
import java.util.HashMap;
import java.util.Map;
import java.util.concurrent.ExecutionException;
import java.util.concurrent.ExecutorService;
import java.util.concurrent.Future;
import java.util.concurrent.TimeUnit;
import java.util.concurrent.TimeoutException;

public class zzdy
{
  private static final String TAG = zzdy.class.getSimpleName();
  protected Context zzlj;
  private volatile boolean zzwf = false;
  private ExecutorService zzxf;
  private DexClassLoader zzxg;
  private zzdj zzxh;
  private byte[] zzxi;
  private volatile AdvertisingIdClient zzxj = null;
  private Future zzxk = null;
  private boolean zzxl;
  private volatile zzbp.zza zzxm = null;
  private Future zzxn = null;
  private zzda zzxo;
  protected boolean zzxp = false;
  private boolean zzxq = false;
  private Map<Pair<String, String>, zzfi> zzxr;
  private boolean zzxs = false;
  private boolean zzxt;
  private boolean zzxu;

  private zzdy(Context paramContext)
  {
    this.zzxt = bool;
    this.zzxu = false;
    Context localContext = paramContext.getApplicationContext();
    if (localContext != null);
    while (true)
    {
      this.zzxl = bool;
      if (this.zzxl)
        paramContext = localContext;
      this.zzlj = paramContext;
      this.zzxr = new HashMap();
      return;
      bool = false;
    }
  }

  // ERROR //
  public static zzdy zza(Context paramContext, String paramString1, String paramString2, boolean paramBoolean)
  {
    // Byte code:
    //   0: iconst_1
    //   1: istore 4
    //   3: new 2	com/google/android/gms/internal/ads/zzdy
    //   6: dup
    //   7: aload_0
    //   8: invokespecial 102	com/google/android/gms/internal/ads/zzdy:<init>	(Landroid/content/Context;)V
    //   11: astore 5
    //   13: aload 5
    //   15: new 104	com/google/android/gms/internal/ads/zzdz
    //   18: dup
    //   19: invokespecial 105	com/google/android/gms/internal/ads/zzdz:<init>	()V
    //   22: invokestatic 111	java/util/concurrent/Executors:newCachedThreadPool	(Ljava/util/concurrent/ThreadFactory;)Ljava/util/concurrent/ExecutorService;
    //   25: putfield 113	com/google/android/gms/internal/ads/zzdy:zzxf	Ljava/util/concurrent/ExecutorService;
    //   28: aload 5
    //   30: iload_3
    //   31: putfield 54	com/google/android/gms/internal/ads/zzdy:zzwf	Z
    //   34: iload_3
    //   35: ifeq +27 -> 62
    //   38: aload 5
    //   40: aload 5
    //   42: getfield 113	com/google/android/gms/internal/ads/zzdy:zzxf	Ljava/util/concurrent/ExecutorService;
    //   45: new 115	com/google/android/gms/internal/ads/zzea
    //   48: dup
    //   49: aload 5
    //   51: invokespecial 118	com/google/android/gms/internal/ads/zzea:<init>	(Lcom/google/android/gms/internal/ads/zzdy;)V
    //   54: invokeinterface 124 2 0
    //   59: putfield 56	com/google/android/gms/internal/ads/zzdy:zzxk	Ljava/util/concurrent/Future;
    //   62: aload 5
    //   64: getfield 113	com/google/android/gms/internal/ads/zzdy:zzxf	Ljava/util/concurrent/ExecutorService;
    //   67: new 126	com/google/android/gms/internal/ads/zzec
    //   70: dup
    //   71: aload 5
    //   73: invokespecial 127	com/google/android/gms/internal/ads/zzec:<init>	(Lcom/google/android/gms/internal/ads/zzdy;)V
    //   76: invokeinterface 131 2 0
    //   81: invokestatic 137	com/google/android/gms/common/GoogleApiAvailabilityLight:getInstance	()Lcom/google/android/gms/common/GoogleApiAvailabilityLight;
    //   84: astore 24
    //   86: aload 24
    //   88: aload 5
    //   90: getfield 80	com/google/android/gms/internal/ads/zzdy:zzlj	Landroid/content/Context;
    //   93: invokevirtual 141	com/google/android/gms/common/GoogleApiAvailabilityLight:getApkVersion	(Landroid/content/Context;)I
    //   96: ifle +509 -> 605
    //   99: iload 4
    //   101: istore 25
    //   103: aload 5
    //   105: iload 25
    //   107: putfield 62	com/google/android/gms/internal/ads/zzdy:zzxp	Z
    //   110: aload 24
    //   112: aload 5
    //   114: getfield 80	com/google/android/gms/internal/ads/zzdy:zzlj	Landroid/content/Context;
    //   117: invokevirtual 144	com/google/android/gms/common/GoogleApiAvailabilityLight:isGooglePlayServicesAvailable	(Landroid/content/Context;)I
    //   120: ifne +491 -> 611
    //   123: aload 5
    //   125: iload 4
    //   127: putfield 64	com/google/android/gms/internal/ads/zzdy:zzxq	Z
    //   130: aload 5
    //   132: iconst_0
    //   133: iconst_1
    //   134: invokevirtual 147	com/google/android/gms/internal/ads/zzdy:zza	(IZ)V
    //   137: invokestatic 153	com/google/android/gms/internal/ads/zzef:isMainThread	()Z
    //   140: ifeq +35 -> 175
    //   143: getstatic 159	com/google/android/gms/internal/ads/zzact:zzcro	Lcom/google/android/gms/internal/ads/zzaci;
    //   146: astore 23
    //   148: invokestatic 165	com/google/android/gms/internal/ads/zzyr:zzpe	()Lcom/google/android/gms/internal/ads/zzacq;
    //   151: aload 23
    //   153: invokevirtual 171	com/google/android/gms/internal/ads/zzacq:zzd	(Lcom/google/android/gms/internal/ads/zzaci;)Ljava/lang/Object;
    //   156: checkcast 173	java/lang/Boolean
    //   159: invokevirtual 176	java/lang/Boolean:booleanValue	()Z
    //   162: ifeq +13 -> 175
    //   165: new 178	java/lang/IllegalStateException
    //   168: dup
    //   169: ldc 180
    //   171: invokespecial 183	java/lang/IllegalStateException:<init>	(Ljava/lang/String;)V
    //   174: athrow
    //   175: aload 5
    //   177: new 185	com/google/android/gms/internal/ads/zzdj
    //   180: dup
    //   181: aconst_null
    //   182: invokespecial 188	com/google/android/gms/internal/ads/zzdj:<init>	(Ljava/security/SecureRandom;)V
    //   185: putfield 190	com/google/android/gms/internal/ads/zzdy:zzxh	Lcom/google/android/gms/internal/ads/zzdj;
    //   188: aload 5
    //   190: aload 5
    //   192: getfield 190	com/google/android/gms/internal/ads/zzdy:zzxh	Lcom/google/android/gms/internal/ads/zzdj;
    //   195: aload_1
    //   196: invokevirtual 194	com/google/android/gms/internal/ads/zzdj:zzan	(Ljava/lang/String;)[B
    //   199: putfield 196	com/google/android/gms/internal/ads/zzdy:zzxi	[B
    //   202: aload 5
    //   204: getfield 80	com/google/android/gms/internal/ads/zzdy:zzlj	Landroid/content/Context;
    //   207: invokevirtual 200	android/content/Context:getCacheDir	()Ljava/io/File;
    //   210: astore 13
    //   212: aload 13
    //   214: ifnonnull +53 -> 267
    //   217: aload 5
    //   219: getfield 80	com/google/android/gms/internal/ads/zzdy:zzlj	Landroid/content/Context;
    //   222: ldc 202
    //   224: iconst_0
    //   225: invokevirtual 206	android/content/Context:getDir	(Ljava/lang/String;I)Ljava/io/File;
    //   228: astore 13
    //   230: aload 13
    //   232: ifnonnull +35 -> 267
    //   235: new 90	com/google/android/gms/internal/ads/zzdv
    //   238: dup
    //   239: invokespecial 207	com/google/android/gms/internal/ads/zzdv:<init>	()V
    //   242: athrow
    //   243: astore 12
    //   245: new 90	com/google/android/gms/internal/ads/zzdv
    //   248: dup
    //   249: aload 12
    //   251: invokespecial 210	com/google/android/gms/internal/ads/zzdv:<init>	(Ljava/lang/Throwable;)V
    //   254: athrow
    //   255: astore 8
    //   257: new 90	com/google/android/gms/internal/ads/zzdv
    //   260: dup
    //   261: aload 8
    //   263: invokespecial 210	com/google/android/gms/internal/ads/zzdv:<init>	(Ljava/lang/Throwable;)V
    //   266: athrow
    //   267: aload 13
    //   269: astore 14
    //   271: new 212	java/io/File
    //   274: dup
    //   275: ldc 214
    //   277: iconst_2
    //   278: anewarray 4	java/lang/Object
    //   281: dup
    //   282: iconst_0
    //   283: aload 14
    //   285: aastore
    //   286: dup
    //   287: iconst_1
    //   288: ldc 216
    //   290: aastore
    //   291: invokestatic 222	java/lang/String:format	(Ljava/lang/String;[Ljava/lang/Object;)Ljava/lang/String;
    //   294: invokespecial 223	java/io/File:<init>	(Ljava/lang/String;)V
    //   297: astore 15
    //   299: aload 15
    //   301: invokevirtual 226	java/io/File:exists	()Z
    //   304: ifne +52 -> 356
    //   307: aload 5
    //   309: getfield 190	com/google/android/gms/internal/ads/zzdy:zzxh	Lcom/google/android/gms/internal/ads/zzdj;
    //   312: aload 5
    //   314: getfield 196	com/google/android/gms/internal/ads/zzdy:zzxi	[B
    //   317: aload_2
    //   318: invokevirtual 229	com/google/android/gms/internal/ads/zzdj:zza	([BLjava/lang/String;)[B
    //   321: astore 20
    //   323: aload 15
    //   325: invokevirtual 232	java/io/File:createNewFile	()Z
    //   328: pop
    //   329: new 234	java/io/FileOutputStream
    //   332: dup
    //   333: aload 15
    //   335: invokespecial 237	java/io/FileOutputStream:<init>	(Ljava/io/File;)V
    //   338: astore 22
    //   340: aload 22
    //   342: aload 20
    //   344: iconst_0
    //   345: aload 20
    //   347: arraylength
    //   348: invokevirtual 241	java/io/FileOutputStream:write	([BII)V
    //   351: aload 22
    //   353: invokevirtual 244	java/io/FileOutputStream:close	()V
    //   356: aload 5
    //   358: aload 14
    //   360: ldc 216
    //   362: invokespecial 248	com/google/android/gms/internal/ads/zzdy:zzb	(Ljava/io/File;Ljava/lang/String;)Z
    //   365: pop
    //   366: aload 5
    //   368: new 250	dalvik/system/DexClassLoader
    //   371: dup
    //   372: aload 15
    //   374: invokevirtual 253	java/io/File:getAbsolutePath	()Ljava/lang/String;
    //   377: aload 14
    //   379: invokevirtual 253	java/io/File:getAbsolutePath	()Ljava/lang/String;
    //   382: aconst_null
    //   383: aload 5
    //   385: getfield 80	com/google/android/gms/internal/ads/zzdy:zzlj	Landroid/content/Context;
    //   388: invokevirtual 257	android/content/Context:getClassLoader	()Ljava/lang/ClassLoader;
    //   391: invokespecial 260	dalvik/system/DexClassLoader:<init>	(Ljava/lang/String;Ljava/lang/String;Ljava/lang/String;Ljava/lang/ClassLoader;)V
    //   394: putfield 262	com/google/android/gms/internal/ads/zzdy:zzxg	Ldalvik/system/DexClassLoader;
    //   397: aload 15
    //   399: invokestatic 264	com/google/android/gms/internal/ads/zzdy:zzb	(Ljava/io/File;)V
    //   402: aload 5
    //   404: aload 14
    //   406: ldc 216
    //   408: invokespecial 267	com/google/android/gms/internal/ads/zzdy:zza	(Ljava/io/File;Ljava/lang/String;)V
    //   411: ldc_w 269
    //   414: iconst_2
    //   415: anewarray 4	java/lang/Object
    //   418: dup
    //   419: iconst_0
    //   420: aload 14
    //   422: aastore
    //   423: dup
    //   424: iconst_1
    //   425: ldc 216
    //   427: aastore
    //   428: invokestatic 222	java/lang/String:format	(Ljava/lang/String;[Ljava/lang/Object;)Ljava/lang/String;
    //   431: invokestatic 272	com/google/android/gms/internal/ads/zzdy:zzao	(Ljava/lang/String;)V
    //   434: aload 5
    //   436: getfield 70	com/google/android/gms/internal/ads/zzdy:zzxu	Z
    //   439: ifne +55 -> 494
    //   442: new 274	android/content/IntentFilter
    //   445: dup
    //   446: invokespecial 275	android/content/IntentFilter:<init>	()V
    //   449: astore 18
    //   451: aload 18
    //   453: ldc_w 277
    //   456: invokevirtual 280	android/content/IntentFilter:addAction	(Ljava/lang/String;)V
    //   459: aload 18
    //   461: ldc_w 282
    //   464: invokevirtual 280	android/content/IntentFilter:addAction	(Ljava/lang/String;)V
    //   467: aload 5
    //   469: getfield 80	com/google/android/gms/internal/ads/zzdy:zzlj	Landroid/content/Context;
    //   472: new 284	com/google/android/gms/internal/ads/zzdy$zza
    //   475: dup
    //   476: aload 5
    //   478: aconst_null
    //   479: invokespecial 287	com/google/android/gms/internal/ads/zzdy$zza:<init>	(Lcom/google/android/gms/internal/ads/zzdy;Lcom/google/android/gms/internal/ads/zzdz;)V
    //   482: aload 18
    //   484: invokevirtual 291	android/content/Context:registerReceiver	(Landroid/content/BroadcastReceiver;Landroid/content/IntentFilter;)Landroid/content/Intent;
    //   487: pop
    //   488: aload 5
    //   490: iconst_1
    //   491: putfield 70	com/google/android/gms/internal/ads/zzdy:zzxu	Z
    //   494: aload 5
    //   496: new 293	com/google/android/gms/internal/ads/zzda
    //   499: dup
    //   500: aload 5
    //   502: invokespecial 294	com/google/android/gms/internal/ads/zzda:<init>	(Lcom/google/android/gms/internal/ads/zzdy;)V
    //   505: putfield 296	com/google/android/gms/internal/ads/zzdy:zzxo	Lcom/google/android/gms/internal/ads/zzda;
    //   508: aload 5
    //   510: iconst_1
    //   511: putfield 66	com/google/android/gms/internal/ads/zzdy:zzxs	Z
    //   514: aload 5
    //   516: areturn
    //   517: astore 17
    //   519: aload 15
    //   521: invokestatic 264	com/google/android/gms/internal/ads/zzdy:zzb	(Ljava/io/File;)V
    //   524: aload 5
    //   526: aload 14
    //   528: ldc 216
    //   530: invokespecial 267	com/google/android/gms/internal/ads/zzdy:zza	(Ljava/io/File;Ljava/lang/String;)V
    //   533: ldc_w 269
    //   536: iconst_2
    //   537: anewarray 4	java/lang/Object
    //   540: dup
    //   541: iconst_0
    //   542: aload 14
    //   544: aastore
    //   545: dup
    //   546: iconst_1
    //   547: ldc 216
    //   549: aastore
    //   550: invokestatic 222	java/lang/String:format	(Ljava/lang/String;[Ljava/lang/Object;)Ljava/lang/String;
    //   553: invokestatic 272	com/google/android/gms/internal/ads/zzdy:zzao	(Ljava/lang/String;)V
    //   556: aload 17
    //   558: athrow
    //   559: astore 11
    //   561: new 90	com/google/android/gms/internal/ads/zzdv
    //   564: dup
    //   565: aload 11
    //   567: invokespecial 210	com/google/android/gms/internal/ads/zzdv:<init>	(Ljava/lang/Throwable;)V
    //   570: athrow
    //   571: astore 10
    //   573: new 90	com/google/android/gms/internal/ads/zzdv
    //   576: dup
    //   577: aload 10
    //   579: invokespecial 210	com/google/android/gms/internal/ads/zzdv:<init>	(Ljava/lang/Throwable;)V
    //   582: athrow
    //   583: astore 9
    //   585: new 90	com/google/android/gms/internal/ads/zzdv
    //   588: dup
    //   589: aload 9
    //   591: invokespecial 210	com/google/android/gms/internal/ads/zzdv:<init>	(Ljava/lang/Throwable;)V
    //   594: athrow
    //   595: astore 7
    //   597: goto -467 -> 130
    //   600: astore 6
    //   602: aload 5
    //   604: areturn
    //   605: iconst_0
    //   606: istore 25
    //   608: goto -505 -> 103
    //   611: iconst_0
    //   612: istore 4
    //   614: goto -491 -> 123
    //
    // Exception table:
    //   from	to	target	type
    //   202	212	243	java/io/FileNotFoundException
    //   217	230	243	java/io/FileNotFoundException
    //   235	243	243	java/io/FileNotFoundException
    //   271	356	243	java/io/FileNotFoundException
    //   356	366	243	java/io/FileNotFoundException
    //   397	434	243	java/io/FileNotFoundException
    //   519	559	243	java/io/FileNotFoundException
    //   188	202	255	com/google/android/gms/internal/ads/zzdk
    //   366	397	517	finally
    //   202	212	559	java/io/IOException
    //   217	230	559	java/io/IOException
    //   235	243	559	java/io/IOException
    //   271	356	559	java/io/IOException
    //   356	366	559	java/io/IOException
    //   397	434	559	java/io/IOException
    //   519	559	559	java/io/IOException
    //   202	212	571	com/google/android/gms/internal/ads/zzdk
    //   217	230	571	com/google/android/gms/internal/ads/zzdk
    //   235	243	571	com/google/android/gms/internal/ads/zzdk
    //   271	356	571	com/google/android/gms/internal/ads/zzdk
    //   356	366	571	com/google/android/gms/internal/ads/zzdk
    //   397	434	571	com/google/android/gms/internal/ads/zzdk
    //   519	559	571	com/google/android/gms/internal/ads/zzdk
    //   202	212	583	java/lang/NullPointerException
    //   217	230	583	java/lang/NullPointerException
    //   235	243	583	java/lang/NullPointerException
    //   271	356	583	java/lang/NullPointerException
    //   356	366	583	java/lang/NullPointerException
    //   397	434	583	java/lang/NullPointerException
    //   519	559	583	java/lang/NullPointerException
    //   81	99	595	java/lang/Throwable
    //   103	123	595	java/lang/Throwable
    //   123	130	595	java/lang/Throwable
    //   13	34	600	com/google/android/gms/internal/ads/zzdv
    //   38	62	600	com/google/android/gms/internal/ads/zzdv
    //   62	81	600	com/google/android/gms/internal/ads/zzdv
    //   81	99	600	com/google/android/gms/internal/ads/zzdv
    //   103	123	600	com/google/android/gms/internal/ads/zzdv
    //   123	130	600	com/google/android/gms/internal/ads/zzdv
    //   130	175	600	com/google/android/gms/internal/ads/zzdv
    //   175	188	600	com/google/android/gms/internal/ads/zzdv
    //   188	202	600	com/google/android/gms/internal/ads/zzdv
    //   202	212	600	com/google/android/gms/internal/ads/zzdv
    //   217	230	600	com/google/android/gms/internal/ads/zzdv
    //   235	243	600	com/google/android/gms/internal/ads/zzdv
    //   245	255	600	com/google/android/gms/internal/ads/zzdv
    //   257	267	600	com/google/android/gms/internal/ads/zzdv
    //   271	356	600	com/google/android/gms/internal/ads/zzdv
    //   356	366	600	com/google/android/gms/internal/ads/zzdv
    //   397	434	600	com/google/android/gms/internal/ads/zzdv
    //   434	494	600	com/google/android/gms/internal/ads/zzdv
    //   494	514	600	com/google/android/gms/internal/ads/zzdv
    //   519	559	600	com/google/android/gms/internal/ads/zzdv
    //   561	571	600	com/google/android/gms/internal/ads/zzdv
    //   573	583	600	com/google/android/gms/internal/ads/zzdv
    //   585	595	600	com/google/android/gms/internal/ads/zzdv
  }

  // ERROR //
  private final void zza(File paramFile, String paramString)
  {
    // Byte code:
    //   0: aconst_null
    //   1: astore_3
    //   2: new 212	java/io/File
    //   5: dup
    //   6: ldc_w 303
    //   9: iconst_2
    //   10: anewarray 4	java/lang/Object
    //   13: dup
    //   14: iconst_0
    //   15: aload_1
    //   16: aastore
    //   17: dup
    //   18: iconst_1
    //   19: aload_2
    //   20: aastore
    //   21: invokestatic 222	java/lang/String:format	(Ljava/lang/String;[Ljava/lang/Object;)Ljava/lang/String;
    //   24: invokespecial 223	java/io/File:<init>	(Ljava/lang/String;)V
    //   27: astore 4
    //   29: aload 4
    //   31: invokevirtual 226	java/io/File:exists	()Z
    //   34: ifeq +4 -> 38
    //   37: return
    //   38: new 212	java/io/File
    //   41: dup
    //   42: ldc_w 269
    //   45: iconst_2
    //   46: anewarray 4	java/lang/Object
    //   49: dup
    //   50: iconst_0
    //   51: aload_1
    //   52: aastore
    //   53: dup
    //   54: iconst_1
    //   55: aload_2
    //   56: aastore
    //   57: invokestatic 222	java/lang/String:format	(Ljava/lang/String;[Ljava/lang/Object;)Ljava/lang/String;
    //   60: invokespecial 223	java/io/File:<init>	(Ljava/lang/String;)V
    //   63: astore 5
    //   65: aload 5
    //   67: invokevirtual 226	java/io/File:exists	()Z
    //   70: ifeq -33 -> 37
    //   73: aload 5
    //   75: invokevirtual 307	java/io/File:length	()J
    //   78: lstore 6
    //   80: lload 6
    //   82: lconst_0
    //   83: lcmp
    //   84: ifle -47 -> 37
    //   87: lload 6
    //   89: l2i
    //   90: newarray byte
    //   92: astore 8
    //   94: new 309	java/io/FileInputStream
    //   97: dup
    //   98: aload 5
    //   100: invokespecial 310	java/io/FileInputStream:<init>	(Ljava/io/File;)V
    //   103: astore 9
    //   105: aload 9
    //   107: aload 8
    //   109: invokevirtual 314	java/io/FileInputStream:read	([B)I
    //   112: istore 21
    //   114: iload 21
    //   116: ifgt +14 -> 130
    //   119: aload 9
    //   121: invokevirtual 315	java/io/FileInputStream:close	()V
    //   124: aload 5
    //   126: invokestatic 264	com/google/android/gms/internal/ads/zzdy:zzb	(Ljava/io/File;)V
    //   129: return
    //   130: getstatic 321	java/lang/System:out	Ljava/io/PrintStream;
    //   133: ldc_w 323
    //   136: invokevirtual 328	java/io/PrintStream:print	(Ljava/lang/String;)V
    //   139: getstatic 321	java/lang/System:out	Ljava/io/PrintStream;
    //   142: ldc_w 323
    //   145: invokevirtual 328	java/io/PrintStream:print	(Ljava/lang/String;)V
    //   148: getstatic 321	java/lang/System:out	Ljava/io/PrintStream;
    //   151: ldc_w 323
    //   154: invokevirtual 328	java/io/PrintStream:print	(Ljava/lang/String;)V
    //   157: invokestatic 334	com/google/android/gms/internal/ads/zzbp$zzd:zzbc	()Lcom/google/android/gms/internal/ads/zzbp$zzd$zza;
    //   160: getstatic 339	android/os/Build$VERSION:SDK	Ljava/lang/String;
    //   163: invokevirtual 343	java/lang/String:getBytes	()[B
    //   166: invokestatic 349	com/google/android/gms/internal/ads/zzdmq:zzz	([B)Lcom/google/android/gms/internal/ads/zzdmq;
    //   169: invokevirtual 355	com/google/android/gms/internal/ads/zzbp$zzd$zza:zzl	(Lcom/google/android/gms/internal/ads/zzdmq;)Lcom/google/android/gms/internal/ads/zzbp$zzd$zza;
    //   172: aload_2
    //   173: invokevirtual 343	java/lang/String:getBytes	()[B
    //   176: invokestatic 349	com/google/android/gms/internal/ads/zzdmq:zzz	([B)Lcom/google/android/gms/internal/ads/zzdmq;
    //   179: invokevirtual 358	com/google/android/gms/internal/ads/zzbp$zzd$zza:zzk	(Lcom/google/android/gms/internal/ads/zzdmq;)Lcom/google/android/gms/internal/ads/zzbp$zzd$zza;
    //   182: astore 22
    //   184: aload_0
    //   185: getfield 190	com/google/android/gms/internal/ads/zzdy:zzxh	Lcom/google/android/gms/internal/ads/zzdj;
    //   188: aload_0
    //   189: getfield 196	com/google/android/gms/internal/ads/zzdy:zzxi	[B
    //   192: aload 8
    //   194: invokevirtual 361	com/google/android/gms/internal/ads/zzdj:zzb	([B[B)Ljava/lang/String;
    //   197: invokevirtual 343	java/lang/String:getBytes	()[B
    //   200: astore 23
    //   202: aload 22
    //   204: aload 23
    //   206: invokestatic 349	com/google/android/gms/internal/ads/zzdmq:zzz	([B)Lcom/google/android/gms/internal/ads/zzdmq;
    //   209: invokevirtual 364	com/google/android/gms/internal/ads/zzbp$zzd$zza:zzi	(Lcom/google/android/gms/internal/ads/zzdmq;)Lcom/google/android/gms/internal/ads/zzbp$zzd$zza;
    //   212: aload 23
    //   214: invokestatic 369	com/google/android/gms/internal/ads/zzci:zzb	([B)[B
    //   217: invokestatic 349	com/google/android/gms/internal/ads/zzdmq:zzz	([B)Lcom/google/android/gms/internal/ads/zzdmq;
    //   220: invokevirtual 372	com/google/android/gms/internal/ads/zzbp$zzd$zza:zzj	(Lcom/google/android/gms/internal/ads/zzdmq;)Lcom/google/android/gms/internal/ads/zzbp$zzd$zza;
    //   223: pop
    //   224: aload 4
    //   226: invokevirtual 232	java/io/File:createNewFile	()Z
    //   229: pop
    //   230: new 234	java/io/FileOutputStream
    //   233: dup
    //   234: aload 4
    //   236: invokespecial 237	java/io/FileOutputStream:<init>	(Ljava/io/File;)V
    //   239: astore 18
    //   241: aload 22
    //   243: invokevirtual 378	com/google/android/gms/internal/ads/zzdoa$zza:zzaya	()Lcom/google/android/gms/internal/ads/zzdpj;
    //   246: checkcast 380	com/google/android/gms/internal/ads/zzdoa
    //   249: checkcast 330	com/google/android/gms/internal/ads/zzbp$zzd
    //   252: invokevirtual 385	com/google/android/gms/internal/ads/zzdmh:toByteArray	()[B
    //   255: astore 29
    //   257: aload 18
    //   259: aload 29
    //   261: iconst_0
    //   262: aload 29
    //   264: arraylength
    //   265: invokevirtual 241	java/io/FileOutputStream:write	([BII)V
    //   268: aload 18
    //   270: invokevirtual 244	java/io/FileOutputStream:close	()V
    //   273: aload 9
    //   275: invokevirtual 315	java/io/FileInputStream:close	()V
    //   278: aload 18
    //   280: invokevirtual 244	java/io/FileOutputStream:close	()V
    //   283: aload 5
    //   285: invokestatic 264	com/google/android/gms/internal/ads/zzdy:zzb	(Ljava/io/File;)V
    //   288: return
    //   289: astore 36
    //   291: aconst_null
    //   292: astore 11
    //   294: aload 11
    //   296: ifnull +8 -> 304
    //   299: aload 11
    //   301: invokevirtual 315	java/io/FileInputStream:close	()V
    //   304: aload_3
    //   305: ifnull +7 -> 312
    //   308: aload_3
    //   309: invokevirtual 244	java/io/FileOutputStream:close	()V
    //   312: aload 5
    //   314: invokestatic 264	com/google/android/gms/internal/ads/zzdy:zzb	(Ljava/io/File;)V
    //   317: return
    //   318: astore 35
    //   320: aconst_null
    //   321: astore 9
    //   323: aload 35
    //   325: astore 17
    //   327: aconst_null
    //   328: astore 18
    //   330: aload 9
    //   332: ifnull +8 -> 340
    //   335: aload 9
    //   337: invokevirtual 315	java/io/FileInputStream:close	()V
    //   340: aload 18
    //   342: ifnull +8 -> 350
    //   345: aload 18
    //   347: invokevirtual 244	java/io/FileOutputStream:close	()V
    //   350: aload 5
    //   352: invokestatic 264	com/google/android/gms/internal/ads/zzdy:zzb	(Ljava/io/File;)V
    //   355: aload 17
    //   357: athrow
    //   358: astore 32
    //   360: goto -236 -> 124
    //   363: astore 30
    //   365: goto -87 -> 278
    //   368: astore 31
    //   370: goto -87 -> 283
    //   373: astore 13
    //   375: goto -71 -> 304
    //   378: astore 12
    //   380: goto -68 -> 312
    //   383: astore 20
    //   385: goto -45 -> 340
    //   388: astore 19
    //   390: goto -40 -> 350
    //   393: astore 16
    //   395: aload 16
    //   397: astore 17
    //   399: aconst_null
    //   400: astore 18
    //   402: goto -72 -> 330
    //   405: astore 17
    //   407: goto -77 -> 330
    //   410: astore 15
    //   412: aload 9
    //   414: astore 11
    //   416: aconst_null
    //   417: astore_3
    //   418: goto -124 -> 294
    //   421: astore 28
    //   423: aload 18
    //   425: astore_3
    //   426: aload 9
    //   428: astore 11
    //   430: goto -136 -> 294
    //   433: astore 34
    //   435: aconst_null
    //   436: astore_3
    //   437: aconst_null
    //   438: astore 11
    //   440: goto -146 -> 294
    //   443: astore 14
    //   445: aload 9
    //   447: astore 11
    //   449: aconst_null
    //   450: astore_3
    //   451: goto -157 -> 294
    //   454: astore 27
    //   456: aload 18
    //   458: astore_3
    //   459: aload 9
    //   461: astore 11
    //   463: goto -169 -> 294
    //   466: astore 33
    //   468: aconst_null
    //   469: astore_3
    //   470: aconst_null
    //   471: astore 11
    //   473: goto -179 -> 294
    //   476: astore 10
    //   478: aload 9
    //   480: astore 11
    //   482: aconst_null
    //   483: astore_3
    //   484: goto -190 -> 294
    //   487: astore 26
    //   489: aload 18
    //   491: astore_3
    //   492: aload 9
    //   494: astore 11
    //   496: goto -202 -> 294
    //
    // Exception table:
    //   from	to	target	type
    //   94	105	289	com/google/android/gms/internal/ads/zzdk
    //   94	105	318	finally
    //   119	124	358	java/io/IOException
    //   273	278	363	java/io/IOException
    //   278	283	368	java/io/IOException
    //   299	304	373	java/io/IOException
    //   308	312	378	java/io/IOException
    //   335	340	383	java/io/IOException
    //   345	350	388	java/io/IOException
    //   105	114	393	finally
    //   130	241	393	finally
    //   241	273	405	finally
    //   105	114	410	com/google/android/gms/internal/ads/zzdk
    //   130	241	410	com/google/android/gms/internal/ads/zzdk
    //   241	273	421	com/google/android/gms/internal/ads/zzdk
    //   94	105	433	java/security/NoSuchAlgorithmException
    //   105	114	443	java/security/NoSuchAlgorithmException
    //   130	241	443	java/security/NoSuchAlgorithmException
    //   241	273	454	java/security/NoSuchAlgorithmException
    //   94	105	466	java/io/IOException
    //   105	114	476	java/io/IOException
    //   130	241	476	java/io/IOException
    //   241	273	487	java/io/IOException
  }

  private static boolean zza(int paramInt, zzbp.zza paramzza)
  {
    if (paramInt < 4)
    {
      if (paramzza == null);
      while ((!paramzza.zzai()) || (paramzza.zzae().equals("0000000000000000000000000000000000000000000000000000000000000000")) || (!paramzza.zzak()) || (!paramzza.zzal().zzbe()) || (paramzza.zzal().zzbf() == -2L))
        return true;
    }
    return false;
  }

  private static void zzao(String paramString)
  {
    zzb(new File(paramString));
  }

  private static void zzb(File paramFile)
  {
    if (!paramFile.exists())
    {
      String str = TAG;
      Object[] arrayOfObject = new Object[1];
      arrayOfObject[0] = paramFile.getAbsolutePath();
      Log.d(str, String.format("File %s not found. No need for deletion", arrayOfObject));
      return;
    }
    paramFile.delete();
  }

  // ERROR //
  private final boolean zzb(File paramFile, String paramString)
  {
    // Byte code:
    //   0: aconst_null
    //   1: astore_3
    //   2: new 212	java/io/File
    //   5: dup
    //   6: ldc_w 303
    //   9: iconst_2
    //   10: anewarray 4	java/lang/Object
    //   13: dup
    //   14: iconst_0
    //   15: aload_1
    //   16: aastore
    //   17: dup
    //   18: iconst_1
    //   19: aload_2
    //   20: aastore
    //   21: invokestatic 222	java/lang/String:format	(Ljava/lang/String;[Ljava/lang/Object;)Ljava/lang/String;
    //   24: invokespecial 223	java/io/File:<init>	(Ljava/lang/String;)V
    //   27: astore 4
    //   29: aload 4
    //   31: invokevirtual 226	java/io/File:exists	()Z
    //   34: ifne +5 -> 39
    //   37: iconst_0
    //   38: ireturn
    //   39: new 212	java/io/File
    //   42: dup
    //   43: ldc_w 269
    //   46: iconst_2
    //   47: anewarray 4	java/lang/Object
    //   50: dup
    //   51: iconst_0
    //   52: aload_1
    //   53: aastore
    //   54: dup
    //   55: iconst_1
    //   56: aload_2
    //   57: aastore
    //   58: invokestatic 222	java/lang/String:format	(Ljava/lang/String;[Ljava/lang/Object;)Ljava/lang/String;
    //   61: invokespecial 223	java/io/File:<init>	(Ljava/lang/String;)V
    //   64: astore 5
    //   66: aload 5
    //   68: invokevirtual 226	java/io/File:exists	()Z
    //   71: ifeq +5 -> 76
    //   74: iconst_0
    //   75: ireturn
    //   76: aload 4
    //   78: invokevirtual 307	java/io/File:length	()J
    //   81: lstore 16
    //   83: lload 16
    //   85: lconst_0
    //   86: lcmp
    //   87: ifgt +10 -> 97
    //   90: aload 4
    //   92: invokestatic 264	com/google/android/gms/internal/ads/zzdy:zzb	(Ljava/io/File;)V
    //   95: iconst_0
    //   96: ireturn
    //   97: lload 16
    //   99: l2i
    //   100: newarray byte
    //   102: astore 18
    //   104: new 309	java/io/FileInputStream
    //   107: dup
    //   108: aload 4
    //   110: invokespecial 310	java/io/FileInputStream:<init>	(Ljava/io/File;)V
    //   113: astore 12
    //   115: aload 12
    //   117: aload 18
    //   119: invokevirtual 314	java/io/FileInputStream:read	([B)I
    //   122: ifgt +25 -> 147
    //   125: getstatic 46	com/google/android/gms/internal/ads/zzdy:TAG	Ljava/lang/String;
    //   128: ldc_w 433
    //   131: invokestatic 426	android/util/Log:d	(Ljava/lang/String;Ljava/lang/String;)I
    //   134: pop
    //   135: aload 4
    //   137: invokestatic 264	com/google/android/gms/internal/ads/zzdy:zzb	(Ljava/io/File;)V
    //   140: aload 12
    //   142: invokevirtual 315	java/io/FileInputStream:close	()V
    //   145: iconst_0
    //   146: ireturn
    //   147: aload 18
    //   149: invokestatic 439	com/google/android/gms/internal/ads/zzdnn:zzaxe	()Lcom/google/android/gms/internal/ads/zzdnn;
    //   152: invokestatic 443	com/google/android/gms/internal/ads/zzbp$zzd:zzc	([BLcom/google/android/gms/internal/ads/zzdnn;)Lcom/google/android/gms/internal/ads/zzbp$zzd;
    //   155: astore 22
    //   157: aload_2
    //   158: new 218	java/lang/String
    //   161: dup
    //   162: aload 22
    //   164: invokevirtual 447	com/google/android/gms/internal/ads/zzbp$zzd:zzba	()Lcom/google/android/gms/internal/ads/zzdmq;
    //   167: invokevirtual 448	com/google/android/gms/internal/ads/zzdmq:toByteArray	()[B
    //   170: invokespecial 451	java/lang/String:<init>	([B)V
    //   173: invokevirtual 400	java/lang/String:equals	(Ljava/lang/Object;)Z
    //   176: ifeq +48 -> 224
    //   179: aload 22
    //   181: invokevirtual 454	com/google/android/gms/internal/ads/zzbp$zzd:zzaz	()Lcom/google/android/gms/internal/ads/zzdmq;
    //   184: invokevirtual 448	com/google/android/gms/internal/ads/zzdmq:toByteArray	()[B
    //   187: aload 22
    //   189: invokevirtual 457	com/google/android/gms/internal/ads/zzbp$zzd:zzay	()Lcom/google/android/gms/internal/ads/zzdmq;
    //   192: invokevirtual 448	com/google/android/gms/internal/ads/zzdmq:toByteArray	()[B
    //   195: invokestatic 369	com/google/android/gms/internal/ads/zzci:zzb	([B)[B
    //   198: invokestatic 462	java/util/Arrays:equals	([B[B)Z
    //   201: ifeq +23 -> 224
    //   204: aload 22
    //   206: invokevirtual 465	com/google/android/gms/internal/ads/zzbp$zzd:zzbb	()Lcom/google/android/gms/internal/ads/zzdmq;
    //   209: invokevirtual 448	com/google/android/gms/internal/ads/zzdmq:toByteArray	()[B
    //   212: getstatic 339	android/os/Build$VERSION:SDK	Ljava/lang/String;
    //   215: invokevirtual 343	java/lang/String:getBytes	()[B
    //   218: invokestatic 462	java/util/Arrays:equals	([B[B)Z
    //   221: ifne +15 -> 236
    //   224: aload 4
    //   226: invokestatic 264	com/google/android/gms/internal/ads/zzdy:zzb	(Ljava/io/File;)V
    //   229: aload 12
    //   231: invokevirtual 315	java/io/FileInputStream:close	()V
    //   234: iconst_0
    //   235: ireturn
    //   236: aload_0
    //   237: getfield 190	com/google/android/gms/internal/ads/zzdy:zzxh	Lcom/google/android/gms/internal/ads/zzdj;
    //   240: aload_0
    //   241: getfield 196	com/google/android/gms/internal/ads/zzdy:zzxi	[B
    //   244: new 218	java/lang/String
    //   247: dup
    //   248: aload 22
    //   250: invokevirtual 457	com/google/android/gms/internal/ads/zzbp$zzd:zzay	()Lcom/google/android/gms/internal/ads/zzdmq;
    //   253: invokevirtual 448	com/google/android/gms/internal/ads/zzdmq:toByteArray	()[B
    //   256: invokespecial 451	java/lang/String:<init>	([B)V
    //   259: invokevirtual 229	com/google/android/gms/internal/ads/zzdj:zza	([BLjava/lang/String;)[B
    //   262: astore 24
    //   264: aload 5
    //   266: invokevirtual 232	java/io/File:createNewFile	()Z
    //   269: pop
    //   270: new 234	java/io/FileOutputStream
    //   273: dup
    //   274: aload 5
    //   276: invokespecial 237	java/io/FileOutputStream:<init>	(Ljava/io/File;)V
    //   279: astore 26
    //   281: aload 26
    //   283: aload 24
    //   285: iconst_0
    //   286: aload 24
    //   288: arraylength
    //   289: invokevirtual 241	java/io/FileOutputStream:write	([BII)V
    //   292: aload 12
    //   294: invokevirtual 315	java/io/FileInputStream:close	()V
    //   297: aload 26
    //   299: invokevirtual 244	java/io/FileOutputStream:close	()V
    //   302: iconst_1
    //   303: ireturn
    //   304: astore 31
    //   306: iconst_1
    //   307: ireturn
    //   308: astore 15
    //   310: aconst_null
    //   311: astore 7
    //   313: aload_3
    //   314: ifnull +7 -> 321
    //   317: aload_3
    //   318: invokevirtual 315	java/io/FileInputStream:close	()V
    //   321: aload 7
    //   323: ifnull +8 -> 331
    //   326: aload 7
    //   328: invokevirtual 244	java/io/FileOutputStream:close	()V
    //   331: iconst_0
    //   332: ireturn
    //   333: astore 11
    //   335: aconst_null
    //   336: astore 12
    //   338: aload 12
    //   340: ifnull +8 -> 348
    //   343: aload 12
    //   345: invokevirtual 315	java/io/FileInputStream:close	()V
    //   348: aload_3
    //   349: ifnull +7 -> 356
    //   352: aload_3
    //   353: invokevirtual 244	java/io/FileOutputStream:close	()V
    //   356: aload 11
    //   358: athrow
    //   359: astore 33
    //   361: goto -216 -> 145
    //   364: astore 23
    //   366: goto -132 -> 234
    //   369: astore 30
    //   371: goto -74 -> 297
    //   374: astore 9
    //   376: goto -55 -> 321
    //   379: astore 8
    //   381: goto -50 -> 331
    //   384: astore 14
    //   386: goto -38 -> 348
    //   389: astore 13
    //   391: goto -35 -> 356
    //   394: astore 11
    //   396: aconst_null
    //   397: astore_3
    //   398: goto -60 -> 338
    //   401: astore 11
    //   403: aload 26
    //   405: astore_3
    //   406: goto -68 -> 338
    //   409: astore 21
    //   411: aload 12
    //   413: astore_3
    //   414: aconst_null
    //   415: astore 7
    //   417: goto -104 -> 313
    //   420: astore 29
    //   422: aload 26
    //   424: astore 7
    //   426: aload 12
    //   428: astore_3
    //   429: goto -116 -> 313
    //   432: astore 10
    //   434: aconst_null
    //   435: astore 7
    //   437: aconst_null
    //   438: astore_3
    //   439: goto -126 -> 313
    //   442: astore 20
    //   444: aload 12
    //   446: astore_3
    //   447: aconst_null
    //   448: astore 7
    //   450: goto -137 -> 313
    //   453: astore 28
    //   455: aload 26
    //   457: astore 7
    //   459: aload 12
    //   461: astore_3
    //   462: goto -149 -> 313
    //   465: astore 6
    //   467: aconst_null
    //   468: astore 7
    //   470: aconst_null
    //   471: astore_3
    //   472: goto -159 -> 313
    //   475: astore 19
    //   477: aload 12
    //   479: astore_3
    //   480: aconst_null
    //   481: astore 7
    //   483: goto -170 -> 313
    //   486: astore 27
    //   488: aload 26
    //   490: astore 7
    //   492: aload 12
    //   494: astore_3
    //   495: goto -182 -> 313
    //
    // Exception table:
    //   from	to	target	type
    //   297	302	304	java/io/IOException
    //   76	83	308	com/google/android/gms/internal/ads/zzdk
    //   90	95	308	com/google/android/gms/internal/ads/zzdk
    //   97	115	308	com/google/android/gms/internal/ads/zzdk
    //   76	83	333	finally
    //   90	95	333	finally
    //   97	115	333	finally
    //   140	145	359	java/io/IOException
    //   229	234	364	java/io/IOException
    //   292	297	369	java/io/IOException
    //   317	321	374	java/io/IOException
    //   326	331	379	java/io/IOException
    //   343	348	384	java/io/IOException
    //   352	356	389	java/io/IOException
    //   115	140	394	finally
    //   147	224	394	finally
    //   224	229	394	finally
    //   236	281	394	finally
    //   281	292	401	finally
    //   115	140	409	com/google/android/gms/internal/ads/zzdk
    //   147	224	409	com/google/android/gms/internal/ads/zzdk
    //   224	229	409	com/google/android/gms/internal/ads/zzdk
    //   236	281	409	com/google/android/gms/internal/ads/zzdk
    //   281	292	420	com/google/android/gms/internal/ads/zzdk
    //   76	83	432	java/security/NoSuchAlgorithmException
    //   90	95	432	java/security/NoSuchAlgorithmException
    //   97	115	432	java/security/NoSuchAlgorithmException
    //   115	140	442	java/security/NoSuchAlgorithmException
    //   147	224	442	java/security/NoSuchAlgorithmException
    //   224	229	442	java/security/NoSuchAlgorithmException
    //   236	281	442	java/security/NoSuchAlgorithmException
    //   281	292	453	java/security/NoSuchAlgorithmException
    //   76	83	465	java/io/IOException
    //   90	95	465	java/io/IOException
    //   97	115	465	java/io/IOException
    //   115	140	475	java/io/IOException
    //   147	224	475	java/io/IOException
    //   224	229	475	java/io/IOException
    //   236	281	475	java/io/IOException
    //   281	292	486	java/io/IOException
  }

  private final void zzcr()
  {
    try
    {
      if ((this.zzxj == null) && (this.zzxl))
      {
        AdvertisingIdClient localAdvertisingIdClient = new AdvertisingIdClient(this.zzlj);
        localAdvertisingIdClient.start();
        this.zzxj = localAdvertisingIdClient;
      }
      return;
    }
    catch (GooglePlayServicesRepairableException localGooglePlayServicesRepairableException)
    {
      this.zzxj = null;
      return;
    }
    catch (GooglePlayServicesNotAvailableException localGooglePlayServicesNotAvailableException)
    {
      break label40;
    }
    catch (IOException localIOException)
    {
      label40: break label40;
    }
  }

  private final zzbp.zza zzcs()
  {
    try
    {
      PackageInfo localPackageInfo = this.zzlj.getPackageManager().getPackageInfo(this.zzlj.getPackageName(), 0);
      zzbp.zza localzza = zzdak.zzj(this.zzlj, this.zzlj.getPackageName(), Integer.toString(localPackageInfo.versionCode));
      return localzza;
    }
    catch (Throwable localThrowable)
    {
    }
    return null;
  }

  public final Context getContext()
  {
    return this.zzlj;
  }

  public final boolean isInitialized()
  {
    return this.zzxs;
  }

  final void zza(int paramInt, boolean paramBoolean)
  {
    if (!this.zzxq);
    Future localFuture;
    do
    {
      return;
      localFuture = this.zzxf.submit(new zzeb(this, paramInt, paramBoolean));
    }
    while (paramInt != 0);
    this.zzxn = localFuture;
  }

  public final boolean zza(String paramString1, String paramString2, Class<?>[] paramArrayOfClass)
  {
    if (!this.zzxr.containsKey(new Pair(paramString1, paramString2)))
    {
      this.zzxr.put(new Pair(paramString1, paramString2), new zzfi(this, paramString1, paramString2, paramArrayOfClass));
      return true;
    }
    return false;
  }

  final zzbp.zza zzb(int paramInt, boolean paramBoolean)
  {
    long l;
    if ((paramInt > 0) && (paramBoolean))
      l = paramInt * 1000;
    try
    {
      Thread.sleep(l);
      label19: return zzcs();
    }
    catch (InterruptedException localInterruptedException)
    {
      break label19;
    }
  }

  public final Method zzc(String paramString1, String paramString2)
  {
    zzfi localzzfi = (zzfi)this.zzxr.get(new Pair(paramString1, paramString2));
    if (localzzfi == null)
      return null;
    return localzzfi.zzdc();
  }

  public final int zzcd()
  {
    int i = -2147483648;
    if (this.zzxo != null)
      i = zzda.zzcd();
    return i;
  }

  public final ExecutorService zzch()
  {
    return this.zzxf;
  }

  public final DexClassLoader zzci()
  {
    return this.zzxg;
  }

  public final zzdj zzcj()
  {
    return this.zzxh;
  }

  public final byte[] zzck()
  {
    return this.zzxi;
  }

  public final boolean zzcl()
  {
    return this.zzxp;
  }

  public final zzda zzcm()
  {
    return this.zzxo;
  }

  public final boolean zzcn()
  {
    return this.zzxq;
  }

  public final boolean zzco()
  {
    return this.zzxt;
  }

  public final zzbp.zza zzcp()
  {
    return this.zzxm;
  }

  public final Future zzcq()
  {
    return this.zzxn;
  }

  public final AdvertisingIdClient zzct()
  {
    if (!this.zzwf)
      return null;
    if (this.zzxj != null)
      return this.zzxj;
    if (this.zzxk != null);
    try
    {
      this.zzxk.get(2000L, TimeUnit.MILLISECONDS);
      this.zzxk = null;
      label49: return this.zzxj;
    }
    catch (TimeoutException localTimeoutException)
    {
      while (true)
        this.zzxk.cancel(true);
    }
    catch (ExecutionException localExecutionException)
    {
      break label49;
    }
    catch (InterruptedException localInterruptedException)
    {
      break label49;
    }
  }

  final class zza extends BroadcastReceiver
  {
    private zza()
    {
    }

    public final void onReceive(Context paramContext, Intent paramIntent)
    {
      if ("android.intent.action.USER_PRESENT".equals(paramIntent.getAction()))
        zzdy.zza(zzdy.this, true);
      while (!"android.intent.action.SCREEN_OFF".equals(paramIntent.getAction()))
        return;
      zzdy.zza(zzdy.this, false);
    }
  }
}

/* Location:           E:\Study\Tools\apktool2_2\dex2jar-0.0.9.15\classes_viber_2_dex2jar.jar
 * Qualified Name:     com.google.android.gms.internal.ads.zzdy
 * JD-Core Version:    0.6.2
 */