package com.google.android.gms.internal.ads;

final class zzed
{
  static zzdbp zzya;

  // ERROR //
  static boolean zzb(zzdy paramzzdy)
    throws java.lang.IllegalAccessException, java.lang.reflect.InvocationTargetException
  {
    // Byte code:
    //   0: getstatic 18	com/google/android/gms/internal/ads/zzed:zzya	Lcom/google/android/gms/internal/ads/zzdbp;
    //   3: ifnull +5 -> 8
    //   6: iconst_1
    //   7: ireturn
    //   8: getstatic 24	com/google/android/gms/internal/ads/zzact:zzcrm	Lcom/google/android/gms/internal/ads/zzaci;
    //   11: astore_1
    //   12: invokestatic 30	com/google/android/gms/internal/ads/zzyr:zzpe	()Lcom/google/android/gms/internal/ads/zzacq;
    //   15: aload_1
    //   16: invokevirtual 36	com/google/android/gms/internal/ads/zzacq:zzd	(Lcom/google/android/gms/internal/ads/zzaci;)Ljava/lang/Object;
    //   19: checkcast 38	java/lang/String
    //   22: astore_2
    //   23: aload_2
    //   24: ifnull +10 -> 34
    //   27: aload_2
    //   28: invokevirtual 42	java/lang/String:length	()I
    //   31: ifne +49 -> 80
    //   34: aload_0
    //   35: ifnonnull +11 -> 46
    //   38: aconst_null
    //   39: astore_2
    //   40: aload_2
    //   41: ifnonnull +39 -> 80
    //   44: iconst_0
    //   45: ireturn
    //   46: aload_0
    //   47: ldc 44
    //   49: ldc 46
    //   51: invokevirtual 52	com/google/android/gms/internal/ads/zzdy:zzc	(Ljava/lang/String;Ljava/lang/String;)Ljava/lang/reflect/Method;
    //   54: astore_3
    //   55: aload_3
    //   56: ifnonnull +8 -> 64
    //   59: aconst_null
    //   60: astore_2
    //   61: goto -21 -> 40
    //   64: aload_3
    //   65: aconst_null
    //   66: iconst_0
    //   67: anewarray 4	java/lang/Object
    //   70: invokevirtual 58	java/lang/reflect/Method:invoke	(Ljava/lang/Object;[Ljava/lang/Object;)Ljava/lang/Object;
    //   73: checkcast 38	java/lang/String
    //   76: astore_2
    //   77: goto -37 -> 40
    //   80: aload_2
    //   81: iconst_1
    //   82: invokestatic 64	com/google/android/gms/internal/ads/zzcg:zza	(Ljava/lang/String;Z)[B
    //   85: astore 5
    //   87: aload 5
    //   89: invokestatic 70	com/google/android/gms/internal/ads/zzdby:zzl	([B)Lcom/google/android/gms/internal/ads/zzdbt;
    //   92: astore 7
    //   94: getstatic 76	com/google/android/gms/internal/ads/zzddb:zzgpt	Lcom/google/android/gms/internal/ads/zzdhn;
    //   97: invokestatic 81	com/google/android/gms/internal/ads/zzdbk:zza	(Lcom/google/android/gms/internal/ads/zzdhn;)V
    //   100: new 83	com/google/android/gms/internal/ads/zzddf
    //   103: dup
    //   104: invokespecial 87	com/google/android/gms/internal/ads/zzddf:<init>	()V
    //   107: invokestatic 92	com/google/android/gms/internal/ads/zzdce:zza	(Lcom/google/android/gms/internal/ads/zzdcb;)V
    //   110: aload 7
    //   112: aconst_null
    //   113: ldc 94
    //   115: invokestatic 97	com/google/android/gms/internal/ads/zzdce:zza	(Lcom/google/android/gms/internal/ads/zzdbt;Lcom/google/android/gms/internal/ads/zzdbr;Ljava/lang/Class;)Lcom/google/android/gms/internal/ads/zzdbz;
    //   118: invokestatic 100	com/google/android/gms/internal/ads/zzdce:zza	(Lcom/google/android/gms/internal/ads/zzdbz;)Ljava/lang/Object;
    //   121: checkcast 94	com/google/android/gms/internal/ads/zzdbp
    //   124: putstatic 18	com/google/android/gms/internal/ads/zzed:zzya	Lcom/google/android/gms/internal/ads/zzdbp;
    //   127: getstatic 18	com/google/android/gms/internal/ads/zzed:zzya	Lcom/google/android/gms/internal/ads/zzdbp;
    //   130: ifnull +13 -> 143
    //   133: iconst_1
    //   134: ireturn
    //   135: astore 4
    //   137: iconst_0
    //   138: ireturn
    //   139: astore 6
    //   141: iconst_0
    //   142: ireturn
    //   143: iconst_0
    //   144: ireturn
    //
    // Exception table:
    //   from	to	target	type
    //   80	87	135	java/lang/IllegalArgumentException
    //   87	127	139	java/security/GeneralSecurityException
  }
}

/* Location:           E:\Study\Tools\apktool2_2\dex2jar-0.0.9.15\classes_viber_2_dex2jar.jar
 * Qualified Name:     com.google.android.gms.internal.ads.zzed
 * JD-Core Version:    0.6.2
 */