package com.google.android.gms.internal.ads;

import android.content.Context;

public final class zzem extends zzfk
{
  private static zzfl<String> zzzf = new zzfl();
  private final Context zzzg;

  public zzem(zzdy paramzzdy, String paramString1, String paramString2, zzbp.zza.zza paramzza, int paramInt1, int paramInt2, Context paramContext)
  {
    super(paramzzdy, paramString1, paramString2, paramzza, paramInt1, 29);
    this.zzzg = paramContext;
  }

  // ERROR //
  protected final void zzcx()
    throws java.lang.IllegalAccessException, java.lang.reflect.InvocationTargetException
  {
    // Byte code:
    //   0: aload_0
    //   1: getfield 33	com/google/android/gms/internal/ads/zzem:zzzm	Lcom/google/android/gms/internal/ads/zzbp$zza$zza;
    //   4: ldc 35
    //   6: invokevirtual 41	com/google/android/gms/internal/ads/zzbp$zza$zza:zzaa	(Ljava/lang/String;)Lcom/google/android/gms/internal/ads/zzbp$zza$zza;
    //   9: pop
    //   10: getstatic 18	com/google/android/gms/internal/ads/zzem:zzzf	Lcom/google/android/gms/internal/ads/zzfl;
    //   13: aload_0
    //   14: getfield 24	com/google/android/gms/internal/ads/zzem:zzzg	Landroid/content/Context;
    //   17: invokevirtual 47	android/content/Context:getPackageName	()Ljava/lang/String;
    //   20: invokevirtual 51	com/google/android/gms/internal/ads/zzfl:zzar	(Ljava/lang/String;)Ljava/util/concurrent/atomic/AtomicReference;
    //   23: astore_2
    //   24: aload_2
    //   25: invokevirtual 57	java/util/concurrent/atomic/AtomicReference:get	()Ljava/lang/Object;
    //   28: ifnonnull +49 -> 77
    //   31: aload_2
    //   32: monitorenter
    //   33: aload_2
    //   34: invokevirtual 57	java/util/concurrent/atomic/AtomicReference:get	()Ljava/lang/Object;
    //   37: ifnonnull +38 -> 75
    //   40: aload_0
    //   41: getfield 61	com/google/android/gms/internal/ads/zzem:zzzw	Ljava/lang/reflect/Method;
    //   44: astore 8
    //   46: iconst_1
    //   47: anewarray 63	java/lang/Object
    //   50: astore 9
    //   52: aload 9
    //   54: iconst_0
    //   55: aload_0
    //   56: getfield 24	com/google/android/gms/internal/ads/zzem:zzzg	Landroid/content/Context;
    //   59: aastore
    //   60: aload_2
    //   61: aload 8
    //   63: aconst_null
    //   64: aload 9
    //   66: invokevirtual 69	java/lang/reflect/Method:invoke	(Ljava/lang/Object;[Ljava/lang/Object;)Ljava/lang/Object;
    //   69: checkcast 71	java/lang/String
    //   72: invokevirtual 75	java/util/concurrent/atomic/AtomicReference:set	(Ljava/lang/Object;)V
    //   75: aload_2
    //   76: monitorexit
    //   77: aload_2
    //   78: invokevirtual 57	java/util/concurrent/atomic/AtomicReference:get	()Ljava/lang/Object;
    //   81: checkcast 71	java/lang/String
    //   84: astore_3
    //   85: aload_0
    //   86: getfield 33	com/google/android/gms/internal/ads/zzem:zzzm	Lcom/google/android/gms/internal/ads/zzbp$zza$zza;
    //   89: astore 4
    //   91: aload 4
    //   93: monitorenter
    //   94: aload_0
    //   95: getfield 33	com/google/android/gms/internal/ads/zzem:zzzm	Lcom/google/android/gms/internal/ads/zzbp$zza$zza;
    //   98: aload_3
    //   99: invokevirtual 79	java/lang/String:getBytes	()[B
    //   102: iconst_1
    //   103: invokestatic 85	com/google/android/gms/internal/ads/zzcg:zza	([BZ)Ljava/lang/String;
    //   106: invokevirtual 41	com/google/android/gms/internal/ads/zzbp$zza$zza:zzaa	(Ljava/lang/String;)Lcom/google/android/gms/internal/ads/zzbp$zza$zza;
    //   109: pop
    //   110: aload 4
    //   112: monitorexit
    //   113: return
    //   114: astore 7
    //   116: aload_2
    //   117: monitorexit
    //   118: aload 7
    //   120: athrow
    //   121: astore 5
    //   123: aload 4
    //   125: monitorexit
    //   126: aload 5
    //   128: athrow
    //
    // Exception table:
    //   from	to	target	type
    //   33	75	114	finally
    //   75	77	114	finally
    //   116	118	114	finally
    //   94	113	121	finally
    //   123	126	121	finally
  }
}

/* Location:           E:\Study\Tools\apktool2_2\dex2jar-0.0.9.15\classes_viber_2_dex2jar.jar
 * Qualified Name:     com.google.android.gms.internal.ads.zzem
 * JD-Core Version:    0.6.2
 */