package com.google.android.gms.internal.ads;

import android.os.Handler;
import android.os.Handler.Callback;
import android.os.HandlerThread;
import android.os.Message;
import android.os.SystemClock;
import android.util.Log;
import android.util.Pair;
import java.io.IOException;

final class zzlc
  implements Handler.Callback, zzqk, zzqm, zzrq
{
  private final Handler handler;
  private int repeatMode;
  private int state;
  private final Handler zzabq;
  private boolean zzabu;
  private final HandlerThread zzaby;
  private boolean zzacf;
  private boolean zzacg;
  private int zzach;
  private int zzaci;
  private long zzacj;
  private final zzlo[] zzaro;
  private final zzrp zzarp;
  private final zzlu zzars;
  private final zzlt zzart;
  private boolean zzarx;
  private zzlr zzary;
  private zzln zzasc;
  private zzle zzasd;
  private final zzlp[] zzasi;
  private final zzll zzasj;
  private final zzsw zzask;
  private final zzkv zzasl;
  private zzlo zzasm;
  private zzso zzasn;
  private zzql zzaso;
  private zzlo[] zzasp;
  private int zzasq;
  private zzlf zzasr;
  private long zzass;
  private zzld zzast;
  private zzld zzasu;
  private zzld zzasv;

  public zzlc(zzlo[] paramArrayOfzzlo, zzrp paramzzrp, zzll paramzzll, boolean paramBoolean, int paramInt, Handler paramHandler, zzle paramzzle, zzkv paramzzkv)
  {
    this.zzaro = paramArrayOfzzlo;
    this.zzarp = paramzzrp;
    this.zzasj = paramzzll;
    this.zzabu = paramBoolean;
    this.repeatMode = 0;
    this.zzabq = paramHandler;
    this.state = 1;
    this.zzasd = paramzzle;
    this.zzasl = paramzzkv;
    this.zzasi = new zzlp[paramArrayOfzzlo.length];
    for (int i = 0; i < paramArrayOfzzlo.length; i++)
    {
      paramArrayOfzzlo[i].setIndex(i);
      this.zzasi[i] = paramArrayOfzzlo[i].zzgi();
    }
    this.zzask = new zzsw();
    this.zzasp = new zzlo[0];
    this.zzars = new zzlu();
    this.zzart = new zzlt();
    paramzzrp.zza(this);
    this.zzasc = zzln.zzaug;
    this.zzaby = new HandlerThread("ExoPlayerImplInternal:Handler", -16);
    this.zzaby.start();
    this.handler = new Handler(this.zzaby.getLooper(), this);
  }

  private final void setState(int paramInt)
  {
    if (this.state != paramInt)
    {
      this.state = paramInt;
      this.zzabq.obtainMessage(1, paramInt, 0).sendToTarget();
    }
  }

  private final int zza(int paramInt, zzlr paramzzlr1, zzlr paramzzlr2)
  {
    int i = paramzzlr1.zzhg();
    int j = 0;
    int k = -1;
    while ((j < i) && (k == -1))
    {
      paramInt = paramzzlr1.zza(paramInt, this.zzart, this.zzars, this.repeatMode);
      k = paramzzlr2.zzc(paramzzlr1.zza(paramInt, this.zzart, true).zzasx);
      j++;
    }
    return k;
  }

  private final Pair<Integer, Long> zza(zzlf paramzzlf)
  {
    zzlr localzzlr1 = paramzzlf.zzary;
    if (localzzlr1.isEmpty());
    for (zzlr localzzlr2 = this.zzary; ; localzzlr2 = localzzlr1)
    {
      Pair localPair;
      try
      {
        localPair = zzb(localzzlr2, paramzzlf.zzati, paramzzlf.zzatj);
        if (this.zzary == localzzlr2)
          return localPair;
      }
      catch (IndexOutOfBoundsException localIndexOutOfBoundsException)
      {
        throw new zzlk(this.zzary, paramzzlf.zzati, paramzzlf.zzatj);
      }
      int i = this.zzary.zzc(localzzlr2.zza(((Integer)localPair.first).intValue(), this.zzart, true).zzasx);
      if (i != -1)
        return Pair.create(Integer.valueOf(i), (Long)localPair.second);
      int j = zza(((Integer)localPair.first).intValue(), localzzlr2, this.zzary);
      if (j != -1)
      {
        this.zzary.zza(j, this.zzart, false);
        return zze(0, -9223372036854775807L);
      }
      return null;
    }
  }

  private final Pair<Integer, Long> zza(zzlr paramzzlr, int paramInt, long paramLong1, long paramLong2)
  {
    zzsk.zzc(paramInt, 0, paramzzlr.zzhf());
    paramzzlr.zza(paramInt, this.zzars, false, paramLong2);
    if (paramLong1 == -9223372036854775807L)
    {
      paramLong1 = this.zzars.zzauw;
      if (paramLong1 == -9223372036854775807L)
        return null;
    }
    long l = paramLong1 + this.zzars.zzaux;
    paramzzlr.zza(0, this.zzart, false);
    return Pair.create(Integer.valueOf(0), Long.valueOf(l));
  }

  private static void zza(zzld paramzzld)
  {
    while (paramzzld != null)
    {
      paramzzld.release();
      paramzzld = paramzzld.zzatf;
    }
  }

  private static void zza(zzlo paramzzlo)
    throws zzku
  {
    if (paramzzlo.getState() == 2)
      paramzzlo.stop();
  }

  private final void zza(Object paramObject, int paramInt)
  {
    this.zzasd = new zzle(0, 0L);
    zzb(paramObject, paramInt);
    this.zzasd = new zzle(0, -9223372036854775807L);
    setState(4);
    zzj(false);
  }

  private final void zza(boolean[] paramArrayOfBoolean, int paramInt)
    throws zzku
  {
    this.zzasp = new zzlo[paramInt];
    int i = 0;
    for (int j = 0; j < this.zzaro.length; j++)
    {
      zzlo localzzlo = this.zzaro[j];
      zzrm localzzrm = this.zzasv.zzatg.zzblz.zzbi(j);
      if (localzzrm != null)
      {
        zzlo[] arrayOfzzlo = this.zzasp;
        int k = i + 1;
        arrayOfzzlo[i] = localzzlo;
        if (localzzlo.getState() == 0)
        {
          zzlq localzzlq = this.zzasv.zzatg.zzbmb[j];
          int m;
          if ((this.zzabu) && (this.state == 3))
          {
            m = 1;
            if ((paramArrayOfBoolean[j] != 0) || (m == 0))
              break label178;
          }
          zzlh[] arrayOfzzlh;
          label178: for (boolean bool = true; ; bool = false)
          {
            arrayOfzzlh = new zzlh[localzzrm.length()];
            for (int n = 0; n < arrayOfzzlh.length; n++)
              arrayOfzzlh[n] = localzzrm.zzbf(n);
            m = 0;
            break;
          }
          localzzlo.zza(localzzlq, arrayOfzzlh, this.zzasv.zzasy[j], this.zzass, bool, this.zzasv.zzgz());
          zzso localzzso = localzzlo.zzgj();
          if (localzzso != null)
          {
            if (this.zzasn != null)
              throw zzku.zza(new IllegalStateException("Multiple renderer media clocks enabled."));
            this.zzasn = localzzso;
            this.zzasm = localzzlo;
            this.zzasn.zzb(this.zzasc);
          }
          if (m != 0)
            localzzlo.start();
        }
        i = k;
      }
    }
  }

  private final boolean zzad(int paramInt)
  {
    this.zzary.zza(paramInt, this.zzart, false);
    boolean bool1 = this.zzary.zza(0, this.zzars, false).zzaut;
    boolean bool2 = false;
    if (!bool1)
    {
      int i = this.zzary.zza(paramInt, this.zzart, this.zzars, this.repeatMode);
      bool2 = false;
      if (i == -1)
        bool2 = true;
    }
    return bool2;
  }

  private final Pair<Integer, Long> zzb(zzlr paramzzlr, int paramInt, long paramLong)
  {
    return zza(paramzzlr, paramInt, paramLong, 0L);
  }

  private final void zzb(long paramLong1, long paramLong2)
  {
    this.handler.removeMessages(2);
    long l = paramLong1 + paramLong2 - SystemClock.elapsedRealtime();
    if (l <= 0L)
    {
      this.handler.sendEmptyMessage(2);
      return;
    }
    this.handler.sendEmptyMessageDelayed(2, l);
  }

  private final void zzb(zzld paramzzld)
    throws zzku
  {
    if (this.zzasv == paramzzld)
      return;
    boolean[] arrayOfBoolean = new boolean[this.zzaro.length];
    int i = 0;
    int j = 0;
    if (i < this.zzaro.length)
    {
      zzlo localzzlo = this.zzaro[i];
      if (localzzlo.getState() != 0);
      for (int k = 1; ; k = 0)
      {
        arrayOfBoolean[i] = k;
        zzrm localzzrm = paramzzld.zzatg.zzblz.zzbi(i);
        if (localzzrm != null)
          j++;
        if ((arrayOfBoolean[i] != 0) && ((localzzrm == null) || ((localzzlo.zzgn()) && (localzzlo.zzgk() == this.zzasv.zzasy[i]))))
        {
          if (localzzlo == this.zzasm)
          {
            this.zzask.zza(this.zzasn);
            this.zzasn = null;
            this.zzasm = null;
          }
          zza(localzzlo);
          localzzlo.disable();
        }
        i++;
        break;
      }
    }
    this.zzasv = paramzzld;
    this.zzabq.obtainMessage(3, paramzzld.zzatg).sendToTarget();
    zza(arrayOfBoolean, j);
  }

  private final void zzb(Object paramObject, int paramInt)
  {
    this.zzabq.obtainMessage(6, new zzlg(this.zzary, paramObject, this.zzasd, paramInt)).sendToTarget();
  }

  private final long zzd(int paramInt, long paramLong)
    throws zzku
  {
    zzdq();
    this.zzacg = false;
    setState(2);
    Object localObject;
    if (this.zzasv == null)
    {
      if (this.zzast == null)
        break label267;
      this.zzast.release();
      localObject = null;
    }
    while (true)
    {
      if ((this.zzasv != localObject) || (this.zzasv != this.zzasu))
      {
        zzlo[] arrayOfzzlo = this.zzasp;
        int i = arrayOfzzlo.length;
        int j = 0;
        while (j < i)
        {
          arrayOfzzlo[j].disable();
          j++;
          continue;
          zzld localzzld = this.zzasv;
          localObject = null;
          label104: if (localzzld != null)
          {
            if ((localzzld.zzatb != paramInt) || (!localzzld.zzacs))
              break label140;
            localObject = localzzld;
          }
          while (true)
          {
            localzzld = localzzld.zzatf;
            break label104;
            break;
            label140: localzzld.release();
          }
        }
        this.zzasp = new zzlo[0];
        this.zzasn = null;
        this.zzasm = null;
        this.zzasv = null;
      }
      if (localObject != null)
      {
        localObject.zzatf = null;
        this.zzast = localObject;
        this.zzasu = localObject;
        zzb(localObject);
        if (this.zzasv.zzate)
          paramLong = this.zzasv.zzasw.zzen(paramLong);
        zzeb(paramLong);
        zzgy();
      }
      while (true)
      {
        this.handler.sendEmptyMessage(2);
        return paramLong;
        this.zzast = null;
        this.zzasu = null;
        this.zzasv = null;
        zzeb(paramLong);
      }
      label267: localObject = null;
    }
  }

  private final void zzdp()
    throws zzku
  {
    int i = 0;
    this.zzacg = false;
    this.zzask.start();
    zzlo[] arrayOfzzlo = this.zzasp;
    int j = arrayOfzzlo.length;
    while (i < j)
    {
      arrayOfzzlo[i].start();
      i++;
    }
  }

  private final void zzdq()
    throws zzku
  {
    this.zzask.stop();
    zzlo[] arrayOfzzlo = this.zzasp;
    int i = arrayOfzzlo.length;
    for (int j = 0; j < i; j++)
      zza(arrayOfzzlo[j]);
  }

  private final void zzds()
  {
    zzj(true);
    this.zzasj.onStopped();
    setState(1);
  }

  private final Pair<Integer, Long> zze(int paramInt, long paramLong)
  {
    return zzb(this.zzary, paramInt, -9223372036854775807L);
  }

  private final void zzeb(long paramLong)
    throws zzku
  {
    if (this.zzasv == null);
    for (long l = 60000000L + paramLong; ; l = paramLong + this.zzasv.zzgz())
    {
      this.zzass = l;
      this.zzask.zzdj(this.zzass);
      zzlo[] arrayOfzzlo = this.zzasp;
      int i = arrayOfzzlo.length;
      for (int j = 0; j < i; j++)
        arrayOfzzlo[j].zzdx(this.zzass);
    }
  }

  private final boolean zzec(long paramLong)
  {
    return (paramLong == -9223372036854775807L) || (this.zzasd.zzacl < paramLong) || ((this.zzasv.zzatf != null) && (this.zzasv.zzatf.zzacs));
  }

  private final void zzgw()
    throws zzku
  {
    if (this.zzasv == null)
      return;
    long l1 = this.zzasv.zzasw.zzja();
    if (l1 != -9223372036854775807L)
    {
      zzeb(l1);
      this.zzasd.zzacl = l1;
      this.zzacj = (1000L * SystemClock.elapsedRealtime());
      if (this.zzasp.length != 0)
        break label188;
    }
    label188: for (long l2 = -9223372036854775808L; ; l2 = this.zzasv.zzasw.zzdu())
    {
      zzle localzzle = this.zzasd;
      if (l2 == -9223372036854775808L)
        l2 = this.zzary.zza(this.zzasv.zzatb, this.zzart, false).zzack;
      localzzle.zzacm = l2;
      return;
      if ((this.zzasm != null) && (!this.zzasm.zzdx()))
      {
        this.zzass = this.zzasn.zzdv();
        this.zzask.zzdj(this.zzass);
      }
      while (true)
      {
        zzld localzzld = this.zzasv;
        l1 = this.zzass - localzzld.zzgz();
        break;
        this.zzass = this.zzask.zzdv();
      }
    }
  }

  private final void zzgx()
    throws IOException
  {
    zzlo[] arrayOfzzlo;
    int i;
    if ((this.zzast != null) && (!this.zzast.zzacs) && ((this.zzasu == null) || (this.zzasu.zzatf == this.zzast)))
    {
      arrayOfzzlo = this.zzasp;
      i = arrayOfzzlo.length;
    }
    for (int j = 0; j < i; j++)
      if (!arrayOfzzlo[j].zzgl())
        return;
    this.zzast.zzasw.zziy();
  }

  private final void zzgy()
  {
    long l1;
    if (!this.zzast.zzacs)
    {
      l1 = 0L;
      if (l1 != -9223372036854775808L)
        break label42;
      zzi(false);
    }
    label42: long l2;
    boolean bool;
    do
    {
      return;
      l1 = this.zzast.zzasw.zzix();
      break;
      zzld localzzld = this.zzast;
      l2 = this.zzass - localzzld.zzgz();
      long l3 = l1 - l2;
      bool = this.zzasj.zzee(l3);
      zzi(bool);
    }
    while (!bool);
    this.zzast.zzasw.zzel(l2);
  }

  private final void zzi(boolean paramBoolean)
  {
    Handler localHandler;
    if (this.zzarx != paramBoolean)
    {
      this.zzarx = paramBoolean;
      localHandler = this.zzabq;
      if (!paramBoolean)
        break label35;
    }
    label35: for (int i = 1; ; i = 0)
    {
      localHandler.obtainMessage(2, i, 0).sendToTarget();
      return;
    }
  }

  private final void zzj(boolean paramBoolean)
  {
    this.handler.removeMessages(2);
    this.zzacg = false;
    this.zzask.stop();
    this.zzasn = null;
    this.zzasm = null;
    this.zzass = 60000000L;
    zzlo[] arrayOfzzlo = this.zzasp;
    int i = arrayOfzzlo.length;
    int j = 0;
    while (true)
    {
      zzlo localzzlo;
      if (j < i)
        localzzlo = arrayOfzzlo[j];
      try
      {
        zza(localzzlo);
        localzzlo.disable();
        j++;
      }
      catch (RuntimeException localRuntimeException)
      {
        while (true)
          Log.e("ExoPlayerImplInternal", "Stop failed.", localRuntimeException);
        this.zzasp = new zzlo[0];
        if (this.zzasv != null);
        for (zzld localzzld = this.zzasv; ; localzzld = this.zzast)
        {
          zza(localzzld);
          this.zzast = null;
          this.zzasu = null;
          this.zzasv = null;
          zzi(false);
          if (paramBoolean)
          {
            if (this.zzaso != null)
            {
              this.zzaso.zzjg();
              this.zzaso = null;
            }
            this.zzary = null;
          }
          return;
        }
      }
      catch (zzku localzzku)
      {
        label80: break label80;
      }
    }
  }

  // ERROR //
  public final boolean handleMessage(Message paramMessage)
  {
    // Byte code:
    //   0: aload_1
    //   1: getfield 555	android/os/Message:what	I
    //   4: tableswitch	default:+4255 -> 4259, 0:+68->72, 1:+165->169, 2:+595->599, 3:+2316->2320, 4:+2690->2694, 5:+2755->2759, 6:+2761->2765, 7:+2908->2912, 8:+2802->2806, 9:+3602->3606, 10:+3640->3644, 11:+4125->4129, 12:+317->321
    //   73: getfield 558	android/os/Message:obj	Ljava/lang/Object;
    //   76: checkcast 547	com/google/android/gms/internal/ads/zzql
    //   79: astore 161
    //   81: aload_1
    //   82: getfield 561	android/os/Message:arg1	I
    //   85: ifeq +4176 -> 4261
    //   88: iconst_1
    //   89: istore 162
    //   91: aload_0
    //   92: getfield 83	com/google/android/gms/internal/ads/zzlc:zzabq	Landroid/os/Handler;
    //   95: iconst_0
    //   96: invokevirtual 391	android/os/Handler:sendEmptyMessage	(I)Z
    //   99: pop
    //   100: aload_0
    //   101: iconst_1
    //   102: invokespecial 298	com/google/android/gms/internal/ads/zzlc:zzj	(Z)V
    //   105: aload_0
    //   106: getfield 77	com/google/android/gms/internal/ads/zzlc:zzasj	Lcom/google/android/gms/internal/ads/zzll;
    //   109: invokeinterface 564 1 0
    //   114: iload 162
    //   116: ifeq +18 -> 134
    //   119: aload_0
    //   120: new 287	com/google/android/gms/internal/ads/zzle
    //   123: dup
    //   124: iconst_0
    //   125: ldc2_w 240
    //   128: invokespecial 290	com/google/android/gms/internal/ads/zzle:<init>	(IJ)V
    //   131: putfield 87	com/google/android/gms/internal/ads/zzlc:zzasd	Lcom/google/android/gms/internal/ads/zzle;
    //   134: aload_0
    //   135: aload 161
    //   137: putfield 545	com/google/android/gms/internal/ads/zzlc:zzaso	Lcom/google/android/gms/internal/ads/zzql;
    //   140: aload 161
    //   142: aload_0
    //   143: getfield 89	com/google/android/gms/internal/ads/zzlc:zzasl	Lcom/google/android/gms/internal/ads/zzkv;
    //   146: iconst_1
    //   147: aload_0
    //   148: invokeinterface 567 4 0
    //   153: aload_0
    //   154: iconst_2
    //   155: invokespecial 294	com/google/android/gms/internal/ads/zzlc:setState	(I)V
    //   158: aload_0
    //   159: getfield 156	com/google/android/gms/internal/ads/zzlc:handler	Landroid/os/Handler;
    //   162: iconst_2
    //   163: invokevirtual 391	android/os/Handler:sendEmptyMessage	(I)Z
    //   166: pop
    //   167: iconst_1
    //   168: ireturn
    //   169: aload_1
    //   170: getfield 561	android/os/Message:arg1	I
    //   173: ifeq +4096 -> 4269
    //   176: iconst_1
    //   177: istore 158
    //   179: aload_0
    //   180: iconst_0
    //   181: putfield 427	com/google/android/gms/internal/ads/zzlc:zzacg	Z
    //   184: aload_0
    //   185: iload 158
    //   187: putfield 79	com/google/android/gms/internal/ads/zzlc:zzabu	Z
    //   190: iload 158
    //   192: ifne +14 -> 206
    //   195: aload_0
    //   196: invokespecial 425	com/google/android/gms/internal/ads/zzlc:zzdq	()V
    //   199: aload_0
    //   200: invokespecial 569	com/google/android/gms/internal/ads/zzlc:zzgw	()V
    //   203: goto +4064 -> 4267
    //   206: aload_0
    //   207: getfield 85	com/google/android/gms/internal/ads/zzlc:state	I
    //   210: iconst_3
    //   211: if_icmpne +53 -> 264
    //   214: aload_0
    //   215: invokespecial 571	com/google/android/gms/internal/ads/zzlc:zzdp	()V
    //   218: aload_0
    //   219: getfield 156	com/google/android/gms/internal/ads/zzlc:handler	Landroid/os/Handler;
    //   222: iconst_2
    //   223: invokevirtual 391	android/os/Handler:sendEmptyMessage	(I)Z
    //   226: pop
    //   227: goto +4040 -> 4267
    //   230: astore 6
    //   232: ldc_w 533
    //   235: ldc_w 573
    //   238: aload 6
    //   240: invokestatic 541	android/util/Log:e	(Ljava/lang/String;Ljava/lang/String;Ljava/lang/Throwable;)I
    //   243: pop
    //   244: aload_0
    //   245: getfield 83	com/google/android/gms/internal/ads/zzlc:zzabq	Landroid/os/Handler;
    //   248: bipush 8
    //   250: aload 6
    //   252: invokevirtual 413	android/os/Handler:obtainMessage	(ILjava/lang/Object;)Landroid/os/Message;
    //   255: invokevirtual 166	android/os/Message:sendToTarget	()V
    //   258: aload_0
    //   259: invokespecial 575	com/google/android/gms/internal/ads/zzlc:zzds	()V
    //   262: iconst_1
    //   263: ireturn
    //   264: aload_0
    //   265: getfield 85	com/google/android/gms/internal/ads/zzlc:state	I
    //   268: iconst_2
    //   269: if_icmpne +3998 -> 4267
    //   272: aload_0
    //   273: getfield 156	com/google/android/gms/internal/ads/zzlc:handler	Landroid/os/Handler;
    //   276: iconst_2
    //   277: invokevirtual 391	android/os/Handler:sendEmptyMessage	(I)Z
    //   280: pop
    //   281: goto +3986 -> 4267
    //   284: astore 4
    //   286: ldc_w 533
    //   289: ldc_w 577
    //   292: aload 4
    //   294: invokestatic 541	android/util/Log:e	(Ljava/lang/String;Ljava/lang/String;Ljava/lang/Throwable;)I
    //   297: pop
    //   298: aload_0
    //   299: getfield 83	com/google/android/gms/internal/ads/zzlc:zzabq	Landroid/os/Handler;
    //   302: bipush 8
    //   304: aload 4
    //   306: invokestatic 580	com/google/android/gms/internal/ads/zzku:zza	(Ljava/io/IOException;)Lcom/google/android/gms/internal/ads/zzku;
    //   309: invokevirtual 413	android/os/Handler:obtainMessage	(ILjava/lang/Object;)Landroid/os/Message;
    //   312: invokevirtual 166	android/os/Message:sendToTarget	()V
    //   315: aload_0
    //   316: invokespecial 575	com/google/android/gms/internal/ads/zzlc:zzds	()V
    //   319: iconst_1
    //   320: ireturn
    //   321: aload_1
    //   322: getfield 561	android/os/Message:arg1	I
    //   325: istore 147
    //   327: aload_0
    //   328: iload 147
    //   330: putfield 81	com/google/android/gms/internal/ads/zzlc:repeatMode	I
    //   333: aload_0
    //   334: getfield 301	com/google/android/gms/internal/ads/zzlc:zzasv	Lcom/google/android/gms/internal/ads/zzld;
    //   337: ifnull +138 -> 475
    //   340: aload_0
    //   341: getfield 301	com/google/android/gms/internal/ads/zzlc:zzasv	Lcom/google/android/gms/internal/ads/zzld;
    //   344: astore 148
    //   346: aload 148
    //   348: ifnull +3973 -> 4321
    //   351: aload 148
    //   353: aload_0
    //   354: getfield 431	com/google/android/gms/internal/ads/zzlc:zzasu	Lcom/google/android/gms/internal/ads/zzld;
    //   357: if_acmpne +3932 -> 4289
    //   360: iconst_1
    //   361: istore 149
    //   363: aload 148
    //   365: aload_0
    //   366: getfield 429	com/google/android/gms/internal/ads/zzlc:zzast	Lcom/google/android/gms/internal/ads/zzld;
    //   369: if_acmpne +3926 -> 4295
    //   372: aload 148
    //   374: astore 150
    //   376: iload 149
    //   378: istore 151
    //   380: iconst_1
    //   381: istore 152
    //   383: aload_0
    //   384: getfield 199	com/google/android/gms/internal/ads/zzlc:zzary	Lcom/google/android/gms/internal/ads/zzlr;
    //   387: aload 150
    //   389: getfield 434	com/google/android/gms/internal/ads/zzld:zzatb	I
    //   392: aload_0
    //   393: getfield 120	com/google/android/gms/internal/ads/zzlc:zzart	Lcom/google/android/gms/internal/ads/zzlt;
    //   396: aload_0
    //   397: getfield 115	com/google/android/gms/internal/ads/zzlc:zzars	Lcom/google/android/gms/internal/ads/zzlu;
    //   400: iload 147
    //   402: invokevirtual 176	com/google/android/gms/internal/ads/zzlr:zza	(ILcom/google/android/gms/internal/ads/zzlt;Lcom/google/android/gms/internal/ads/zzlu;I)I
    //   405: istore 153
    //   407: aload 150
    //   409: getfield 275	com/google/android/gms/internal/ads/zzld:zzatf	Lcom/google/android/gms/internal/ads/zzld;
    //   412: ifnull +72 -> 484
    //   415: iload 153
    //   417: iconst_m1
    //   418: if_icmpeq +66 -> 484
    //   421: aload 150
    //   423: getfield 275	com/google/android/gms/internal/ads/zzld:zzatf	Lcom/google/android/gms/internal/ads/zzld;
    //   426: getfield 434	com/google/android/gms/internal/ads/zzld:zzatb	I
    //   429: iload 153
    //   431: if_icmpne +53 -> 484
    //   434: aload 150
    //   436: getfield 275	com/google/android/gms/internal/ads/zzld:zzatf	Lcom/google/android/gms/internal/ads/zzld;
    //   439: astore 155
    //   441: aload 155
    //   443: aload_0
    //   444: getfield 431	com/google/android/gms/internal/ads/zzlc:zzasu	Lcom/google/android/gms/internal/ads/zzld;
    //   447: if_acmpne +3862 -> 4309
    //   450: iconst_1
    //   451: istore 156
    //   453: iload 151
    //   455: iload 156
    //   457: ior
    //   458: istore 151
    //   460: aload 155
    //   462: aload_0
    //   463: getfield 429	com/google/android/gms/internal/ads/zzlc:zzast	Lcom/google/android/gms/internal/ads/zzld;
    //   466: if_acmpne +3849 -> 4315
    //   469: iconst_1
    //   470: istore 157
    //   472: goto +3803 -> 4275
    //   475: aload_0
    //   476: getfield 429	com/google/android/gms/internal/ads/zzlc:zzast	Lcom/google/android/gms/internal/ads/zzld;
    //   479: astore 148
    //   481: goto -135 -> 346
    //   484: aload 150
    //   486: getfield 275	com/google/android/gms/internal/ads/zzld:zzatf	Lcom/google/android/gms/internal/ads/zzld;
    //   489: ifnull +17 -> 506
    //   492: aload 150
    //   494: getfield 275	com/google/android/gms/internal/ads/zzld:zzatf	Lcom/google/android/gms/internal/ads/zzld;
    //   497: invokestatic 543	com/google/android/gms/internal/ads/zzlc:zza	(Lcom/google/android/gms/internal/ads/zzld;)V
    //   500: aload 150
    //   502: aconst_null
    //   503: putfield 275	com/google/android/gms/internal/ads/zzld:zzatf	Lcom/google/android/gms/internal/ads/zzld;
    //   506: aload 150
    //   508: aload_0
    //   509: aload 150
    //   511: getfield 434	com/google/android/gms/internal/ads/zzld:zzatb	I
    //   514: invokespecial 582	com/google/android/gms/internal/ads/zzlc:zzad	(I)Z
    //   517: putfield 585	com/google/android/gms/internal/ads/zzld:zzatd	Z
    //   520: iload 152
    //   522: ifne +9 -> 531
    //   525: aload_0
    //   526: aload 150
    //   528: putfield 429	com/google/android/gms/internal/ads/zzlc:zzast	Lcom/google/android/gms/internal/ads/zzld;
    //   531: iload 151
    //   533: ifne +45 -> 578
    //   536: aload_0
    //   537: getfield 301	com/google/android/gms/internal/ads/zzlc:zzasv	Lcom/google/android/gms/internal/ads/zzld;
    //   540: ifnull +38 -> 578
    //   543: aload_0
    //   544: getfield 301	com/google/android/gms/internal/ads/zzlc:zzasv	Lcom/google/android/gms/internal/ads/zzld;
    //   547: getfield 434	com/google/android/gms/internal/ads/zzld:zzatb	I
    //   550: istore 154
    //   552: aload_0
    //   553: new 287	com/google/android/gms/internal/ads/zzle
    //   556: dup
    //   557: iload 154
    //   559: aload_0
    //   560: iload 154
    //   562: aload_0
    //   563: getfield 87	com/google/android/gms/internal/ads/zzlc:zzasd	Lcom/google/android/gms/internal/ads/zzle;
    //   566: getfield 481	com/google/android/gms/internal/ads/zzle:zzacl	J
    //   569: invokespecial 587	com/google/android/gms/internal/ads/zzlc:zzd	(IJ)J
    //   572: invokespecial 290	com/google/android/gms/internal/ads/zzle:<init>	(IJ)V
    //   575: putfield 87	com/google/android/gms/internal/ads/zzlc:zzasd	Lcom/google/android/gms/internal/ads/zzle;
    //   578: aload_0
    //   579: getfield 85	com/google/android/gms/internal/ads/zzlc:state	I
    //   582: iconst_4
    //   583: if_icmpne +3738 -> 4321
    //   586: iload 147
    //   588: ifeq +3733 -> 4321
    //   591: aload_0
    //   592: iconst_2
    //   593: invokespecial 294	com/google/android/gms/internal/ads/zzlc:setState	(I)V
    //   596: goto +3725 -> 4321
    //   599: invokestatic 388	android/os/SystemClock:elapsedRealtime	()J
    //   602: lstore 94
    //   604: aload_0
    //   605: getfield 199	com/google/android/gms/internal/ads/zzlc:zzary	Lcom/google/android/gms/internal/ads/zzlr;
    //   608: ifnonnull +35 -> 643
    //   611: aload_0
    //   612: getfield 545	com/google/android/gms/internal/ads/zzlc:zzaso	Lcom/google/android/gms/internal/ads/zzql;
    //   615: invokeinterface 590 1 0
    //   620: aload_0
    //   621: getfield 301	com/google/android/gms/internal/ads/zzlc:zzasv	Lcom/google/android/gms/internal/ads/zzld;
    //   624: ifnonnull +1070 -> 1694
    //   627: aload_0
    //   628: invokespecial 592	com/google/android/gms/internal/ads/zzlc:zzgx	()V
    //   631: aload_0
    //   632: lload 94
    //   634: ldc2_w 593
    //   637: invokespecial 596	com/google/android/gms/internal/ads/zzlc:zzb	(JJ)V
    //   640: goto +3683 -> 4323
    //   643: aload_0
    //   644: getfield 429	com/google/android/gms/internal/ads/zzlc:zzast	Lcom/google/android/gms/internal/ads/zzld;
    //   647: ifnonnull +190 -> 837
    //   650: aload_0
    //   651: getfield 87	com/google/android/gms/internal/ads/zzlc:zzasd	Lcom/google/android/gms/internal/ads/zzle;
    //   654: getfield 597	com/google/android/gms/internal/ads/zzle:zzatb	I
    //   657: istore 97
    //   659: iload 97
    //   661: aload_0
    //   662: getfield 199	com/google/android/gms/internal/ads/zzlc:zzary	Lcom/google/android/gms/internal/ads/zzlr;
    //   665: invokevirtual 173	com/google/android/gms/internal/ads/zzlr:zzhg	()I
    //   668: if_icmplt +275 -> 943
    //   671: aload_0
    //   672: getfield 545	com/google/android/gms/internal/ads/zzlc:zzaso	Lcom/google/android/gms/internal/ads/zzql;
    //   675: invokeinterface 590 1 0
    //   680: aload_0
    //   681: getfield 429	com/google/android/gms/internal/ads/zzlc:zzast	Lcom/google/android/gms/internal/ads/zzld;
    //   684: ifnull +13 -> 697
    //   687: aload_0
    //   688: getfield 429	com/google/android/gms/internal/ads/zzlc:zzast	Lcom/google/android/gms/internal/ads/zzld;
    //   691: invokevirtual 600	com/google/android/gms/internal/ads/zzld:zzha	()Z
    //   694: ifeq +584 -> 1278
    //   697: aload_0
    //   698: iconst_0
    //   699: invokespecial 518	com/google/android/gms/internal/ads/zzlc:zzi	(Z)V
    //   702: aload_0
    //   703: getfield 301	com/google/android/gms/internal/ads/zzlc:zzasv	Lcom/google/android/gms/internal/ads/zzld;
    //   706: ifnull -86 -> 620
    //   709: aload_0
    //   710: getfield 301	com/google/android/gms/internal/ads/zzlc:zzasv	Lcom/google/android/gms/internal/ads/zzld;
    //   713: aload_0
    //   714: getfield 431	com/google/android/gms/internal/ads/zzlc:zzasu	Lcom/google/android/gms/internal/ads/zzld;
    //   717: if_acmpeq +582 -> 1299
    //   720: aload_0
    //   721: getfield 338	com/google/android/gms/internal/ads/zzlc:zzass	J
    //   724: aload_0
    //   725: getfield 301	com/google/android/gms/internal/ads/zzlc:zzasv	Lcom/google/android/gms/internal/ads/zzld;
    //   728: getfield 275	com/google/android/gms/internal/ads/zzld:zzatf	Lcom/google/android/gms/internal/ads/zzld;
    //   731: getfield 603	com/google/android/gms/internal/ads/zzld:zzata	J
    //   734: lcmp
    //   735: iflt +564 -> 1299
    //   738: aload_0
    //   739: getfield 301	com/google/android/gms/internal/ads/zzlc:zzasv	Lcom/google/android/gms/internal/ads/zzld;
    //   742: invokevirtual 272	com/google/android/gms/internal/ads/zzld:release	()V
    //   745: aload_0
    //   746: aload_0
    //   747: getfield 301	com/google/android/gms/internal/ads/zzlc:zzasv	Lcom/google/android/gms/internal/ads/zzld;
    //   750: getfield 275	com/google/android/gms/internal/ads/zzld:zzatf	Lcom/google/android/gms/internal/ads/zzld;
    //   753: invokespecial 439	com/google/android/gms/internal/ads/zzlc:zzb	(Lcom/google/android/gms/internal/ads/zzld;)V
    //   756: aload_0
    //   757: new 287	com/google/android/gms/internal/ads/zzle
    //   760: dup
    //   761: aload_0
    //   762: getfield 301	com/google/android/gms/internal/ads/zzlc:zzasv	Lcom/google/android/gms/internal/ads/zzld;
    //   765: getfield 434	com/google/android/gms/internal/ads/zzld:zzatb	I
    //   768: aload_0
    //   769: getfield 301	com/google/android/gms/internal/ads/zzlc:zzasv	Lcom/google/android/gms/internal/ads/zzld;
    //   772: getfield 606	com/google/android/gms/internal/ads/zzld:zzatc	J
    //   775: invokespecial 290	com/google/android/gms/internal/ads/zzle:<init>	(IJ)V
    //   778: putfield 87	com/google/android/gms/internal/ads/zzlc:zzasd	Lcom/google/android/gms/internal/ads/zzle;
    //   781: aload_0
    //   782: invokespecial 569	com/google/android/gms/internal/ads/zzlc:zzgw	()V
    //   785: aload_0
    //   786: getfield 83	com/google/android/gms/internal/ads/zzlc:zzabq	Landroid/os/Handler;
    //   789: iconst_5
    //   790: aload_0
    //   791: getfield 87	com/google/android/gms/internal/ads/zzlc:zzasd	Lcom/google/android/gms/internal/ads/zzle;
    //   794: invokevirtual 413	android/os/Handler:obtainMessage	(ILjava/lang/Object;)Landroid/os/Message;
    //   797: invokevirtual 166	android/os/Message:sendToTarget	()V
    //   800: goto -91 -> 709
    //   803: astore_2
    //   804: ldc_w 533
    //   807: ldc_w 608
    //   810: aload_2
    //   811: invokestatic 541	android/util/Log:e	(Ljava/lang/String;Ljava/lang/String;Ljava/lang/Throwable;)I
    //   814: pop
    //   815: aload_0
    //   816: getfield 83	com/google/android/gms/internal/ads/zzlc:zzabq	Landroid/os/Handler;
    //   819: bipush 8
    //   821: aload_2
    //   822: invokestatic 361	com/google/android/gms/internal/ads/zzku:zza	(Ljava/lang/RuntimeException;)Lcom/google/android/gms/internal/ads/zzku;
    //   825: invokevirtual 413	android/os/Handler:obtainMessage	(ILjava/lang/Object;)Landroid/os/Message;
    //   828: invokevirtual 166	android/os/Message:sendToTarget	()V
    //   831: aload_0
    //   832: invokespecial 575	com/google/android/gms/internal/ads/zzlc:zzds	()V
    //   835: iconst_1
    //   836: ireturn
    //   837: aload_0
    //   838: getfield 429	com/google/android/gms/internal/ads/zzlc:zzast	Lcom/google/android/gms/internal/ads/zzld;
    //   841: getfield 434	com/google/android/gms/internal/ads/zzld:zzatb	I
    //   844: istore 96
    //   846: aload_0
    //   847: getfield 429	com/google/android/gms/internal/ads/zzlc:zzast	Lcom/google/android/gms/internal/ads/zzld;
    //   850: getfield 585	com/google/android/gms/internal/ads/zzld:zzatd	Z
    //   853: ifne -173 -> 680
    //   856: aload_0
    //   857: getfield 429	com/google/android/gms/internal/ads/zzlc:zzast	Lcom/google/android/gms/internal/ads/zzld;
    //   860: invokevirtual 600	com/google/android/gms/internal/ads/zzld:zzha	()Z
    //   863: ifeq -183 -> 680
    //   866: aload_0
    //   867: getfield 199	com/google/android/gms/internal/ads/zzlc:zzary	Lcom/google/android/gms/internal/ads/zzlr;
    //   870: iload 96
    //   872: aload_0
    //   873: getfield 120	com/google/android/gms/internal/ads/zzlc:zzart	Lcom/google/android/gms/internal/ads/zzlt;
    //   876: iconst_0
    //   877: invokevirtual 179	com/google/android/gms/internal/ads/zzlr:zza	(ILcom/google/android/gms/internal/ads/zzlt;Z)Lcom/google/android/gms/internal/ads/zzlt;
    //   880: getfield 494	com/google/android/gms/internal/ads/zzlt:zzack	J
    //   883: ldc2_w 240
    //   886: lcmp
    //   887: ifeq -207 -> 680
    //   890: aload_0
    //   891: getfield 301	com/google/android/gms/internal/ads/zzlc:zzasv	Lcom/google/android/gms/internal/ads/zzld;
    //   894: ifnull +23 -> 917
    //   897: aload_0
    //   898: getfield 429	com/google/android/gms/internal/ads/zzlc:zzast	Lcom/google/android/gms/internal/ads/zzld;
    //   901: getfield 611	com/google/android/gms/internal/ads/zzld:index	I
    //   904: aload_0
    //   905: getfield 301	com/google/android/gms/internal/ads/zzlc:zzasv	Lcom/google/android/gms/internal/ads/zzld;
    //   908: getfield 611	com/google/android/gms/internal/ads/zzld:index	I
    //   911: isub
    //   912: bipush 100
    //   914: if_icmpeq -234 -> 680
    //   917: aload_0
    //   918: getfield 199	com/google/android/gms/internal/ads/zzlc:zzary	Lcom/google/android/gms/internal/ads/zzlr;
    //   921: iload 96
    //   923: aload_0
    //   924: getfield 120	com/google/android/gms/internal/ads/zzlc:zzart	Lcom/google/android/gms/internal/ads/zzlt;
    //   927: aload_0
    //   928: getfield 115	com/google/android/gms/internal/ads/zzlc:zzars	Lcom/google/android/gms/internal/ads/zzlu;
    //   931: aload_0
    //   932: getfield 81	com/google/android/gms/internal/ads/zzlc:repeatMode	I
    //   935: invokevirtual 176	com/google/android/gms/internal/ads/zzlr:zza	(ILcom/google/android/gms/internal/ads/zzlt;Lcom/google/android/gms/internal/ads/zzlu;I)I
    //   938: istore 97
    //   940: goto -281 -> 659
    //   943: aload_0
    //   944: getfield 429	com/google/android/gms/internal/ads/zzlc:zzast	Lcom/google/android/gms/internal/ads/zzld;
    //   947: ifnonnull +151 -> 1098
    //   950: aload_0
    //   951: getfield 87	com/google/android/gms/internal/ads/zzlc:zzasd	Lcom/google/android/gms/internal/ads/zzle;
    //   954: getfield 481	com/google/android/gms/internal/ads/zzle:zzacl	J
    //   957: lstore 103
    //   959: aload_0
    //   960: getfield 429	com/google/android/gms/internal/ads/zzlc:zzast	Lcom/google/android/gms/internal/ads/zzld;
    //   963: ifnonnull +266 -> 1229
    //   966: lload 103
    //   968: ldc2_w 469
    //   971: ladd
    //   972: lstore 105
    //   974: aload_0
    //   975: getfield 429	com/google/android/gms/internal/ads/zzlc:zzast	Lcom/google/android/gms/internal/ads/zzld;
    //   978: ifnonnull +286 -> 1264
    //   981: iconst_0
    //   982: istore 107
    //   984: aload_0
    //   985: iload 97
    //   987: invokespecial 582	com/google/android/gms/internal/ads/zzlc:zzad	(I)Z
    //   990: istore 108
    //   992: aload_0
    //   993: getfield 199	com/google/android/gms/internal/ads/zzlc:zzary	Lcom/google/android/gms/internal/ads/zzlr;
    //   996: iload 97
    //   998: aload_0
    //   999: getfield 120	com/google/android/gms/internal/ads/zzlc:zzart	Lcom/google/android/gms/internal/ads/zzlt;
    //   1002: iconst_1
    //   1003: invokevirtual 179	com/google/android/gms/internal/ads/zzlr:zza	(ILcom/google/android/gms/internal/ads/zzlt;Z)Lcom/google/android/gms/internal/ads/zzlt;
    //   1006: pop
    //   1007: new 269	com/google/android/gms/internal/ads/zzld
    //   1010: dup
    //   1011: aload_0
    //   1012: getfield 73	com/google/android/gms/internal/ads/zzlc:zzaro	[Lcom/google/android/gms/internal/ads/zzlo;
    //   1015: aload_0
    //   1016: getfield 93	com/google/android/gms/internal/ads/zzlc:zzasi	[Lcom/google/android/gms/internal/ads/zzlp;
    //   1019: lload 105
    //   1021: aload_0
    //   1022: getfield 75	com/google/android/gms/internal/ads/zzlc:zzarp	Lcom/google/android/gms/internal/ads/zzrp;
    //   1025: aload_0
    //   1026: getfield 77	com/google/android/gms/internal/ads/zzlc:zzasj	Lcom/google/android/gms/internal/ads/zzll;
    //   1029: aload_0
    //   1030: getfield 545	com/google/android/gms/internal/ads/zzlc:zzaso	Lcom/google/android/gms/internal/ads/zzql;
    //   1033: aload_0
    //   1034: getfield 120	com/google/android/gms/internal/ads/zzlc:zzart	Lcom/google/android/gms/internal/ads/zzlt;
    //   1037: getfield 183	com/google/android/gms/internal/ads/zzlt:zzasx	Ljava/lang/Object;
    //   1040: iload 107
    //   1042: iload 97
    //   1044: iload 108
    //   1046: lload 103
    //   1048: invokespecial 614	com/google/android/gms/internal/ads/zzld:<init>	([Lcom/google/android/gms/internal/ads/zzlo;[Lcom/google/android/gms/internal/ads/zzlp;JLcom/google/android/gms/internal/ads/zzrp;Lcom/google/android/gms/internal/ads/zzll;Lcom/google/android/gms/internal/ads/zzql;Ljava/lang/Object;IIZJ)V
    //   1051: astore 110
    //   1053: aload_0
    //   1054: getfield 429	com/google/android/gms/internal/ads/zzlc:zzast	Lcom/google/android/gms/internal/ads/zzld;
    //   1057: ifnull +12 -> 1069
    //   1060: aload_0
    //   1061: getfield 429	com/google/android/gms/internal/ads/zzlc:zzast	Lcom/google/android/gms/internal/ads/zzld;
    //   1064: aload 110
    //   1066: putfield 275	com/google/android/gms/internal/ads/zzld:zzatf	Lcom/google/android/gms/internal/ads/zzld;
    //   1069: aload_0
    //   1070: aload 110
    //   1072: putfield 429	com/google/android/gms/internal/ads/zzlc:zzast	Lcom/google/android/gms/internal/ads/zzld;
    //   1075: aload_0
    //   1076: getfield 429	com/google/android/gms/internal/ads/zzlc:zzast	Lcom/google/android/gms/internal/ads/zzld;
    //   1079: getfield 446	com/google/android/gms/internal/ads/zzld:zzasw	Lcom/google/android/gms/internal/ads/zzqj;
    //   1082: aload_0
    //   1083: lload 103
    //   1085: invokeinterface 617 4 0
    //   1090: aload_0
    //   1091: iconst_1
    //   1092: invokespecial 518	com/google/android/gms/internal/ads/zzlc:zzi	(Z)V
    //   1095: goto -415 -> 680
    //   1098: aload_0
    //   1099: getfield 199	com/google/android/gms/internal/ads/zzlc:zzary	Lcom/google/android/gms/internal/ads/zzlr;
    //   1102: iload 97
    //   1104: aload_0
    //   1105: getfield 120	com/google/android/gms/internal/ads/zzlc:zzart	Lcom/google/android/gms/internal/ads/zzlt;
    //   1108: iconst_0
    //   1109: invokevirtual 179	com/google/android/gms/internal/ads/zzlr:zza	(ILcom/google/android/gms/internal/ads/zzlt;Z)Lcom/google/android/gms/internal/ads/zzlt;
    //   1112: pop
    //   1113: aload_0
    //   1114: getfield 199	com/google/android/gms/internal/ads/zzlc:zzary	Lcom/google/android/gms/internal/ads/zzlr;
    //   1117: iconst_0
    //   1118: aload_0
    //   1119: getfield 115	com/google/android/gms/internal/ads/zzlc:zzars	Lcom/google/android/gms/internal/ads/zzlu;
    //   1122: iconst_0
    //   1123: invokevirtual 374	com/google/android/gms/internal/ads/zzlr:zza	(ILcom/google/android/gms/internal/ads/zzlu;Z)Lcom/google/android/gms/internal/ads/zzlu;
    //   1126: pop
    //   1127: iload 97
    //   1129: ifeq +9 -> 1138
    //   1132: lconst_0
    //   1133: lstore 103
    //   1135: goto -176 -> 959
    //   1138: aload_0
    //   1139: getfield 429	com/google/android/gms/internal/ads/zzlc:zzast	Lcom/google/android/gms/internal/ads/zzld;
    //   1142: invokevirtual 342	com/google/android/gms/internal/ads/zzld:zzgz	()J
    //   1145: aload_0
    //   1146: getfield 199	com/google/android/gms/internal/ads/zzlc:zzary	Lcom/google/android/gms/internal/ads/zzlr;
    //   1149: aload_0
    //   1150: getfield 429	com/google/android/gms/internal/ads/zzlc:zzast	Lcom/google/android/gms/internal/ads/zzld;
    //   1153: getfield 434	com/google/android/gms/internal/ads/zzld:zzatb	I
    //   1156: aload_0
    //   1157: getfield 120	com/google/android/gms/internal/ads/zzlc:zzart	Lcom/google/android/gms/internal/ads/zzlt;
    //   1160: iconst_0
    //   1161: invokevirtual 179	com/google/android/gms/internal/ads/zzlr:zza	(ILcom/google/android/gms/internal/ads/zzlt;Z)Lcom/google/android/gms/internal/ads/zzlt;
    //   1164: getfield 494	com/google/android/gms/internal/ads/zzlt:zzack	J
    //   1167: ladd
    //   1168: aload_0
    //   1169: getfield 338	com/google/android/gms/internal/ads/zzlc:zzass	J
    //   1172: lsub
    //   1173: lstore 100
    //   1175: aload_0
    //   1176: aload_0
    //   1177: getfield 199	com/google/android/gms/internal/ads/zzlc:zzary	Lcom/google/android/gms/internal/ads/zzlr;
    //   1180: iconst_0
    //   1181: ldc2_w 240
    //   1184: lconst_0
    //   1185: lload 100
    //   1187: invokestatic 623	java/lang/Math:max	(JJ)J
    //   1190: invokespecial 379	com/google/android/gms/internal/ads/zzlc:zza	(Lcom/google/android/gms/internal/ads/zzlr;IJJ)Landroid/util/Pair;
    //   1193: astore 102
    //   1195: aload 102
    //   1197: ifnull -517 -> 680
    //   1200: aload 102
    //   1202: getfield 219	android/util/Pair:first	Ljava/lang/Object;
    //   1205: checkcast 221	java/lang/Integer
    //   1208: invokevirtual 224	java/lang/Integer:intValue	()I
    //   1211: istore 97
    //   1213: aload 102
    //   1215: getfield 231	android/util/Pair:second	Ljava/lang/Object;
    //   1218: checkcast 233	java/lang/Long
    //   1221: invokevirtual 626	java/lang/Long:longValue	()J
    //   1224: lstore 103
    //   1226: goto -267 -> 959
    //   1229: aload_0
    //   1230: getfield 429	com/google/android/gms/internal/ads/zzlc:zzast	Lcom/google/android/gms/internal/ads/zzld;
    //   1233: invokevirtual 342	com/google/android/gms/internal/ads/zzld:zzgz	()J
    //   1236: aload_0
    //   1237: getfield 199	com/google/android/gms/internal/ads/zzlc:zzary	Lcom/google/android/gms/internal/ads/zzlr;
    //   1240: aload_0
    //   1241: getfield 429	com/google/android/gms/internal/ads/zzlc:zzast	Lcom/google/android/gms/internal/ads/zzld;
    //   1244: getfield 434	com/google/android/gms/internal/ads/zzld:zzatb	I
    //   1247: aload_0
    //   1248: getfield 120	com/google/android/gms/internal/ads/zzlc:zzart	Lcom/google/android/gms/internal/ads/zzlt;
    //   1251: iconst_0
    //   1252: invokevirtual 179	com/google/android/gms/internal/ads/zzlr:zza	(ILcom/google/android/gms/internal/ads/zzlt;Z)Lcom/google/android/gms/internal/ads/zzlt;
    //   1255: getfield 494	com/google/android/gms/internal/ads/zzlt:zzack	J
    //   1258: ladd
    //   1259: lstore 105
    //   1261: goto -287 -> 974
    //   1264: iconst_1
    //   1265: aload_0
    //   1266: getfield 429	com/google/android/gms/internal/ads/zzlc:zzast	Lcom/google/android/gms/internal/ads/zzld;
    //   1269: getfield 611	com/google/android/gms/internal/ads/zzld:index	I
    //   1272: iadd
    //   1273: istore 107
    //   1275: goto -291 -> 984
    //   1278: aload_0
    //   1279: getfield 429	com/google/android/gms/internal/ads/zzlc:zzast	Lcom/google/android/gms/internal/ads/zzld;
    //   1282: ifnull -580 -> 702
    //   1285: aload_0
    //   1286: getfield 529	com/google/android/gms/internal/ads/zzlc:zzarx	Z
    //   1289: ifne -587 -> 702
    //   1292: aload_0
    //   1293: invokespecial 459	com/google/android/gms/internal/ads/zzlc:zzgy	()V
    //   1296: goto -594 -> 702
    //   1299: aload_0
    //   1300: getfield 431	com/google/android/gms/internal/ads/zzlc:zzasu	Lcom/google/android/gms/internal/ads/zzld;
    //   1303: getfield 585	com/google/android/gms/internal/ads/zzld:zzatd	Z
    //   1306: ifeq +3025 -> 4331
    //   1309: iconst_0
    //   1310: istore 111
    //   1312: iload 111
    //   1314: aload_0
    //   1315: getfield 73	com/google/android/gms/internal/ads/zzlc:zzaro	[Lcom/google/android/gms/internal/ads/zzlo;
    //   1318: arraylength
    //   1319: if_icmpge -699 -> 620
    //   1322: aload_0
    //   1323: getfield 73	com/google/android/gms/internal/ads/zzlc:zzaro	[Lcom/google/android/gms/internal/ads/zzlo;
    //   1326: iload 111
    //   1328: aaload
    //   1329: astore 112
    //   1331: aload_0
    //   1332: getfield 431	com/google/android/gms/internal/ads/zzlc:zzasu	Lcom/google/android/gms/internal/ads/zzld;
    //   1335: getfield 336	com/google/android/gms/internal/ads/zzld:zzasy	[Lcom/google/android/gms/internal/ads/zzqw;
    //   1338: iload 111
    //   1340: aaload
    //   1341: astore 113
    //   1343: aload 113
    //   1345: ifnull +2980 -> 4325
    //   1348: aload 112
    //   1350: invokeinterface 402 1 0
    //   1355: aload 113
    //   1357: if_acmpne +2968 -> 4325
    //   1360: aload 112
    //   1362: invokeinterface 512 1 0
    //   1367: ifeq +2958 -> 4325
    //   1370: aload 112
    //   1372: invokeinterface 629 1 0
    //   1377: goto +2948 -> 4325
    //   1380: iload 134
    //   1382: aload_0
    //   1383: getfield 73	com/google/android/gms/internal/ads/zzlc:zzaro	[Lcom/google/android/gms/internal/ads/zzlo;
    //   1386: arraylength
    //   1387: if_icmpge +54 -> 1441
    //   1390: aload_0
    //   1391: getfield 73	com/google/android/gms/internal/ads/zzlc:zzaro	[Lcom/google/android/gms/internal/ads/zzlo;
    //   1394: iload 134
    //   1396: aaload
    //   1397: astore 145
    //   1399: aload_0
    //   1400: getfield 431	com/google/android/gms/internal/ads/zzlc:zzasu	Lcom/google/android/gms/internal/ads/zzld;
    //   1403: getfield 336	com/google/android/gms/internal/ads/zzld:zzasy	[Lcom/google/android/gms/internal/ads/zzqw;
    //   1406: iload 134
    //   1408: aaload
    //   1409: astore 146
    //   1411: aload 145
    //   1413: invokeinterface 402 1 0
    //   1418: aload 146
    //   1420: if_acmpne -800 -> 620
    //   1423: aload 146
    //   1425: ifnull +2912 -> 4337
    //   1428: aload 145
    //   1430: invokeinterface 512 1 0
    //   1435: ifeq -815 -> 620
    //   1438: goto +2899 -> 4337
    //   1441: aload_0
    //   1442: getfield 431	com/google/android/gms/internal/ads/zzlc:zzasu	Lcom/google/android/gms/internal/ads/zzld;
    //   1445: getfield 275	com/google/android/gms/internal/ads/zzld:zzatf	Lcom/google/android/gms/internal/ads/zzld;
    //   1448: ifnull -828 -> 620
    //   1451: aload_0
    //   1452: getfield 431	com/google/android/gms/internal/ads/zzlc:zzasu	Lcom/google/android/gms/internal/ads/zzld;
    //   1455: getfield 275	com/google/android/gms/internal/ads/zzld:zzatf	Lcom/google/android/gms/internal/ads/zzld;
    //   1458: getfield 437	com/google/android/gms/internal/ads/zzld:zzacs	Z
    //   1461: ifeq -841 -> 620
    //   1464: aload_0
    //   1465: getfield 431	com/google/android/gms/internal/ads/zzlc:zzasu	Lcom/google/android/gms/internal/ads/zzld;
    //   1468: getfield 305	com/google/android/gms/internal/ads/zzld:zzatg	Lcom/google/android/gms/internal/ads/zzrr;
    //   1471: astore 135
    //   1473: aload_0
    //   1474: aload_0
    //   1475: getfield 431	com/google/android/gms/internal/ads/zzlc:zzasu	Lcom/google/android/gms/internal/ads/zzld;
    //   1478: getfield 275	com/google/android/gms/internal/ads/zzld:zzatf	Lcom/google/android/gms/internal/ads/zzld;
    //   1481: putfield 431	com/google/android/gms/internal/ads/zzlc:zzasu	Lcom/google/android/gms/internal/ads/zzld;
    //   1484: aload_0
    //   1485: getfield 431	com/google/android/gms/internal/ads/zzlc:zzasu	Lcom/google/android/gms/internal/ads/zzld;
    //   1488: getfield 305	com/google/android/gms/internal/ads/zzld:zzatg	Lcom/google/android/gms/internal/ads/zzrr;
    //   1491: astore 136
    //   1493: aload_0
    //   1494: getfield 431	com/google/android/gms/internal/ads/zzlc:zzasu	Lcom/google/android/gms/internal/ads/zzld;
    //   1497: getfield 446	com/google/android/gms/internal/ads/zzld:zzasw	Lcom/google/android/gms/internal/ads/zzqj;
    //   1500: invokeinterface 485 1 0
    //   1505: ldc2_w 240
    //   1508: lcmp
    //   1509: ifeq +2840 -> 4349
    //   1512: iconst_1
    //   1513: istore 137
    //   1515: goto +2828 -> 4343
    //   1518: iload 138
    //   1520: aload_0
    //   1521: getfield 73	com/google/android/gms/internal/ads/zzlc:zzaro	[Lcom/google/android/gms/internal/ads/zzlo;
    //   1524: arraylength
    //   1525: if_icmpge -905 -> 620
    //   1528: aload_0
    //   1529: getfield 73	com/google/android/gms/internal/ads/zzlc:zzaro	[Lcom/google/android/gms/internal/ads/zzlo;
    //   1532: iload 138
    //   1534: aaload
    //   1535: astore 139
    //   1537: aload 135
    //   1539: getfield 311	com/google/android/gms/internal/ads/zzrr:zzblz	Lcom/google/android/gms/internal/ads/zzro;
    //   1542: iload 138
    //   1544: invokevirtual 317	com/google/android/gms/internal/ads/zzro:zzbi	(I)Lcom/google/android/gms/internal/ads/zzrm;
    //   1547: ifnull +2808 -> 4355
    //   1550: iload 137
    //   1552: ifne +132 -> 1684
    //   1555: aload 139
    //   1557: invokeinterface 398 1 0
    //   1562: ifne +2793 -> 4355
    //   1565: aload 136
    //   1567: getfield 311	com/google/android/gms/internal/ads/zzrr:zzblz	Lcom/google/android/gms/internal/ads/zzro;
    //   1570: iload 138
    //   1572: invokevirtual 317	com/google/android/gms/internal/ads/zzro:zzbi	(I)Lcom/google/android/gms/internal/ads/zzrm;
    //   1575: astore 140
    //   1577: aload 135
    //   1579: getfield 321	com/google/android/gms/internal/ads/zzrr:zzbmb	[Lcom/google/android/gms/internal/ads/zzlq;
    //   1582: iload 138
    //   1584: aaload
    //   1585: astore 141
    //   1587: aload 136
    //   1589: getfield 321	com/google/android/gms/internal/ads/zzrr:zzbmb	[Lcom/google/android/gms/internal/ads/zzlq;
    //   1592: iload 138
    //   1594: aaload
    //   1595: astore 142
    //   1597: aload 140
    //   1599: ifnull +85 -> 1684
    //   1602: aload 142
    //   1604: aload 141
    //   1606: invokevirtual 635	com/google/android/gms/internal/ads/zzlq:equals	(Ljava/lang/Object;)Z
    //   1609: ifeq +75 -> 1684
    //   1612: aload 140
    //   1614: invokeinterface 326 1 0
    //   1619: anewarray 328	com/google/android/gms/internal/ads/zzlh
    //   1622: astore 143
    //   1624: iconst_0
    //   1625: istore 144
    //   1627: iload 144
    //   1629: aload 143
    //   1631: arraylength
    //   1632: if_icmpge +23 -> 1655
    //   1635: aload 143
    //   1637: iload 144
    //   1639: aload 140
    //   1641: iload 144
    //   1643: invokeinterface 332 2 0
    //   1648: aastore
    //   1649: iinc 144 1
    //   1652: goto -25 -> 1627
    //   1655: aload 139
    //   1657: aload 143
    //   1659: aload_0
    //   1660: getfield 431	com/google/android/gms/internal/ads/zzlc:zzasu	Lcom/google/android/gms/internal/ads/zzld;
    //   1663: getfield 336	com/google/android/gms/internal/ads/zzld:zzasy	[Lcom/google/android/gms/internal/ads/zzqw;
    //   1666: iload 138
    //   1668: aaload
    //   1669: aload_0
    //   1670: getfield 431	com/google/android/gms/internal/ads/zzlc:zzasu	Lcom/google/android/gms/internal/ads/zzld;
    //   1673: invokevirtual 342	com/google/android/gms/internal/ads/zzld:zzgz	()J
    //   1676: invokeinterface 638 5 0
    //   1681: goto +2674 -> 4355
    //   1684: aload 139
    //   1686: invokeinterface 629 1 0
    //   1691: goto +2664 -> 4355
    //   1694: ldc_w 640
    //   1697: invokestatic 645	com/google/android/gms/internal/ads/zzsx:beginSection	(Ljava/lang/String;)V
    //   1700: aload_0
    //   1701: invokespecial 569	com/google/android/gms/internal/ads/zzlc:zzgw	()V
    //   1704: aload_0
    //   1705: getfield 301	com/google/android/gms/internal/ads/zzlc:zzasv	Lcom/google/android/gms/internal/ads/zzld;
    //   1708: getfield 446	com/google/android/gms/internal/ads/zzld:zzasw	Lcom/google/android/gms/internal/ads/zzqj;
    //   1711: aload_0
    //   1712: getfield 87	com/google/android/gms/internal/ads/zzlc:zzasd	Lcom/google/android/gms/internal/ads/zzle;
    //   1715: getfield 481	com/google/android/gms/internal/ads/zzle:zzacl	J
    //   1718: invokeinterface 648 3 0
    //   1723: iconst_1
    //   1724: istore 114
    //   1726: aload_0
    //   1727: getfield 110	com/google/android/gms/internal/ads/zzlc:zzasp	[Lcom/google/android/gms/internal/ads/zzlo;
    //   1730: astore 115
    //   1732: aload 115
    //   1734: arraylength
    //   1735: istore 116
    //   1737: iconst_0
    //   1738: istore 117
    //   1740: iconst_1
    //   1741: istore 118
    //   1743: iload 117
    //   1745: iload 116
    //   1747: if_icmpge +81 -> 1828
    //   1750: aload 115
    //   1752: iload 117
    //   1754: aaload
    //   1755: astore 119
    //   1757: aload 119
    //   1759: aload_0
    //   1760: getfield 338	com/google/android/gms/internal/ads/zzlc:zzass	J
    //   1763: aload_0
    //   1764: getfield 489	com/google/android/gms/internal/ads/zzlc:zzacj	J
    //   1767: invokeinterface 650 5 0
    //   1772: iload 114
    //   1774: ifeq +2612 -> 4386
    //   1777: aload 119
    //   1779: invokeinterface 499 1 0
    //   1784: ifeq +2602 -> 4386
    //   1787: iconst_1
    //   1788: istore 114
    //   1790: aload 119
    //   1792: invokeinterface 653 1 0
    //   1797: ifne +2564 -> 4361
    //   1800: aload 119
    //   1802: invokeinterface 499 1 0
    //   1807: ifeq +2585 -> 4392
    //   1810: goto +2551 -> 4361
    //   1813: iload 120
    //   1815: ifne +2552 -> 4367
    //   1818: aload 119
    //   1820: invokeinterface 656 1 0
    //   1825: goto +2542 -> 4367
    //   1828: iload 118
    //   1830: ifne +7 -> 1837
    //   1833: aload_0
    //   1834: invokespecial 592	com/google/android/gms/internal/ads/zzlc:zzgx	()V
    //   1837: aload_0
    //   1838: getfield 351	com/google/android/gms/internal/ads/zzlc:zzasn	Lcom/google/android/gms/internal/ads/zzso;
    //   1841: ifnull +57 -> 1898
    //   1844: aload_0
    //   1845: getfield 351	com/google/android/gms/internal/ads/zzlc:zzasn	Lcom/google/android/gms/internal/ads/zzso;
    //   1848: invokeinterface 660 1 0
    //   1853: astore 133
    //   1855: aload 133
    //   1857: aload_0
    //   1858: getfield 133	com/google/android/gms/internal/ads/zzlc:zzasc	Lcom/google/android/gms/internal/ads/zzln;
    //   1861: invokevirtual 661	com/google/android/gms/internal/ads/zzln:equals	(Ljava/lang/Object;)Z
    //   1864: ifne +34 -> 1898
    //   1867: aload_0
    //   1868: aload 133
    //   1870: putfield 133	com/google/android/gms/internal/ads/zzlc:zzasc	Lcom/google/android/gms/internal/ads/zzln;
    //   1873: aload_0
    //   1874: getfield 108	com/google/android/gms/internal/ads/zzlc:zzask	Lcom/google/android/gms/internal/ads/zzsw;
    //   1877: aload_0
    //   1878: getfield 351	com/google/android/gms/internal/ads/zzlc:zzasn	Lcom/google/android/gms/internal/ads/zzso;
    //   1881: invokevirtual 405	com/google/android/gms/internal/ads/zzsw:zza	(Lcom/google/android/gms/internal/ads/zzso;)V
    //   1884: aload_0
    //   1885: getfield 83	com/google/android/gms/internal/ads/zzlc:zzabq	Landroid/os/Handler;
    //   1888: bipush 7
    //   1890: aload 133
    //   1892: invokevirtual 413	android/os/Handler:obtainMessage	(ILjava/lang/Object;)Landroid/os/Message;
    //   1895: invokevirtual 166	android/os/Message:sendToTarget	()V
    //   1898: aload_0
    //   1899: getfield 199	com/google/android/gms/internal/ads/zzlc:zzary	Lcom/google/android/gms/internal/ads/zzlr;
    //   1902: aload_0
    //   1903: getfield 301	com/google/android/gms/internal/ads/zzlc:zzasv	Lcom/google/android/gms/internal/ads/zzld;
    //   1906: getfield 434	com/google/android/gms/internal/ads/zzld:zzatb	I
    //   1909: aload_0
    //   1910: getfield 120	com/google/android/gms/internal/ads/zzlc:zzart	Lcom/google/android/gms/internal/ads/zzlt;
    //   1913: iconst_0
    //   1914: invokevirtual 179	com/google/android/gms/internal/ads/zzlr:zza	(ILcom/google/android/gms/internal/ads/zzlt;Z)Lcom/google/android/gms/internal/ads/zzlt;
    //   1917: getfield 494	com/google/android/gms/internal/ads/zzlt:zzack	J
    //   1920: lstore 121
    //   1922: iload 114
    //   1924: ifeq +89 -> 2013
    //   1927: lload 121
    //   1929: ldc2_w 240
    //   1932: lcmp
    //   1933: ifeq +16 -> 1949
    //   1936: lload 121
    //   1938: aload_0
    //   1939: getfield 87	com/google/android/gms/internal/ads/zzlc:zzasd	Lcom/google/android/gms/internal/ads/zzle;
    //   1942: getfield 481	com/google/android/gms/internal/ads/zzle:zzacl	J
    //   1945: lcmp
    //   1946: ifgt +67 -> 2013
    //   1949: aload_0
    //   1950: getfield 301	com/google/android/gms/internal/ads/zzlc:zzasv	Lcom/google/android/gms/internal/ads/zzld;
    //   1953: getfield 585	com/google/android/gms/internal/ads/zzld:zzatd	Z
    //   1956: ifeq +57 -> 2013
    //   1959: aload_0
    //   1960: iconst_4
    //   1961: invokespecial 294	com/google/android/gms/internal/ads/zzlc:setState	(I)V
    //   1964: aload_0
    //   1965: invokespecial 425	com/google/android/gms/internal/ads/zzlc:zzdq	()V
    //   1968: aload_0
    //   1969: getfield 85	com/google/android/gms/internal/ads/zzlc:state	I
    //   1972: iconst_2
    //   1973: if_icmpne +278 -> 2251
    //   1976: aload_0
    //   1977: getfield 110	com/google/android/gms/internal/ads/zzlc:zzasp	[Lcom/google/android/gms/internal/ads/zzlo;
    //   1980: astore 123
    //   1982: aload 123
    //   1984: arraylength
    //   1985: istore 124
    //   1987: iconst_0
    //   1988: istore 125
    //   1990: iload 125
    //   1992: iload 124
    //   1994: if_icmpge +257 -> 2251
    //   1997: aload 123
    //   1999: iload 125
    //   2001: aaload
    //   2002: invokeinterface 656 1 0
    //   2007: iinc 125 1
    //   2010: goto -20 -> 1990
    //   2013: aload_0
    //   2014: getfield 85	com/google/android/gms/internal/ads/zzlc:state	I
    //   2017: iconst_2
    //   2018: if_icmpne +181 -> 2199
    //   2021: aload_0
    //   2022: getfield 110	com/google/android/gms/internal/ads/zzlc:zzasp	[Lcom/google/android/gms/internal/ads/zzlo;
    //   2025: arraylength
    //   2026: ifle +162 -> 2188
    //   2029: iload 118
    //   2031: ifeq +2384 -> 4415
    //   2034: aload_0
    //   2035: getfield 427	com/google/android/gms/internal/ads/zzlc:zzacg	Z
    //   2038: istore 126
    //   2040: aload_0
    //   2041: getfield 429	com/google/android/gms/internal/ads/zzlc:zzast	Lcom/google/android/gms/internal/ads/zzld;
    //   2044: getfield 437	com/google/android/gms/internal/ads/zzld:zzacs	Z
    //   2047: ifne +61 -> 2108
    //   2050: aload_0
    //   2051: getfield 429	com/google/android/gms/internal/ads/zzlc:zzast	Lcom/google/android/gms/internal/ads/zzld;
    //   2054: getfield 606	com/google/android/gms/internal/ads/zzld:zzatc	J
    //   2057: lstore 127
    //   2059: lload 127
    //   2061: ldc2_w 490
    //   2064: lcmp
    //   2065: ifne +84 -> 2149
    //   2068: aload_0
    //   2069: getfield 429	com/google/android/gms/internal/ads/zzlc:zzast	Lcom/google/android/gms/internal/ads/zzld;
    //   2072: getfield 585	com/google/android/gms/internal/ads/zzld:zzatd	Z
    //   2075: ifeq +50 -> 2125
    //   2078: iconst_1
    //   2079: istore 129
    //   2081: goto +2323 -> 4404
    //   2084: iload 130
    //   2086: ifeq -118 -> 1968
    //   2089: aload_0
    //   2090: iconst_3
    //   2091: invokespecial 294	com/google/android/gms/internal/ads/zzlc:setState	(I)V
    //   2094: aload_0
    //   2095: getfield 79	com/google/android/gms/internal/ads/zzlc:zzabu	Z
    //   2098: ifeq -130 -> 1968
    //   2101: aload_0
    //   2102: invokespecial 571	com/google/android/gms/internal/ads/zzlc:zzdp	()V
    //   2105: goto -137 -> 1968
    //   2108: aload_0
    //   2109: getfield 429	com/google/android/gms/internal/ads/zzlc:zzast	Lcom/google/android/gms/internal/ads/zzld;
    //   2112: getfield 446	com/google/android/gms/internal/ads/zzld:zzasw	Lcom/google/android/gms/internal/ads/zzqj;
    //   2115: invokeinterface 506 1 0
    //   2120: lstore 127
    //   2122: goto -63 -> 2059
    //   2125: aload_0
    //   2126: getfield 199	com/google/android/gms/internal/ads/zzlc:zzary	Lcom/google/android/gms/internal/ads/zzlr;
    //   2129: aload_0
    //   2130: getfield 429	com/google/android/gms/internal/ads/zzlc:zzast	Lcom/google/android/gms/internal/ads/zzld;
    //   2133: getfield 434	com/google/android/gms/internal/ads/zzld:zzatb	I
    //   2136: aload_0
    //   2137: getfield 120	com/google/android/gms/internal/ads/zzlc:zzart	Lcom/google/android/gms/internal/ads/zzlt;
    //   2140: iconst_0
    //   2141: invokevirtual 179	com/google/android/gms/internal/ads/zzlr:zza	(ILcom/google/android/gms/internal/ads/zzlt;Z)Lcom/google/android/gms/internal/ads/zzlt;
    //   2144: getfield 494	com/google/android/gms/internal/ads/zzlt:zzack	J
    //   2147: lstore 127
    //   2149: aload_0
    //   2150: getfield 77	com/google/android/gms/internal/ads/zzlc:zzasj	Lcom/google/android/gms/internal/ads/zzll;
    //   2153: astore 131
    //   2155: aload_0
    //   2156: getfield 429	com/google/android/gms/internal/ads/zzlc:zzast	Lcom/google/android/gms/internal/ads/zzld;
    //   2159: astore 132
    //   2161: aload 131
    //   2163: lload 127
    //   2165: aload_0
    //   2166: getfield 338	com/google/android/gms/internal/ads/zzlc:zzass	J
    //   2169: aload 132
    //   2171: invokevirtual 342	com/google/android/gms/internal/ads/zzld:zzgz	()J
    //   2174: lsub
    //   2175: lsub
    //   2176: iload 126
    //   2178: invokeinterface 665 4 0
    //   2183: istore 129
    //   2185: goto +2219 -> 4404
    //   2188: aload_0
    //   2189: lload 121
    //   2191: invokespecial 667	com/google/android/gms/internal/ads/zzlc:zzec	(J)Z
    //   2194: istore 130
    //   2196: goto -112 -> 2084
    //   2199: aload_0
    //   2200: getfield 85	com/google/android/gms/internal/ads/zzlc:state	I
    //   2203: iconst_3
    //   2204: if_icmpne -236 -> 1968
    //   2207: aload_0
    //   2208: getfield 110	com/google/android/gms/internal/ads/zzlc:zzasp	[Lcom/google/android/gms/internal/ads/zzlo;
    //   2211: arraylength
    //   2212: ifle +28 -> 2240
    //   2215: iload 118
    //   2217: ifne -249 -> 1968
    //   2220: aload_0
    //   2221: aload_0
    //   2222: getfield 79	com/google/android/gms/internal/ads/zzlc:zzabu	Z
    //   2225: putfield 427	com/google/android/gms/internal/ads/zzlc:zzacg	Z
    //   2228: aload_0
    //   2229: iconst_2
    //   2230: invokespecial 294	com/google/android/gms/internal/ads/zzlc:setState	(I)V
    //   2233: aload_0
    //   2234: invokespecial 425	com/google/android/gms/internal/ads/zzlc:zzdq	()V
    //   2237: goto -269 -> 1968
    //   2240: aload_0
    //   2241: lload 121
    //   2243: invokespecial 667	com/google/android/gms/internal/ads/zzlc:zzec	(J)Z
    //   2246: istore 118
    //   2248: goto -33 -> 2215
    //   2251: aload_0
    //   2252: getfield 79	com/google/android/gms/internal/ads/zzlc:zzabu	Z
    //   2255: ifeq +11 -> 2266
    //   2258: aload_0
    //   2259: getfield 85	com/google/android/gms/internal/ads/zzlc:state	I
    //   2262: iconst_3
    //   2263: if_icmpeq +11 -> 2274
    //   2266: aload_0
    //   2267: getfield 85	com/google/android/gms/internal/ads/zzlc:state	I
    //   2270: iconst_2
    //   2271: if_icmpne +18 -> 2289
    //   2274: aload_0
    //   2275: lload 94
    //   2277: ldc2_w 593
    //   2280: invokespecial 596	com/google/android/gms/internal/ads/zzlc:zzb	(JJ)V
    //   2283: invokestatic 670	com/google/android/gms/internal/ads/zzsx:endSection	()V
    //   2286: goto +2037 -> 4323
    //   2289: aload_0
    //   2290: getfield 110	com/google/android/gms/internal/ads/zzlc:zzasp	[Lcom/google/android/gms/internal/ads/zzlo;
    //   2293: arraylength
    //   2294: ifeq +15 -> 2309
    //   2297: aload_0
    //   2298: lload 94
    //   2300: ldc2_w 486
    //   2303: invokespecial 596	com/google/android/gms/internal/ads/zzlc:zzb	(JJ)V
    //   2306: goto -23 -> 2283
    //   2309: aload_0
    //   2310: getfield 156	com/google/android/gms/internal/ads/zzlc:handler	Landroid/os/Handler;
    //   2313: iconst_2
    //   2314: invokevirtual 383	android/os/Handler:removeMessages	(I)V
    //   2317: goto -34 -> 2283
    //   2320: aload_1
    //   2321: getfield 558	android/os/Message:obj	Ljava/lang/Object;
    //   2324: checkcast 192	com/google/android/gms/internal/ads/zzlf
    //   2327: astore 73
    //   2329: aload_0
    //   2330: getfield 199	com/google/android/gms/internal/ads/zzlc:zzary	Lcom/google/android/gms/internal/ads/zzlr;
    //   2333: ifnonnull +22 -> 2355
    //   2336: aload_0
    //   2337: iconst_1
    //   2338: aload_0
    //   2339: getfield 672	com/google/android/gms/internal/ads/zzlc:zzasq	I
    //   2342: iadd
    //   2343: putfield 672	com/google/android/gms/internal/ads/zzlc:zzasq	I
    //   2346: aload_0
    //   2347: aload 73
    //   2349: putfield 674	com/google/android/gms/internal/ads/zzlc:zzasr	Lcom/google/android/gms/internal/ads/zzlf;
    //   2352: goto +2069 -> 4421
    //   2355: aload_0
    //   2356: aload 73
    //   2358: invokespecial 676	com/google/android/gms/internal/ads/zzlc:zza	(Lcom/google/android/gms/internal/ads/zzlf;)Landroid/util/Pair;
    //   2361: astore 74
    //   2363: aload 74
    //   2365: ifnonnull +61 -> 2426
    //   2368: aload_0
    //   2369: new 287	com/google/android/gms/internal/ads/zzle
    //   2372: dup
    //   2373: iconst_0
    //   2374: lconst_0
    //   2375: invokespecial 290	com/google/android/gms/internal/ads/zzle:<init>	(IJ)V
    //   2378: putfield 87	com/google/android/gms/internal/ads/zzlc:zzasd	Lcom/google/android/gms/internal/ads/zzle;
    //   2381: aload_0
    //   2382: getfield 83	com/google/android/gms/internal/ads/zzlc:zzabq	Landroid/os/Handler;
    //   2385: iconst_4
    //   2386: iconst_1
    //   2387: iconst_0
    //   2388: aload_0
    //   2389: getfield 87	com/google/android/gms/internal/ads/zzlc:zzasd	Lcom/google/android/gms/internal/ads/zzle;
    //   2392: invokevirtual 679	android/os/Handler:obtainMessage	(IIILjava/lang/Object;)Landroid/os/Message;
    //   2395: invokevirtual 166	android/os/Message:sendToTarget	()V
    //   2398: aload_0
    //   2399: new 287	com/google/android/gms/internal/ads/zzle
    //   2402: dup
    //   2403: iconst_0
    //   2404: ldc2_w 240
    //   2407: invokespecial 290	com/google/android/gms/internal/ads/zzle:<init>	(IJ)V
    //   2410: putfield 87	com/google/android/gms/internal/ads/zzlc:zzasd	Lcom/google/android/gms/internal/ads/zzle;
    //   2413: aload_0
    //   2414: iconst_4
    //   2415: invokespecial 294	com/google/android/gms/internal/ads/zzlc:setState	(I)V
    //   2418: aload_0
    //   2419: iconst_0
    //   2420: invokespecial 298	com/google/android/gms/internal/ads/zzlc:zzj	(Z)V
    //   2423: goto +1998 -> 4421
    //   2426: aload 73
    //   2428: getfield 205	com/google/android/gms/internal/ads/zzlf:zzatj	J
    //   2431: ldc2_w 240
    //   2434: lcmp
    //   2435: ifne +121 -> 2556
    //   2438: iconst_1
    //   2439: istore 75
    //   2441: aload 74
    //   2443: getfield 219	android/util/Pair:first	Ljava/lang/Object;
    //   2446: checkcast 221	java/lang/Integer
    //   2449: invokevirtual 224	java/lang/Integer:intValue	()I
    //   2452: istore 76
    //   2454: aload 74
    //   2456: getfield 231	android/util/Pair:second	Ljava/lang/Object;
    //   2459: checkcast 233	java/lang/Long
    //   2462: invokevirtual 626	java/lang/Long:longValue	()J
    //   2465: lstore 77
    //   2467: iload 76
    //   2469: aload_0
    //   2470: getfield 87	com/google/android/gms/internal/ads/zzlc:zzasd	Lcom/google/android/gms/internal/ads/zzle;
    //   2473: getfield 597	com/google/android/gms/internal/ads/zzle:zzatb	I
    //   2476: if_icmpne +92 -> 2568
    //   2479: lload 77
    //   2481: ldc2_w 486
    //   2484: ldiv
    //   2485: lstore 88
    //   2487: aload_0
    //   2488: getfield 87	com/google/android/gms/internal/ads/zzlc:zzasd	Lcom/google/android/gms/internal/ads/zzle;
    //   2491: getfield 481	com/google/android/gms/internal/ads/zzle:zzacl	J
    //   2494: ldc2_w 486
    //   2497: ldiv
    //   2498: lstore 90
    //   2500: lload 88
    //   2502: lload 90
    //   2504: lcmp
    //   2505: ifne +63 -> 2568
    //   2508: aload_0
    //   2509: new 287	com/google/android/gms/internal/ads/zzle
    //   2512: dup
    //   2513: iload 76
    //   2515: lload 77
    //   2517: invokespecial 290	com/google/android/gms/internal/ads/zzle:<init>	(IJ)V
    //   2520: putfield 87	com/google/android/gms/internal/ads/zzlc:zzasd	Lcom/google/android/gms/internal/ads/zzle;
    //   2523: aload_0
    //   2524: getfield 83	com/google/android/gms/internal/ads/zzlc:zzabq	Landroid/os/Handler;
    //   2527: astore 92
    //   2529: iload 75
    //   2531: ifeq +31 -> 2562
    //   2534: iconst_1
    //   2535: istore 93
    //   2537: aload 92
    //   2539: iconst_4
    //   2540: iload 93
    //   2542: iconst_0
    //   2543: aload_0
    //   2544: getfield 87	com/google/android/gms/internal/ads/zzlc:zzasd	Lcom/google/android/gms/internal/ads/zzle;
    //   2547: invokevirtual 679	android/os/Handler:obtainMessage	(IIILjava/lang/Object;)Landroid/os/Message;
    //   2550: invokevirtual 166	android/os/Message:sendToTarget	()V
    //   2553: goto +1868 -> 4421
    //   2556: iconst_0
    //   2557: istore 75
    //   2559: goto -118 -> 2441
    //   2562: iconst_0
    //   2563: istore 93
    //   2565: goto -28 -> 2537
    //   2568: aload_0
    //   2569: iload 76
    //   2571: lload 77
    //   2573: invokespecial 587	com/google/android/gms/internal/ads/zzlc:zzd	(IJ)J
    //   2576: lstore 82
    //   2578: lload 77
    //   2580: lload 82
    //   2582: lcmp
    //   2583: ifeq +1840 -> 4423
    //   2586: iconst_1
    //   2587: istore 84
    //   2589: iload 84
    //   2591: iload 75
    //   2593: ior
    //   2594: istore 85
    //   2596: aload_0
    //   2597: new 287	com/google/android/gms/internal/ads/zzle
    //   2600: dup
    //   2601: iload 76
    //   2603: lload 82
    //   2605: invokespecial 290	com/google/android/gms/internal/ads/zzle:<init>	(IJ)V
    //   2608: putfield 87	com/google/android/gms/internal/ads/zzlc:zzasd	Lcom/google/android/gms/internal/ads/zzle;
    //   2611: aload_0
    //   2612: getfield 83	com/google/android/gms/internal/ads/zzlc:zzabq	Landroid/os/Handler;
    //   2615: astore 86
    //   2617: iload 85
    //   2619: ifeq +1810 -> 4429
    //   2622: iconst_1
    //   2623: istore 87
    //   2625: aload 86
    //   2627: iconst_4
    //   2628: iload 87
    //   2630: iconst_0
    //   2631: aload_0
    //   2632: getfield 87	com/google/android/gms/internal/ads/zzlc:zzasd	Lcom/google/android/gms/internal/ads/zzle;
    //   2635: invokevirtual 679	android/os/Handler:obtainMessage	(IIILjava/lang/Object;)Landroid/os/Message;
    //   2638: invokevirtual 166	android/os/Message:sendToTarget	()V
    //   2641: goto +1780 -> 4421
    //   2644: astore 79
    //   2646: aload_0
    //   2647: new 287	com/google/android/gms/internal/ads/zzle
    //   2650: dup
    //   2651: iload 76
    //   2653: lload 77
    //   2655: invokespecial 290	com/google/android/gms/internal/ads/zzle:<init>	(IJ)V
    //   2658: putfield 87	com/google/android/gms/internal/ads/zzlc:zzasd	Lcom/google/android/gms/internal/ads/zzle;
    //   2661: aload_0
    //   2662: getfield 83	com/google/android/gms/internal/ads/zzlc:zzabq	Landroid/os/Handler;
    //   2665: astore 80
    //   2667: iload 75
    //   2669: ifeq +1766 -> 4435
    //   2672: iconst_1
    //   2673: istore 81
    //   2675: aload 80
    //   2677: iconst_4
    //   2678: iload 81
    //   2680: iconst_0
    //   2681: aload_0
    //   2682: getfield 87	com/google/android/gms/internal/ads/zzlc:zzasd	Lcom/google/android/gms/internal/ads/zzle;
    //   2685: invokevirtual 679	android/os/Handler:obtainMessage	(IIILjava/lang/Object;)Landroid/os/Message;
    //   2688: invokevirtual 166	android/os/Message:sendToTarget	()V
    //   2691: aload 79
    //   2693: athrow
    //   2694: aload_1
    //   2695: getfield 558	android/os/Message:obj	Ljava/lang/Object;
    //   2698: checkcast 128	com/google/android/gms/internal/ads/zzln
    //   2701: astore 71
    //   2703: aload_0
    //   2704: getfield 351	com/google/android/gms/internal/ads/zzlc:zzasn	Lcom/google/android/gms/internal/ads/zzso;
    //   2707: ifnull +38 -> 2745
    //   2710: aload_0
    //   2711: getfield 351	com/google/android/gms/internal/ads/zzlc:zzasn	Lcom/google/android/gms/internal/ads/zzso;
    //   2714: aload 71
    //   2716: invokeinterface 368 2 0
    //   2721: astore 72
    //   2723: aload_0
    //   2724: aload 72
    //   2726: putfield 133	com/google/android/gms/internal/ads/zzlc:zzasc	Lcom/google/android/gms/internal/ads/zzln;
    //   2729: aload_0
    //   2730: getfield 83	com/google/android/gms/internal/ads/zzlc:zzabq	Landroid/os/Handler;
    //   2733: bipush 7
    //   2735: aload 72
    //   2737: invokevirtual 413	android/os/Handler:obtainMessage	(ILjava/lang/Object;)Landroid/os/Message;
    //   2740: invokevirtual 166	android/os/Message:sendToTarget	()V
    //   2743: iconst_1
    //   2744: ireturn
    //   2745: aload_0
    //   2746: getfield 108	com/google/android/gms/internal/ads/zzlc:zzask	Lcom/google/android/gms/internal/ads/zzsw;
    //   2749: aload 71
    //   2751: invokevirtual 680	com/google/android/gms/internal/ads/zzsw:zzb	(Lcom/google/android/gms/internal/ads/zzln;)Lcom/google/android/gms/internal/ads/zzln;
    //   2754: astore 72
    //   2756: goto -33 -> 2723
    //   2759: aload_0
    //   2760: invokespecial 575	com/google/android/gms/internal/ads/zzlc:zzds	()V
    //   2763: iconst_1
    //   2764: ireturn
    //   2765: aload_0
    //   2766: iconst_1
    //   2767: invokespecial 298	com/google/android/gms/internal/ads/zzlc:zzj	(Z)V
    //   2770: aload_0
    //   2771: getfield 77	com/google/android/gms/internal/ads/zzlc:zzasj	Lcom/google/android/gms/internal/ads/zzll;
    //   2774: invokeinterface 682 1 0
    //   2779: aload_0
    //   2780: iconst_1
    //   2781: invokespecial 294	com/google/android/gms/internal/ads/zzlc:setState	(I)V
    //   2784: aload_0
    //   2785: monitorenter
    //   2786: aload_0
    //   2787: iconst_1
    //   2788: putfield 684	com/google/android/gms/internal/ads/zzlc:zzacf	Z
    //   2791: aload_0
    //   2792: invokevirtual 687	java/lang/Object:notifyAll	()V
    //   2795: aload_0
    //   2796: monitorexit
    //   2797: iconst_1
    //   2798: ireturn
    //   2799: astore 70
    //   2801: aload_0
    //   2802: monitorexit
    //   2803: aload 70
    //   2805: athrow
    //   2806: aload_1
    //   2807: getfield 558	android/os/Message:obj	Ljava/lang/Object;
    //   2810: checkcast 448	com/google/android/gms/internal/ads/zzqj
    //   2813: astore 67
    //   2815: aload_0
    //   2816: getfield 429	com/google/android/gms/internal/ads/zzlc:zzast	Lcom/google/android/gms/internal/ads/zzld;
    //   2819: ifnull +1622 -> 4441
    //   2822: aload_0
    //   2823: getfield 429	com/google/android/gms/internal/ads/zzlc:zzast	Lcom/google/android/gms/internal/ads/zzld;
    //   2826: getfield 446	com/google/android/gms/internal/ads/zzld:zzasw	Lcom/google/android/gms/internal/ads/zzqj;
    //   2829: aload 67
    //   2831: if_acmpeq +6 -> 2837
    //   2834: goto +1607 -> 4441
    //   2837: aload_0
    //   2838: getfield 429	com/google/android/gms/internal/ads/zzlc:zzast	Lcom/google/android/gms/internal/ads/zzld;
    //   2841: astore 68
    //   2843: aload 68
    //   2845: iconst_1
    //   2846: putfield 437	com/google/android/gms/internal/ads/zzld:zzacs	Z
    //   2849: aload 68
    //   2851: invokevirtual 690	com/google/android/gms/internal/ads/zzld:zzhb	()Z
    //   2854: pop
    //   2855: aload 68
    //   2857: aload 68
    //   2859: aload 68
    //   2861: getfield 606	com/google/android/gms/internal/ads/zzld:zzatc	J
    //   2864: iconst_0
    //   2865: invokevirtual 693	com/google/android/gms/internal/ads/zzld:zze	(JZ)J
    //   2868: putfield 606	com/google/android/gms/internal/ads/zzld:zzatc	J
    //   2871: aload_0
    //   2872: getfield 301	com/google/android/gms/internal/ads/zzlc:zzasv	Lcom/google/android/gms/internal/ads/zzld;
    //   2875: ifnonnull +30 -> 2905
    //   2878: aload_0
    //   2879: aload_0
    //   2880: getfield 429	com/google/android/gms/internal/ads/zzlc:zzast	Lcom/google/android/gms/internal/ads/zzld;
    //   2883: putfield 431	com/google/android/gms/internal/ads/zzlc:zzasu	Lcom/google/android/gms/internal/ads/zzld;
    //   2886: aload_0
    //   2887: aload_0
    //   2888: getfield 431	com/google/android/gms/internal/ads/zzlc:zzasu	Lcom/google/android/gms/internal/ads/zzld;
    //   2891: getfield 606	com/google/android/gms/internal/ads/zzld:zzatc	J
    //   2894: invokespecial 456	com/google/android/gms/internal/ads/zzlc:zzeb	(J)V
    //   2897: aload_0
    //   2898: aload_0
    //   2899: getfield 431	com/google/android/gms/internal/ads/zzlc:zzasu	Lcom/google/android/gms/internal/ads/zzld;
    //   2902: invokespecial 439	com/google/android/gms/internal/ads/zzlc:zzb	(Lcom/google/android/gms/internal/ads/zzld;)V
    //   2905: aload_0
    //   2906: invokespecial 459	com/google/android/gms/internal/ads/zzlc:zzgy	()V
    //   2909: goto +1532 -> 4441
    //   2912: aload_1
    //   2913: getfield 558	android/os/Message:obj	Ljava/lang/Object;
    //   2916: checkcast 216	android/util/Pair
    //   2919: astore 39
    //   2921: aload_0
    //   2922: getfield 199	com/google/android/gms/internal/ads/zzlc:zzary	Lcom/google/android/gms/internal/ads/zzlr;
    //   2925: astore 40
    //   2927: aload_0
    //   2928: aload 39
    //   2930: getfield 219	android/util/Pair:first	Ljava/lang/Object;
    //   2933: checkcast 169	com/google/android/gms/internal/ads/zzlr
    //   2936: putfield 199	com/google/android/gms/internal/ads/zzlc:zzary	Lcom/google/android/gms/internal/ads/zzlr;
    //   2939: aload 39
    //   2941: getfield 231	android/util/Pair:second	Ljava/lang/Object;
    //   2944: astore 41
    //   2946: aload 40
    //   2948: ifnonnull +1497 -> 4445
    //   2951: aload_0
    //   2952: getfield 672	com/google/android/gms/internal/ads/zzlc:zzasq	I
    //   2955: ifle +154 -> 3109
    //   2958: aload_0
    //   2959: aload_0
    //   2960: getfield 674	com/google/android/gms/internal/ads/zzlc:zzasr	Lcom/google/android/gms/internal/ads/zzlf;
    //   2963: invokespecial 676	com/google/android/gms/internal/ads/zzlc:zza	(Lcom/google/android/gms/internal/ads/zzlf;)Landroid/util/Pair;
    //   2966: astore 65
    //   2968: aload_0
    //   2969: getfield 672	com/google/android/gms/internal/ads/zzlc:zzasq	I
    //   2972: istore 66
    //   2974: aload_0
    //   2975: iconst_0
    //   2976: putfield 672	com/google/android/gms/internal/ads/zzlc:zzasq	I
    //   2979: aload_0
    //   2980: aconst_null
    //   2981: putfield 674	com/google/android/gms/internal/ads/zzlc:zzasr	Lcom/google/android/gms/internal/ads/zzlf;
    //   2984: aload 65
    //   2986: ifnonnull +14 -> 3000
    //   2989: aload_0
    //   2990: aload 41
    //   2992: iload 66
    //   2994: invokespecial 695	com/google/android/gms/internal/ads/zzlc:zza	(Ljava/lang/Object;I)V
    //   2997: goto +1446 -> 4443
    //   3000: aload_0
    //   3001: new 287	com/google/android/gms/internal/ads/zzle
    //   3004: dup
    //   3005: aload 65
    //   3007: getfield 219	android/util/Pair:first	Ljava/lang/Object;
    //   3010: checkcast 221	java/lang/Integer
    //   3013: invokevirtual 224	java/lang/Integer:intValue	()I
    //   3016: aload 65
    //   3018: getfield 231	android/util/Pair:second	Ljava/lang/Object;
    //   3021: checkcast 233	java/lang/Long
    //   3024: invokevirtual 626	java/lang/Long:longValue	()J
    //   3027: invokespecial 290	com/google/android/gms/internal/ads/zzle:<init>	(IJ)V
    //   3030: putfield 87	com/google/android/gms/internal/ads/zzlc:zzasd	Lcom/google/android/gms/internal/ads/zzle;
    //   3033: iload 66
    //   3035: istore 42
    //   3037: aload_0
    //   3038: getfield 301	com/google/android/gms/internal/ads/zzlc:zzasv	Lcom/google/android/gms/internal/ads/zzld;
    //   3041: ifnull +148 -> 3189
    //   3044: aload_0
    //   3045: getfield 301	com/google/android/gms/internal/ads/zzlc:zzasv	Lcom/google/android/gms/internal/ads/zzld;
    //   3048: astore 43
    //   3050: aload 43
    //   3052: ifnull +290 -> 3342
    //   3055: aload_0
    //   3056: getfield 199	com/google/android/gms/internal/ads/zzlc:zzary	Lcom/google/android/gms/internal/ads/zzlr;
    //   3059: aload 43
    //   3061: getfield 696	com/google/android/gms/internal/ads/zzld:zzasx	Ljava/lang/Object;
    //   3064: invokevirtual 187	com/google/android/gms/internal/ads/zzlr:zzc	(Ljava/lang/Object;)I
    //   3067: istore 44
    //   3069: iload 44
    //   3071: iconst_m1
    //   3072: if_icmpne +281 -> 3353
    //   3075: aload_0
    //   3076: aload 43
    //   3078: getfield 434	com/google/android/gms/internal/ads/zzld:zzatb	I
    //   3081: aload 40
    //   3083: aload_0
    //   3084: getfield 199	com/google/android/gms/internal/ads/zzlc:zzary	Lcom/google/android/gms/internal/ads/zzlr;
    //   3087: invokespecial 239	com/google/android/gms/internal/ads/zzlc:zza	(ILcom/google/android/gms/internal/ads/zzlr;Lcom/google/android/gms/internal/ads/zzlr;)I
    //   3090: istore 45
    //   3092: iload 45
    //   3094: iconst_m1
    //   3095: if_icmpne +103 -> 3198
    //   3098: aload_0
    //   3099: aload 41
    //   3101: iload 42
    //   3103: invokespecial 695	com/google/android/gms/internal/ads/zzlc:zza	(Ljava/lang/Object;I)V
    //   3106: goto +1337 -> 4443
    //   3109: aload_0
    //   3110: getfield 87	com/google/android/gms/internal/ads/zzlc:zzasd	Lcom/google/android/gms/internal/ads/zzle;
    //   3113: getfield 697	com/google/android/gms/internal/ads/zzle:zzatc	J
    //   3116: ldc2_w 240
    //   3119: lcmp
    //   3120: ifne +1325 -> 4445
    //   3123: aload_0
    //   3124: getfield 199	com/google/android/gms/internal/ads/zzlc:zzary	Lcom/google/android/gms/internal/ads/zzlr;
    //   3127: invokevirtual 198	com/google/android/gms/internal/ads/zzlr:isEmpty	()Z
    //   3130: ifeq +13 -> 3143
    //   3133: aload_0
    //   3134: aload 41
    //   3136: iconst_0
    //   3137: invokespecial 695	com/google/android/gms/internal/ads/zzlc:zza	(Ljava/lang/Object;I)V
    //   3140: goto +1303 -> 4443
    //   3143: aload_0
    //   3144: iconst_0
    //   3145: ldc2_w 240
    //   3148: invokespecial 245	com/google/android/gms/internal/ads/zzlc:zze	(IJ)Landroid/util/Pair;
    //   3151: astore 64
    //   3153: aload_0
    //   3154: new 287	com/google/android/gms/internal/ads/zzle
    //   3157: dup
    //   3158: aload 64
    //   3160: getfield 219	android/util/Pair:first	Ljava/lang/Object;
    //   3163: checkcast 221	java/lang/Integer
    //   3166: invokevirtual 224	java/lang/Integer:intValue	()I
    //   3169: aload 64
    //   3171: getfield 231	android/util/Pair:second	Ljava/lang/Object;
    //   3174: checkcast 233	java/lang/Long
    //   3177: invokevirtual 626	java/lang/Long:longValue	()J
    //   3180: invokespecial 290	com/google/android/gms/internal/ads/zzle:<init>	(IJ)V
    //   3183: putfield 87	com/google/android/gms/internal/ads/zzlc:zzasd	Lcom/google/android/gms/internal/ads/zzle;
    //   3186: goto +1259 -> 4445
    //   3189: aload_0
    //   3190: getfield 429	com/google/android/gms/internal/ads/zzlc:zzast	Lcom/google/android/gms/internal/ads/zzld;
    //   3193: astore 43
    //   3195: goto -145 -> 3050
    //   3198: aload_0
    //   3199: getfield 199	com/google/android/gms/internal/ads/zzlc:zzary	Lcom/google/android/gms/internal/ads/zzlr;
    //   3202: iload 45
    //   3204: aload_0
    //   3205: getfield 120	com/google/android/gms/internal/ads/zzlc:zzart	Lcom/google/android/gms/internal/ads/zzlt;
    //   3208: iconst_0
    //   3209: invokevirtual 179	com/google/android/gms/internal/ads/zzlr:zza	(ILcom/google/android/gms/internal/ads/zzlt;Z)Lcom/google/android/gms/internal/ads/zzlt;
    //   3212: pop
    //   3213: aload_0
    //   3214: iconst_0
    //   3215: ldc2_w 240
    //   3218: invokespecial 245	com/google/android/gms/internal/ads/zzlc:zze	(IJ)Landroid/util/Pair;
    //   3221: astore 47
    //   3223: aload 47
    //   3225: getfield 219	android/util/Pair:first	Ljava/lang/Object;
    //   3228: checkcast 221	java/lang/Integer
    //   3231: invokevirtual 224	java/lang/Integer:intValue	()I
    //   3234: istore 48
    //   3236: aload 47
    //   3238: getfield 231	android/util/Pair:second	Ljava/lang/Object;
    //   3241: checkcast 233	java/lang/Long
    //   3244: invokevirtual 626	java/lang/Long:longValue	()J
    //   3247: lstore 49
    //   3249: aload_0
    //   3250: getfield 199	com/google/android/gms/internal/ads/zzlc:zzary	Lcom/google/android/gms/internal/ads/zzlr;
    //   3253: iload 48
    //   3255: aload_0
    //   3256: getfield 120	com/google/android/gms/internal/ads/zzlc:zzart	Lcom/google/android/gms/internal/ads/zzlt;
    //   3259: iconst_1
    //   3260: invokevirtual 179	com/google/android/gms/internal/ads/zzlr:zza	(ILcom/google/android/gms/internal/ads/zzlt;Z)Lcom/google/android/gms/internal/ads/zzlt;
    //   3263: pop
    //   3264: aload_0
    //   3265: getfield 120	com/google/android/gms/internal/ads/zzlc:zzart	Lcom/google/android/gms/internal/ads/zzlt;
    //   3268: getfield 183	com/google/android/gms/internal/ads/zzlt:zzasx	Ljava/lang/Object;
    //   3271: astore 52
    //   3273: aload 43
    //   3275: iconst_m1
    //   3276: putfield 434	com/google/android/gms/internal/ads/zzld:zzatb	I
    //   3279: aload 43
    //   3281: getfield 275	com/google/android/gms/internal/ads/zzld:zzatf	Lcom/google/android/gms/internal/ads/zzld;
    //   3284: ifnull +37 -> 3321
    //   3287: aload 43
    //   3289: getfield 275	com/google/android/gms/internal/ads/zzld:zzatf	Lcom/google/android/gms/internal/ads/zzld;
    //   3292: astore 43
    //   3294: aload 43
    //   3296: getfield 696	com/google/android/gms/internal/ads/zzld:zzasx	Ljava/lang/Object;
    //   3299: aload 52
    //   3301: invokevirtual 698	java/lang/Object:equals	(Ljava/lang/Object;)Z
    //   3304: ifeq +1147 -> 4451
    //   3307: iload 48
    //   3309: istore 53
    //   3311: aload 43
    //   3313: iload 53
    //   3315: putfield 434	com/google/android/gms/internal/ads/zzld:zzatb	I
    //   3318: goto -39 -> 3279
    //   3321: aload_0
    //   3322: new 287	com/google/android/gms/internal/ads/zzle
    //   3325: dup
    //   3326: iload 48
    //   3328: aload_0
    //   3329: iload 48
    //   3331: lload 49
    //   3333: invokespecial 587	com/google/android/gms/internal/ads/zzlc:zzd	(IJ)J
    //   3336: invokespecial 290	com/google/android/gms/internal/ads/zzle:<init>	(IJ)V
    //   3339: putfield 87	com/google/android/gms/internal/ads/zzlc:zzasd	Lcom/google/android/gms/internal/ads/zzle;
    //   3342: aload_0
    //   3343: aload 41
    //   3345: iload 42
    //   3347: invokespecial 292	com/google/android/gms/internal/ads/zzlc:zzb	(Ljava/lang/Object;I)V
    //   3350: goto +1093 -> 4443
    //   3353: aload 43
    //   3355: iload 44
    //   3357: aload_0
    //   3358: iload 44
    //   3360: invokespecial 582	com/google/android/gms/internal/ads/zzlc:zzad	(I)Z
    //   3363: invokevirtual 701	com/google/android/gms/internal/ads/zzld:zzd	(IZ)V
    //   3366: aload 43
    //   3368: aload_0
    //   3369: getfield 431	com/google/android/gms/internal/ads/zzlc:zzasu	Lcom/google/android/gms/internal/ads/zzld;
    //   3372: if_acmpne +1118 -> 4490
    //   3375: iconst_1
    //   3376: istore 54
    //   3378: iload 44
    //   3380: aload_0
    //   3381: getfield 87	com/google/android/gms/internal/ads/zzlc:zzasd	Lcom/google/android/gms/internal/ads/zzle;
    //   3384: getfield 597	com/google/android/gms/internal/ads/zzle:zzatb	I
    //   3387: if_icmpeq +1070 -> 4457
    //   3390: aload_0
    //   3391: getfield 87	com/google/android/gms/internal/ads/zzlc:zzasd	Lcom/google/android/gms/internal/ads/zzle;
    //   3394: astore 62
    //   3396: new 287	com/google/android/gms/internal/ads/zzle
    //   3399: dup
    //   3400: iload 44
    //   3402: aload 62
    //   3404: getfield 697	com/google/android/gms/internal/ads/zzle:zzatc	J
    //   3407: invokespecial 290	com/google/android/gms/internal/ads/zzle:<init>	(IJ)V
    //   3410: astore 63
    //   3412: aload 63
    //   3414: aload 62
    //   3416: getfield 481	com/google/android/gms/internal/ads/zzle:zzacl	J
    //   3419: putfield 481	com/google/android/gms/internal/ads/zzle:zzacl	J
    //   3422: aload 63
    //   3424: aload 62
    //   3426: getfield 497	com/google/android/gms/internal/ads/zzle:zzacm	J
    //   3429: putfield 497	com/google/android/gms/internal/ads/zzle:zzacm	J
    //   3432: aload_0
    //   3433: aload 63
    //   3435: putfield 87	com/google/android/gms/internal/ads/zzlc:zzasd	Lcom/google/android/gms/internal/ads/zzle;
    //   3438: goto +1019 -> 4457
    //   3441: aload 55
    //   3443: getfield 275	com/google/android/gms/internal/ads/zzld:zzatf	Lcom/google/android/gms/internal/ads/zzld;
    //   3446: ifnull -104 -> 3342
    //   3449: aload 55
    //   3451: getfield 275	com/google/android/gms/internal/ads/zzld:zzatf	Lcom/google/android/gms/internal/ads/zzld;
    //   3454: astore 58
    //   3456: aload_0
    //   3457: getfield 199	com/google/android/gms/internal/ads/zzlc:zzary	Lcom/google/android/gms/internal/ads/zzlr;
    //   3460: iload 57
    //   3462: aload_0
    //   3463: getfield 120	com/google/android/gms/internal/ads/zzlc:zzart	Lcom/google/android/gms/internal/ads/zzlt;
    //   3466: aload_0
    //   3467: getfield 115	com/google/android/gms/internal/ads/zzlc:zzars	Lcom/google/android/gms/internal/ads/zzlu;
    //   3470: aload_0
    //   3471: getfield 81	com/google/android/gms/internal/ads/zzlc:repeatMode	I
    //   3474: invokevirtual 176	com/google/android/gms/internal/ads/zzlr:zza	(ILcom/google/android/gms/internal/ads/zzlt;Lcom/google/android/gms/internal/ads/zzlu;I)I
    //   3477: istore 59
    //   3479: iload 59
    //   3481: iconst_m1
    //   3482: if_icmpeq +59 -> 3541
    //   3485: aload 58
    //   3487: getfield 696	com/google/android/gms/internal/ads/zzld:zzasx	Ljava/lang/Object;
    //   3490: aload_0
    //   3491: getfield 199	com/google/android/gms/internal/ads/zzlc:zzary	Lcom/google/android/gms/internal/ads/zzlr;
    //   3494: iload 59
    //   3496: aload_0
    //   3497: getfield 120	com/google/android/gms/internal/ads/zzlc:zzart	Lcom/google/android/gms/internal/ads/zzlt;
    //   3500: iconst_1
    //   3501: invokevirtual 179	com/google/android/gms/internal/ads/zzlr:zza	(ILcom/google/android/gms/internal/ads/zzlt;Z)Lcom/google/android/gms/internal/ads/zzlt;
    //   3504: getfield 183	com/google/android/gms/internal/ads/zzlt:zzasx	Ljava/lang/Object;
    //   3507: invokevirtual 698	java/lang/Object:equals	(Ljava/lang/Object;)Z
    //   3510: ifeq +31 -> 3541
    //   3513: aload 58
    //   3515: iload 59
    //   3517: aload_0
    //   3518: iload 59
    //   3520: invokespecial 582	com/google/android/gms/internal/ads/zzlc:zzad	(I)Z
    //   3523: invokevirtual 701	com/google/android/gms/internal/ads/zzld:zzd	(IZ)V
    //   3526: aload 58
    //   3528: aload_0
    //   3529: getfield 431	com/google/android/gms/internal/ads/zzlc:zzasu	Lcom/google/android/gms/internal/ads/zzld;
    //   3532: if_acmpne +964 -> 4496
    //   3535: iconst_1
    //   3536: istore 61
    //   3538: goto +934 -> 4472
    //   3541: iload 56
    //   3543: ifne +41 -> 3584
    //   3546: aload_0
    //   3547: getfield 301	com/google/android/gms/internal/ads/zzlc:zzasv	Lcom/google/android/gms/internal/ads/zzld;
    //   3550: getfield 434	com/google/android/gms/internal/ads/zzld:zzatb	I
    //   3553: istore 60
    //   3555: aload_0
    //   3556: new 287	com/google/android/gms/internal/ads/zzle
    //   3559: dup
    //   3560: iload 60
    //   3562: aload_0
    //   3563: iload 60
    //   3565: aload_0
    //   3566: getfield 87	com/google/android/gms/internal/ads/zzlc:zzasd	Lcom/google/android/gms/internal/ads/zzle;
    //   3569: getfield 481	com/google/android/gms/internal/ads/zzle:zzacl	J
    //   3572: invokespecial 587	com/google/android/gms/internal/ads/zzlc:zzd	(IJ)J
    //   3575: invokespecial 290	com/google/android/gms/internal/ads/zzle:<init>	(IJ)V
    //   3578: putfield 87	com/google/android/gms/internal/ads/zzlc:zzasd	Lcom/google/android/gms/internal/ads/zzle;
    //   3581: goto -239 -> 3342
    //   3584: aload_0
    //   3585: aload 55
    //   3587: putfield 429	com/google/android/gms/internal/ads/zzlc:zzast	Lcom/google/android/gms/internal/ads/zzld;
    //   3590: aload_0
    //   3591: getfield 429	com/google/android/gms/internal/ads/zzlc:zzast	Lcom/google/android/gms/internal/ads/zzld;
    //   3594: aconst_null
    //   3595: putfield 275	com/google/android/gms/internal/ads/zzld:zzatf	Lcom/google/android/gms/internal/ads/zzld;
    //   3598: aload 58
    //   3600: invokestatic 543	com/google/android/gms/internal/ads/zzlc:zza	(Lcom/google/android/gms/internal/ads/zzld;)V
    //   3603: goto -261 -> 3342
    //   3606: aload_1
    //   3607: getfield 558	android/os/Message:obj	Ljava/lang/Object;
    //   3610: checkcast 448	com/google/android/gms/internal/ads/zzqj
    //   3613: astore 38
    //   3615: aload_0
    //   3616: getfield 429	com/google/android/gms/internal/ads/zzlc:zzast	Lcom/google/android/gms/internal/ads/zzld;
    //   3619: ifnull +883 -> 4502
    //   3622: aload_0
    //   3623: getfield 429	com/google/android/gms/internal/ads/zzlc:zzast	Lcom/google/android/gms/internal/ads/zzld;
    //   3626: getfield 446	com/google/android/gms/internal/ads/zzld:zzasw	Lcom/google/android/gms/internal/ads/zzqj;
    //   3629: aload 38
    //   3631: if_acmpeq +6 -> 3637
    //   3634: goto +868 -> 4502
    //   3637: aload_0
    //   3638: invokespecial 459	com/google/android/gms/internal/ads/zzlc:zzgy	()V
    //   3641: goto +861 -> 4502
    //   3644: aload_0
    //   3645: getfield 301	com/google/android/gms/internal/ads/zzlc:zzasv	Lcom/google/android/gms/internal/ads/zzld;
    //   3648: ifnull +856 -> 4504
    //   3651: aload_0
    //   3652: getfield 301	com/google/android/gms/internal/ads/zzlc:zzasv	Lcom/google/android/gms/internal/ads/zzld;
    //   3655: astore 16
    //   3657: iconst_1
    //   3658: istore 17
    //   3660: aload 16
    //   3662: astore 18
    //   3664: aload 18
    //   3666: ifnull +838 -> 4504
    //   3669: aload 18
    //   3671: getfield 437	com/google/android/gms/internal/ads/zzld:zzacs	Z
    //   3674: ifne +6 -> 3680
    //   3677: goto +827 -> 4504
    //   3680: aload 18
    //   3682: invokevirtual 690	com/google/android/gms/internal/ads/zzld:zzhb	()Z
    //   3685: ifne +25 -> 3710
    //   3688: aload 18
    //   3690: aload_0
    //   3691: getfield 431	com/google/android/gms/internal/ads/zzlc:zzasu	Lcom/google/android/gms/internal/ads/zzld;
    //   3694: if_acmpne +6 -> 3700
    //   3697: iconst_0
    //   3698: istore 17
    //   3700: aload 18
    //   3702: getfield 275	com/google/android/gms/internal/ads/zzld:zzatf	Lcom/google/android/gms/internal/ads/zzld;
    //   3705: astore 18
    //   3707: goto -43 -> 3664
    //   3710: iload 17
    //   3712: ifeq +318 -> 4030
    //   3715: aload_0
    //   3716: getfield 431	com/google/android/gms/internal/ads/zzlc:zzasu	Lcom/google/android/gms/internal/ads/zzld;
    //   3719: aload_0
    //   3720: getfield 301	com/google/android/gms/internal/ads/zzlc:zzasv	Lcom/google/android/gms/internal/ads/zzld;
    //   3723: if_acmpeq +789 -> 4512
    //   3726: iconst_1
    //   3727: istore 19
    //   3729: aload_0
    //   3730: getfield 301	com/google/android/gms/internal/ads/zzlc:zzasv	Lcom/google/android/gms/internal/ads/zzld;
    //   3733: getfield 275	com/google/android/gms/internal/ads/zzld:zzatf	Lcom/google/android/gms/internal/ads/zzld;
    //   3736: invokestatic 543	com/google/android/gms/internal/ads/zzlc:zza	(Lcom/google/android/gms/internal/ads/zzld;)V
    //   3739: aload_0
    //   3740: getfield 301	com/google/android/gms/internal/ads/zzlc:zzasv	Lcom/google/android/gms/internal/ads/zzld;
    //   3743: aconst_null
    //   3744: putfield 275	com/google/android/gms/internal/ads/zzld:zzatf	Lcom/google/android/gms/internal/ads/zzld;
    //   3747: aload_0
    //   3748: aload_0
    //   3749: getfield 301	com/google/android/gms/internal/ads/zzlc:zzasv	Lcom/google/android/gms/internal/ads/zzld;
    //   3752: putfield 429	com/google/android/gms/internal/ads/zzlc:zzast	Lcom/google/android/gms/internal/ads/zzld;
    //   3755: aload_0
    //   3756: aload_0
    //   3757: getfield 301	com/google/android/gms/internal/ads/zzlc:zzasv	Lcom/google/android/gms/internal/ads/zzld;
    //   3760: putfield 431	com/google/android/gms/internal/ads/zzlc:zzasu	Lcom/google/android/gms/internal/ads/zzld;
    //   3763: aload_0
    //   3764: getfield 73	com/google/android/gms/internal/ads/zzlc:zzaro	[Lcom/google/android/gms/internal/ads/zzlo;
    //   3767: arraylength
    //   3768: newarray boolean
    //   3770: astore 20
    //   3772: aload_0
    //   3773: getfield 301	com/google/android/gms/internal/ads/zzlc:zzasv	Lcom/google/android/gms/internal/ads/zzld;
    //   3776: aload_0
    //   3777: getfield 87	com/google/android/gms/internal/ads/zzlc:zzasd	Lcom/google/android/gms/internal/ads/zzle;
    //   3780: getfield 481	com/google/android/gms/internal/ads/zzle:zzacl	J
    //   3783: iload 19
    //   3785: aload 20
    //   3787: invokevirtual 704	com/google/android/gms/internal/ads/zzld:zza	(JZ[Z)J
    //   3790: lstore 21
    //   3792: lload 21
    //   3794: aload_0
    //   3795: getfield 87	com/google/android/gms/internal/ads/zzlc:zzasd	Lcom/google/android/gms/internal/ads/zzle;
    //   3798: getfield 481	com/google/android/gms/internal/ads/zzle:zzacl	J
    //   3801: lcmp
    //   3802: ifeq +18 -> 3820
    //   3805: aload_0
    //   3806: getfield 87	com/google/android/gms/internal/ads/zzlc:zzasd	Lcom/google/android/gms/internal/ads/zzle;
    //   3809: lload 21
    //   3811: putfield 481	com/google/android/gms/internal/ads/zzle:zzacl	J
    //   3814: aload_0
    //   3815: lload 21
    //   3817: invokespecial 456	com/google/android/gms/internal/ads/zzlc:zzeb	(J)V
    //   3820: aload_0
    //   3821: getfield 73	com/google/android/gms/internal/ads/zzlc:zzaro	[Lcom/google/android/gms/internal/ads/zzlo;
    //   3824: arraylength
    //   3825: newarray boolean
    //   3827: astore 23
    //   3829: iconst_0
    //   3830: istore 24
    //   3832: iconst_0
    //   3833: istore 25
    //   3835: iload 24
    //   3837: aload_0
    //   3838: getfield 73	com/google/android/gms/internal/ads/zzlc:zzaro	[Lcom/google/android/gms/internal/ads/zzlo;
    //   3841: arraylength
    //   3842: if_icmpge +144 -> 3986
    //   3845: aload_0
    //   3846: getfield 73	com/google/android/gms/internal/ads/zzlc:zzaro	[Lcom/google/android/gms/internal/ads/zzlo;
    //   3849: iload 24
    //   3851: aaload
    //   3852: astore 27
    //   3854: aload 27
    //   3856: invokeinterface 281 1 0
    //   3861: ifeq +657 -> 4518
    //   3864: iconst_1
    //   3865: istore 28
    //   3867: aload 23
    //   3869: iload 24
    //   3871: iload 28
    //   3873: bastore
    //   3874: aload_0
    //   3875: getfield 301	com/google/android/gms/internal/ads/zzlc:zzasv	Lcom/google/android/gms/internal/ads/zzld;
    //   3878: getfield 336	com/google/android/gms/internal/ads/zzld:zzasy	[Lcom/google/android/gms/internal/ads/zzqw;
    //   3881: iload 24
    //   3883: aaload
    //   3884: astore 29
    //   3886: aload 29
    //   3888: ifnull +6 -> 3894
    //   3891: iinc 25 1
    //   3894: aload 23
    //   3896: iload 24
    //   3898: baload
    //   3899: ifeq +607 -> 4506
    //   3902: aload 29
    //   3904: aload 27
    //   3906: invokeinterface 402 1 0
    //   3911: if_acmpeq +53 -> 3964
    //   3914: aload 27
    //   3916: aload_0
    //   3917: getfield 363	com/google/android/gms/internal/ads/zzlc:zzasm	Lcom/google/android/gms/internal/ads/zzlo;
    //   3920: if_acmpne +29 -> 3949
    //   3923: aload 29
    //   3925: ifnonnull +14 -> 3939
    //   3928: aload_0
    //   3929: getfield 108	com/google/android/gms/internal/ads/zzlc:zzask	Lcom/google/android/gms/internal/ads/zzsw;
    //   3932: aload_0
    //   3933: getfield 351	com/google/android/gms/internal/ads/zzlc:zzasn	Lcom/google/android/gms/internal/ads/zzso;
    //   3936: invokevirtual 405	com/google/android/gms/internal/ads/zzsw:zza	(Lcom/google/android/gms/internal/ads/zzso;)V
    //   3939: aload_0
    //   3940: aconst_null
    //   3941: putfield 351	com/google/android/gms/internal/ads/zzlc:zzasn	Lcom/google/android/gms/internal/ads/zzso;
    //   3944: aload_0
    //   3945: aconst_null
    //   3946: putfield 363	com/google/android/gms/internal/ads/zzlc:zzasm	Lcom/google/android/gms/internal/ads/zzlo;
    //   3949: aload 27
    //   3951: invokestatic 407	com/google/android/gms/internal/ads/zzlc:zza	(Lcom/google/android/gms/internal/ads/zzlo;)V
    //   3954: aload 27
    //   3956: invokeinterface 410 1 0
    //   3961: goto +545 -> 4506
    //   3964: aload 20
    //   3966: iload 24
    //   3968: baload
    //   3969: ifeq +537 -> 4506
    //   3972: aload 27
    //   3974: aload_0
    //   3975: getfield 338	com/google/android/gms/internal/ads/zzlc:zzass	J
    //   3978: invokeinterface 476 3 0
    //   3983: goto +523 -> 4506
    //   3986: aload_0
    //   3987: getfield 83	com/google/android/gms/internal/ads/zzlc:zzabq	Landroid/os/Handler;
    //   3990: iconst_3
    //   3991: aload 18
    //   3993: getfield 305	com/google/android/gms/internal/ads/zzld:zzatg	Lcom/google/android/gms/internal/ads/zzrr;
    //   3996: invokevirtual 413	android/os/Handler:obtainMessage	(ILjava/lang/Object;)Landroid/os/Message;
    //   3999: invokevirtual 166	android/os/Message:sendToTarget	()V
    //   4002: aload_0
    //   4003: aload 23
    //   4005: iload 25
    //   4007: invokespecial 415	com/google/android/gms/internal/ads/zzlc:zza	([ZI)V
    //   4010: aload_0
    //   4011: invokespecial 459	com/google/android/gms/internal/ads/zzlc:zzgy	()V
    //   4014: aload_0
    //   4015: invokespecial 569	com/google/android/gms/internal/ads/zzlc:zzgw	()V
    //   4018: aload_0
    //   4019: getfield 156	com/google/android/gms/internal/ads/zzlc:handler	Landroid/os/Handler;
    //   4022: iconst_2
    //   4023: invokevirtual 391	android/os/Handler:sendEmptyMessage	(I)Z
    //   4026: pop
    //   4027: goto +477 -> 4504
    //   4030: aload_0
    //   4031: aload 18
    //   4033: putfield 429	com/google/android/gms/internal/ads/zzlc:zzast	Lcom/google/android/gms/internal/ads/zzld;
    //   4036: aload_0
    //   4037: getfield 429	com/google/android/gms/internal/ads/zzlc:zzast	Lcom/google/android/gms/internal/ads/zzld;
    //   4040: getfield 275	com/google/android/gms/internal/ads/zzld:zzatf	Lcom/google/android/gms/internal/ads/zzld;
    //   4043: astore 30
    //   4045: aload 30
    //   4047: ifnull +18 -> 4065
    //   4050: aload 30
    //   4052: invokevirtual 272	com/google/android/gms/internal/ads/zzld:release	()V
    //   4055: aload 30
    //   4057: getfield 275	com/google/android/gms/internal/ads/zzld:zzatf	Lcom/google/android/gms/internal/ads/zzld;
    //   4060: astore 30
    //   4062: goto -17 -> 4045
    //   4065: aload_0
    //   4066: getfield 429	com/google/android/gms/internal/ads/zzlc:zzast	Lcom/google/android/gms/internal/ads/zzld;
    //   4069: aconst_null
    //   4070: putfield 275	com/google/android/gms/internal/ads/zzld:zzatf	Lcom/google/android/gms/internal/ads/zzld;
    //   4073: aload_0
    //   4074: getfield 429	com/google/android/gms/internal/ads/zzlc:zzast	Lcom/google/android/gms/internal/ads/zzld;
    //   4077: getfield 437	com/google/android/gms/internal/ads/zzld:zzacs	Z
    //   4080: ifeq -70 -> 4010
    //   4083: aload_0
    //   4084: getfield 429	com/google/android/gms/internal/ads/zzlc:zzast	Lcom/google/android/gms/internal/ads/zzld;
    //   4087: getfield 606	com/google/android/gms/internal/ads/zzld:zzatc	J
    //   4090: lstore 31
    //   4092: aload_0
    //   4093: getfield 429	com/google/android/gms/internal/ads/zzlc:zzast	Lcom/google/android/gms/internal/ads/zzld;
    //   4096: astore 33
    //   4098: lload 31
    //   4100: aload_0
    //   4101: getfield 338	com/google/android/gms/internal/ads/zzlc:zzass	J
    //   4104: aload 33
    //   4106: invokevirtual 342	com/google/android/gms/internal/ads/zzld:zzgz	()J
    //   4109: lsub
    //   4110: invokestatic 623	java/lang/Math:max	(JJ)J
    //   4113: lstore 34
    //   4115: aload_0
    //   4116: getfield 429	com/google/android/gms/internal/ads/zzlc:zzast	Lcom/google/android/gms/internal/ads/zzld;
    //   4119: lload 34
    //   4121: iconst_0
    //   4122: invokevirtual 693	com/google/android/gms/internal/ads/zzld:zze	(JZ)J
    //   4125: pop2
    //   4126: goto -116 -> 4010
    //   4129: aload_1
    //   4130: getfield 558	android/os/Message:obj	Ljava/lang/Object;
    //   4133: checkcast 706	[Lcom/google/android/gms/internal/ads/zzky;
    //   4136: astore 8
    //   4138: aload 8
    //   4140: arraylength
    //   4141: istore 11
    //   4143: iconst_0
    //   4144: istore 12
    //   4146: iload 12
    //   4148: iload 11
    //   4150: if_icmpge +36 -> 4186
    //   4153: aload 8
    //   4155: iload 12
    //   4157: aaload
    //   4158: astore 13
    //   4160: aload 13
    //   4162: getfield 712	com/google/android/gms/internal/ads/zzky:zzarl	Lcom/google/android/gms/internal/ads/zzkx;
    //   4165: aload 13
    //   4167: getfield 715	com/google/android/gms/internal/ads/zzky:zzarm	I
    //   4170: aload 13
    //   4172: getfield 718	com/google/android/gms/internal/ads/zzky:zzarn	Ljava/lang/Object;
    //   4175: invokeinterface 723 3 0
    //   4180: iinc 12 1
    //   4183: goto -37 -> 4146
    //   4186: aload_0
    //   4187: getfield 545	com/google/android/gms/internal/ads/zzlc:zzaso	Lcom/google/android/gms/internal/ads/zzql;
    //   4190: ifnull +12 -> 4202
    //   4193: aload_0
    //   4194: getfield 156	com/google/android/gms/internal/ads/zzlc:handler	Landroid/os/Handler;
    //   4197: iconst_2
    //   4198: invokevirtual 391	android/os/Handler:sendEmptyMessage	(I)Z
    //   4201: pop
    //   4202: aload_0
    //   4203: monitorenter
    //   4204: aload_0
    //   4205: iconst_1
    //   4206: aload_0
    //   4207: getfield 725	com/google/android/gms/internal/ads/zzlc:zzaci	I
    //   4210: iadd
    //   4211: putfield 725	com/google/android/gms/internal/ads/zzlc:zzaci	I
    //   4214: aload_0
    //   4215: invokevirtual 687	java/lang/Object:notifyAll	()V
    //   4218: aload_0
    //   4219: monitorexit
    //   4220: iconst_1
    //   4221: ireturn
    //   4222: astore 14
    //   4224: aload_0
    //   4225: monitorexit
    //   4226: aload 14
    //   4228: athrow
    //   4229: astore 9
    //   4231: aload_0
    //   4232: monitorenter
    //   4233: aload_0
    //   4234: iconst_1
    //   4235: aload_0
    //   4236: getfield 725	com/google/android/gms/internal/ads/zzlc:zzaci	I
    //   4239: iadd
    //   4240: putfield 725	com/google/android/gms/internal/ads/zzlc:zzaci	I
    //   4243: aload_0
    //   4244: invokevirtual 687	java/lang/Object:notifyAll	()V
    //   4247: aload_0
    //   4248: monitorexit
    //   4249: aload 9
    //   4251: athrow
    //   4252: astore 10
    //   4254: aload_0
    //   4255: monitorexit
    //   4256: aload 10
    //   4258: athrow
    //   4259: iconst_0
    //   4260: ireturn
    //   4261: iconst_0
    //   4262: istore 162
    //   4264: goto -4173 -> 91
    //   4267: iconst_1
    //   4268: ireturn
    //   4269: iconst_0
    //   4270: istore 158
    //   4272: goto -4093 -> 179
    //   4275: iload 157
    //   4277: iload 152
    //   4279: ior
    //   4280: istore 152
    //   4282: aload 155
    //   4284: astore 150
    //   4286: goto -3903 -> 383
    //   4289: iconst_0
    //   4290: istore 149
    //   4292: goto -3929 -> 363
    //   4295: aload 148
    //   4297: astore 150
    //   4299: iload 149
    //   4301: istore 151
    //   4303: iconst_0
    //   4304: istore 152
    //   4306: goto -3923 -> 383
    //   4309: iconst_0
    //   4310: istore 156
    //   4312: goto -3859 -> 453
    //   4315: iconst_0
    //   4316: istore 157
    //   4318: goto -43 -> 4275
    //   4321: iconst_1
    //   4322: ireturn
    //   4323: iconst_1
    //   4324: ireturn
    //   4325: iinc 111 1
    //   4328: goto -3016 -> 1312
    //   4331: iconst_0
    //   4332: istore 134
    //   4334: goto -2954 -> 1380
    //   4337: iinc 134 1
    //   4340: goto -2960 -> 1380
    //   4343: iconst_0
    //   4344: istore 138
    //   4346: goto -2828 -> 1518
    //   4349: iconst_0
    //   4350: istore 137
    //   4352: goto -9 -> 4343
    //   4355: iinc 138 1
    //   4358: goto -2840 -> 1518
    //   4361: iconst_1
    //   4362: istore 120
    //   4364: goto -2551 -> 1813
    //   4367: iload 118
    //   4369: ifeq +29 -> 4398
    //   4372: iload 120
    //   4374: ifeq +24 -> 4398
    //   4377: iconst_1
    //   4378: istore 118
    //   4380: iinc 117 1
    //   4383: goto -2640 -> 1743
    //   4386: iconst_0
    //   4387: istore 114
    //   4389: goto -2599 -> 1790
    //   4392: iconst_0
    //   4393: istore 120
    //   4395: goto -2582 -> 1813
    //   4398: iconst_0
    //   4399: istore 118
    //   4401: goto -21 -> 4380
    //   4404: iload 129
    //   4406: ifeq +9 -> 4415
    //   4409: iconst_1
    //   4410: istore 130
    //   4412: goto -2328 -> 2084
    //   4415: iconst_0
    //   4416: istore 130
    //   4418: goto -2334 -> 2084
    //   4421: iconst_1
    //   4422: ireturn
    //   4423: iconst_0
    //   4424: istore 84
    //   4426: goto -1837 -> 2589
    //   4429: iconst_0
    //   4430: istore 87
    //   4432: goto -1807 -> 2625
    //   4435: iconst_0
    //   4436: istore 81
    //   4438: goto -1763 -> 2675
    //   4441: iconst_1
    //   4442: ireturn
    //   4443: iconst_1
    //   4444: ireturn
    //   4445: iconst_0
    //   4446: istore 42
    //   4448: goto -1411 -> 3037
    //   4451: iconst_m1
    //   4452: istore 53
    //   4454: goto -1143 -> 3311
    //   4457: aload 43
    //   4459: astore 55
    //   4461: iload 54
    //   4463: istore 56
    //   4465: iload 44
    //   4467: istore 57
    //   4469: goto -1028 -> 3441
    //   4472: iload 61
    //   4474: iload 56
    //   4476: ior
    //   4477: istore 56
    //   4479: aload 58
    //   4481: astore 55
    //   4483: iload 59
    //   4485: istore 57
    //   4487: goto -1046 -> 3441
    //   4490: iconst_0
    //   4491: istore 54
    //   4493: goto -1115 -> 3378
    //   4496: iconst_0
    //   4497: istore 61
    //   4499: goto -27 -> 4472
    //   4502: iconst_1
    //   4503: ireturn
    //   4504: iconst_1
    //   4505: ireturn
    //   4506: iinc 24 1
    //   4509: goto -674 -> 3835
    //   4512: iconst_0
    //   4513: istore 19
    //   4515: goto -786 -> 3729
    //   4518: iconst_0
    //   4519: istore 28
    //   4521: goto -654 -> 3867
    //
    // Exception table:
    //   from	to	target	type
    //   0	72	230	com/google/android/gms/internal/ads/zzku
    //   72	88	230	com/google/android/gms/internal/ads/zzku
    //   91	114	230	com/google/android/gms/internal/ads/zzku
    //   119	134	230	com/google/android/gms/internal/ads/zzku
    //   134	167	230	com/google/android/gms/internal/ads/zzku
    //   169	176	230	com/google/android/gms/internal/ads/zzku
    //   179	190	230	com/google/android/gms/internal/ads/zzku
    //   195	203	230	com/google/android/gms/internal/ads/zzku
    //   206	227	230	com/google/android/gms/internal/ads/zzku
    //   264	281	230	com/google/android/gms/internal/ads/zzku
    //   321	346	230	com/google/android/gms/internal/ads/zzku
    //   351	360	230	com/google/android/gms/internal/ads/zzku
    //   363	372	230	com/google/android/gms/internal/ads/zzku
    //   383	415	230	com/google/android/gms/internal/ads/zzku
    //   421	450	230	com/google/android/gms/internal/ads/zzku
    //   460	469	230	com/google/android/gms/internal/ads/zzku
    //   475	481	230	com/google/android/gms/internal/ads/zzku
    //   484	506	230	com/google/android/gms/internal/ads/zzku
    //   506	520	230	com/google/android/gms/internal/ads/zzku
    //   525	531	230	com/google/android/gms/internal/ads/zzku
    //   536	578	230	com/google/android/gms/internal/ads/zzku
    //   578	586	230	com/google/android/gms/internal/ads/zzku
    //   591	596	230	com/google/android/gms/internal/ads/zzku
    //   599	620	230	com/google/android/gms/internal/ads/zzku
    //   620	640	230	com/google/android/gms/internal/ads/zzku
    //   643	659	230	com/google/android/gms/internal/ads/zzku
    //   659	680	230	com/google/android/gms/internal/ads/zzku
    //   680	697	230	com/google/android/gms/internal/ads/zzku
    //   697	702	230	com/google/android/gms/internal/ads/zzku
    //   702	709	230	com/google/android/gms/internal/ads/zzku
    //   709	800	230	com/google/android/gms/internal/ads/zzku
    //   837	917	230	com/google/android/gms/internal/ads/zzku
    //   917	940	230	com/google/android/gms/internal/ads/zzku
    //   943	959	230	com/google/android/gms/internal/ads/zzku
    //   959	966	230	com/google/android/gms/internal/ads/zzku
    //   974	981	230	com/google/android/gms/internal/ads/zzku
    //   984	1069	230	com/google/android/gms/internal/ads/zzku
    //   1069	1095	230	com/google/android/gms/internal/ads/zzku
    //   1098	1127	230	com/google/android/gms/internal/ads/zzku
    //   1138	1195	230	com/google/android/gms/internal/ads/zzku
    //   1200	1226	230	com/google/android/gms/internal/ads/zzku
    //   1229	1261	230	com/google/android/gms/internal/ads/zzku
    //   1264	1275	230	com/google/android/gms/internal/ads/zzku
    //   1278	1296	230	com/google/android/gms/internal/ads/zzku
    //   1299	1309	230	com/google/android/gms/internal/ads/zzku
    //   1312	1343	230	com/google/android/gms/internal/ads/zzku
    //   1348	1377	230	com/google/android/gms/internal/ads/zzku
    //   1380	1423	230	com/google/android/gms/internal/ads/zzku
    //   1428	1438	230	com/google/android/gms/internal/ads/zzku
    //   1441	1512	230	com/google/android/gms/internal/ads/zzku
    //   1518	1550	230	com/google/android/gms/internal/ads/zzku
    //   1555	1597	230	com/google/android/gms/internal/ads/zzku
    //   1602	1624	230	com/google/android/gms/internal/ads/zzku
    //   1627	1649	230	com/google/android/gms/internal/ads/zzku
    //   1655	1681	230	com/google/android/gms/internal/ads/zzku
    //   1684	1691	230	com/google/android/gms/internal/ads/zzku
    //   1694	1723	230	com/google/android/gms/internal/ads/zzku
    //   1726	1737	230	com/google/android/gms/internal/ads/zzku
    //   1750	1772	230	com/google/android/gms/internal/ads/zzku
    //   1777	1787	230	com/google/android/gms/internal/ads/zzku
    //   1790	1810	230	com/google/android/gms/internal/ads/zzku
    //   1818	1825	230	com/google/android/gms/internal/ads/zzku
    //   1833	1837	230	com/google/android/gms/internal/ads/zzku
    //   1837	1898	230	com/google/android/gms/internal/ads/zzku
    //   1898	1922	230	com/google/android/gms/internal/ads/zzku
    //   1936	1949	230	com/google/android/gms/internal/ads/zzku
    //   1949	1968	230	com/google/android/gms/internal/ads/zzku
    //   1968	1987	230	com/google/android/gms/internal/ads/zzku
    //   1997	2007	230	com/google/android/gms/internal/ads/zzku
    //   2013	2029	230	com/google/android/gms/internal/ads/zzku
    //   2034	2059	230	com/google/android/gms/internal/ads/zzku
    //   2068	2078	230	com/google/android/gms/internal/ads/zzku
    //   2089	2105	230	com/google/android/gms/internal/ads/zzku
    //   2108	2122	230	com/google/android/gms/internal/ads/zzku
    //   2125	2149	230	com/google/android/gms/internal/ads/zzku
    //   2149	2185	230	com/google/android/gms/internal/ads/zzku
    //   2188	2196	230	com/google/android/gms/internal/ads/zzku
    //   2199	2215	230	com/google/android/gms/internal/ads/zzku
    //   2220	2237	230	com/google/android/gms/internal/ads/zzku
    //   2240	2248	230	com/google/android/gms/internal/ads/zzku
    //   2251	2266	230	com/google/android/gms/internal/ads/zzku
    //   2266	2274	230	com/google/android/gms/internal/ads/zzku
    //   2274	2283	230	com/google/android/gms/internal/ads/zzku
    //   2283	2286	230	com/google/android/gms/internal/ads/zzku
    //   2289	2306	230	com/google/android/gms/internal/ads/zzku
    //   2309	2317	230	com/google/android/gms/internal/ads/zzku
    //   2320	2352	230	com/google/android/gms/internal/ads/zzku
    //   2355	2363	230	com/google/android/gms/internal/ads/zzku
    //   2368	2423	230	com/google/android/gms/internal/ads/zzku
    //   2426	2438	230	com/google/android/gms/internal/ads/zzku
    //   2441	2467	230	com/google/android/gms/internal/ads/zzku
    //   2508	2529	230	com/google/android/gms/internal/ads/zzku
    //   2537	2553	230	com/google/android/gms/internal/ads/zzku
    //   2596	2617	230	com/google/android/gms/internal/ads/zzku
    //   2625	2641	230	com/google/android/gms/internal/ads/zzku
    //   2646	2667	230	com/google/android/gms/internal/ads/zzku
    //   2675	2694	230	com/google/android/gms/internal/ads/zzku
    //   2694	2723	230	com/google/android/gms/internal/ads/zzku
    //   2723	2743	230	com/google/android/gms/internal/ads/zzku
    //   2745	2756	230	com/google/android/gms/internal/ads/zzku
    //   2759	2763	230	com/google/android/gms/internal/ads/zzku
    //   2765	2786	230	com/google/android/gms/internal/ads/zzku
    //   2803	2806	230	com/google/android/gms/internal/ads/zzku
    //   2806	2834	230	com/google/android/gms/internal/ads/zzku
    //   2837	2905	230	com/google/android/gms/internal/ads/zzku
    //   2905	2909	230	com/google/android/gms/internal/ads/zzku
    //   2912	2946	230	com/google/android/gms/internal/ads/zzku
    //   2951	2984	230	com/google/android/gms/internal/ads/zzku
    //   2989	2997	230	com/google/android/gms/internal/ads/zzku
    //   3000	3033	230	com/google/android/gms/internal/ads/zzku
    //   3037	3050	230	com/google/android/gms/internal/ads/zzku
    //   3055	3069	230	com/google/android/gms/internal/ads/zzku
    //   3075	3092	230	com/google/android/gms/internal/ads/zzku
    //   3098	3106	230	com/google/android/gms/internal/ads/zzku
    //   3109	3140	230	com/google/android/gms/internal/ads/zzku
    //   3143	3186	230	com/google/android/gms/internal/ads/zzku
    //   3189	3195	230	com/google/android/gms/internal/ads/zzku
    //   3198	3279	230	com/google/android/gms/internal/ads/zzku
    //   3279	3307	230	com/google/android/gms/internal/ads/zzku
    //   3311	3318	230	com/google/android/gms/internal/ads/zzku
    //   3321	3342	230	com/google/android/gms/internal/ads/zzku
    //   3342	3350	230	com/google/android/gms/internal/ads/zzku
    //   3353	3375	230	com/google/android/gms/internal/ads/zzku
    //   3378	3438	230	com/google/android/gms/internal/ads/zzku
    //   3441	3479	230	com/google/android/gms/internal/ads/zzku
    //   3485	3535	230	com/google/android/gms/internal/ads/zzku
    //   3546	3581	230	com/google/android/gms/internal/ads/zzku
    //   3584	3603	230	com/google/android/gms/internal/ads/zzku
    //   3606	3634	230	com/google/android/gms/internal/ads/zzku
    //   3637	3641	230	com/google/android/gms/internal/ads/zzku
    //   3644	3657	230	com/google/android/gms/internal/ads/zzku
    //   3669	3677	230	com/google/android/gms/internal/ads/zzku
    //   3680	3697	230	com/google/android/gms/internal/ads/zzku
    //   3700	3707	230	com/google/android/gms/internal/ads/zzku
    //   3715	3726	230	com/google/android/gms/internal/ads/zzku
    //   3729	3820	230	com/google/android/gms/internal/ads/zzku
    //   3820	3829	230	com/google/android/gms/internal/ads/zzku
    //   3835	3864	230	com/google/android/gms/internal/ads/zzku
    //   3867	3886	230	com/google/android/gms/internal/ads/zzku
    //   3894	3923	230	com/google/android/gms/internal/ads/zzku
    //   3928	3939	230	com/google/android/gms/internal/ads/zzku
    //   3939	3949	230	com/google/android/gms/internal/ads/zzku
    //   3949	3961	230	com/google/android/gms/internal/ads/zzku
    //   3964	3983	230	com/google/android/gms/internal/ads/zzku
    //   3986	4010	230	com/google/android/gms/internal/ads/zzku
    //   4010	4027	230	com/google/android/gms/internal/ads/zzku
    //   4030	4045	230	com/google/android/gms/internal/ads/zzku
    //   4050	4062	230	com/google/android/gms/internal/ads/zzku
    //   4065	4126	230	com/google/android/gms/internal/ads/zzku
    //   4129	4138	230	com/google/android/gms/internal/ads/zzku
    //   4202	4204	230	com/google/android/gms/internal/ads/zzku
    //   4226	4229	230	com/google/android/gms/internal/ads/zzku
    //   4231	4233	230	com/google/android/gms/internal/ads/zzku
    //   4249	4252	230	com/google/android/gms/internal/ads/zzku
    //   4256	4259	230	com/google/android/gms/internal/ads/zzku
    //   0	72	284	java/io/IOException
    //   72	88	284	java/io/IOException
    //   91	114	284	java/io/IOException
    //   119	134	284	java/io/IOException
    //   134	167	284	java/io/IOException
    //   169	176	284	java/io/IOException
    //   179	190	284	java/io/IOException
    //   195	203	284	java/io/IOException
    //   206	227	284	java/io/IOException
    //   264	281	284	java/io/IOException
    //   321	346	284	java/io/IOException
    //   351	360	284	java/io/IOException
    //   363	372	284	java/io/IOException
    //   383	415	284	java/io/IOException
    //   421	450	284	java/io/IOException
    //   460	469	284	java/io/IOException
    //   475	481	284	java/io/IOException
    //   484	506	284	java/io/IOException
    //   506	520	284	java/io/IOException
    //   525	531	284	java/io/IOException
    //   536	578	284	java/io/IOException
    //   578	586	284	java/io/IOException
    //   591	596	284	java/io/IOException
    //   599	620	284	java/io/IOException
    //   620	640	284	java/io/IOException
    //   643	659	284	java/io/IOException
    //   659	680	284	java/io/IOException
    //   680	697	284	java/io/IOException
    //   697	702	284	java/io/IOException
    //   702	709	284	java/io/IOException
    //   709	800	284	java/io/IOException
    //   837	917	284	java/io/IOException
    //   917	940	284	java/io/IOException
    //   943	959	284	java/io/IOException
    //   959	966	284	java/io/IOException
    //   974	981	284	java/io/IOException
    //   984	1069	284	java/io/IOException
    //   1069	1095	284	java/io/IOException
    //   1098	1127	284	java/io/IOException
    //   1138	1195	284	java/io/IOException
    //   1200	1226	284	java/io/IOException
    //   1229	1261	284	java/io/IOException
    //   1264	1275	284	java/io/IOException
    //   1278	1296	284	java/io/IOException
    //   1299	1309	284	java/io/IOException
    //   1312	1343	284	java/io/IOException
    //   1348	1377	284	java/io/IOException
    //   1380	1423	284	java/io/IOException
    //   1428	1438	284	java/io/IOException
    //   1441	1512	284	java/io/IOException
    //   1518	1550	284	java/io/IOException
    //   1555	1597	284	java/io/IOException
    //   1602	1624	284	java/io/IOException
    //   1627	1649	284	java/io/IOException
    //   1655	1681	284	java/io/IOException
    //   1684	1691	284	java/io/IOException
    //   1694	1723	284	java/io/IOException
    //   1726	1737	284	java/io/IOException
    //   1750	1772	284	java/io/IOException
    //   1777	1787	284	java/io/IOException
    //   1790	1810	284	java/io/IOException
    //   1818	1825	284	java/io/IOException
    //   1833	1837	284	java/io/IOException
    //   1837	1898	284	java/io/IOException
    //   1898	1922	284	java/io/IOException
    //   1936	1949	284	java/io/IOException
    //   1949	1968	284	java/io/IOException
    //   1968	1987	284	java/io/IOException
    //   1997	2007	284	java/io/IOException
    //   2013	2029	284	java/io/IOException
    //   2034	2059	284	java/io/IOException
    //   2068	2078	284	java/io/IOException
    //   2089	2105	284	java/io/IOException
    //   2108	2122	284	java/io/IOException
    //   2125	2149	284	java/io/IOException
    //   2149	2185	284	java/io/IOException
    //   2188	2196	284	java/io/IOException
    //   2199	2215	284	java/io/IOException
    //   2220	2237	284	java/io/IOException
    //   2240	2248	284	java/io/IOException
    //   2251	2266	284	java/io/IOException
    //   2266	2274	284	java/io/IOException
    //   2274	2283	284	java/io/IOException
    //   2283	2286	284	java/io/IOException
    //   2289	2306	284	java/io/IOException
    //   2309	2317	284	java/io/IOException
    //   2320	2352	284	java/io/IOException
    //   2355	2363	284	java/io/IOException
    //   2368	2423	284	java/io/IOException
    //   2426	2438	284	java/io/IOException
    //   2441	2467	284	java/io/IOException
    //   2508	2529	284	java/io/IOException
    //   2537	2553	284	java/io/IOException
    //   2596	2617	284	java/io/IOException
    //   2625	2641	284	java/io/IOException
    //   2646	2667	284	java/io/IOException
    //   2675	2694	284	java/io/IOException
    //   2694	2723	284	java/io/IOException
    //   2723	2743	284	java/io/IOException
    //   2745	2756	284	java/io/IOException
    //   2759	2763	284	java/io/IOException
    //   2765	2786	284	java/io/IOException
    //   2803	2806	284	java/io/IOException
    //   2806	2834	284	java/io/IOException
    //   2837	2905	284	java/io/IOException
    //   2905	2909	284	java/io/IOException
    //   2912	2946	284	java/io/IOException
    //   2951	2984	284	java/io/IOException
    //   2989	2997	284	java/io/IOException
    //   3000	3033	284	java/io/IOException
    //   3037	3050	284	java/io/IOException
    //   3055	3069	284	java/io/IOException
    //   3075	3092	284	java/io/IOException
    //   3098	3106	284	java/io/IOException
    //   3109	3140	284	java/io/IOException
    //   3143	3186	284	java/io/IOException
    //   3189	3195	284	java/io/IOException
    //   3198	3279	284	java/io/IOException
    //   3279	3307	284	java/io/IOException
    //   3311	3318	284	java/io/IOException
    //   3321	3342	284	java/io/IOException
    //   3342	3350	284	java/io/IOException
    //   3353	3375	284	java/io/IOException
    //   3378	3438	284	java/io/IOException
    //   3441	3479	284	java/io/IOException
    //   3485	3535	284	java/io/IOException
    //   3546	3581	284	java/io/IOException
    //   3584	3603	284	java/io/IOException
    //   3606	3634	284	java/io/IOException
    //   3637	3641	284	java/io/IOException
    //   3644	3657	284	java/io/IOException
    //   3669	3677	284	java/io/IOException
    //   3680	3697	284	java/io/IOException
    //   3700	3707	284	java/io/IOException
    //   3715	3726	284	java/io/IOException
    //   3729	3820	284	java/io/IOException
    //   3820	3829	284	java/io/IOException
    //   3835	3864	284	java/io/IOException
    //   3867	3886	284	java/io/IOException
    //   3894	3923	284	java/io/IOException
    //   3928	3939	284	java/io/IOException
    //   3939	3949	284	java/io/IOException
    //   3949	3961	284	java/io/IOException
    //   3964	3983	284	java/io/IOException
    //   3986	4010	284	java/io/IOException
    //   4010	4027	284	java/io/IOException
    //   4030	4045	284	java/io/IOException
    //   4050	4062	284	java/io/IOException
    //   4065	4126	284	java/io/IOException
    //   4129	4138	284	java/io/IOException
    //   4202	4204	284	java/io/IOException
    //   4226	4229	284	java/io/IOException
    //   4231	4233	284	java/io/IOException
    //   4249	4252	284	java/io/IOException
    //   4256	4259	284	java/io/IOException
    //   0	72	803	java/lang/RuntimeException
    //   72	88	803	java/lang/RuntimeException
    //   91	114	803	java/lang/RuntimeException
    //   119	134	803	java/lang/RuntimeException
    //   134	167	803	java/lang/RuntimeException
    //   169	176	803	java/lang/RuntimeException
    //   179	190	803	java/lang/RuntimeException
    //   195	203	803	java/lang/RuntimeException
    //   206	227	803	java/lang/RuntimeException
    //   264	281	803	java/lang/RuntimeException
    //   321	346	803	java/lang/RuntimeException
    //   351	360	803	java/lang/RuntimeException
    //   363	372	803	java/lang/RuntimeException
    //   383	415	803	java/lang/RuntimeException
    //   421	450	803	java/lang/RuntimeException
    //   460	469	803	java/lang/RuntimeException
    //   475	481	803	java/lang/RuntimeException
    //   484	506	803	java/lang/RuntimeException
    //   506	520	803	java/lang/RuntimeException
    //   525	531	803	java/lang/RuntimeException
    //   536	578	803	java/lang/RuntimeException
    //   578	586	803	java/lang/RuntimeException
    //   591	596	803	java/lang/RuntimeException
    //   599	620	803	java/lang/RuntimeException
    //   620	640	803	java/lang/RuntimeException
    //   643	659	803	java/lang/RuntimeException
    //   659	680	803	java/lang/RuntimeException
    //   680	697	803	java/lang/RuntimeException
    //   697	702	803	java/lang/RuntimeException
    //   702	709	803	java/lang/RuntimeException
    //   709	800	803	java/lang/RuntimeException
    //   837	917	803	java/lang/RuntimeException
    //   917	940	803	java/lang/RuntimeException
    //   943	959	803	java/lang/RuntimeException
    //   959	966	803	java/lang/RuntimeException
    //   974	981	803	java/lang/RuntimeException
    //   984	1069	803	java/lang/RuntimeException
    //   1069	1095	803	java/lang/RuntimeException
    //   1098	1127	803	java/lang/RuntimeException
    //   1138	1195	803	java/lang/RuntimeException
    //   1200	1226	803	java/lang/RuntimeException
    //   1229	1261	803	java/lang/RuntimeException
    //   1264	1275	803	java/lang/RuntimeException
    //   1278	1296	803	java/lang/RuntimeException
    //   1299	1309	803	java/lang/RuntimeException
    //   1312	1343	803	java/lang/RuntimeException
    //   1348	1377	803	java/lang/RuntimeException
    //   1380	1423	803	java/lang/RuntimeException
    //   1428	1438	803	java/lang/RuntimeException
    //   1441	1512	803	java/lang/RuntimeException
    //   1518	1550	803	java/lang/RuntimeException
    //   1555	1597	803	java/lang/RuntimeException
    //   1602	1624	803	java/lang/RuntimeException
    //   1627	1649	803	java/lang/RuntimeException
    //   1655	1681	803	java/lang/RuntimeException
    //   1684	1691	803	java/lang/RuntimeException
    //   1694	1723	803	java/lang/RuntimeException
    //   1726	1737	803	java/lang/RuntimeException
    //   1750	1772	803	java/lang/RuntimeException
    //   1777	1787	803	java/lang/RuntimeException
    //   1790	1810	803	java/lang/RuntimeException
    //   1818	1825	803	java/lang/RuntimeException
    //   1833	1837	803	java/lang/RuntimeException
    //   1837	1898	803	java/lang/RuntimeException
    //   1898	1922	803	java/lang/RuntimeException
    //   1936	1949	803	java/lang/RuntimeException
    //   1949	1968	803	java/lang/RuntimeException
    //   1968	1987	803	java/lang/RuntimeException
    //   1997	2007	803	java/lang/RuntimeException
    //   2013	2029	803	java/lang/RuntimeException
    //   2034	2059	803	java/lang/RuntimeException
    //   2068	2078	803	java/lang/RuntimeException
    //   2089	2105	803	java/lang/RuntimeException
    //   2108	2122	803	java/lang/RuntimeException
    //   2125	2149	803	java/lang/RuntimeException
    //   2149	2185	803	java/lang/RuntimeException
    //   2188	2196	803	java/lang/RuntimeException
    //   2199	2215	803	java/lang/RuntimeException
    //   2220	2237	803	java/lang/RuntimeException
    //   2240	2248	803	java/lang/RuntimeException
    //   2251	2266	803	java/lang/RuntimeException
    //   2266	2274	803	java/lang/RuntimeException
    //   2274	2283	803	java/lang/RuntimeException
    //   2283	2286	803	java/lang/RuntimeException
    //   2289	2306	803	java/lang/RuntimeException
    //   2309	2317	803	java/lang/RuntimeException
    //   2320	2352	803	java/lang/RuntimeException
    //   2355	2363	803	java/lang/RuntimeException
    //   2368	2423	803	java/lang/RuntimeException
    //   2426	2438	803	java/lang/RuntimeException
    //   2441	2467	803	java/lang/RuntimeException
    //   2508	2529	803	java/lang/RuntimeException
    //   2537	2553	803	java/lang/RuntimeException
    //   2596	2617	803	java/lang/RuntimeException
    //   2625	2641	803	java/lang/RuntimeException
    //   2646	2667	803	java/lang/RuntimeException
    //   2675	2694	803	java/lang/RuntimeException
    //   2694	2723	803	java/lang/RuntimeException
    //   2723	2743	803	java/lang/RuntimeException
    //   2745	2756	803	java/lang/RuntimeException
    //   2759	2763	803	java/lang/RuntimeException
    //   2765	2786	803	java/lang/RuntimeException
    //   2803	2806	803	java/lang/RuntimeException
    //   2806	2834	803	java/lang/RuntimeException
    //   2837	2905	803	java/lang/RuntimeException
    //   2905	2909	803	java/lang/RuntimeException
    //   2912	2946	803	java/lang/RuntimeException
    //   2951	2984	803	java/lang/RuntimeException
    //   2989	2997	803	java/lang/RuntimeException
    //   3000	3033	803	java/lang/RuntimeException
    //   3037	3050	803	java/lang/RuntimeException
    //   3055	3069	803	java/lang/RuntimeException
    //   3075	3092	803	java/lang/RuntimeException
    //   3098	3106	803	java/lang/RuntimeException
    //   3109	3140	803	java/lang/RuntimeException
    //   3143	3186	803	java/lang/RuntimeException
    //   3189	3195	803	java/lang/RuntimeException
    //   3198	3279	803	java/lang/RuntimeException
    //   3279	3307	803	java/lang/RuntimeException
    //   3311	3318	803	java/lang/RuntimeException
    //   3321	3342	803	java/lang/RuntimeException
    //   3342	3350	803	java/lang/RuntimeException
    //   3353	3375	803	java/lang/RuntimeException
    //   3378	3438	803	java/lang/RuntimeException
    //   3441	3479	803	java/lang/RuntimeException
    //   3485	3535	803	java/lang/RuntimeException
    //   3546	3581	803	java/lang/RuntimeException
    //   3584	3603	803	java/lang/RuntimeException
    //   3606	3634	803	java/lang/RuntimeException
    //   3637	3641	803	java/lang/RuntimeException
    //   3644	3657	803	java/lang/RuntimeException
    //   3669	3677	803	java/lang/RuntimeException
    //   3680	3697	803	java/lang/RuntimeException
    //   3700	3707	803	java/lang/RuntimeException
    //   3715	3726	803	java/lang/RuntimeException
    //   3729	3820	803	java/lang/RuntimeException
    //   3820	3829	803	java/lang/RuntimeException
    //   3835	3864	803	java/lang/RuntimeException
    //   3867	3886	803	java/lang/RuntimeException
    //   3894	3923	803	java/lang/RuntimeException
    //   3928	3939	803	java/lang/RuntimeException
    //   3939	3949	803	java/lang/RuntimeException
    //   3949	3961	803	java/lang/RuntimeException
    //   3964	3983	803	java/lang/RuntimeException
    //   3986	4010	803	java/lang/RuntimeException
    //   4010	4027	803	java/lang/RuntimeException
    //   4030	4045	803	java/lang/RuntimeException
    //   4050	4062	803	java/lang/RuntimeException
    //   4065	4126	803	java/lang/RuntimeException
    //   4129	4138	803	java/lang/RuntimeException
    //   4202	4204	803	java/lang/RuntimeException
    //   4226	4229	803	java/lang/RuntimeException
    //   4231	4233	803	java/lang/RuntimeException
    //   4249	4252	803	java/lang/RuntimeException
    //   4256	4259	803	java/lang/RuntimeException
    //   2467	2500	2644	finally
    //   2568	2578	2644	finally
    //   2786	2797	2799	finally
    //   2801	2803	2799	finally
    //   4204	4220	4222	finally
    //   4224	4226	4222	finally
    //   4138	4143	4229	finally
    //   4153	4180	4229	finally
    //   4186	4202	4229	finally
    //   4233	4249	4252	finally
    //   4254	4256	4252	finally
  }

  public final void release()
  {
    while (true)
    {
      try
      {
        boolean bool1 = this.zzacf;
        if (bool1)
          return;
        this.handler.sendEmptyMessage(6);
        boolean bool2 = this.zzacf;
        if (!bool2)
        {
          try
          {
            wait();
          }
          catch (InterruptedException localInterruptedException)
          {
            Thread.currentThread().interrupt();
          }
          continue;
        }
      }
      finally
      {
      }
      this.zzaby.quit();
    }
  }

  public final void stop()
  {
    this.handler.sendEmptyMessage(5);
  }

  public final void zza(zzlr paramzzlr, int paramInt, long paramLong)
  {
    this.handler.obtainMessage(3, new zzlf(paramzzlr, paramInt, paramLong)).sendToTarget();
  }

  public final void zza(zzqj paramzzqj)
  {
    this.handler.obtainMessage(8, paramzzqj).sendToTarget();
  }

  public final void zza(zzql paramzzql, boolean paramBoolean)
  {
    this.handler.obtainMessage(0, 1, 0, paramzzql).sendToTarget();
  }

  public final void zza(zzky[] paramArrayOfzzky)
  {
    if (this.zzacf)
    {
      Log.w("ExoPlayerImplInternal", "Ignoring messages sent after release.");
      return;
    }
    this.zzach = (1 + this.zzach);
    this.handler.obtainMessage(11, paramArrayOfzzky).sendToTarget();
  }

  public final void zzb(zzlr paramzzlr, Object paramObject)
  {
    this.handler.obtainMessage(7, Pair.create(paramzzlr, paramObject)).sendToTarget();
  }

  public final void zzb(zzky[] paramArrayOfzzky)
  {
    try
    {
      if (this.zzacf)
      {
        Log.w("ExoPlayerImplInternal", "Ignoring messages sent after release.");
        return;
      }
      int i = this.zzach;
      this.zzach = (i + 1);
      this.handler.obtainMessage(11, paramArrayOfzzky).sendToTarget();
      while (true)
      {
        int j = this.zzaci;
        if (j > i)
          break;
        try
        {
          wait();
        }
        catch (InterruptedException localInterruptedException)
        {
          Thread.currentThread().interrupt();
        }
      }
    }
    finally
    {
    }
  }

  public final void zzd(boolean paramBoolean)
  {
    Handler localHandler = this.handler;
    if (paramBoolean);
    for (int i = 1; ; i = 0)
    {
      localHandler.obtainMessage(1, i, 0).sendToTarget();
      return;
    }
  }

  public final void zzgv()
  {
    this.handler.sendEmptyMessage(10);
  }
}

/* Location:           E:\Study\Tools\apktool2_2\dex2jar-0.0.9.15\classes_viber_2_dex2jar.jar
 * Qualified Name:     com.google.android.gms.internal.ads.zzlc
 * JD-Core Version:    0.6.2
 */