package com.google.android.gms.internal.ads;

final class zzqf
{
  private final zznp zzbbf;
  private final zznn[] zzbix;
  private zznn zzbiy;

  public zzqf(zznn[] paramArrayOfzznn, zznp paramzznp)
  {
    this.zzbix = paramArrayOfzznn;
    this.zzbbf = paramzznp;
  }

  public final void release()
  {
    if (this.zzbiy != null)
    {
      this.zzbiy.release();
      this.zzbiy = null;
    }
  }

  // ERROR //
  public final zznn zza(zzno paramzzno, android.net.Uri paramUri)
    throws java.io.IOException, java.lang.InterruptedException
  {
    // Byte code:
    //   0: aload_0
    //   1: getfield 22	com/google/android/gms/internal/ads/zzqf:zzbiy	Lcom/google/android/gms/internal/ads/zznn;
    //   4: ifnull +8 -> 12
    //   7: aload_0
    //   8: getfield 22	com/google/android/gms/internal/ads/zzqf:zzbiy	Lcom/google/android/gms/internal/ads/zznn;
    //   11: areturn
    //   12: aload_0
    //   13: getfield 17	com/google/android/gms/internal/ads/zzqf:zzbix	[Lcom/google/android/gms/internal/ads/zznn;
    //   16: astore_3
    //   17: aload_3
    //   18: arraylength
    //   19: istore 4
    //   21: iconst_0
    //   22: istore 5
    //   24: iload 5
    //   26: iload 4
    //   28: if_icmpge +32 -> 60
    //   31: aload_3
    //   32: iload 5
    //   34: aaload
    //   35: astore 7
    //   37: aload 7
    //   39: aload_1
    //   40: invokeinterface 37 2 0
    //   45: ifeq +76 -> 121
    //   48: aload_0
    //   49: aload 7
    //   51: putfield 22	com/google/android/gms/internal/ads/zzqf:zzbiy	Lcom/google/android/gms/internal/ads/zznn;
    //   54: aload_1
    //   55: invokeinterface 42 1 0
    //   60: aload_0
    //   61: getfield 22	com/google/android/gms/internal/ads/zzqf:zzbiy	Lcom/google/android/gms/internal/ads/zznn;
    //   64: ifnonnull +91 -> 155
    //   67: aload_0
    //   68: getfield 17	com/google/android/gms/internal/ads/zzqf:zzbix	[Lcom/google/android/gms/internal/ads/zznn;
    //   71: invokestatic 47	com/google/android/gms/internal/ads/zzsy:zza	([Ljava/lang/Object;)Ljava/lang/String;
    //   74: astore 6
    //   76: new 49	com/google/android/gms/internal/ads/zzrc
    //   79: dup
    //   80: new 51	java/lang/StringBuilder
    //   83: dup
    //   84: bipush 58
    //   86: aload 6
    //   88: invokestatic 57	java/lang/String:valueOf	(Ljava/lang/Object;)Ljava/lang/String;
    //   91: invokevirtual 61	java/lang/String:length	()I
    //   94: iadd
    //   95: invokespecial 64	java/lang/StringBuilder:<init>	(I)V
    //   98: ldc 66
    //   100: invokevirtual 70	java/lang/StringBuilder:append	(Ljava/lang/String;)Ljava/lang/StringBuilder;
    //   103: aload 6
    //   105: invokevirtual 70	java/lang/StringBuilder:append	(Ljava/lang/String;)Ljava/lang/StringBuilder;
    //   108: ldc 72
    //   110: invokevirtual 70	java/lang/StringBuilder:append	(Ljava/lang/String;)Ljava/lang/StringBuilder;
    //   113: invokevirtual 76	java/lang/StringBuilder:toString	()Ljava/lang/String;
    //   116: aload_2
    //   117: invokespecial 79	com/google/android/gms/internal/ads/zzrc:<init>	(Ljava/lang/String;Landroid/net/Uri;)V
    //   120: athrow
    //   121: aload_1
    //   122: invokeinterface 42 1 0
    //   127: iinc 5 1
    //   130: goto -106 -> 24
    //   133: astore 9
    //   135: aload_1
    //   136: invokeinterface 42 1 0
    //   141: goto -14 -> 127
    //   144: astore 8
    //   146: aload_1
    //   147: invokeinterface 42 1 0
    //   152: aload 8
    //   154: athrow
    //   155: aload_0
    //   156: getfield 22	com/google/android/gms/internal/ads/zzqf:zzbiy	Lcom/google/android/gms/internal/ads/zznn;
    //   159: aload_0
    //   160: getfield 19	com/google/android/gms/internal/ads/zzqf:zzbbf	Lcom/google/android/gms/internal/ads/zznp;
    //   163: invokeinterface 82 2 0
    //   168: aload_0
    //   169: getfield 22	com/google/android/gms/internal/ads/zzqf:zzbiy	Lcom/google/android/gms/internal/ads/zznn;
    //   172: areturn
    //
    // Exception table:
    //   from	to	target	type
    //   37	54	133	java/io/EOFException
    //   37	54	144	finally
  }
}

/* Location:           E:\Study\Tools\apktool2_2\dex2jar-0.0.9.15\classes_viber_2_dex2jar.jar
 * Qualified Name:     com.google.android.gms.internal.ads.zzqf
 * JD-Core Version:    0.6.2
 */