package com.yandex.metrica.impl;

public class au
{
  // ERROR //
  public void a(as paramas)
  {
    // Byte code:
    //   0: aconst_null
    //   1: astore_2
    //   2: aload_1
    //   3: invokevirtual 17	com/yandex/metrica/impl/as:f	()V
    //   6: aload_1
    //   7: invokevirtual 21	com/yandex/metrica/impl/as:e	()Lcom/yandex/metrica/impl/ob/io;
    //   10: invokevirtual 26	com/yandex/metrica/impl/ob/io:a	()Ljava/net/HttpURLConnection;
    //   13: astore 15
    //   15: aload 15
    //   17: astore 14
    //   19: aload_1
    //   20: invokevirtual 30	com/yandex/metrica/impl/as:D	()Ljava/util/Map;
    //   23: invokeinterface 36 1 0
    //   28: invokeinterface 42 1 0
    //   33: astore 17
    //   35: aload 17
    //   37: invokeinterface 48 1 0
    //   42: ifeq +92 -> 134
    //   45: aload 17
    //   47: invokeinterface 52 1 0
    //   52: checkcast 54	java/util/Map$Entry
    //   55: astore 36
    //   57: aload 14
    //   59: aload 36
    //   61: invokeinterface 57 1 0
    //   66: checkcast 59	java/lang/String
    //   69: ldc 61
    //   71: aload 36
    //   73: invokeinterface 64 1 0
    //   78: checkcast 66	java/lang/Iterable
    //   81: invokestatic 72	android/text/TextUtils:join	(Ljava/lang/CharSequence;Ljava/lang/Iterable;)Ljava/lang/String;
    //   84: invokevirtual 78	java/net/HttpURLConnection:setRequestProperty	(Ljava/lang/String;Ljava/lang/String;)V
    //   87: goto -52 -> 35
    //   90: astore 16
    //   92: aconst_null
    //   93: astore 4
    //   95: aload 14
    //   97: astore 5
    //   99: aconst_null
    //   100: astore 6
    //   102: aconst_null
    //   103: astore 7
    //   105: aload_1
    //   106: invokevirtual 81	com/yandex/metrica/impl/as:i	()V
    //   109: aload 6
    //   111: invokestatic 86	com/yandex/metrica/impl/bw:a	(Ljava/io/Closeable;)V
    //   114: aload 7
    //   116: invokestatic 86	com/yandex/metrica/impl/bw:a	(Ljava/io/Closeable;)V
    //   119: aload 4
    //   121: invokestatic 86	com/yandex/metrica/impl/bw:a	(Ljava/io/Closeable;)V
    //   124: aload_2
    //   125: invokestatic 86	com/yandex/metrica/impl/bw:a	(Ljava/io/Closeable;)V
    //   128: aload 5
    //   130: invokestatic 89	com/yandex/metrica/impl/bw:a	(Ljava/net/HttpURLConnection;)V
    //   133: return
    //   134: iconst_2
    //   135: aload_1
    //   136: invokevirtual 93	com/yandex/metrica/impl/as:l	()I
    //   139: if_icmpne +527 -> 666
    //   142: aload_1
    //   143: invokevirtual 97	com/yandex/metrica/impl/as:m	()[B
    //   146: astore 28
    //   148: aload 28
    //   150: ifnull +516 -> 666
    //   153: aload 28
    //   155: arraylength
    //   156: ifle +510 -> 666
    //   159: aload_1
    //   160: invokevirtual 101	com/yandex/metrica/impl/as:C	()Ljava/lang/Long;
    //   163: astore 29
    //   165: aload 14
    //   167: iconst_1
    //   168: invokevirtual 105	java/net/HttpURLConnection:setDoOutput	(Z)V
    //   171: aload 29
    //   173: ifnull +24 -> 197
    //   176: aload 14
    //   178: ldc 107
    //   180: getstatic 113	java/util/concurrent/TimeUnit:MILLISECONDS	Ljava/util/concurrent/TimeUnit;
    //   183: aload 29
    //   185: invokevirtual 119	java/lang/Long:longValue	()J
    //   188: invokevirtual 123	java/util/concurrent/TimeUnit:toSeconds	(J)J
    //   191: invokestatic 127	java/lang/String:valueOf	(J)Ljava/lang/String;
    //   194: invokevirtual 78	java/net/HttpURLConnection:setRequestProperty	(Ljava/lang/String;Ljava/lang/String;)V
    //   197: aload 14
    //   199: invokevirtual 131	java/net/HttpURLConnection:getOutputStream	()Ljava/io/OutputStream;
    //   202: astore 30
    //   204: aload 30
    //   206: astore 4
    //   208: new 133	java/io/BufferedOutputStream
    //   211: dup
    //   212: aload 4
    //   214: aload 28
    //   216: arraylength
    //   217: invokespecial 136	java/io/BufferedOutputStream:<init>	(Ljava/io/OutputStream;I)V
    //   220: astore 31
    //   222: aload 31
    //   224: aload_1
    //   225: invokevirtual 97	com/yandex/metrica/impl/as:m	()[B
    //   228: invokevirtual 142	java/io/OutputStream:write	([B)V
    //   231: aload 31
    //   233: invokevirtual 145	java/io/OutputStream:flush	()V
    //   236: aload 4
    //   238: invokestatic 86	com/yandex/metrica/impl/bw:a	(Ljava/io/Closeable;)V
    //   241: aload 4
    //   243: astore 10
    //   245: aload 31
    //   247: astore 9
    //   249: aload 14
    //   251: invokevirtual 148	java/net/HttpURLConnection:getResponseCode	()I
    //   254: istore 19
    //   256: aload_1
    //   257: iload 19
    //   259: invokevirtual 151	com/yandex/metrica/impl/as:a	(I)V
    //   262: aload_1
    //   263: aload 14
    //   265: invokevirtual 154	java/net/HttpURLConnection:getHeaderFields	()Ljava/util/Map;
    //   268: invokevirtual 157	com/yandex/metrica/impl/as:a	(Ljava/util/Map;)V
    //   271: aload_1
    //   272: iload 19
    //   274: invokevirtual 161	com/yandex/metrica/impl/as:b	(I)Z
    //   277: ifeq +70 -> 347
    //   280: aload 14
    //   282: invokevirtual 165	java/net/HttpURLConnection:getInputStream	()Ljava/io/InputStream;
    //   285: astore 22
    //   287: aload 22
    //   289: astore 21
    //   291: new 167	java/io/BufferedInputStream
    //   294: dup
    //   295: aload 21
    //   297: sipush 8000
    //   300: invokespecial 170	java/io/BufferedInputStream:<init>	(Ljava/io/InputStream;I)V
    //   303: astore 13
    //   305: aload_1
    //   306: aload 13
    //   308: ldc 171
    //   310: invokestatic 176	com/yandex/metrica/impl/w:a	(Ljava/io/InputStream;I)[B
    //   313: invokevirtual 178	com/yandex/metrica/impl/as:b	([B)V
    //   316: aload 21
    //   318: invokestatic 86	com/yandex/metrica/impl/bw:a	(Ljava/io/Closeable;)V
    //   321: aload 9
    //   323: invokestatic 86	com/yandex/metrica/impl/bw:a	(Ljava/io/Closeable;)V
    //   326: aload 13
    //   328: invokestatic 86	com/yandex/metrica/impl/bw:a	(Ljava/io/Closeable;)V
    //   331: aload 10
    //   333: invokestatic 86	com/yandex/metrica/impl/bw:a	(Ljava/io/Closeable;)V
    //   336: aload 21
    //   338: invokestatic 86	com/yandex/metrica/impl/bw:a	(Ljava/io/Closeable;)V
    //   341: aload 14
    //   343: invokestatic 89	com/yandex/metrica/impl/bw:a	(Ljava/net/HttpURLConnection;)V
    //   346: return
    //   347: new 167	java/io/BufferedInputStream
    //   350: dup
    //   351: aload 14
    //   353: invokevirtual 181	java/net/HttpURLConnection:getErrorStream	()Ljava/io/InputStream;
    //   356: sipush 8000
    //   359: invokespecial 170	java/io/BufferedInputStream:<init>	(Ljava/io/InputStream;I)V
    //   362: astore 20
    //   364: aload 20
    //   366: astore 13
    //   368: aconst_null
    //   369: astore 21
    //   371: goto -50 -> 321
    //   374: astore 11
    //   376: aconst_null
    //   377: astore 10
    //   379: aconst_null
    //   380: astore 14
    //   382: aconst_null
    //   383: astore 9
    //   385: aconst_null
    //   386: astore 13
    //   388: aload 9
    //   390: invokestatic 86	com/yandex/metrica/impl/bw:a	(Ljava/io/Closeable;)V
    //   393: aload 13
    //   395: invokestatic 86	com/yandex/metrica/impl/bw:a	(Ljava/io/Closeable;)V
    //   398: aload 10
    //   400: invokestatic 86	com/yandex/metrica/impl/bw:a	(Ljava/io/Closeable;)V
    //   403: aload_2
    //   404: invokestatic 86	com/yandex/metrica/impl/bw:a	(Ljava/io/Closeable;)V
    //   407: aload 14
    //   409: invokestatic 89	com/yandex/metrica/impl/bw:a	(Ljava/net/HttpURLConnection;)V
    //   412: aload 11
    //   414: athrow
    //   415: astore 11
    //   417: aconst_null
    //   418: astore 13
    //   420: aconst_null
    //   421: astore_2
    //   422: aconst_null
    //   423: astore 10
    //   425: aconst_null
    //   426: astore 9
    //   428: goto -40 -> 388
    //   431: astore 35
    //   433: aload 4
    //   435: astore 10
    //   437: aload 35
    //   439: astore 11
    //   441: aconst_null
    //   442: astore 13
    //   444: aconst_null
    //   445: astore_2
    //   446: aconst_null
    //   447: astore 9
    //   449: goto -61 -> 388
    //   452: astore 33
    //   454: aload 31
    //   456: astore 9
    //   458: aload 4
    //   460: astore 10
    //   462: aload 33
    //   464: astore 11
    //   466: aconst_null
    //   467: astore 13
    //   469: aconst_null
    //   470: astore_2
    //   471: goto -83 -> 388
    //   474: astore 11
    //   476: aconst_null
    //   477: astore 13
    //   479: aconst_null
    //   480: astore_2
    //   481: goto -93 -> 388
    //   484: astore 27
    //   486: aload 21
    //   488: astore_2
    //   489: aload 27
    //   491: astore 11
    //   493: aconst_null
    //   494: astore 13
    //   496: goto -108 -> 388
    //   499: astore 25
    //   501: aload 21
    //   503: astore_2
    //   504: aload 25
    //   506: astore 11
    //   508: goto -120 -> 388
    //   511: astore 8
    //   513: aload 6
    //   515: astore 9
    //   517: aload 4
    //   519: astore 10
    //   521: aload 8
    //   523: astore 11
    //   525: aload 5
    //   527: astore 12
    //   529: aload 7
    //   531: astore 13
    //   533: aload 12
    //   535: astore 14
    //   537: goto -149 -> 388
    //   540: astore_3
    //   541: aconst_null
    //   542: astore 4
    //   544: aconst_null
    //   545: astore 5
    //   547: aconst_null
    //   548: astore_2
    //   549: aconst_null
    //   550: astore 6
    //   552: aconst_null
    //   553: astore 7
    //   555: goto -450 -> 105
    //   558: astore 34
    //   560: aload 14
    //   562: astore 5
    //   564: aconst_null
    //   565: astore_2
    //   566: aconst_null
    //   567: astore 6
    //   569: aconst_null
    //   570: astore 7
    //   572: goto -467 -> 105
    //   575: astore 32
    //   577: aload 31
    //   579: astore 6
    //   581: aload 14
    //   583: astore 5
    //   585: aconst_null
    //   586: astore_2
    //   587: aconst_null
    //   588: astore 7
    //   590: goto -485 -> 105
    //   593: astore 18
    //   595: aload 10
    //   597: astore 4
    //   599: aload 14
    //   601: astore 5
    //   603: aload 9
    //   605: astore 6
    //   607: aconst_null
    //   608: astore_2
    //   609: aconst_null
    //   610: astore 7
    //   612: goto -507 -> 105
    //   615: astore 26
    //   617: aload 14
    //   619: astore 5
    //   621: aload 21
    //   623: astore_2
    //   624: aload 10
    //   626: astore 4
    //   628: aload 9
    //   630: astore 6
    //   632: aconst_null
    //   633: astore 7
    //   635: goto -530 -> 105
    //   638: astore 23
    //   640: aload 21
    //   642: astore_2
    //   643: aload 10
    //   645: astore 4
    //   647: aload 9
    //   649: astore 6
    //   651: aload 14
    //   653: astore 24
    //   655: aload 13
    //   657: astore 7
    //   659: aload 24
    //   661: astore 5
    //   663: goto -558 -> 105
    //   666: aconst_null
    //   667: astore 10
    //   669: aconst_null
    //   670: astore 9
    //   672: goto -423 -> 249
    //
    // Exception table:
    //   from	to	target	type
    //   19	35	90	java/lang/Throwable
    //   35	87	90	java/lang/Throwable
    //   134	148	90	java/lang/Throwable
    //   153	171	90	java/lang/Throwable
    //   176	197	90	java/lang/Throwable
    //   197	204	90	java/lang/Throwable
    //   2	15	374	finally
    //   19	35	415	finally
    //   35	87	415	finally
    //   134	148	415	finally
    //   153	171	415	finally
    //   176	197	415	finally
    //   197	204	415	finally
    //   208	222	431	finally
    //   222	241	452	finally
    //   249	287	474	finally
    //   347	364	474	finally
    //   291	305	484	finally
    //   305	321	499	finally
    //   105	109	511	finally
    //   2	15	540	java/lang/Throwable
    //   208	222	558	java/lang/Throwable
    //   222	241	575	java/lang/Throwable
    //   249	287	593	java/lang/Throwable
    //   347	364	593	java/lang/Throwable
    //   291	305	615	java/lang/Throwable
    //   305	321	638	java/lang/Throwable
  }
}

/* Location:           E:\Study\Tools\apktool2_2\dex2jar-0.0.9.15\classes_viber_4_dex2jar.jar
 * Qualified Name:     com.yandex.metrica.impl.au
 * JD-Core Version:    0.6.2
 */