package com.yandex.metrica.impl;

import android.text.TextUtils;
import android.util.Pair;
import com.yandex.metrica.impl.ob.hk;
import com.yandex.metrica.impl.ob.hp;
import com.yandex.metrica.impl.ob.iy;
import com.yandex.metrica.impl.ob.kt.a.a.a;
import com.yandex.metrica.impl.ob.kt.a.c;
import com.yandex.metrica.impl.ob.ml;
import com.yandex.metrica.impl.ob.ml.a;
import com.yandex.metrica.impl.ob.mm;
import com.yandex.metrica.impl.ob.mn;
import com.yandex.metrica.impl.ob.my;
import com.yandex.metrica.impl.ob.nz;
import com.yandex.metrica.impl.ob.nz.a;
import com.yandex.metrica.impl.ob.ol;
import com.yandex.metrica.impl.ob.oq;
import java.text.DateFormat;
import java.text.SimpleDateFormat;
import java.util.ArrayList;
import java.util.Collections;
import java.util.Date;
import java.util.HashMap;
import java.util.Iterator;
import java.util.List;
import java.util.Locale;
import java.util.Map;
import java.util.concurrent.TimeUnit;
import org.json.JSONArray;
import org.json.JSONException;
import org.json.JSONObject;

public class br
{
  private static final Map<String, br.a.a> a = Collections.unmodifiableMap(new HashMap()
  {
  });

  private static a a(JSONObject paramJSONObject)
    throws JSONException
  {
    JSONObject localJSONObject = paramJSONObject.getJSONObject("headers");
    ArrayList localArrayList = new ArrayList(localJSONObject.length());
    Iterator localIterator = localJSONObject.keys();
    while (localIterator.hasNext())
    {
      String str = (String)localIterator.next();
      JSONArray localJSONArray = localJSONObject.getJSONArray(str);
      for (int i = 0; i < localJSONArray.length(); i++)
        localArrayList.add(new Pair(str, localJSONArray.getString(i)));
    }
    return new a(paramJSONObject.optString("id", null), paramJSONObject.optString("url", null), paramJSONObject.optString("method", null), localArrayList, Long.valueOf(paramJSONObject.getLong("delay_seconds")), b(paramJSONObject));
  }

  private static kt.a.c a(JSONObject paramJSONObject, boolean paramBoolean1, boolean paramBoolean2)
  {
    kt.a.c localc = new kt.a.c();
    localc.b = oq.a(nz.a(paramJSONObject, "min_update_interval_seconds"), TimeUnit.SECONDS, localc.b);
    localc.c = oq.a(nz.d(paramJSONObject, "min_update_distance_meters"), localc.c);
    localc.d = oq.a(nz.b(paramJSONObject, "records_count_to_force_flush"), localc.d);
    localc.e = oq.a(nz.b(paramJSONObject, "max_records_count_in_batch"), localc.e);
    localc.f = oq.a(nz.a(paramJSONObject, "max_age_seconds_to_force_flush"), TimeUnit.SECONDS, localc.f);
    localc.g = oq.a(nz.b(paramJSONObject, "max_records_to_store_locally"), localc.g);
    localc.h = paramBoolean1;
    localc.j = oq.a(nz.a(paramJSONObject, "lbs_min_update_interval_seconds"), TimeUnit.SECONDS, localc.j);
    localc.i = paramBoolean2;
    return localc;
  }

  public static Long a(Map<String, List<String>> paramMap)
  {
    if (!bw.a(paramMap))
    {
      List localList = (List)paramMap.get("Date");
      if (!bw.a(localList))
        try
        {
          String str = (String)localList.get(0);
          Long localLong = Long.valueOf(new SimpleDateFormat("E, d MMM yyyy HH:mm:ss z", Locale.US).parse(str).getTime());
          return localLong;
        }
        catch (Exception localException)
        {
        }
    }
    return null;
  }

  private static String a(JSONObject paramJSONObject, String paramString)
  {
    try
    {
      String str = paramJSONObject.getJSONObject(paramString).getString("value");
      return str;
    }
    catch (Exception localException)
    {
    }
    return "";
  }

  static void a(b paramb, nz.a parama)
  {
    JSONObject localJSONObject1 = parama.optJSONObject("permissions");
    if (localJSONObject1 != null)
    {
      JSONArray localJSONArray = localJSONObject1.optJSONArray("list");
      if (localJSONArray != null)
      {
        int i = 0;
        if (i < localJSONArray.length())
        {
          JSONObject localJSONObject2 = localJSONArray.optJSONObject(i);
          String str;
          boolean bool;
          if (localJSONObject2 != null)
          {
            str = localJSONObject2.optString("name");
            bool = localJSONObject2.optBoolean("enabled");
            if (!TextUtils.isEmpty(str))
              break label88;
            paramb.a("", false);
          }
          while (true)
          {
            i++;
            break;
            label88: paramb.a(str, bool);
          }
        }
      }
    }
  }

  private static void a(b paramb, JSONObject paramJSONObject)
    throws JSONException
  {
    HashMap localHashMap = new HashMap();
    Iterator localIterator = paramJSONObject.keys();
    while (localIterator.hasNext())
    {
      String str = (String)localIterator.next();
      JSONObject localJSONObject = paramJSONObject.optJSONObject(str);
      if ((localJSONObject != null) && (localJSONObject.has("value")))
        localHashMap.put(str, localJSONObject.getString("value"));
    }
    paramb.g(ol.a(localHashMap));
  }

  private static boolean a(String paramString)
  {
    return !TextUtils.isEmpty(paramString);
  }

  private static boolean a(List<String> paramList)
  {
    return !bw.a(paramList);
  }

  private static boolean a(JSONObject paramJSONObject, String paramString, boolean paramBoolean)
    throws JSONException
  {
    boolean bool1 = paramJSONObject.has(paramString);
    boolean bool2 = false;
    if (bool1)
      bool2 = paramJSONObject.getJSONObject(paramString).optBoolean("enabled", paramBoolean);
    return bool2;
  }

  private static kt.a.a.a[] a(JSONArray paramJSONArray, kt.a.a.a[] paramArrayOfa)
  {
    if ((paramJSONArray != null) && (paramJSONArray.length() > 0))
      try
      {
        paramArrayOfa = new kt.a.a.a[paramJSONArray.length()];
        for (int i = 0; i < paramJSONArray.length(); i++)
        {
          paramArrayOfa[i] = new kt.a.a.a();
          JSONObject localJSONObject = paramJSONArray.getJSONObject(i);
          paramArrayOfa[i].b = TimeUnit.SECONDS.toMillis(localJSONObject.getLong("min"));
          paramArrayOfa[i].c = TimeUnit.SECONDS.toMillis(localJSONObject.getLong("max"));
        }
      }
      catch (Exception localException)
      {
      }
    return paramArrayOfa;
  }

  private static String b(JSONObject paramJSONObject, String paramString)
  {
    try
    {
      String str = paramJSONObject.getJSONObject(paramString).getJSONArray("urls").getString(0);
      return str;
    }
    catch (Exception localException)
    {
    }
    return "";
  }

  private static List<br.a.a> b(JSONObject paramJSONObject)
    throws JSONException
  {
    ArrayList localArrayList = new ArrayList();
    if (paramJSONObject.has("accept_network_types"))
    {
      JSONArray localJSONArray = paramJSONObject.getJSONArray("accept_network_types");
      for (int i = 0; i < localJSONArray.length(); i++)
        localArrayList.add(a.get(localJSONArray.getString(i)));
    }
    return localArrayList;
  }

  private static void b(b paramb, nz.a parama)
    throws JSONException
  {
    JSONArray localJSONArray;
    ArrayList localArrayList;
    int i;
    if (parama.has("requests"))
    {
      JSONObject localJSONObject = parama.getJSONObject("requests");
      if (localJSONObject.has("list"))
      {
        localJSONArray = localJSONObject.getJSONArray("list");
        localArrayList = new ArrayList(localJSONArray.length());
        i = 0;
      }
    }
    while (true)
    {
      if (i < localJSONArray.length());
      try
      {
        localArrayList.add(a(localJSONArray.getJSONObject(i)));
        label74: i++;
        continue;
        if (!localArrayList.isEmpty())
          paramb.d(localArrayList);
        return;
      }
      catch (JSONException localJSONException)
      {
        break label74;
      }
    }
  }

  private static List<String> c(JSONObject paramJSONObject, String paramString)
  {
    ArrayList localArrayList;
    try
    {
      JSONArray localJSONArray = paramJSONObject.getJSONObject(paramString).getJSONArray("urls");
      if ((localJSONArray != null) && (localJSONArray.length() > 0))
      {
        localArrayList = new ArrayList(localJSONArray.length());
        for (int i = 0; i < localJSONArray.length(); i++)
          localArrayList.add(localJSONArray.getString(i));
      }
    }
    catch (Exception localException)
    {
      localArrayList = null;
    }
    return localArrayList;
  }

  private static void c(b paramb, nz.a parama)
  {
    JSONObject localJSONObject = parama.optJSONObject("socket");
    if (localJSONObject != null)
    {
      long l = localJSONObject.optLong("seconds_to_live");
      String str = localJSONObject.optString("token");
      JSONArray localJSONArray = localJSONObject.optJSONArray("ports");
      if ((l > 0L) && (a(str)) && (localJSONArray != null) && (localJSONArray.length() > 0))
      {
        ArrayList localArrayList = new ArrayList(localJSONArray.length());
        for (int i = 0; i < localJSONArray.length(); i++)
        {
          int j = localJSONArray.optInt(i);
          if (j != 0)
            localArrayList.add(Integer.valueOf(j));
        }
        if (!localArrayList.isEmpty())
          paramb.a(new mn(l, str, localArrayList));
      }
    }
  }

  // ERROR //
  public b a(byte[] paramArrayOfByte)
  {
    // Byte code:
    //   0: new 277	com/yandex/metrica/impl/br$b
    //   3: dup
    //   4: invokespecial 372	com/yandex/metrica/impl/br$b:<init>	()V
    //   7: astore_2
    //   8: new 248	com/yandex/metrica/impl/ob/nz$a
    //   11: dup
    //   12: new 59	java/lang/String
    //   15: dup
    //   16: aload_1
    //   17: ldc_w 374
    //   20: invokespecial 377	java/lang/String:<init>	([BLjava/lang/String;)V
    //   23: invokespecial 379	com/yandex/metrica/impl/ob/nz$a:<init>	(Ljava/lang/String;)V
    //   26: astore_3
    //   27: ldc 243
    //   29: astore 4
    //   31: ldc 243
    //   33: astore 5
    //   35: aload_3
    //   36: ldc_w 381
    //   39: invokevirtual 251	com/yandex/metrica/impl/ob/nz$a:optJSONObject	(Ljava/lang/String;)Lorg/json/JSONObject;
    //   42: astore 8
    //   44: aload 8
    //   46: ifnull +22 -> 68
    //   49: aload 8
    //   51: ldc_w 383
    //   54: invokevirtual 263	org/json/JSONObject:optString	(Ljava/lang/String;)Ljava/lang/String;
    //   57: astore 5
    //   59: aload 8
    //   61: ldc 238
    //   63: invokevirtual 263	org/json/JSONObject:optString	(Ljava/lang/String;)Ljava/lang/String;
    //   66: astore 4
    //   68: aload_2
    //   69: aload 4
    //   71: invokevirtual 385	com/yandex/metrica/impl/br$b:d	(Ljava/lang/String;)V
    //   74: aload_2
    //   75: aload 5
    //   77: invokevirtual 387	com/yandex/metrica/impl/br$b:e	(Ljava/lang/String;)V
    //   80: aload_2
    //   81: aload_3
    //   82: ldc_w 389
    //   85: invokestatic 391	com/yandex/metrica/impl/br:a	(Lorg/json/JSONObject;Ljava/lang/String;)Ljava/lang/String;
    //   88: invokevirtual 393	com/yandex/metrica/impl/br$b:f	(Ljava/lang/String;)V
    //   91: aload_3
    //   92: ldc_w 395
    //   95: invokevirtual 251	com/yandex/metrica/impl/ob/nz$a:optJSONObject	(Ljava/lang/String;)Lorg/json/JSONObject;
    //   98: astore 9
    //   100: aload 9
    //   102: ifnull +44 -> 146
    //   105: aload 9
    //   107: ldc 253
    //   109: invokevirtual 285	org/json/JSONObject:optJSONObject	(Ljava/lang/String;)Lorg/json/JSONObject;
    //   112: astore 10
    //   114: aload 10
    //   116: ifnull +30 -> 146
    //   119: aload 10
    //   121: ldc_w 397
    //   124: invokevirtual 285	org/json/JSONObject:optJSONObject	(Ljava/lang/String;)Lorg/json/JSONObject;
    //   127: astore 11
    //   129: aload 11
    //   131: ifnull +15 -> 146
    //   134: aload_2
    //   135: aload 11
    //   137: ldc 91
    //   139: aconst_null
    //   140: invokevirtual 89	org/json/JSONObject:optString	(Ljava/lang/String;Ljava/lang/String;)Ljava/lang/String;
    //   143: invokevirtual 399	com/yandex/metrica/impl/br$b:a	(Ljava/lang/String;)V
    //   146: aload_3
    //   147: ldc_w 401
    //   150: new 30	org/json/JSONObject
    //   153: dup
    //   154: invokespecial 402	org/json/JSONObject:<init>	()V
    //   157: invokevirtual 405	com/yandex/metrica/impl/ob/nz$a:a	(Ljava/lang/String;Ljava/lang/Object;)Ljava/lang/Object;
    //   160: checkcast 30	org/json/JSONObject
    //   163: astore 12
    //   165: aload 12
    //   167: ldc 253
    //   169: invokevirtual 288	org/json/JSONObject:has	(Ljava/lang/String;)Z
    //   172: ifeq +156 -> 328
    //   175: aload 12
    //   177: ldc 253
    //   179: invokevirtual 34	org/json/JSONObject:getJSONObject	(Ljava/lang/String;)Lorg/json/JSONObject;
    //   182: astore 51
    //   184: aload 51
    //   186: ldc_w 407
    //   189: invokestatic 409	com/yandex/metrica/impl/br:b	(Lorg/json/JSONObject;Ljava/lang/String;)Ljava/lang/String;
    //   192: astore 52
    //   194: aload 52
    //   196: invokestatic 353	com/yandex/metrica/impl/br:a	(Ljava/lang/String;)Z
    //   199: ifeq +9 -> 208
    //   202: aload_2
    //   203: aload 52
    //   205: invokevirtual 411	com/yandex/metrica/impl/br$b:b	(Ljava/lang/String;)V
    //   208: aload 51
    //   210: ldc_w 413
    //   213: invokestatic 415	com/yandex/metrica/impl/br:c	(Lorg/json/JSONObject;Ljava/lang/String;)Ljava/util/List;
    //   216: astore 53
    //   218: aload 53
    //   220: invokestatic 417	com/yandex/metrica/impl/br:a	(Ljava/util/List;)Z
    //   223: ifeq +9 -> 232
    //   226: aload_2
    //   227: aload 53
    //   229: invokevirtual 419	com/yandex/metrica/impl/br$b:b	(Ljava/util/List;)V
    //   232: aload 51
    //   234: ldc_w 421
    //   237: invokestatic 409	com/yandex/metrica/impl/br:b	(Lorg/json/JSONObject;Ljava/lang/String;)Ljava/lang/String;
    //   240: astore 54
    //   242: aload 54
    //   244: invokestatic 353	com/yandex/metrica/impl/br:a	(Ljava/lang/String;)Z
    //   247: ifeq +9 -> 256
    //   250: aload_2
    //   251: aload 54
    //   253: invokevirtual 423	com/yandex/metrica/impl/br$b:c	(Ljava/lang/String;)V
    //   256: aload 51
    //   258: ldc_w 425
    //   261: invokestatic 415	com/yandex/metrica/impl/br:c	(Lorg/json/JSONObject;Ljava/lang/String;)Ljava/util/List;
    //   264: astore 55
    //   266: aload 55
    //   268: invokestatic 417	com/yandex/metrica/impl/br:a	(Ljava/util/List;)Z
    //   271: ifeq +9 -> 280
    //   274: aload_2
    //   275: aload 55
    //   277: invokevirtual 427	com/yandex/metrica/impl/br$b:c	(Ljava/util/List;)V
    //   280: aload 51
    //   282: ldc_w 429
    //   285: invokestatic 415	com/yandex/metrica/impl/br:c	(Lorg/json/JSONObject;Ljava/lang/String;)Ljava/util/List;
    //   288: astore 56
    //   290: aload 56
    //   292: invokestatic 417	com/yandex/metrica/impl/br:a	(Ljava/util/List;)Z
    //   295: ifeq +9 -> 304
    //   298: aload_2
    //   299: aload 56
    //   301: invokevirtual 431	com/yandex/metrica/impl/br$b:a	(Ljava/util/List;)V
    //   304: aload 51
    //   306: ldc_w 433
    //   309: invokestatic 415	com/yandex/metrica/impl/br:c	(Lorg/json/JSONObject;Ljava/lang/String;)Ljava/util/List;
    //   312: astore 57
    //   314: aload 57
    //   316: invokestatic 417	com/yandex/metrica/impl/br:a	(Ljava/util/List;)Z
    //   319: ifeq +9 -> 328
    //   322: aload_2
    //   323: aload 57
    //   325: invokevirtual 435	com/yandex/metrica/impl/br$b:e	(Ljava/util/List;)V
    //   328: aload_3
    //   329: ldc_w 437
    //   332: new 30	org/json/JSONObject
    //   335: dup
    //   336: invokespecial 402	org/json/JSONObject:<init>	()V
    //   339: invokevirtual 405	com/yandex/metrica/impl/ob/nz$a:a	(Ljava/lang/String;Ljava/lang/Object;)Ljava/lang/Object;
    //   342: checkcast 30	org/json/JSONObject
    //   345: ldc_w 439
    //   348: invokevirtual 285	org/json/JSONObject:optJSONObject	(Ljava/lang/String;)Lorg/json/JSONObject;
    //   351: astore 13
    //   353: aload 13
    //   355: ifnull +9 -> 364
    //   358: aload_2
    //   359: aload 13
    //   361: invokestatic 441	com/yandex/metrica/impl/br:a	(Lcom/yandex/metrica/impl/br$b;Lorg/json/JSONObject;)V
    //   364: aload_3
    //   365: ldc_w 443
    //   368: new 30	org/json/JSONObject
    //   371: dup
    //   372: invokespecial 402	org/json/JSONObject:<init>	()V
    //   375: invokevirtual 405	com/yandex/metrica/impl/ob/nz$a:a	(Ljava/lang/String;Ljava/lang/Object;)Ljava/lang/Object;
    //   378: checkcast 30	org/json/JSONObject
    //   381: astore 14
    //   383: aload_2
    //   384: iconst_0
    //   385: invokevirtual 446	com/yandex/metrica/impl/br$b:b	(Z)V
    //   388: aload_2
    //   389: iconst_0
    //   390: invokevirtual 448	com/yandex/metrica/impl/br$b:c	(Z)V
    //   393: aload 14
    //   395: ldc 253
    //   397: invokevirtual 288	org/json/JSONObject:has	(Ljava/lang/String;)Z
    //   400: ifeq +298 -> 698
    //   403: aload 14
    //   405: ldc 253
    //   407: invokevirtual 34	org/json/JSONObject:getJSONObject	(Ljava/lang/String;)Lorg/json/JSONObject;
    //   410: astore 38
    //   412: aload_2
    //   413: aload 38
    //   415: ldc_w 450
    //   418: iconst_0
    //   419: invokestatic 452	com/yandex/metrica/impl/br:a	(Lorg/json/JSONObject;Ljava/lang/String;Z)Z
    //   422: invokevirtual 446	com/yandex/metrica/impl/br$b:b	(Z)V
    //   425: aload_2
    //   426: aload 38
    //   428: ldc_w 454
    //   431: iconst_0
    //   432: invokestatic 452	com/yandex/metrica/impl/br:a	(Lorg/json/JSONObject;Ljava/lang/String;Z)Z
    //   435: invokevirtual 448	com/yandex/metrica/impl/br$b:c	(Z)V
    //   438: aload_2
    //   439: aload 38
    //   441: ldc_w 342
    //   444: iconst_0
    //   445: invokestatic 452	com/yandex/metrica/impl/br:a	(Lorg/json/JSONObject;Ljava/lang/String;Z)Z
    //   448: invokevirtual 456	com/yandex/metrica/impl/br$b:f	(Z)V
    //   451: aload_2
    //   452: aload 38
    //   454: ldc_w 458
    //   457: iconst_0
    //   458: invokestatic 452	com/yandex/metrica/impl/br:a	(Lorg/json/JSONObject;Ljava/lang/String;Z)Z
    //   461: invokevirtual 460	com/yandex/metrica/impl/br$b:g	(Z)V
    //   464: aload_2
    //   465: aload 38
    //   467: ldc_w 462
    //   470: iconst_0
    //   471: invokestatic 452	com/yandex/metrica/impl/br:a	(Lorg/json/JSONObject;Ljava/lang/String;Z)Z
    //   474: invokevirtual 464	com/yandex/metrica/impl/br$b:h	(Z)V
    //   477: aload_2
    //   478: aload 38
    //   480: ldc_w 466
    //   483: iconst_0
    //   484: invokestatic 452	com/yandex/metrica/impl/br:a	(Lorg/json/JSONObject;Ljava/lang/String;Z)Z
    //   487: invokevirtual 468	com/yandex/metrica/impl/br$b:d	(Z)V
    //   490: aload_2
    //   491: aload 38
    //   493: ldc_w 470
    //   496: iconst_0
    //   497: invokestatic 452	com/yandex/metrica/impl/br:a	(Lorg/json/JSONObject;Ljava/lang/String;Z)Z
    //   500: invokevirtual 472	com/yandex/metrica/impl/br$b:e	(Z)V
    //   503: aload_2
    //   504: aload 38
    //   506: ldc_w 474
    //   509: iconst_0
    //   510: invokestatic 452	com/yandex/metrica/impl/br:a	(Lorg/json/JSONObject;Ljava/lang/String;Z)Z
    //   513: invokevirtual 476	com/yandex/metrica/impl/br$b:a	(Z)V
    //   516: aload_2
    //   517: aload 38
    //   519: ldc_w 478
    //   522: iconst_0
    //   523: invokestatic 452	com/yandex/metrica/impl/br:a	(Lorg/json/JSONObject;Ljava/lang/String;Z)Z
    //   526: invokestatic 481	com/yandex/metrica/impl/br$b:a	(Lcom/yandex/metrica/impl/br$b;Z)Z
    //   529: pop
    //   530: aload_2
    //   531: aload 38
    //   533: ldc_w 483
    //   536: iconst_0
    //   537: invokestatic 452	com/yandex/metrica/impl/br:a	(Lorg/json/JSONObject;Ljava/lang/String;Z)Z
    //   540: invokestatic 485	com/yandex/metrica/impl/br$b:b	(Lcom/yandex/metrica/impl/br$b;Z)Z
    //   543: pop
    //   544: aload_2
    //   545: aload 38
    //   547: ldc_w 397
    //   550: iconst_0
    //   551: invokestatic 452	com/yandex/metrica/impl/br:a	(Lorg/json/JSONObject;Ljava/lang/String;Z)Z
    //   554: invokevirtual 487	com/yandex/metrica/impl/br$b:i	(Z)V
    //   557: aload_2
    //   558: invokevirtual 490	com/yandex/metrica/impl/br$b:b	()Lcom/yandex/metrica/impl/ob/ml$a;
    //   561: astore 41
    //   563: aload 41
    //   565: aload 38
    //   567: ldc_w 492
    //   570: iconst_0
    //   571: invokestatic 452	com/yandex/metrica/impl/br:a	(Lorg/json/JSONObject;Ljava/lang/String;Z)Z
    //   574: invokevirtual 497	com/yandex/metrica/impl/ob/ml$a:f	(Z)Lcom/yandex/metrica/impl/ob/ml$a;
    //   577: pop
    //   578: aload 41
    //   580: aload 38
    //   582: ldc_w 499
    //   585: iconst_0
    //   586: invokestatic 452	com/yandex/metrica/impl/br:a	(Lorg/json/JSONObject;Ljava/lang/String;Z)Z
    //   589: invokevirtual 501	com/yandex/metrica/impl/ob/ml$a:g	(Z)Lcom/yandex/metrica/impl/ob/ml$a;
    //   592: pop
    //   593: aload 41
    //   595: aload 38
    //   597: ldc_w 503
    //   600: iconst_0
    //   601: invokestatic 452	com/yandex/metrica/impl/br:a	(Lorg/json/JSONObject;Ljava/lang/String;Z)Z
    //   604: invokevirtual 505	com/yandex/metrica/impl/ob/ml$a:h	(Z)Lcom/yandex/metrica/impl/ob/ml$a;
    //   607: pop
    //   608: aload 41
    //   610: aload 38
    //   612: ldc_w 507
    //   615: iconst_0
    //   616: invokestatic 452	com/yandex/metrica/impl/br:a	(Lorg/json/JSONObject;Ljava/lang/String;Z)Z
    //   619: invokevirtual 509	com/yandex/metrica/impl/ob/ml$a:i	(Z)Lcom/yandex/metrica/impl/ob/ml$a;
    //   622: pop
    //   623: aload 41
    //   625: aload 38
    //   627: ldc_w 511
    //   630: iconst_0
    //   631: invokestatic 452	com/yandex/metrica/impl/br:a	(Lorg/json/JSONObject;Ljava/lang/String;Z)Z
    //   634: invokevirtual 513	com/yandex/metrica/impl/ob/ml$a:j	(Z)Lcom/yandex/metrica/impl/ob/ml$a;
    //   637: pop
    //   638: aload 41
    //   640: aload 38
    //   642: ldc_w 515
    //   645: iconst_0
    //   646: invokestatic 452	com/yandex/metrica/impl/br:a	(Lorg/json/JSONObject;Ljava/lang/String;Z)Z
    //   649: invokevirtual 518	com/yandex/metrica/impl/ob/ml$a:k	(Z)Lcom/yandex/metrica/impl/ob/ml$a;
    //   652: pop
    //   653: aload 41
    //   655: aload 38
    //   657: ldc_w 520
    //   660: iconst_0
    //   661: invokestatic 452	com/yandex/metrica/impl/br:a	(Lorg/json/JSONObject;Ljava/lang/String;Z)Z
    //   664: invokevirtual 523	com/yandex/metrica/impl/ob/ml$a:l	(Z)Lcom/yandex/metrica/impl/ob/ml$a;
    //   667: pop
    //   668: aload 41
    //   670: aload 38
    //   672: ldc_w 525
    //   675: iconst_0
    //   676: invokestatic 452	com/yandex/metrica/impl/br:a	(Lorg/json/JSONObject;Ljava/lang/String;Z)Z
    //   679: invokevirtual 528	com/yandex/metrica/impl/ob/ml$a:m	(Z)Lcom/yandex/metrica/impl/ob/ml$a;
    //   682: pop
    //   683: aload 41
    //   685: aload 38
    //   687: ldc_w 530
    //   690: iconst_0
    //   691: invokestatic 452	com/yandex/metrica/impl/br:a	(Lorg/json/JSONObject;Ljava/lang/String;Z)Z
    //   694: invokevirtual 533	com/yandex/metrica/impl/ob/ml$a:n	(Z)Lcom/yandex/metrica/impl/ob/ml$a;
    //   697: pop
    //   698: aload_3
    //   699: ldc_w 535
    //   702: invokevirtual 251	com/yandex/metrica/impl/ob/nz$a:optJSONObject	(Ljava/lang/String;)Lorg/json/JSONObject;
    //   705: astore 15
    //   707: ldc 243
    //   709: astore 16
    //   711: aload 15
    //   713: ifnull +41 -> 754
    //   716: aload 15
    //   718: ldc_w 537
    //   721: invokevirtual 285	org/json/JSONObject:optJSONObject	(Ljava/lang/String;)Lorg/json/JSONObject;
    //   724: astore 17
    //   726: aload 17
    //   728: ifnull +26 -> 754
    //   731: aload 17
    //   733: ldc_w 539
    //   736: iconst_0
    //   737: invokevirtual 305	org/json/JSONObject:optBoolean	(Ljava/lang/String;Z)Z
    //   740: ifeq +14 -> 754
    //   743: aload 17
    //   745: ldc 238
    //   747: ldc 243
    //   749: invokevirtual 89	org/json/JSONObject:optString	(Ljava/lang/String;Ljava/lang/String;)Ljava/lang/String;
    //   752: astore 16
    //   754: aload_2
    //   755: aload 16
    //   757: invokevirtual 541	com/yandex/metrica/impl/br$b:h	(Ljava/lang/String;)V
    //   760: aload_2
    //   761: aload_3
    //   762: invokestatic 543	com/yandex/metrica/impl/br:a	(Lcom/yandex/metrica/impl/br$b;Lcom/yandex/metrica/impl/ob/nz$a;)V
    //   765: new 545	com/yandex/metrica/impl/ob/gx
    //   768: dup
    //   769: invokespecial 546	com/yandex/metrica/impl/ob/gx:<init>	()V
    //   772: astore 18
    //   774: new 548	com/yandex/metrica/impl/ob/kt$a$f
    //   777: dup
    //   778: invokespecial 549	com/yandex/metrica/impl/ob/kt$a$f:<init>	()V
    //   781: astore 19
    //   783: aload_3
    //   784: ldc_w 397
    //   787: invokevirtual 251	com/yandex/metrica/impl/ob/nz$a:optJSONObject	(Ljava/lang/String;)Lorg/json/JSONObject;
    //   790: astore 20
    //   792: aload 20
    //   794: ifnonnull +338 -> 1132
    //   797: aload_2
    //   798: aload 18
    //   800: aload 19
    //   802: invokevirtual 552	com/yandex/metrica/impl/ob/gx:a	(Lcom/yandex/metrica/impl/ob/kt$a$f;)Lcom/yandex/metrica/impl/ob/mm;
    //   805: invokevirtual 555	com/yandex/metrica/impl/br$b:a	(Lcom/yandex/metrica/impl/ob/mm;)V
    //   808: aload_2
    //   809: invokevirtual 557	com/yandex/metrica/impl/br$b:n	()Z
    //   812: ifeq +8 -> 820
    //   815: aload_2
    //   816: aload_3
    //   817: invokestatic 559	com/yandex/metrica/impl/br:c	(Lcom/yandex/metrica/impl/br$b;Lcom/yandex/metrica/impl/ob/nz$a;)V
    //   820: aload_3
    //   821: ldc_w 466
    //   824: invokevirtual 251	com/yandex/metrica/impl/ob/nz$a:optJSONObject	(Ljava/lang/String;)Lorg/json/JSONObject;
    //   827: astore 21
    //   829: aload_2
    //   830: invokestatic 562	com/yandex/metrica/impl/br$b:a	(Lcom/yandex/metrica/impl/br$b;)Z
    //   833: istore 22
    //   835: aload_2
    //   836: invokestatic 564	com/yandex/metrica/impl/br$b:b	(Lcom/yandex/metrica/impl/br$b;)Z
    //   839: istore 23
    //   841: aload_2
    //   842: new 566	com/yandex/metrica/impl/ob/gp
    //   845: dup
    //   846: invokespecial 567	com/yandex/metrica/impl/ob/gp:<init>	()V
    //   849: aload 21
    //   851: iload 22
    //   853: iload 23
    //   855: invokestatic 569	com/yandex/metrica/impl/br:a	(Lorg/json/JSONObject;ZZ)Lcom/yandex/metrica/impl/ob/kt$a$c;
    //   858: invokevirtual 572	com/yandex/metrica/impl/ob/gp:a	(Lcom/yandex/metrica/impl/ob/kt$a$c;)Lcom/yandex/metrica/impl/ob/hp;
    //   861: invokestatic 575	com/yandex/metrica/impl/br$b:a	(Lcom/yandex/metrica/impl/br$b;Lcom/yandex/metrica/impl/ob/hp;)Lcom/yandex/metrica/impl/ob/hp;
    //   864: pop
    //   865: aload_3
    //   866: ldc_w 470
    //   869: invokevirtual 251	com/yandex/metrica/impl/ob/nz$a:optJSONObject	(Ljava/lang/String;)Lorg/json/JSONObject;
    //   872: astore 25
    //   874: aload_2
    //   875: invokestatic 577	com/yandex/metrica/impl/br$b:c	(Lcom/yandex/metrica/impl/br$b;)Z
    //   878: istore 26
    //   880: aload_2
    //   881: invokestatic 579	com/yandex/metrica/impl/br$b:d	(Lcom/yandex/metrica/impl/br$b;)Z
    //   884: istore 27
    //   886: new 581	com/yandex/metrica/impl/ob/kt$a$a
    //   889: dup
    //   890: invokespecial 582	com/yandex/metrica/impl/ob/kt$a$a:<init>	()V
    //   893: astore 28
    //   895: aload 28
    //   897: aload 25
    //   899: iload 26
    //   901: iload 27
    //   903: invokestatic 569	com/yandex/metrica/impl/br:a	(Lorg/json/JSONObject;ZZ)Lcom/yandex/metrica/impl/ob/kt$a$c;
    //   906: putfield 585	com/yandex/metrica/impl/ob/kt$a$a:b	Lcom/yandex/metrica/impl/ob/kt$a$c;
    //   909: aload 28
    //   911: aload 25
    //   913: ldc_w 587
    //   916: invokestatic 123	com/yandex/metrica/impl/ob/nz:a	(Lorg/json/JSONObject;Ljava/lang/String;)Ljava/lang/Long;
    //   919: getstatic 129	java/util/concurrent/TimeUnit:SECONDS	Ljava/util/concurrent/TimeUnit;
    //   922: aload 28
    //   924: getfield 588	com/yandex/metrica/impl/ob/kt$a$a:c	J
    //   927: invokestatic 137	com/yandex/metrica/impl/ob/oq:a	(Ljava/lang/Long;Ljava/util/concurrent/TimeUnit;J)J
    //   930: putfield 588	com/yandex/metrica/impl/ob/kt$a$a:c	J
    //   933: aload 28
    //   935: aload 25
    //   937: ldc_w 590
    //   940: invokestatic 123	com/yandex/metrica/impl/ob/nz:a	(Lorg/json/JSONObject;Ljava/lang/String;)Ljava/lang/Long;
    //   943: getstatic 129	java/util/concurrent/TimeUnit:SECONDS	Ljava/util/concurrent/TimeUnit;
    //   946: aload 28
    //   948: getfield 592	com/yandex/metrica/impl/ob/kt$a$a:d	J
    //   951: invokestatic 137	com/yandex/metrica/impl/ob/oq:a	(Ljava/lang/Long;Ljava/util/concurrent/TimeUnit;J)J
    //   954: putfield 592	com/yandex/metrica/impl/ob/kt$a$a:d	J
    //   957: aload 28
    //   959: getfield 594	com/yandex/metrica/impl/ob/kt$a$a:e	Z
    //   962: istore 29
    //   964: aload 25
    //   966: ldc_w 596
    //   969: invokestatic 599	com/yandex/metrica/impl/ob/nz:c	(Lorg/json/JSONObject;Ljava/lang/String;)Ljava/lang/Boolean;
    //   972: astore 30
    //   974: aload 30
    //   976: ifnonnull +277 -> 1253
    //   979: aload 28
    //   981: iload 29
    //   983: putfield 594	com/yandex/metrica/impl/ob/kt$a$a:e	Z
    //   986: aload 25
    //   988: ifnonnull +275 -> 1263
    //   991: aconst_null
    //   992: astore 32
    //   994: aload 28
    //   996: aload 32
    //   998: aload 28
    //   1000: getfield 602	com/yandex/metrica/impl/ob/kt$a$a:f	[Lcom/yandex/metrica/impl/ob/kt$a$a$a;
    //   1003: invokestatic 604	com/yandex/metrica/impl/br:a	(Lorg/json/JSONArray;[Lcom/yandex/metrica/impl/ob/kt$a$a$a;)[Lcom/yandex/metrica/impl/ob/kt$a$a$a;
    //   1006: putfield 602	com/yandex/metrica/impl/ob/kt$a$a:f	[Lcom/yandex/metrica/impl/ob/kt$a$a$a;
    //   1009: aload_2
    //   1010: new 606	com/yandex/metrica/impl/ob/gl
    //   1013: dup
    //   1014: invokespecial 607	com/yandex/metrica/impl/ob/gl:<init>	()V
    //   1017: aload 28
    //   1019: invokevirtual 610	com/yandex/metrica/impl/ob/gl:a	(Lcom/yandex/metrica/impl/ob/kt$a$a;)Lcom/yandex/metrica/impl/ob/hk;
    //   1022: invokestatic 613	com/yandex/metrica/impl/br$b:a	(Lcom/yandex/metrica/impl/br$b;Lcom/yandex/metrica/impl/ob/hk;)Lcom/yandex/metrica/impl/ob/hk;
    //   1025: pop
    //   1026: aload_3
    //   1027: ldc_w 615
    //   1030: invokevirtual 285	org/json/JSONObject:optJSONObject	(Ljava/lang/String;)Lorg/json/JSONObject;
    //   1033: astore 34
    //   1035: aload 34
    //   1037: ifnull +18 -> 1055
    //   1040: aload_2
    //   1041: aload 34
    //   1043: ldc_w 617
    //   1046: invokevirtual 99	org/json/JSONObject:getLong	(Ljava/lang/String;)J
    //   1049: invokestatic 105	java/lang/Long:valueOf	(J)Ljava/lang/Long;
    //   1052: invokevirtual 620	com/yandex/metrica/impl/br$b:a	(Ljava/lang/Long;)V
    //   1055: aload_2
    //   1056: aload_3
    //   1057: invokestatic 622	com/yandex/metrica/impl/br:b	(Lcom/yandex/metrica/impl/br$b;Lcom/yandex/metrica/impl/ob/nz$a;)V
    //   1060: new 624	com/yandex/metrica/impl/ob/kt$a$h
    //   1063: dup
    //   1064: invokespecial 625	com/yandex/metrica/impl/ob/kt$a$h:<init>	()V
    //   1067: astore 35
    //   1069: aload_3
    //   1070: ldc_w 627
    //   1073: invokevirtual 251	com/yandex/metrica/impl/ob/nz$a:optJSONObject	(Ljava/lang/String;)Lorg/json/JSONObject;
    //   1076: astore 36
    //   1078: aload 36
    //   1080: ifnull +27 -> 1107
    //   1083: aload 35
    //   1085: aload 36
    //   1087: ldc_w 629
    //   1090: invokestatic 123	com/yandex/metrica/impl/ob/nz:a	(Lorg/json/JSONObject;Ljava/lang/String;)Ljava/lang/Long;
    //   1093: getstatic 129	java/util/concurrent/TimeUnit:SECONDS	Ljava/util/concurrent/TimeUnit;
    //   1096: aload 35
    //   1098: getfield 630	com/yandex/metrica/impl/ob/kt$a$h:b	J
    //   1101: invokestatic 137	com/yandex/metrica/impl/ob/oq:a	(Ljava/lang/Long;Ljava/util/concurrent/TimeUnit;J)J
    //   1104: putfield 630	com/yandex/metrica/impl/ob/kt$a$h:b	J
    //   1107: aload_2
    //   1108: new 632	com/yandex/metrica/impl/ob/hb
    //   1111: dup
    //   1112: invokespecial 633	com/yandex/metrica/impl/ob/hb:<init>	()V
    //   1115: aload 35
    //   1117: invokevirtual 636	com/yandex/metrica/impl/ob/hb:a	(Lcom/yandex/metrica/impl/ob/kt$a$h;)Lcom/yandex/metrica/impl/ob/my;
    //   1120: invokevirtual 639	com/yandex/metrica/impl/br$b:a	(Lcom/yandex/metrica/impl/ob/my;)V
    //   1123: aload_2
    //   1124: getstatic 644	com/yandex/metrica/impl/br$b$a:b	Lcom/yandex/metrica/impl/br$b$a;
    //   1127: invokevirtual 647	com/yandex/metrica/impl/br$b:a	(Lcom/yandex/metrica/impl/br$b$a;)V
    //   1130: aload_2
    //   1131: areturn
    //   1132: aload 19
    //   1134: aload 20
    //   1136: ldc_w 649
    //   1139: invokestatic 123	com/yandex/metrica/impl/ob/nz:a	(Lorg/json/JSONObject;Ljava/lang/String;)Ljava/lang/Long;
    //   1142: getstatic 129	java/util/concurrent/TimeUnit:SECONDS	Ljava/util/concurrent/TimeUnit;
    //   1145: aload 19
    //   1147: getfield 650	com/yandex/metrica/impl/ob/kt$a$f:b	J
    //   1150: invokestatic 137	com/yandex/metrica/impl/ob/oq:a	(Ljava/lang/Long;Ljava/util/concurrent/TimeUnit;J)J
    //   1153: putfield 650	com/yandex/metrica/impl/ob/kt$a$f:b	J
    //   1156: aload 19
    //   1158: aload 20
    //   1160: ldc_w 652
    //   1163: invokestatic 123	com/yandex/metrica/impl/ob/nz:a	(Lorg/json/JSONObject;Ljava/lang/String;)Ljava/lang/Long;
    //   1166: getstatic 129	java/util/concurrent/TimeUnit:SECONDS	Ljava/util/concurrent/TimeUnit;
    //   1169: aload 19
    //   1171: getfield 653	com/yandex/metrica/impl/ob/kt$a$f:c	J
    //   1174: invokestatic 137	com/yandex/metrica/impl/ob/oq:a	(Ljava/lang/Long;Ljava/util/concurrent/TimeUnit;J)J
    //   1177: putfield 653	com/yandex/metrica/impl/ob/kt$a$f:c	J
    //   1180: aload 19
    //   1182: aload 20
    //   1184: ldc_w 655
    //   1187: invokestatic 123	com/yandex/metrica/impl/ob/nz:a	(Lorg/json/JSONObject;Ljava/lang/String;)Ljava/lang/Long;
    //   1190: getstatic 129	java/util/concurrent/TimeUnit:SECONDS	Ljava/util/concurrent/TimeUnit;
    //   1193: aload 19
    //   1195: getfield 656	com/yandex/metrica/impl/ob/kt$a$f:d	J
    //   1198: invokestatic 137	com/yandex/metrica/impl/ob/oq:a	(Ljava/lang/Long;Ljava/util/concurrent/TimeUnit;J)J
    //   1201: putfield 656	com/yandex/metrica/impl/ob/kt$a$f:d	J
    //   1204: aload 19
    //   1206: aload 20
    //   1208: ldc_w 658
    //   1211: invokestatic 123	com/yandex/metrica/impl/ob/nz:a	(Lorg/json/JSONObject;Ljava/lang/String;)Ljava/lang/Long;
    //   1214: getstatic 129	java/util/concurrent/TimeUnit:SECONDS	Ljava/util/concurrent/TimeUnit;
    //   1217: aload 19
    //   1219: getfield 660	com/yandex/metrica/impl/ob/kt$a$f:e	J
    //   1222: invokestatic 137	com/yandex/metrica/impl/ob/oq:a	(Ljava/lang/Long;Ljava/util/concurrent/TimeUnit;J)J
    //   1225: putfield 660	com/yandex/metrica/impl/ob/kt$a$f:e	J
    //   1228: goto -431 -> 797
    //   1231: astore 6
    //   1233: new 277	com/yandex/metrica/impl/br$b
    //   1236: dup
    //   1237: invokespecial 372	com/yandex/metrica/impl/br$b:<init>	()V
    //   1240: astore 7
    //   1242: aload 7
    //   1244: getstatic 662	com/yandex/metrica/impl/br$b$a:a	Lcom/yandex/metrica/impl/br$b$a;
    //   1247: invokevirtual 647	com/yandex/metrica/impl/br$b:a	(Lcom/yandex/metrica/impl/br$b$a;)V
    //   1250: aload 7
    //   1252: areturn
    //   1253: aload 30
    //   1255: invokevirtual 667	java/lang/Boolean:booleanValue	()Z
    //   1258: istore 29
    //   1260: goto -281 -> 979
    //   1263: aload 25
    //   1265: ldc_w 669
    //   1268: invokevirtual 256	org/json/JSONObject:optJSONArray	(Ljava/lang/String;)Lorg/json/JSONArray;
    //   1271: astore 31
    //   1273: aload 31
    //   1275: astore 32
    //   1277: goto -283 -> 994
    //   1280: astore 37
    //   1282: goto -227 -> 1055
    //
    // Exception table:
    //   from	to	target	type
    //   8	27	1231	java/lang/Exception
    //   35	44	1231	java/lang/Exception
    //   49	68	1231	java/lang/Exception
    //   68	100	1231	java/lang/Exception
    //   105	114	1231	java/lang/Exception
    //   119	129	1231	java/lang/Exception
    //   134	146	1231	java/lang/Exception
    //   146	208	1231	java/lang/Exception
    //   208	232	1231	java/lang/Exception
    //   232	256	1231	java/lang/Exception
    //   256	280	1231	java/lang/Exception
    //   280	304	1231	java/lang/Exception
    //   304	328	1231	java/lang/Exception
    //   328	353	1231	java/lang/Exception
    //   358	364	1231	java/lang/Exception
    //   364	698	1231	java/lang/Exception
    //   698	707	1231	java/lang/Exception
    //   716	726	1231	java/lang/Exception
    //   731	754	1231	java/lang/Exception
    //   754	792	1231	java/lang/Exception
    //   797	820	1231	java/lang/Exception
    //   820	974	1231	java/lang/Exception
    //   979	986	1231	java/lang/Exception
    //   994	1035	1231	java/lang/Exception
    //   1040	1055	1231	java/lang/Exception
    //   1055	1078	1231	java/lang/Exception
    //   1083	1107	1231	java/lang/Exception
    //   1107	1123	1231	java/lang/Exception
    //   1132	1228	1231	java/lang/Exception
    //   1253	1260	1231	java/lang/Exception
    //   1263	1273	1231	java/lang/Exception
    //   1040	1055	1280	org/json/JSONException
  }

  public static class a
  {
    public final String a;
    public final String b;
    public final String c;
    public final List<Pair<String, String>> d;
    public final Long e;
    public final List<a> f;

    public a(String paramString1, String paramString2, String paramString3, List<Pair<String, String>> paramList, Long paramLong, List<a> paramList1)
    {
      this.a = paramString1;
      this.b = paramString2;
      this.c = paramString3;
      this.d = Collections.unmodifiableList(paramList);
      this.e = paramLong;
      this.f = paramList1;
    }

    public static enum a
    {
      static
      {
        a[] arrayOfa = new a[2];
        arrayOfa[0] = a;
        arrayOfa[1] = b;
      }
    }
  }

  public static class b
  {
    private mm A;
    private List<iy> B = new ArrayList();
    private ml.a a = new ml.a();
    private a b;
    private boolean c;
    private boolean d;
    private boolean e;
    private boolean f;
    private boolean g;
    private List<String> h;
    private boolean i;
    private String j;
    private List<String> k;
    private String l;
    private List<String> m;
    private String n;
    private String o;
    private String p;
    private String q;
    private String r;
    private mn s = null;
    private hp t;
    private hk u;
    private Long v;
    private List<br.a> w;
    private String x;
    private List<String> y;
    private my z;

    public ml a()
    {
      return this.a.a();
    }

    void a(a parama)
    {
      this.b = parama;
    }

    public void a(mm parammm)
    {
      this.A = parammm;
    }

    void a(mn parammn)
    {
      this.s = parammn;
    }

    public void a(my parammy)
    {
      this.z = parammy;
    }

    public void a(Long paramLong)
    {
      this.v = paramLong;
    }

    void a(String paramString)
    {
      this.n = paramString;
    }

    void a(String paramString, boolean paramBoolean)
    {
      this.B.add(new iy(paramString, paramBoolean));
    }

    void a(List<String> paramList)
    {
      this.h = paramList;
    }

    public void a(boolean paramBoolean)
    {
      this.i = paramBoolean;
    }

    public ml.a b()
    {
      return this.a;
    }

    void b(String paramString)
    {
      this.j = paramString;
    }

    void b(List<String> paramList)
    {
      this.k = paramList;
    }

    void b(boolean paramBoolean)
    {
      this.a.a(paramBoolean);
    }

    public List<String> c()
    {
      return this.h;
    }

    void c(String paramString)
    {
      this.l = paramString;
    }

    public void c(List<String> paramList)
    {
      this.m = paramList;
    }

    void c(boolean paramBoolean)
    {
      this.a.b(paramBoolean);
    }

    public String d()
    {
      return this.n;
    }

    void d(String paramString)
    {
      this.o = paramString;
    }

    public void d(List<br.a> paramList)
    {
      this.w = paramList;
    }

    void d(boolean paramBoolean)
    {
      this.d = paramBoolean;
    }

    public String e()
    {
      return this.j;
    }

    void e(String paramString)
    {
      this.p = paramString;
    }

    public void e(List<String> paramList)
    {
      this.y = paramList;
    }

    void e(boolean paramBoolean)
    {
      this.e = paramBoolean;
    }

    public List<String> f()
    {
      return this.k;
    }

    void f(String paramString)
    {
      this.q = paramString;
    }

    public void f(boolean paramBoolean)
    {
      this.c = paramBoolean;
    }

    public String g()
    {
      return this.l;
    }

    void g(String paramString)
    {
      this.r = paramString;
    }

    public void g(boolean paramBoolean)
    {
      this.a.c(paramBoolean);
    }

    public List<String> h()
    {
      return this.m;
    }

    public void h(String paramString)
    {
      this.x = paramString;
    }

    public void h(boolean paramBoolean)
    {
      this.a.d(paramBoolean);
    }

    public String i()
    {
      return this.o;
    }

    public void i(boolean paramBoolean)
    {
      this.a.e(paramBoolean);
    }

    public String j()
    {
      return this.p;
    }

    public String k()
    {
      return this.q;
    }

    public String l()
    {
      return this.r;
    }

    public a m()
    {
      return this.b;
    }

    public boolean n()
    {
      return this.c;
    }

    public mn o()
    {
      return this.s;
    }

    public mm p()
    {
      return this.A;
    }

    public List<iy> q()
    {
      return this.B;
    }

    public hp r()
    {
      return this.t;
    }

    public hk s()
    {
      return this.u;
    }

    public Long t()
    {
      return this.v;
    }

    public List<br.a> u()
    {
      return this.w;
    }

    public String v()
    {
      return this.x;
    }

    public List<String> w()
    {
      return this.y;
    }

    public my x()
    {
      return this.z;
    }

    public static enum a
    {
      static
      {
        a[] arrayOfa = new a[2];
        arrayOfa[0] = a;
        arrayOfa[1] = b;
      }
    }
  }
}

/* Location:           E:\Study\Tools\apktool2_2\dex2jar-0.0.9.15\classes_viber_4_dex2jar.jar
 * Qualified Name:     com.yandex.metrica.impl.br
 * JD-Core Version:    0.6.2
 */