package com.google.a.a.c;

import com.google.a.a.f.ab;
import com.google.a.a.f.z;

public final class p
{
  private l a;
  private m b = new m();
  private m c = new m();
  private int d = 10;
  private int e = 16384;
  private boolean f = true;
  private boolean g = true;
  private i h;
  private final w i;
  private String j;
  private h k;
  private int l = 20000;
  private int m = 20000;
  private x n;
  private n o;
  private u p;
  private com.google.a.a.f.x q;
  private j r;

  @Deprecated
  private c s;
  private boolean t = true;
  private boolean u = true;

  @Deprecated
  private boolean v = false;
  private boolean w;
  private ab x = ab.a;

  p(w paramw, String paramString)
  {
    this.i = paramw;
    a(paramString);
  }

  public p a(int paramInt)
  {
    if (paramInt >= 0);
    for (boolean bool = true; ; bool = false)
    {
      z.a(bool);
      this.l = paramInt;
      return this;
    }
  }

  public p a(h paramh)
  {
    this.k = ((h)z.a(paramh));
    return this;
  }

  public p a(i parami)
  {
    this.h = parami;
    return this;
  }

  public p a(j paramj)
  {
    this.r = paramj;
    return this;
  }

  public p a(l paraml)
  {
    this.a = paraml;
    return this;
  }

  public p a(n paramn)
  {
    this.o = paramn;
    return this;
  }

  public p a(u paramu)
  {
    this.p = paramu;
    return this;
  }

  public p a(x paramx)
  {
    this.n = paramx;
    return this;
  }

  public p a(com.google.a.a.f.x paramx)
  {
    this.q = paramx;
    return this;
  }

  public p a(String paramString)
  {
    if ((paramString == null) || (o.e(paramString)));
    for (boolean bool = true; ; bool = false)
    {
      z.a(bool);
      this.j = paramString;
      return this;
    }
  }

  public p a(boolean paramBoolean)
  {
    this.u = paramBoolean;
    return this;
  }

  public w a()
  {
    return this.i;
  }

  public boolean a(int paramInt, m paramm)
  {
    String str = paramm.e();
    if ((m()) && (v.b(paramInt)) && (str != null))
    {
      a(new h(this.k.a(str)));
      if (paramInt == 303)
      {
        a("GET");
        a(null);
      }
      this.b.b((String)null);
      this.b.g((String)null);
      this.b.h((String)null);
      this.b.f((String)null);
      this.b.i((String)null);
      this.b.j((String)null);
      return true;
    }
    return false;
  }

  public p b(int paramInt)
  {
    if (paramInt >= 0);
    for (boolean bool = true; ; bool = false)
    {
      z.a(bool);
      this.m = paramInt;
      return this;
    }
  }

  public String b()
  {
    return this.j;
  }

  public h c()
  {
    return this.k;
  }

  public i d()
  {
    return this.h;
  }

  public int e()
  {
    return this.e;
  }

  public boolean f()
  {
    return this.f;
  }

  public m g()
  {
    return this.b;
  }

  public m h()
  {
    return this.c;
  }

  public x i()
  {
    return this.n;
  }

  public n j()
  {
    return this.o;
  }

  public u k()
  {
    return this.p;
  }

  public final com.google.a.a.f.x l()
  {
    return this.q;
  }

  public boolean m()
  {
    return this.t;
  }

  public boolean n()
  {
    return this.u;
  }

  // ERROR //
  public s o()
    throws java.io.IOException
  {
    // Byte code:
    //   0: aload_0
    //   1: getfield 58	com/google/a/a/c/p:d	I
    //   4: iflt +914 -> 918
    //   7: iconst_1
    //   8: istore_1
    //   9: iload_1
    //   10: invokestatic 91	com/google/a/a/f/z:a	(Z)V
    //   13: aload_0
    //   14: getfield 58	com/google/a/a/c/p:d	I
    //   17: istore_2
    //   18: aload_0
    //   19: getfield 183	com/google/a/a/c/p:s	Lcom/google/a/a/c/c;
    //   22: ifnull +12 -> 34
    //   25: aload_0
    //   26: getfield 183	com/google/a/a/c/p:s	Lcom/google/a/a/c/c;
    //   29: invokeinterface 187 1 0
    //   34: aconst_null
    //   35: astore_3
    //   36: aload_0
    //   37: getfield 127	com/google/a/a/c/p:j	Ljava/lang/String;
    //   40: invokestatic 95	com/google/a/a/f/z:a	(Ljava/lang/Object;)Ljava/lang/Object;
    //   43: pop
    //   44: aload_0
    //   45: getfield 99	com/google/a/a/c/p:k	Lcom/google/a/a/c/h;
    //   48: invokestatic 95	com/google/a/a/f/z:a	(Ljava/lang/Object;)Ljava/lang/Object;
    //   51: pop
    //   52: iload_2
    //   53: istore 6
    //   55: aload_3
    //   56: ifnull +7 -> 63
    //   59: aload_3
    //   60: invokevirtual 191	com/google/a/a/c/s:h	()V
    //   63: aload_0
    //   64: getfield 108	com/google/a/a/c/p:a	Lcom/google/a/a/c/l;
    //   67: ifnull +13 -> 80
    //   70: aload_0
    //   71: getfield 108	com/google/a/a/c/p:a	Lcom/google/a/a/c/l;
    //   74: aload_0
    //   75: invokeinterface 196 2 0
    //   80: aload_0
    //   81: getfield 99	com/google/a/a/c/p:k	Lcom/google/a/a/c/h;
    //   84: invokevirtual 198	com/google/a/a/c/h:b	()Ljava/lang/String;
    //   87: astore 7
    //   89: aload_0
    //   90: getfield 82	com/google/a/a/c/p:i	Lcom/google/a/a/c/w;
    //   93: aload_0
    //   94: getfield 127	com/google/a/a/c/p:j	Ljava/lang/String;
    //   97: aload 7
    //   99: invokevirtual 203	com/google/a/a/c/w:a	(Ljava/lang/String;Ljava/lang/String;)Lcom/google/a/a/c/z;
    //   102: astore 8
    //   104: getstatic 206	com/google/a/a/c/w:a	Ljava/util/logging/Logger;
    //   107: astore 9
    //   109: aload_0
    //   110: getfield 62	com/google/a/a/c/p:f	Z
    //   113: ifeq +810 -> 923
    //   116: aload 9
    //   118: getstatic 212	java/util/logging/Level:CONFIG	Ljava/util/logging/Level;
    //   121: invokevirtual 218	java/util/logging/Logger:isLoggable	(Ljava/util/logging/Level;)Z
    //   124: ifeq +799 -> 923
    //   127: iconst_1
    //   128: istore 10
    //   130: aconst_null
    //   131: astore 11
    //   133: aconst_null
    //   134: astore 12
    //   136: iload 10
    //   138: ifeq +104 -> 242
    //   141: new 220	java/lang/StringBuilder
    //   144: dup
    //   145: invokespecial 221	java/lang/StringBuilder:<init>	()V
    //   148: astore 12
    //   150: aload 12
    //   152: ldc 223
    //   154: invokevirtual 227	java/lang/StringBuilder:append	(Ljava/lang/String;)Ljava/lang/StringBuilder;
    //   157: getstatic 231	com/google/a/a/f/ad:a	Ljava/lang/String;
    //   160: invokevirtual 227	java/lang/StringBuilder:append	(Ljava/lang/String;)Ljava/lang/StringBuilder;
    //   163: pop
    //   164: aload 12
    //   166: aload_0
    //   167: getfield 127	com/google/a/a/c/p:j	Ljava/lang/String;
    //   170: invokevirtual 227	java/lang/StringBuilder:append	(Ljava/lang/String;)Ljava/lang/StringBuilder;
    //   173: bipush 32
    //   175: invokevirtual 234	java/lang/StringBuilder:append	(C)Ljava/lang/StringBuilder;
    //   178: aload 7
    //   180: invokevirtual 227	java/lang/StringBuilder:append	(Ljava/lang/String;)Ljava/lang/StringBuilder;
    //   183: getstatic 231	com/google/a/a/f/ad:a	Ljava/lang/String;
    //   186: invokevirtual 227	java/lang/StringBuilder:append	(Ljava/lang/String;)Ljava/lang/StringBuilder;
    //   189: pop
    //   190: aload_0
    //   191: getfield 64	com/google/a/a/c/p:g	Z
    //   194: istore 15
    //   196: aconst_null
    //   197: astore 11
    //   199: iload 15
    //   201: ifeq +41 -> 242
    //   204: new 220	java/lang/StringBuilder
    //   207: dup
    //   208: ldc 236
    //   210: invokespecial 239	java/lang/StringBuilder:<init>	(Ljava/lang/String;)V
    //   213: astore 11
    //   215: aload_0
    //   216: getfield 127	com/google/a/a/c/p:j	Ljava/lang/String;
    //   219: ldc 151
    //   221: invokevirtual 243	java/lang/String:equals	(Ljava/lang/Object;)Z
    //   224: ifne +18 -> 242
    //   227: aload 11
    //   229: ldc 245
    //   231: invokevirtual 227	java/lang/StringBuilder:append	(Ljava/lang/String;)Ljava/lang/StringBuilder;
    //   234: aload_0
    //   235: getfield 127	com/google/a/a/c/p:j	Ljava/lang/String;
    //   238: invokevirtual 227	java/lang/StringBuilder:append	(Ljava/lang/String;)Ljava/lang/StringBuilder;
    //   241: pop
    //   242: aload_0
    //   243: getfield 54	com/google/a/a/c/p:b	Lcom/google/a/a/c/m;
    //   246: invokevirtual 247	com/google/a/a/c/m:g	()Ljava/lang/String;
    //   249: astore 16
    //   251: aload_0
    //   252: getfield 249	com/google/a/a/c/p:w	Z
    //   255: ifne +18 -> 273
    //   258: aload 16
    //   260: ifnonnull +669 -> 929
    //   263: aload_0
    //   264: getfield 54	com/google/a/a/c/p:b	Lcom/google/a/a/c/m;
    //   267: ldc 251
    //   269: invokevirtual 253	com/google/a/a/c/m:k	(Ljava/lang/String;)Lcom/google/a/a/c/m;
    //   272: pop
    //   273: aload_0
    //   274: getfield 54	com/google/a/a/c/p:b	Lcom/google/a/a/c/m;
    //   277: aload 12
    //   279: aload 11
    //   281: aload 9
    //   283: aload 8
    //   285: invokestatic 256	com/google/a/a/c/m:a	(Lcom/google/a/a/c/m;Ljava/lang/StringBuilder;Ljava/lang/StringBuilder;Ljava/util/logging/Logger;Lcom/google/a/a/c/z;)V
    //   288: aload_0
    //   289: getfield 249	com/google/a/a/c/p:w	Z
    //   292: ifne +13 -> 305
    //   295: aload_0
    //   296: getfield 54	com/google/a/a/c/p:b	Lcom/google/a/a/c/m;
    //   299: aload 16
    //   301: invokevirtual 253	com/google/a/a/c/m:k	(Ljava/lang/String;)Lcom/google/a/a/c/m;
    //   304: pop
    //   305: aload_0
    //   306: getfield 102	com/google/a/a/c/p:h	Lcom/google/a/a/c/i;
    //   309: astore 17
    //   311: aload 17
    //   313: ifnull +15 -> 328
    //   316: aload_0
    //   317: getfield 102	com/google/a/a/c/p:h	Lcom/google/a/a/c/i;
    //   320: invokeinterface 260 1 0
    //   325: ifeq +678 -> 1003
    //   328: iconst_1
    //   329: istore 18
    //   331: aload 17
    //   333: ifnull +354 -> 687
    //   336: aload_0
    //   337: getfield 102	com/google/a/a/c/p:h	Lcom/google/a/a/c/i;
    //   340: invokeinterface 262 1 0
    //   345: astore 39
    //   347: iload 10
    //   349: ifeq +995 -> 1344
    //   352: new 264	com/google/a/a/f/u
    //   355: dup
    //   356: aload 17
    //   358: getstatic 206	com/google/a/a/c/w:a	Ljava/util/logging/Logger;
    //   361: getstatic 212	java/util/logging/Level:CONFIG	Ljava/util/logging/Level;
    //   364: aload_0
    //   365: getfield 60	com/google/a/a/c/p:e	I
    //   368: invokespecial 267	com/google/a/a/f/u:<init>	(Lcom/google/a/a/f/ac;Ljava/util/logging/Logger;Ljava/util/logging/Level;I)V
    //   371: astore 40
    //   373: aload_0
    //   374: getfield 105	com/google/a/a/c/p:r	Lcom/google/a/a/c/j;
    //   377: ifnonnull +632 -> 1009
    //   380: aload_0
    //   381: getfield 102	com/google/a/a/c/p:h	Lcom/google/a/a/c/i;
    //   384: invokeinterface 270 1 0
    //   389: lstore 47
    //   391: aconst_null
    //   392: astore 41
    //   394: aload 40
    //   396: astore 17
    //   398: iload 10
    //   400: ifeq +245 -> 645
    //   403: aload 39
    //   405: ifnull +98 -> 503
    //   408: aload 39
    //   410: invokestatic 274	java/lang/String:valueOf	(Ljava/lang/Object;)Ljava/lang/String;
    //   413: astore 56
    //   415: aload 56
    //   417: invokevirtual 277	java/lang/String:length	()I
    //   420: ifeq +650 -> 1070
    //   423: ldc_w 279
    //   426: aload 56
    //   428: invokevirtual 283	java/lang/String:concat	(Ljava/lang/String;)Ljava/lang/String;
    //   431: astore 57
    //   433: aload 12
    //   435: aload 57
    //   437: invokevirtual 227	java/lang/StringBuilder:append	(Ljava/lang/String;)Ljava/lang/StringBuilder;
    //   440: getstatic 231	com/google/a/a/f/ad:a	Ljava/lang/String;
    //   443: invokevirtual 227	java/lang/StringBuilder:append	(Ljava/lang/String;)Ljava/lang/StringBuilder;
    //   446: pop
    //   447: aload 11
    //   449: ifnull +54 -> 503
    //   452: aload 57
    //   454: invokestatic 274	java/lang/String:valueOf	(Ljava/lang/Object;)Ljava/lang/String;
    //   457: invokestatic 274	java/lang/String:valueOf	(Ljava/lang/Object;)Ljava/lang/String;
    //   460: astore 59
    //   462: aload 11
    //   464: new 220	java/lang/StringBuilder
    //   467: dup
    //   468: bipush 6
    //   470: aload 59
    //   472: invokevirtual 277	java/lang/String:length	()I
    //   475: iadd
    //   476: invokespecial 286	java/lang/StringBuilder:<init>	(I)V
    //   479: ldc_w 288
    //   482: invokevirtual 227	java/lang/StringBuilder:append	(Ljava/lang/String;)Ljava/lang/StringBuilder;
    //   485: aload 59
    //   487: invokevirtual 227	java/lang/StringBuilder:append	(Ljava/lang/String;)Ljava/lang/StringBuilder;
    //   490: ldc_w 290
    //   493: invokevirtual 227	java/lang/StringBuilder:append	(Ljava/lang/String;)Ljava/lang/StringBuilder;
    //   496: invokevirtual 293	java/lang/StringBuilder:toString	()Ljava/lang/String;
    //   499: invokevirtual 227	java/lang/StringBuilder:append	(Ljava/lang/String;)Ljava/lang/StringBuilder;
    //   502: pop
    //   503: aload 41
    //   505: ifnull +98 -> 603
    //   508: aload 41
    //   510: invokestatic 274	java/lang/String:valueOf	(Ljava/lang/Object;)Ljava/lang/String;
    //   513: astore 51
    //   515: aload 51
    //   517: invokevirtual 277	java/lang/String:length	()I
    //   520: ifeq +565 -> 1085
    //   523: ldc_w 295
    //   526: aload 51
    //   528: invokevirtual 283	java/lang/String:concat	(Ljava/lang/String;)Ljava/lang/String;
    //   531: astore 52
    //   533: aload 12
    //   535: aload 52
    //   537: invokevirtual 227	java/lang/StringBuilder:append	(Ljava/lang/String;)Ljava/lang/StringBuilder;
    //   540: getstatic 231	com/google/a/a/f/ad:a	Ljava/lang/String;
    //   543: invokevirtual 227	java/lang/StringBuilder:append	(Ljava/lang/String;)Ljava/lang/StringBuilder;
    //   546: pop
    //   547: aload 11
    //   549: ifnull +54 -> 603
    //   552: aload 52
    //   554: invokestatic 274	java/lang/String:valueOf	(Ljava/lang/Object;)Ljava/lang/String;
    //   557: invokestatic 274	java/lang/String:valueOf	(Ljava/lang/Object;)Ljava/lang/String;
    //   560: astore 54
    //   562: aload 11
    //   564: new 220	java/lang/StringBuilder
    //   567: dup
    //   568: bipush 6
    //   570: aload 54
    //   572: invokevirtual 277	java/lang/String:length	()I
    //   575: iadd
    //   576: invokespecial 286	java/lang/StringBuilder:<init>	(I)V
    //   579: ldc_w 288
    //   582: invokevirtual 227	java/lang/StringBuilder:append	(Ljava/lang/String;)Ljava/lang/StringBuilder;
    //   585: aload 54
    //   587: invokevirtual 227	java/lang/StringBuilder:append	(Ljava/lang/String;)Ljava/lang/StringBuilder;
    //   590: ldc_w 290
    //   593: invokevirtual 227	java/lang/StringBuilder:append	(Ljava/lang/String;)Ljava/lang/StringBuilder;
    //   596: invokevirtual 293	java/lang/StringBuilder:toString	()Ljava/lang/String;
    //   599: invokevirtual 227	java/lang/StringBuilder:append	(Ljava/lang/String;)Ljava/lang/StringBuilder;
    //   602: pop
    //   603: lload 47
    //   605: lconst_0
    //   606: lcmp
    //   607: iflt +38 -> 645
    //   610: aload 12
    //   612: new 220	java/lang/StringBuilder
    //   615: dup
    //   616: bipush 36
    //   618: invokespecial 286	java/lang/StringBuilder:<init>	(I)V
    //   621: ldc_w 297
    //   624: invokevirtual 227	java/lang/StringBuilder:append	(Ljava/lang/String;)Ljava/lang/StringBuilder;
    //   627: lload 47
    //   629: invokevirtual 300	java/lang/StringBuilder:append	(J)Ljava/lang/StringBuilder;
    //   632: invokevirtual 293	java/lang/StringBuilder:toString	()Ljava/lang/String;
    //   635: invokevirtual 227	java/lang/StringBuilder:append	(Ljava/lang/String;)Ljava/lang/StringBuilder;
    //   638: getstatic 231	com/google/a/a/f/ad:a	Ljava/lang/String;
    //   641: invokevirtual 227	java/lang/StringBuilder:append	(Ljava/lang/String;)Ljava/lang/StringBuilder;
    //   644: pop
    //   645: aload 11
    //   647: ifnull +12 -> 659
    //   650: aload 11
    //   652: ldc_w 302
    //   655: invokevirtual 227	java/lang/StringBuilder:append	(Ljava/lang/String;)Ljava/lang/StringBuilder;
    //   658: pop
    //   659: aload 8
    //   661: aload 39
    //   663: invokevirtual 306	com/google/a/a/c/z:b	(Ljava/lang/String;)V
    //   666: aload 8
    //   668: aload 41
    //   670: invokevirtual 308	com/google/a/a/c/z:a	(Ljava/lang/String;)V
    //   673: aload 8
    //   675: lload 47
    //   677: invokevirtual 311	com/google/a/a/c/z:a	(J)V
    //   680: aload 8
    //   682: aload 17
    //   684: invokevirtual 314	com/google/a/a/c/z:a	(Lcom/google/a/a/f/ac;)V
    //   687: iload 10
    //   689: ifeq +77 -> 766
    //   692: aload 9
    //   694: aload 12
    //   696: invokevirtual 293	java/lang/StringBuilder:toString	()Ljava/lang/String;
    //   699: invokevirtual 317	java/util/logging/Logger:config	(Ljava/lang/String;)V
    //   702: aload 11
    //   704: ifnull +62 -> 766
    //   707: aload 11
    //   709: ldc_w 319
    //   712: invokevirtual 227	java/lang/StringBuilder:append	(Ljava/lang/String;)Ljava/lang/StringBuilder;
    //   715: pop
    //   716: aload 11
    //   718: aload 7
    //   720: ldc_w 290
    //   723: ldc_w 321
    //   726: invokevirtual 325	java/lang/String:replaceAll	(Ljava/lang/String;Ljava/lang/String;)Ljava/lang/String;
    //   729: invokevirtual 227	java/lang/StringBuilder:append	(Ljava/lang/String;)Ljava/lang/StringBuilder;
    //   732: pop
    //   733: aload 11
    //   735: ldc_w 290
    //   738: invokevirtual 227	java/lang/StringBuilder:append	(Ljava/lang/String;)Ljava/lang/StringBuilder;
    //   741: pop
    //   742: aload 17
    //   744: ifnull +12 -> 756
    //   747: aload 11
    //   749: ldc_w 327
    //   752: invokevirtual 227	java/lang/StringBuilder:append	(Ljava/lang/String;)Ljava/lang/StringBuilder;
    //   755: pop
    //   756: aload 9
    //   758: aload 11
    //   760: invokevirtual 293	java/lang/StringBuilder:toString	()Ljava/lang/String;
    //   763: invokevirtual 317	java/util/logging/Logger:config	(Ljava/lang/String;)V
    //   766: iload 18
    //   768: ifeq +332 -> 1100
    //   771: iload 6
    //   773: ifle +327 -> 1100
    //   776: iconst_1
    //   777: istore 19
    //   779: aload 8
    //   781: aload_0
    //   782: getfield 66	com/google/a/a/c/p:l	I
    //   785: aload_0
    //   786: getfield 68	com/google/a/a/c/p:m	I
    //   789: invokevirtual 330	com/google/a/a/c/z:a	(II)V
    //   792: aload 8
    //   794: invokevirtual 333	com/google/a/a/c/z:a	()Lcom/google/a/a/c/aa;
    //   797: astore 31
    //   799: new 189	com/google/a/a/c/s
    //   802: dup
    //   803: aload_0
    //   804: aload 31
    //   806: invokespecial 336	com/google/a/a/c/s:<init>	(Lcom/google/a/a/c/p;Lcom/google/a/a/c/aa;)V
    //   809: astore 32
    //   811: aload 32
    //   813: astore_3
    //   814: aconst_null
    //   815: astore 20
    //   817: aload_3
    //   818: ifnull +427 -> 1245
    //   821: aload_3
    //   822: invokevirtual 338	com/google/a/a/c/s:c	()Z
    //   825: ifne +420 -> 1245
    //   828: aload_0
    //   829: getfield 117	com/google/a/a/c/p:n	Lcom/google/a/a/c/x;
    //   832: astore 26
    //   834: iconst_0
    //   835: istore 27
    //   837: aload 26
    //   839: ifnull +18 -> 857
    //   842: aload_0
    //   843: getfield 117	com/google/a/a/c/p:n	Lcom/google/a/a/c/x;
    //   846: aload_0
    //   847: aload_3
    //   848: iload 19
    //   850: invokeinterface 343 4 0
    //   855: istore 27
    //   857: iload 27
    //   859: ifne +21 -> 880
    //   862: aload_0
    //   863: aload_3
    //   864: invokevirtual 345	com/google/a/a/c/s:d	()I
    //   867: aload_3
    //   868: invokevirtual 347	com/google/a/a/c/s:b	()Lcom/google/a/a/c/m;
    //   871: invokevirtual 349	com/google/a/a/c/p:a	(ILcom/google/a/a/c/m;)Z
    //   874: ifeq +306 -> 1180
    //   877: iconst_1
    //   878: istore 27
    //   880: iload 19
    //   882: iload 27
    //   884: iand
    //   885: istore 22
    //   887: iload 22
    //   889: ifeq +7 -> 896
    //   892: aload_3
    //   893: invokevirtual 191	com/google/a/a/c/s:h	()V
    //   896: iload 6
    //   898: iconst_1
    //   899: isub
    //   900: istore 23
    //   902: aload_3
    //   903: ifnull +3 -> 906
    //   906: iload 22
    //   908: ifne +429 -> 1337
    //   911: aload_3
    //   912: ifnonnull +369 -> 1281
    //   915: aload 20
    //   917: athrow
    //   918: iconst_0
    //   919: istore_1
    //   920: goto -911 -> 9
    //   923: iconst_0
    //   924: istore 10
    //   926: goto -796 -> 130
    //   929: aload_0
    //   930: getfield 54	com/google/a/a/c/p:b	Lcom/google/a/a/c/m;
    //   933: astore 62
    //   935: aload 16
    //   937: invokestatic 274	java/lang/String:valueOf	(Ljava/lang/Object;)Ljava/lang/String;
    //   940: invokestatic 274	java/lang/String:valueOf	(Ljava/lang/Object;)Ljava/lang/String;
    //   943: astore 63
    //   945: ldc 251
    //   947: invokestatic 274	java/lang/String:valueOf	(Ljava/lang/Object;)Ljava/lang/String;
    //   950: invokestatic 274	java/lang/String:valueOf	(Ljava/lang/Object;)Ljava/lang/String;
    //   953: astore 64
    //   955: aload 62
    //   957: new 220	java/lang/StringBuilder
    //   960: dup
    //   961: iconst_1
    //   962: aload 63
    //   964: invokevirtual 277	java/lang/String:length	()I
    //   967: iadd
    //   968: aload 64
    //   970: invokevirtual 277	java/lang/String:length	()I
    //   973: iadd
    //   974: invokespecial 286	java/lang/StringBuilder:<init>	(I)V
    //   977: aload 63
    //   979: invokevirtual 227	java/lang/StringBuilder:append	(Ljava/lang/String;)Ljava/lang/StringBuilder;
    //   982: ldc_w 351
    //   985: invokevirtual 227	java/lang/StringBuilder:append	(Ljava/lang/String;)Ljava/lang/StringBuilder;
    //   988: aload 64
    //   990: invokevirtual 227	java/lang/StringBuilder:append	(Ljava/lang/String;)Ljava/lang/StringBuilder;
    //   993: invokevirtual 293	java/lang/StringBuilder:toString	()Ljava/lang/String;
    //   996: invokevirtual 253	com/google/a/a/c/m:k	(Ljava/lang/String;)Lcom/google/a/a/c/m;
    //   999: pop
    //   1000: goto -727 -> 273
    //   1003: iconst_0
    //   1004: istore 18
    //   1006: goto -675 -> 331
    //   1009: aload_0
    //   1010: getfield 105	com/google/a/a/c/p:r	Lcom/google/a/a/c/j;
    //   1013: invokeinterface 355 1 0
    //   1018: astore 41
    //   1020: new 357	com/google/a/a/c/k
    //   1023: dup
    //   1024: aload 40
    //   1026: aload_0
    //   1027: getfield 105	com/google/a/a/c/p:r	Lcom/google/a/a/c/j;
    //   1030: invokespecial 360	com/google/a/a/c/k:<init>	(Lcom/google/a/a/f/ac;Lcom/google/a/a/c/j;)V
    //   1033: astore 42
    //   1035: iload 18
    //   1037: ifeq +25 -> 1062
    //   1040: aload 42
    //   1042: invokestatic 365	com/google/a/a/f/o:a	(Lcom/google/a/a/f/ac;)J
    //   1045: lstore 43
    //   1047: lload 43
    //   1049: lstore 45
    //   1051: aload 42
    //   1053: astore 17
    //   1055: lload 45
    //   1057: lstore 47
    //   1059: goto -661 -> 398
    //   1062: ldc2_w 366
    //   1065: lstore 43
    //   1067: goto -20 -> 1047
    //   1070: new 155	java/lang/String
    //   1073: dup
    //   1074: ldc_w 279
    //   1077: invokespecial 368	java/lang/String:<init>	(Ljava/lang/String;)V
    //   1080: astore 57
    //   1082: goto -649 -> 433
    //   1085: new 155	java/lang/String
    //   1088: dup
    //   1089: ldc_w 295
    //   1092: invokespecial 368	java/lang/String:<init>	(Ljava/lang/String;)V
    //   1095: astore 52
    //   1097: goto -564 -> 533
    //   1100: iconst_0
    //   1101: istore 19
    //   1103: goto -324 -> 779
    //   1106: astore 33
    //   1108: aload 31
    //   1110: invokevirtual 373	com/google/a/a/c/aa:a	()Ljava/io/InputStream;
    //   1113: astore 34
    //   1115: aload 34
    //   1117: ifnull +8 -> 1125
    //   1120: aload 34
    //   1122: invokevirtual 378	java/io/InputStream:close	()V
    //   1125: aload 33
    //   1127: athrow
    //   1128: astore 20
    //   1130: aload_0
    //   1131: getfield 74	com/google/a/a/c/p:v	Z
    //   1134: ifne +28 -> 1162
    //   1137: aload_0
    //   1138: getfield 111	com/google/a/a/c/p:o	Lcom/google/a/a/c/n;
    //   1141: ifnull +18 -> 1159
    //   1144: aload_0
    //   1145: getfield 111	com/google/a/a/c/p:o	Lcom/google/a/a/c/n;
    //   1148: aload_0
    //   1149: iload 19
    //   1151: invokeinterface 383 3 0
    //   1156: ifne +6 -> 1162
    //   1159: aload 20
    //   1161: athrow
    //   1162: aload 9
    //   1164: getstatic 386	java/util/logging/Level:WARNING	Ljava/util/logging/Level;
    //   1167: ldc_w 388
    //   1170: aload 20
    //   1172: invokevirtual 392	java/util/logging/Logger:log	(Ljava/util/logging/Level;Ljava/lang/String;Ljava/lang/Throwable;)V
    //   1175: aconst_null
    //   1176: astore_3
    //   1177: goto -360 -> 817
    //   1180: iload 19
    //   1182: ifeq -302 -> 880
    //   1185: aload_0
    //   1186: getfield 183	com/google/a/a/c/p:s	Lcom/google/a/a/c/c;
    //   1189: ifnull -309 -> 880
    //   1192: aload_0
    //   1193: getfield 183	com/google/a/a/c/p:s	Lcom/google/a/a/c/c;
    //   1196: aload_3
    //   1197: invokevirtual 345	com/google/a/a/c/s:d	()I
    //   1200: invokeinterface 394 2 0
    //   1205: ifeq -325 -> 880
    //   1208: aload_0
    //   1209: getfield 183	com/google/a/a/c/p:s	Lcom/google/a/a/c/c;
    //   1212: invokeinterface 396 1 0
    //   1217: lstore 28
    //   1219: lload 28
    //   1221: ldc2_w 366
    //   1224: lcmp
    //   1225: ifeq -345 -> 880
    //   1228: aload_0
    //   1229: getfield 80	com/google/a/a/c/p:x	Lcom/google/a/a/f/ab;
    //   1232: lload 28
    //   1234: invokeinterface 397 3 0
    //   1239: iconst_1
    //   1240: istore 27
    //   1242: goto -362 -> 880
    //   1245: aload_3
    //   1246: ifnonnull +16 -> 1262
    //   1249: iconst_1
    //   1250: istore 21
    //   1252: iload 19
    //   1254: iload 21
    //   1256: iand
    //   1257: istore 22
    //   1259: goto -363 -> 896
    //   1262: iconst_0
    //   1263: istore 21
    //   1265: goto -13 -> 1252
    //   1268: astore 25
    //   1270: aload_3
    //   1271: ifnull +7 -> 1278
    //   1274: aload_3
    //   1275: invokevirtual 399	com/google/a/a/c/s:i	()V
    //   1278: aload 25
    //   1280: athrow
    //   1281: aload_0
    //   1282: getfield 114	com/google/a/a/c/p:p	Lcom/google/a/a/c/u;
    //   1285: ifnull +13 -> 1298
    //   1288: aload_0
    //   1289: getfield 114	com/google/a/a/c/p:p	Lcom/google/a/a/c/u;
    //   1292: aload_3
    //   1293: invokeinterface 404 2 0
    //   1298: aload_0
    //   1299: getfield 72	com/google/a/a/c/p:u	Z
    //   1302: ifeq +28 -> 1330
    //   1305: aload_3
    //   1306: invokevirtual 338	com/google/a/a/c/s:c	()Z
    //   1309: ifne +21 -> 1330
    //   1312: new 406	com/google/a/a/c/t
    //   1315: dup
    //   1316: aload_3
    //   1317: invokespecial 408	com/google/a/a/c/t:<init>	(Lcom/google/a/a/c/s;)V
    //   1320: athrow
    //   1321: astore 24
    //   1323: aload_3
    //   1324: invokevirtual 399	com/google/a/a/c/s:i	()V
    //   1327: aload 24
    //   1329: athrow
    //   1330: aload_3
    //   1331: areturn
    //   1332: astore 30
    //   1334: goto -95 -> 1239
    //   1337: iload 23
    //   1339: istore 6
    //   1341: goto -1286 -> 55
    //   1344: aload 17
    //   1346: astore 40
    //   1348: goto -975 -> 373
    //
    // Exception table:
    //   from	to	target	type
    //   799	811	1106	finally
    //   792	799	1128	java/io/IOException
    //   1108	1115	1128	java/io/IOException
    //   1120	1125	1128	java/io/IOException
    //   1125	1128	1128	java/io/IOException
    //   821	834	1268	finally
    //   842	857	1268	finally
    //   862	877	1268	finally
    //   892	896	1268	finally
    //   1185	1219	1268	finally
    //   1228	1239	1268	finally
    //   1312	1321	1321	finally
    //   1228	1239	1332	java/lang/InterruptedException
  }
}

/* Location:           E:\Study\Tools\apktool2_2\dex2jar-0.0.9.15\classes_viber_dex2jar.jar
 * Qualified Name:     com.google.a.a.c.p
 * JD-Core Version:    0.6.2
 */