package a.a;

import com.appboy.f.c;

public class dv
{
  private static final String a = c.a(dv.class);

  // ERROR //
  public static String a(String paramString1, String paramString2)
  {
    // Byte code:
    //   0: aconst_null
    //   1: astore_2
    //   2: invokestatic 27	java/lang/Runtime:getRuntime	()Ljava/lang/Runtime;
    //   5: iconst_2
    //   6: anewarray 29	java/lang/String
    //   9: dup
    //   10: iconst_0
    //   11: ldc 31
    //   13: aastore
    //   14: dup
    //   15: iconst_1
    //   16: aload_0
    //   17: aastore
    //   18: invokevirtual 35	java/lang/Runtime:exec	([Ljava/lang/String;)Ljava/lang/Process;
    //   21: astore 13
    //   23: new 37	java/io/BufferedReader
    //   26: dup
    //   27: new 39	java/io/InputStreamReader
    //   30: dup
    //   31: aload 13
    //   33: invokevirtual 45	java/lang/Process:getInputStream	()Ljava/io/InputStream;
    //   36: ldc 47
    //   38: invokespecial 50	java/io/InputStreamReader:<init>	(Ljava/io/InputStream;Ljava/lang/String;)V
    //   41: invokespecial 53	java/io/BufferedReader:<init>	(Ljava/io/Reader;)V
    //   44: astore 7
    //   46: aload 7
    //   48: invokevirtual 57	java/io/BufferedReader:readLine	()Ljava/lang/String;
    //   51: astore 15
    //   53: aload 15
    //   55: astore 9
    //   57: aload 13
    //   59: invokevirtual 60	java/lang/Process:destroy	()V
    //   62: aload 7
    //   64: ifnull +8 -> 72
    //   67: aload 7
    //   69: invokevirtual 63	java/io/BufferedReader:close	()V
    //   72: aload 9
    //   74: areturn
    //   75: astore 16
    //   77: getstatic 15	a/a/dv:a	Ljava/lang/String;
    //   80: ldc 65
    //   82: aload 16
    //   84: invokestatic 69	com/appboy/f/c:d	(Ljava/lang/String;Ljava/lang/String;Ljava/lang/Throwable;)I
    //   87: pop
    //   88: aload 9
    //   90: areturn
    //   91: astore 6
    //   93: aconst_null
    //   94: astore 7
    //   96: aload 6
    //   98: astore 8
    //   100: aload_1
    //   101: astore 9
    //   103: getstatic 15	a/a/dv:a	Ljava/lang/String;
    //   106: ldc 71
    //   108: aload 8
    //   110: invokestatic 69	com/appboy/f/c:d	(Ljava/lang/String;Ljava/lang/String;Ljava/lang/Throwable;)I
    //   113: pop
    //   114: aload 7
    //   116: ifnull -44 -> 72
    //   119: aload 7
    //   121: invokevirtual 63	java/io/BufferedReader:close	()V
    //   124: aload 9
    //   126: areturn
    //   127: astore 11
    //   129: getstatic 15	a/a/dv:a	Ljava/lang/String;
    //   132: ldc 65
    //   134: aload 11
    //   136: invokestatic 69	com/appboy/f/c:d	(Ljava/lang/String;Ljava/lang/String;Ljava/lang/Throwable;)I
    //   139: pop
    //   140: aload 9
    //   142: areturn
    //   143: astore_3
    //   144: aload_2
    //   145: ifnull +7 -> 152
    //   148: aload_2
    //   149: invokevirtual 63	java/io/BufferedReader:close	()V
    //   152: aload_3
    //   153: athrow
    //   154: astore 4
    //   156: getstatic 15	a/a/dv:a	Ljava/lang/String;
    //   159: ldc 65
    //   161: aload 4
    //   163: invokestatic 69	com/appboy/f/c:d	(Ljava/lang/String;Ljava/lang/String;Ljava/lang/Throwable;)I
    //   166: pop
    //   167: goto -15 -> 152
    //   170: astore_3
    //   171: aload 7
    //   173: astore_2
    //   174: goto -30 -> 144
    //   177: astore 14
    //   179: aload 14
    //   181: astore 8
    //   183: aload_1
    //   184: astore 9
    //   186: goto -83 -> 103
    //   189: astore 8
    //   191: goto -88 -> 103
    //
    // Exception table:
    //   from	to	target	type
    //   67	72	75	java/lang/Exception
    //   2	46	91	java/lang/Exception
    //   119	124	127	java/lang/Exception
    //   2	46	143	finally
    //   148	152	154	java/lang/Exception
    //   46	53	170	finally
    //   57	62	170	finally
    //   103	114	170	finally
    //   46	53	177	java/lang/Exception
    //   57	62	189	java/lang/Exception
  }
}

/* Location:           E:\Study\Tools\apktool2_2\dex2jar-0.0.9.15\classes_viber_dex2jar.jar
 * Qualified Name:     a.a.dv
 * JD-Core Version:    0.6.2
 */