package a.a;

import android.app.AlarmManager;
import android.content.Context;
import java.util.concurrent.ThreadPoolExecutor;

public final class dx
{
  private static final String a = com.appboy.f.c.a(dx.class);
  private final dh b;
  private final cu c;
  private final c d;
  private final gk e;
  private final ap f;
  private final cx g;
  private final b h;
  private final ac i;
  private final cd j;
  private final gn k;
  private final ar l;
  private final ax m;
  private final fo n;
  private final dd o;
  private final am p;
  private final al q;
  private final ct r;

  public dx(Context paramContext, gi paramgi, com.appboy.a.b paramb, d paramd, ak paramak, ay paramay, boolean paramBoolean1, boolean paramBoolean2, ba paramba)
  {
    String str1 = paramgi.a();
    String str2 = paramb.b().toString();
    dc localdc = new dc(paramContext);
    y localy = new y();
    this.i = new ac("user_dependency_manager_parallel_executor_identifier", localy);
    this.d = new c(this.i, localdc);
    this.o = new dd(paramContext, str2);
    if (str1.equals(""))
    {
      this.b = new dh(paramContext, paramay, this.o, localdc);
      this.c = new cu(paramContext);
    }
    for (cr localcr = cr.a(paramContext, null, str2); ; localcr = cr.a(paramContext, str1, str2))
    {
      as localas = new as(paramContext, paramb, paramak, this.c);
      this.j = new cd();
      go localgo = new go(this.b, localas, paramb);
      cw localcw = new cw(new dg(paramContext, str1, str2), this.d);
      ad localad = new ad("user_dependency_manager_database_serial_identifier", localy);
      localy.a(new aa(this.d));
      cy localcy = a(localcr, localad);
      this.q = new al(a(paramContext, str1, str2), localcy);
      AlarmManager localAlarmManager = (AlarmManager)paramContext.getSystemService("alarm");
      this.l = new ar(paramContext, localcw, this.d, localAlarmManager, this.o, paramb.h(), paramb.t());
      this.g = new cx(paramContext, str1);
      this.r = new ct(paramContext, str1, str2);
      cm localcm = new cm(this.j, de.a(), this.d, paramd, this.i, this.g, this.o, this.r);
      c localc = this.d;
      gl localgl = new gl();
      gm localgm = new gm(paramContext);
      this.k = new gn(paramContext, localc, localgl, localAlarmManager, localgm, str1);
      this.k.a(this.d);
      this.k.a(paramBoolean2);
      this.e = new gk(paramb, this.d, localcm, localgo, localy, paramBoolean1);
      aq localaq = new aq(paramContext, this.d, this.o);
      this.f = new ap(this.l, this.e, this.d, localas, paramb, this.o, this.q, str1, paramBoolean2, localaq, localdc);
      this.n = new fo(paramContext, this.f, this.d, paramb, str1, str2);
      this.p = new am(paramContext, str2, this.f, paramb, this.o);
      if ((!paramBoolean1) && ((localcm instanceof cm)))
        ((cm)localcm).a(this.f);
      this.g.a(this.f);
      this.r.a(this.f);
      this.i.a(this.f);
      localad.a(this.f);
      this.m = new ao(paramContext, this.f, paramb, this.o);
      this.h = new b(paramContext, this.m, this.e, this.f, this.b, this.c, this.o, this.n, this.n.a(), this.q, this.p, paramba, paramd);
      return;
      this.b = new dh(paramContext, str1, str2, paramay, this.o, localdc);
      this.c = new cu(paramContext, str1, str2);
    }
  }

  private cy a(cr paramcr, ad paramad)
  {
    return new cv(new cs(new db(paramcr), paramad), this.d);
  }

  private cy a(Context paramContext, String paramString1, String paramString2)
  {
    return new cv(new cs(new df(paramContext, paramString1, paramString2), this.i), this.d);
  }

  public dd a()
  {
    return this.o;
  }

  public gn b()
  {
    return this.k;
  }

  public b c()
  {
    return this.h;
  }

  public ap d()
  {
    return this.f;
  }

  public gk e()
  {
    return this.e;
  }

  public c f()
  {
    return this.d;
  }

  public dh g()
  {
    return this.b;
  }

  public ThreadPoolExecutor h()
  {
    return this.i;
  }

  public cx i()
  {
    return this.g;
  }

  public ax j()
  {
    return this.m;
  }

  public al k()
  {
    return this.q;
  }

  public fo l()
  {
    return this.n;
  }

  public am m()
  {
    return this.p;
  }

  public ct n()
  {
    return this.r;
  }

  public void o()
  {
    this.i.execute(new Runnable()
    {
      // ERROR //
      public void run()
      {
        // Byte code:
        //   0: aload_0
        //   1: getfield 17	a/a/dx$1:a	La/a/dx;
        //   4: invokestatic 27	a/a/dx:a	(La/a/dx;)La/a/dh;
        //   7: astore 6
        //   9: aload 6
        //   11: monitorenter
        //   12: aload_0
        //   13: getfield 17	a/a/dx$1:a	La/a/dx;
        //   16: invokestatic 27	a/a/dx:a	(La/a/dx;)La/a/dh;
        //   19: invokevirtual 33	a/a/dh:c	()Z
        //   22: ifeq +31 -> 53
        //   25: invokestatic 37	a/a/dx:p	()Ljava/lang/String;
        //   28: ldc 39
        //   30: invokestatic 44	com/appboy/f/c:c	(Ljava/lang/String;Ljava/lang/String;)I
        //   33: pop
        //   34: aload_0
        //   35: getfield 17	a/a/dx$1:a	La/a/dx;
        //   38: invokestatic 27	a/a/dx:a	(La/a/dx;)La/a/dh;
        //   41: invokevirtual 47	java/lang/Object:wait	()V
        //   44: invokestatic 37	a/a/dx:p	()Ljava/lang/String;
        //   47: ldc 49
        //   49: invokestatic 52	com/appboy/f/c:b	(Ljava/lang/String;Ljava/lang/String;)I
        //   52: pop
        //   53: aload 6
        //   55: monitorexit
        //   56: aload_0
        //   57: getfield 17	a/a/dx$1:a	La/a/dx;
        //   60: invokestatic 55	a/a/dx:b	(La/a/dx;)La/a/cu;
        //   63: astore 8
        //   65: aload 8
        //   67: monitorenter
        //   68: aload_0
        //   69: getfield 17	a/a/dx$1:a	La/a/dx;
        //   72: invokestatic 55	a/a/dx:b	(La/a/dx;)La/a/cu;
        //   75: invokevirtual 58	a/a/cu:c	()Z
        //   78: ifeq +31 -> 109
        //   81: invokestatic 37	a/a/dx:p	()Ljava/lang/String;
        //   84: ldc 60
        //   86: invokestatic 44	com/appboy/f/c:c	(Ljava/lang/String;Ljava/lang/String;)I
        //   89: pop
        //   90: aload_0
        //   91: getfield 17	a/a/dx$1:a	La/a/dx;
        //   94: invokestatic 55	a/a/dx:b	(La/a/dx;)La/a/cu;
        //   97: invokevirtual 47	java/lang/Object:wait	()V
        //   100: invokestatic 37	a/a/dx:p	()Ljava/lang/String;
        //   103: ldc 62
        //   105: invokestatic 52	com/appboy/f/c:b	(Ljava/lang/String;Ljava/lang/String;)I
        //   108: pop
        //   109: aload 8
        //   111: monitorexit
        //   112: aload_0
        //   113: getfield 17	a/a/dx$1:a	La/a/dx;
        //   116: invokestatic 66	a/a/dx:d	(La/a/dx;)La/a/gk;
        //   119: aload_0
        //   120: getfield 17	a/a/dx$1:a	La/a/dx;
        //   123: invokestatic 69	a/a/dx:c	(La/a/dx;)La/a/c;
        //   126: invokevirtual 74	a/a/gk:a	(La/a/c;)V
        //   129: aload_0
        //   130: getfield 17	a/a/dx$1:a	La/a/dx;
        //   133: invokestatic 78	a/a/dx:e	(La/a/dx;)La/a/gn;
        //   136: invokevirtual 82	a/a/gn:b	()Z
        //   139: pop
        //   140: return
        //   141: astore 7
        //   143: aload 6
        //   145: monitorexit
        //   146: aload 7
        //   148: athrow
        //   149: astore_1
        //   150: invokestatic 37	a/a/dx:p	()Ljava/lang/String;
        //   153: ldc 84
        //   155: aload_1
        //   156: invokestatic 87	com/appboy/f/c:c	(Ljava/lang/String;Ljava/lang/String;Ljava/lang/Throwable;)I
        //   159: pop
        //   160: goto -31 -> 129
        //   163: astore 9
        //   165: aload 8
        //   167: monitorexit
        //   168: aload 9
        //   170: athrow
        //   171: astore_3
        //   172: invokestatic 37	a/a/dx:p	()Ljava/lang/String;
        //   175: ldc 89
        //   177: aload_3
        //   178: invokestatic 87	com/appboy/f/c:c	(Ljava/lang/String;Ljava/lang/String;Ljava/lang/Throwable;)I
        //   181: pop
        //   182: return
        //   183: astore 11
        //   185: goto -76 -> 109
        //   188: astore 14
        //   190: goto -137 -> 53
        //
        // Exception table:
        //   from	to	target	type
        //   12	34	141	finally
        //   34	53	141	finally
        //   53	56	141	finally
        //   143	146	141	finally
        //   0	12	149	java/lang/Exception
        //   56	68	149	java/lang/Exception
        //   112	129	149	java/lang/Exception
        //   146	149	149	java/lang/Exception
        //   168	171	149	java/lang/Exception
        //   68	90	163	finally
        //   90	109	163	finally
        //   109	112	163	finally
        //   165	168	163	finally
        //   129	140	171	java/lang/Exception
        //   90	109	183	java/lang/InterruptedException
        //   34	53	188	java/lang/InterruptedException
      }
    });
  }
}

/* Location:           E:\Study\Tools\apktool2_2\dex2jar-0.0.9.15\classes_viber_dex2jar.jar
 * Qualified Name:     a.a.dx
 * JD-Core Version:    0.6.2
 */