package com.google.android.gms.internal.measurement;

import java.io.IOException;
import java.lang.reflect.Field;
import java.util.Arrays;
import java.util.Collection;
import java.util.Iterator;
import java.util.List;
import java.util.Map;
import java.util.Map.Entry;
import java.util.Set;
import sun.misc.Unsafe;

final class zzvz<T>
  implements zzwl<T>
{
  private static final int[] zzcaq = new int[0];
  private static final Unsafe zzcar = zzxj.zzyq();
  private final int[] zzcas;
  private final Object[] zzcat;
  private final int zzcau;
  private final int zzcav;
  private final zzvv zzcaw;
  private final boolean zzcax;
  private final boolean zzcay;
  private final boolean zzcaz;
  private final boolean zzcba;
  private final int[] zzcbb;
  private final int zzcbc;
  private final int zzcbd;
  private final zzwc zzcbe;
  private final zzvf zzcbf;
  private final zzxd<?, ?> zzcbg;
  private final zzuc<?> zzcbh;
  private final zzvq zzcbi;

  private zzvz(int[] paramArrayOfInt1, Object[] paramArrayOfObject, int paramInt1, int paramInt2, zzvv paramzzvv, boolean paramBoolean1, boolean paramBoolean2, int[] paramArrayOfInt2, int paramInt3, int paramInt4, zzwc paramzzwc, zzvf paramzzvf, zzxd<?, ?> paramzzxd, zzuc<?> paramzzuc, zzvq paramzzvq)
  {
    this.zzcas = paramArrayOfInt1;
    this.zzcat = paramArrayOfObject;
    this.zzcau = paramInt1;
    this.zzcav = paramInt2;
    this.zzcay = (paramzzvv instanceof zzuo);
    this.zzcaz = paramBoolean1;
    if ((paramzzuc != null) && (paramzzuc.zze(paramzzvv)));
    for (boolean bool = true; ; bool = false)
    {
      this.zzcax = bool;
      this.zzcba = false;
      this.zzcbb = paramArrayOfInt2;
      this.zzcbc = paramInt3;
      this.zzcbd = paramInt4;
      this.zzcbe = paramzzwc;
      this.zzcbf = paramzzvf;
      this.zzcbg = paramzzxd;
      this.zzcbh = paramzzuc;
      this.zzcaw = paramzzvv;
      this.zzcbi = paramzzvq;
      return;
    }
  }

  private static <UT, UB> int zza(zzxd<UT, UB> paramzzxd, T paramT)
  {
    return paramzzxd.zzai(paramzzxd.zzal(paramT));
  }

  static <T> zzvz<T> zza(Class<T> paramClass, zzvt paramzzvt, zzwc paramzzwc, zzvf paramzzvf, zzxd<?, ?> paramzzxd, zzuc<?> paramzzuc, zzvq paramzzvq)
  {
    zzwj localzzwj;
    boolean bool;
    String str;
    int i;
    int j;
    int k;
    int n;
    int m;
    if ((paramzzvt instanceof zzwj))
    {
      localzzwj = (zzwj)paramzzvt;
      if (localzzwj.zzxm() == zzuo.zze.zzbyv);
      int i137;
      int i138;
      int i139;
      for (bool = true; ; bool = false)
      {
        str = localzzwj.zzxv();
        i = str.length();
        j = 1;
        k = str.charAt(0);
        if (k < 55296)
          break label2499;
        i137 = k & 0x1FFF;
        i138 = 13;
        while (true)
        {
          n = j + 1;
          i139 = str.charAt(j);
          if (i139 < 55296)
            break;
          i137 |= (i139 & 0x1FFF) << i138;
          i138 += 13;
          j = n;
        }
      }
      m = i137 | i139 << i138;
    }
    while (true)
    {
      int i1 = n + 1;
      int i2 = str.charAt(n);
      int i135;
      if (i2 >= 55296)
      {
        int i133 = i2 & 0x1FFF;
        int i134 = 13;
        int i136;
        while (true)
        {
          i135 = i1 + 1;
          i136 = str.charAt(i1);
          if (i136 < 55296)
            break;
          i133 |= (i136 & 0x1FFF) << i134;
          i134 += 13;
          i1 = i135;
        }
        i2 = i133 | i136 << i134;
      }
      for (int i3 = i135; ; i3 = i1)
      {
        int i19;
        int[] arrayOfInt1;
        int i23;
        int i21;
        int i22;
        int i25;
        int i26;
        int i27;
        Unsafe localUnsafe;
        Object[] arrayOfObject1;
        int i28;
        Class localClass;
        int[] arrayOfInt2;
        Object[] arrayOfObject2;
        int i29;
        int i30;
        int i31;
        int i32;
        int i33;
        int i34;
        int i35;
        int i99;
        int i100;
        int i37;
        int i101;
        int i4;
        int i5;
        int i6;
        if (i2 == 0)
        {
          i19 = 0;
          arrayOfInt1 = zzcaq;
          i23 = 0;
          i21 = 0;
          i22 = 0;
          i25 = 0;
          i26 = 0;
          i27 = 0;
          localUnsafe = zzcar;
          arrayOfObject1 = localzzwj.zzxw();
          i28 = 0;
          localClass = localzzwj.zzxo().getClass();
          arrayOfInt2 = new int[i26 * 3];
          arrayOfObject2 = new Object[i26 << 1];
          i29 = i19 + i21;
          i30 = 0;
          i31 = i19;
          i32 = i23;
          i33 = i3;
          if (i33 < i)
          {
            i34 = i33 + 1;
            i35 = str.charAt(i33);
            if (i35 < 55296)
              break label2474;
            i99 = i35 & 0x1FFF;
            i100 = 13;
            while (true)
            {
              i37 = i34 + 1;
              i101 = str.charAt(i34);
              if (i101 < 55296)
                break;
              i99 |= (i101 & 0x1FFF) << i100;
              i100 += 13;
              i34 = i37;
            }
          }
        }
        else
        {
          i4 = i3 + 1;
          i5 = str.charAt(i3);
          if (i5 < 55296)
            break label2485;
          int i130 = i5 & 0x1FFF;
          int i131 = 13;
          int i132;
          while (true)
          {
            i6 = i4 + 1;
            i132 = str.charAt(i4);
            if (i132 < 55296)
              break;
            i130 |= (i132 & 0x1FFF) << i131;
            i131 += 13;
            i4 = i6;
          }
          i5 = i130 | i132 << i131;
        }
        while (true)
        {
          int i7 = i6 + 1;
          int i8 = str.charAt(i6);
          if (i8 >= 55296)
          {
            int i126 = i8 & 0x1FFF;
            int i127 = 13;
            int i129;
            for (int i128 = i7; ; i128 = i7)
            {
              i7 = i128 + 1;
              i129 = str.charAt(i128);
              if (i129 < 55296)
                break;
              i126 |= (i129 & 0x1FFF) << i127;
              i127 += 13;
            }
            i8 = i126 | i129 << i127;
          }
          int i9 = i7 + 1;
          int i10 = str.charAt(i7);
          if (i10 >= 55296)
          {
            int i122 = i10 & 0x1FFF;
            int i123 = 13;
            int i125;
            for (int i124 = i9; ; i124 = i9)
            {
              i9 = i124 + 1;
              i125 = str.charAt(i124);
              if (i125 < 55296)
                break;
              i122 |= (i125 & 0x1FFF) << i123;
              i123 += 13;
            }
            i10 = i122 | i125 << i123;
          }
          int i11 = i9 + 1;
          int i12 = str.charAt(i9);
          if (i12 >= 55296)
          {
            int i118 = i12 & 0x1FFF;
            int i119 = 13;
            int i121;
            for (int i120 = i11; ; i120 = i11)
            {
              i11 = i120 + 1;
              i121 = str.charAt(i120);
              if (i121 < 55296)
                break;
              i118 |= (i121 & 0x1FFF) << i119;
              i119 += 13;
            }
            i12 = i118 | i121 << i119;
          }
          int i13 = i11 + 1;
          int i14 = str.charAt(i11);
          if (i14 >= 55296)
          {
            int i114 = i14 & 0x1FFF;
            int i115 = 13;
            int i117;
            for (int i116 = i13; ; i116 = i13)
            {
              i13 = i116 + 1;
              i117 = str.charAt(i116);
              if (i117 < 55296)
                break;
              i114 |= (i117 & 0x1FFF) << i115;
              i115 += 13;
            }
            i14 = i114 | i117 << i115;
          }
          int i15 = i13 + 1;
          int i16 = str.charAt(i13);
          if (i16 >= 55296)
          {
            int i110 = i16 & 0x1FFF;
            int i111 = 13;
            int i113;
            for (int i112 = i15; ; i112 = i15)
            {
              i15 = i112 + 1;
              i113 = str.charAt(i112);
              if (i113 < 55296)
                break;
              i110 |= (i113 & 0x1FFF) << i111;
              i111 += 13;
            }
            i16 = i110 | i113 << i111;
          }
          int i17 = i15 + 1;
          int i18 = str.charAt(i15);
          if (i18 >= 55296)
          {
            int i106 = i18 & 0x1FFF;
            int i107 = 13;
            int i109;
            for (int i108 = i17; ; i108 = i17)
            {
              i17 = i108 + 1;
              i109 = str.charAt(i108);
              if (i109 < 55296)
                break;
              i106 |= (i109 & 0x1FFF) << i107;
              i107 += 13;
            }
            i18 = i106 | i109 << i107;
          }
          i3 = i17 + 1;
          i19 = str.charAt(i17);
          if (i19 >= 55296)
          {
            int i102 = i19 & 0x1FFF;
            int i103 = 13;
            int i105;
            for (int i104 = i3; ; i104 = i3)
            {
              i3 = i104 + 1;
              i105 = str.charAt(i104);
              if (i105 < 55296)
                break;
              i102 |= (i105 & 0x1FFF) << i103;
              i103 += 13;
            }
            i19 = i102 | i105 << i103;
          }
          arrayOfInt1 = new int[i18 + (i19 + i16)];
          int i20 = i8 + (i5 << 1);
          i21 = i16;
          i22 = i5;
          i23 = i20;
          int i24 = i12;
          i25 = i10;
          i26 = i14;
          i27 = i24;
          break;
          int i36 = i99 | i101 << i100;
          while (true)
          {
            int i38 = i37 + 1;
            int i39 = str.charAt(i37);
            int i97;
            int i40;
            if (i39 >= 55296)
            {
              int i94 = i39 & 0x1FFF;
              int i95 = 13;
              int i98;
              for (int i96 = i38; ; i96 = i97)
              {
                i97 = i96 + 1;
                i98 = str.charAt(i96);
                if (i98 < 55296)
                  break;
                i94 |= (i98 & 0x1FFF) << i95;
                i95 += 13;
              }
              i40 = i94 | i98 << i95;
            }
            for (int i41 = i97; ; i41 = i38)
            {
              int i42 = 0xFF & i40;
              int i93;
              if ((0x400 & i40) != 0)
              {
                i93 = i28 + 1;
                arrayOfInt1[i28] = i30;
              }
              for (int i43 = i93; ; i43 = i28)
              {
                int i77;
                int i78;
                int i79;
                int i52;
                if (i42 >= 51)
                {
                  i77 = i41 + 1;
                  i78 = str.charAt(i41);
                  if (i78 < 55296)
                    break label2445;
                  int i89 = i78 & 0x1FFF;
                  int i90 = 13;
                  int i91;
                  int i92;
                  while (true)
                  {
                    i91 = i77 + 1;
                    i92 = str.charAt(i77);
                    if (i92 < 55296)
                      break;
                    i89 |= (i92 & 0x1FFF) << i90;
                    i90 += 13;
                    i77 = i91;
                  }
                  i79 = i89 | i92 << i90;
                  i52 = i91;
                }
                while (true)
                {
                  int i80 = i42 - 51;
                  int i83;
                  if ((i80 == 9) || (i80 == 17))
                  {
                    int i81 = 1 + (i30 / 3 << 1);
                    int i82 = i32 + 1;
                    arrayOfObject2[i81] = arrayOfObject1[i32];
                    i83 = i82;
                  }
                  while (true)
                  {
                    label1503: int i84 = i79 << 1;
                    Object localObject2 = arrayOfObject1[i84];
                    Field localField3;
                    label1531: int i85;
                    int i86;
                    Object localObject3;
                    Field localField4;
                    if ((localObject2 instanceof Field))
                    {
                      localField3 = (Field)localObject2;
                      i85 = (int)localUnsafe.objectFieldOffset(localField3);
                      i86 = i84 + 1;
                      localObject3 = arrayOfObject1[i86];
                      if (!(localObject3 instanceof Field))
                        break label1766;
                      localField4 = (Field)localObject3;
                    }
                    int i49;
                    int i53;
                    int i51;
                    int i54;
                    int i57;
                    label1626: int i58;
                    while (true)
                    {
                      i49 = (int)localUnsafe.objectFieldOffset(localField4);
                      i32 = i83;
                      i53 = 0;
                      i51 = i85;
                      i54 = i29;
                      int i55 = i30 + 1;
                      arrayOfInt2[i30] = i36;
                      int i56 = i55 + 1;
                      if ((0x200 & i40) == 0)
                        break label2313;
                      i57 = 536870912;
                      if ((0x100 & i40) == 0)
                        break label2319;
                      i58 = 268435456;
                      label1639: arrayOfInt2[i55] = (i51 | (i58 | i57 | i42 << 20));
                      int i59 = i56 + 1;
                      arrayOfInt2[i56] = (i49 | i53 << 20);
                      i30 = i59;
                      i29 = i54;
                      i33 = i52;
                      i28 = i43;
                      break;
                      if ((i80 != 12) || ((m & 0x1) != 1))
                        break label2438;
                      int i87 = 1 + (i30 / 3 << 1);
                      int i88 = i32 + 1;
                      arrayOfObject2[i87] = arrayOfObject1[i32];
                      i83 = i88;
                      break label1503;
                      localField3 = zza(localClass, (String)localObject2);
                      arrayOfObject1[i84] = localField3;
                      break label1531;
                      label1766: localField4 = zza(localClass, (String)localObject3);
                      arrayOfObject1[i86] = localField4;
                    }
                    int i44 = i32 + 1;
                    Field localField1 = zza(localClass, (String)arrayOfObject1[i32]);
                    int i45;
                    int i46;
                    if ((i42 == 9) || (i42 == 17))
                    {
                      arrayOfObject2[(1 + (i30 / 3 << 1))] = localField1.getType();
                      i45 = i44;
                      i46 = i31;
                    }
                    while (true)
                    {
                      int i47 = (int)localUnsafe.objectFieldOffset(localField1);
                      int i62;
                      int i63;
                      int i48;
                      int i73;
                      int i64;
                      if (((m & 0x1) == 1) && (i42 <= 17))
                      {
                        i62 = i41 + 1;
                        i63 = str.charAt(i41);
                        if (i63 >= 55296)
                        {
                          int i66 = i63 & 0x1FFF;
                          int i67 = 13;
                          int i68;
                          while (true)
                          {
                            i48 = i62 + 1;
                            i68 = str.charAt(i62);
                            if (i68 < 55296)
                              break;
                            i66 |= (i68 & 0x1FFF) << i67;
                            i67 += 13;
                            i62 = i48;
                          }
                          if ((i42 == 27) || (i42 == 49))
                          {
                            int i69 = 1 + (i30 / 3 << 1);
                            int i70 = i44 + 1;
                            arrayOfObject2[i69] = arrayOfObject1[i44];
                            i46 = i31;
                            i45 = i70;
                            continue;
                          }
                          if ((i42 == 12) || (i42 == 30) || (i42 == 44))
                          {
                            if ((m & 0x1) != 1)
                              break label2427;
                            int i71 = 1 + (i30 / 3 << 1);
                            int i72 = i44 + 1;
                            arrayOfObject2[i71] = arrayOfObject1[i44];
                            i46 = i31;
                            i45 = i72;
                            continue;
                          }
                          if (i42 != 50)
                            break label2427;
                          i73 = i31 + 1;
                          arrayOfInt1[i31] = i30;
                          int i74 = i30 / 3 << 1;
                          i45 = i44 + 1;
                          arrayOfObject2[i74] = arrayOfObject1[i44];
                          if ((0x800 & i40) == 0)
                            break label2420;
                          int i75 = 1 + (i30 / 3 << 1);
                          int i76 = i45 + 1;
                          arrayOfObject2[i75] = arrayOfObject1[i45];
                          i45 = i76;
                          i46 = i73;
                          continue;
                          i64 = i66 | i68 << i67;
                        }
                      }
                      else
                      {
                        while (true)
                        {
                          int i65 = (i22 << 1) + i64 / 32;
                          Object localObject1 = arrayOfObject1[i65];
                          Field localField2;
                          label2203: int i50;
                          if ((localObject1 instanceof Field))
                          {
                            localField2 = (Field)localObject1;
                            i49 = (int)localUnsafe.objectFieldOffset(localField2);
                            i50 = i64 % 32;
                          }
                          while (true)
                            if ((i42 >= 18) && (i42 <= 49))
                            {
                              int i60 = i29 + 1;
                              arrayOfInt1[i29] = i47;
                              int i61 = i50;
                              i54 = i60;
                              i32 = i45;
                              i51 = i47;
                              i52 = i48;
                              i31 = i46;
                              i53 = i61;
                              break;
                              localField2 = zza(localClass, (String)localObject1);
                              arrayOfObject1[i65] = localField2;
                              break label2203;
                              i48 = i41;
                              i49 = 0;
                              i50 = 0;
                              continue;
                              label2313: i57 = 0;
                              break label1626;
                              label2319: i58 = 0;
                              break label1639;
                              return new zzvz(arrayOfInt2, arrayOfObject2, i25, i27, localzzwj.zzxo(), bool, false, arrayOfInt1, i19, i21 + i19, paramzzwc, paramzzvf, paramzzxd, paramzzuc, paramzzvq);
                              ((zzwy)paramzzvt).zzxm();
                              throw new NoSuchMethodError();
                            }
                          i32 = i45;
                          i51 = i47;
                          i52 = i48;
                          i31 = i46;
                          i53 = i50;
                          i54 = i29;
                          break;
                          i64 = i63;
                          i48 = i62;
                        }
                        label2420: i46 = i73;
                        continue;
                        label2427: i45 = i44;
                        i46 = i31;
                      }
                    }
                    label2438: i83 = i32;
                  }
                  label2445: i52 = i77;
                  i79 = i78;
                }
              }
              i40 = i39;
            }
            label2474: i36 = i35;
            i37 = i34;
          }
          label2485: i6 = i4;
        }
      }
      label2499: m = k;
      n = j;
    }
  }

  private final <K, V, UT, UB> UB zza(int paramInt1, int paramInt2, Map<K, V> paramMap, zzut paramzzut, UB paramUB, zzxd<UT, UB> paramzzxd)
  {
    zzvo localzzvo = this.zzcbi.zzah(zzbr(paramInt1));
    Iterator localIterator = paramMap.entrySet().iterator();
    while (localIterator.hasNext())
    {
      Map.Entry localEntry = (Map.Entry)localIterator.next();
      if (!paramzzut.zzb(((Integer)localEntry.getValue()).intValue()))
      {
        if (paramUB == null)
          paramUB = paramzzxd.zzyk();
        zztm localzztm = zzte.zzao(zzvn.zza(localzzvo, localEntry.getKey(), localEntry.getValue()));
        zztv localzztv = localzztm.zzui();
        try
        {
          zzvn.zza(localzztv, localzzvo, localEntry.getKey(), localEntry.getValue());
          paramzzxd.zza(paramUB, paramInt2, localzztm.zzuh());
          localIterator.remove();
        }
        catch (IOException localIOException)
        {
          throw new RuntimeException(localIOException);
        }
      }
    }
    return paramUB;
  }

  private final <UT, UB> UB zza(Object paramObject, int paramInt, UB paramUB, zzxd<UT, UB> paramzzxd)
  {
    int i = this.zzcas[paramInt];
    Object localObject = zzxj.zzp(paramObject, 0xFFFFF & zzbt(paramInt));
    if (localObject == null);
    zzut localzzut;
    do
    {
      return paramUB;
      localzzut = zzbs(paramInt);
    }
    while (localzzut == null);
    return zza(paramInt, i, this.zzcbi.zzac(localObject), localzzut, paramUB, paramzzxd);
  }

  private static Field zza(Class<?> paramClass, String paramString)
  {
    try
    {
      Field localField2 = paramClass.getDeclaredField(paramString);
      localField1 = localField2;
      return localField1;
    }
    catch (NoSuchFieldException localNoSuchFieldException)
    {
      Field localField1;
      Field[] arrayOfField = paramClass.getDeclaredFields();
      int i = arrayOfField.length;
      for (int j = 0; ; j++)
      {
        if (j >= i)
          break label58;
        localField1 = arrayOfField[j];
        if (paramString.equals(localField1.getName()))
          break;
      }
      label58: String str1 = paramClass.getName();
      String str2 = Arrays.toString(arrayOfField);
      throw new RuntimeException(40 + String.valueOf(paramString).length() + String.valueOf(str1).length() + String.valueOf(str2).length() + "Field " + paramString + " for " + str1 + " not found. Known fields are " + str2);
    }
  }

  private static void zza(int paramInt, Object paramObject, zzxy paramzzxy)
    throws IOException
  {
    if ((paramObject instanceof String))
    {
      paramzzxy.zzb(paramInt, (String)paramObject);
      return;
    }
    paramzzxy.zza(paramInt, (zzte)paramObject);
  }

  private static <UT, UB> void zza(zzxd<UT, UB> paramzzxd, T paramT, zzxy paramzzxy)
    throws IOException
  {
    paramzzxd.zza(paramzzxd.zzal(paramT), paramzzxy);
  }

  private final <K, V> void zza(zzxy paramzzxy, int paramInt1, Object paramObject, int paramInt2)
    throws IOException
  {
    if (paramObject != null)
      paramzzxy.zza(paramInt1, this.zzcbi.zzah(zzbr(paramInt2)), this.zzcbi.zzad(paramObject));
  }

  private final void zza(Object paramObject, int paramInt, zzwk paramzzwk)
    throws IOException
  {
    if (zzbv(paramInt))
    {
      zzxj.zza(paramObject, paramInt & 0xFFFFF, paramzzwk.zzuq());
      return;
    }
    if (this.zzcay)
    {
      zzxj.zza(paramObject, paramInt & 0xFFFFF, paramzzwk.readString());
      return;
    }
    zzxj.zza(paramObject, paramInt & 0xFFFFF, paramzzwk.zzur());
  }

  private final void zza(T paramT1, T paramT2, int paramInt)
  {
    long l = 0xFFFFF & zzbt(paramInt);
    if (!zzb(paramT2, paramInt));
    Object localObject2;
    do
    {
      return;
      Object localObject1 = zzxj.zzp(paramT1, l);
      localObject2 = zzxj.zzp(paramT2, l);
      if ((localObject1 != null) && (localObject2 != null))
      {
        zzxj.zza(paramT1, l, zzuq.zzb(localObject1, localObject2));
        zzc(paramT1, paramInt);
        return;
      }
    }
    while (localObject2 == null);
    zzxj.zza(paramT1, l, localObject2);
    zzc(paramT1, paramInt);
  }

  private final boolean zza(T paramT, int paramInt1, int paramInt2)
  {
    return zzxj.zzk(paramT, 0xFFFFF & zzbu(paramInt2)) == paramInt1;
  }

  private final boolean zza(T paramT, int paramInt1, int paramInt2, int paramInt3)
  {
    if (this.zzcaz)
      return zzb(paramT, paramInt1);
    return (paramInt2 & paramInt3) != 0;
  }

  private static boolean zza(Object paramObject, int paramInt, zzwl paramzzwl)
  {
    return paramzzwl.zzaj(zzxj.zzp(paramObject, 0xFFFFF & paramInt));
  }

  private final void zzb(T paramT, int paramInt1, int paramInt2)
  {
    zzxj.zzb(paramT, 0xFFFFF & zzbu(paramInt2), paramInt1);
  }

  private final void zzb(T paramT, zzxy paramzzxy)
    throws IOException
  {
    boolean bool1 = this.zzcax;
    Map.Entry localEntry1 = null;
    Iterator localIterator = null;
    if (bool1)
    {
      zzuf localzzuf = this.zzcbh.zzw(paramT);
      boolean bool2 = localzzuf.isEmpty();
      localEntry1 = null;
      localIterator = null;
      if (!bool2)
      {
        localIterator = localzzuf.iterator();
        localEntry1 = (Map.Entry)localIterator.next();
      }
    }
    int i = this.zzcas.length;
    Unsafe localUnsafe = zzcar;
    int j = 0;
    int k = -1;
    Object localObject1 = localEntry1;
    int m = 0;
    int i7;
    Object localObject3;
    int i3;
    int i5;
    int i4;
    label198: Object localObject2;
    if (j < i)
    {
      int n = zzbt(j);
      int i1 = this.zzcas[j];
      int i2 = (0xFF00000 & n) >>> 20;
      if ((!this.zzcaz) && (i2 <= 17))
      {
        int i6 = this.zzcas[(j + 2)];
        i7 = 0xFFFFF & i6;
        if (i7 != k)
        {
          m = localUnsafe.getInt(paramT, i7);
          int i8 = 1 << (i6 >>> 20);
          localObject3 = localObject1;
          i3 = i7;
          i5 = i8;
          i4 = m;
          if ((localObject3 != null) && (this.zzcbh.zzb(localObject3) <= i1))
          {
            this.zzcbh.zza(paramzzxy, localObject3);
            if (localIterator.hasNext());
            for (Map.Entry localEntry2 = (Map.Entry)localIterator.next(); ; localEntry2 = null)
            {
              localObject3 = localEntry2;
              break;
            }
          }
          long l = 0xFFFFF & n;
          switch (i2)
          {
          default:
          case 0:
          case 1:
          case 2:
          case 3:
          case 4:
          case 5:
          case 6:
          case 7:
          case 8:
          case 9:
          case 10:
          case 11:
          case 12:
          case 13:
          case 14:
          case 15:
          case 16:
          case 17:
          case 18:
          case 19:
          case 20:
          case 21:
          case 22:
          case 23:
          case 24:
          case 25:
          case 26:
          case 27:
          case 28:
          case 29:
          case 30:
          case 31:
          case 32:
          case 33:
          case 34:
          case 35:
          case 36:
          case 37:
          case 38:
          case 39:
          case 40:
          case 41:
          case 42:
          case 43:
          case 44:
          case 45:
          case 46:
          case 47:
          case 48:
          case 49:
          case 50:
          case 51:
          case 52:
          case 53:
          case 54:
          case 55:
          case 56:
          case 57:
          case 58:
          case 59:
          case 60:
          case 61:
          case 62:
          case 63:
          case 64:
          case 65:
          case 66:
          case 67:
          case 68:
          }
          while (true)
          {
            j += 3;
            m = i4;
            k = i3;
            localObject1 = localObject3;
            break;
            if ((i4 & i5) != 0)
            {
              paramzzxy.zza(i1, zzxj.zzo(paramT, l));
              continue;
              if ((i4 & i5) != 0)
              {
                paramzzxy.zza(i1, zzxj.zzn(paramT, l));
                continue;
                if ((i4 & i5) != 0)
                {
                  paramzzxy.zzi(i1, localUnsafe.getLong(paramT, l));
                  continue;
                  if ((i4 & i5) != 0)
                  {
                    paramzzxy.zza(i1, localUnsafe.getLong(paramT, l));
                    continue;
                    if ((i4 & i5) != 0)
                    {
                      paramzzxy.zzd(i1, localUnsafe.getInt(paramT, l));
                      continue;
                      if ((i4 & i5) != 0)
                      {
                        paramzzxy.zzc(i1, localUnsafe.getLong(paramT, l));
                        continue;
                        if ((i4 & i5) != 0)
                        {
                          paramzzxy.zzg(i1, localUnsafe.getInt(paramT, l));
                          continue;
                          if ((i4 & i5) != 0)
                          {
                            paramzzxy.zzb(i1, zzxj.zzm(paramT, l));
                            continue;
                            if ((i4 & i5) != 0)
                            {
                              zza(i1, localUnsafe.getObject(paramT, l), paramzzxy);
                              continue;
                              if ((i4 & i5) != 0)
                              {
                                paramzzxy.zza(i1, localUnsafe.getObject(paramT, l), zzbq(j));
                                continue;
                                if ((i4 & i5) != 0)
                                {
                                  paramzzxy.zza(i1, (zzte)localUnsafe.getObject(paramT, l));
                                  continue;
                                  if ((i4 & i5) != 0)
                                  {
                                    paramzzxy.zze(i1, localUnsafe.getInt(paramT, l));
                                    continue;
                                    if ((i4 & i5) != 0)
                                    {
                                      paramzzxy.zzo(i1, localUnsafe.getInt(paramT, l));
                                      continue;
                                      if ((i4 & i5) != 0)
                                      {
                                        paramzzxy.zzn(i1, localUnsafe.getInt(paramT, l));
                                        continue;
                                        if ((i4 & i5) != 0)
                                        {
                                          paramzzxy.zzj(i1, localUnsafe.getLong(paramT, l));
                                          continue;
                                          if ((i4 & i5) != 0)
                                          {
                                            paramzzxy.zzf(i1, localUnsafe.getInt(paramT, l));
                                            continue;
                                            if ((i4 & i5) != 0)
                                            {
                                              paramzzxy.zzb(i1, localUnsafe.getLong(paramT, l));
                                              continue;
                                              if ((i4 & i5) != 0)
                                              {
                                                paramzzxy.zzb(i1, localUnsafe.getObject(paramT, l), zzbq(j));
                                                continue;
                                                zzwn.zza(this.zzcas[j], (List)localUnsafe.getObject(paramT, l), paramzzxy, false);
                                                continue;
                                                zzwn.zzb(this.zzcas[j], (List)localUnsafe.getObject(paramT, l), paramzzxy, false);
                                                continue;
                                                zzwn.zzc(this.zzcas[j], (List)localUnsafe.getObject(paramT, l), paramzzxy, false);
                                                continue;
                                                zzwn.zzd(this.zzcas[j], (List)localUnsafe.getObject(paramT, l), paramzzxy, false);
                                                continue;
                                                zzwn.zzh(this.zzcas[j], (List)localUnsafe.getObject(paramT, l), paramzzxy, false);
                                                continue;
                                                zzwn.zzf(this.zzcas[j], (List)localUnsafe.getObject(paramT, l), paramzzxy, false);
                                                continue;
                                                zzwn.zzk(this.zzcas[j], (List)localUnsafe.getObject(paramT, l), paramzzxy, false);
                                                continue;
                                                zzwn.zzn(this.zzcas[j], (List)localUnsafe.getObject(paramT, l), paramzzxy, false);
                                                continue;
                                                zzwn.zza(this.zzcas[j], (List)localUnsafe.getObject(paramT, l), paramzzxy);
                                                continue;
                                                zzwn.zza(this.zzcas[j], (List)localUnsafe.getObject(paramT, l), paramzzxy, zzbq(j));
                                                continue;
                                                zzwn.zzb(this.zzcas[j], (List)localUnsafe.getObject(paramT, l), paramzzxy);
                                                continue;
                                                zzwn.zzi(this.zzcas[j], (List)localUnsafe.getObject(paramT, l), paramzzxy, false);
                                                continue;
                                                zzwn.zzm(this.zzcas[j], (List)localUnsafe.getObject(paramT, l), paramzzxy, false);
                                                continue;
                                                zzwn.zzl(this.zzcas[j], (List)localUnsafe.getObject(paramT, l), paramzzxy, false);
                                                continue;
                                                zzwn.zzg(this.zzcas[j], (List)localUnsafe.getObject(paramT, l), paramzzxy, false);
                                                continue;
                                                zzwn.zzj(this.zzcas[j], (List)localUnsafe.getObject(paramT, l), paramzzxy, false);
                                                continue;
                                                zzwn.zze(this.zzcas[j], (List)localUnsafe.getObject(paramT, l), paramzzxy, false);
                                                continue;
                                                zzwn.zza(this.zzcas[j], (List)localUnsafe.getObject(paramT, l), paramzzxy, true);
                                                continue;
                                                zzwn.zzb(this.zzcas[j], (List)localUnsafe.getObject(paramT, l), paramzzxy, true);
                                                continue;
                                                zzwn.zzc(this.zzcas[j], (List)localUnsafe.getObject(paramT, l), paramzzxy, true);
                                                continue;
                                                zzwn.zzd(this.zzcas[j], (List)localUnsafe.getObject(paramT, l), paramzzxy, true);
                                                continue;
                                                zzwn.zzh(this.zzcas[j], (List)localUnsafe.getObject(paramT, l), paramzzxy, true);
                                                continue;
                                                zzwn.zzf(this.zzcas[j], (List)localUnsafe.getObject(paramT, l), paramzzxy, true);
                                                continue;
                                                zzwn.zzk(this.zzcas[j], (List)localUnsafe.getObject(paramT, l), paramzzxy, true);
                                                continue;
                                                zzwn.zzn(this.zzcas[j], (List)localUnsafe.getObject(paramT, l), paramzzxy, true);
                                                continue;
                                                zzwn.zzi(this.zzcas[j], (List)localUnsafe.getObject(paramT, l), paramzzxy, true);
                                                continue;
                                                zzwn.zzm(this.zzcas[j], (List)localUnsafe.getObject(paramT, l), paramzzxy, true);
                                                continue;
                                                zzwn.zzl(this.zzcas[j], (List)localUnsafe.getObject(paramT, l), paramzzxy, true);
                                                continue;
                                                zzwn.zzg(this.zzcas[j], (List)localUnsafe.getObject(paramT, l), paramzzxy, true);
                                                continue;
                                                zzwn.zzj(this.zzcas[j], (List)localUnsafe.getObject(paramT, l), paramzzxy, true);
                                                continue;
                                                zzwn.zze(this.zzcas[j], (List)localUnsafe.getObject(paramT, l), paramzzxy, true);
                                                continue;
                                                zzwn.zzb(this.zzcas[j], (List)localUnsafe.getObject(paramT, l), paramzzxy, zzbq(j));
                                                continue;
                                                zza(paramzzxy, i1, localUnsafe.getObject(paramT, l), j);
                                                continue;
                                                if (zza(paramT, i1, j))
                                                {
                                                  paramzzxy.zza(i1, zzf(paramT, l));
                                                  continue;
                                                  if (zza(paramT, i1, j))
                                                  {
                                                    paramzzxy.zza(i1, zzg(paramT, l));
                                                    continue;
                                                    if (zza(paramT, i1, j))
                                                    {
                                                      paramzzxy.zzi(i1, zzi(paramT, l));
                                                      continue;
                                                      if (zza(paramT, i1, j))
                                                      {
                                                        paramzzxy.zza(i1, zzi(paramT, l));
                                                        continue;
                                                        if (zza(paramT, i1, j))
                                                        {
                                                          paramzzxy.zzd(i1, zzh(paramT, l));
                                                          continue;
                                                          if (zza(paramT, i1, j))
                                                          {
                                                            paramzzxy.zzc(i1, zzi(paramT, l));
                                                            continue;
                                                            if (zza(paramT, i1, j))
                                                            {
                                                              paramzzxy.zzg(i1, zzh(paramT, l));
                                                              continue;
                                                              if (zza(paramT, i1, j))
                                                              {
                                                                paramzzxy.zzb(i1, zzj(paramT, l));
                                                                continue;
                                                                if (zza(paramT, i1, j))
                                                                {
                                                                  zza(i1, localUnsafe.getObject(paramT, l), paramzzxy);
                                                                  continue;
                                                                  if (zza(paramT, i1, j))
                                                                  {
                                                                    paramzzxy.zza(i1, localUnsafe.getObject(paramT, l), zzbq(j));
                                                                    continue;
                                                                    if (zza(paramT, i1, j))
                                                                    {
                                                                      paramzzxy.zza(i1, (zzte)localUnsafe.getObject(paramT, l));
                                                                      continue;
                                                                      if (zza(paramT, i1, j))
                                                                      {
                                                                        paramzzxy.zze(i1, zzh(paramT, l));
                                                                        continue;
                                                                        if (zza(paramT, i1, j))
                                                                        {
                                                                          paramzzxy.zzo(i1, zzh(paramT, l));
                                                                          continue;
                                                                          if (zza(paramT, i1, j))
                                                                          {
                                                                            paramzzxy.zzn(i1, zzh(paramT, l));
                                                                            continue;
                                                                            if (zza(paramT, i1, j))
                                                                            {
                                                                              paramzzxy.zzj(i1, zzi(paramT, l));
                                                                              continue;
                                                                              if (zza(paramT, i1, j))
                                                                              {
                                                                                paramzzxy.zzf(i1, zzh(paramT, l));
                                                                                continue;
                                                                                if (zza(paramT, i1, j))
                                                                                {
                                                                                  paramzzxy.zzb(i1, zzi(paramT, l));
                                                                                  continue;
                                                                                  if (zza(paramT, i1, j))
                                                                                    paramzzxy.zzb(i1, localUnsafe.getObject(paramT, l), zzbq(j));
                                                                                }
                                                                              }
                                                                            }
                                                                          }
                                                                        }
                                                                      }
                                                                    }
                                                                  }
                                                                }
                                                              }
                                                            }
                                                          }
                                                        }
                                                      }
                                                    }
                                                  }
                                                }
                                              }
                                            }
                                          }
                                        }
                                      }
                                    }
                                  }
                                }
                              }
                            }
                          }
                        }
                      }
                    }
                  }
                }
              }
            }
          }
          label2478: localObject2 = null;
        }
      }
    }
    while (true)
    {
      if (localObject2 != null)
      {
        this.zzcbh.zza(paramzzxy, (Map.Entry)localObject2);
        if (!localIterator.hasNext())
          break label2478;
        localObject2 = (Map.Entry)localIterator.next();
        continue;
      }
      zza(this.zzcbg, paramT, paramzzxy);
      return;
      i7 = k;
      break;
      localObject3 = localObject1;
      i3 = k;
      i4 = m;
      i5 = 0;
      break label198;
      localObject2 = localObject1;
    }
  }

  private final void zzb(T paramT1, T paramT2, int paramInt)
  {
    int i = zzbt(paramInt);
    int j = this.zzcas[paramInt];
    long l = i & 0xFFFFF;
    if (!zza(paramT2, j, paramInt));
    Object localObject2;
    do
    {
      return;
      Object localObject1 = zzxj.zzp(paramT1, l);
      localObject2 = zzxj.zzp(paramT2, l);
      if ((localObject1 != null) && (localObject2 != null))
      {
        zzxj.zza(paramT1, l, zzuq.zzb(localObject1, localObject2));
        zzb(paramT1, j, paramInt);
        return;
      }
    }
    while (localObject2 == null);
    zzxj.zza(paramT1, l, localObject2);
    zzb(paramT1, j, paramInt);
  }

  private final boolean zzb(T paramT, int paramInt)
  {
    if (this.zzcaz)
    {
      int j = zzbt(paramInt);
      long l = j & 0xFFFFF;
      switch ((j & 0xFF00000) >>> 20)
      {
      default:
        throw new IllegalArgumentException();
      case 0:
        return zzxj.zzo(paramT, l) != 0.0D;
      case 1:
        return zzxj.zzn(paramT, l) != 0.0F;
      case 2:
        return zzxj.zzl(paramT, l) != 0L;
      case 3:
        return zzxj.zzl(paramT, l) != 0L;
      case 4:
        return zzxj.zzk(paramT, l) != 0;
      case 5:
        return zzxj.zzl(paramT, l) != 0L;
      case 6:
        return zzxj.zzk(paramT, l) != 0;
      case 7:
        return zzxj.zzm(paramT, l);
      case 8:
        Object localObject = zzxj.zzp(paramT, l);
        if ((localObject instanceof String))
          return !((String)localObject).isEmpty();
        if ((localObject instanceof zzte))
          return !zzte.zzbts.equals(localObject);
        throw new IllegalArgumentException();
      case 9:
        return zzxj.zzp(paramT, l) != null;
      case 10:
        return !zzte.zzbts.equals(zzxj.zzp(paramT, l));
      case 11:
        return zzxj.zzk(paramT, l) != 0;
      case 12:
        return zzxj.zzk(paramT, l) != 0;
      case 13:
        return zzxj.zzk(paramT, l) != 0;
      case 14:
        return zzxj.zzl(paramT, l) != 0L;
      case 15:
        return zzxj.zzk(paramT, l) != 0;
      case 16:
        return zzxj.zzl(paramT, l) != 0L;
      case 17:
      }
      return zzxj.zzp(paramT, l) != null;
    }
    int i = zzbu(paramInt);
    return (1 << (i >>> 20) & zzxj.zzk(paramT, i & 0xFFFFF)) != 0;
  }

  private final zzwl zzbq(int paramInt)
  {
    int i = paramInt / 3 << 1;
    zzwl localzzwl1 = (zzwl)this.zzcat[i];
    if (localzzwl1 != null)
      return localzzwl1;
    zzwl localzzwl2 = zzwh.zzxt().zzi((Class)this.zzcat[(i + 1)]);
    this.zzcat[i] = localzzwl2;
    return localzzwl2;
  }

  private final Object zzbr(int paramInt)
  {
    return this.zzcat[(paramInt / 3 << 1)];
  }

  private final zzut zzbs(int paramInt)
  {
    return (zzut)this.zzcat[(1 + (paramInt / 3 << 1))];
  }

  private final int zzbt(int paramInt)
  {
    return this.zzcas[(paramInt + 1)];
  }

  private final int zzbu(int paramInt)
  {
    return this.zzcas[(paramInt + 2)];
  }

  private static boolean zzbv(int paramInt)
  {
    return (0x20000000 & paramInt) != 0;
  }

  private final void zzc(T paramT, int paramInt)
  {
    if (this.zzcaz)
      return;
    int i = zzbu(paramInt);
    int j = 1 << (i >>> 20);
    long l = i & 0xFFFFF;
    zzxj.zzb(paramT, l, j | zzxj.zzk(paramT, l));
  }

  private final boolean zzc(T paramT1, T paramT2, int paramInt)
  {
    return zzb(paramT1, paramInt) == zzb(paramT2, paramInt);
  }

  private static <E> List<E> zze(Object paramObject, long paramLong)
  {
    return (List)zzxj.zzp(paramObject, paramLong);
  }

  private static <T> double zzf(T paramT, long paramLong)
  {
    return ((Double)zzxj.zzp(paramT, paramLong)).doubleValue();
  }

  private static <T> float zzg(T paramT, long paramLong)
  {
    return ((Float)zzxj.zzp(paramT, paramLong)).floatValue();
  }

  private static <T> int zzh(T paramT, long paramLong)
  {
    return ((Integer)zzxj.zzp(paramT, paramLong)).intValue();
  }

  private static <T> long zzi(T paramT, long paramLong)
  {
    return ((Long)zzxj.zzp(paramT, paramLong)).longValue();
  }

  private static <T> boolean zzj(T paramT, long paramLong)
  {
    return ((Boolean)zzxj.zzp(paramT, paramLong)).booleanValue();
  }

  public final boolean equals(T paramT1, T paramT2)
  {
    int i = this.zzcas.length;
    int j = 0;
    if (j < i)
    {
      k = zzbt(j);
      l = k & 0xFFFFF;
      switch ((k & 0xFF00000) >>> 20)
      {
      default:
        bool = true;
        if (bool)
          break;
      case 0:
      case 1:
      case 2:
      case 3:
      case 4:
      case 5:
      case 6:
      case 7:
      case 8:
      case 9:
      case 10:
      case 11:
      case 12:
      case 13:
      case 14:
      case 15:
      case 16:
      case 17:
      case 18:
      case 19:
      case 20:
      case 21:
      case 22:
      case 23:
      case 24:
      case 25:
      case 26:
      case 27:
      case 28:
      case 29:
      case 30:
      case 31:
      case 32:
      case 33:
      case 34:
      case 35:
      case 36:
      case 37:
      case 38:
      case 39:
      case 40:
      case 41:
      case 42:
      case 43:
      case 44:
      case 45:
      case 46:
      case 47:
      case 48:
      case 49:
      case 50:
      case 51:
      case 52:
      case 53:
      case 54:
      case 55:
      case 56:
      case 57:
      case 58:
      case 59:
      case 60:
      case 61:
      case 62:
      case 63:
      case 64:
      case 65:
      case 66:
      case 67:
      case 68:
      }
    }
    while (!this.zzcbg.zzal(paramT1).equals(this.zzcbg.zzal(paramT2)))
    {
      while (true)
      {
        int k;
        long l;
        boolean bool;
        return false;
        if ((!zzc(paramT1, paramT2, j)) || (Double.doubleToLongBits(zzxj.zzo(paramT1, l)) != Double.doubleToLongBits(zzxj.zzo(paramT2, l))))
        {
          bool = false;
          continue;
          if ((!zzc(paramT1, paramT2, j)) || (Float.floatToIntBits(zzxj.zzn(paramT1, l)) != Float.floatToIntBits(zzxj.zzn(paramT2, l))))
          {
            bool = false;
            continue;
            if ((!zzc(paramT1, paramT2, j)) || (zzxj.zzl(paramT1, l) != zzxj.zzl(paramT2, l)))
            {
              bool = false;
              continue;
              if ((!zzc(paramT1, paramT2, j)) || (zzxj.zzl(paramT1, l) != zzxj.zzl(paramT2, l)))
              {
                bool = false;
                continue;
                if ((!zzc(paramT1, paramT2, j)) || (zzxj.zzk(paramT1, l) != zzxj.zzk(paramT2, l)))
                {
                  bool = false;
                  continue;
                  if ((!zzc(paramT1, paramT2, j)) || (zzxj.zzl(paramT1, l) != zzxj.zzl(paramT2, l)))
                  {
                    bool = false;
                    continue;
                    if ((!zzc(paramT1, paramT2, j)) || (zzxj.zzk(paramT1, l) != zzxj.zzk(paramT2, l)))
                    {
                      bool = false;
                      continue;
                      if ((!zzc(paramT1, paramT2, j)) || (zzxj.zzm(paramT1, l) != zzxj.zzm(paramT2, l)))
                      {
                        bool = false;
                        continue;
                        if ((!zzc(paramT1, paramT2, j)) || (!zzwn.zze(zzxj.zzp(paramT1, l), zzxj.zzp(paramT2, l))))
                        {
                          bool = false;
                          continue;
                          if ((!zzc(paramT1, paramT2, j)) || (!zzwn.zze(zzxj.zzp(paramT1, l), zzxj.zzp(paramT2, l))))
                          {
                            bool = false;
                            continue;
                            if ((!zzc(paramT1, paramT2, j)) || (!zzwn.zze(zzxj.zzp(paramT1, l), zzxj.zzp(paramT2, l))))
                            {
                              bool = false;
                              continue;
                              if ((!zzc(paramT1, paramT2, j)) || (zzxj.zzk(paramT1, l) != zzxj.zzk(paramT2, l)))
                              {
                                bool = false;
                                continue;
                                if ((!zzc(paramT1, paramT2, j)) || (zzxj.zzk(paramT1, l) != zzxj.zzk(paramT2, l)))
                                {
                                  bool = false;
                                  continue;
                                  if ((!zzc(paramT1, paramT2, j)) || (zzxj.zzk(paramT1, l) != zzxj.zzk(paramT2, l)))
                                  {
                                    bool = false;
                                    continue;
                                    if ((!zzc(paramT1, paramT2, j)) || (zzxj.zzl(paramT1, l) != zzxj.zzl(paramT2, l)))
                                    {
                                      bool = false;
                                      continue;
                                      if ((!zzc(paramT1, paramT2, j)) || (zzxj.zzk(paramT1, l) != zzxj.zzk(paramT2, l)))
                                      {
                                        bool = false;
                                        continue;
                                        if ((!zzc(paramT1, paramT2, j)) || (zzxj.zzl(paramT1, l) != zzxj.zzl(paramT2, l)))
                                        {
                                          bool = false;
                                          continue;
                                          if ((!zzc(paramT1, paramT2, j)) || (!zzwn.zze(zzxj.zzp(paramT1, l), zzxj.zzp(paramT2, l))))
                                          {
                                            bool = false;
                                            continue;
                                            bool = zzwn.zze(zzxj.zzp(paramT1, l), zzxj.zzp(paramT2, l));
                                            continue;
                                            bool = zzwn.zze(zzxj.zzp(paramT1, l), zzxj.zzp(paramT2, l));
                                            continue;
                                            int m = zzbu(j);
                                            if ((zzxj.zzk(paramT1, m & 0xFFFFF) != zzxj.zzk(paramT2, m & 0xFFFFF)) || (!zzwn.zze(zzxj.zzp(paramT1, l), zzxj.zzp(paramT2, l))))
                                              bool = false;
                                          }
                                        }
                                      }
                                    }
                                  }
                                }
                              }
                            }
                          }
                        }
                      }
                    }
                  }
                }
              }
            }
          }
        }
      }
      j += 3;
      break;
    }
    if (this.zzcax)
      return this.zzcbh.zzw(paramT1).equals(this.zzcbh.zzw(paramT2));
    return true;
  }

  public final int hashCode(T paramT)
  {
    int i = this.zzcas.length;
    int j = 0;
    int k = 0;
    int i1;
    long l;
    int i2;
    label344: Object localObject4;
    if (j < i)
    {
      int n = zzbt(j);
      i1 = this.zzcas[j];
      l = 0xFFFFF & n;
      switch ((n & 0xFF00000) >>> 20)
      {
      default:
        i2 = k;
      case 0:
      case 1:
      case 2:
      case 3:
      case 4:
      case 5:
      case 6:
      case 7:
      case 8:
        while (true)
        {
          j += 3;
          k = i2;
          break;
          i2 = k * 53 + zzuq.zzbd(Double.doubleToLongBits(zzxj.zzo(paramT, l)));
          continue;
          i2 = k * 53 + Float.floatToIntBits(zzxj.zzn(paramT, l));
          continue;
          i2 = k * 53 + zzuq.zzbd(zzxj.zzl(paramT, l));
          continue;
          i2 = k * 53 + zzuq.zzbd(zzxj.zzl(paramT, l));
          continue;
          i2 = k * 53 + zzxj.zzk(paramT, l);
          continue;
          i2 = k * 53 + zzuq.zzbd(zzxj.zzl(paramT, l));
          continue;
          i2 = k * 53 + zzxj.zzk(paramT, l);
          continue;
          i2 = k * 53 + zzuq.zzu(zzxj.zzm(paramT, l));
          continue;
          i2 = k * 53 + ((String)zzxj.zzp(paramT, l)).hashCode();
        }
      case 9:
        localObject4 = zzxj.zzp(paramT, l);
        if (localObject4 == null)
          break;
      case 10:
      case 11:
      case 12:
      case 13:
      case 14:
      case 15:
      case 16:
      case 17:
      case 18:
      case 19:
      case 20:
      case 21:
      case 22:
      case 23:
      case 24:
      case 25:
      case 26:
      case 27:
      case 28:
      case 29:
      case 30:
      case 31:
      case 32:
      case 33:
      case 34:
      case 35:
      case 36:
      case 37:
      case 38:
      case 39:
      case 40:
      case 41:
      case 42:
      case 43:
      case 44:
      case 45:
      case 46:
      case 47:
      case 48:
      case 49:
      case 50:
      case 51:
      case 52:
      case 53:
      case 54:
      case 55:
      case 56:
      case 57:
      case 58:
      case 59:
      case 60:
      case 61:
      case 62:
      case 63:
      case 64:
      case 65:
      case 66:
      case 67:
      case 68:
      }
    }
    for (int i4 = localObject4.hashCode(); ; i4 = 37)
    {
      i2 = i4 + k * 53;
      break label344;
      i2 = k * 53 + zzxj.zzp(paramT, l).hashCode();
      break label344;
      i2 = k * 53 + zzxj.zzk(paramT, l);
      break label344;
      i2 = k * 53 + zzxj.zzk(paramT, l);
      break label344;
      i2 = k * 53 + zzxj.zzk(paramT, l);
      break label344;
      i2 = k * 53 + zzuq.zzbd(zzxj.zzl(paramT, l));
      break label344;
      i2 = k * 53 + zzxj.zzk(paramT, l);
      break label344;
      i2 = k * 53 + zzuq.zzbd(zzxj.zzl(paramT, l));
      break label344;
      Object localObject3 = zzxj.zzp(paramT, l);
      if (localObject3 != null);
      for (int i3 = localObject3.hashCode(); ; i3 = 37)
      {
        i2 = i3 + k * 53;
        break label344;
        i2 = k * 53 + zzxj.zzp(paramT, l).hashCode();
        break label344;
        i2 = k * 53 + zzxj.zzp(paramT, l).hashCode();
        break label344;
        if (!zza(paramT, i1, j))
          break;
        i2 = k * 53 + zzuq.zzbd(Double.doubleToLongBits(zzf(paramT, l)));
        break label344;
        if (!zza(paramT, i1, j))
          break;
        i2 = k * 53 + Float.floatToIntBits(zzg(paramT, l));
        break label344;
        if (!zza(paramT, i1, j))
          break;
        i2 = k * 53 + zzuq.zzbd(zzi(paramT, l));
        break label344;
        if (!zza(paramT, i1, j))
          break;
        i2 = k * 53 + zzuq.zzbd(zzi(paramT, l));
        break label344;
        if (!zza(paramT, i1, j))
          break;
        i2 = k * 53 + zzh(paramT, l);
        break label344;
        if (!zza(paramT, i1, j))
          break;
        i2 = k * 53 + zzuq.zzbd(zzi(paramT, l));
        break label344;
        if (!zza(paramT, i1, j))
          break;
        i2 = k * 53 + zzh(paramT, l);
        break label344;
        if (!zza(paramT, i1, j))
          break;
        i2 = k * 53 + zzuq.zzu(zzj(paramT, l));
        break label344;
        if (!zza(paramT, i1, j))
          break;
        i2 = k * 53 + ((String)zzxj.zzp(paramT, l)).hashCode();
        break label344;
        if (!zza(paramT, i1, j))
          break;
        Object localObject2 = zzxj.zzp(paramT, l);
        i2 = k * 53 + localObject2.hashCode();
        break label344;
        if (!zza(paramT, i1, j))
          break;
        i2 = k * 53 + zzxj.zzp(paramT, l).hashCode();
        break label344;
        if (!zza(paramT, i1, j))
          break;
        i2 = k * 53 + zzh(paramT, l);
        break label344;
        if (!zza(paramT, i1, j))
          break;
        i2 = k * 53 + zzh(paramT, l);
        break label344;
        if (!zza(paramT, i1, j))
          break;
        i2 = k * 53 + zzh(paramT, l);
        break label344;
        if (!zza(paramT, i1, j))
          break;
        i2 = k * 53 + zzuq.zzbd(zzi(paramT, l));
        break label344;
        if (!zza(paramT, i1, j))
          break;
        i2 = k * 53 + zzh(paramT, l);
        break label344;
        if (!zza(paramT, i1, j))
          break;
        i2 = k * 53 + zzuq.zzbd(zzi(paramT, l));
        break label344;
        if (!zza(paramT, i1, j))
          break;
        Object localObject1 = zzxj.zzp(paramT, l);
        i2 = k * 53 + localObject1.hashCode();
        break label344;
        int m = k * 53 + this.zzcbg.zzal(paramT).hashCode();
        if (this.zzcax)
          m = m * 53 + this.zzcbh.zzw(paramT).hashCode();
        return m;
      }
    }
  }

  public final T newInstance()
  {
    return this.zzcbe.newInstance(this.zzcaw);
  }

  // ERROR //
  public final void zza(T paramT, zzwk paramzzwk, zzub paramzzub)
    throws IOException
  {
    // Byte code:
    //   0: aload_3
    //   1: ifnonnull +11 -> 12
    //   4: new 635	java/lang/NullPointerException
    //   7: dup
    //   8: invokespecial 636	java/lang/NullPointerException:<init>	()V
    //   11: athrow
    //   12: aload_0
    //   13: getfield 91	com/google/android/gms/internal/measurement/zzvz:zzcbg	Lcom/google/android/gms/internal/measurement/zzxd;
    //   16: astore 4
    //   18: aload_0
    //   19: getfield 93	com/google/android/gms/internal/measurement/zzvz:zzcbh	Lcom/google/android/gms/internal/measurement/zzuc;
    //   22: astore 5
    //   24: aconst_null
    //   25: astore 6
    //   27: aconst_null
    //   28: astore 7
    //   30: aload_2
    //   31: invokeinterface 639 1 0
    //   36: istore 12
    //   38: iload 12
    //   40: aload_0
    //   41: getfield 61	com/google/android/gms/internal/measurement/zzvz:zzcau	I
    //   44: if_icmplt +151 -> 195
    //   47: iload 12
    //   49: aload_0
    //   50: getfield 63	com/google/android/gms/internal/measurement/zzvz:zzcav	I
    //   53: if_icmpgt +142 -> 195
    //   56: iconst_m1
    //   57: aload_0
    //   58: getfield 57	com/google/android/gms/internal/measurement/zzvz:zzcas	[I
    //   61: arraylength
    //   62: iconst_3
    //   63: idiv
    //   64: iadd
    //   65: istore 58
    //   67: iconst_0
    //   68: istore 59
    //   70: iload 58
    //   72: istore 60
    //   74: iload 59
    //   76: iload 60
    //   78: if_icmpgt +111 -> 189
    //   81: iload 60
    //   83: iload 59
    //   85: iadd
    //   86: iconst_1
    //   87: iushr
    //   88: istore 61
    //   90: iload 61
    //   92: iconst_3
    //   93: imul
    //   94: istore 13
    //   96: aload_0
    //   97: getfield 57	com/google/android/gms/internal/measurement/zzvz:zzcas	[I
    //   100: iload 13
    //   102: iaload
    //   103: istore 62
    //   105: iload 12
    //   107: iload 62
    //   109: if_icmpne +55 -> 164
    //   112: iload 13
    //   114: ifge +258 -> 372
    //   117: iload 12
    //   119: ldc_w 640
    //   122: if_icmpne +93 -> 215
    //   125: aload_0
    //   126: getfield 83	com/google/android/gms/internal/measurement/zzvz:zzcbc	I
    //   129: istore 57
    //   131: iload 57
    //   133: aload_0
    //   134: getfield 85	com/google/android/gms/internal/measurement/zzvz:zzcbd	I
    //   137: if_icmpge +64 -> 201
    //   140: aload_0
    //   141: aload_1
    //   142: aload_0
    //   143: getfield 81	com/google/android/gms/internal/measurement/zzvz:zzcbb	[I
    //   146: iload 57
    //   148: iaload
    //   149: aload 6
    //   151: aload 4
    //   153: invokespecial 642	com/google/android/gms/internal/measurement/zzvz:zza	(Ljava/lang/Object;ILjava/lang/Object;Lcom/google/android/gms/internal/measurement/zzxd;)Ljava/lang/Object;
    //   156: astore 6
    //   158: iinc 57 1
    //   161: goto -30 -> 131
    //   164: iload 12
    //   166: iload 62
    //   168: if_icmpge +12 -> 180
    //   171: iload 61
    //   173: iconst_1
    //   174: isub
    //   175: istore 60
    //   177: goto -103 -> 74
    //   180: iload 61
    //   182: iconst_1
    //   183: iadd
    //   184: istore 59
    //   186: goto -112 -> 74
    //   189: iconst_m1
    //   190: istore 13
    //   192: goto -80 -> 112
    //   195: iconst_m1
    //   196: istore 13
    //   198: goto -86 -> 112
    //   201: aload 6
    //   203: ifnull +11 -> 214
    //   206: aload 4
    //   208: aload_1
    //   209: aload 6
    //   211: invokevirtual 645	com/google/android/gms/internal/measurement/zzxd:zzg	(Ljava/lang/Object;Ljava/lang/Object;)V
    //   214: return
    //   215: aload_0
    //   216: getfield 77	com/google/android/gms/internal/measurement/zzvz:zzcax	Z
    //   219: ifne +44 -> 263
    //   222: aconst_null
    //   223: astore 52
    //   225: aload 52
    //   227: ifnull +53 -> 280
    //   230: aload 7
    //   232: ifnonnull +11 -> 243
    //   235: aload 5
    //   237: aload_1
    //   238: invokevirtual 648	com/google/android/gms/internal/measurement/zzuc:zzx	(Ljava/lang/Object;)Lcom/google/android/gms/internal/measurement/zzuf;
    //   241: astore 7
    //   243: aload 5
    //   245: aload_2
    //   246: aload 52
    //   248: aload_3
    //   249: aload 7
    //   251: aload 6
    //   253: aload 4
    //   255: invokevirtual 651	com/google/android/gms/internal/measurement/zzuc:zza	(Lcom/google/android/gms/internal/measurement/zzwk;Ljava/lang/Object;Lcom/google/android/gms/internal/measurement/zzub;Lcom/google/android/gms/internal/measurement/zzuf;Ljava/lang/Object;Lcom/google/android/gms/internal/measurement/zzxd;)Ljava/lang/Object;
    //   258: astore 6
    //   260: goto -230 -> 30
    //   263: aload 5
    //   265: aload_3
    //   266: aload_0
    //   267: getfield 95	com/google/android/gms/internal/measurement/zzvz:zzcaw	Lcom/google/android/gms/internal/measurement/zzvv;
    //   270: iload 12
    //   272: invokevirtual 654	com/google/android/gms/internal/measurement/zzuc:zza	(Lcom/google/android/gms/internal/measurement/zzub;Lcom/google/android/gms/internal/measurement/zzvv;I)Ljava/lang/Object;
    //   275: astore 52
    //   277: goto -52 -> 225
    //   280: aload 4
    //   282: aload_2
    //   283: invokevirtual 657	com/google/android/gms/internal/measurement/zzxd:zza	(Lcom/google/android/gms/internal/measurement/zzwk;)Z
    //   286: pop
    //   287: aload 6
    //   289: ifnonnull +3045 -> 3334
    //   292: aload 4
    //   294: aload_1
    //   295: invokevirtual 660	com/google/android/gms/internal/measurement/zzxd:zzam	(Ljava/lang/Object;)Ljava/lang/Object;
    //   298: astore 54
    //   300: aload 54
    //   302: astore 10
    //   304: aload 4
    //   306: aload 10
    //   308: aload_2
    //   309: invokevirtual 663	com/google/android/gms/internal/measurement/zzxd:zza	(Ljava/lang/Object;Lcom/google/android/gms/internal/measurement/zzwk;)Z
    //   312: istore 55
    //   314: iload 55
    //   316: ifne +3011 -> 3327
    //   319: aload_0
    //   320: getfield 83	com/google/android/gms/internal/measurement/zzvz:zzcbc	I
    //   323: istore 56
    //   325: iload 56
    //   327: aload_0
    //   328: getfield 85	com/google/android/gms/internal/measurement/zzvz:zzcbd	I
    //   331: if_icmpge +27 -> 358
    //   334: aload_0
    //   335: aload_1
    //   336: aload_0
    //   337: getfield 81	com/google/android/gms/internal/measurement/zzvz:zzcbb	[I
    //   340: iload 56
    //   342: iaload
    //   343: aload 10
    //   345: aload 4
    //   347: invokespecial 642	com/google/android/gms/internal/measurement/zzvz:zza	(Ljava/lang/Object;ILjava/lang/Object;Lcom/google/android/gms/internal/measurement/zzxd;)Ljava/lang/Object;
    //   350: astore 10
    //   352: iinc 56 1
    //   355: goto -30 -> 325
    //   358: aload 10
    //   360: ifnull -146 -> 214
    //   363: aload 4
    //   365: aload_1
    //   366: aload 10
    //   368: invokevirtual 645	com/google/android/gms/internal/measurement/zzxd:zzg	(Ljava/lang/Object;Ljava/lang/Object;)V
    //   371: return
    //   372: aload_0
    //   373: iload 13
    //   375: invokespecial 269	com/google/android/gms/internal/measurement/zzvz:zzbt	(I)I
    //   378: istore 14
    //   380: ldc_w 412
    //   383: iload 14
    //   385: iand
    //   386: bipush 20
    //   388: iushr
    //   389: tableswitch	default:+291 -> 680, 0:+361->750, 1:+472->861, 2:+552->941, 3:+583->972, 4:+610->999, 5:+637->1026, 6:+664->1053, 7:+691->1080, 8:+718->1107, 9:+736->1125, 10:+825->1214, 11:+852->1241, 12:+879->1268, 13:+951->1340, 14:+978->1367, 15:+1005->1394, 16:+1032->1421, 17:+1059->1448, 18:+1148->1537, 19:+1172->1561, 20:+1196->1585, 21:+1220->1609, 22:+1244->1633, 23:+1268->1657, 24:+1292->1681, 25:+1316->1705, 26:+1340->1729, 27:+1396->1785, 28:+1435->1824, 29:+1459->1848, 30:+1483->1872, 31:+1530->1919, 32:+1554->1943, 33:+1578->1967, 34:+1602->1991, 35:+1626->2015, 36:+1650->2039, 37:+1674->2063, 38:+1698->2087, 39:+1722->2111, 40:+1746->2135, 41:+1770->2159, 42:+1794->2183, 43:+1818->2207, 44:+1842->2231, 45:+1889->2278, 46:+1913->2302, 47:+1937->2326, 48:+1961->2350, 49:+1985->2374, 50:+2024->2413, 51:+2163->2552, 52:+2195->2584, 53:+2227->2616, 54:+2259->2648, 55:+2291->2680, 56:+2323->2712, 57:+2355->2744, 58:+2387->2776, 59:+2419->2808, 60:+2439->2828, 61:+2539->2928, 62:+2568->2957, 63:+2600->2989, 64:+2677->3066, 65:+2709->3098, 66:+2741->3130, 67:+2773->3162, 68:+2805->3194
    //   681: iconst_3
    //   682: ifnonnull +2631 -> 3313
    //   685: aload 4
    //   687: invokevirtual 225	com/google/android/gms/internal/measurement/zzxd:zzyk	()Ljava/lang/Object;
    //   690: astore 51
    //   692: aload 51
    //   694: astore 10
    //   696: aload 4
    //   698: aload 10
    //   700: aload_2
    //   701: invokevirtual 663	com/google/android/gms/internal/measurement/zzxd:zza	(Ljava/lang/Object;Lcom/google/android/gms/internal/measurement/zzwk;)Z
    //   704: istore 49
    //   706: iload 49
    //   708: ifne +2536 -> 3244
    //   711: aload_0
    //   712: getfield 83	com/google/android/gms/internal/measurement/zzvz:zzcbc	I
    //   715: istore 50
    //   717: iload 50
    //   719: aload_0
    //   720: getfield 85	com/google/android/gms/internal/measurement/zzvz:zzcbd	I
    //   723: if_icmpge +2507 -> 3230
    //   726: aload_0
    //   727: aload_1
    //   728: aload_0
    //   729: getfield 81	com/google/android/gms/internal/measurement/zzvz:zzcbb	[I
    //   732: iload 50
    //   734: iaload
    //   735: aload 10
    //   737: aload 4
    //   739: invokespecial 642	com/google/android/gms/internal/measurement/zzvz:zza	(Ljava/lang/Object;ILjava/lang/Object;Lcom/google/android/gms/internal/measurement/zzxd;)Ljava/lang/Object;
    //   742: astore 10
    //   744: iinc 50 1
    //   747: goto -30 -> 717
    //   750: iload 14
    //   752: ldc_w 265
    //   755: iand
    //   756: i2l
    //   757: lstore 46
    //   759: aload_1
    //   760: lload 46
    //   762: aload_2
    //   763: invokeinterface 666 1 0
    //   768: invokestatic 669	com/google/android/gms/internal/measurement/zzxj:zza	(Ljava/lang/Object;JD)V
    //   771: aload_0
    //   772: aload_1
    //   773: iload 13
    //   775: invokespecial 384	com/google/android/gms/internal/measurement/zzvz:zzc	(Ljava/lang/Object;I)V
    //   778: goto -748 -> 30
    //   781: astore 15
    //   783: aload 4
    //   785: aload_2
    //   786: invokevirtual 657	com/google/android/gms/internal/measurement/zzxd:zza	(Lcom/google/android/gms/internal/measurement/zzwk;)Z
    //   789: pop
    //   790: aload 6
    //   792: ifnonnull +2514 -> 3306
    //   795: aload 4
    //   797: aload_1
    //   798: invokevirtual 660	com/google/android/gms/internal/measurement/zzxd:zzam	(Ljava/lang/Object;)Ljava/lang/Object;
    //   801: astore 17
    //   803: aload 17
    //   805: astore 10
    //   807: aload 4
    //   809: aload 10
    //   811: aload_2
    //   812: invokevirtual 663	com/google/android/gms/internal/measurement/zzxd:zza	(Ljava/lang/Object;Lcom/google/android/gms/internal/measurement/zzwk;)Z
    //   815: istore 19
    //   817: iload 19
    //   819: ifne +2446 -> 3265
    //   822: aload_0
    //   823: getfield 83	com/google/android/gms/internal/measurement/zzvz:zzcbc	I
    //   826: istore 20
    //   828: iload 20
    //   830: aload_0
    //   831: getfield 85	com/google/android/gms/internal/measurement/zzvz:zzcbd	I
    //   834: if_icmpge +2417 -> 3251
    //   837: aload_0
    //   838: aload_1
    //   839: aload_0
    //   840: getfield 81	com/google/android/gms/internal/measurement/zzvz:zzcbb	[I
    //   843: iload 20
    //   845: iaload
    //   846: aload 10
    //   848: aload 4
    //   850: invokespecial 642	com/google/android/gms/internal/measurement/zzvz:zza	(Ljava/lang/Object;ILjava/lang/Object;Lcom/google/android/gms/internal/measurement/zzxd;)Ljava/lang/Object;
    //   853: astore 10
    //   855: iinc 20 1
    //   858: goto -30 -> 828
    //   861: iload 14
    //   863: ldc_w 265
    //   866: iand
    //   867: i2l
    //   868: lstore 44
    //   870: aload_1
    //   871: lload 44
    //   873: aload_2
    //   874: invokeinterface 672 1 0
    //   879: invokestatic 675	com/google/android/gms/internal/measurement/zzxj:zza	(Ljava/lang/Object;JF)V
    //   882: aload_0
    //   883: aload_1
    //   884: iload 13
    //   886: invokespecial 384	com/google/android/gms/internal/measurement/zzvz:zzc	(Ljava/lang/Object;I)V
    //   889: goto -859 -> 30
    //   892: astore 8
    //   894: aload 8
    //   896: astore 9
    //   898: aload 6
    //   900: astore 10
    //   902: aload_0
    //   903: getfield 83	com/google/android/gms/internal/measurement/zzvz:zzcbc	I
    //   906: istore 11
    //   908: iload 11
    //   910: aload_0
    //   911: getfield 85	com/google/android/gms/internal/measurement/zzvz:zzcbd	I
    //   914: if_icmpge +2358 -> 3272
    //   917: aload_0
    //   918: aload_1
    //   919: aload_0
    //   920: getfield 81	com/google/android/gms/internal/measurement/zzvz:zzcbb	[I
    //   923: iload 11
    //   925: iaload
    //   926: aload 10
    //   928: aload 4
    //   930: invokespecial 642	com/google/android/gms/internal/measurement/zzvz:zza	(Ljava/lang/Object;ILjava/lang/Object;Lcom/google/android/gms/internal/measurement/zzxd;)Ljava/lang/Object;
    //   933: astore 10
    //   935: iinc 11 1
    //   938: goto -30 -> 908
    //   941: iload 14
    //   943: ldc_w 265
    //   946: iand
    //   947: i2l
    //   948: lstore 42
    //   950: aload_1
    //   951: lload 42
    //   953: aload_2
    //   954: invokeinterface 678 1 0
    //   959: invokestatic 681	com/google/android/gms/internal/measurement/zzxj:zza	(Ljava/lang/Object;JJ)V
    //   962: aload_0
    //   963: aload_1
    //   964: iload 13
    //   966: invokespecial 384	com/google/android/gms/internal/measurement/zzvz:zzc	(Ljava/lang/Object;I)V
    //   969: goto -939 -> 30
    //   972: aload_1
    //   973: iload 14
    //   975: ldc_w 265
    //   978: iand
    //   979: i2l
    //   980: aload_2
    //   981: invokeinterface 684 1 0
    //   986: invokestatic 681	com/google/android/gms/internal/measurement/zzxj:zza	(Ljava/lang/Object;JJ)V
    //   989: aload_0
    //   990: aload_1
    //   991: iload 13
    //   993: invokespecial 384	com/google/android/gms/internal/measurement/zzvz:zzc	(Ljava/lang/Object;I)V
    //   996: goto -966 -> 30
    //   999: aload_1
    //   1000: iload 14
    //   1002: ldc_w 265
    //   1005: iand
    //   1006: i2l
    //   1007: aload_2
    //   1008: invokeinterface 687 1 0
    //   1013: invokestatic 401	com/google/android/gms/internal/measurement/zzxj:zzb	(Ljava/lang/Object;JI)V
    //   1016: aload_0
    //   1017: aload_1
    //   1018: iload 13
    //   1020: invokespecial 384	com/google/android/gms/internal/measurement/zzvz:zzc	(Ljava/lang/Object;I)V
    //   1023: goto -993 -> 30
    //   1026: aload_1
    //   1027: iload 14
    //   1029: ldc_w 265
    //   1032: iand
    //   1033: i2l
    //   1034: aload_2
    //   1035: invokeinterface 690 1 0
    //   1040: invokestatic 681	com/google/android/gms/internal/measurement/zzxj:zza	(Ljava/lang/Object;JJ)V
    //   1043: aload_0
    //   1044: aload_1
    //   1045: iload 13
    //   1047: invokespecial 384	com/google/android/gms/internal/measurement/zzvz:zzc	(Ljava/lang/Object;I)V
    //   1050: goto -1020 -> 30
    //   1053: aload_1
    //   1054: iload 14
    //   1056: ldc_w 265
    //   1059: iand
    //   1060: i2l
    //   1061: aload_2
    //   1062: invokeinterface 693 1 0
    //   1067: invokestatic 401	com/google/android/gms/internal/measurement/zzxj:zzb	(Ljava/lang/Object;JI)V
    //   1070: aload_0
    //   1071: aload_1
    //   1072: iload 13
    //   1074: invokespecial 384	com/google/android/gms/internal/measurement/zzvz:zzc	(Ljava/lang/Object;I)V
    //   1077: goto -1047 -> 30
    //   1080: aload_1
    //   1081: iload 14
    //   1083: ldc_w 265
    //   1086: iand
    //   1087: i2l
    //   1088: aload_2
    //   1089: invokeinterface 696 1 0
    //   1094: invokestatic 699	com/google/android/gms/internal/measurement/zzxj:zza	(Ljava/lang/Object;JZ)V
    //   1097: aload_0
    //   1098: aload_1
    //   1099: iload 13
    //   1101: invokespecial 384	com/google/android/gms/internal/measurement/zzvz:zzc	(Ljava/lang/Object;I)V
    //   1104: goto -1074 -> 30
    //   1107: aload_0
    //   1108: aload_1
    //   1109: iload 14
    //   1111: aload_2
    //   1112: invokespecial 701	com/google/android/gms/internal/measurement/zzvz:zza	(Ljava/lang/Object;ILcom/google/android/gms/internal/measurement/zzwk;)V
    //   1115: aload_0
    //   1116: aload_1
    //   1117: iload 13
    //   1119: invokespecial 384	com/google/android/gms/internal/measurement/zzvz:zzc	(Ljava/lang/Object;I)V
    //   1122: goto -1092 -> 30
    //   1125: aload_0
    //   1126: aload_1
    //   1127: iload 13
    //   1129: invokespecial 375	com/google/android/gms/internal/measurement/zzvz:zzb	(Ljava/lang/Object;I)Z
    //   1132: ifeq +48 -> 1180
    //   1135: aload_1
    //   1136: ldc_w 265
    //   1139: iload 14
    //   1141: iand
    //   1142: i2l
    //   1143: invokestatic 273	com/google/android/gms/internal/measurement/zzxj:zzp	(Ljava/lang/Object;J)Ljava/lang/Object;
    //   1146: aload_2
    //   1147: aload_0
    //   1148: iload 13
    //   1150: invokespecial 470	com/google/android/gms/internal/measurement/zzvz:zzbq	(I)Lcom/google/android/gms/internal/measurement/zzwl;
    //   1153: aload_3
    //   1154: invokeinterface 704 3 0
    //   1159: invokestatic 380	com/google/android/gms/internal/measurement/zzuq:zzb	(Ljava/lang/Object;Ljava/lang/Object;)Ljava/lang/Object;
    //   1162: astore 41
    //   1164: aload_1
    //   1165: iload 14
    //   1167: ldc_w 265
    //   1170: iand
    //   1171: i2l
    //   1172: aload 41
    //   1174: invokestatic 365	com/google/android/gms/internal/measurement/zzxj:zza	(Ljava/lang/Object;JLjava/lang/Object;)V
    //   1177: goto -1147 -> 30
    //   1180: aload_1
    //   1181: iload 14
    //   1183: ldc_w 265
    //   1186: iand
    //   1187: i2l
    //   1188: aload_2
    //   1189: aload_0
    //   1190: iload 13
    //   1192: invokespecial 470	com/google/android/gms/internal/measurement/zzvz:zzbq	(I)Lcom/google/android/gms/internal/measurement/zzwl;
    //   1195: aload_3
    //   1196: invokeinterface 704 3 0
    //   1201: invokestatic 365	com/google/android/gms/internal/measurement/zzxj:zza	(Ljava/lang/Object;JLjava/lang/Object;)V
    //   1204: aload_0
    //   1205: aload_1
    //   1206: iload 13
    //   1208: invokespecial 384	com/google/android/gms/internal/measurement/zzvz:zzc	(Ljava/lang/Object;I)V
    //   1211: goto -1181 -> 30
    //   1214: aload_1
    //   1215: iload 14
    //   1217: ldc_w 265
    //   1220: iand
    //   1221: i2l
    //   1222: aload_2
    //   1223: invokeinterface 371 1 0
    //   1228: invokestatic 365	com/google/android/gms/internal/measurement/zzxj:zza	(Ljava/lang/Object;JLjava/lang/Object;)V
    //   1231: aload_0
    //   1232: aload_1
    //   1233: iload 13
    //   1235: invokespecial 384	com/google/android/gms/internal/measurement/zzvz:zzc	(Ljava/lang/Object;I)V
    //   1238: goto -1208 -> 30
    //   1241: aload_1
    //   1242: iload 14
    //   1244: ldc_w 265
    //   1247: iand
    //   1248: i2l
    //   1249: aload_2
    //   1250: invokeinterface 707 1 0
    //   1255: invokestatic 401	com/google/android/gms/internal/measurement/zzxj:zzb	(Ljava/lang/Object;JI)V
    //   1258: aload_0
    //   1259: aload_1
    //   1260: iload 13
    //   1262: invokespecial 384	com/google/android/gms/internal/measurement/zzvz:zzc	(Ljava/lang/Object;I)V
    //   1265: goto -1235 -> 30
    //   1268: aload_2
    //   1269: invokeinterface 710 1 0
    //   1274: istore 39
    //   1276: aload_0
    //   1277: iload 13
    //   1279: invokespecial 277	com/google/android/gms/internal/measurement/zzvz:zzbs	(I)Lcom/google/android/gms/internal/measurement/zzut;
    //   1282: astore 40
    //   1284: aload 40
    //   1286: ifnull +15 -> 1301
    //   1289: aload 40
    //   1291: iload 39
    //   1293: invokeinterface 222 2 0
    //   1298: ifeq +26 -> 1324
    //   1301: aload_1
    //   1302: iload 14
    //   1304: ldc_w 265
    //   1307: iand
    //   1308: i2l
    //   1309: iload 39
    //   1311: invokestatic 401	com/google/android/gms/internal/measurement/zzxj:zzb	(Ljava/lang/Object;JI)V
    //   1314: aload_0
    //   1315: aload_1
    //   1316: iload 13
    //   1318: invokespecial 384	com/google/android/gms/internal/measurement/zzvz:zzc	(Ljava/lang/Object;I)V
    //   1321: goto -1291 -> 30
    //   1324: iload 12
    //   1326: iload 39
    //   1328: aload 6
    //   1330: aload 4
    //   1332: invokestatic 713	com/google/android/gms/internal/measurement/zzwn:zza	(IILjava/lang/Object;Lcom/google/android/gms/internal/measurement/zzxd;)Ljava/lang/Object;
    //   1335: astore 6
    //   1337: goto -1307 -> 30
    //   1340: aload_1
    //   1341: iload 14
    //   1343: ldc_w 265
    //   1346: iand
    //   1347: i2l
    //   1348: aload_2
    //   1349: invokeinterface 716 1 0
    //   1354: invokestatic 401	com/google/android/gms/internal/measurement/zzxj:zzb	(Ljava/lang/Object;JI)V
    //   1357: aload_0
    //   1358: aload_1
    //   1359: iload 13
    //   1361: invokespecial 384	com/google/android/gms/internal/measurement/zzvz:zzc	(Ljava/lang/Object;I)V
    //   1364: goto -1334 -> 30
    //   1367: aload_1
    //   1368: iload 14
    //   1370: ldc_w 265
    //   1373: iand
    //   1374: i2l
    //   1375: aload_2
    //   1376: invokeinterface 719 1 0
    //   1381: invokestatic 681	com/google/android/gms/internal/measurement/zzxj:zza	(Ljava/lang/Object;JJ)V
    //   1384: aload_0
    //   1385: aload_1
    //   1386: iload 13
    //   1388: invokespecial 384	com/google/android/gms/internal/measurement/zzvz:zzc	(Ljava/lang/Object;I)V
    //   1391: goto -1361 -> 30
    //   1394: aload_1
    //   1395: iload 14
    //   1397: ldc_w 265
    //   1400: iand
    //   1401: i2l
    //   1402: aload_2
    //   1403: invokeinterface 722 1 0
    //   1408: invokestatic 401	com/google/android/gms/internal/measurement/zzxj:zzb	(Ljava/lang/Object;JI)V
    //   1411: aload_0
    //   1412: aload_1
    //   1413: iload 13
    //   1415: invokespecial 384	com/google/android/gms/internal/measurement/zzvz:zzc	(Ljava/lang/Object;I)V
    //   1418: goto -1388 -> 30
    //   1421: aload_1
    //   1422: iload 14
    //   1424: ldc_w 265
    //   1427: iand
    //   1428: i2l
    //   1429: aload_2
    //   1430: invokeinterface 725 1 0
    //   1435: invokestatic 681	com/google/android/gms/internal/measurement/zzxj:zza	(Ljava/lang/Object;JJ)V
    //   1438: aload_0
    //   1439: aload_1
    //   1440: iload 13
    //   1442: invokespecial 384	com/google/android/gms/internal/measurement/zzvz:zzc	(Ljava/lang/Object;I)V
    //   1445: goto -1415 -> 30
    //   1448: aload_0
    //   1449: aload_1
    //   1450: iload 13
    //   1452: invokespecial 375	com/google/android/gms/internal/measurement/zzvz:zzb	(Ljava/lang/Object;I)Z
    //   1455: ifeq +48 -> 1503
    //   1458: aload_1
    //   1459: ldc_w 265
    //   1462: iload 14
    //   1464: iand
    //   1465: i2l
    //   1466: invokestatic 273	com/google/android/gms/internal/measurement/zzxj:zzp	(Ljava/lang/Object;J)Ljava/lang/Object;
    //   1469: aload_2
    //   1470: aload_0
    //   1471: iload 13
    //   1473: invokespecial 470	com/google/android/gms/internal/measurement/zzvz:zzbq	(I)Lcom/google/android/gms/internal/measurement/zzwl;
    //   1476: aload_3
    //   1477: invokeinterface 727 3 0
    //   1482: invokestatic 380	com/google/android/gms/internal/measurement/zzuq:zzb	(Ljava/lang/Object;Ljava/lang/Object;)Ljava/lang/Object;
    //   1485: astore 38
    //   1487: aload_1
    //   1488: iload 14
    //   1490: ldc_w 265
    //   1493: iand
    //   1494: i2l
    //   1495: aload 38
    //   1497: invokestatic 365	com/google/android/gms/internal/measurement/zzxj:zza	(Ljava/lang/Object;JLjava/lang/Object;)V
    //   1500: goto -1470 -> 30
    //   1503: aload_1
    //   1504: iload 14
    //   1506: ldc_w 265
    //   1509: iand
    //   1510: i2l
    //   1511: aload_2
    //   1512: aload_0
    //   1513: iload 13
    //   1515: invokespecial 470	com/google/android/gms/internal/measurement/zzvz:zzbq	(I)Lcom/google/android/gms/internal/measurement/zzwl;
    //   1518: aload_3
    //   1519: invokeinterface 727 3 0
    //   1524: invokestatic 365	com/google/android/gms/internal/measurement/zzxj:zza	(Ljava/lang/Object;JLjava/lang/Object;)V
    //   1527: aload_0
    //   1528: aload_1
    //   1529: iload 13
    //   1531: invokespecial 384	com/google/android/gms/internal/measurement/zzvz:zzc	(Ljava/lang/Object;I)V
    //   1534: goto -1504 -> 30
    //   1537: aload_2
    //   1538: aload_0
    //   1539: getfield 89	com/google/android/gms/internal/measurement/zzvz:zzcbf	Lcom/google/android/gms/internal/measurement/zzvf;
    //   1542: aload_1
    //   1543: iload 14
    //   1545: ldc_w 265
    //   1548: iand
    //   1549: i2l
    //   1550: invokevirtual 731	com/google/android/gms/internal/measurement/zzvf:zza	(Ljava/lang/Object;J)Ljava/util/List;
    //   1553: invokeinterface 734 2 0
    //   1558: goto -1528 -> 30
    //   1561: aload_2
    //   1562: aload_0
    //   1563: getfield 89	com/google/android/gms/internal/measurement/zzvz:zzcbf	Lcom/google/android/gms/internal/measurement/zzvf;
    //   1566: aload_1
    //   1567: iload 14
    //   1569: ldc_w 265
    //   1572: iand
    //   1573: i2l
    //   1574: invokevirtual 731	com/google/android/gms/internal/measurement/zzvf:zza	(Ljava/lang/Object;J)Ljava/util/List;
    //   1577: invokeinterface 736 2 0
    //   1582: goto -1552 -> 30
    //   1585: aload_2
    //   1586: aload_0
    //   1587: getfield 89	com/google/android/gms/internal/measurement/zzvz:zzcbf	Lcom/google/android/gms/internal/measurement/zzvf;
    //   1590: aload_1
    //   1591: iload 14
    //   1593: ldc_w 265
    //   1596: iand
    //   1597: i2l
    //   1598: invokevirtual 731	com/google/android/gms/internal/measurement/zzvf:zza	(Ljava/lang/Object;J)Ljava/util/List;
    //   1601: invokeinterface 738 2 0
    //   1606: goto -1576 -> 30
    //   1609: aload_2
    //   1610: aload_0
    //   1611: getfield 89	com/google/android/gms/internal/measurement/zzvz:zzcbf	Lcom/google/android/gms/internal/measurement/zzvf;
    //   1614: aload_1
    //   1615: iload 14
    //   1617: ldc_w 265
    //   1620: iand
    //   1621: i2l
    //   1622: invokevirtual 731	com/google/android/gms/internal/measurement/zzvf:zza	(Ljava/lang/Object;J)Ljava/util/List;
    //   1625: invokeinterface 740 2 0
    //   1630: goto -1600 -> 30
    //   1633: aload_2
    //   1634: aload_0
    //   1635: getfield 89	com/google/android/gms/internal/measurement/zzvz:zzcbf	Lcom/google/android/gms/internal/measurement/zzvf;
    //   1638: aload_1
    //   1639: iload 14
    //   1641: ldc_w 265
    //   1644: iand
    //   1645: i2l
    //   1646: invokevirtual 731	com/google/android/gms/internal/measurement/zzvf:zza	(Ljava/lang/Object;J)Ljava/util/List;
    //   1649: invokeinterface 742 2 0
    //   1654: goto -1624 -> 30
    //   1657: aload_2
    //   1658: aload_0
    //   1659: getfield 89	com/google/android/gms/internal/measurement/zzvz:zzcbf	Lcom/google/android/gms/internal/measurement/zzvf;
    //   1662: aload_1
    //   1663: iload 14
    //   1665: ldc_w 265
    //   1668: iand
    //   1669: i2l
    //   1670: invokevirtual 731	com/google/android/gms/internal/measurement/zzvf:zza	(Ljava/lang/Object;J)Ljava/util/List;
    //   1673: invokeinterface 744 2 0
    //   1678: goto -1648 -> 30
    //   1681: aload_2
    //   1682: aload_0
    //   1683: getfield 89	com/google/android/gms/internal/measurement/zzvz:zzcbf	Lcom/google/android/gms/internal/measurement/zzvf;
    //   1686: aload_1
    //   1687: iload 14
    //   1689: ldc_w 265
    //   1692: iand
    //   1693: i2l
    //   1694: invokevirtual 731	com/google/android/gms/internal/measurement/zzvf:zza	(Ljava/lang/Object;J)Ljava/util/List;
    //   1697: invokeinterface 746 2 0
    //   1702: goto -1672 -> 30
    //   1705: aload_2
    //   1706: aload_0
    //   1707: getfield 89	com/google/android/gms/internal/measurement/zzvz:zzcbf	Lcom/google/android/gms/internal/measurement/zzvf;
    //   1710: aload_1
    //   1711: iload 14
    //   1713: ldc_w 265
    //   1716: iand
    //   1717: i2l
    //   1718: invokevirtual 731	com/google/android/gms/internal/measurement/zzvf:zza	(Ljava/lang/Object;J)Ljava/util/List;
    //   1721: invokeinterface 748 2 0
    //   1726: goto -1696 -> 30
    //   1729: iload 14
    //   1731: invokestatic 357	com/google/android/gms/internal/measurement/zzvz:zzbv	(I)Z
    //   1734: ifeq +27 -> 1761
    //   1737: aload_2
    //   1738: aload_0
    //   1739: getfield 89	com/google/android/gms/internal/measurement/zzvz:zzcbf	Lcom/google/android/gms/internal/measurement/zzvf;
    //   1742: aload_1
    //   1743: iload 14
    //   1745: ldc_w 265
    //   1748: iand
    //   1749: i2l
    //   1750: invokevirtual 731	com/google/android/gms/internal/measurement/zzvf:zza	(Ljava/lang/Object;J)Ljava/util/List;
    //   1753: invokeinterface 751 2 0
    //   1758: goto -1728 -> 30
    //   1761: aload_2
    //   1762: aload_0
    //   1763: getfield 89	com/google/android/gms/internal/measurement/zzvz:zzcbf	Lcom/google/android/gms/internal/measurement/zzvf;
    //   1766: aload_1
    //   1767: iload 14
    //   1769: ldc_w 265
    //   1772: iand
    //   1773: i2l
    //   1774: invokevirtual 731	com/google/android/gms/internal/measurement/zzvf:zza	(Ljava/lang/Object;J)Ljava/util/List;
    //   1777: invokeinterface 754 2 0
    //   1782: goto -1752 -> 30
    //   1785: aload_0
    //   1786: iload 13
    //   1788: invokespecial 470	com/google/android/gms/internal/measurement/zzvz:zzbq	(I)Lcom/google/android/gms/internal/measurement/zzwl;
    //   1791: astore 35
    //   1793: iload 14
    //   1795: ldc_w 265
    //   1798: iand
    //   1799: i2l
    //   1800: lstore 36
    //   1802: aload_2
    //   1803: aload_0
    //   1804: getfield 89	com/google/android/gms/internal/measurement/zzvz:zzcbf	Lcom/google/android/gms/internal/measurement/zzvf;
    //   1807: aload_1
    //   1808: lload 36
    //   1810: invokevirtual 731	com/google/android/gms/internal/measurement/zzvf:zza	(Ljava/lang/Object;J)Ljava/util/List;
    //   1813: aload 35
    //   1815: aload_3
    //   1816: invokeinterface 757 4 0
    //   1821: goto -1791 -> 30
    //   1824: aload_2
    //   1825: aload_0
    //   1826: getfield 89	com/google/android/gms/internal/measurement/zzvz:zzcbf	Lcom/google/android/gms/internal/measurement/zzvf;
    //   1829: aload_1
    //   1830: iload 14
    //   1832: ldc_w 265
    //   1835: iand
    //   1836: i2l
    //   1837: invokevirtual 731	com/google/android/gms/internal/measurement/zzvf:zza	(Ljava/lang/Object;J)Ljava/util/List;
    //   1840: invokeinterface 760 2 0
    //   1845: goto -1815 -> 30
    //   1848: aload_2
    //   1849: aload_0
    //   1850: getfield 89	com/google/android/gms/internal/measurement/zzvz:zzcbf	Lcom/google/android/gms/internal/measurement/zzvf;
    //   1853: aload_1
    //   1854: iload 14
    //   1856: ldc_w 265
    //   1859: iand
    //   1860: i2l
    //   1861: invokevirtual 731	com/google/android/gms/internal/measurement/zzvf:zza	(Ljava/lang/Object;J)Ljava/util/List;
    //   1864: invokeinterface 763 2 0
    //   1869: goto -1839 -> 30
    //   1872: aload_0
    //   1873: getfield 89	com/google/android/gms/internal/measurement/zzvz:zzcbf	Lcom/google/android/gms/internal/measurement/zzvf;
    //   1876: aload_1
    //   1877: iload 14
    //   1879: ldc_w 265
    //   1882: iand
    //   1883: i2l
    //   1884: invokevirtual 731	com/google/android/gms/internal/measurement/zzvf:zza	(Ljava/lang/Object;J)Ljava/util/List;
    //   1887: astore 34
    //   1889: aload_2
    //   1890: aload 34
    //   1892: invokeinterface 766 2 0
    //   1897: iload 12
    //   1899: aload 34
    //   1901: aload_0
    //   1902: iload 13
    //   1904: invokespecial 277	com/google/android/gms/internal/measurement/zzvz:zzbs	(I)Lcom/google/android/gms/internal/measurement/zzut;
    //   1907: aload 6
    //   1909: aload 4
    //   1911: invokestatic 769	com/google/android/gms/internal/measurement/zzwn:zza	(ILjava/util/List;Lcom/google/android/gms/internal/measurement/zzut;Ljava/lang/Object;Lcom/google/android/gms/internal/measurement/zzxd;)Ljava/lang/Object;
    //   1914: astore 6
    //   1916: goto -1886 -> 30
    //   1919: aload_2
    //   1920: aload_0
    //   1921: getfield 89	com/google/android/gms/internal/measurement/zzvz:zzcbf	Lcom/google/android/gms/internal/measurement/zzvf;
    //   1924: aload_1
    //   1925: iload 14
    //   1927: ldc_w 265
    //   1930: iand
    //   1931: i2l
    //   1932: invokevirtual 731	com/google/android/gms/internal/measurement/zzvf:zza	(Ljava/lang/Object;J)Ljava/util/List;
    //   1935: invokeinterface 771 2 0
    //   1940: goto -1910 -> 30
    //   1943: aload_2
    //   1944: aload_0
    //   1945: getfield 89	com/google/android/gms/internal/measurement/zzvz:zzcbf	Lcom/google/android/gms/internal/measurement/zzvf;
    //   1948: aload_1
    //   1949: iload 14
    //   1951: ldc_w 265
    //   1954: iand
    //   1955: i2l
    //   1956: invokevirtual 731	com/google/android/gms/internal/measurement/zzvf:zza	(Ljava/lang/Object;J)Ljava/util/List;
    //   1959: invokeinterface 774 2 0
    //   1964: goto -1934 -> 30
    //   1967: aload_2
    //   1968: aload_0
    //   1969: getfield 89	com/google/android/gms/internal/measurement/zzvz:zzcbf	Lcom/google/android/gms/internal/measurement/zzvf;
    //   1972: aload_1
    //   1973: iload 14
    //   1975: ldc_w 265
    //   1978: iand
    //   1979: i2l
    //   1980: invokevirtual 731	com/google/android/gms/internal/measurement/zzvf:zza	(Ljava/lang/Object;J)Ljava/util/List;
    //   1983: invokeinterface 776 2 0
    //   1988: goto -1958 -> 30
    //   1991: aload_2
    //   1992: aload_0
    //   1993: getfield 89	com/google/android/gms/internal/measurement/zzvz:zzcbf	Lcom/google/android/gms/internal/measurement/zzvf;
    //   1996: aload_1
    //   1997: iload 14
    //   1999: ldc_w 265
    //   2002: iand
    //   2003: i2l
    //   2004: invokevirtual 731	com/google/android/gms/internal/measurement/zzvf:zza	(Ljava/lang/Object;J)Ljava/util/List;
    //   2007: invokeinterface 778 2 0
    //   2012: goto -1982 -> 30
    //   2015: aload_2
    //   2016: aload_0
    //   2017: getfield 89	com/google/android/gms/internal/measurement/zzvz:zzcbf	Lcom/google/android/gms/internal/measurement/zzvf;
    //   2020: aload_1
    //   2021: iload 14
    //   2023: ldc_w 265
    //   2026: iand
    //   2027: i2l
    //   2028: invokevirtual 731	com/google/android/gms/internal/measurement/zzvf:zza	(Ljava/lang/Object;J)Ljava/util/List;
    //   2031: invokeinterface 734 2 0
    //   2036: goto -2006 -> 30
    //   2039: aload_2
    //   2040: aload_0
    //   2041: getfield 89	com/google/android/gms/internal/measurement/zzvz:zzcbf	Lcom/google/android/gms/internal/measurement/zzvf;
    //   2044: aload_1
    //   2045: iload 14
    //   2047: ldc_w 265
    //   2050: iand
    //   2051: i2l
    //   2052: invokevirtual 731	com/google/android/gms/internal/measurement/zzvf:zza	(Ljava/lang/Object;J)Ljava/util/List;
    //   2055: invokeinterface 736 2 0
    //   2060: goto -2030 -> 30
    //   2063: aload_2
    //   2064: aload_0
    //   2065: getfield 89	com/google/android/gms/internal/measurement/zzvz:zzcbf	Lcom/google/android/gms/internal/measurement/zzvf;
    //   2068: aload_1
    //   2069: iload 14
    //   2071: ldc_w 265
    //   2074: iand
    //   2075: i2l
    //   2076: invokevirtual 731	com/google/android/gms/internal/measurement/zzvf:zza	(Ljava/lang/Object;J)Ljava/util/List;
    //   2079: invokeinterface 738 2 0
    //   2084: goto -2054 -> 30
    //   2087: aload_2
    //   2088: aload_0
    //   2089: getfield 89	com/google/android/gms/internal/measurement/zzvz:zzcbf	Lcom/google/android/gms/internal/measurement/zzvf;
    //   2092: aload_1
    //   2093: iload 14
    //   2095: ldc_w 265
    //   2098: iand
    //   2099: i2l
    //   2100: invokevirtual 731	com/google/android/gms/internal/measurement/zzvf:zza	(Ljava/lang/Object;J)Ljava/util/List;
    //   2103: invokeinterface 740 2 0
    //   2108: goto -2078 -> 30
    //   2111: aload_2
    //   2112: aload_0
    //   2113: getfield 89	com/google/android/gms/internal/measurement/zzvz:zzcbf	Lcom/google/android/gms/internal/measurement/zzvf;
    //   2116: aload_1
    //   2117: iload 14
    //   2119: ldc_w 265
    //   2122: iand
    //   2123: i2l
    //   2124: invokevirtual 731	com/google/android/gms/internal/measurement/zzvf:zza	(Ljava/lang/Object;J)Ljava/util/List;
    //   2127: invokeinterface 742 2 0
    //   2132: goto -2102 -> 30
    //   2135: aload_2
    //   2136: aload_0
    //   2137: getfield 89	com/google/android/gms/internal/measurement/zzvz:zzcbf	Lcom/google/android/gms/internal/measurement/zzvf;
    //   2140: aload_1
    //   2141: iload 14
    //   2143: ldc_w 265
    //   2146: iand
    //   2147: i2l
    //   2148: invokevirtual 731	com/google/android/gms/internal/measurement/zzvf:zza	(Ljava/lang/Object;J)Ljava/util/List;
    //   2151: invokeinterface 744 2 0
    //   2156: goto -2126 -> 30
    //   2159: aload_2
    //   2160: aload_0
    //   2161: getfield 89	com/google/android/gms/internal/measurement/zzvz:zzcbf	Lcom/google/android/gms/internal/measurement/zzvf;
    //   2164: aload_1
    //   2165: iload 14
    //   2167: ldc_w 265
    //   2170: iand
    //   2171: i2l
    //   2172: invokevirtual 731	com/google/android/gms/internal/measurement/zzvf:zza	(Ljava/lang/Object;J)Ljava/util/List;
    //   2175: invokeinterface 746 2 0
    //   2180: goto -2150 -> 30
    //   2183: aload_2
    //   2184: aload_0
    //   2185: getfield 89	com/google/android/gms/internal/measurement/zzvz:zzcbf	Lcom/google/android/gms/internal/measurement/zzvf;
    //   2188: aload_1
    //   2189: iload 14
    //   2191: ldc_w 265
    //   2194: iand
    //   2195: i2l
    //   2196: invokevirtual 731	com/google/android/gms/internal/measurement/zzvf:zza	(Ljava/lang/Object;J)Ljava/util/List;
    //   2199: invokeinterface 748 2 0
    //   2204: goto -2174 -> 30
    //   2207: aload_2
    //   2208: aload_0
    //   2209: getfield 89	com/google/android/gms/internal/measurement/zzvz:zzcbf	Lcom/google/android/gms/internal/measurement/zzvf;
    //   2212: aload_1
    //   2213: iload 14
    //   2215: ldc_w 265
    //   2218: iand
    //   2219: i2l
    //   2220: invokevirtual 731	com/google/android/gms/internal/measurement/zzvf:zza	(Ljava/lang/Object;J)Ljava/util/List;
    //   2223: invokeinterface 763 2 0
    //   2228: goto -2198 -> 30
    //   2231: aload_0
    //   2232: getfield 89	com/google/android/gms/internal/measurement/zzvz:zzcbf	Lcom/google/android/gms/internal/measurement/zzvf;
    //   2235: aload_1
    //   2236: iload 14
    //   2238: ldc_w 265
    //   2241: iand
    //   2242: i2l
    //   2243: invokevirtual 731	com/google/android/gms/internal/measurement/zzvf:zza	(Ljava/lang/Object;J)Ljava/util/List;
    //   2246: astore 33
    //   2248: aload_2
    //   2249: aload 33
    //   2251: invokeinterface 766 2 0
    //   2256: iload 12
    //   2258: aload 33
    //   2260: aload_0
    //   2261: iload 13
    //   2263: invokespecial 277	com/google/android/gms/internal/measurement/zzvz:zzbs	(I)Lcom/google/android/gms/internal/measurement/zzut;
    //   2266: aload 6
    //   2268: aload 4
    //   2270: invokestatic 769	com/google/android/gms/internal/measurement/zzwn:zza	(ILjava/util/List;Lcom/google/android/gms/internal/measurement/zzut;Ljava/lang/Object;Lcom/google/android/gms/internal/measurement/zzxd;)Ljava/lang/Object;
    //   2273: astore 6
    //   2275: goto -2245 -> 30
    //   2278: aload_2
    //   2279: aload_0
    //   2280: getfield 89	com/google/android/gms/internal/measurement/zzvz:zzcbf	Lcom/google/android/gms/internal/measurement/zzvf;
    //   2283: aload_1
    //   2284: iload 14
    //   2286: ldc_w 265
    //   2289: iand
    //   2290: i2l
    //   2291: invokevirtual 731	com/google/android/gms/internal/measurement/zzvf:zza	(Ljava/lang/Object;J)Ljava/util/List;
    //   2294: invokeinterface 771 2 0
    //   2299: goto -2269 -> 30
    //   2302: aload_2
    //   2303: aload_0
    //   2304: getfield 89	com/google/android/gms/internal/measurement/zzvz:zzcbf	Lcom/google/android/gms/internal/measurement/zzvf;
    //   2307: aload_1
    //   2308: iload 14
    //   2310: ldc_w 265
    //   2313: iand
    //   2314: i2l
    //   2315: invokevirtual 731	com/google/android/gms/internal/measurement/zzvf:zza	(Ljava/lang/Object;J)Ljava/util/List;
    //   2318: invokeinterface 774 2 0
    //   2323: goto -2293 -> 30
    //   2326: aload_2
    //   2327: aload_0
    //   2328: getfield 89	com/google/android/gms/internal/measurement/zzvz:zzcbf	Lcom/google/android/gms/internal/measurement/zzvf;
    //   2331: aload_1
    //   2332: iload 14
    //   2334: ldc_w 265
    //   2337: iand
    //   2338: i2l
    //   2339: invokevirtual 731	com/google/android/gms/internal/measurement/zzvf:zza	(Ljava/lang/Object;J)Ljava/util/List;
    //   2342: invokeinterface 776 2 0
    //   2347: goto -2317 -> 30
    //   2350: aload_2
    //   2351: aload_0
    //   2352: getfield 89	com/google/android/gms/internal/measurement/zzvz:zzcbf	Lcom/google/android/gms/internal/measurement/zzvf;
    //   2355: aload_1
    //   2356: iload 14
    //   2358: ldc_w 265
    //   2361: iand
    //   2362: i2l
    //   2363: invokevirtual 731	com/google/android/gms/internal/measurement/zzvf:zza	(Ljava/lang/Object;J)Ljava/util/List;
    //   2366: invokeinterface 778 2 0
    //   2371: goto -2341 -> 30
    //   2374: iload 14
    //   2376: ldc_w 265
    //   2379: iand
    //   2380: i2l
    //   2381: lstore 30
    //   2383: aload_0
    //   2384: iload 13
    //   2386: invokespecial 470	com/google/android/gms/internal/measurement/zzvz:zzbq	(I)Lcom/google/android/gms/internal/measurement/zzwl;
    //   2389: astore 32
    //   2391: aload_2
    //   2392: aload_0
    //   2393: getfield 89	com/google/android/gms/internal/measurement/zzvz:zzcbf	Lcom/google/android/gms/internal/measurement/zzvf;
    //   2396: aload_1
    //   2397: lload 30
    //   2399: invokevirtual 731	com/google/android/gms/internal/measurement/zzvf:zza	(Ljava/lang/Object;J)Ljava/util/List;
    //   2402: aload 32
    //   2404: aload_3
    //   2405: invokeinterface 780 4 0
    //   2410: goto -2380 -> 30
    //   2413: aload_0
    //   2414: iload 13
    //   2416: invokespecial 178	com/google/android/gms/internal/measurement/zzvz:zzbr	(I)Ljava/lang/Object;
    //   2419: astore 24
    //   2421: ldc_w 265
    //   2424: aload_0
    //   2425: iload 13
    //   2427: invokespecial 269	com/google/android/gms/internal/measurement/zzvz:zzbt	(I)I
    //   2430: iand
    //   2431: i2l
    //   2432: lstore 25
    //   2434: aload_1
    //   2435: lload 25
    //   2437: invokestatic 273	com/google/android/gms/internal/measurement/zzxj:zzp	(Ljava/lang/Object;J)Ljava/lang/Object;
    //   2440: astore 27
    //   2442: aload 27
    //   2444: ifnonnull +56 -> 2500
    //   2447: aload_0
    //   2448: getfield 97	com/google/android/gms/internal/measurement/zzvz:zzcbi	Lcom/google/android/gms/internal/measurement/zzvq;
    //   2451: aload 24
    //   2453: invokeinterface 783 2 0
    //   2458: astore 28
    //   2460: aload_1
    //   2461: lload 25
    //   2463: aload 28
    //   2465: invokestatic 365	com/google/android/gms/internal/measurement/zzxj:zza	(Ljava/lang/Object;JLjava/lang/Object;)V
    //   2468: aload_2
    //   2469: aload_0
    //   2470: getfield 97	com/google/android/gms/internal/measurement/zzvz:zzcbi	Lcom/google/android/gms/internal/measurement/zzvq;
    //   2473: aload 28
    //   2475: invokeinterface 281 2 0
    //   2480: aload_0
    //   2481: getfield 97	com/google/android/gms/internal/measurement/zzvz:zzcbi	Lcom/google/android/gms/internal/measurement/zzvq;
    //   2484: aload 24
    //   2486: invokeinterface 184 2 0
    //   2491: aload_3
    //   2492: invokeinterface 786 4 0
    //   2497: goto -2467 -> 30
    //   2500: aload_0
    //   2501: getfield 97	com/google/android/gms/internal/measurement/zzvz:zzcbi	Lcom/google/android/gms/internal/measurement/zzvq;
    //   2504: aload 27
    //   2506: invokeinterface 789 2 0
    //   2511: ifeq +809 -> 3320
    //   2514: aload_0
    //   2515: getfield 97	com/google/android/gms/internal/measurement/zzvz:zzcbi	Lcom/google/android/gms/internal/measurement/zzvq;
    //   2518: aload 24
    //   2520: invokeinterface 783 2 0
    //   2525: astore 28
    //   2527: aload_0
    //   2528: getfield 97	com/google/android/gms/internal/measurement/zzvz:zzcbi	Lcom/google/android/gms/internal/measurement/zzvq;
    //   2531: aload 28
    //   2533: aload 27
    //   2535: invokeinterface 791 3 0
    //   2540: pop
    //   2541: aload_1
    //   2542: lload 25
    //   2544: aload 28
    //   2546: invokestatic 365	com/google/android/gms/internal/measurement/zzxj:zza	(Ljava/lang/Object;JLjava/lang/Object;)V
    //   2549: goto -81 -> 2468
    //   2552: aload_1
    //   2553: iload 14
    //   2555: ldc_w 265
    //   2558: iand
    //   2559: i2l
    //   2560: aload_2
    //   2561: invokeinterface 666 1 0
    //   2566: invokestatic 794	java/lang/Double:valueOf	(D)Ljava/lang/Double;
    //   2569: invokestatic 365	com/google/android/gms/internal/measurement/zzxj:zza	(Ljava/lang/Object;JLjava/lang/Object;)V
    //   2572: aload_0
    //   2573: aload_1
    //   2574: iload 12
    //   2576: iload 13
    //   2578: invokespecial 552	com/google/android/gms/internal/measurement/zzvz:zzb	(Ljava/lang/Object;II)V
    //   2581: goto -2551 -> 30
    //   2584: aload_1
    //   2585: iload 14
    //   2587: ldc_w 265
    //   2590: iand
    //   2591: i2l
    //   2592: aload_2
    //   2593: invokeinterface 672 1 0
    //   2598: invokestatic 797	java/lang/Float:valueOf	(F)Ljava/lang/Float;
    //   2601: invokestatic 365	com/google/android/gms/internal/measurement/zzxj:zza	(Ljava/lang/Object;JLjava/lang/Object;)V
    //   2604: aload_0
    //   2605: aload_1
    //   2606: iload 12
    //   2608: iload 13
    //   2610: invokespecial 552	com/google/android/gms/internal/measurement/zzvz:zzb	(Ljava/lang/Object;II)V
    //   2613: goto -2583 -> 30
    //   2616: aload_1
    //   2617: iload 14
    //   2619: ldc_w 265
    //   2622: iand
    //   2623: i2l
    //   2624: aload_2
    //   2625: invokeinterface 678 1 0
    //   2630: invokestatic 800	java/lang/Long:valueOf	(J)Ljava/lang/Long;
    //   2633: invokestatic 365	com/google/android/gms/internal/measurement/zzxj:zza	(Ljava/lang/Object;JLjava/lang/Object;)V
    //   2636: aload_0
    //   2637: aload_1
    //   2638: iload 12
    //   2640: iload 13
    //   2642: invokespecial 552	com/google/android/gms/internal/measurement/zzvz:zzb	(Ljava/lang/Object;II)V
    //   2645: goto -2615 -> 30
    //   2648: aload_1
    //   2649: iload 14
    //   2651: ldc_w 265
    //   2654: iand
    //   2655: i2l
    //   2656: aload_2
    //   2657: invokeinterface 684 1 0
    //   2662: invokestatic 800	java/lang/Long:valueOf	(J)Ljava/lang/Long;
    //   2665: invokestatic 365	com/google/android/gms/internal/measurement/zzxj:zza	(Ljava/lang/Object;JLjava/lang/Object;)V
    //   2668: aload_0
    //   2669: aload_1
    //   2670: iload 12
    //   2672: iload 13
    //   2674: invokespecial 552	com/google/android/gms/internal/measurement/zzvz:zzb	(Ljava/lang/Object;II)V
    //   2677: goto -2647 -> 30
    //   2680: aload_1
    //   2681: iload 14
    //   2683: ldc_w 265
    //   2686: iand
    //   2687: i2l
    //   2688: aload_2
    //   2689: invokeinterface 687 1 0
    //   2694: invokestatic 803	java/lang/Integer:valueOf	(I)Ljava/lang/Integer;
    //   2697: invokestatic 365	com/google/android/gms/internal/measurement/zzxj:zza	(Ljava/lang/Object;JLjava/lang/Object;)V
    //   2700: aload_0
    //   2701: aload_1
    //   2702: iload 12
    //   2704: iload 13
    //   2706: invokespecial 552	com/google/android/gms/internal/measurement/zzvz:zzb	(Ljava/lang/Object;II)V
    //   2709: goto -2679 -> 30
    //   2712: aload_1
    //   2713: iload 14
    //   2715: ldc_w 265
    //   2718: iand
    //   2719: i2l
    //   2720: aload_2
    //   2721: invokeinterface 690 1 0
    //   2726: invokestatic 800	java/lang/Long:valueOf	(J)Ljava/lang/Long;
    //   2729: invokestatic 365	com/google/android/gms/internal/measurement/zzxj:zza	(Ljava/lang/Object;JLjava/lang/Object;)V
    //   2732: aload_0
    //   2733: aload_1
    //   2734: iload 12
    //   2736: iload 13
    //   2738: invokespecial 552	com/google/android/gms/internal/measurement/zzvz:zzb	(Ljava/lang/Object;II)V
    //   2741: goto -2711 -> 30
    //   2744: aload_1
    //   2745: iload 14
    //   2747: ldc_w 265
    //   2750: iand
    //   2751: i2l
    //   2752: aload_2
    //   2753: invokeinterface 693 1 0
    //   2758: invokestatic 803	java/lang/Integer:valueOf	(I)Ljava/lang/Integer;
    //   2761: invokestatic 365	com/google/android/gms/internal/measurement/zzxj:zza	(Ljava/lang/Object;JLjava/lang/Object;)V
    //   2764: aload_0
    //   2765: aload_1
    //   2766: iload 12
    //   2768: iload 13
    //   2770: invokespecial 552	com/google/android/gms/internal/measurement/zzvz:zzb	(Ljava/lang/Object;II)V
    //   2773: goto -2743 -> 30
    //   2776: aload_1
    //   2777: iload 14
    //   2779: ldc_w 265
    //   2782: iand
    //   2783: i2l
    //   2784: aload_2
    //   2785: invokeinterface 696 1 0
    //   2790: invokestatic 806	java/lang/Boolean:valueOf	(Z)Ljava/lang/Boolean;
    //   2793: invokestatic 365	com/google/android/gms/internal/measurement/zzxj:zza	(Ljava/lang/Object;JLjava/lang/Object;)V
    //   2796: aload_0
    //   2797: aload_1
    //   2798: iload 12
    //   2800: iload 13
    //   2802: invokespecial 552	com/google/android/gms/internal/measurement/zzvz:zzb	(Ljava/lang/Object;II)V
    //   2805: goto -2775 -> 30
    //   2808: aload_0
    //   2809: aload_1
    //   2810: iload 14
    //   2812: aload_2
    //   2813: invokespecial 701	com/google/android/gms/internal/measurement/zzvz:zza	(Ljava/lang/Object;ILcom/google/android/gms/internal/measurement/zzwk;)V
    //   2816: aload_0
    //   2817: aload_1
    //   2818: iload 12
    //   2820: iload 13
    //   2822: invokespecial 552	com/google/android/gms/internal/measurement/zzvz:zzb	(Ljava/lang/Object;II)V
    //   2825: goto -2795 -> 30
    //   2828: aload_0
    //   2829: aload_1
    //   2830: iload 12
    //   2832: iload 13
    //   2834: invokespecial 538	com/google/android/gms/internal/measurement/zzvz:zza	(Ljava/lang/Object;II)Z
    //   2837: ifeq +57 -> 2894
    //   2840: aload_1
    //   2841: ldc_w 265
    //   2844: iload 14
    //   2846: iand
    //   2847: i2l
    //   2848: invokestatic 273	com/google/android/gms/internal/measurement/zzxj:zzp	(Ljava/lang/Object;J)Ljava/lang/Object;
    //   2851: aload_2
    //   2852: aload_0
    //   2853: iload 13
    //   2855: invokespecial 470	com/google/android/gms/internal/measurement/zzvz:zzbq	(I)Lcom/google/android/gms/internal/measurement/zzwl;
    //   2858: aload_3
    //   2859: invokeinterface 704 3 0
    //   2864: invokestatic 380	com/google/android/gms/internal/measurement/zzuq:zzb	(Ljava/lang/Object;Ljava/lang/Object;)Ljava/lang/Object;
    //   2867: astore 23
    //   2869: aload_1
    //   2870: iload 14
    //   2872: ldc_w 265
    //   2875: iand
    //   2876: i2l
    //   2877: aload 23
    //   2879: invokestatic 365	com/google/android/gms/internal/measurement/zzxj:zza	(Ljava/lang/Object;JLjava/lang/Object;)V
    //   2882: aload_0
    //   2883: aload_1
    //   2884: iload 12
    //   2886: iload 13
    //   2888: invokespecial 552	com/google/android/gms/internal/measurement/zzvz:zzb	(Ljava/lang/Object;II)V
    //   2891: goto -2861 -> 30
    //   2894: aload_1
    //   2895: iload 14
    //   2897: ldc_w 265
    //   2900: iand
    //   2901: i2l
    //   2902: aload_2
    //   2903: aload_0
    //   2904: iload 13
    //   2906: invokespecial 470	com/google/android/gms/internal/measurement/zzvz:zzbq	(I)Lcom/google/android/gms/internal/measurement/zzwl;
    //   2909: aload_3
    //   2910: invokeinterface 704 3 0
    //   2915: invokestatic 365	com/google/android/gms/internal/measurement/zzxj:zza	(Ljava/lang/Object;JLjava/lang/Object;)V
    //   2918: aload_0
    //   2919: aload_1
    //   2920: iload 13
    //   2922: invokespecial 384	com/google/android/gms/internal/measurement/zzvz:zzc	(Ljava/lang/Object;I)V
    //   2925: goto -43 -> 2882
    //   2928: aload_1
    //   2929: iload 14
    //   2931: ldc_w 265
    //   2934: iand
    //   2935: i2l
    //   2936: aload_2
    //   2937: invokeinterface 371 1 0
    //   2942: invokestatic 365	com/google/android/gms/internal/measurement/zzxj:zza	(Ljava/lang/Object;JLjava/lang/Object;)V
    //   2945: aload_0
    //   2946: aload_1
    //   2947: iload 12
    //   2949: iload 13
    //   2951: invokespecial 552	com/google/android/gms/internal/measurement/zzvz:zzb	(Ljava/lang/Object;II)V
    //   2954: goto -2924 -> 30
    //   2957: aload_1
    //   2958: iload 14
    //   2960: ldc_w 265
    //   2963: iand
    //   2964: i2l
    //   2965: aload_2
    //   2966: invokeinterface 707 1 0
    //   2971: invokestatic 803	java/lang/Integer:valueOf	(I)Ljava/lang/Integer;
    //   2974: invokestatic 365	com/google/android/gms/internal/measurement/zzxj:zza	(Ljava/lang/Object;JLjava/lang/Object;)V
    //   2977: aload_0
    //   2978: aload_1
    //   2979: iload 12
    //   2981: iload 13
    //   2983: invokespecial 552	com/google/android/gms/internal/measurement/zzvz:zzb	(Ljava/lang/Object;II)V
    //   2986: goto -2956 -> 30
    //   2989: aload_2
    //   2990: invokeinterface 710 1 0
    //   2995: istore 21
    //   2997: aload_0
    //   2998: iload 13
    //   3000: invokespecial 277	com/google/android/gms/internal/measurement/zzvz:zzbs	(I)Lcom/google/android/gms/internal/measurement/zzut;
    //   3003: astore 22
    //   3005: aload 22
    //   3007: ifnull +15 -> 3022
    //   3010: aload 22
    //   3012: iload 21
    //   3014: invokeinterface 222 2 0
    //   3019: ifeq +31 -> 3050
    //   3022: aload_1
    //   3023: iload 14
    //   3025: ldc_w 265
    //   3028: iand
    //   3029: i2l
    //   3030: iload 21
    //   3032: invokestatic 803	java/lang/Integer:valueOf	(I)Ljava/lang/Integer;
    //   3035: invokestatic 365	com/google/android/gms/internal/measurement/zzxj:zza	(Ljava/lang/Object;JLjava/lang/Object;)V
    //   3038: aload_0
    //   3039: aload_1
    //   3040: iload 12
    //   3042: iload 13
    //   3044: invokespecial 552	com/google/android/gms/internal/measurement/zzvz:zzb	(Ljava/lang/Object;II)V
    //   3047: goto -3017 -> 30
    //   3050: iload 12
    //   3052: iload 21
    //   3054: aload 6
    //   3056: aload 4
    //   3058: invokestatic 713	com/google/android/gms/internal/measurement/zzwn:zza	(IILjava/lang/Object;Lcom/google/android/gms/internal/measurement/zzxd;)Ljava/lang/Object;
    //   3061: astore 6
    //   3063: goto -3033 -> 30
    //   3066: aload_1
    //   3067: iload 14
    //   3069: ldc_w 265
    //   3072: iand
    //   3073: i2l
    //   3074: aload_2
    //   3075: invokeinterface 716 1 0
    //   3080: invokestatic 803	java/lang/Integer:valueOf	(I)Ljava/lang/Integer;
    //   3083: invokestatic 365	com/google/android/gms/internal/measurement/zzxj:zza	(Ljava/lang/Object;JLjava/lang/Object;)V
    //   3086: aload_0
    //   3087: aload_1
    //   3088: iload 12
    //   3090: iload 13
    //   3092: invokespecial 552	com/google/android/gms/internal/measurement/zzvz:zzb	(Ljava/lang/Object;II)V
    //   3095: goto -3065 -> 30
    //   3098: aload_1
    //   3099: iload 14
    //   3101: ldc_w 265
    //   3104: iand
    //   3105: i2l
    //   3106: aload_2
    //   3107: invokeinterface 719 1 0
    //   3112: invokestatic 800	java/lang/Long:valueOf	(J)Ljava/lang/Long;
    //   3115: invokestatic 365	com/google/android/gms/internal/measurement/zzxj:zza	(Ljava/lang/Object;JLjava/lang/Object;)V
    //   3118: aload_0
    //   3119: aload_1
    //   3120: iload 12
    //   3122: iload 13
    //   3124: invokespecial 552	com/google/android/gms/internal/measurement/zzvz:zzb	(Ljava/lang/Object;II)V
    //   3127: goto -3097 -> 30
    //   3130: aload_1
    //   3131: iload 14
    //   3133: ldc_w 265
    //   3136: iand
    //   3137: i2l
    //   3138: aload_2
    //   3139: invokeinterface 722 1 0
    //   3144: invokestatic 803	java/lang/Integer:valueOf	(I)Ljava/lang/Integer;
    //   3147: invokestatic 365	com/google/android/gms/internal/measurement/zzxj:zza	(Ljava/lang/Object;JLjava/lang/Object;)V
    //   3150: aload_0
    //   3151: aload_1
    //   3152: iload 12
    //   3154: iload 13
    //   3156: invokespecial 552	com/google/android/gms/internal/measurement/zzvz:zzb	(Ljava/lang/Object;II)V
    //   3159: goto -3129 -> 30
    //   3162: aload_1
    //   3163: iload 14
    //   3165: ldc_w 265
    //   3168: iand
    //   3169: i2l
    //   3170: aload_2
    //   3171: invokeinterface 725 1 0
    //   3176: invokestatic 800	java/lang/Long:valueOf	(J)Ljava/lang/Long;
    //   3179: invokestatic 365	com/google/android/gms/internal/measurement/zzxj:zza	(Ljava/lang/Object;JLjava/lang/Object;)V
    //   3182: aload_0
    //   3183: aload_1
    //   3184: iload 12
    //   3186: iload 13
    //   3188: invokespecial 552	com/google/android/gms/internal/measurement/zzvz:zzb	(Ljava/lang/Object;II)V
    //   3191: goto -3161 -> 30
    //   3194: aload_1
    //   3195: iload 14
    //   3197: ldc_w 265
    //   3200: iand
    //   3201: i2l
    //   3202: aload_2
    //   3203: aload_0
    //   3204: iload 13
    //   3206: invokespecial 470	com/google/android/gms/internal/measurement/zzvz:zzbq	(I)Lcom/google/android/gms/internal/measurement/zzwl;
    //   3209: aload_3
    //   3210: invokeinterface 727 3 0
    //   3215: invokestatic 365	com/google/android/gms/internal/measurement/zzxj:zza	(Ljava/lang/Object;JLjava/lang/Object;)V
    //   3218: aload_0
    //   3219: aload_1
    //   3220: iload 12
    //   3222: iload 13
    //   3224: invokespecial 552	com/google/android/gms/internal/measurement/zzvz:zzb	(Ljava/lang/Object;II)V
    //   3227: goto -3197 -> 30
    //   3230: aload 10
    //   3232: ifnull -3018 -> 214
    //   3235: aload 4
    //   3237: aload_1
    //   3238: aload 10
    //   3240: invokevirtual 645	com/google/android/gms/internal/measurement/zzxd:zzg	(Ljava/lang/Object;Ljava/lang/Object;)V
    //   3243: return
    //   3244: aload 10
    //   3246: astore 6
    //   3248: goto -3218 -> 30
    //   3251: aload 10
    //   3253: ifnull -3039 -> 214
    //   3256: aload 4
    //   3258: aload_1
    //   3259: aload 10
    //   3261: invokevirtual 645	com/google/android/gms/internal/measurement/zzxd:zzg	(Ljava/lang/Object;Ljava/lang/Object;)V
    //   3264: return
    //   3265: aload 10
    //   3267: astore 6
    //   3269: goto -3239 -> 30
    //   3272: aload 10
    //   3274: ifnull +11 -> 3285
    //   3277: aload 4
    //   3279: aload_1
    //   3280: aload 10
    //   3282: invokevirtual 645	com/google/android/gms/internal/measurement/zzxd:zzg	(Ljava/lang/Object;Ljava/lang/Object;)V
    //   3285: aload 9
    //   3287: athrow
    //   3288: astore 18
    //   3290: aload 18
    //   3292: astore 9
    //   3294: goto -2392 -> 902
    //   3297: astore 48
    //   3299: aload 10
    //   3301: astore 6
    //   3303: goto -2520 -> 783
    //   3306: aload 6
    //   3308: astore 10
    //   3310: goto -2503 -> 807
    //   3313: aload 6
    //   3315: astore 10
    //   3317: goto -2621 -> 696
    //   3320: aload 27
    //   3322: astore 28
    //   3324: goto -856 -> 2468
    //   3327: aload 10
    //   3329: astore 6
    //   3331: goto -3301 -> 30
    //   3334: aload 6
    //   3336: astore 10
    //   3338: goto -3034 -> 304
    //
    // Exception table:
    //   from	to	target	type
    //   685	692	781	com/google/android/gms/internal/measurement/zzuw
    //   759	778	781	com/google/android/gms/internal/measurement/zzuw
    //   870	889	781	com/google/android/gms/internal/measurement/zzuw
    //   950	969	781	com/google/android/gms/internal/measurement/zzuw
    //   972	996	781	com/google/android/gms/internal/measurement/zzuw
    //   999	1023	781	com/google/android/gms/internal/measurement/zzuw
    //   1026	1050	781	com/google/android/gms/internal/measurement/zzuw
    //   1053	1077	781	com/google/android/gms/internal/measurement/zzuw
    //   1080	1104	781	com/google/android/gms/internal/measurement/zzuw
    //   1107	1122	781	com/google/android/gms/internal/measurement/zzuw
    //   1125	1177	781	com/google/android/gms/internal/measurement/zzuw
    //   1180	1211	781	com/google/android/gms/internal/measurement/zzuw
    //   1214	1238	781	com/google/android/gms/internal/measurement/zzuw
    //   1241	1265	781	com/google/android/gms/internal/measurement/zzuw
    //   1268	1284	781	com/google/android/gms/internal/measurement/zzuw
    //   1289	1301	781	com/google/android/gms/internal/measurement/zzuw
    //   1301	1321	781	com/google/android/gms/internal/measurement/zzuw
    //   1324	1337	781	com/google/android/gms/internal/measurement/zzuw
    //   1340	1364	781	com/google/android/gms/internal/measurement/zzuw
    //   1367	1391	781	com/google/android/gms/internal/measurement/zzuw
    //   1394	1418	781	com/google/android/gms/internal/measurement/zzuw
    //   1421	1445	781	com/google/android/gms/internal/measurement/zzuw
    //   1448	1500	781	com/google/android/gms/internal/measurement/zzuw
    //   1503	1534	781	com/google/android/gms/internal/measurement/zzuw
    //   1537	1558	781	com/google/android/gms/internal/measurement/zzuw
    //   1561	1582	781	com/google/android/gms/internal/measurement/zzuw
    //   1585	1606	781	com/google/android/gms/internal/measurement/zzuw
    //   1609	1630	781	com/google/android/gms/internal/measurement/zzuw
    //   1633	1654	781	com/google/android/gms/internal/measurement/zzuw
    //   1657	1678	781	com/google/android/gms/internal/measurement/zzuw
    //   1681	1702	781	com/google/android/gms/internal/measurement/zzuw
    //   1705	1726	781	com/google/android/gms/internal/measurement/zzuw
    //   1729	1758	781	com/google/android/gms/internal/measurement/zzuw
    //   1761	1782	781	com/google/android/gms/internal/measurement/zzuw
    //   1785	1793	781	com/google/android/gms/internal/measurement/zzuw
    //   1802	1821	781	com/google/android/gms/internal/measurement/zzuw
    //   1824	1845	781	com/google/android/gms/internal/measurement/zzuw
    //   1848	1869	781	com/google/android/gms/internal/measurement/zzuw
    //   1872	1916	781	com/google/android/gms/internal/measurement/zzuw
    //   1919	1940	781	com/google/android/gms/internal/measurement/zzuw
    //   1943	1964	781	com/google/android/gms/internal/measurement/zzuw
    //   1967	1988	781	com/google/android/gms/internal/measurement/zzuw
    //   1991	2012	781	com/google/android/gms/internal/measurement/zzuw
    //   2015	2036	781	com/google/android/gms/internal/measurement/zzuw
    //   2039	2060	781	com/google/android/gms/internal/measurement/zzuw
    //   2063	2084	781	com/google/android/gms/internal/measurement/zzuw
    //   2087	2108	781	com/google/android/gms/internal/measurement/zzuw
    //   2111	2132	781	com/google/android/gms/internal/measurement/zzuw
    //   2135	2156	781	com/google/android/gms/internal/measurement/zzuw
    //   2159	2180	781	com/google/android/gms/internal/measurement/zzuw
    //   2183	2204	781	com/google/android/gms/internal/measurement/zzuw
    //   2207	2228	781	com/google/android/gms/internal/measurement/zzuw
    //   2231	2275	781	com/google/android/gms/internal/measurement/zzuw
    //   2278	2299	781	com/google/android/gms/internal/measurement/zzuw
    //   2302	2323	781	com/google/android/gms/internal/measurement/zzuw
    //   2326	2347	781	com/google/android/gms/internal/measurement/zzuw
    //   2350	2371	781	com/google/android/gms/internal/measurement/zzuw
    //   2383	2410	781	com/google/android/gms/internal/measurement/zzuw
    //   2413	2442	781	com/google/android/gms/internal/measurement/zzuw
    //   2447	2468	781	com/google/android/gms/internal/measurement/zzuw
    //   2468	2497	781	com/google/android/gms/internal/measurement/zzuw
    //   2500	2549	781	com/google/android/gms/internal/measurement/zzuw
    //   2552	2581	781	com/google/android/gms/internal/measurement/zzuw
    //   2584	2613	781	com/google/android/gms/internal/measurement/zzuw
    //   2616	2645	781	com/google/android/gms/internal/measurement/zzuw
    //   2648	2677	781	com/google/android/gms/internal/measurement/zzuw
    //   2680	2709	781	com/google/android/gms/internal/measurement/zzuw
    //   2712	2741	781	com/google/android/gms/internal/measurement/zzuw
    //   2744	2773	781	com/google/android/gms/internal/measurement/zzuw
    //   2776	2805	781	com/google/android/gms/internal/measurement/zzuw
    //   2808	2825	781	com/google/android/gms/internal/measurement/zzuw
    //   2828	2882	781	com/google/android/gms/internal/measurement/zzuw
    //   2882	2891	781	com/google/android/gms/internal/measurement/zzuw
    //   2894	2925	781	com/google/android/gms/internal/measurement/zzuw
    //   2928	2954	781	com/google/android/gms/internal/measurement/zzuw
    //   2957	2986	781	com/google/android/gms/internal/measurement/zzuw
    //   2989	3005	781	com/google/android/gms/internal/measurement/zzuw
    //   3010	3022	781	com/google/android/gms/internal/measurement/zzuw
    //   3022	3047	781	com/google/android/gms/internal/measurement/zzuw
    //   3050	3063	781	com/google/android/gms/internal/measurement/zzuw
    //   3066	3095	781	com/google/android/gms/internal/measurement/zzuw
    //   3098	3127	781	com/google/android/gms/internal/measurement/zzuw
    //   3130	3159	781	com/google/android/gms/internal/measurement/zzuw
    //   3162	3191	781	com/google/android/gms/internal/measurement/zzuw
    //   3194	3227	781	com/google/android/gms/internal/measurement/zzuw
    //   30	67	892	finally
    //   96	105	892	finally
    //   215	222	892	finally
    //   235	243	892	finally
    //   243	260	892	finally
    //   263	277	892	finally
    //   280	287	892	finally
    //   292	300	892	finally
    //   372	380	892	finally
    //   685	692	892	finally
    //   759	778	892	finally
    //   783	790	892	finally
    //   795	803	892	finally
    //   870	889	892	finally
    //   950	969	892	finally
    //   972	996	892	finally
    //   999	1023	892	finally
    //   1026	1050	892	finally
    //   1053	1077	892	finally
    //   1080	1104	892	finally
    //   1107	1122	892	finally
    //   1125	1177	892	finally
    //   1180	1211	892	finally
    //   1214	1238	892	finally
    //   1241	1265	892	finally
    //   1268	1284	892	finally
    //   1289	1301	892	finally
    //   1301	1321	892	finally
    //   1324	1337	892	finally
    //   1340	1364	892	finally
    //   1367	1391	892	finally
    //   1394	1418	892	finally
    //   1421	1445	892	finally
    //   1448	1500	892	finally
    //   1503	1534	892	finally
    //   1537	1558	892	finally
    //   1561	1582	892	finally
    //   1585	1606	892	finally
    //   1609	1630	892	finally
    //   1633	1654	892	finally
    //   1657	1678	892	finally
    //   1681	1702	892	finally
    //   1705	1726	892	finally
    //   1729	1758	892	finally
    //   1761	1782	892	finally
    //   1785	1793	892	finally
    //   1802	1821	892	finally
    //   1824	1845	892	finally
    //   1848	1869	892	finally
    //   1872	1916	892	finally
    //   1919	1940	892	finally
    //   1943	1964	892	finally
    //   1967	1988	892	finally
    //   1991	2012	892	finally
    //   2015	2036	892	finally
    //   2039	2060	892	finally
    //   2063	2084	892	finally
    //   2087	2108	892	finally
    //   2111	2132	892	finally
    //   2135	2156	892	finally
    //   2159	2180	892	finally
    //   2183	2204	892	finally
    //   2207	2228	892	finally
    //   2231	2275	892	finally
    //   2278	2299	892	finally
    //   2302	2323	892	finally
    //   2326	2347	892	finally
    //   2350	2371	892	finally
    //   2383	2410	892	finally
    //   2413	2442	892	finally
    //   2447	2468	892	finally
    //   2468	2497	892	finally
    //   2500	2549	892	finally
    //   2552	2581	892	finally
    //   2584	2613	892	finally
    //   2616	2645	892	finally
    //   2648	2677	892	finally
    //   2680	2709	892	finally
    //   2712	2741	892	finally
    //   2744	2773	892	finally
    //   2776	2805	892	finally
    //   2808	2825	892	finally
    //   2828	2882	892	finally
    //   2882	2891	892	finally
    //   2894	2925	892	finally
    //   2928	2954	892	finally
    //   2957	2986	892	finally
    //   2989	3005	892	finally
    //   3010	3022	892	finally
    //   3022	3047	892	finally
    //   3050	3063	892	finally
    //   3066	3095	892	finally
    //   3098	3127	892	finally
    //   3130	3159	892	finally
    //   3162	3191	892	finally
    //   3194	3227	892	finally
    //   304	314	3288	finally
    //   696	706	3288	finally
    //   807	817	3288	finally
    //   696	706	3297	com/google/android/gms/internal/measurement/zzuw
  }

  public final void zza(T paramT, zzxy paramzzxy)
    throws IOException
  {
    if (paramzzxy.zzvm() == zzuo.zze.zzbyy)
    {
      zza(this.zzcbg, paramT, paramzzxy);
      boolean bool3 = this.zzcax;
      Object localObject3 = null;
      Iterator localIterator2 = null;
      if (bool3)
      {
        zzuf localzzuf2 = this.zzcbh.zzw(paramT);
        boolean bool4 = localzzuf2.isEmpty();
        localObject3 = null;
        localIterator2 = null;
        if (!bool4)
        {
          localIterator2 = localzzuf2.descendingIterator();
          localObject3 = (Map.Entry)localIterator2.next();
        }
      }
      int n = -3 + this.zzcas.length;
      if (n >= 0)
      {
        int i1 = zzbt(n);
        int i2 = this.zzcas[n];
        Object localObject4 = localObject3;
        if ((localObject4 != null) && (this.zzcbh.zzb(localObject4) > i2))
        {
          this.zzcbh.zza(paramzzxy, localObject4);
          if (localIterator2.hasNext());
          for (Map.Entry localEntry2 = (Map.Entry)localIterator2.next(); ; localEntry2 = null)
          {
            localObject4 = localEntry2;
            break;
          }
        }
        switch ((0xFF00000 & i1) >>> 20)
        {
        default:
        case 0:
        case 1:
        case 2:
        case 3:
        case 4:
        case 5:
        case 6:
        case 7:
        case 8:
        case 9:
        case 10:
        case 11:
        case 12:
        case 13:
        case 14:
        case 15:
        case 16:
        case 17:
        case 18:
        case 19:
        case 20:
        case 21:
        case 22:
        case 23:
        case 24:
        case 25:
        case 26:
        case 27:
        case 28:
        case 29:
        case 30:
        case 31:
        case 32:
        case 33:
        case 34:
        case 35:
        case 36:
        case 37:
        case 38:
        case 39:
        case 40:
        case 41:
        case 42:
        case 43:
        case 44:
        case 45:
        case 46:
        case 47:
        case 48:
        case 49:
        case 50:
        case 51:
        case 52:
        case 53:
        case 54:
        case 55:
        case 56:
        case 57:
        case 58:
        case 59:
        case 60:
        case 61:
        case 62:
        case 63:
        case 64:
        case 65:
        case 66:
        case 67:
        case 68:
        }
        while (true)
        {
          n -= 3;
          localObject3 = localObject4;
          break;
          if (zzb(paramT, n))
          {
            paramzzxy.zza(i2, zzxj.zzo(paramT, 0xFFFFF & i1));
            continue;
            if (zzb(paramT, n))
            {
              paramzzxy.zza(i2, zzxj.zzn(paramT, 0xFFFFF & i1));
              continue;
              if (zzb(paramT, n))
              {
                paramzzxy.zzi(i2, zzxj.zzl(paramT, 0xFFFFF & i1));
                continue;
                if (zzb(paramT, n))
                {
                  paramzzxy.zza(i2, zzxj.zzl(paramT, 0xFFFFF & i1));
                  continue;
                  if (zzb(paramT, n))
                  {
                    paramzzxy.zzd(i2, zzxj.zzk(paramT, 0xFFFFF & i1));
                    continue;
                    if (zzb(paramT, n))
                    {
                      paramzzxy.zzc(i2, zzxj.zzl(paramT, 0xFFFFF & i1));
                      continue;
                      if (zzb(paramT, n))
                      {
                        paramzzxy.zzg(i2, zzxj.zzk(paramT, 0xFFFFF & i1));
                        continue;
                        if (zzb(paramT, n))
                        {
                          paramzzxy.zzb(i2, zzxj.zzm(paramT, 0xFFFFF & i1));
                          continue;
                          if (zzb(paramT, n))
                          {
                            zza(i2, zzxj.zzp(paramT, 0xFFFFF & i1), paramzzxy);
                            continue;
                            if (zzb(paramT, n))
                            {
                              paramzzxy.zza(i2, zzxj.zzp(paramT, 0xFFFFF & i1), zzbq(n));
                              continue;
                              if (zzb(paramT, n))
                              {
                                paramzzxy.zza(i2, (zzte)zzxj.zzp(paramT, 0xFFFFF & i1));
                                continue;
                                if (zzb(paramT, n))
                                {
                                  paramzzxy.zze(i2, zzxj.zzk(paramT, 0xFFFFF & i1));
                                  continue;
                                  if (zzb(paramT, n))
                                  {
                                    paramzzxy.zzo(i2, zzxj.zzk(paramT, 0xFFFFF & i1));
                                    continue;
                                    if (zzb(paramT, n))
                                    {
                                      paramzzxy.zzn(i2, zzxj.zzk(paramT, 0xFFFFF & i1));
                                      continue;
                                      if (zzb(paramT, n))
                                      {
                                        paramzzxy.zzj(i2, zzxj.zzl(paramT, 0xFFFFF & i1));
                                        continue;
                                        if (zzb(paramT, n))
                                        {
                                          paramzzxy.zzf(i2, zzxj.zzk(paramT, 0xFFFFF & i1));
                                          continue;
                                          if (zzb(paramT, n))
                                          {
                                            paramzzxy.zzb(i2, zzxj.zzl(paramT, 0xFFFFF & i1));
                                            continue;
                                            if (zzb(paramT, n))
                                            {
                                              paramzzxy.zzb(i2, zzxj.zzp(paramT, 0xFFFFF & i1), zzbq(n));
                                              continue;
                                              zzwn.zza(this.zzcas[n], (List)zzxj.zzp(paramT, 0xFFFFF & i1), paramzzxy, false);
                                              continue;
                                              zzwn.zzb(this.zzcas[n], (List)zzxj.zzp(paramT, 0xFFFFF & i1), paramzzxy, false);
                                              continue;
                                              zzwn.zzc(this.zzcas[n], (List)zzxj.zzp(paramT, 0xFFFFF & i1), paramzzxy, false);
                                              continue;
                                              zzwn.zzd(this.zzcas[n], (List)zzxj.zzp(paramT, 0xFFFFF & i1), paramzzxy, false);
                                              continue;
                                              zzwn.zzh(this.zzcas[n], (List)zzxj.zzp(paramT, 0xFFFFF & i1), paramzzxy, false);
                                              continue;
                                              zzwn.zzf(this.zzcas[n], (List)zzxj.zzp(paramT, 0xFFFFF & i1), paramzzxy, false);
                                              continue;
                                              zzwn.zzk(this.zzcas[n], (List)zzxj.zzp(paramT, 0xFFFFF & i1), paramzzxy, false);
                                              continue;
                                              zzwn.zzn(this.zzcas[n], (List)zzxj.zzp(paramT, 0xFFFFF & i1), paramzzxy, false);
                                              continue;
                                              zzwn.zza(this.zzcas[n], (List)zzxj.zzp(paramT, 0xFFFFF & i1), paramzzxy);
                                              continue;
                                              zzwn.zza(this.zzcas[n], (List)zzxj.zzp(paramT, 0xFFFFF & i1), paramzzxy, zzbq(n));
                                              continue;
                                              zzwn.zzb(this.zzcas[n], (List)zzxj.zzp(paramT, 0xFFFFF & i1), paramzzxy);
                                              continue;
                                              zzwn.zzi(this.zzcas[n], (List)zzxj.zzp(paramT, 0xFFFFF & i1), paramzzxy, false);
                                              continue;
                                              zzwn.zzm(this.zzcas[n], (List)zzxj.zzp(paramT, 0xFFFFF & i1), paramzzxy, false);
                                              continue;
                                              zzwn.zzl(this.zzcas[n], (List)zzxj.zzp(paramT, 0xFFFFF & i1), paramzzxy, false);
                                              continue;
                                              zzwn.zzg(this.zzcas[n], (List)zzxj.zzp(paramT, 0xFFFFF & i1), paramzzxy, false);
                                              continue;
                                              zzwn.zzj(this.zzcas[n], (List)zzxj.zzp(paramT, 0xFFFFF & i1), paramzzxy, false);
                                              continue;
                                              zzwn.zze(this.zzcas[n], (List)zzxj.zzp(paramT, 0xFFFFF & i1), paramzzxy, false);
                                              continue;
                                              zzwn.zza(this.zzcas[n], (List)zzxj.zzp(paramT, 0xFFFFF & i1), paramzzxy, true);
                                              continue;
                                              zzwn.zzb(this.zzcas[n], (List)zzxj.zzp(paramT, 0xFFFFF & i1), paramzzxy, true);
                                              continue;
                                              zzwn.zzc(this.zzcas[n], (List)zzxj.zzp(paramT, 0xFFFFF & i1), paramzzxy, true);
                                              continue;
                                              zzwn.zzd(this.zzcas[n], (List)zzxj.zzp(paramT, 0xFFFFF & i1), paramzzxy, true);
                                              continue;
                                              zzwn.zzh(this.zzcas[n], (List)zzxj.zzp(paramT, 0xFFFFF & i1), paramzzxy, true);
                                              continue;
                                              zzwn.zzf(this.zzcas[n], (List)zzxj.zzp(paramT, 0xFFFFF & i1), paramzzxy, true);
                                              continue;
                                              zzwn.zzk(this.zzcas[n], (List)zzxj.zzp(paramT, 0xFFFFF & i1), paramzzxy, true);
                                              continue;
                                              zzwn.zzn(this.zzcas[n], (List)zzxj.zzp(paramT, 0xFFFFF & i1), paramzzxy, true);
                                              continue;
                                              zzwn.zzi(this.zzcas[n], (List)zzxj.zzp(paramT, 0xFFFFF & i1), paramzzxy, true);
                                              continue;
                                              zzwn.zzm(this.zzcas[n], (List)zzxj.zzp(paramT, 0xFFFFF & i1), paramzzxy, true);
                                              continue;
                                              zzwn.zzl(this.zzcas[n], (List)zzxj.zzp(paramT, 0xFFFFF & i1), paramzzxy, true);
                                              continue;
                                              zzwn.zzg(this.zzcas[n], (List)zzxj.zzp(paramT, 0xFFFFF & i1), paramzzxy, true);
                                              continue;
                                              zzwn.zzj(this.zzcas[n], (List)zzxj.zzp(paramT, 0xFFFFF & i1), paramzzxy, true);
                                              continue;
                                              zzwn.zze(this.zzcas[n], (List)zzxj.zzp(paramT, 0xFFFFF & i1), paramzzxy, true);
                                              continue;
                                              zzwn.zzb(this.zzcas[n], (List)zzxj.zzp(paramT, 0xFFFFF & i1), paramzzxy, zzbq(n));
                                              continue;
                                              zza(paramzzxy, i2, zzxj.zzp(paramT, 0xFFFFF & i1), n);
                                              continue;
                                              if (zza(paramT, i2, n))
                                              {
                                                paramzzxy.zza(i2, zzf(paramT, 0xFFFFF & i1));
                                                continue;
                                                if (zza(paramT, i2, n))
                                                {
                                                  paramzzxy.zza(i2, zzg(paramT, 0xFFFFF & i1));
                                                  continue;
                                                  if (zza(paramT, i2, n))
                                                  {
                                                    paramzzxy.zzi(i2, zzi(paramT, 0xFFFFF & i1));
                                                    continue;
                                                    if (zza(paramT, i2, n))
                                                    {
                                                      paramzzxy.zza(i2, zzi(paramT, 0xFFFFF & i1));
                                                      continue;
                                                      if (zza(paramT, i2, n))
                                                      {
                                                        paramzzxy.zzd(i2, zzh(paramT, 0xFFFFF & i1));
                                                        continue;
                                                        if (zza(paramT, i2, n))
                                                        {
                                                          paramzzxy.zzc(i2, zzi(paramT, 0xFFFFF & i1));
                                                          continue;
                                                          if (zza(paramT, i2, n))
                                                          {
                                                            paramzzxy.zzg(i2, zzh(paramT, 0xFFFFF & i1));
                                                            continue;
                                                            if (zza(paramT, i2, n))
                                                            {
                                                              paramzzxy.zzb(i2, zzj(paramT, 0xFFFFF & i1));
                                                              continue;
                                                              if (zza(paramT, i2, n))
                                                              {
                                                                zza(i2, zzxj.zzp(paramT, 0xFFFFF & i1), paramzzxy);
                                                                continue;
                                                                if (zza(paramT, i2, n))
                                                                {
                                                                  paramzzxy.zza(i2, zzxj.zzp(paramT, 0xFFFFF & i1), zzbq(n));
                                                                  continue;
                                                                  if (zza(paramT, i2, n))
                                                                  {
                                                                    paramzzxy.zza(i2, (zzte)zzxj.zzp(paramT, 0xFFFFF & i1));
                                                                    continue;
                                                                    if (zza(paramT, i2, n))
                                                                    {
                                                                      paramzzxy.zze(i2, zzh(paramT, 0xFFFFF & i1));
                                                                      continue;
                                                                      if (zza(paramT, i2, n))
                                                                      {
                                                                        paramzzxy.zzo(i2, zzh(paramT, 0xFFFFF & i1));
                                                                        continue;
                                                                        if (zza(paramT, i2, n))
                                                                        {
                                                                          paramzzxy.zzn(i2, zzh(paramT, 0xFFFFF & i1));
                                                                          continue;
                                                                          if (zza(paramT, i2, n))
                                                                          {
                                                                            paramzzxy.zzj(i2, zzi(paramT, 0xFFFFF & i1));
                                                                            continue;
                                                                            if (zza(paramT, i2, n))
                                                                            {
                                                                              paramzzxy.zzf(i2, zzh(paramT, 0xFFFFF & i1));
                                                                              continue;
                                                                              if (zza(paramT, i2, n))
                                                                              {
                                                                                paramzzxy.zzb(i2, zzi(paramT, 0xFFFFF & i1));
                                                                                continue;
                                                                                if (zza(paramT, i2, n))
                                                                                  paramzzxy.zzb(i2, zzxj.zzp(paramT, 0xFFFFF & i1), zzbq(n));
                                                                              }
                                                                            }
                                                                          }
                                                                        }
                                                                      }
                                                                    }
                                                                  }
                                                                }
                                                              }
                                                            }
                                                          }
                                                        }
                                                      }
                                                    }
                                                  }
                                                }
                                              }
                                            }
                                          }
                                        }
                                      }
                                    }
                                  }
                                }
                              }
                            }
                          }
                        }
                      }
                    }
                  }
                }
              }
            }
          }
        }
      }
      for (localObject3 = null; ; localObject3 = (Map.Entry)localIterator2.next())
      {
        if (localObject3 == null)
          break label5415;
        this.zzcbh.zza(paramzzxy, (Map.Entry)localObject3);
        if (!localIterator2.hasNext())
          break;
      }
    }
    if (this.zzcaz)
    {
      boolean bool1 = this.zzcax;
      Object localObject1 = null;
      Iterator localIterator1 = null;
      if (bool1)
      {
        zzuf localzzuf1 = this.zzcbh.zzw(paramT);
        boolean bool2 = localzzuf1.isEmpty();
        localObject1 = null;
        localIterator1 = null;
        if (!bool2)
        {
          localIterator1 = localzzuf1.iterator();
          localObject1 = (Map.Entry)localIterator1.next();
        }
      }
      int i = this.zzcas.length;
      int j = 0;
      if (j < i)
      {
        int k = zzbt(j);
        int m = this.zzcas[j];
        Object localObject2 = localObject1;
        if ((localObject2 != null) && (this.zzcbh.zzb(localObject2) <= m))
        {
          this.zzcbh.zza(paramzzxy, localObject2);
          if (localIterator1.hasNext());
          for (Map.Entry localEntry1 = (Map.Entry)localIterator1.next(); ; localEntry1 = null)
          {
            localObject2 = localEntry1;
            break;
          }
        }
        switch ((0xFF00000 & k) >>> 20)
        {
        default:
        case 0:
        case 1:
        case 2:
        case 3:
        case 4:
        case 5:
        case 6:
        case 7:
        case 8:
        case 9:
        case 10:
        case 11:
        case 12:
        case 13:
        case 14:
        case 15:
        case 16:
        case 17:
        case 18:
        case 19:
        case 20:
        case 21:
        case 22:
        case 23:
        case 24:
        case 25:
        case 26:
        case 27:
        case 28:
        case 29:
        case 30:
        case 31:
        case 32:
        case 33:
        case 34:
        case 35:
        case 36:
        case 37:
        case 38:
        case 39:
        case 40:
        case 41:
        case 42:
        case 43:
        case 44:
        case 45:
        case 46:
        case 47:
        case 48:
        case 49:
        case 50:
        case 51:
        case 52:
        case 53:
        case 54:
        case 55:
        case 56:
        case 57:
        case 58:
        case 59:
        case 60:
        case 61:
        case 62:
        case 63:
        case 64:
        case 65:
        case 66:
        case 67:
        case 68:
        }
        while (true)
        {
          j += 3;
          localObject1 = localObject2;
          break;
          if (zzb(paramT, j))
          {
            paramzzxy.zza(m, zzxj.zzo(paramT, 0xFFFFF & k));
            continue;
            if (zzb(paramT, j))
            {
              paramzzxy.zza(m, zzxj.zzn(paramT, 0xFFFFF & k));
              continue;
              if (zzb(paramT, j))
              {
                paramzzxy.zzi(m, zzxj.zzl(paramT, 0xFFFFF & k));
                continue;
                if (zzb(paramT, j))
                {
                  paramzzxy.zza(m, zzxj.zzl(paramT, 0xFFFFF & k));
                  continue;
                  if (zzb(paramT, j))
                  {
                    paramzzxy.zzd(m, zzxj.zzk(paramT, 0xFFFFF & k));
                    continue;
                    if (zzb(paramT, j))
                    {
                      paramzzxy.zzc(m, zzxj.zzl(paramT, 0xFFFFF & k));
                      continue;
                      if (zzb(paramT, j))
                      {
                        paramzzxy.zzg(m, zzxj.zzk(paramT, 0xFFFFF & k));
                        continue;
                        if (zzb(paramT, j))
                        {
                          paramzzxy.zzb(m, zzxj.zzm(paramT, 0xFFFFF & k));
                          continue;
                          if (zzb(paramT, j))
                          {
                            zza(m, zzxj.zzp(paramT, 0xFFFFF & k), paramzzxy);
                            continue;
                            if (zzb(paramT, j))
                            {
                              paramzzxy.zza(m, zzxj.zzp(paramT, 0xFFFFF & k), zzbq(j));
                              continue;
                              if (zzb(paramT, j))
                              {
                                paramzzxy.zza(m, (zzte)zzxj.zzp(paramT, 0xFFFFF & k));
                                continue;
                                if (zzb(paramT, j))
                                {
                                  paramzzxy.zze(m, zzxj.zzk(paramT, 0xFFFFF & k));
                                  continue;
                                  if (zzb(paramT, j))
                                  {
                                    paramzzxy.zzo(m, zzxj.zzk(paramT, 0xFFFFF & k));
                                    continue;
                                    if (zzb(paramT, j))
                                    {
                                      paramzzxy.zzn(m, zzxj.zzk(paramT, 0xFFFFF & k));
                                      continue;
                                      if (zzb(paramT, j))
                                      {
                                        paramzzxy.zzj(m, zzxj.zzl(paramT, 0xFFFFF & k));
                                        continue;
                                        if (zzb(paramT, j))
                                        {
                                          paramzzxy.zzf(m, zzxj.zzk(paramT, 0xFFFFF & k));
                                          continue;
                                          if (zzb(paramT, j))
                                          {
                                            paramzzxy.zzb(m, zzxj.zzl(paramT, 0xFFFFF & k));
                                            continue;
                                            if (zzb(paramT, j))
                                            {
                                              paramzzxy.zzb(m, zzxj.zzp(paramT, 0xFFFFF & k), zzbq(j));
                                              continue;
                                              zzwn.zza(this.zzcas[j], (List)zzxj.zzp(paramT, 0xFFFFF & k), paramzzxy, false);
                                              continue;
                                              zzwn.zzb(this.zzcas[j], (List)zzxj.zzp(paramT, 0xFFFFF & k), paramzzxy, false);
                                              continue;
                                              zzwn.zzc(this.zzcas[j], (List)zzxj.zzp(paramT, 0xFFFFF & k), paramzzxy, false);
                                              continue;
                                              zzwn.zzd(this.zzcas[j], (List)zzxj.zzp(paramT, 0xFFFFF & k), paramzzxy, false);
                                              continue;
                                              zzwn.zzh(this.zzcas[j], (List)zzxj.zzp(paramT, 0xFFFFF & k), paramzzxy, false);
                                              continue;
                                              zzwn.zzf(this.zzcas[j], (List)zzxj.zzp(paramT, 0xFFFFF & k), paramzzxy, false);
                                              continue;
                                              zzwn.zzk(this.zzcas[j], (List)zzxj.zzp(paramT, 0xFFFFF & k), paramzzxy, false);
                                              continue;
                                              zzwn.zzn(this.zzcas[j], (List)zzxj.zzp(paramT, 0xFFFFF & k), paramzzxy, false);
                                              continue;
                                              zzwn.zza(this.zzcas[j], (List)zzxj.zzp(paramT, 0xFFFFF & k), paramzzxy);
                                              continue;
                                              zzwn.zza(this.zzcas[j], (List)zzxj.zzp(paramT, 0xFFFFF & k), paramzzxy, zzbq(j));
                                              continue;
                                              zzwn.zzb(this.zzcas[j], (List)zzxj.zzp(paramT, 0xFFFFF & k), paramzzxy);
                                              continue;
                                              zzwn.zzi(this.zzcas[j], (List)zzxj.zzp(paramT, 0xFFFFF & k), paramzzxy, false);
                                              continue;
                                              zzwn.zzm(this.zzcas[j], (List)zzxj.zzp(paramT, 0xFFFFF & k), paramzzxy, false);
                                              continue;
                                              zzwn.zzl(this.zzcas[j], (List)zzxj.zzp(paramT, 0xFFFFF & k), paramzzxy, false);
                                              continue;
                                              zzwn.zzg(this.zzcas[j], (List)zzxj.zzp(paramT, 0xFFFFF & k), paramzzxy, false);
                                              continue;
                                              zzwn.zzj(this.zzcas[j], (List)zzxj.zzp(paramT, 0xFFFFF & k), paramzzxy, false);
                                              continue;
                                              zzwn.zze(this.zzcas[j], (List)zzxj.zzp(paramT, 0xFFFFF & k), paramzzxy, false);
                                              continue;
                                              zzwn.zza(this.zzcas[j], (List)zzxj.zzp(paramT, 0xFFFFF & k), paramzzxy, true);
                                              continue;
                                              zzwn.zzb(this.zzcas[j], (List)zzxj.zzp(paramT, 0xFFFFF & k), paramzzxy, true);
                                              continue;
                                              zzwn.zzc(this.zzcas[j], (List)zzxj.zzp(paramT, 0xFFFFF & k), paramzzxy, true);
                                              continue;
                                              zzwn.zzd(this.zzcas[j], (List)zzxj.zzp(paramT, 0xFFFFF & k), paramzzxy, true);
                                              continue;
                                              zzwn.zzh(this.zzcas[j], (List)zzxj.zzp(paramT, 0xFFFFF & k), paramzzxy, true);
                                              continue;
                                              zzwn.zzf(this.zzcas[j], (List)zzxj.zzp(paramT, 0xFFFFF & k), paramzzxy, true);
                                              continue;
                                              zzwn.zzk(this.zzcas[j], (List)zzxj.zzp(paramT, 0xFFFFF & k), paramzzxy, true);
                                              continue;
                                              zzwn.zzn(this.zzcas[j], (List)zzxj.zzp(paramT, 0xFFFFF & k), paramzzxy, true);
                                              continue;
                                              zzwn.zzi(this.zzcas[j], (List)zzxj.zzp(paramT, 0xFFFFF & k), paramzzxy, true);
                                              continue;
                                              zzwn.zzm(this.zzcas[j], (List)zzxj.zzp(paramT, 0xFFFFF & k), paramzzxy, true);
                                              continue;
                                              zzwn.zzl(this.zzcas[j], (List)zzxj.zzp(paramT, 0xFFFFF & k), paramzzxy, true);
                                              continue;
                                              zzwn.zzg(this.zzcas[j], (List)zzxj.zzp(paramT, 0xFFFFF & k), paramzzxy, true);
                                              continue;
                                              zzwn.zzj(this.zzcas[j], (List)zzxj.zzp(paramT, 0xFFFFF & k), paramzzxy, true);
                                              continue;
                                              zzwn.zze(this.zzcas[j], (List)zzxj.zzp(paramT, 0xFFFFF & k), paramzzxy, true);
                                              continue;
                                              zzwn.zzb(this.zzcas[j], (List)zzxj.zzp(paramT, 0xFFFFF & k), paramzzxy, zzbq(j));
                                              continue;
                                              zza(paramzzxy, m, zzxj.zzp(paramT, 0xFFFFF & k), j);
                                              continue;
                                              if (zza(paramT, m, j))
                                              {
                                                paramzzxy.zza(m, zzf(paramT, 0xFFFFF & k));
                                                continue;
                                                if (zza(paramT, m, j))
                                                {
                                                  paramzzxy.zza(m, zzg(paramT, 0xFFFFF & k));
                                                  continue;
                                                  if (zza(paramT, m, j))
                                                  {
                                                    paramzzxy.zzi(m, zzi(paramT, 0xFFFFF & k));
                                                    continue;
                                                    if (zza(paramT, m, j))
                                                    {
                                                      paramzzxy.zza(m, zzi(paramT, 0xFFFFF & k));
                                                      continue;
                                                      if (zza(paramT, m, j))
                                                      {
                                                        paramzzxy.zzd(m, zzh(paramT, 0xFFFFF & k));
                                                        continue;
                                                        if (zza(paramT, m, j))
                                                        {
                                                          paramzzxy.zzc(m, zzi(paramT, 0xFFFFF & k));
                                                          continue;
                                                          if (zza(paramT, m, j))
                                                          {
                                                            paramzzxy.zzg(m, zzh(paramT, 0xFFFFF & k));
                                                            continue;
                                                            if (zza(paramT, m, j))
                                                            {
                                                              paramzzxy.zzb(m, zzj(paramT, 0xFFFFF & k));
                                                              continue;
                                                              if (zza(paramT, m, j))
                                                              {
                                                                zza(m, zzxj.zzp(paramT, 0xFFFFF & k), paramzzxy);
                                                                continue;
                                                                if (zza(paramT, m, j))
                                                                {
                                                                  paramzzxy.zza(m, zzxj.zzp(paramT, 0xFFFFF & k), zzbq(j));
                                                                  continue;
                                                                  if (zza(paramT, m, j))
                                                                  {
                                                                    paramzzxy.zza(m, (zzte)zzxj.zzp(paramT, 0xFFFFF & k));
                                                                    continue;
                                                                    if (zza(paramT, m, j))
                                                                    {
                                                                      paramzzxy.zze(m, zzh(paramT, 0xFFFFF & k));
                                                                      continue;
                                                                      if (zza(paramT, m, j))
                                                                      {
                                                                        paramzzxy.zzo(m, zzh(paramT, 0xFFFFF & k));
                                                                        continue;
                                                                        if (zza(paramT, m, j))
                                                                        {
                                                                          paramzzxy.zzn(m, zzh(paramT, 0xFFFFF & k));
                                                                          continue;
                                                                          if (zza(paramT, m, j))
                                                                          {
                                                                            paramzzxy.zzj(m, zzi(paramT, 0xFFFFF & k));
                                                                            continue;
                                                                            if (zza(paramT, m, j))
                                                                            {
                                                                              paramzzxy.zzf(m, zzh(paramT, 0xFFFFF & k));
                                                                              continue;
                                                                              if (zza(paramT, m, j))
                                                                              {
                                                                                paramzzxy.zzb(m, zzi(paramT, 0xFFFFF & k));
                                                                                continue;
                                                                                if (zza(paramT, m, j))
                                                                                  paramzzxy.zzb(m, zzxj.zzp(paramT, 0xFFFFF & k), zzbq(j));
                                                                              }
                                                                            }
                                                                          }
                                                                        }
                                                                      }
                                                                    }
                                                                  }
                                                                }
                                                              }
                                                            }
                                                          }
                                                        }
                                                      }
                                                    }
                                                  }
                                                }
                                              }
                                            }
                                          }
                                        }
                                      }
                                    }
                                  }
                                }
                              }
                            }
                          }
                        }
                      }
                    }
                  }
                }
              }
            }
          }
        }
      }
      for (localObject1 = null; ; localObject1 = (Map.Entry)localIterator1.next())
      {
        if (localObject1 == null)
          break label5406;
        this.zzcbh.zza(paramzzxy, (Map.Entry)localObject1);
        if (!localIterator1.hasNext())
          break;
      }
      label5406: zza(this.zzcbg, paramT, paramzzxy);
      label5415: return;
    }
    zzb(paramT, paramzzxy);
  }

  public final int zzai(T paramT)
  {
    label102: int n;
    if (this.zzcaz)
    {
      Unsafe localUnsafe2 = zzcar;
      int i25 = 0;
      int i26 = 0;
      if (i26 < this.zzcas.length)
      {
        int i27 = zzbt(i26);
        int i28 = (0xFF00000 & i27) >>> 20;
        int i29 = this.zzcas[i26];
        long l2 = i27 & 0xFFFFF;
        int i30;
        if ((i28 >= zzui.zzbww.id()) && (i28 <= zzui.zzbxj.id()))
        {
          i30 = 0xFFFFF & this.zzcas[(i26 + 2)];
          switch (i28)
          {
          default:
          case 0:
          case 1:
          case 2:
          case 3:
          case 4:
          case 5:
          case 6:
          case 7:
          case 8:
          case 9:
          case 10:
          case 11:
          case 12:
          case 13:
          case 14:
          case 15:
          case 16:
          case 17:
          case 18:
          case 19:
          case 20:
          case 21:
          case 22:
          case 23:
          case 24:
          case 25:
          case 26:
          case 27:
          case 28:
          case 29:
          case 30:
          case 31:
          case 32:
          case 33:
          case 34:
          case 35:
          case 36:
          case 37:
          case 38:
          case 39:
          case 40:
          case 41:
          case 42:
          case 43:
          case 44:
          case 45:
          case 46:
          case 47:
          case 48:
          case 49:
          case 50:
          case 51:
          case 52:
          case 53:
          case 54:
          case 55:
          case 56:
          case 57:
          case 58:
          case 59:
          case 60:
          case 61:
          case 62:
          case 63:
          case 64:
          case 65:
          case 66:
          case 67:
          case 68:
          }
        }
        while (true)
        {
          i26 += 3;
          break;
          i30 = 0;
          break label102;
          if (zzb(paramT, i26))
          {
            i25 += zztv.zzb(i29, 0.0D);
            continue;
            if (zzb(paramT, i26))
            {
              i25 += zztv.zzb(i29, 0.0F);
              continue;
              if (zzb(paramT, i26))
              {
                i25 += zztv.zzd(i29, zzxj.zzl(paramT, l2));
                continue;
                if (zzb(paramT, i26))
                {
                  i25 += zztv.zze(i29, zzxj.zzl(paramT, l2));
                  continue;
                  if (zzb(paramT, i26))
                  {
                    i25 += zztv.zzh(i29, zzxj.zzk(paramT, l2));
                    continue;
                    if (zzb(paramT, i26))
                    {
                      i25 += zztv.zzg(i29, 0L);
                      continue;
                      if (zzb(paramT, i26))
                      {
                        i25 += zztv.zzk(i29, 0);
                        continue;
                        if (zzb(paramT, i26))
                        {
                          i25 += zztv.zzc(i29, true);
                          continue;
                          if (zzb(paramT, i26))
                          {
                            Object localObject4 = zzxj.zzp(paramT, l2);
                            if ((localObject4 instanceof zzte))
                            {
                              i25 += zztv.zzc(i29, (zzte)localObject4);
                            }
                            else
                            {
                              i25 += zztv.zzc(i29, (String)localObject4);
                              continue;
                              if (zzb(paramT, i26))
                              {
                                i25 += zzwn.zzc(i29, zzxj.zzp(paramT, l2), zzbq(i26));
                                continue;
                                if (zzb(paramT, i26))
                                {
                                  i25 += zztv.zzc(i29, (zzte)zzxj.zzp(paramT, l2));
                                  continue;
                                  if (zzb(paramT, i26))
                                  {
                                    i25 += zztv.zzi(i29, zzxj.zzk(paramT, l2));
                                    continue;
                                    if (zzb(paramT, i26))
                                    {
                                      i25 += zztv.zzm(i29, zzxj.zzk(paramT, l2));
                                      continue;
                                      if (zzb(paramT, i26))
                                      {
                                        i25 += zztv.zzl(i29, 0);
                                        continue;
                                        if (zzb(paramT, i26))
                                        {
                                          i25 += zztv.zzh(i29, 0L);
                                          continue;
                                          if (zzb(paramT, i26))
                                          {
                                            i25 += zztv.zzj(i29, zzxj.zzk(paramT, l2));
                                            continue;
                                            if (zzb(paramT, i26))
                                            {
                                              i25 += zztv.zzf(i29, zzxj.zzl(paramT, l2));
                                              continue;
                                              if (zzb(paramT, i26))
                                              {
                                                i25 += zztv.zzc(i29, (zzvv)zzxj.zzp(paramT, l2), zzbq(i26));
                                                continue;
                                                i25 += zzwn.zzw(i29, zze(paramT, l2), false);
                                                continue;
                                                i25 += zzwn.zzv(i29, zze(paramT, l2), false);
                                                continue;
                                                i25 += zzwn.zzo(i29, zze(paramT, l2), false);
                                                continue;
                                                i25 += zzwn.zzp(i29, zze(paramT, l2), false);
                                                continue;
                                                i25 += zzwn.zzs(i29, zze(paramT, l2), false);
                                                continue;
                                                i25 += zzwn.zzw(i29, zze(paramT, l2), false);
                                                continue;
                                                i25 += zzwn.zzv(i29, zze(paramT, l2), false);
                                                continue;
                                                i25 += zzwn.zzx(i29, zze(paramT, l2), false);
                                                continue;
                                                i25 += zzwn.zzc(i29, zze(paramT, l2));
                                                continue;
                                                i25 += zzwn.zzc(i29, zze(paramT, l2), zzbq(i26));
                                                continue;
                                                i25 += zzwn.zzd(i29, zze(paramT, l2));
                                                continue;
                                                i25 += zzwn.zzt(i29, zze(paramT, l2), false);
                                                continue;
                                                i25 += zzwn.zzr(i29, zze(paramT, l2), false);
                                                continue;
                                                i25 += zzwn.zzv(i29, zze(paramT, l2), false);
                                                continue;
                                                i25 += zzwn.zzw(i29, zze(paramT, l2), false);
                                                continue;
                                                i25 += zzwn.zzu(i29, zze(paramT, l2), false);
                                                continue;
                                                i25 += zzwn.zzq(i29, zze(paramT, l2), false);
                                                continue;
                                                int i44 = zzwn.zzag((List)localUnsafe2.getObject(paramT, l2));
                                                if (i44 > 0)
                                                {
                                                  if (this.zzcba)
                                                    localUnsafe2.putInt(paramT, i30, i44);
                                                  i25 += i44 + (zztv.zzbd(i29) + zztv.zzbf(i44));
                                                  continue;
                                                  int i43 = zzwn.zzaf((List)localUnsafe2.getObject(paramT, l2));
                                                  if (i43 > 0)
                                                  {
                                                    if (this.zzcba)
                                                      localUnsafe2.putInt(paramT, i30, i43);
                                                    i25 += i43 + (zztv.zzbd(i29) + zztv.zzbf(i43));
                                                    continue;
                                                    int i42 = zzwn.zzy((List)localUnsafe2.getObject(paramT, l2));
                                                    if (i42 > 0)
                                                    {
                                                      if (this.zzcba)
                                                        localUnsafe2.putInt(paramT, i30, i42);
                                                      i25 += i42 + (zztv.zzbd(i29) + zztv.zzbf(i42));
                                                      continue;
                                                      int i41 = zzwn.zzz((List)localUnsafe2.getObject(paramT, l2));
                                                      if (i41 > 0)
                                                      {
                                                        if (this.zzcba)
                                                          localUnsafe2.putInt(paramT, i30, i41);
                                                        i25 += i41 + (zztv.zzbd(i29) + zztv.zzbf(i41));
                                                        continue;
                                                        int i40 = zzwn.zzac((List)localUnsafe2.getObject(paramT, l2));
                                                        if (i40 > 0)
                                                        {
                                                          if (this.zzcba)
                                                            localUnsafe2.putInt(paramT, i30, i40);
                                                          i25 += i40 + (zztv.zzbd(i29) + zztv.zzbf(i40));
                                                          continue;
                                                          int i39 = zzwn.zzag((List)localUnsafe2.getObject(paramT, l2));
                                                          if (i39 > 0)
                                                          {
                                                            if (this.zzcba)
                                                              localUnsafe2.putInt(paramT, i30, i39);
                                                            i25 += i39 + (zztv.zzbd(i29) + zztv.zzbf(i39));
                                                            continue;
                                                            int i38 = zzwn.zzaf((List)localUnsafe2.getObject(paramT, l2));
                                                            if (i38 > 0)
                                                            {
                                                              if (this.zzcba)
                                                                localUnsafe2.putInt(paramT, i30, i38);
                                                              i25 += i38 + (zztv.zzbd(i29) + zztv.zzbf(i38));
                                                              continue;
                                                              int i37 = zzwn.zzah((List)localUnsafe2.getObject(paramT, l2));
                                                              if (i37 > 0)
                                                              {
                                                                if (this.zzcba)
                                                                  localUnsafe2.putInt(paramT, i30, i37);
                                                                i25 += i37 + (zztv.zzbd(i29) + zztv.zzbf(i37));
                                                                continue;
                                                                int i36 = zzwn.zzad((List)localUnsafe2.getObject(paramT, l2));
                                                                if (i36 > 0)
                                                                {
                                                                  if (this.zzcba)
                                                                    localUnsafe2.putInt(paramT, i30, i36);
                                                                  i25 += i36 + (zztv.zzbd(i29) + zztv.zzbf(i36));
                                                                  continue;
                                                                  int i35 = zzwn.zzab((List)localUnsafe2.getObject(paramT, l2));
                                                                  if (i35 > 0)
                                                                  {
                                                                    if (this.zzcba)
                                                                      localUnsafe2.putInt(paramT, i30, i35);
                                                                    i25 += i35 + (zztv.zzbd(i29) + zztv.zzbf(i35));
                                                                    continue;
                                                                    int i34 = zzwn.zzaf((List)localUnsafe2.getObject(paramT, l2));
                                                                    if (i34 > 0)
                                                                    {
                                                                      if (this.zzcba)
                                                                        localUnsafe2.putInt(paramT, i30, i34);
                                                                      i25 += i34 + (zztv.zzbd(i29) + zztv.zzbf(i34));
                                                                      continue;
                                                                      int i33 = zzwn.zzag((List)localUnsafe2.getObject(paramT, l2));
                                                                      if (i33 > 0)
                                                                      {
                                                                        if (this.zzcba)
                                                                          localUnsafe2.putInt(paramT, i30, i33);
                                                                        i25 += i33 + (zztv.zzbd(i29) + zztv.zzbf(i33));
                                                                        continue;
                                                                        int i32 = zzwn.zzae((List)localUnsafe2.getObject(paramT, l2));
                                                                        if (i32 > 0)
                                                                        {
                                                                          if (this.zzcba)
                                                                            localUnsafe2.putInt(paramT, i30, i32);
                                                                          i25 += i32 + (zztv.zzbd(i29) + zztv.zzbf(i32));
                                                                          continue;
                                                                          int i31 = zzwn.zzaa((List)localUnsafe2.getObject(paramT, l2));
                                                                          if (i31 > 0)
                                                                          {
                                                                            if (this.zzcba)
                                                                              localUnsafe2.putInt(paramT, i30, i31);
                                                                            i25 += i31 + (zztv.zzbd(i29) + zztv.zzbf(i31));
                                                                            continue;
                                                                            i25 += zzwn.zzd(i29, zze(paramT, l2), zzbq(i26));
                                                                            continue;
                                                                            i25 += this.zzcbi.zzb(i29, zzxj.zzp(paramT, l2), zzbr(i26));
                                                                            continue;
                                                                            if (zza(paramT, i29, i26))
                                                                            {
                                                                              i25 += zztv.zzb(i29, 0.0D);
                                                                              continue;
                                                                              if (zza(paramT, i29, i26))
                                                                              {
                                                                                i25 += zztv.zzb(i29, 0.0F);
                                                                                continue;
                                                                                if (zza(paramT, i29, i26))
                                                                                {
                                                                                  i25 += zztv.zzd(i29, zzi(paramT, l2));
                                                                                  continue;
                                                                                  if (zza(paramT, i29, i26))
                                                                                  {
                                                                                    i25 += zztv.zze(i29, zzi(paramT, l2));
                                                                                    continue;
                                                                                    if (zza(paramT, i29, i26))
                                                                                    {
                                                                                      i25 += zztv.zzh(i29, zzh(paramT, l2));
                                                                                      continue;
                                                                                      if (zza(paramT, i29, i26))
                                                                                      {
                                                                                        i25 += zztv.zzg(i29, 0L);
                                                                                        continue;
                                                                                        if (zza(paramT, i29, i26))
                                                                                        {
                                                                                          i25 += zztv.zzk(i29, 0);
                                                                                          continue;
                                                                                          if (zza(paramT, i29, i26))
                                                                                          {
                                                                                            i25 += zztv.zzc(i29, true);
                                                                                            continue;
                                                                                            if (zza(paramT, i29, i26))
                                                                                            {
                                                                                              Object localObject3 = zzxj.zzp(paramT, l2);
                                                                                              if ((localObject3 instanceof zzte))
                                                                                              {
                                                                                                i25 += zztv.zzc(i29, (zzte)localObject3);
                                                                                              }
                                                                                              else
                                                                                              {
                                                                                                i25 += zztv.zzc(i29, (String)localObject3);
                                                                                                continue;
                                                                                                if (zza(paramT, i29, i26))
                                                                                                {
                                                                                                  i25 += zzwn.zzc(i29, zzxj.zzp(paramT, l2), zzbq(i26));
                                                                                                  continue;
                                                                                                  if (zza(paramT, i29, i26))
                                                                                                  {
                                                                                                    i25 += zztv.zzc(i29, (zzte)zzxj.zzp(paramT, l2));
                                                                                                    continue;
                                                                                                    if (zza(paramT, i29, i26))
                                                                                                    {
                                                                                                      i25 += zztv.zzi(i29, zzh(paramT, l2));
                                                                                                      continue;
                                                                                                      if (zza(paramT, i29, i26))
                                                                                                      {
                                                                                                        i25 += zztv.zzm(i29, zzh(paramT, l2));
                                                                                                        continue;
                                                                                                        if (zza(paramT, i29, i26))
                                                                                                        {
                                                                                                          i25 += zztv.zzl(i29, 0);
                                                                                                          continue;
                                                                                                          if (zza(paramT, i29, i26))
                                                                                                          {
                                                                                                            i25 += zztv.zzh(i29, 0L);
                                                                                                            continue;
                                                                                                            if (zza(paramT, i29, i26))
                                                                                                            {
                                                                                                              i25 += zztv.zzj(i29, zzh(paramT, l2));
                                                                                                              continue;
                                                                                                              if (zza(paramT, i29, i26))
                                                                                                              {
                                                                                                                i25 += zztv.zzf(i29, zzi(paramT, l2));
                                                                                                                continue;
                                                                                                                if (zza(paramT, i29, i26))
                                                                                                                  i25 += zztv.zzc(i29, (zzvv)zzxj.zzp(paramT, l2), zzbq(i26));
                                                                                                              }
                                                                                                            }
                                                                                                          }
                                                                                                        }
                                                                                                      }
                                                                                                    }
                                                                                                  }
                                                                                                }
                                                                                              }
                                                                                            }
                                                                                          }
                                                                                        }
                                                                                      }
                                                                                    }
                                                                                  }
                                                                                }
                                                                              }
                                                                            }
                                                                          }
                                                                        }
                                                                      }
                                                                    }
                                                                  }
                                                                }
                                                              }
                                                            }
                                                          }
                                                        }
                                                      }
                                                    }
                                                  }
                                                }
                                              }
                                            }
                                          }
                                        }
                                      }
                                    }
                                  }
                                }
                              }
                            }
                          }
                        }
                      }
                    }
                  }
                }
              }
            }
          }
        }
      }
      n = i25 + zza(this.zzcbg, paramT);
      return n;
    }
    Unsafe localUnsafe1 = zzcar;
    int i = -1;
    int j = 0;
    int k = 0;
    int m = 0;
    int i1;
    int i2;
    int i3;
    int i4;
    int i5;
    int i6;
    int i7;
    if (k < this.zzcas.length)
    {
      i1 = zzbt(k);
      i2 = this.zzcas[k];
      i3 = (0xFF00000 & i1) >>> 20;
      if (i3 <= 17)
      {
        int i22 = this.zzcas[(k + 2)];
        int i23 = 0xFFFFF & i22;
        int i24 = 1 << (i22 >>> 20);
        if (i23 != i)
        {
          m = localUnsafe1.getInt(paramT, i23);
          i = i23;
        }
        i4 = i;
        i5 = m;
        i6 = i24;
        i7 = i22;
      }
    }
    while (true)
    {
      label2911: long l1 = 0xFFFFF & i1;
      switch (i3)
      {
      default:
      case 0:
      case 1:
      case 2:
      case 3:
      case 4:
      case 5:
      case 6:
      case 7:
      case 8:
      case 9:
      case 10:
      case 11:
      case 12:
      case 13:
      case 14:
      case 15:
      case 16:
      case 17:
      case 18:
      case 19:
      case 20:
      case 21:
      case 22:
      case 23:
      case 24:
      case 25:
      case 26:
      case 27:
      case 28:
      case 29:
      case 30:
      case 31:
      case 32:
      case 33:
      case 34:
      case 35:
      case 36:
      case 37:
      case 38:
      case 39:
      case 40:
      case 41:
      case 42:
      case 43:
      case 44:
      case 45:
      case 46:
      case 47:
      case 48:
      case 49:
      case 50:
      case 51:
      case 52:
      case 53:
      case 54:
      case 55:
      case 56:
      case 57:
      case 58:
      case 59:
      case 60:
      case 61:
      case 62:
      case 63:
      case 64:
      case 65:
      case 66:
      case 67:
      case 68:
      }
      while (true)
      {
        k += 3;
        m = i5;
        i = i4;
        break;
        if ((!this.zzcba) || (i3 < zzui.zzbww.id()) || (i3 > zzui.zzbxj.id()))
          break label5706;
        i7 = 0xFFFFF & this.zzcas[(k + 2)];
        i4 = i;
        i5 = m;
        i6 = 0;
        break label2911;
        if ((i6 & i5) != 0)
        {
          j += zztv.zzb(i2, 0.0D);
          continue;
          if ((i6 & i5) != 0)
          {
            j += zztv.zzb(i2, 0.0F);
            continue;
            if ((i6 & i5) != 0)
            {
              j += zztv.zzd(i2, localUnsafe1.getLong(paramT, l1));
              continue;
              if ((i6 & i5) != 0)
              {
                j += zztv.zze(i2, localUnsafe1.getLong(paramT, l1));
                continue;
                if ((i6 & i5) != 0)
                {
                  j += zztv.zzh(i2, localUnsafe1.getInt(paramT, l1));
                  continue;
                  if ((i6 & i5) != 0)
                  {
                    j += zztv.zzg(i2, 0L);
                    continue;
                    if ((i6 & i5) != 0)
                    {
                      j += zztv.zzk(i2, 0);
                      continue;
                      if ((i6 & i5) != 0)
                      {
                        j += zztv.zzc(i2, true);
                        continue;
                        if ((i6 & i5) != 0)
                        {
                          Object localObject2 = localUnsafe1.getObject(paramT, l1);
                          if ((localObject2 instanceof zzte))
                          {
                            j += zztv.zzc(i2, (zzte)localObject2);
                          }
                          else
                          {
                            j += zztv.zzc(i2, (String)localObject2);
                            continue;
                            if ((i6 & i5) != 0)
                            {
                              j += zzwn.zzc(i2, localUnsafe1.getObject(paramT, l1), zzbq(k));
                              continue;
                              if ((i6 & i5) != 0)
                              {
                                j += zztv.zzc(i2, (zzte)localUnsafe1.getObject(paramT, l1));
                                continue;
                                if ((i6 & i5) != 0)
                                {
                                  j += zztv.zzi(i2, localUnsafe1.getInt(paramT, l1));
                                  continue;
                                  if ((i6 & i5) != 0)
                                  {
                                    j += zztv.zzm(i2, localUnsafe1.getInt(paramT, l1));
                                    continue;
                                    if ((i6 & i5) != 0)
                                    {
                                      j += zztv.zzl(i2, 0);
                                      continue;
                                      if ((i6 & i5) != 0)
                                      {
                                        j += zztv.zzh(i2, 0L);
                                        continue;
                                        if ((i6 & i5) != 0)
                                        {
                                          j += zztv.zzj(i2, localUnsafe1.getInt(paramT, l1));
                                          continue;
                                          if ((i6 & i5) != 0)
                                          {
                                            j += zztv.zzf(i2, localUnsafe1.getLong(paramT, l1));
                                            continue;
                                            if ((i6 & i5) != 0)
                                            {
                                              j += zztv.zzc(i2, (zzvv)localUnsafe1.getObject(paramT, l1), zzbq(k));
                                              continue;
                                              j += zzwn.zzw(i2, (List)localUnsafe1.getObject(paramT, l1), false);
                                              continue;
                                              j += zzwn.zzv(i2, (List)localUnsafe1.getObject(paramT, l1), false);
                                              continue;
                                              j += zzwn.zzo(i2, (List)localUnsafe1.getObject(paramT, l1), false);
                                              continue;
                                              j += zzwn.zzp(i2, (List)localUnsafe1.getObject(paramT, l1), false);
                                              continue;
                                              j += zzwn.zzs(i2, (List)localUnsafe1.getObject(paramT, l1), false);
                                              continue;
                                              j += zzwn.zzw(i2, (List)localUnsafe1.getObject(paramT, l1), false);
                                              continue;
                                              j += zzwn.zzv(i2, (List)localUnsafe1.getObject(paramT, l1), false);
                                              continue;
                                              j += zzwn.zzx(i2, (List)localUnsafe1.getObject(paramT, l1), false);
                                              continue;
                                              j += zzwn.zzc(i2, (List)localUnsafe1.getObject(paramT, l1));
                                              continue;
                                              j += zzwn.zzc(i2, (List)localUnsafe1.getObject(paramT, l1), zzbq(k));
                                              continue;
                                              j += zzwn.zzd(i2, (List)localUnsafe1.getObject(paramT, l1));
                                              continue;
                                              j += zzwn.zzt(i2, (List)localUnsafe1.getObject(paramT, l1), false);
                                              continue;
                                              j += zzwn.zzr(i2, (List)localUnsafe1.getObject(paramT, l1), false);
                                              continue;
                                              j += zzwn.zzv(i2, (List)localUnsafe1.getObject(paramT, l1), false);
                                              continue;
                                              j += zzwn.zzw(i2, (List)localUnsafe1.getObject(paramT, l1), false);
                                              continue;
                                              j += zzwn.zzu(i2, (List)localUnsafe1.getObject(paramT, l1), false);
                                              continue;
                                              j += zzwn.zzq(i2, (List)localUnsafe1.getObject(paramT, l1), false);
                                              continue;
                                              int i21 = zzwn.zzag((List)localUnsafe1.getObject(paramT, l1));
                                              if (i21 > 0)
                                              {
                                                if (this.zzcba)
                                                  localUnsafe1.putInt(paramT, i7, i21);
                                                j += i21 + (zztv.zzbd(i2) + zztv.zzbf(i21));
                                                continue;
                                                int i20 = zzwn.zzaf((List)localUnsafe1.getObject(paramT, l1));
                                                if (i20 > 0)
                                                {
                                                  if (this.zzcba)
                                                    localUnsafe1.putInt(paramT, i7, i20);
                                                  j += i20 + (zztv.zzbd(i2) + zztv.zzbf(i20));
                                                  continue;
                                                  int i19 = zzwn.zzy((List)localUnsafe1.getObject(paramT, l1));
                                                  if (i19 > 0)
                                                  {
                                                    if (this.zzcba)
                                                      localUnsafe1.putInt(paramT, i7, i19);
                                                    j += i19 + (zztv.zzbd(i2) + zztv.zzbf(i19));
                                                    continue;
                                                    int i18 = zzwn.zzz((List)localUnsafe1.getObject(paramT, l1));
                                                    if (i18 > 0)
                                                    {
                                                      if (this.zzcba)
                                                        localUnsafe1.putInt(paramT, i7, i18);
                                                      j += i18 + (zztv.zzbd(i2) + zztv.zzbf(i18));
                                                      continue;
                                                      int i17 = zzwn.zzac((List)localUnsafe1.getObject(paramT, l1));
                                                      if (i17 > 0)
                                                      {
                                                        if (this.zzcba)
                                                          localUnsafe1.putInt(paramT, i7, i17);
                                                        j += i17 + (zztv.zzbd(i2) + zztv.zzbf(i17));
                                                        continue;
                                                        int i16 = zzwn.zzag((List)localUnsafe1.getObject(paramT, l1));
                                                        if (i16 > 0)
                                                        {
                                                          if (this.zzcba)
                                                            localUnsafe1.putInt(paramT, i7, i16);
                                                          j += i16 + (zztv.zzbd(i2) + zztv.zzbf(i16));
                                                          continue;
                                                          int i15 = zzwn.zzaf((List)localUnsafe1.getObject(paramT, l1));
                                                          if (i15 > 0)
                                                          {
                                                            if (this.zzcba)
                                                              localUnsafe1.putInt(paramT, i7, i15);
                                                            j += i15 + (zztv.zzbd(i2) + zztv.zzbf(i15));
                                                            continue;
                                                            int i14 = zzwn.zzah((List)localUnsafe1.getObject(paramT, l1));
                                                            if (i14 > 0)
                                                            {
                                                              if (this.zzcba)
                                                                localUnsafe1.putInt(paramT, i7, i14);
                                                              j += i14 + (zztv.zzbd(i2) + zztv.zzbf(i14));
                                                              continue;
                                                              int i13 = zzwn.zzad((List)localUnsafe1.getObject(paramT, l1));
                                                              if (i13 > 0)
                                                              {
                                                                if (this.zzcba)
                                                                  localUnsafe1.putInt(paramT, i7, i13);
                                                                j += i13 + (zztv.zzbd(i2) + zztv.zzbf(i13));
                                                                continue;
                                                                int i12 = zzwn.zzab((List)localUnsafe1.getObject(paramT, l1));
                                                                if (i12 > 0)
                                                                {
                                                                  if (this.zzcba)
                                                                    localUnsafe1.putInt(paramT, i7, i12);
                                                                  j += i12 + (zztv.zzbd(i2) + zztv.zzbf(i12));
                                                                  continue;
                                                                  int i11 = zzwn.zzaf((List)localUnsafe1.getObject(paramT, l1));
                                                                  if (i11 > 0)
                                                                  {
                                                                    if (this.zzcba)
                                                                      localUnsafe1.putInt(paramT, i7, i11);
                                                                    j += i11 + (zztv.zzbd(i2) + zztv.zzbf(i11));
                                                                    continue;
                                                                    int i10 = zzwn.zzag((List)localUnsafe1.getObject(paramT, l1));
                                                                    if (i10 > 0)
                                                                    {
                                                                      if (this.zzcba)
                                                                        localUnsafe1.putInt(paramT, i7, i10);
                                                                      j += i10 + (zztv.zzbd(i2) + zztv.zzbf(i10));
                                                                      continue;
                                                                      int i9 = zzwn.zzae((List)localUnsafe1.getObject(paramT, l1));
                                                                      if (i9 > 0)
                                                                      {
                                                                        if (this.zzcba)
                                                                          localUnsafe1.putInt(paramT, i7, i9);
                                                                        j += i9 + (zztv.zzbd(i2) + zztv.zzbf(i9));
                                                                        continue;
                                                                        int i8 = zzwn.zzaa((List)localUnsafe1.getObject(paramT, l1));
                                                                        if (i8 > 0)
                                                                        {
                                                                          if (this.zzcba)
                                                                            localUnsafe1.putInt(paramT, i7, i8);
                                                                          j += i8 + (zztv.zzbd(i2) + zztv.zzbf(i8));
                                                                          continue;
                                                                          j += zzwn.zzd(i2, (List)localUnsafe1.getObject(paramT, l1), zzbq(k));
                                                                          continue;
                                                                          j += this.zzcbi.zzb(i2, localUnsafe1.getObject(paramT, l1), zzbr(k));
                                                                          continue;
                                                                          if (zza(paramT, i2, k))
                                                                          {
                                                                            j += zztv.zzb(i2, 0.0D);
                                                                            continue;
                                                                            if (zza(paramT, i2, k))
                                                                            {
                                                                              j += zztv.zzb(i2, 0.0F);
                                                                              continue;
                                                                              if (zza(paramT, i2, k))
                                                                              {
                                                                                j += zztv.zzd(i2, zzi(paramT, l1));
                                                                                continue;
                                                                                if (zza(paramT, i2, k))
                                                                                {
                                                                                  j += zztv.zze(i2, zzi(paramT, l1));
                                                                                  continue;
                                                                                  if (zza(paramT, i2, k))
                                                                                  {
                                                                                    j += zztv.zzh(i2, zzh(paramT, l1));
                                                                                    continue;
                                                                                    if (zza(paramT, i2, k))
                                                                                    {
                                                                                      j += zztv.zzg(i2, 0L);
                                                                                      continue;
                                                                                      if (zza(paramT, i2, k))
                                                                                      {
                                                                                        j += zztv.zzk(i2, 0);
                                                                                        continue;
                                                                                        if (zza(paramT, i2, k))
                                                                                        {
                                                                                          j += zztv.zzc(i2, true);
                                                                                          continue;
                                                                                          if (zza(paramT, i2, k))
                                                                                          {
                                                                                            Object localObject1 = localUnsafe1.getObject(paramT, l1);
                                                                                            if ((localObject1 instanceof zzte))
                                                                                            {
                                                                                              j += zztv.zzc(i2, (zzte)localObject1);
                                                                                            }
                                                                                            else
                                                                                            {
                                                                                              j += zztv.zzc(i2, (String)localObject1);
                                                                                              continue;
                                                                                              if (zza(paramT, i2, k))
                                                                                              {
                                                                                                j += zzwn.zzc(i2, localUnsafe1.getObject(paramT, l1), zzbq(k));
                                                                                                continue;
                                                                                                if (zza(paramT, i2, k))
                                                                                                {
                                                                                                  j += zztv.zzc(i2, (zzte)localUnsafe1.getObject(paramT, l1));
                                                                                                  continue;
                                                                                                  if (zza(paramT, i2, k))
                                                                                                  {
                                                                                                    j += zztv.zzi(i2, zzh(paramT, l1));
                                                                                                    continue;
                                                                                                    if (zza(paramT, i2, k))
                                                                                                    {
                                                                                                      j += zztv.zzm(i2, zzh(paramT, l1));
                                                                                                      continue;
                                                                                                      if (zza(paramT, i2, k))
                                                                                                      {
                                                                                                        j += zztv.zzl(i2, 0);
                                                                                                        continue;
                                                                                                        if (zza(paramT, i2, k))
                                                                                                        {
                                                                                                          j += zztv.zzh(i2, 0L);
                                                                                                          continue;
                                                                                                          if (zza(paramT, i2, k))
                                                                                                          {
                                                                                                            j += zztv.zzj(i2, zzh(paramT, l1));
                                                                                                            continue;
                                                                                                            if (zza(paramT, i2, k))
                                                                                                            {
                                                                                                              j += zztv.zzf(i2, zzi(paramT, l1));
                                                                                                              continue;
                                                                                                              if (zza(paramT, i2, k))
                                                                                                                j += zztv.zzc(i2, (zzvv)localUnsafe1.getObject(paramT, l1), zzbq(k));
                                                                                                            }
                                                                                                          }
                                                                                                        }
                                                                                                      }
                                                                                                    }
                                                                                                  }
                                                                                                }
                                                                                              }
                                                                                            }
                                                                                          }
                                                                                        }
                                                                                      }
                                                                                    }
                                                                                  }
                                                                                }
                                                                              }
                                                                            }
                                                                          }
                                                                        }
                                                                      }
                                                                    }
                                                                  }
                                                                }
                                                              }
                                                            }
                                                          }
                                                        }
                                                      }
                                                    }
                                                  }
                                                }
                                              }
                                            }
                                          }
                                        }
                                      }
                                    }
                                  }
                                }
                              }
                            }
                          }
                        }
                      }
                    }
                  }
                }
              }
            }
          }
        }
      }
      n = j + zza(this.zzcbg, paramT);
      if (!this.zzcax)
        break;
      return n + this.zzcbh.zzw(paramT).zzvx();
      label5706: i4 = i;
      i5 = m;
      i6 = 0;
      i7 = 0;
    }
  }

  public final boolean zzaj(T paramT)
  {
    int i = 0;
    int j = -1;
    int k = 0;
    int m;
    int n;
    int i1;
    int i11;
    int i3;
    int i2;
    int i4;
    if (i < this.zzcbc)
    {
      m = this.zzcbb[i];
      n = this.zzcas[m];
      i1 = zzbt(m);
      if (this.zzcaz)
        break label561;
      int i9 = this.zzcas[(m + 2)];
      int i10 = i9 & 0xFFFFF;
      i11 = 1 << (i9 >>> 20);
      if (i10 == j)
        break label547;
      i3 = zzcar.getInt(paramT, i10);
      i2 = i10;
      i4 = i11;
    }
    while (true)
    {
      int i5;
      if ((0x10000000 & i1) != 0)
      {
        i5 = 1;
        label112: if ((i5 == 0) || (zza(paramT, m, i3, i4)))
          break label139;
      }
      label139: label348: 
      do
      {
        return false;
        i5 = 0;
        break label112;
        switch ((0xFF00000 & i1) >>> 20)
        {
        default:
        case 9:
        case 17:
        case 27:
        case 49:
        case 60:
        case 68:
        case 50:
        }
        while (true)
        {
          i++;
          k = i3;
          j = i2;
          break;
          if ((zza(paramT, m, i3, i4)) && (!zza(paramT, i1, zzbq(m))))
          {
            return false;
            List localList = (List)zzxj.zzp(paramT, i1 & 0xFFFFF);
            int i8;
            if (!localList.isEmpty())
            {
              zzwl localzzwl2 = zzbq(m);
              i8 = 0;
              if (i8 < localList.size())
                if (localzzwl2.zzaj(localList.get(i8)));
            }
            for (int i7 = 0; ; i7 = 1)
            {
              if (i7 != 0)
                break label348;
              return false;
              i8++;
              break;
            }
            continue;
            if ((zza(paramT, n, m)) && (!zza(paramT, i1, zzbq(m))))
            {
              return false;
              Map localMap = this.zzcbi.zzad(zzxj.zzp(paramT, i1 & 0xFFFFF));
              if (!localMap.isEmpty())
              {
                Object localObject1 = zzbr(m);
                if (this.zzcbi.zzah(localObject1).zzcam.zzyv() == zzxx.zzcem)
                {
                  zzwl localzzwl1 = null;
                  Iterator localIterator = localMap.values().iterator();
                  Object localObject2;
                  do
                  {
                    if (!localIterator.hasNext())
                      break;
                    localObject2 = localIterator.next();
                    if (localzzwl1 == null)
                      localzzwl1 = zzwh.zzxt().zzi(localObject2.getClass());
                  }
                  while (localzzwl1.zzaj(localObject2));
                }
              }
              for (int i6 = 0; i6 == 0; i6 = 1)
                return false;
            }
          }
        }
      }
      while ((this.zzcax) && (!this.zzcbh.zzw(paramT).isInitialized()));
      return true;
      label547: i4 = i11;
      i2 = j;
      i3 = k;
      continue;
      label561: i2 = j;
      i3 = k;
      i4 = 0;
    }
  }

  public final void zzd(T paramT1, T paramT2)
  {
    if (paramT2 == null)
      throw new NullPointerException();
    int i = 0;
    if (i < this.zzcas.length)
    {
      int j = zzbt(i);
      long l = 0xFFFFF & j;
      int k = this.zzcas[i];
      switch ((j & 0xFF00000) >>> 20)
      {
      default:
      case 0:
      case 1:
      case 2:
      case 3:
      case 4:
      case 5:
      case 6:
      case 7:
      case 8:
      case 9:
      case 10:
      case 11:
      case 12:
      case 13:
      case 14:
      case 15:
      case 16:
      case 17:
      case 18:
      case 19:
      case 20:
      case 21:
      case 22:
      case 23:
      case 24:
      case 25:
      case 26:
      case 27:
      case 28:
      case 29:
      case 30:
      case 31:
      case 32:
      case 33:
      case 34:
      case 35:
      case 36:
      case 37:
      case 38:
      case 39:
      case 40:
      case 41:
      case 42:
      case 43:
      case 44:
      case 45:
      case 46:
      case 47:
      case 48:
      case 49:
      case 50:
      case 51:
      case 52:
      case 53:
      case 54:
      case 55:
      case 56:
      case 57:
      case 58:
      case 59:
      case 60:
      case 61:
      case 62:
      case 63:
      case 64:
      case 65:
      case 66:
      case 67:
      case 68:
      }
      while (true)
      {
        i += 3;
        break;
        if (zzb(paramT2, i))
        {
          zzxj.zza(paramT1, l, zzxj.zzo(paramT2, l));
          zzc(paramT1, i);
          continue;
          if (zzb(paramT2, i))
          {
            zzxj.zza(paramT1, l, zzxj.zzn(paramT2, l));
            zzc(paramT1, i);
            continue;
            if (zzb(paramT2, i))
            {
              zzxj.zza(paramT1, l, zzxj.zzl(paramT2, l));
              zzc(paramT1, i);
              continue;
              if (zzb(paramT2, i))
              {
                zzxj.zza(paramT1, l, zzxj.zzl(paramT2, l));
                zzc(paramT1, i);
                continue;
                if (zzb(paramT2, i))
                {
                  zzxj.zzb(paramT1, l, zzxj.zzk(paramT2, l));
                  zzc(paramT1, i);
                  continue;
                  if (zzb(paramT2, i))
                  {
                    zzxj.zza(paramT1, l, zzxj.zzl(paramT2, l));
                    zzc(paramT1, i);
                    continue;
                    if (zzb(paramT2, i))
                    {
                      zzxj.zzb(paramT1, l, zzxj.zzk(paramT2, l));
                      zzc(paramT1, i);
                      continue;
                      if (zzb(paramT2, i))
                      {
                        zzxj.zza(paramT1, l, zzxj.zzm(paramT2, l));
                        zzc(paramT1, i);
                        continue;
                        if (zzb(paramT2, i))
                        {
                          zzxj.zza(paramT1, l, zzxj.zzp(paramT2, l));
                          zzc(paramT1, i);
                          continue;
                          zza(paramT1, paramT2, i);
                          continue;
                          if (zzb(paramT2, i))
                          {
                            zzxj.zza(paramT1, l, zzxj.zzp(paramT2, l));
                            zzc(paramT1, i);
                            continue;
                            if (zzb(paramT2, i))
                            {
                              zzxj.zzb(paramT1, l, zzxj.zzk(paramT2, l));
                              zzc(paramT1, i);
                              continue;
                              if (zzb(paramT2, i))
                              {
                                zzxj.zzb(paramT1, l, zzxj.zzk(paramT2, l));
                                zzc(paramT1, i);
                                continue;
                                if (zzb(paramT2, i))
                                {
                                  zzxj.zzb(paramT1, l, zzxj.zzk(paramT2, l));
                                  zzc(paramT1, i);
                                  continue;
                                  if (zzb(paramT2, i))
                                  {
                                    zzxj.zza(paramT1, l, zzxj.zzl(paramT2, l));
                                    zzc(paramT1, i);
                                    continue;
                                    if (zzb(paramT2, i))
                                    {
                                      zzxj.zzb(paramT1, l, zzxj.zzk(paramT2, l));
                                      zzc(paramT1, i);
                                      continue;
                                      if (zzb(paramT2, i))
                                      {
                                        zzxj.zza(paramT1, l, zzxj.zzl(paramT2, l));
                                        zzc(paramT1, i);
                                        continue;
                                        zza(paramT1, paramT2, i);
                                        continue;
                                        this.zzcbf.zza(paramT1, paramT2, l);
                                        continue;
                                        zzwn.zza(this.zzcbi, paramT1, paramT2, l);
                                        continue;
                                        if (zza(paramT2, k, i))
                                        {
                                          zzxj.zza(paramT1, l, zzxj.zzp(paramT2, l));
                                          zzb(paramT1, k, i);
                                          continue;
                                          zzb(paramT1, paramT2, i);
                                          continue;
                                          if (zza(paramT2, k, i))
                                          {
                                            zzxj.zza(paramT1, l, zzxj.zzp(paramT2, l));
                                            zzb(paramT1, k, i);
                                            continue;
                                            zzb(paramT1, paramT2, i);
                                          }
                                        }
                                      }
                                    }
                                  }
                                }
                              }
                            }
                          }
                        }
                      }
                    }
                  }
                }
              }
            }
          }
        }
      }
    }
    if (!this.zzcaz)
    {
      zzwn.zza(this.zzcbg, paramT1, paramT2);
      if (this.zzcax)
        zzwn.zza(this.zzcbh, paramT1, paramT2);
    }
  }

  public final void zzy(T paramT)
  {
    for (int i = this.zzcbc; i < this.zzcbd; i++)
    {
      long l = 0xFFFFF & zzbt(this.zzcbb[i]);
      Object localObject = zzxj.zzp(paramT, l);
      if (localObject != null)
        zzxj.zza(paramT, l, this.zzcbi.zzaf(localObject));
    }
    int j = this.zzcbb.length;
    for (int k = this.zzcbd; k < j; k++)
      this.zzcbf.zzb(paramT, this.zzcbb[k]);
    this.zzcbg.zzy(paramT);
    if (this.zzcax)
      this.zzcbh.zzy(paramT);
  }
}

/* Location:           E:\Study\Tools\apktool2_2\dex2jar-0.0.9.15\classes_viber_2_dex2jar.jar
 * Qualified Name:     com.google.android.gms.internal.measurement.zzvz
 * JD-Core Version:    0.6.2
 */