package com.viber.common.a;

public class d
{
  // ERROR //
  public static void a(java.io.File paramFile)
  {
    // Byte code:
    //   0: aconst_null
    //   1: astore_1
    //   2: new 10	java/io/BufferedWriter
    //   5: dup
    //   6: new 12	java/io/FileWriter
    //   9: dup
    //   10: aload_0
    //   11: invokespecial 15	java/io/FileWriter:<init>	(Ljava/io/File;)V
    //   14: invokespecial 18	java/io/BufferedWriter:<init>	(Ljava/io/Writer;)V
    //   17: astore_2
    //   18: new 20	java/lang/ProcessBuilder
    //   21: dup
    //   22: ldc 22
    //   24: ldc 24
    //   26: invokevirtual 30	java/lang/String:split	(Ljava/lang/String;)[Ljava/lang/String;
    //   29: invokespecial 33	java/lang/ProcessBuilder:<init>	([Ljava/lang/String;)V
    //   32: astore_3
    //   33: aload_3
    //   34: iconst_1
    //   35: invokevirtual 37	java/lang/ProcessBuilder:redirectErrorStream	(Z)Ljava/lang/ProcessBuilder;
    //   38: pop
    //   39: new 39	java/io/BufferedReader
    //   42: dup
    //   43: new 41	java/io/InputStreamReader
    //   46: dup
    //   47: aload_3
    //   48: invokevirtual 45	java/lang/ProcessBuilder:start	()Ljava/lang/Process;
    //   51: invokevirtual 51	java/lang/Process:getInputStream	()Ljava/io/InputStream;
    //   54: invokespecial 54	java/io/InputStreamReader:<init>	(Ljava/io/InputStream;)V
    //   57: invokespecial 57	java/io/BufferedReader:<init>	(Ljava/io/Reader;)V
    //   60: astore 10
    //   62: sipush 8192
    //   65: newarray char
    //   67: astore 11
    //   69: aload 10
    //   71: aload 11
    //   73: iconst_0
    //   74: aload 11
    //   76: arraylength
    //   77: invokevirtual 61	java/io/BufferedReader:read	([CII)I
    //   80: istore 12
    //   82: iload 12
    //   84: iconst_m1
    //   85: if_icmpeq +22 -> 107
    //   88: aload_2
    //   89: aload 11
    //   91: iconst_0
    //   92: iload 12
    //   94: invokevirtual 65	java/io/BufferedWriter:write	([CII)V
    //   97: goto -28 -> 69
    //   100: astore 7
    //   102: aload_2
    //   103: invokevirtual 69	java/io/BufferedWriter:close	()V
    //   106: return
    //   107: aload_2
    //   108: invokevirtual 72	java/io/BufferedWriter:flush	()V
    //   111: aload_2
    //   112: invokevirtual 69	java/io/BufferedWriter:close	()V
    //   115: return
    //   116: astore 13
    //   118: return
    //   119: astore 5
    //   121: aload_1
    //   122: invokevirtual 69	java/io/BufferedWriter:close	()V
    //   125: aload 5
    //   127: athrow
    //   128: astore 8
    //   130: return
    //   131: astore 6
    //   133: goto -8 -> 125
    //   136: astore 4
    //   138: aload_2
    //   139: astore_1
    //   140: aload 4
    //   142: astore 5
    //   144: goto -23 -> 121
    //   147: astore 14
    //   149: aconst_null
    //   150: astore_2
    //   151: goto -49 -> 102
    //
    // Exception table:
    //   from	to	target	type
    //   18	69	100	java/io/IOException
    //   69	82	100	java/io/IOException
    //   88	97	100	java/io/IOException
    //   107	111	100	java/io/IOException
    //   111	115	116	java/io/IOException
    //   2	18	119	finally
    //   102	106	128	java/io/IOException
    //   121	125	131	java/io/IOException
    //   18	69	136	finally
    //   69	82	136	finally
    //   88	97	136	finally
    //   107	111	136	finally
    //   2	18	147	java/io/IOException
  }
}

/* Location:           E:\Study\Tools\apktool2_2\dex2jar-0.0.9.15\classes_viber_2_dex2jar.jar
 * Qualified Name:     com.viber.common.a.d
 * JD-Core Version:    0.6.2
 */