package com.yandex.metrica.impl.ob;

public class mf
{
  // ERROR //
  public java.util.List<me> a(java.lang.String paramString)
  {
    // Byte code:
    //   0: new 16	java/util/ArrayList
    //   3: dup
    //   4: invokespecial 17	java/util/ArrayList:<init>	()V
    //   7: astore_2
    //   8: new 19	com/yandex/metrica/impl/ob/nz$a
    //   11: dup
    //   12: aload_1
    //   13: invokespecial 22	com/yandex/metrica/impl/ob/nz$a:<init>	(Ljava/lang/String;)V
    //   16: ldc 24
    //   18: invokevirtual 28	com/yandex/metrica/impl/ob/nz$a:optJSONArray	(Ljava/lang/String;)Lorg/json/JSONArray;
    //   21: astore 4
    //   23: aload 4
    //   25: ifnull +153 -> 178
    //   28: iconst_0
    //   29: istore 5
    //   31: iload 5
    //   33: aload 4
    //   35: invokevirtual 34	org/json/JSONArray:length	()I
    //   38: if_icmpge +140 -> 178
    //   41: aload 4
    //   43: iload 5
    //   45: invokevirtual 38	org/json/JSONArray:getJSONObject	(I)Lorg/json/JSONObject;
    //   48: astore 6
    //   50: aload 6
    //   52: ldc 40
    //   54: invokevirtual 46	org/json/JSONObject:optString	(Ljava/lang/String;)Ljava/lang/String;
    //   57: astore 7
    //   59: aload 7
    //   61: invokestatic 52	android/text/TextUtils:isEmpty	(Ljava/lang/CharSequence;)Z
    //   64: ifne +107 -> 171
    //   67: aload 6
    //   69: ldc 54
    //   71: invokevirtual 55	org/json/JSONObject:optJSONArray	(Ljava/lang/String;)Lorg/json/JSONArray;
    //   74: astore 8
    //   76: new 16	java/util/ArrayList
    //   79: dup
    //   80: invokespecial 17	java/util/ArrayList:<init>	()V
    //   83: astore 9
    //   85: aload 8
    //   87: ifnull +58 -> 145
    //   90: iconst_0
    //   91: istore 11
    //   93: aload 8
    //   95: invokevirtual 34	org/json/JSONArray:length	()I
    //   98: istore 12
    //   100: iload 11
    //   102: iload 12
    //   104: if_icmpge +41 -> 145
    //   107: aload 8
    //   109: iload 11
    //   111: invokevirtual 38	org/json/JSONArray:getJSONObject	(I)Lorg/json/JSONObject;
    //   114: ldc 40
    //   116: invokevirtual 46	org/json/JSONObject:optString	(Ljava/lang/String;)Ljava/lang/String;
    //   119: astore 14
    //   121: aload 14
    //   123: invokestatic 52	android/text/TextUtils:isEmpty	(Ljava/lang/CharSequence;)Z
    //   126: ifne +13 -> 139
    //   129: aload 9
    //   131: aload 14
    //   133: invokeinterface 61 2 0
    //   138: pop
    //   139: iinc 11 1
    //   142: goto -49 -> 93
    //   145: aload 9
    //   147: invokestatic 66	com/yandex/metrica/impl/bw:a	(Ljava/util/Collection;)Z
    //   150: ifne +21 -> 171
    //   153: aload_2
    //   154: new 68	com/yandex/metrica/impl/ob/me
    //   157: dup
    //   158: aload 7
    //   160: aload 9
    //   162: invokespecial 71	com/yandex/metrica/impl/ob/me:<init>	(Ljava/lang/String;Ljava/util/List;)V
    //   165: invokeinterface 61 2 0
    //   170: pop
    //   171: iinc 5 1
    //   174: goto -143 -> 31
    //   177: astore_3
    //   178: aload_2
    //   179: areturn
    //   180: astore 13
    //   182: goto -43 -> 139
    //
    // Exception table:
    //   from	to	target	type
    //   8	23	177	org/json/JSONException
    //   31	85	177	org/json/JSONException
    //   93	100	177	org/json/JSONException
    //   107	139	177	org/json/JSONException
    //   145	171	177	org/json/JSONException
    //   107	139	180	java/lang/Exception
  }
}

/* Location:           E:\Study\Tools\apktool2_2\dex2jar-0.0.9.15\classes_viber_4_dex2jar.jar
 * Qualified Name:     com.yandex.metrica.impl.ob.mf
 * JD-Core Version:    0.6.2
 */