package com.yandex.metrica.impl.ob;

import android.content.ComponentName;
import android.content.Context;
import android.content.Intent;
import android.content.ServiceConnection;
import android.net.Uri;
import android.os.Handler;
import android.os.IBinder;
import android.os.Looper;
import android.os.Message;
import android.util.Base64;
import com.yandex.metrica.MetricaService;
import com.yandex.metrica.c;
import java.io.IOException;
import java.io.OutputStream;
import java.net.ServerSocket;
import java.net.Socket;
import java.util.HashMap;
import java.util.Map;
import java.util.concurrent.TimeUnit;
import org.json.JSONException;

public class mk
  implements Runnable
{
  private final ServiceConnection a = new ServiceConnection()
  {
    public void onServiceConnected(ComponentName paramAnonymousComponentName, IBinder paramAnonymousIBinder)
    {
    }

    public void onServiceDisconnected(ComponentName paramAnonymousComponentName)
    {
    }
  };
  private final Handler b = new Handler(Looper.getMainLooper())
  {
    public void handleMessage(Message paramAnonymousMessage)
    {
      super.handleMessage(paramAnonymousMessage);
      switch (paramAnonymousMessage.what)
      {
      default:
        return;
      case 100:
      }
      mk.this.e();
      try
      {
        mk.b(mk.this).unbindService(mk.a(mk.this));
        return;
      }
      catch (Exception localException)
      {
        mi.a(mk.b(mk.this)).reportEvent("socket_unbind_has_thrown_exception");
      }
    }
  };
  private HashMap<String, d> c = new HashMap()
  {
  };
  private final Context d;
  private boolean e;
  private ServerSocket f;
  private final mj g = new mj();
  private mn h;
  private Thread i;

  public mk(Context paramContext)
  {
    this.d = paramContext;
    h.a().a(this, s.class, l.a(new k()
    {
      public void a(s paramAnonymouss)
      {
        mk.d(mk.this).a(paramAnonymouss.a);
      }
    }).a(new i()
    {
      public boolean a(s paramAnonymouss)
      {
        return !mk.b(mk.this).getPackageName().equals(paramAnonymouss.b);
      }
    }).a());
    h.a().a(this, o.class, l.a(new k()
    {
      public void a(o paramAnonymouso)
      {
        mk.d(mk.this).b(paramAnonymouso.a);
      }
    }).a());
    h.a().a(this, m.class, l.a(new k()
    {
      public void a(m paramAnonymousm)
      {
        mk.d(mk.this).c(paramAnonymousm.a);
      }
    }).a());
    h.a().a(this, n.class, l.a(new k()
    {
      public void a(n paramAnonymousn)
      {
        mk.d(mk.this).d(paramAnonymousn.a);
      }
    }).a());
    h.a().a(this, q.class, l.a(new k()
    {
      public void a(q paramAnonymousq)
      {
        mk.this.a(paramAnonymousq.a);
        mk.this.c();
      }
    }).a());
  }

  private void a(String paramString1, String paramString2)
  {
    HashMap localHashMap = new HashMap();
    localHashMap.put("uri", paramString2);
    mi.a(this.d).reportEvent("socket_".concat(String.valueOf(paramString1)), localHashMap);
  }

  private static HashMap<String, Object> c(int paramInt)
  {
    HashMap localHashMap = new HashMap();
    localHashMap.put("port", String.valueOf(paramInt));
    return localHashMap;
  }

  ServerSocket a(int paramInt)
    throws IOException
  {
    return new ServerSocket(paramInt);
  }

  public void a()
  {
    if (this.e)
    {
      b();
      this.b.sendMessageDelayed(this.b.obtainMessage(100), TimeUnit.SECONDS.toMillis(this.h.a));
    }
  }

  void a(mn parammn)
  {
    this.h = parammn;
  }

  public void b()
  {
    this.b.removeMessages(100);
  }

  public void c()
  {
    try
    {
      if ((this.e != true) && (this.h != null))
      {
        this.e = true;
        d();
        this.i = od.a("YMM-IB", this);
        this.i.start();
      }
      return;
    }
    finally
    {
      localObject = finally;
      throw localObject;
    }
  }

  void d()
  {
    Intent localIntent = new Intent(this.d, MetricaService.class);
    localIntent.setAction("com.yandex.metrica.ACTION_BIND_TO_LOCAL_SERVER");
    try
    {
      if (!this.d.bindService(localIntent, this.a, 1))
        mi.a(this.d).reportEvent("socket_bind_has_failed");
      return;
    }
    catch (Exception localException)
    {
      mi.a(this.d).reportEvent("socket_bind_has_thrown_exception");
    }
  }

  // ERROR //
  public void e()
  {
    // Byte code:
    //   0: aload_0
    //   1: monitorenter
    //   2: aload_0
    //   3: iconst_0
    //   4: putfield 171	com/yandex/metrica/impl/ob/mk:e	Z
    //   7: aload_0
    //   8: getfield 213	com/yandex/metrica/impl/ob/mk:i	Ljava/lang/Thread;
    //   11: ifnull +15 -> 26
    //   14: aload_0
    //   15: getfield 213	com/yandex/metrica/impl/ob/mk:i	Ljava/lang/Thread;
    //   18: invokevirtual 249	java/lang/Thread:interrupt	()V
    //   21: aload_0
    //   22: aconst_null
    //   23: putfield 213	com/yandex/metrica/impl/ob/mk:i	Ljava/lang/Thread;
    //   26: aload_0
    //   27: getfield 251	com/yandex/metrica/impl/ob/mk:f	Ljava/net/ServerSocket;
    //   30: ifnull +15 -> 45
    //   33: aload_0
    //   34: getfield 251	com/yandex/metrica/impl/ob/mk:f	Ljava/net/ServerSocket;
    //   37: invokevirtual 254	java/net/ServerSocket:close	()V
    //   40: aload_0
    //   41: aconst_null
    //   42: putfield 251	com/yandex/metrica/impl/ob/mk:f	Ljava/net/ServerSocket;
    //   45: aload_0
    //   46: monitorexit
    //   47: return
    //   48: astore_2
    //   49: aload_0
    //   50: monitorexit
    //   51: aload_2
    //   52: athrow
    //   53: astore_1
    //   54: goto -9 -> 45
    //
    // Exception table:
    //   from	to	target	type
    //   2	26	48	finally
    //   26	45	48	finally
    //   2	26	53	java/io/IOException
    //   26	45	53	java/io/IOException
  }

  // ERROR //
  ServerSocket f()
  {
    // Byte code:
    //   0: aload_0
    //   1: getfield 154	com/yandex/metrica/impl/ob/mk:h	Lcom/yandex/metrica/impl/ob/mn;
    //   4: getfield 260	com/yandex/metrica/impl/ob/mn:c	Ljava/util/List;
    //   7: invokeinterface 266 1 0
    //   12: astore_1
    //   13: aconst_null
    //   14: astore_2
    //   15: aconst_null
    //   16: astore_3
    //   17: aload_3
    //   18: ifnonnull +93 -> 111
    //   21: aload_1
    //   22: invokeinterface 272 1 0
    //   27: ifeq +84 -> 111
    //   30: aload_1
    //   31: invokeinterface 276 1 0
    //   36: checkcast 278	java/lang/Integer
    //   39: astore 5
    //   41: aload 5
    //   43: ifnull +17 -> 60
    //   46: aload_0
    //   47: aload 5
    //   49: invokevirtual 282	java/lang/Integer:intValue	()I
    //   52: invokevirtual 284	com/yandex/metrica/impl/ob/mk:a	(I)Ljava/net/ServerSocket;
    //   55: astore 9
    //   57: aload 9
    //   59: astore_3
    //   60: aload 5
    //   62: astore_2
    //   63: goto -46 -> 17
    //   66: astore 6
    //   68: aload_2
    //   69: astore 5
    //   71: aload_0
    //   72: getfield 62	com/yandex/metrica/impl/ob/mk:d	Landroid/content/Context;
    //   75: invokestatic 129	com/yandex/metrica/impl/ob/mi:a	(Landroid/content/Context;)Lcom/yandex/metrica/c;
    //   78: ldc_w 286
    //   81: aload 5
    //   83: invokevirtual 282	java/lang/Integer:intValue	()I
    //   86: invokestatic 151	com/yandex/metrica/impl/ob/mk:c	(I)Ljava/util/HashMap;
    //   89: invokeinterface 147 3 0
    //   94: aload 5
    //   96: astore_2
    //   97: goto -80 -> 17
    //   100: astore 4
    //   102: aload_2
    //   103: astore 5
    //   105: aload 5
    //   107: astore_2
    //   108: goto -91 -> 17
    //   111: aload_3
    //   112: areturn
    //   113: astore 8
    //   115: goto -10 -> 105
    //   118: astore 7
    //   120: goto -49 -> 71
    //
    // Exception table:
    //   from	to	target	type
    //   30	41	66	java/net/SocketException
    //   30	41	100	java/io/IOException
    //   46	57	113	java/io/IOException
    //   46	57	118	java/net/SocketException
  }

  // ERROR //
  public void run()
  {
    // Byte code:
    //   0: aload_0
    //   1: aload_0
    //   2: invokevirtual 289	com/yandex/metrica/impl/ob/mk:f	()Ljava/net/ServerSocket;
    //   5: putfield 251	com/yandex/metrica/impl/ob/mk:f	Ljava/net/ServerSocket;
    //   8: bipush 26
    //   10: invokestatic 294	com/yandex/metrica/impl/bw:a	(I)Z
    //   13: ifeq +9 -> 22
    //   16: ldc_w 295
    //   19: invokestatic 300	android/net/TrafficStats:setThreadStatsTag	(I)V
    //   22: aload_0
    //   23: getfield 251	com/yandex/metrica/impl/ob/mk:f	Ljava/net/ServerSocket;
    //   26: ifnull +385 -> 411
    //   29: aload_0
    //   30: getfield 171	com/yandex/metrica/impl/ob/mk:e	Z
    //   33: ifeq +378 -> 411
    //   36: aload_0
    //   37: monitorenter
    //   38: aload_0
    //   39: getfield 251	com/yandex/metrica/impl/ob/mk:f	Ljava/net/ServerSocket;
    //   42: astore_2
    //   43: aload_0
    //   44: monitorexit
    //   45: aload_2
    //   46: ifnull -17 -> 29
    //   49: aload_2
    //   50: invokevirtual 304	java/net/ServerSocket:accept	()Ljava/net/Socket;
    //   53: astore 9
    //   55: aload 9
    //   57: astore 7
    //   59: bipush 26
    //   61: invokestatic 294	com/yandex/metrica/impl/bw:a	(I)Z
    //   64: ifeq +8 -> 72
    //   67: aload 7
    //   69: invokestatic 308	android/net/TrafficStats:tagSocket	(Ljava/net/Socket;)V
    //   72: aload 7
    //   74: sipush 1000
    //   77: invokevirtual 313	java/net/Socket:setSoTimeout	(I)V
    //   80: new 115	java/util/HashMap
    //   83: dup
    //   84: invokespecial 116	java/util/HashMap:<init>	()V
    //   87: astore 15
    //   89: new 315	java/io/BufferedReader
    //   92: dup
    //   93: new 317	java/io/InputStreamReader
    //   96: dup
    //   97: aload 7
    //   99: invokevirtual 321	java/net/Socket:getInputStream	()Ljava/io/InputStream;
    //   102: invokespecial 324	java/io/InputStreamReader:<init>	(Ljava/io/InputStream;)V
    //   105: invokespecial 327	java/io/BufferedReader:<init>	(Ljava/io/Reader;)V
    //   108: astore 12
    //   110: aload 12
    //   112: invokevirtual 331	java/io/BufferedReader:readLine	()Ljava/lang/String;
    //   115: astore 16
    //   117: aload 16
    //   119: invokestatic 337	android/text/TextUtils:isEmpty	(Ljava/lang/CharSequence;)Z
    //   122: ifne +198 -> 320
    //   125: aload 16
    //   127: ldc_w 339
    //   130: invokevirtual 343	java/lang/String:startsWith	(Ljava/lang/String;)Z
    //   133: ifeq +187 -> 320
    //   136: iconst_1
    //   137: aload 16
    //   139: bipush 47
    //   141: invokevirtual 347	java/lang/String:indexOf	(I)I
    //   144: iadd
    //   145: istore 17
    //   147: aload 16
    //   149: bipush 32
    //   151: iload 17
    //   153: invokevirtual 350	java/lang/String:indexOf	(II)I
    //   156: istore 18
    //   158: iload 18
    //   160: ifle +234 -> 394
    //   163: aload 16
    //   165: iload 17
    //   167: iload 18
    //   169: invokevirtual 354	java/lang/String:substring	(II)Ljava/lang/String;
    //   172: astore 19
    //   174: aload 19
    //   176: invokestatic 360	android/net/Uri:parse	(Ljava/lang/String;)Landroid/net/Uri;
    //   179: astore 20
    //   181: aload 12
    //   183: invokevirtual 331	java/io/BufferedReader:readLine	()Ljava/lang/String;
    //   186: astore 21
    //   188: aload 21
    //   190: invokestatic 337	android/text/TextUtils:isEmpty	(Ljava/lang/CharSequence;)Z
    //   193: ifne +91 -> 284
    //   196: aload 21
    //   198: ldc_w 362
    //   201: invokevirtual 365	java/lang/String:indexOf	(Ljava/lang/String;)I
    //   204: istore 23
    //   206: aload 15
    //   208: aload 21
    //   210: iconst_0
    //   211: iload 23
    //   213: invokevirtual 354	java/lang/String:substring	(II)Ljava/lang/String;
    //   216: aload 21
    //   218: iload 23
    //   220: iconst_2
    //   221: iadd
    //   222: invokevirtual 367	java/lang/String:substring	(I)Ljava/lang/String;
    //   225: invokevirtual 160	java/util/HashMap:put	(Ljava/lang/Object;Ljava/lang/Object;)Ljava/lang/Object;
    //   228: pop
    //   229: goto -48 -> 181
    //   232: astore 11
    //   234: aload_0
    //   235: getfield 62	com/yandex/metrica/impl/ob/mk:d	Landroid/content/Context;
    //   238: invokestatic 129	com/yandex/metrica/impl/ob/mi:a	(Landroid/content/Context;)Lcom/yandex/metrica/c;
    //   241: ldc_w 369
    //   244: aload 11
    //   246: invokeinterface 373 3 0
    //   251: aload 12
    //   253: ifnull +8 -> 261
    //   256: aload 12
    //   258: invokevirtual 374	java/io/BufferedReader:close	()V
    //   261: aload 7
    //   263: ifnull -234 -> 29
    //   266: aload 7
    //   268: invokevirtual 375	java/net/Socket:close	()V
    //   271: goto -242 -> 29
    //   274: astore 14
    //   276: goto -247 -> 29
    //   279: astore_1
    //   280: aload_0
    //   281: monitorexit
    //   282: aload_1
    //   283: athrow
    //   284: aload_0
    //   285: getfield 55	com/yandex/metrica/impl/ob/mk:c	Ljava/util/HashMap;
    //   288: aload 20
    //   290: invokevirtual 378	android/net/Uri:getPath	()Ljava/lang/String;
    //   293: invokevirtual 382	java/util/HashMap:get	(Ljava/lang/Object;)Ljava/lang/Object;
    //   296: checkcast 384	com/yandex/metrica/impl/ob/mk$d
    //   299: astore 22
    //   301: aload 22
    //   303: ifnull +49 -> 352
    //   306: aload 22
    //   308: aload 20
    //   310: aload 15
    //   312: aload 7
    //   314: invokevirtual 387	com/yandex/metrica/impl/ob/mk$d:a	(Landroid/net/Uri;Ljava/util/Map;Ljava/net/Socket;)Lcom/yandex/metrica/impl/ob/mk$c;
    //   317: invokevirtual 391	com/yandex/metrica/impl/ob/mk$c:a	()V
    //   320: aload 12
    //   322: invokevirtual 374	java/io/BufferedReader:close	()V
    //   325: goto -64 -> 261
    //   328: astore 10
    //   330: aload 7
    //   332: astore 4
    //   334: aload 4
    //   336: ifnull -307 -> 29
    //   339: aload 4
    //   341: invokevirtual 375	java/net/Socket:close	()V
    //   344: goto -315 -> 29
    //   347: astore 5
    //   349: goto -320 -> 29
    //   352: aload_0
    //   353: ldc_w 393
    //   356: aload 19
    //   358: invokespecial 395	com/yandex/metrica/impl/ob/mk:a	(Ljava/lang/String;Ljava/lang/String;)V
    //   361: goto -41 -> 320
    //   364: astore 13
    //   366: aload 12
    //   368: ifnull +8 -> 376
    //   371: aload 12
    //   373: invokevirtual 374	java/io/BufferedReader:close	()V
    //   376: aload 13
    //   378: athrow
    //   379: astore 6
    //   381: aload 7
    //   383: ifnull +8 -> 391
    //   386: aload 7
    //   388: invokevirtual 375	java/net/Socket:close	()V
    //   391: aload 6
    //   393: athrow
    //   394: aload_0
    //   395: ldc_w 397
    //   398: aload 16
    //   400: invokespecial 395	com/yandex/metrica/impl/ob/mk:a	(Ljava/lang/String;Ljava/lang/String;)V
    //   403: goto -83 -> 320
    //   406: astore 8
    //   408: goto -17 -> 391
    //   411: return
    //   412: astore 6
    //   414: aconst_null
    //   415: astore 7
    //   417: goto -36 -> 381
    //   420: astore_3
    //   421: aconst_null
    //   422: astore 4
    //   424: goto -90 -> 334
    //   427: astore 13
    //   429: aconst_null
    //   430: astore 12
    //   432: goto -66 -> 366
    //   435: astore 11
    //   437: aconst_null
    //   438: astore 12
    //   440: goto -206 -> 234
    //
    // Exception table:
    //   from	to	target	type
    //   110	158	232	java/lang/Exception
    //   163	181	232	java/lang/Exception
    //   181	229	232	java/lang/Exception
    //   284	301	232	java/lang/Exception
    //   306	320	232	java/lang/Exception
    //   352	361	232	java/lang/Exception
    //   394	403	232	java/lang/Exception
    //   266	271	274	java/io/IOException
    //   38	45	279	finally
    //   280	282	279	finally
    //   59	72	328	java/lang/Exception
    //   256	261	328	java/lang/Exception
    //   320	325	328	java/lang/Exception
    //   371	376	328	java/lang/Exception
    //   376	379	328	java/lang/Exception
    //   339	344	347	java/io/IOException
    //   110	158	364	finally
    //   163	181	364	finally
    //   181	229	364	finally
    //   234	251	364	finally
    //   284	301	364	finally
    //   306	320	364	finally
    //   352	361	364	finally
    //   394	403	364	finally
    //   59	72	379	finally
    //   256	261	379	finally
    //   320	325	379	finally
    //   371	376	379	finally
    //   376	379	379	finally
    //   386	391	406	java/io/IOException
    //   49	55	412	finally
    //   49	55	420	java/lang/Exception
    //   72	110	427	finally
    //   72	110	435	java/lang/Exception
  }

  class a extends mk.c
  {
    a(Map<String, String> paramSocket, Socket arg3)
    {
      super(paramSocket, localMap, localSocket);
    }

    public void a()
    {
      String str = this.b.getQueryParameter("t");
      if (mk.c(mk.this).b.equals(str))
      {
        a("HTTP/1.1 200 OK", new HashMap()
        {
        }
        , c());
        return;
      }
      mi.a(mk.b(mk.this)).reportEvent("socket_request_with_wrong_token");
    }

    protected void a(Throwable paramThrowable)
    {
      mi.a(mk.b(mk.this)).reportError("socket_io_exception_during_sync", paramThrowable);
    }

    protected void b()
    {
      mi.a(mk.b(mk.this)).reportEvent("socket_sync_succeed", mk.b(this.d.getLocalPort()));
    }

    protected byte[] c()
    {
      try
      {
        byte[] arrayOfByte = Base64.encode(new ov().a(mk.d(mk.this).a().getBytes()), 0);
        return arrayOfByte;
      }
      catch (JSONException localJSONException)
      {
      }
      return new byte[0];
    }
  }

  public static class b
  {
    public mk a(Context paramContext)
    {
      return new mk(paramContext);
    }
  }

  abstract class c
  {
    Uri b;
    Map<String, String> c;
    Socket d;

    c(Map<String, String> paramSocket, Socket arg3)
    {
      this.b = paramSocket;
      Object localObject1;
      this.c = localObject1;
      Object localObject2;
      this.d = localObject2;
    }

    private static void a(OutputStream paramOutputStream)
      throws IOException
    {
      paramOutputStream.write("\r\n".getBytes());
    }

    private static void a(OutputStream paramOutputStream, String paramString1, String paramString2)
      throws IOException
    {
      paramOutputStream.write((paramString1 + ": " + paramString2).getBytes());
      a(paramOutputStream);
    }

    public abstract void a();

    // ERROR //
    void a(String paramString, Map<String, String> paramMap, byte[] paramArrayOfByte)
    {
      // Byte code:
      //   0: new 63	java/io/BufferedOutputStream
      //   3: dup
      //   4: aload_0
      //   5: getfield 26	com/yandex/metrica/impl/ob/mk$c:d	Ljava/net/Socket;
      //   8: invokevirtual 69	java/net/Socket:getOutputStream	()Ljava/io/OutputStream;
      //   11: invokespecial 71	java/io/BufferedOutputStream:<init>	(Ljava/io/OutputStream;)V
      //   14: astore 4
      //   16: aload 4
      //   18: aload_1
      //   19: invokevirtual 38	java/lang/String:getBytes	()[B
      //   22: invokevirtual 44	java/io/OutputStream:write	([B)V
      //   25: aload 4
      //   27: invokestatic 60	com/yandex/metrica/impl/ob/mk$c:a	(Ljava/io/OutputStream;)V
      //   30: aload_2
      //   31: invokeinterface 77 1 0
      //   36: invokeinterface 83 1 0
      //   41: astore 8
      //   43: aload 8
      //   45: invokeinterface 89 1 0
      //   50: ifeq +61 -> 111
      //   53: aload 8
      //   55: invokeinterface 93 1 0
      //   60: checkcast 95	java/util/Map$Entry
      //   63: astore 9
      //   65: aload 4
      //   67: aload 9
      //   69: invokeinterface 98 1 0
      //   74: checkcast 34	java/lang/String
      //   77: aload 9
      //   79: invokeinterface 101 1 0
      //   84: checkcast 34	java/lang/String
      //   87: invokestatic 103	com/yandex/metrica/impl/ob/mk$c:a	(Ljava/io/OutputStream;Ljava/lang/String;Ljava/lang/String;)V
      //   90: goto -47 -> 43
      //   93: astore 6
      //   95: aload 4
      //   97: astore 7
      //   99: aload_0
      //   100: aload 6
      //   102: invokevirtual 106	com/yandex/metrica/impl/ob/mk$c:a	(Ljava/lang/Throwable;)V
      //   105: aload 7
      //   107: invokestatic 111	com/yandex/metrica/impl/bw:a	(Ljava/io/Closeable;)V
      //   110: return
      //   111: aload 4
      //   113: ldc 113
      //   115: aload_3
      //   116: arraylength
      //   117: invokestatic 117	java/lang/String:valueOf	(I)Ljava/lang/String;
      //   120: invokestatic 103	com/yandex/metrica/impl/ob/mk$c:a	(Ljava/io/OutputStream;Ljava/lang/String;Ljava/lang/String;)V
      //   123: aload 4
      //   125: invokestatic 60	com/yandex/metrica/impl/ob/mk$c:a	(Ljava/io/OutputStream;)V
      //   128: aload 4
      //   130: aload_3
      //   131: invokevirtual 44	java/io/OutputStream:write	([B)V
      //   134: aload 4
      //   136: invokevirtual 120	java/io/OutputStream:flush	()V
      //   139: aload_0
      //   140: invokevirtual 122	com/yandex/metrica/impl/ob/mk$c:b	()V
      //   143: aload 4
      //   145: invokestatic 111	com/yandex/metrica/impl/bw:a	(Ljava/io/Closeable;)V
      //   148: return
      //   149: astore 5
      //   151: aconst_null
      //   152: astore 4
      //   154: aload 4
      //   156: invokestatic 111	com/yandex/metrica/impl/bw:a	(Ljava/io/Closeable;)V
      //   159: aload 5
      //   161: athrow
      //   162: astore 5
      //   164: goto -10 -> 154
      //   167: astore 5
      //   169: aload 7
      //   171: astore 4
      //   173: goto -19 -> 154
      //   176: astore 6
      //   178: aconst_null
      //   179: astore 7
      //   181: goto -82 -> 99
      //
      // Exception table:
      //   from	to	target	type
      //   16	43	93	java/io/IOException
      //   43	90	93	java/io/IOException
      //   111	143	93	java/io/IOException
      //   0	16	149	finally
      //   16	43	162	finally
      //   43	90	162	finally
      //   111	143	162	finally
      //   99	105	167	finally
      //   0	16	176	java/io/IOException
    }

    protected abstract void a(Throwable paramThrowable);

    protected abstract void b();
  }

  static abstract class d
  {
    public abstract mk.c a(Uri paramUri, Map<String, String> paramMap, Socket paramSocket);
  }
}

/* Location:           E:\Study\Tools\apktool2_2\dex2jar-0.0.9.15\classes_viber_4_dex2jar.jar
 * Qualified Name:     com.yandex.metrica.impl.ob.mk
 * JD-Core Version:    0.6.2
 */