package com.adsnative.a;

public final class b
{
  // ERROR //
  public static void a(android.content.Context paramContext, com.adsnative.b.c paramc, a.a parama)
  {
    // Byte code:
    //   0: aconst_null
    //   1: astore_3
    //   2: aload_1
    //   3: invokevirtual 14	com/adsnative/b/c:f	()Ljava/lang/String;
    //   6: astore_3
    //   7: aload_3
    //   8: invokestatic 19	com/adsnative/a/c:a	(Ljava/lang/String;)Lcom/adsnative/a/a;
    //   11: astore 5
    //   13: aload 5
    //   15: aload_0
    //   16: aload_2
    //   17: aload_1
    //   18: invokevirtual 24	com/adsnative/a/a:a	(Landroid/content/Context;Lcom/adsnative/a/a$a;Lcom/adsnative/b/c;)V
    //   21: return
    //   22: astore 4
    //   24: new 26	java/lang/StringBuilder
    //   27: dup
    //   28: invokespecial 30	java/lang/StringBuilder:<init>	()V
    //   31: ldc 32
    //   33: invokevirtual 36	java/lang/StringBuilder:append	(Ljava/lang/String;)Ljava/lang/StringBuilder;
    //   36: aload_3
    //   37: invokevirtual 36	java/lang/StringBuilder:append	(Ljava/lang/String;)Ljava/lang/StringBuilder;
    //   40: invokevirtual 39	java/lang/StringBuilder:toString	()Ljava/lang/String;
    //   43: invokestatic 45	com/adsnative/c/i:d	(Ljava/lang/String;)V
    //   46: aload_2
    //   47: getstatic 51	com/adsnative/ads/e:p	Lcom/adsnative/ads/e;
    //   50: invokeinterface 56 2 0
    //   55: return
    //   56: astore 6
    //   58: ldc 58
    //   60: aload 6
    //   62: invokestatic 62	com/adsnative/c/i:e	(Ljava/lang/String;Ljava/lang/Throwable;)V
    //   65: aload_2
    //   66: getstatic 51	com/adsnative/ads/e:p	Lcom/adsnative/ads/e;
    //   69: invokeinterface 56 2 0
    //   74: return
    //
    // Exception table:
    //   from	to	target	type
    //   2	13	22	java/lang/Exception
    //   13	21	56	java/lang/Exception
  }

  // ERROR //
  public static void a(android.content.Context paramContext, com.adsnative.b.c paramc, d.a parama)
  {
    // Byte code:
    //   0: aconst_null
    //   1: astore_3
    //   2: aload_1
    //   3: invokevirtual 14	com/adsnative/b/c:f	()Ljava/lang/String;
    //   6: astore_3
    //   7: aload_3
    //   8: invokestatic 68	com/adsnative/a/e:a	(Ljava/lang/String;)Lcom/adsnative/a/d;
    //   11: astore 5
    //   13: aload 5
    //   15: aload_0
    //   16: aload_2
    //   17: aload_1
    //   18: invokevirtual 73	com/adsnative/a/d:a	(Landroid/content/Context;Lcom/adsnative/a/d$a;Lcom/adsnative/b/c;)V
    //   21: return
    //   22: astore 4
    //   24: new 26	java/lang/StringBuilder
    //   27: dup
    //   28: invokespecial 30	java/lang/StringBuilder:<init>	()V
    //   31: ldc 75
    //   33: invokevirtual 36	java/lang/StringBuilder:append	(Ljava/lang/String;)Ljava/lang/StringBuilder;
    //   36: aload_3
    //   37: invokevirtual 36	java/lang/StringBuilder:append	(Ljava/lang/String;)Ljava/lang/StringBuilder;
    //   40: invokevirtual 39	java/lang/StringBuilder:toString	()Ljava/lang/String;
    //   43: invokestatic 45	com/adsnative/c/i:d	(Ljava/lang/String;)V
    //   46: aload_2
    //   47: getstatic 78	com/adsnative/ads/e:r	Lcom/adsnative/ads/e;
    //   50: invokeinterface 81 2 0
    //   55: return
    //   56: astore 6
    //   58: ldc 83
    //   60: aload 6
    //   62: invokestatic 62	com/adsnative/c/i:e	(Ljava/lang/String;Ljava/lang/Throwable;)V
    //   65: aload_2
    //   66: getstatic 78	com/adsnative/ads/e:r	Lcom/adsnative/ads/e;
    //   69: invokeinterface 81 2 0
    //   74: return
    //
    // Exception table:
    //   from	to	target	type
    //   2	13	22	java/lang/Exception
    //   13	21	56	java/lang/Exception
  }
}

/* Location:           E:\Study\Tools\apktool2_2\dex2jar-0.0.9.15\classes_viber_dex2jar.jar
 * Qualified Name:     com.adsnative.a.b
 * JD-Core Version:    0.6.2
 */