package com.google.android.gms.measurement.internal;

import com.google.android.gms.common.internal.Preconditions;
import java.net.URL;
import java.util.Map;

final class zzba
  implements Runnable
{
  private final String packageName;
  private final URL url;
  private final byte[] zzamt;
  private final zzay zzamu;
  private final Map<String, String> zzamv;

  public zzba(String paramString, URL paramURL, byte[] paramArrayOfByte, Map<String, String> paramMap, zzay paramzzay)
  {
    Preconditions.checkNotEmpty(paramURL);
    Preconditions.checkNotNull(paramArrayOfByte);
    Object localObject;
    Preconditions.checkNotNull(localObject);
    this.url = paramArrayOfByte;
    this.zzamt = paramMap;
    this.zzamu = localObject;
    this.packageName = paramURL;
    this.zzamv = paramzzay;
  }

  // ERROR //
  public final void run()
  {
    // Byte code:
    //   0: aload_0
    //   1: getfield 23	com/google/android/gms/measurement/internal/zzba:zzamw	Lcom/google/android/gms/measurement/internal/zzaw;
    //   4: invokevirtual 54	com/google/android/gms/measurement/internal/zzcr:zzgh	()V
    //   7: iconst_0
    //   8: istore_1
    //   9: aload_0
    //   10: getfield 23	com/google/android/gms/measurement/internal/zzba:zzamw	Lcom/google/android/gms/measurement/internal/zzaw;
    //   13: aload_0
    //   14: getfield 38	com/google/android/gms/measurement/internal/zzba:url	Ljava/net/URL;
    //   17: invokevirtual 60	com/google/android/gms/measurement/internal/zzaw:zzb	(Ljava/net/URL;)Ljava/net/HttpURLConnection;
    //   20: astore 13
    //   22: aload 13
    //   24: astore 11
    //   26: aload_0
    //   27: getfield 46	com/google/android/gms/measurement/internal/zzba:zzamv	Ljava/util/Map;
    //   30: astore 15
    //   32: iconst_0
    //   33: istore_1
    //   34: aload 15
    //   36: ifnull +139 -> 175
    //   39: aload_0
    //   40: getfield 46	com/google/android/gms/measurement/internal/zzba:zzamv	Ljava/util/Map;
    //   43: invokeinterface 66 1 0
    //   48: invokeinterface 72 1 0
    //   53: astore 16
    //   55: aload 16
    //   57: invokeinterface 78 1 0
    //   62: istore 17
    //   64: iconst_0
    //   65: istore_1
    //   66: iload 17
    //   68: ifeq +107 -> 175
    //   71: aload 16
    //   73: invokeinterface 82 1 0
    //   78: checkcast 84	java/util/Map$Entry
    //   81: astore 18
    //   83: aload 11
    //   85: aload 18
    //   87: invokeinterface 87 1 0
    //   92: checkcast 89	java/lang/String
    //   95: aload 18
    //   97: invokeinterface 92 1 0
    //   102: checkcast 89	java/lang/String
    //   105: invokevirtual 98	java/net/HttpURLConnection:addRequestProperty	(Ljava/lang/String;Ljava/lang/String;)V
    //   108: goto -53 -> 55
    //   111: astore_2
    //   112: aconst_null
    //   113: astore 6
    //   115: iload_1
    //   116: istore 5
    //   118: aconst_null
    //   119: astore_3
    //   120: aload 11
    //   122: astore 4
    //   124: aload_3
    //   125: ifnull +7 -> 132
    //   128: aload_3
    //   129: invokevirtual 103	java/io/OutputStream:close	()V
    //   132: aload 4
    //   134: ifnull +8 -> 142
    //   137: aload 4
    //   139: invokevirtual 106	java/net/HttpURLConnection:disconnect	()V
    //   142: aload_0
    //   143: getfield 23	com/google/android/gms/measurement/internal/zzba:zzamw	Lcom/google/android/gms/measurement/internal/zzaw;
    //   146: invokevirtual 110	com/google/android/gms/measurement/internal/zzcr:zzgs	()Lcom/google/android/gms/measurement/internal/zzbr;
    //   149: new 112	com/google/android/gms/measurement/internal/zzaz
    //   152: dup
    //   153: aload_0
    //   154: getfield 44	com/google/android/gms/measurement/internal/zzba:packageName	Ljava/lang/String;
    //   157: aload_0
    //   158: getfield 42	com/google/android/gms/measurement/internal/zzba:zzamu	Lcom/google/android/gms/measurement/internal/zzay;
    //   161: iload 5
    //   163: aload_2
    //   164: aconst_null
    //   165: aload 6
    //   167: aconst_null
    //   168: invokespecial 115	com/google/android/gms/measurement/internal/zzaz:<init>	(Ljava/lang/String;Lcom/google/android/gms/measurement/internal/zzay;ILjava/lang/Throwable;[BLjava/util/Map;Lcom/google/android/gms/measurement/internal/zzax;)V
    //   171: invokevirtual 121	com/google/android/gms/measurement/internal/zzbr:zzc	(Ljava/lang/Runnable;)V
    //   174: return
    //   175: aload_0
    //   176: getfield 40	com/google/android/gms/measurement/internal/zzba:zzamt	[B
    //   179: astore 19
    //   181: iconst_0
    //   182: istore_1
    //   183: aload 19
    //   185: ifnull +88 -> 273
    //   188: aload_0
    //   189: getfield 23	com/google/android/gms/measurement/internal/zzba:zzamw	Lcom/google/android/gms/measurement/internal/zzaw;
    //   192: invokevirtual 127	com/google/android/gms/measurement/internal/zzfl:zzjr	()Lcom/google/android/gms/measurement/internal/zzft;
    //   195: aload_0
    //   196: getfield 40	com/google/android/gms/measurement/internal/zzba:zzamt	[B
    //   199: invokevirtual 132	com/google/android/gms/measurement/internal/zzft:zzb	([B)[B
    //   202: astore 20
    //   204: aload_0
    //   205: getfield 23	com/google/android/gms/measurement/internal/zzba:zzamw	Lcom/google/android/gms/measurement/internal/zzaw;
    //   208: invokevirtual 136	com/google/android/gms/measurement/internal/zzcr:zzgt	()Lcom/google/android/gms/measurement/internal/zzas;
    //   211: invokevirtual 142	com/google/android/gms/measurement/internal/zzas:zzjo	()Lcom/google/android/gms/measurement/internal/zzau;
    //   214: ldc 144
    //   216: aload 20
    //   218: arraylength
    //   219: invokestatic 150	java/lang/Integer:valueOf	(I)Ljava/lang/Integer;
    //   222: invokevirtual 156	com/google/android/gms/measurement/internal/zzau:zzg	(Ljava/lang/String;Ljava/lang/Object;)V
    //   225: aload 11
    //   227: iconst_1
    //   228: invokevirtual 160	java/net/HttpURLConnection:setDoOutput	(Z)V
    //   231: aload 11
    //   233: ldc 162
    //   235: ldc 164
    //   237: invokevirtual 98	java/net/HttpURLConnection:addRequestProperty	(Ljava/lang/String;Ljava/lang/String;)V
    //   240: aload 11
    //   242: aload 20
    //   244: arraylength
    //   245: invokevirtual 168	java/net/HttpURLConnection:setFixedLengthStreamingMode	(I)V
    //   248: aload 11
    //   250: invokevirtual 171	java/net/HttpURLConnection:connect	()V
    //   253: aload 11
    //   255: invokevirtual 175	java/net/HttpURLConnection:getOutputStream	()Ljava/io/OutputStream;
    //   258: astore 21
    //   260: aload 21
    //   262: astore_3
    //   263: aload_3
    //   264: aload 20
    //   266: invokevirtual 179	java/io/OutputStream:write	([B)V
    //   269: aload_3
    //   270: invokevirtual 103	java/io/OutputStream:close	()V
    //   273: aload 11
    //   275: invokevirtual 183	java/net/HttpURLConnection:getResponseCode	()I
    //   278: istore_1
    //   279: aload 11
    //   281: invokevirtual 187	java/net/HttpURLConnection:getHeaderFields	()Ljava/util/Map;
    //   284: astore 23
    //   286: aload 23
    //   288: astore 10
    //   290: aload_0
    //   291: getfield 23	com/google/android/gms/measurement/internal/zzba:zzamw	Lcom/google/android/gms/measurement/internal/zzaw;
    //   294: aload 11
    //   296: invokestatic 191	com/google/android/gms/measurement/internal/zzaw:zza	(Lcom/google/android/gms/measurement/internal/zzaw;Ljava/net/HttpURLConnection;)[B
    //   299: astore 25
    //   301: aload 11
    //   303: ifnull +8 -> 311
    //   306: aload 11
    //   308: invokevirtual 106	java/net/HttpURLConnection:disconnect	()V
    //   311: aload_0
    //   312: getfield 23	com/google/android/gms/measurement/internal/zzba:zzamw	Lcom/google/android/gms/measurement/internal/zzaw;
    //   315: invokevirtual 110	com/google/android/gms/measurement/internal/zzcr:zzgs	()Lcom/google/android/gms/measurement/internal/zzbr;
    //   318: new 112	com/google/android/gms/measurement/internal/zzaz
    //   321: dup
    //   322: aload_0
    //   323: getfield 44	com/google/android/gms/measurement/internal/zzba:packageName	Ljava/lang/String;
    //   326: aload_0
    //   327: getfield 42	com/google/android/gms/measurement/internal/zzba:zzamu	Lcom/google/android/gms/measurement/internal/zzay;
    //   330: iload_1
    //   331: aconst_null
    //   332: aload 25
    //   334: aload 10
    //   336: aconst_null
    //   337: invokespecial 115	com/google/android/gms/measurement/internal/zzaz:<init>	(Ljava/lang/String;Lcom/google/android/gms/measurement/internal/zzay;ILjava/lang/Throwable;[BLjava/util/Map;Lcom/google/android/gms/measurement/internal/zzax;)V
    //   340: invokevirtual 121	com/google/android/gms/measurement/internal/zzbr:zzc	(Ljava/lang/Runnable;)V
    //   343: return
    //   344: astore 7
    //   346: aload_0
    //   347: getfield 23	com/google/android/gms/measurement/internal/zzba:zzamw	Lcom/google/android/gms/measurement/internal/zzaw;
    //   350: invokevirtual 136	com/google/android/gms/measurement/internal/zzcr:zzgt	()Lcom/google/android/gms/measurement/internal/zzas;
    //   353: invokevirtual 194	com/google/android/gms/measurement/internal/zzas:zzjg	()Lcom/google/android/gms/measurement/internal/zzau;
    //   356: ldc 196
    //   358: aload_0
    //   359: getfield 44	com/google/android/gms/measurement/internal/zzba:packageName	Ljava/lang/String;
    //   362: invokestatic 200	com/google/android/gms/measurement/internal/zzas:zzbw	(Ljava/lang/String;)Ljava/lang/Object;
    //   365: aload 7
    //   367: invokevirtual 204	com/google/android/gms/measurement/internal/zzau:zze	(Ljava/lang/String;Ljava/lang/Object;Ljava/lang/Object;)V
    //   370: goto -238 -> 132
    //   373: astore 8
    //   375: aload 8
    //   377: astore 9
    //   379: aconst_null
    //   380: astore 10
    //   382: aconst_null
    //   383: astore 11
    //   385: aconst_null
    //   386: astore_3
    //   387: aload_3
    //   388: ifnull +7 -> 395
    //   391: aload_3
    //   392: invokevirtual 103	java/io/OutputStream:close	()V
    //   395: aload 11
    //   397: ifnull +8 -> 405
    //   400: aload 11
    //   402: invokevirtual 106	java/net/HttpURLConnection:disconnect	()V
    //   405: aload_0
    //   406: getfield 23	com/google/android/gms/measurement/internal/zzba:zzamw	Lcom/google/android/gms/measurement/internal/zzaw;
    //   409: invokevirtual 110	com/google/android/gms/measurement/internal/zzcr:zzgs	()Lcom/google/android/gms/measurement/internal/zzbr;
    //   412: new 112	com/google/android/gms/measurement/internal/zzaz
    //   415: dup
    //   416: aload_0
    //   417: getfield 44	com/google/android/gms/measurement/internal/zzba:packageName	Ljava/lang/String;
    //   420: aload_0
    //   421: getfield 42	com/google/android/gms/measurement/internal/zzba:zzamu	Lcom/google/android/gms/measurement/internal/zzay;
    //   424: iload_1
    //   425: aconst_null
    //   426: aconst_null
    //   427: aload 10
    //   429: aconst_null
    //   430: invokespecial 115	com/google/android/gms/measurement/internal/zzaz:<init>	(Ljava/lang/String;Lcom/google/android/gms/measurement/internal/zzay;ILjava/lang/Throwable;[BLjava/util/Map;Lcom/google/android/gms/measurement/internal/zzax;)V
    //   433: invokevirtual 121	com/google/android/gms/measurement/internal/zzbr:zzc	(Ljava/lang/Runnable;)V
    //   436: aload 9
    //   438: athrow
    //   439: astore 12
    //   441: aload_0
    //   442: getfield 23	com/google/android/gms/measurement/internal/zzba:zzamw	Lcom/google/android/gms/measurement/internal/zzaw;
    //   445: invokevirtual 136	com/google/android/gms/measurement/internal/zzcr:zzgt	()Lcom/google/android/gms/measurement/internal/zzas;
    //   448: invokevirtual 194	com/google/android/gms/measurement/internal/zzas:zzjg	()Lcom/google/android/gms/measurement/internal/zzau;
    //   451: ldc 196
    //   453: aload_0
    //   454: getfield 44	com/google/android/gms/measurement/internal/zzba:packageName	Ljava/lang/String;
    //   457: invokestatic 200	com/google/android/gms/measurement/internal/zzas:zzbw	(Ljava/lang/String;)Ljava/lang/Object;
    //   460: aload 12
    //   462: invokevirtual 204	com/google/android/gms/measurement/internal/zzau:zze	(Ljava/lang/String;Ljava/lang/Object;Ljava/lang/Object;)V
    //   465: goto -70 -> 395
    //   468: astore 14
    //   470: aload 14
    //   472: astore 9
    //   474: aconst_null
    //   475: astore_3
    //   476: aconst_null
    //   477: astore 10
    //   479: goto -92 -> 387
    //   482: astore 22
    //   484: aload 22
    //   486: astore 9
    //   488: iconst_0
    //   489: istore_1
    //   490: aconst_null
    //   491: astore 10
    //   493: goto -106 -> 387
    //   496: astore 24
    //   498: aload 24
    //   500: astore 9
    //   502: aconst_null
    //   503: astore_3
    //   504: goto -117 -> 387
    //   507: astore_2
    //   508: aconst_null
    //   509: astore_3
    //   510: aconst_null
    //   511: astore 4
    //   513: iconst_0
    //   514: istore 5
    //   516: aconst_null
    //   517: astore 6
    //   519: goto -395 -> 124
    //   522: astore_2
    //   523: aload 11
    //   525: astore 4
    //   527: iconst_0
    //   528: istore 5
    //   530: aconst_null
    //   531: astore 6
    //   533: goto -409 -> 124
    //   536: astore_2
    //   537: aload 10
    //   539: astore 6
    //   541: iload_1
    //   542: istore 5
    //   544: aload 11
    //   546: astore 4
    //   548: aconst_null
    //   549: astore_3
    //   550: goto -426 -> 124
    //
    // Exception table:
    //   from	to	target	type
    //   26	32	111	java/io/IOException
    //   39	55	111	java/io/IOException
    //   55	64	111	java/io/IOException
    //   71	108	111	java/io/IOException
    //   175	181	111	java/io/IOException
    //   188	260	111	java/io/IOException
    //   273	286	111	java/io/IOException
    //   128	132	344	java/io/IOException
    //   9	22	373	finally
    //   391	395	439	java/io/IOException
    //   26	32	468	finally
    //   39	55	468	finally
    //   55	64	468	finally
    //   71	108	468	finally
    //   175	181	468	finally
    //   188	260	468	finally
    //   273	286	468	finally
    //   263	273	482	finally
    //   290	301	496	finally
    //   9	22	507	java/io/IOException
    //   263	273	522	java/io/IOException
    //   290	301	536	java/io/IOException
  }
}

/* Location:           E:\Study\Tools\apktool2_2\dex2jar-0.0.9.15\classes_viber_2_dex2jar.jar
 * Qualified Name:     com.google.android.gms.measurement.internal.zzba
 * JD-Core Version:    0.6.2
 */