package com.google.android.gms.measurement.internal;

import java.util.concurrent.atomic.AtomicReference;

final class zzdn
  implements Runnable
{
  zzdn(zzda paramzzda, AtomicReference paramAtomicReference)
  {
  }

  // ERROR //
  public final void run()
  {
    // Byte code:
    //   0: aload_0
    //   1: getfield 16	com/google/android/gms/measurement/internal/zzdn:zzarg	Ljava/util/concurrent/atomic/AtomicReference;
    //   4: astore_1
    //   5: aload_1
    //   6: monitorenter
    //   7: aload_0
    //   8: getfield 16	com/google/android/gms/measurement/internal/zzdn:zzarg	Ljava/util/concurrent/atomic/AtomicReference;
    //   11: aload_0
    //   12: getfield 14	com/google/android/gms/measurement/internal/zzdn:zzarh	Lcom/google/android/gms/measurement/internal/zzda;
    //   15: invokevirtual 26	com/google/android/gms/measurement/internal/zzcr:zzgv	()Lcom/google/android/gms/measurement/internal/zzq;
    //   18: aload_0
    //   19: getfield 14	com/google/android/gms/measurement/internal/zzdn:zzarh	Lcom/google/android/gms/measurement/internal/zzda;
    //   22: invokevirtual 32	com/google/android/gms/measurement/internal/zze:zzgk	()Lcom/google/android/gms/measurement/internal/zzam;
    //   25: invokevirtual 38	com/google/android/gms/measurement/internal/zzam:zzal	()Ljava/lang/String;
    //   28: getstatic 44	com/google/android/gms/measurement/internal/zzai:zzakd	Lcom/google/android/gms/measurement/internal/zzai$zza;
    //   31: invokevirtual 50	com/google/android/gms/measurement/internal/zzq:zza	(Ljava/lang/String;Lcom/google/android/gms/measurement/internal/zzai$zza;)J
    //   34: invokestatic 56	java/lang/Long:valueOf	(J)Ljava/lang/Long;
    //   37: invokevirtual 62	java/util/concurrent/atomic/AtomicReference:set	(Ljava/lang/Object;)V
    //   40: aload_0
    //   41: getfield 16	com/google/android/gms/measurement/internal/zzdn:zzarg	Ljava/util/concurrent/atomic/AtomicReference;
    //   44: invokevirtual 65	java/lang/Object:notify	()V
    //   47: aload_1
    //   48: monitorexit
    //   49: return
    //   50: astore_2
    //   51: aload_0
    //   52: getfield 16	com/google/android/gms/measurement/internal/zzdn:zzarg	Ljava/util/concurrent/atomic/AtomicReference;
    //   55: invokevirtual 65	java/lang/Object:notify	()V
    //   58: aload_2
    //   59: athrow
    //   60: astore_3
    //   61: aload_1
    //   62: monitorexit
    //   63: aload_3
    //   64: athrow
    //
    // Exception table:
    //   from	to	target	type
    //   7	40	50	finally
    //   40	49	60	finally
    //   51	60	60	finally
    //   61	63	60	finally
  }
}

/* Location:           E:\Study\Tools\apktool2_2\dex2jar-0.0.9.15\classes_viber_2_dex2jar.jar
 * Qualified Name:     com.google.android.gms.measurement.internal.zzdn
 * JD-Core Version:    0.6.2
 */