package com.google.android.gms.measurement.internal;

final class zzdv extends zzfm
{
  public zzdv(zzfn paramzzfn)
  {
    super(paramzzfn);
  }

  private static String zzr(String paramString1, String paramString2)
  {
    throw new SecurityException("This implementation should not be used.");
  }

  // ERROR //
  public final byte[] zzb(zzag paramzzag, String paramString)
  {
    // Byte code:
    //   0: aload_0
    //   1: invokevirtual 27	com/google/android/gms/measurement/internal/zzcr:zzaf	()V
    //   4: aload_0
    //   5: getfield 31	com/google/android/gms/measurement/internal/zzdv:zzada	Lcom/google/android/gms/measurement/internal/zzbw;
    //   8: invokevirtual 36	com/google/android/gms/measurement/internal/zzbw:zzgf	()V
    //   11: aload_1
    //   12: invokestatic 42	com/google/android/gms/common/internal/Preconditions:checkNotNull	(Ljava/lang/Object;)Ljava/lang/Object;
    //   15: pop
    //   16: aload_2
    //   17: invokestatic 46	com/google/android/gms/common/internal/Preconditions:checkNotEmpty	(Ljava/lang/String;)Ljava/lang/String;
    //   20: pop
    //   21: aload_0
    //   22: invokevirtual 50	com/google/android/gms/measurement/internal/zzcr:zzgv	()Lcom/google/android/gms/measurement/internal/zzq;
    //   25: aload_2
    //   26: getstatic 56	com/google/android/gms/measurement/internal/zzai:zzalh	Lcom/google/android/gms/measurement/internal/zzai$zza;
    //   29: invokevirtual 62	com/google/android/gms/measurement/internal/zzq:zze	(Ljava/lang/String;Lcom/google/android/gms/measurement/internal/zzai$zza;)Z
    //   32: ifne +20 -> 52
    //   35: aload_0
    //   36: invokevirtual 66	com/google/android/gms/measurement/internal/zzcr:zzgt	()Lcom/google/android/gms/measurement/internal/zzas;
    //   39: invokevirtual 72	com/google/android/gms/measurement/internal/zzas:zzjn	()Lcom/google/android/gms/measurement/internal/zzau;
    //   42: ldc 74
    //   44: aload_2
    //   45: invokevirtual 80	com/google/android/gms/measurement/internal/zzau:zzg	(Ljava/lang/String;Ljava/lang/Object;)V
    //   48: iconst_0
    //   49: newarray byte
    //   51: areturn
    //   52: ldc 82
    //   54: aload_1
    //   55: getfield 88	com/google/android/gms/measurement/internal/zzag:name	Ljava/lang/String;
    //   58: invokevirtual 94	java/lang/String:equals	(Ljava/lang/Object;)Z
    //   61: ifne +34 -> 95
    //   64: ldc 96
    //   66: aload_1
    //   67: getfield 88	com/google/android/gms/measurement/internal/zzag:name	Ljava/lang/String;
    //   70: invokevirtual 94	java/lang/String:equals	(Ljava/lang/Object;)Z
    //   73: ifne +22 -> 95
    //   76: aload_0
    //   77: invokevirtual 66	com/google/android/gms/measurement/internal/zzcr:zzgt	()Lcom/google/android/gms/measurement/internal/zzas;
    //   80: invokevirtual 72	com/google/android/gms/measurement/internal/zzas:zzjn	()Lcom/google/android/gms/measurement/internal/zzau;
    //   83: ldc 98
    //   85: aload_2
    //   86: aload_1
    //   87: getfield 88	com/google/android/gms/measurement/internal/zzag:name	Ljava/lang/String;
    //   90: invokevirtual 101	com/google/android/gms/measurement/internal/zzau:zze	(Ljava/lang/String;Ljava/lang/Object;Ljava/lang/Object;)V
    //   93: aconst_null
    //   94: areturn
    //   95: new 103	com/google/android/gms/internal/measurement/zzfv
    //   98: dup
    //   99: invokespecial 105	com/google/android/gms/internal/measurement/zzfv:<init>	()V
    //   102: astore 5
    //   104: aload_0
    //   105: invokevirtual 111	com/google/android/gms/measurement/internal/zzfl:zzjt	()Lcom/google/android/gms/measurement/internal/zzt;
    //   108: invokevirtual 116	com/google/android/gms/measurement/internal/zzt:beginTransaction	()V
    //   111: aload_0
    //   112: invokevirtual 111	com/google/android/gms/measurement/internal/zzfl:zzjt	()Lcom/google/android/gms/measurement/internal/zzt;
    //   115: aload_2
    //   116: invokevirtual 120	com/google/android/gms/measurement/internal/zzt:zzbm	(Ljava/lang/String;)Lcom/google/android/gms/measurement/internal/zzg;
    //   119: astore 7
    //   121: aload 7
    //   123: ifnonnull +31 -> 154
    //   126: aload_0
    //   127: invokevirtual 66	com/google/android/gms/measurement/internal/zzcr:zzgt	()Lcom/google/android/gms/measurement/internal/zzas;
    //   130: invokevirtual 72	com/google/android/gms/measurement/internal/zzas:zzjn	()Lcom/google/android/gms/measurement/internal/zzau;
    //   133: ldc 122
    //   135: aload_2
    //   136: invokevirtual 80	com/google/android/gms/measurement/internal/zzau:zzg	(Ljava/lang/String;Ljava/lang/Object;)V
    //   139: iconst_0
    //   140: newarray byte
    //   142: astore 8
    //   144: aload_0
    //   145: invokevirtual 111	com/google/android/gms/measurement/internal/zzfl:zzjt	()Lcom/google/android/gms/measurement/internal/zzt;
    //   148: invokevirtual 125	com/google/android/gms/measurement/internal/zzt:endTransaction	()V
    //   151: aload 8
    //   153: areturn
    //   154: aload 7
    //   156: invokevirtual 131	com/google/android/gms/measurement/internal/zzg:isMeasurementEnabled	()Z
    //   159: ifne +31 -> 190
    //   162: aload_0
    //   163: invokevirtual 66	com/google/android/gms/measurement/internal/zzcr:zzgt	()Lcom/google/android/gms/measurement/internal/zzas;
    //   166: invokevirtual 72	com/google/android/gms/measurement/internal/zzas:zzjn	()Lcom/google/android/gms/measurement/internal/zzau;
    //   169: ldc 133
    //   171: aload_2
    //   172: invokevirtual 80	com/google/android/gms/measurement/internal/zzau:zzg	(Ljava/lang/String;Ljava/lang/Object;)V
    //   175: iconst_0
    //   176: newarray byte
    //   178: astore 53
    //   180: aload_0
    //   181: invokevirtual 111	com/google/android/gms/measurement/internal/zzfl:zzjt	()Lcom/google/android/gms/measurement/internal/zzt;
    //   184: invokevirtual 125	com/google/android/gms/measurement/internal/zzt:endTransaction	()V
    //   187: aload 53
    //   189: areturn
    //   190: new 135	com/google/android/gms/internal/measurement/zzfw
    //   193: dup
    //   194: invokespecial 136	com/google/android/gms/internal/measurement/zzfw:<init>	()V
    //   197: astore 9
    //   199: aload 5
    //   201: iconst_1
    //   202: anewarray 135	com/google/android/gms/internal/measurement/zzfw
    //   205: dup
    //   206: iconst_0
    //   207: aload 9
    //   209: aastore
    //   210: putfield 140	com/google/android/gms/internal/measurement/zzfv:zzaxh	[Lcom/google/android/gms/internal/measurement/zzfw;
    //   213: aload 9
    //   215: iconst_1
    //   216: invokestatic 146	java/lang/Integer:valueOf	(I)Ljava/lang/Integer;
    //   219: putfield 150	com/google/android/gms/internal/measurement/zzfw:zzaxj	Ljava/lang/Integer;
    //   222: aload 9
    //   224: ldc 152
    //   226: putfield 155	com/google/android/gms/internal/measurement/zzfw:zzaxr	Ljava/lang/String;
    //   229: aload 9
    //   231: aload 7
    //   233: invokevirtual 159	com/google/android/gms/measurement/internal/zzg:zzal	()Ljava/lang/String;
    //   236: putfield 162	com/google/android/gms/internal/measurement/zzfw:zztt	Ljava/lang/String;
    //   239: aload 9
    //   241: aload 7
    //   243: invokevirtual 165	com/google/android/gms/measurement/internal/zzg:zzhg	()Ljava/lang/String;
    //   246: putfield 168	com/google/android/gms/internal/measurement/zzfw:zzafp	Ljava/lang/String;
    //   249: aload 9
    //   251: aload 7
    //   253: invokevirtual 171	com/google/android/gms/measurement/internal/zzg:zzak	()Ljava/lang/String;
    //   256: putfield 174	com/google/android/gms/internal/measurement/zzfw:zzts	Ljava/lang/String;
    //   259: aload 7
    //   261: invokevirtual 178	com/google/android/gms/measurement/internal/zzg:zzhf	()J
    //   264: lstore 10
    //   266: lload 10
    //   268: ldc2_w 179
    //   271: lcmp
    //   272: ifne +529 -> 801
    //   275: aconst_null
    //   276: astore 12
    //   278: aload 9
    //   280: aload 12
    //   282: putfield 183	com/google/android/gms/internal/measurement/zzfw:zzayd	Ljava/lang/Integer;
    //   285: aload 9
    //   287: aload 7
    //   289: invokevirtual 186	com/google/android/gms/measurement/internal/zzg:zzhh	()J
    //   292: invokestatic 191	java/lang/Long:valueOf	(J)Ljava/lang/Long;
    //   295: putfield 195	com/google/android/gms/internal/measurement/zzfw:zzaxv	Ljava/lang/Long;
    //   298: aload 9
    //   300: aload 7
    //   302: invokevirtual 198	com/google/android/gms/measurement/internal/zzg:getGmpAppId	()Ljava/lang/String;
    //   305: putfield 201	com/google/android/gms/internal/measurement/zzfw:zzafi	Ljava/lang/String;
    //   308: aload 9
    //   310: getfield 201	com/google/android/gms/internal/measurement/zzfw:zzafi	Ljava/lang/String;
    //   313: invokestatic 207	android/text/TextUtils:isEmpty	(Ljava/lang/CharSequence;)Z
    //   316: ifeq +13 -> 329
    //   319: aload 9
    //   321: aload 7
    //   323: invokevirtual 210	com/google/android/gms/measurement/internal/zzg:zzhb	()Ljava/lang/String;
    //   326: putfield 213	com/google/android/gms/internal/measurement/zzfw:zzawr	Ljava/lang/String;
    //   329: aload 9
    //   331: aload 7
    //   333: invokevirtual 216	com/google/android/gms/measurement/internal/zzg:zzhi	()J
    //   336: invokestatic 191	java/lang/Long:valueOf	(J)Ljava/lang/Long;
    //   339: putfield 219	com/google/android/gms/internal/measurement/zzfw:zzaxz	Ljava/lang/Long;
    //   342: aload_0
    //   343: getfield 31	com/google/android/gms/measurement/internal/zzdv:zzada	Lcom/google/android/gms/measurement/internal/zzbw;
    //   346: invokevirtual 222	com/google/android/gms/measurement/internal/zzbw:isEnabled	()Z
    //   349: ifeq +30 -> 379
    //   352: invokestatic 225	com/google/android/gms/measurement/internal/zzq:zzie	()Z
    //   355: ifeq +24 -> 379
    //   358: aload_0
    //   359: invokevirtual 50	com/google/android/gms/measurement/internal/zzcr:zzgv	()Lcom/google/android/gms/measurement/internal/zzq;
    //   362: aload 9
    //   364: getfield 162	com/google/android/gms/internal/measurement/zzfw:zztt	Ljava/lang/String;
    //   367: invokevirtual 229	com/google/android/gms/measurement/internal/zzq:zzas	(Ljava/lang/String;)Z
    //   370: ifeq +9 -> 379
    //   373: aload 9
    //   375: aconst_null
    //   376: putfield 232	com/google/android/gms/internal/measurement/zzfw:zzayj	Ljava/lang/String;
    //   379: aload_0
    //   380: invokevirtual 236	com/google/android/gms/measurement/internal/zzcr:zzgu	()Lcom/google/android/gms/measurement/internal/zzbd;
    //   383: aload 7
    //   385: invokevirtual 159	com/google/android/gms/measurement/internal/zzg:zzal	()Ljava/lang/String;
    //   388: invokevirtual 242	com/google/android/gms/measurement/internal/zzbd:zzbz	(Ljava/lang/String;)Landroid/util/Pair;
    //   391: astore 13
    //   393: aload 7
    //   395: invokevirtual 245	com/google/android/gms/measurement/internal/zzg:zzhw	()Z
    //   398: ifeq +62 -> 460
    //   401: aload 13
    //   403: ifnull +57 -> 460
    //   406: aload 13
    //   408: getfield 251	android/util/Pair:first	Ljava/lang/Object;
    //   411: checkcast 253	java/lang/CharSequence
    //   414: invokestatic 207	android/text/TextUtils:isEmpty	(Ljava/lang/CharSequence;)Z
    //   417: istore 14
    //   419: iload 14
    //   421: ifne +39 -> 460
    //   424: aload 9
    //   426: aload 13
    //   428: getfield 251	android/util/Pair:first	Ljava/lang/Object;
    //   431: checkcast 90	java/lang/String
    //   434: aload_1
    //   435: getfield 257	com/google/android/gms/measurement/internal/zzag:zzaig	J
    //   438: invokestatic 261	java/lang/Long:toString	(J)Ljava/lang/String;
    //   441: invokestatic 263	com/google/android/gms/measurement/internal/zzdv:zzr	(Ljava/lang/String;Ljava/lang/String;)Ljava/lang/String;
    //   444: putfield 266	com/google/android/gms/internal/measurement/zzfw:zzaxx	Ljava/lang/String;
    //   447: aload 9
    //   449: aload 13
    //   451: getfield 269	android/util/Pair:second	Ljava/lang/Object;
    //   454: checkcast 271	java/lang/Boolean
    //   457: putfield 275	com/google/android/gms/internal/measurement/zzfw:zzaxy	Ljava/lang/Boolean;
    //   460: aload_0
    //   461: invokevirtual 279	com/google/android/gms/measurement/internal/zzcr:zzgp	()Lcom/google/android/gms/measurement/internal/zzaa;
    //   464: invokevirtual 284	com/google/android/gms/measurement/internal/zzcs:zzcl	()V
    //   467: aload 9
    //   469: getstatic 289	android/os/Build:MODEL	Ljava/lang/String;
    //   472: putfield 292	com/google/android/gms/internal/measurement/zzfw:zzaxt	Ljava/lang/String;
    //   475: aload_0
    //   476: invokevirtual 279	com/google/android/gms/measurement/internal/zzcr:zzgp	()Lcom/google/android/gms/measurement/internal/zzaa;
    //   479: invokevirtual 284	com/google/android/gms/measurement/internal/zzcs:zzcl	()V
    //   482: aload 9
    //   484: getstatic 297	android/os/Build$VERSION:RELEASE	Ljava/lang/String;
    //   487: putfield 300	com/google/android/gms/internal/measurement/zzfw:zzaxs	Ljava/lang/String;
    //   490: aload 9
    //   492: aload_0
    //   493: invokevirtual 279	com/google/android/gms/measurement/internal/zzcr:zzgp	()Lcom/google/android/gms/measurement/internal/zzaa;
    //   496: invokevirtual 305	com/google/android/gms/measurement/internal/zzaa:zziw	()J
    //   499: l2i
    //   500: invokestatic 146	java/lang/Integer:valueOf	(I)Ljava/lang/Integer;
    //   503: putfield 308	com/google/android/gms/internal/measurement/zzfw:zzaxu	Ljava/lang/Integer;
    //   506: aload 9
    //   508: aload_0
    //   509: invokevirtual 279	com/google/android/gms/measurement/internal/zzcr:zzgp	()Lcom/google/android/gms/measurement/internal/zzaa;
    //   512: invokevirtual 311	com/google/android/gms/measurement/internal/zzaa:zzix	()Ljava/lang/String;
    //   515: putfield 314	com/google/android/gms/internal/measurement/zzfw:zzahr	Ljava/lang/String;
    //   518: aload 9
    //   520: aload 7
    //   522: invokevirtual 317	com/google/android/gms/measurement/internal/zzg:getAppInstanceId	()Ljava/lang/String;
    //   525: aload_1
    //   526: getfield 257	com/google/android/gms/measurement/internal/zzag:zzaig	J
    //   529: invokestatic 261	java/lang/Long:toString	(J)Ljava/lang/String;
    //   532: invokestatic 263	com/google/android/gms/measurement/internal/zzdv:zzr	(Ljava/lang/String;Ljava/lang/String;)Ljava/lang/String;
    //   535: putfield 320	com/google/android/gms/internal/measurement/zzfw:zzafh	Ljava/lang/String;
    //   538: aload 9
    //   540: aload 7
    //   542: invokevirtual 323	com/google/android/gms/measurement/internal/zzg:getFirebaseInstanceId	()Ljava/lang/String;
    //   545: putfield 326	com/google/android/gms/internal/measurement/zzfw:zzafk	Ljava/lang/String;
    //   548: aload 9
    //   550: getfield 162	com/google/android/gms/internal/measurement/zzfw:zztt	Ljava/lang/String;
    //   553: astore 17
    //   555: aload_0
    //   556: invokevirtual 111	com/google/android/gms/measurement/internal/zzfl:zzjt	()Lcom/google/android/gms/measurement/internal/zzt;
    //   559: aload 17
    //   561: invokevirtual 330	com/google/android/gms/measurement/internal/zzt:zzbl	(Ljava/lang/String;)Ljava/util/List;
    //   564: astore 18
    //   566: aload_0
    //   567: invokevirtual 50	com/google/android/gms/measurement/internal/zzcr:zzgv	()Lcom/google/android/gms/measurement/internal/zzq;
    //   570: aload_2
    //   571: invokevirtual 333	com/google/android/gms/measurement/internal/zzq:zzau	(Ljava/lang/String;)Z
    //   574: ifeq +111 -> 685
    //   577: aload 18
    //   579: invokeinterface 339 1 0
    //   584: astore 46
    //   586: aload 46
    //   588: invokeinterface 344 1 0
    //   593: ifeq +1039 -> 1632
    //   596: aload 46
    //   598: invokeinterface 348 1 0
    //   603: checkcast 350	com/google/android/gms/measurement/internal/zzfw
    //   606: astore 47
    //   608: ldc_w 352
    //   611: aload 47
    //   613: getfield 353	com/google/android/gms/measurement/internal/zzfw:name	Ljava/lang/String;
    //   616: invokevirtual 94	java/lang/String:equals	(Ljava/lang/Object;)Z
    //   619: ifeq -33 -> 586
    //   622: aload 47
    //   624: ifnull +11 -> 635
    //   627: aload 47
    //   629: getfield 356	com/google/android/gms/measurement/internal/zzfw:value	Ljava/lang/Object;
    //   632: ifnonnull +53 -> 685
    //   635: new 350	com/google/android/gms/measurement/internal/zzfw
    //   638: dup
    //   639: aload 17
    //   641: ldc_w 358
    //   644: ldc_w 352
    //   647: aload_0
    //   648: invokevirtual 362	com/google/android/gms/measurement/internal/zzcr:zzbx	()Lcom/google/android/gms/common/util/Clock;
    //   651: invokeinterface 367 1 0
    //   656: lconst_0
    //   657: invokestatic 191	java/lang/Long:valueOf	(J)Ljava/lang/Long;
    //   660: invokespecial 370	com/google/android/gms/measurement/internal/zzfw:<init>	(Ljava/lang/String;Ljava/lang/String;Ljava/lang/String;JLjava/lang/Object;)V
    //   663: astore 48
    //   665: aload 18
    //   667: aload 48
    //   669: invokeinterface 373 2 0
    //   674: pop
    //   675: aload_0
    //   676: invokevirtual 111	com/google/android/gms/measurement/internal/zzfl:zzjt	()Lcom/google/android/gms/measurement/internal/zzt;
    //   679: aload 48
    //   681: invokevirtual 377	com/google/android/gms/measurement/internal/zzt:zza	(Lcom/google/android/gms/measurement/internal/zzfw;)Z
    //   684: pop
    //   685: aload 18
    //   687: invokeinterface 381 1 0
    //   692: anewarray 383	com/google/android/gms/internal/measurement/zzfz
    //   695: astore 19
    //   697: iconst_0
    //   698: istore 20
    //   700: iload 20
    //   702: aload 18
    //   704: invokeinterface 381 1 0
    //   709: if_icmpge +173 -> 882
    //   712: new 383	com/google/android/gms/internal/measurement/zzfz
    //   715: dup
    //   716: invokespecial 384	com/google/android/gms/internal/measurement/zzfz:<init>	()V
    //   719: astore 21
    //   721: aload 19
    //   723: iload 20
    //   725: aload 21
    //   727: aastore
    //   728: aload 21
    //   730: aload 18
    //   732: iload 20
    //   734: invokeinterface 388 2 0
    //   739: checkcast 350	com/google/android/gms/measurement/internal/zzfw
    //   742: getfield 353	com/google/android/gms/measurement/internal/zzfw:name	Ljava/lang/String;
    //   745: putfield 389	com/google/android/gms/internal/measurement/zzfz:name	Ljava/lang/String;
    //   748: aload 21
    //   750: aload 18
    //   752: iload 20
    //   754: invokeinterface 388 2 0
    //   759: checkcast 350	com/google/android/gms/measurement/internal/zzfw
    //   762: getfield 392	com/google/android/gms/measurement/internal/zzfw:zzaum	J
    //   765: invokestatic 191	java/lang/Long:valueOf	(J)Ljava/lang/Long;
    //   768: putfield 395	com/google/android/gms/internal/measurement/zzfz:zzayw	Ljava/lang/Long;
    //   771: aload_0
    //   772: invokevirtual 399	com/google/android/gms/measurement/internal/zzfl:zzjr	()Lcom/google/android/gms/measurement/internal/zzft;
    //   775: aload 21
    //   777: aload 18
    //   779: iload 20
    //   781: invokeinterface 388 2 0
    //   786: checkcast 350	com/google/android/gms/measurement/internal/zzfw
    //   789: getfield 356	com/google/android/gms/measurement/internal/zzfw:value	Ljava/lang/Object;
    //   792: invokevirtual 404	com/google/android/gms/measurement/internal/zzft:zza	(Lcom/google/android/gms/internal/measurement/zzfz;Ljava/lang/Object;)V
    //   795: iinc 20 1
    //   798: goto -98 -> 700
    //   801: lload 10
    //   803: l2i
    //   804: invokestatic 146	java/lang/Integer:valueOf	(I)Ljava/lang/Integer;
    //   807: astore 12
    //   809: goto -531 -> 278
    //   812: astore 51
    //   814: aload_0
    //   815: invokevirtual 66	com/google/android/gms/measurement/internal/zzcr:zzgt	()Lcom/google/android/gms/measurement/internal/zzas;
    //   818: invokevirtual 72	com/google/android/gms/measurement/internal/zzas:zzjn	()Lcom/google/android/gms/measurement/internal/zzau;
    //   821: ldc_w 406
    //   824: aload 51
    //   826: invokevirtual 409	java/lang/SecurityException:getMessage	()Ljava/lang/String;
    //   829: invokevirtual 80	com/google/android/gms/measurement/internal/zzau:zzg	(Ljava/lang/String;Ljava/lang/Object;)V
    //   832: iconst_0
    //   833: newarray byte
    //   835: astore 52
    //   837: aload_0
    //   838: invokevirtual 111	com/google/android/gms/measurement/internal/zzfl:zzjt	()Lcom/google/android/gms/measurement/internal/zzt;
    //   841: invokevirtual 125	com/google/android/gms/measurement/internal/zzt:endTransaction	()V
    //   844: aload 52
    //   846: areturn
    //   847: astore 15
    //   849: aload_0
    //   850: invokevirtual 66	com/google/android/gms/measurement/internal/zzcr:zzgt	()Lcom/google/android/gms/measurement/internal/zzas;
    //   853: invokevirtual 72	com/google/android/gms/measurement/internal/zzas:zzjn	()Lcom/google/android/gms/measurement/internal/zzau;
    //   856: ldc_w 411
    //   859: aload 15
    //   861: invokevirtual 409	java/lang/SecurityException:getMessage	()Ljava/lang/String;
    //   864: invokevirtual 80	com/google/android/gms/measurement/internal/zzau:zzg	(Ljava/lang/String;Ljava/lang/Object;)V
    //   867: iconst_0
    //   868: newarray byte
    //   870: astore 16
    //   872: aload_0
    //   873: invokevirtual 111	com/google/android/gms/measurement/internal/zzfl:zzjt	()Lcom/google/android/gms/measurement/internal/zzt;
    //   876: invokevirtual 125	com/google/android/gms/measurement/internal/zzt:endTransaction	()V
    //   879: aload 16
    //   881: areturn
    //   882: aload 9
    //   884: aload 19
    //   886: putfield 415	com/google/android/gms/internal/measurement/zzfw:zzaxl	[Lcom/google/android/gms/internal/measurement/zzfz;
    //   889: aload_1
    //   890: getfield 419	com/google/android/gms/measurement/internal/zzag:zzahu	Lcom/google/android/gms/measurement/internal/zzad;
    //   893: invokevirtual 425	com/google/android/gms/measurement/internal/zzad:zziy	()Landroid/os/Bundle;
    //   896: astore 22
    //   898: aload 22
    //   900: ldc_w 427
    //   903: lconst_1
    //   904: invokevirtual 433	android/os/Bundle:putLong	(Ljava/lang/String;J)V
    //   907: aload_0
    //   908: invokevirtual 66	com/google/android/gms/measurement/internal/zzcr:zzgt	()Lcom/google/android/gms/measurement/internal/zzas;
    //   911: invokevirtual 72	com/google/android/gms/measurement/internal/zzas:zzjn	()Lcom/google/android/gms/measurement/internal/zzau;
    //   914: ldc_w 435
    //   917: invokevirtual 438	com/google/android/gms/measurement/internal/zzau:zzby	(Ljava/lang/String;)V
    //   920: aload 22
    //   922: ldc_w 440
    //   925: lconst_1
    //   926: invokevirtual 433	android/os/Bundle:putLong	(Ljava/lang/String;J)V
    //   929: aload 22
    //   931: ldc_w 442
    //   934: aload_1
    //   935: getfield 445	com/google/android/gms/measurement/internal/zzag:origin	Ljava/lang/String;
    //   938: invokevirtual 449	android/os/Bundle:putString	(Ljava/lang/String;Ljava/lang/String;)V
    //   941: aload_0
    //   942: invokevirtual 453	com/google/android/gms/measurement/internal/zzcr:zzgr	()Lcom/google/android/gms/measurement/internal/zzfx;
    //   945: aload 9
    //   947: getfield 162	com/google/android/gms/internal/measurement/zzfw:zztt	Ljava/lang/String;
    //   950: invokevirtual 458	com/google/android/gms/measurement/internal/zzfx:zzcz	(Ljava/lang/String;)Z
    //   953: ifeq +35 -> 988
    //   956: aload_0
    //   957: invokevirtual 453	com/google/android/gms/measurement/internal/zzcr:zzgr	()Lcom/google/android/gms/measurement/internal/zzfx;
    //   960: aload 22
    //   962: ldc_w 460
    //   965: lconst_1
    //   966: invokestatic 191	java/lang/Long:valueOf	(J)Ljava/lang/Long;
    //   969: invokevirtual 463	com/google/android/gms/measurement/internal/zzfx:zza	(Landroid/os/Bundle;Ljava/lang/String;Ljava/lang/Object;)V
    //   972: aload_0
    //   973: invokevirtual 453	com/google/android/gms/measurement/internal/zzcr:zzgr	()Lcom/google/android/gms/measurement/internal/zzfx;
    //   976: aload 22
    //   978: ldc_w 440
    //   981: lconst_1
    //   982: invokestatic 191	java/lang/Long:valueOf	(J)Ljava/lang/Long;
    //   985: invokevirtual 463	com/google/android/gms/measurement/internal/zzfx:zza	(Landroid/os/Bundle;Ljava/lang/String;Ljava/lang/Object;)V
    //   988: aload_0
    //   989: invokevirtual 111	com/google/android/gms/measurement/internal/zzfl:zzjt	()Lcom/google/android/gms/measurement/internal/zzt;
    //   992: aload_2
    //   993: aload_1
    //   994: getfield 88	com/google/android/gms/measurement/internal/zzag:name	Ljava/lang/String;
    //   997: invokevirtual 466	com/google/android/gms/measurement/internal/zzt:zzg	(Ljava/lang/String;Ljava/lang/String;)Lcom/google/android/gms/measurement/internal/zzac;
    //   1000: astore 23
    //   1002: aload 23
    //   1004: ifnonnull +246 -> 1250
    //   1007: new 468	com/google/android/gms/measurement/internal/zzac
    //   1010: dup
    //   1011: aload_2
    //   1012: aload_1
    //   1013: getfield 88	com/google/android/gms/measurement/internal/zzag:name	Ljava/lang/String;
    //   1016: lconst_0
    //   1017: lconst_0
    //   1018: aload_1
    //   1019: getfield 257	com/google/android/gms/measurement/internal/zzag:zzaig	J
    //   1022: lconst_0
    //   1023: aconst_null
    //   1024: aconst_null
    //   1025: aconst_null
    //   1026: aconst_null
    //   1027: invokespecial 471	com/google/android/gms/measurement/internal/zzac:<init>	(Ljava/lang/String;Ljava/lang/String;JJJJLjava/lang/Long;Ljava/lang/Long;Ljava/lang/Long;Ljava/lang/Boolean;)V
    //   1030: astore 24
    //   1032: lconst_0
    //   1033: lstore 25
    //   1035: aload_0
    //   1036: invokevirtual 111	com/google/android/gms/measurement/internal/zzfl:zzjt	()Lcom/google/android/gms/measurement/internal/zzt;
    //   1039: aload 24
    //   1041: invokevirtual 474	com/google/android/gms/measurement/internal/zzt:zza	(Lcom/google/android/gms/measurement/internal/zzac;)V
    //   1044: new 476	com/google/android/gms/measurement/internal/zzab
    //   1047: dup
    //   1048: aload_0
    //   1049: getfield 31	com/google/android/gms/measurement/internal/zzdv:zzada	Lcom/google/android/gms/measurement/internal/zzbw;
    //   1052: aload_1
    //   1053: getfield 445	com/google/android/gms/measurement/internal/zzag:origin	Ljava/lang/String;
    //   1056: aload_2
    //   1057: aload_1
    //   1058: getfield 88	com/google/android/gms/measurement/internal/zzag:name	Ljava/lang/String;
    //   1061: aload_1
    //   1062: getfield 257	com/google/android/gms/measurement/internal/zzag:zzaig	J
    //   1065: lload 25
    //   1067: aload 22
    //   1069: invokespecial 479	com/google/android/gms/measurement/internal/zzab:<init>	(Lcom/google/android/gms/measurement/internal/zzbw;Ljava/lang/String;Ljava/lang/String;Ljava/lang/String;JJLandroid/os/Bundle;)V
    //   1072: astore 27
    //   1074: new 481	com/google/android/gms/internal/measurement/zzft
    //   1077: dup
    //   1078: invokespecial 482	com/google/android/gms/internal/measurement/zzft:<init>	()V
    //   1081: astore 28
    //   1083: aload 9
    //   1085: iconst_1
    //   1086: anewarray 481	com/google/android/gms/internal/measurement/zzft
    //   1089: dup
    //   1090: iconst_0
    //   1091: aload 28
    //   1093: aastore
    //   1094: putfield 486	com/google/android/gms/internal/measurement/zzfw:zzaxk	[Lcom/google/android/gms/internal/measurement/zzft;
    //   1097: aload 28
    //   1099: aload 27
    //   1101: getfield 489	com/google/android/gms/measurement/internal/zzab:timestamp	J
    //   1104: invokestatic 191	java/lang/Long:valueOf	(J)Ljava/lang/Long;
    //   1107: putfield 492	com/google/android/gms/internal/measurement/zzft:zzaxd	Ljava/lang/Long;
    //   1110: aload 28
    //   1112: aload 27
    //   1114: getfield 493	com/google/android/gms/measurement/internal/zzab:name	Ljava/lang/String;
    //   1117: putfield 494	com/google/android/gms/internal/measurement/zzft:name	Ljava/lang/String;
    //   1120: aload 28
    //   1122: aload 27
    //   1124: getfield 497	com/google/android/gms/measurement/internal/zzab:zzaht	J
    //   1127: invokestatic 191	java/lang/Long:valueOf	(J)Ljava/lang/Long;
    //   1130: putfield 500	com/google/android/gms/internal/measurement/zzft:zzaxe	Ljava/lang/Long;
    //   1133: aload 28
    //   1135: aload 27
    //   1137: getfield 501	com/google/android/gms/measurement/internal/zzab:zzahu	Lcom/google/android/gms/measurement/internal/zzad;
    //   1140: invokevirtual 502	com/google/android/gms/measurement/internal/zzad:size	()I
    //   1143: anewarray 504	com/google/android/gms/internal/measurement/zzfu
    //   1146: putfield 508	com/google/android/gms/internal/measurement/zzft:zzaxc	[Lcom/google/android/gms/internal/measurement/zzfu;
    //   1149: aload 27
    //   1151: getfield 501	com/google/android/gms/measurement/internal/zzab:zzahu	Lcom/google/android/gms/measurement/internal/zzad;
    //   1154: invokevirtual 509	com/google/android/gms/measurement/internal/zzad:iterator	()Ljava/util/Iterator;
    //   1157: astore 29
    //   1159: iconst_0
    //   1160: istore 30
    //   1162: aload 29
    //   1164: invokeinterface 344 1 0
    //   1169: ifeq +102 -> 1271
    //   1172: aload 29
    //   1174: invokeinterface 348 1 0
    //   1179: checkcast 90	java/lang/String
    //   1182: astore 41
    //   1184: new 504	com/google/android/gms/internal/measurement/zzfu
    //   1187: dup
    //   1188: invokespecial 510	com/google/android/gms/internal/measurement/zzfu:<init>	()V
    //   1191: astore 42
    //   1193: aload 28
    //   1195: getfield 508	com/google/android/gms/internal/measurement/zzft:zzaxc	[Lcom/google/android/gms/internal/measurement/zzfu;
    //   1198: astore 43
    //   1200: iload 30
    //   1202: iconst_1
    //   1203: iadd
    //   1204: istore 44
    //   1206: aload 43
    //   1208: iload 30
    //   1210: aload 42
    //   1212: aastore
    //   1213: aload 42
    //   1215: aload 41
    //   1217: putfield 511	com/google/android/gms/internal/measurement/zzfu:name	Ljava/lang/String;
    //   1220: aload 27
    //   1222: getfield 501	com/google/android/gms/measurement/internal/zzab:zzahu	Lcom/google/android/gms/measurement/internal/zzad;
    //   1225: aload 41
    //   1227: invokevirtual 514	com/google/android/gms/measurement/internal/zzad:get	(Ljava/lang/String;)Ljava/lang/Object;
    //   1230: astore 45
    //   1232: aload_0
    //   1233: invokevirtual 399	com/google/android/gms/measurement/internal/zzfl:zzjr	()Lcom/google/android/gms/measurement/internal/zzft;
    //   1236: aload 42
    //   1238: aload 45
    //   1240: invokevirtual 517	com/google/android/gms/measurement/internal/zzft:zza	(Lcom/google/android/gms/internal/measurement/zzfu;Ljava/lang/Object;)V
    //   1243: iload 44
    //   1245: istore 30
    //   1247: goto -85 -> 1162
    //   1250: aload 23
    //   1252: getfield 520	com/google/android/gms/measurement/internal/zzac:zzahx	J
    //   1255: lstore 25
    //   1257: aload 23
    //   1259: aload_1
    //   1260: getfield 257	com/google/android/gms/measurement/internal/zzag:zzaig	J
    //   1263: invokevirtual 524	com/google/android/gms/measurement/internal/zzac:zzae	(J)Lcom/google/android/gms/measurement/internal/zzac;
    //   1266: astore 24
    //   1268: goto -233 -> 1035
    //   1271: aload 9
    //   1273: invokestatic 530	com/google/android/gms/internal/measurement/zzfe$zzb:zzmp	()Lcom/google/android/gms/internal/measurement/zzfe$zzb$zza;
    //   1276: invokestatic 536	com/google/android/gms/internal/measurement/zzfe$zza:zzmn	()Lcom/google/android/gms/internal/measurement/zzfe$zza$zza;
    //   1279: aload 24
    //   1281: getfield 539	com/google/android/gms/measurement/internal/zzac:zzahv	J
    //   1284: invokevirtual 545	com/google/android/gms/internal/measurement/zzfe$zza$zza:zzan	(J)Lcom/google/android/gms/internal/measurement/zzfe$zza$zza;
    //   1287: aload_1
    //   1288: getfield 88	com/google/android/gms/measurement/internal/zzag:name	Ljava/lang/String;
    //   1291: invokevirtual 549	com/google/android/gms/internal/measurement/zzfe$zza$zza:zzda	(Ljava/lang/String;)Lcom/google/android/gms/internal/measurement/zzfe$zza$zza;
    //   1294: invokevirtual 555	com/google/android/gms/internal/measurement/zzuo$zza:zzwo	()Lcom/google/android/gms/internal/measurement/zzvv;
    //   1297: checkcast 557	com/google/android/gms/internal/measurement/zzuo
    //   1300: checkcast 532	com/google/android/gms/internal/measurement/zzfe$zza
    //   1303: invokevirtual 562	com/google/android/gms/internal/measurement/zzfe$zzb$zza:zzb	(Lcom/google/android/gms/internal/measurement/zzfe$zza;)Lcom/google/android/gms/internal/measurement/zzfe$zzb$zza;
    //   1306: invokevirtual 555	com/google/android/gms/internal/measurement/zzuo$zza:zzwo	()Lcom/google/android/gms/internal/measurement/zzvv;
    //   1309: checkcast 557	com/google/android/gms/internal/measurement/zzuo
    //   1312: checkcast 526	com/google/android/gms/internal/measurement/zzfe$zzb
    //   1315: putfield 566	com/google/android/gms/internal/measurement/zzfw:zzaym	Lcom/google/android/gms/internal/measurement/zzfe$zzb;
    //   1318: aload 9
    //   1320: aload_0
    //   1321: invokevirtual 570	com/google/android/gms/measurement/internal/zzfl:zzjs	()Lcom/google/android/gms/measurement/internal/zzm;
    //   1324: aload 7
    //   1326: invokevirtual 159	com/google/android/gms/measurement/internal/zzg:zzal	()Ljava/lang/String;
    //   1329: aconst_null
    //   1330: aload 9
    //   1332: getfield 415	com/google/android/gms/internal/measurement/zzfw:zzaxl	[Lcom/google/android/gms/internal/measurement/zzfz;
    //   1335: invokevirtual 575	com/google/android/gms/measurement/internal/zzm:zza	(Ljava/lang/String;[Lcom/google/android/gms/internal/measurement/zzft;[Lcom/google/android/gms/internal/measurement/zzfz;)[Lcom/google/android/gms/internal/measurement/zzfr;
    //   1338: putfield 579	com/google/android/gms/internal/measurement/zzfw:zzayc	[Lcom/google/android/gms/internal/measurement/zzfr;
    //   1341: aload 9
    //   1343: aload 28
    //   1345: getfield 492	com/google/android/gms/internal/measurement/zzft:zzaxd	Ljava/lang/Long;
    //   1348: putfield 582	com/google/android/gms/internal/measurement/zzfw:zzaxn	Ljava/lang/Long;
    //   1351: aload 9
    //   1353: aload 28
    //   1355: getfield 492	com/google/android/gms/internal/measurement/zzft:zzaxd	Ljava/lang/Long;
    //   1358: putfield 585	com/google/android/gms/internal/measurement/zzfw:zzaxo	Ljava/lang/Long;
    //   1361: aload 7
    //   1363: invokevirtual 588	com/google/android/gms/measurement/internal/zzg:zzhe	()J
    //   1366: lstore 31
    //   1368: lload 31
    //   1370: lconst_0
    //   1371: lcmp
    //   1372: ifeq +206 -> 1578
    //   1375: lload 31
    //   1377: invokestatic 191	java/lang/Long:valueOf	(J)Ljava/lang/Long;
    //   1380: astore 33
    //   1382: aload 9
    //   1384: aload 33
    //   1386: putfield 591	com/google/android/gms/internal/measurement/zzfw:zzaxq	Ljava/lang/Long;
    //   1389: aload 7
    //   1391: invokevirtual 594	com/google/android/gms/measurement/internal/zzg:zzhd	()J
    //   1394: lstore 34
    //   1396: lload 34
    //   1398: lconst_0
    //   1399: lcmp
    //   1400: ifne +225 -> 1625
    //   1403: lload 31
    //   1405: lconst_0
    //   1406: lcmp
    //   1407: ifeq +177 -> 1584
    //   1410: lload 31
    //   1412: invokestatic 191	java/lang/Long:valueOf	(J)Ljava/lang/Long;
    //   1415: astore 36
    //   1417: aload 9
    //   1419: aload 36
    //   1421: putfield 597	com/google/android/gms/internal/measurement/zzfw:zzaxp	Ljava/lang/Long;
    //   1424: aload 7
    //   1426: invokevirtual 600	com/google/android/gms/measurement/internal/zzg:zzhm	()V
    //   1429: aload 9
    //   1431: aload 7
    //   1433: invokevirtual 603	com/google/android/gms/measurement/internal/zzg:zzhj	()J
    //   1436: l2i
    //   1437: invokestatic 146	java/lang/Integer:valueOf	(I)Ljava/lang/Integer;
    //   1440: putfield 606	com/google/android/gms/internal/measurement/zzfw:zzaya	Ljava/lang/Integer;
    //   1443: aload 9
    //   1445: aload_0
    //   1446: invokevirtual 50	com/google/android/gms/measurement/internal/zzcr:zzgv	()Lcom/google/android/gms/measurement/internal/zzq;
    //   1449: invokevirtual 607	com/google/android/gms/measurement/internal/zzq:zzhh	()J
    //   1452: invokestatic 191	java/lang/Long:valueOf	(J)Ljava/lang/Long;
    //   1455: putfield 610	com/google/android/gms/internal/measurement/zzfw:zzaxw	Ljava/lang/Long;
    //   1458: aload 9
    //   1460: aload_0
    //   1461: invokevirtual 362	com/google/android/gms/measurement/internal/zzcr:zzbx	()Lcom/google/android/gms/common/util/Clock;
    //   1464: invokeinterface 367 1 0
    //   1469: invokestatic 191	java/lang/Long:valueOf	(J)Ljava/lang/Long;
    //   1472: putfield 613	com/google/android/gms/internal/measurement/zzfw:zzaxm	Ljava/lang/Long;
    //   1475: aload 9
    //   1477: getstatic 616	java/lang/Boolean:TRUE	Ljava/lang/Boolean;
    //   1480: putfield 619	com/google/android/gms/internal/measurement/zzfw:zzayb	Ljava/lang/Boolean;
    //   1483: aload 7
    //   1485: aload 9
    //   1487: getfield 582	com/google/android/gms/internal/measurement/zzfw:zzaxn	Ljava/lang/Long;
    //   1490: invokevirtual 622	java/lang/Long:longValue	()J
    //   1493: invokevirtual 626	com/google/android/gms/measurement/internal/zzg:zzo	(J)V
    //   1496: aload 7
    //   1498: aload 9
    //   1500: getfield 585	com/google/android/gms/internal/measurement/zzfw:zzaxo	Ljava/lang/Long;
    //   1503: invokevirtual 622	java/lang/Long:longValue	()J
    //   1506: invokevirtual 629	com/google/android/gms/measurement/internal/zzg:zzp	(J)V
    //   1509: aload_0
    //   1510: invokevirtual 111	com/google/android/gms/measurement/internal/zzfl:zzjt	()Lcom/google/android/gms/measurement/internal/zzt;
    //   1513: aload 7
    //   1515: invokevirtual 632	com/google/android/gms/measurement/internal/zzt:zza	(Lcom/google/android/gms/measurement/internal/zzg;)V
    //   1518: aload_0
    //   1519: invokevirtual 111	com/google/android/gms/measurement/internal/zzfl:zzjt	()Lcom/google/android/gms/measurement/internal/zzt;
    //   1522: invokevirtual 635	com/google/android/gms/measurement/internal/zzt:setTransactionSuccessful	()V
    //   1525: aload_0
    //   1526: invokevirtual 111	com/google/android/gms/measurement/internal/zzfl:zzjt	()Lcom/google/android/gms/measurement/internal/zzt;
    //   1529: invokevirtual 125	com/google/android/gms/measurement/internal/zzt:endTransaction	()V
    //   1532: aload 5
    //   1534: invokevirtual 640	com/google/android/gms/internal/measurement/zzyi:zzvx	()I
    //   1537: newarray byte
    //   1539: astore 38
    //   1541: aload 38
    //   1543: iconst_0
    //   1544: aload 38
    //   1546: arraylength
    //   1547: invokestatic 646	com/google/android/gms/internal/measurement/zzya:zzk	([BII)Lcom/google/android/gms/internal/measurement/zzya;
    //   1550: astore 39
    //   1552: aload 5
    //   1554: aload 39
    //   1556: invokevirtual 649	com/google/android/gms/internal/measurement/zzyi:zza	(Lcom/google/android/gms/internal/measurement/zzya;)V
    //   1559: aload 39
    //   1561: invokevirtual 652	com/google/android/gms/internal/measurement/zzya:zzza	()V
    //   1564: aload_0
    //   1565: invokevirtual 399	com/google/android/gms/measurement/internal/zzfl:zzjr	()Lcom/google/android/gms/measurement/internal/zzft;
    //   1568: aload 38
    //   1570: invokevirtual 655	com/google/android/gms/measurement/internal/zzft:zzb	([B)[B
    //   1573: astore 40
    //   1575: aload 40
    //   1577: areturn
    //   1578: aconst_null
    //   1579: astore 33
    //   1581: goto -199 -> 1382
    //   1584: aconst_null
    //   1585: astore 36
    //   1587: goto -170 -> 1417
    //   1590: astore 6
    //   1592: aload_0
    //   1593: invokevirtual 111	com/google/android/gms/measurement/internal/zzfl:zzjt	()Lcom/google/android/gms/measurement/internal/zzt;
    //   1596: invokevirtual 125	com/google/android/gms/measurement/internal/zzt:endTransaction	()V
    //   1599: aload 6
    //   1601: athrow
    //   1602: astore 37
    //   1604: aload_0
    //   1605: invokevirtual 66	com/google/android/gms/measurement/internal/zzcr:zzgt	()Lcom/google/android/gms/measurement/internal/zzas;
    //   1608: invokevirtual 658	com/google/android/gms/measurement/internal/zzas:zzjg	()Lcom/google/android/gms/measurement/internal/zzau;
    //   1611: ldc_w 660
    //   1614: aload_2
    //   1615: invokestatic 663	com/google/android/gms/measurement/internal/zzas:zzbw	(Ljava/lang/String;)Ljava/lang/Object;
    //   1618: aload 37
    //   1620: invokevirtual 101	com/google/android/gms/measurement/internal/zzau:zze	(Ljava/lang/String;Ljava/lang/Object;Ljava/lang/Object;)V
    //   1623: aconst_null
    //   1624: areturn
    //   1625: lload 34
    //   1627: lstore 31
    //   1629: goto -226 -> 1403
    //   1632: aconst_null
    //   1633: astore 47
    //   1635: goto -1013 -> 622
    //
    // Exception table:
    //   from	to	target	type
    //   424	447	812	java/lang/SecurityException
    //   518	538	847	java/lang/SecurityException
    //   111	121	1590	finally
    //   126	144	1590	finally
    //   154	180	1590	finally
    //   190	266	1590	finally
    //   278	329	1590	finally
    //   329	379	1590	finally
    //   379	401	1590	finally
    //   406	419	1590	finally
    //   424	447	1590	finally
    //   447	460	1590	finally
    //   460	518	1590	finally
    //   518	538	1590	finally
    //   538	586	1590	finally
    //   586	622	1590	finally
    //   627	635	1590	finally
    //   635	685	1590	finally
    //   685	697	1590	finally
    //   700	795	1590	finally
    //   801	809	1590	finally
    //   814	837	1590	finally
    //   849	872	1590	finally
    //   882	988	1590	finally
    //   988	1002	1590	finally
    //   1007	1032	1590	finally
    //   1035	1159	1590	finally
    //   1162	1200	1590	finally
    //   1206	1243	1590	finally
    //   1250	1268	1590	finally
    //   1271	1368	1590	finally
    //   1375	1382	1590	finally
    //   1382	1396	1590	finally
    //   1410	1417	1590	finally
    //   1417	1525	1590	finally
    //   1532	1575	1602	java/io/IOException
  }

  protected final boolean zzgy()
  {
    return false;
  }
}

/* Location:           E:\Study\Tools\apktool2_2\dex2jar-0.0.9.15\classes_viber_2_dex2jar.jar
 * Qualified Name:     com.google.android.gms.measurement.internal.zzdv
 * JD-Core Version:    0.6.2
 */