package com.google.android.gms.measurement.internal;

import android.support.v4.util.ArrayMap;
import android.text.TextUtils;
import com.google.android.gms.common.internal.Preconditions;
import com.google.android.gms.common.util.VisibleForTesting;
import com.google.android.gms.internal.measurement.zzfj;
import com.google.android.gms.internal.measurement.zzfk;
import com.google.android.gms.internal.measurement.zzfl;
import com.google.android.gms.internal.measurement.zzfs;
import com.google.android.gms.internal.measurement.zzfu;
import com.google.android.gms.internal.measurement.zzfz;
import java.math.BigDecimal;
import java.util.ArrayList;
import java.util.Arrays;
import java.util.HashSet;
import java.util.Iterator;
import java.util.List;
import java.util.Locale;
import java.util.Map;
import java.util.Set;
import java.util.regex.Matcher;
import java.util.regex.Pattern;
import java.util.regex.PatternSyntaxException;

final class zzm extends zzfm
{
  zzm(zzfn paramzzfn)
  {
    super(paramzzfn);
  }

  private final Boolean zza(double paramDouble, zzfl paramzzfl)
  {
    try
    {
      Boolean localBoolean = zza(new BigDecimal(paramDouble), paramzzfl, Math.ulp(paramDouble));
      return localBoolean;
    }
    catch (NumberFormatException localNumberFormatException)
    {
    }
    return null;
  }

  private final Boolean zza(long paramLong, zzfl paramzzfl)
  {
    try
    {
      Boolean localBoolean = zza(new BigDecimal(paramLong), paramzzfl, 0.0D);
      return localBoolean;
    }
    catch (NumberFormatException localNumberFormatException)
    {
    }
    return null;
  }

  private final Boolean zza(zzfj paramzzfj, String paramString, zzfu[] paramArrayOfzzfu, long paramLong)
  {
    if (paramzzfj.zzavq != null)
    {
      Boolean localBoolean4 = zza(paramLong, paramzzfj.zzavq);
      if (localBoolean4 == null)
        return null;
      if (!localBoolean4.booleanValue())
        return Boolean.valueOf(false);
    }
    HashSet localHashSet = new HashSet();
    for (zzfk localzzfk2 : paramzzfj.zzavo)
    {
      if (TextUtils.isEmpty(localzzfk2.zzavv))
      {
        zzgt().zzjj().zzg("null or empty param name in filter. event", zzgq().zzbt(paramString));
        return null;
      }
      localHashSet.add(localzzfk2.zzavv);
    }
    ArrayMap localArrayMap = new ArrayMap();
    int k = paramArrayOfzzfu.length;
    int m = 0;
    if (m < k)
    {
      zzfu localzzfu = paramArrayOfzzfu[m];
      if (localHashSet.contains(localzzfu.name))
      {
        if (localzzfu.zzaxg == null)
          break label204;
        localArrayMap.put(localzzfu.name, localzzfu.zzaxg);
      }
      while (true)
      {
        m++;
        break;
        label204: if (localzzfu.zzaup != null)
        {
          localArrayMap.put(localzzfu.name, localzzfu.zzaup);
        }
        else
        {
          if (localzzfu.zzamn == null)
            break label262;
          localArrayMap.put(localzzfu.name, localzzfu.zzamn);
        }
      }
      label262: zzgt().zzjj().zze("Unknown value for param. event, param", zzgq().zzbt(paramString), zzgq().zzbu(localzzfu.name));
      return null;
    }
    for (zzfk localzzfk1 : paramzzfj.zzavo)
    {
      boolean bool1 = Boolean.TRUE.equals(localzzfk1.zzavu);
      String str = localzzfk1.zzavv;
      if (TextUtils.isEmpty(str))
      {
        zzgt().zzjj().zzg("Event has empty param name. event", zzgq().zzbt(paramString));
        return null;
      }
      Object localObject = localArrayMap.get(str);
      if ((localObject instanceof Long))
      {
        if (localzzfk1.zzavt == null)
        {
          zzgt().zzjj().zze("No number filter for long param. event, param", zzgq().zzbt(paramString), zzgq().zzbu(str));
          return null;
        }
        Boolean localBoolean3 = zza(((Long)localObject).longValue(), localzzfk1.zzavt);
        if (localBoolean3 == null)
          return null;
        if (!localBoolean3.booleanValue());
        for (boolean bool4 = true; (bool4 ^ bool1); bool4 = false)
          return Boolean.valueOf(false);
      }
      if ((localObject instanceof Double))
      {
        if (localzzfk1.zzavt == null)
        {
          zzgt().zzjj().zze("No number filter for double param. event, param", zzgq().zzbt(paramString), zzgq().zzbu(str));
          return null;
        }
        Boolean localBoolean2 = zza(((Double)localObject).doubleValue(), localzzfk1.zzavt);
        if (localBoolean2 == null)
          return null;
        if (!localBoolean2.booleanValue());
        for (boolean bool3 = true; (bool3 ^ bool1); bool3 = false)
          return Boolean.valueOf(false);
      }
      if ((localObject instanceof String))
      {
        Boolean localBoolean1;
        if (localzzfk1.zzavs != null)
          localBoolean1 = zza((String)localObject, localzzfk1.zzavs);
        while (localBoolean1 == null)
        {
          return null;
          if (localzzfk1.zzavt != null)
          {
            if (zzft.zzcs((String)localObject))
            {
              localBoolean1 = zza((String)localObject, localzzfk1.zzavt);
            }
            else
            {
              zzgt().zzjj().zze("Invalid param value for number filter. event, param", zzgq().zzbt(paramString), zzgq().zzbu(str));
              return null;
            }
          }
          else
          {
            zzgt().zzjj().zze("No filter for String param. event, param", zzgq().zzbt(paramString), zzgq().zzbu(str));
            return null;
          }
        }
        if (!localBoolean1.booleanValue());
        for (boolean bool2 = true; (bool2 ^ bool1); bool2 = false)
          return Boolean.valueOf(false);
      }
      if (localObject == null)
      {
        zzgt().zzjo().zze("Missing param for filter. event, param", zzgq().zzbt(paramString), zzgq().zzbu(str));
        return Boolean.valueOf(false);
      }
      zzgt().zzjj().zze("Unknown param type. event, param", zzgq().zzbt(paramString), zzgq().zzbu(str));
      return null;
    }
    return Boolean.valueOf(true);
  }

  private final Boolean zza(com.google.android.gms.internal.measurement.zzfm paramzzfm, zzfz paramzzfz)
  {
    zzfk localzzfk = paramzzfm.zzawd;
    if (localzzfk == null)
    {
      zzgt().zzjj().zzg("Missing property filter. property", zzgq().zzbv(paramzzfz.name));
      return null;
    }
    boolean bool = Boolean.TRUE.equals(localzzfk.zzavu);
    if (paramzzfz.zzaxg != null)
    {
      if (localzzfk.zzavt == null)
      {
        zzgt().zzjj().zzg("No number filter for long property. property", zzgq().zzbv(paramzzfz.name));
        return null;
      }
      return zza(zza(paramzzfz.zzaxg.longValue(), localzzfk.zzavt), bool);
    }
    if (paramzzfz.zzaup != null)
    {
      if (localzzfk.zzavt == null)
      {
        zzgt().zzjj().zzg("No number filter for double property. property", zzgq().zzbv(paramzzfz.name));
        return null;
      }
      return zza(zza(paramzzfz.zzaup.doubleValue(), localzzfk.zzavt), bool);
    }
    if (paramzzfz.zzamn != null)
    {
      if (localzzfk.zzavs == null)
      {
        if (localzzfk.zzavt == null)
        {
          zzgt().zzjj().zzg("No string or number filter defined. property", zzgq().zzbv(paramzzfz.name));
          return null;
        }
        if (zzft.zzcs(paramzzfz.zzamn))
          return zza(zza(paramzzfz.zzamn, localzzfk.zzavt), bool);
        zzgt().zzjj().zze("Invalid user property value for Numeric number filter. property, value", zzgq().zzbv(paramzzfz.name), paramzzfz.zzamn);
        return null;
      }
      return zza(zza(paramzzfz.zzamn, localzzfk.zzavs), bool);
    }
    zzgt().zzjj().zzg("User property has no value, property", zzgq().zzbv(paramzzfz.name));
    return null;
  }

  @VisibleForTesting
  private static Boolean zza(Boolean paramBoolean, boolean paramBoolean1)
  {
    if (paramBoolean == null)
      return null;
    return Boolean.valueOf(paramBoolean1 ^ paramBoolean.booleanValue());
  }

  private final Boolean zza(String paramString1, int paramInt, boolean paramBoolean, String paramString2, List<String> paramList, String paramString3)
  {
    if (paramString1 == null)
      return null;
    if (paramInt == 6)
    {
      if ((paramList == null) || (paramList.size() == 0))
        return null;
    }
    else if (paramString2 == null)
      return null;
    if ((paramBoolean) || (paramInt == 1));
    while (true)
      switch (paramInt)
      {
      default:
        return null;
        paramString1 = paramString1.toUpperCase(Locale.ENGLISH);
      case 1:
      case 2:
      case 3:
      case 4:
      case 5:
      case 6:
      }
    int i;
    if (paramBoolean)
      i = 0;
    try
    {
      while (true)
      {
        Boolean localBoolean = Boolean.valueOf(Pattern.compile(paramString3, i).matcher(paramString1).matches());
        return localBoolean;
        i = 66;
      }
    }
    catch (PatternSyntaxException localPatternSyntaxException)
    {
      zzgt().zzjj().zzg("Invalid regular expression in REGEXP audience filter. expression", paramString3);
      return null;
    }
    return Boolean.valueOf(paramString1.startsWith(paramString2));
    return Boolean.valueOf(paramString1.endsWith(paramString2));
    return Boolean.valueOf(paramString1.contains(paramString2));
    return Boolean.valueOf(paramString1.equals(paramString2));
    return Boolean.valueOf(paramList.contains(paramString1));
  }

  private final Boolean zza(String paramString, zzfl paramzzfl)
  {
    if (!zzft.zzcs(paramString))
      return null;
    try
    {
      Boolean localBoolean = zza(new BigDecimal(paramString), paramzzfl, 0.0D);
      return localBoolean;
    }
    catch (NumberFormatException localNumberFormatException)
    {
    }
    return null;
  }

  @VisibleForTesting
  private final Boolean zza(String paramString, com.google.android.gms.internal.measurement.zzfn paramzzfn)
  {
    int i = 0;
    Preconditions.checkNotNull(paramzzfn);
    if (paramString == null);
    do
    {
      do
        return null;
      while ((paramzzfn.zzawe == null) || (paramzzfn.zzawe.intValue() == 0));
      if (paramzzfn.zzawe.intValue() != 6)
        break;
    }
    while ((paramzzfn.zzawh == null) || (paramzzfn.zzawh.length == 0));
    int j = paramzzfn.zzawe.intValue();
    boolean bool;
    label86: String str1;
    label110: Object localObject;
    if ((paramzzfn.zzawg != null) && (paramzzfn.zzawg.booleanValue()))
    {
      bool = true;
      if ((!bool) && (j != 1) && (j != 6))
        break label164;
      str1 = paramzzfn.zzawf;
      if (paramzzfn.zzawh != null)
        break label179;
      localObject = null;
    }
    while (true)
    {
      String str2 = null;
      if (j == 1)
        str2 = str1;
      return zza(paramString, j, bool, str1, (List)localObject, str2);
      if (paramzzfn.zzawf != null)
        break;
      return null;
      bool = false;
      break label86;
      label164: str1 = paramzzfn.zzawf.toUpperCase(Locale.ENGLISH);
      break label110;
      label179: String[] arrayOfString = paramzzfn.zzawh;
      if (bool)
      {
        localObject = Arrays.asList(arrayOfString);
      }
      else
      {
        localObject = new ArrayList();
        int k = arrayOfString.length;
        while (i < k)
        {
          ((List)localObject).add(arrayOfString[i].toUpperCase(Locale.ENGLISH));
          i++;
        }
      }
    }
  }

  @VisibleForTesting
  private static Boolean zza(BigDecimal paramBigDecimal, zzfl paramzzfl, double paramDouble)
  {
    int i = 1;
    Preconditions.checkNotNull(paramzzfl);
    if ((paramzzfl.zzavw == null) || (paramzzfl.zzavw.intValue() == 0))
      return null;
    if (paramzzfl.zzavw.intValue() == 4)
    {
      if ((paramzzfl.zzavz == null) || (paramzzfl.zzawa == null))
        return null;
    }
    else if (paramzzfl.zzavy == null)
      return null;
    int n = paramzzfl.zzavw.intValue();
    if (paramzzfl.zzavw.intValue() == 4)
      if ((!zzft.zzcs(paramzzfl.zzavz)) || (!zzft.zzcs(paramzzfl.zzawa)))
        return null;
    BigDecimal localBigDecimal3;
    BigDecimal localBigDecimal2;
    Object localObject;
    while (true)
    {
      try
      {
        localBigDecimal3 = new BigDecimal(paramzzfl.zzavz);
        localBigDecimal2 = new BigDecimal(paramzzfl.zzawa);
        localObject = null;
        if (n != 4)
          break;
        if (localBigDecimal3 != null)
          break label198;
        return null;
      }
      catch (NumberFormatException localNumberFormatException2)
      {
        return null;
      }
      if (!zzft.zzcs(paramzzfl.zzavy))
        return null;
      try
      {
        BigDecimal localBigDecimal1 = new BigDecimal(paramzzfl.zzavy);
        localObject = localBigDecimal1;
        localBigDecimal2 = null;
        localBigDecimal3 = null;
      }
      catch (NumberFormatException localNumberFormatException1)
      {
        return null;
      }
    }
    if (localObject != null);
    label198: int j;
    int k;
    switch (n)
    {
    default:
      return null;
    case 1:
      if (paramBigDecimal.compareTo(localObject) == -1);
      while (true)
      {
        return Boolean.valueOf(i);
        i = 0;
      }
    case 2:
      if (paramBigDecimal.compareTo(localObject) == i);
      while (true)
      {
        return Boolean.valueOf(i);
        j = 0;
      }
    case 3:
      if (paramDouble != 0.0D)
      {
        if ((paramBigDecimal.compareTo(localObject.subtract(new BigDecimal(paramDouble).multiply(new BigDecimal(2)))) == j) && (paramBigDecimal.compareTo(localObject.add(new BigDecimal(paramDouble).multiply(new BigDecimal(2)))) == -1));
        while (true)
        {
          return Boolean.valueOf(j);
          k = 0;
        }
      }
      if (paramBigDecimal.compareTo(localObject) == 0);
      while (true)
      {
        return Boolean.valueOf(k);
        k = 0;
      }
    case 4:
    }
    if ((paramBigDecimal.compareTo(localBigDecimal3) != -1) && (paramBigDecimal.compareTo(localBigDecimal2) != k));
    while (true)
    {
      return Boolean.valueOf(k);
      int m = 0;
    }
  }

  private static void zza(Map<Integer, Long> paramMap, int paramInt, long paramLong)
  {
    Long localLong = (Long)paramMap.get(Integer.valueOf(paramInt));
    long l = paramLong / 1000L;
    if ((localLong == null) || (l > localLong.longValue()))
      paramMap.put(Integer.valueOf(paramInt), Long.valueOf(l));
  }

  private static void zzb(Map<Integer, List<Long>> paramMap, int paramInt, long paramLong)
  {
    Object localObject = (List)paramMap.get(Integer.valueOf(paramInt));
    if (localObject == null)
    {
      localObject = new ArrayList();
      paramMap.put(Integer.valueOf(paramInt), localObject);
    }
    ((List)localObject).add(Long.valueOf(paramLong / 1000L));
  }

  private static zzfs[] zzb(Map<Integer, Long> paramMap)
  {
    if (paramMap == null)
      return null;
    zzfs[] arrayOfzzfs = new zzfs[paramMap.size()];
    Iterator localIterator = paramMap.keySet().iterator();
    int j;
    for (int i = 0; localIterator.hasNext(); i = j)
    {
      Integer localInteger = (Integer)localIterator.next();
      zzfs localzzfs = new zzfs();
      localzzfs.zzawz = localInteger;
      localzzfs.zzaxa = ((Long)paramMap.get(localInteger));
      j = i + 1;
      arrayOfzzfs[i] = localzzfs;
    }
    return arrayOfzzfs;
  }

  // ERROR //
  final com.google.android.gms.internal.measurement.zzfr[] zza(String paramString, com.google.android.gms.internal.measurement.zzft[] paramArrayOfzzft, zzfz[] paramArrayOfzzfz)
  {
    // Byte code:
    //   0: aload_1
    //   1: invokestatic 404	com/google/android/gms/common/internal/Preconditions:checkNotEmpty	(Ljava/lang/String;)Ljava/lang/String;
    //   4: pop
    //   5: new 51	java/util/HashSet
    //   8: dup
    //   9: invokespecial 54	java/util/HashSet:<init>	()V
    //   12: astore 5
    //   14: new 108	android/support/v4/util/ArrayMap
    //   17: dup
    //   18: invokespecial 109	android/support/v4/util/ArrayMap:<init>	()V
    //   21: astore 6
    //   23: new 108	android/support/v4/util/ArrayMap
    //   26: dup
    //   27: invokespecial 109	android/support/v4/util/ArrayMap:<init>	()V
    //   30: astore 7
    //   32: new 108	android/support/v4/util/ArrayMap
    //   35: dup
    //   36: invokespecial 109	android/support/v4/util/ArrayMap:<init>	()V
    //   39: astore 8
    //   41: new 108	android/support/v4/util/ArrayMap
    //   44: dup
    //   45: invokespecial 109	android/support/v4/util/ArrayMap:<init>	()V
    //   48: astore 9
    //   50: new 108	android/support/v4/util/ArrayMap
    //   53: dup
    //   54: invokespecial 109	android/support/v4/util/ArrayMap:<init>	()V
    //   57: astore 10
    //   59: aload_0
    //   60: invokevirtual 408	com/google/android/gms/measurement/internal/zzcr:zzgv	()Lcom/google/android/gms/measurement/internal/zzq;
    //   63: aload_1
    //   64: invokevirtual 413	com/google/android/gms/measurement/internal/zzq:zzbb	(Ljava/lang/String;)Z
    //   67: istore 11
    //   69: aload_0
    //   70: invokevirtual 419	com/google/android/gms/measurement/internal/zzfl:zzjt	()Lcom/google/android/gms/measurement/internal/zzt;
    //   73: aload_1
    //   74: invokevirtual 425	com/google/android/gms/measurement/internal/zzt:zzbp	(Ljava/lang/String;)Ljava/util/Map;
    //   77: astore 12
    //   79: aload 12
    //   81: ifnull +498 -> 579
    //   84: aload 12
    //   86: invokeinterface 376 1 0
    //   91: invokeinterface 380 1 0
    //   96: astore 182
    //   98: aload 182
    //   100: invokeinterface 385 1 0
    //   105: ifeq +474 -> 579
    //   108: aload 182
    //   110: invokeinterface 389 1 0
    //   115: checkcast 303	java/lang/Integer
    //   118: invokevirtual 306	java/lang/Integer:intValue	()I
    //   121: istore 183
    //   123: aload 12
    //   125: iload 183
    //   127: invokestatic 362	java/lang/Integer:valueOf	(I)Ljava/lang/Integer;
    //   130: invokeinterface 159 2 0
    //   135: checkcast 427	com/google/android/gms/internal/measurement/zzfx
    //   138: astore 184
    //   140: aload 7
    //   142: iload 183
    //   144: invokestatic 362	java/lang/Integer:valueOf	(I)Ljava/lang/Integer;
    //   147: invokeinterface 159 2 0
    //   152: checkcast 429	java/util/BitSet
    //   155: astore 185
    //   157: aload 8
    //   159: iload 183
    //   161: invokestatic 362	java/lang/Integer:valueOf	(I)Ljava/lang/Integer;
    //   164: invokeinterface 159 2 0
    //   169: checkcast 429	java/util/BitSet
    //   172: astore 186
    //   174: iload 11
    //   176: ifeq +4204 -> 4380
    //   179: new 108	android/support/v4/util/ArrayMap
    //   182: dup
    //   183: invokespecial 109	android/support/v4/util/ArrayMap:<init>	()V
    //   186: astore 187
    //   188: aload 184
    //   190: ifnull +11 -> 201
    //   193: aload 184
    //   195: getfield 433	com/google/android/gms/internal/measurement/zzfx:zzayr	[Lcom/google/android/gms/internal/measurement/zzfs;
    //   198: ifnonnull +201 -> 399
    //   201: aload 9
    //   203: iload 183
    //   205: invokestatic 362	java/lang/Integer:valueOf	(I)Ljava/lang/Integer;
    //   208: aload 187
    //   210: invokeinterface 127 3 0
    //   215: pop
    //   216: aload 187
    //   218: astore 189
    //   220: aload 185
    //   222: ifnonnull +51 -> 273
    //   225: new 429	java/util/BitSet
    //   228: dup
    //   229: invokespecial 434	java/util/BitSet:<init>	()V
    //   232: astore 185
    //   234: aload 7
    //   236: iload 183
    //   238: invokestatic 362	java/lang/Integer:valueOf	(I)Ljava/lang/Integer;
    //   241: aload 185
    //   243: invokeinterface 127 3 0
    //   248: pop
    //   249: new 429	java/util/BitSet
    //   252: dup
    //   253: invokespecial 434	java/util/BitSet:<init>	()V
    //   256: astore 186
    //   258: aload 8
    //   260: iload 183
    //   262: invokestatic 362	java/lang/Integer:valueOf	(I)Ljava/lang/Integer;
    //   265: aload 186
    //   267: invokeinterface 127 3 0
    //   272: pop
    //   273: iconst_0
    //   274: istore 192
    //   276: iload 192
    //   278: aload 184
    //   280: getfield 438	com/google/android/gms/internal/measurement/zzfx:zzayp	[J
    //   283: arraylength
    //   284: bipush 6
    //   286: ishl
    //   287: if_icmpge +173 -> 460
    //   290: aload 184
    //   292: getfield 438	com/google/android/gms/internal/measurement/zzfx:zzayp	[J
    //   295: iload 192
    //   297: invokestatic 441	com/google/android/gms/measurement/internal/zzft:zza	([JI)Z
    //   300: istore 196
    //   302: iconst_0
    //   303: istore 197
    //   305: iload 196
    //   307: ifeq +63 -> 370
    //   310: aload_0
    //   311: invokevirtual 76	com/google/android/gms/measurement/internal/zzcr:zzgt	()Lcom/google/android/gms/measurement/internal/zzas;
    //   314: invokevirtual 205	com/google/android/gms/measurement/internal/zzas:zzjo	()Lcom/google/android/gms/measurement/internal/zzau;
    //   317: ldc_w 443
    //   320: iload 183
    //   322: invokestatic 362	java/lang/Integer:valueOf	(I)Ljava/lang/Integer;
    //   325: iload 192
    //   327: invokestatic 362	java/lang/Integer:valueOf	(I)Ljava/lang/Integer;
    //   330: invokevirtual 143	com/google/android/gms/measurement/internal/zzau:zze	(Ljava/lang/String;Ljava/lang/Object;Ljava/lang/Object;)V
    //   333: aload 186
    //   335: iload 192
    //   337: invokevirtual 446	java/util/BitSet:set	(I)V
    //   340: aload 184
    //   342: getfield 449	com/google/android/gms/internal/measurement/zzfx:zzayq	[J
    //   345: iload 192
    //   347: invokestatic 441	com/google/android/gms/measurement/internal/zzft:zza	([JI)Z
    //   350: istore 199
    //   352: iconst_0
    //   353: istore 197
    //   355: iload 199
    //   357: ifeq +13 -> 370
    //   360: aload 185
    //   362: iload 192
    //   364: invokevirtual 446	java/util/BitSet:set	(I)V
    //   367: iconst_1
    //   368: istore 197
    //   370: aload 189
    //   372: ifnull +21 -> 393
    //   375: iload 197
    //   377: ifne +16 -> 393
    //   380: aload 189
    //   382: iload 192
    //   384: invokestatic 362	java/lang/Integer:valueOf	(I)Ljava/lang/Integer;
    //   387: invokeinterface 452 2 0
    //   392: pop
    //   393: iinc 192 1
    //   396: goto -120 -> 276
    //   399: aload 184
    //   401: getfield 433	com/google/android/gms/internal/measurement/zzfx:zzayr	[Lcom/google/android/gms/internal/measurement/zzfs;
    //   404: astore 200
    //   406: aload 200
    //   408: arraylength
    //   409: istore 201
    //   411: iconst_0
    //   412: istore 202
    //   414: iload 202
    //   416: iload 201
    //   418: if_icmpge -217 -> 201
    //   421: aload 200
    //   423: iload 202
    //   425: aaload
    //   426: astore 203
    //   428: aload 203
    //   430: getfield 393	com/google/android/gms/internal/measurement/zzfs:zzawz	Ljava/lang/Integer;
    //   433: ifnull +21 -> 454
    //   436: aload 187
    //   438: aload 203
    //   440: getfield 393	com/google/android/gms/internal/measurement/zzfs:zzawz	Ljava/lang/Integer;
    //   443: aload 203
    //   445: getfield 396	com/google/android/gms/internal/measurement/zzfs:zzaxa	Ljava/lang/Long;
    //   448: invokeinterface 127 3 0
    //   453: pop
    //   454: iinc 202 1
    //   457: goto -43 -> 414
    //   460: new 454	com/google/android/gms/internal/measurement/zzfr
    //   463: dup
    //   464: invokespecial 455	com/google/android/gms/internal/measurement/zzfr:<init>	()V
    //   467: astore 193
    //   469: aload 6
    //   471: iload 183
    //   473: invokestatic 362	java/lang/Integer:valueOf	(I)Ljava/lang/Integer;
    //   476: aload 193
    //   478: invokeinterface 127 3 0
    //   483: pop
    //   484: aload 193
    //   486: iconst_0
    //   487: invokestatic 49	java/lang/Boolean:valueOf	(Z)Ljava/lang/Boolean;
    //   490: putfield 458	com/google/android/gms/internal/measurement/zzfr:zzawx	Ljava/lang/Boolean;
    //   493: aload 193
    //   495: aload 184
    //   497: putfield 462	com/google/android/gms/internal/measurement/zzfr:zzaww	Lcom/google/android/gms/internal/measurement/zzfx;
    //   500: aload 193
    //   502: new 427	com/google/android/gms/internal/measurement/zzfx
    //   505: dup
    //   506: invokespecial 463	com/google/android/gms/internal/measurement/zzfx:<init>	()V
    //   509: putfield 466	com/google/android/gms/internal/measurement/zzfr:zzawv	Lcom/google/android/gms/internal/measurement/zzfx;
    //   512: aload 193
    //   514: getfield 466	com/google/android/gms/internal/measurement/zzfr:zzawv	Lcom/google/android/gms/internal/measurement/zzfx;
    //   517: aload 185
    //   519: invokestatic 469	com/google/android/gms/measurement/internal/zzft:zza	(Ljava/util/BitSet;)[J
    //   522: putfield 449	com/google/android/gms/internal/measurement/zzfx:zzayq	[J
    //   525: aload 193
    //   527: getfield 466	com/google/android/gms/internal/measurement/zzfr:zzawv	Lcom/google/android/gms/internal/measurement/zzfx;
    //   530: aload 186
    //   532: invokestatic 469	com/google/android/gms/measurement/internal/zzft:zza	(Ljava/util/BitSet;)[J
    //   535: putfield 438	com/google/android/gms/internal/measurement/zzfx:zzayp	[J
    //   538: iload 11
    //   540: ifeq -442 -> 98
    //   543: aload 193
    //   545: getfield 466	com/google/android/gms/internal/measurement/zzfr:zzawv	Lcom/google/android/gms/internal/measurement/zzfx;
    //   548: aload 189
    //   550: invokestatic 471	com/google/android/gms/measurement/internal/zzm:zzb	(Ljava/util/Map;)[Lcom/google/android/gms/internal/measurement/zzfs;
    //   553: putfield 433	com/google/android/gms/internal/measurement/zzfx:zzayr	[Lcom/google/android/gms/internal/measurement/zzfs;
    //   556: aload 10
    //   558: iload 183
    //   560: invokestatic 362	java/lang/Integer:valueOf	(I)Ljava/lang/Integer;
    //   563: new 108	android/support/v4/util/ArrayMap
    //   566: dup
    //   567: invokespecial 109	android/support/v4/util/ArrayMap:<init>	()V
    //   570: invokeinterface 127 3 0
    //   575: pop
    //   576: goto -478 -> 98
    //   579: aload_2
    //   580: ifnull +1907 -> 2487
    //   583: aconst_null
    //   584: astore 89
    //   586: lconst_0
    //   587: lstore 90
    //   589: aconst_null
    //   590: astore 92
    //   592: new 108	android/support/v4/util/ArrayMap
    //   595: dup
    //   596: invokespecial 109	android/support/v4/util/ArrayMap:<init>	()V
    //   599: astore 93
    //   601: aload_2
    //   602: arraylength
    //   603: istore 94
    //   605: iconst_0
    //   606: istore 95
    //   608: iload 95
    //   610: iload 94
    //   612: if_icmpge +1875 -> 2487
    //   615: aload_2
    //   616: iload 95
    //   618: aaload
    //   619: astore 96
    //   621: aload 96
    //   623: getfield 474	com/google/android/gms/internal/measurement/zzft:name	Ljava/lang/String;
    //   626: astore 97
    //   628: aload 96
    //   630: getfield 478	com/google/android/gms/internal/measurement/zzft:zzaxc	[Lcom/google/android/gms/internal/measurement/zzfu;
    //   633: astore 98
    //   635: aload_0
    //   636: invokevirtual 408	com/google/android/gms/measurement/internal/zzcr:zzgv	()Lcom/google/android/gms/measurement/internal/zzq;
    //   639: aload_1
    //   640: getstatic 484	com/google/android/gms/measurement/internal/zzai:zzaki	Lcom/google/android/gms/measurement/internal/zzai$zza;
    //   643: invokevirtual 488	com/google/android/gms/measurement/internal/zzq:zzd	(Ljava/lang/String;Lcom/google/android/gms/measurement/internal/zzai$zza;)Z
    //   646: ifeq +3637 -> 4283
    //   649: aload_0
    //   650: invokevirtual 492	com/google/android/gms/measurement/internal/zzfl:zzjr	()Lcom/google/android/gms/measurement/internal/zzft;
    //   653: pop
    //   654: aload 96
    //   656: ldc_w 494
    //   659: invokestatic 497	com/google/android/gms/measurement/internal/zzft:zzb	(Lcom/google/android/gms/internal/measurement/zzft;Ljava/lang/String;)Ljava/lang/Object;
    //   662: checkcast 161	java/lang/Long
    //   665: astore 149
    //   667: aload 149
    //   669: ifnull +77 -> 746
    //   672: iconst_1
    //   673: istore 150
    //   675: iload 150
    //   677: ifeq +75 -> 752
    //   680: aload 97
    //   682: ldc_w 499
    //   685: invokevirtual 286	java/lang/String:equals	(Ljava/lang/Object;)Z
    //   688: ifeq +64 -> 752
    //   691: iconst_1
    //   692: istore 151
    //   694: iload 151
    //   696: ifeq +724 -> 1420
    //   699: aload_0
    //   700: invokevirtual 492	com/google/android/gms/measurement/internal/zzfl:zzjr	()Lcom/google/android/gms/measurement/internal/zzft;
    //   703: pop
    //   704: aload 96
    //   706: ldc_w 501
    //   709: invokestatic 497	com/google/android/gms/measurement/internal/zzft:zzb	(Lcom/google/android/gms/internal/measurement/zzft;Ljava/lang/String;)Ljava/lang/Object;
    //   712: checkcast 182	java/lang/String
    //   715: astore 159
    //   717: aload 159
    //   719: invokestatic 70	android/text/TextUtils:isEmpty	(Ljava/lang/CharSequence;)Z
    //   722: ifeq +36 -> 758
    //   725: aload_0
    //   726: invokevirtual 76	com/google/android/gms/measurement/internal/zzcr:zzgt	()Lcom/google/android/gms/measurement/internal/zzas;
    //   729: invokevirtual 504	com/google/android/gms/measurement/internal/zzas:zzjg	()Lcom/google/android/gms/measurement/internal/zzau;
    //   732: ldc_w 506
    //   735: aload 149
    //   737: invokevirtual 100	com/google/android/gms/measurement/internal/zzau:zzg	(Ljava/lang/String;Ljava/lang/Object;)V
    //   740: iinc 95 1
    //   743: goto -135 -> 608
    //   746: iconst_0
    //   747: istore 150
    //   749: goto -74 -> 675
    //   752: iconst_0
    //   753: istore 151
    //   755: goto -61 -> 694
    //   758: aload 89
    //   760: ifnull +22 -> 782
    //   763: aload 92
    //   765: ifnull +17 -> 782
    //   768: aload 149
    //   770: invokevirtual 170	java/lang/Long:longValue	()J
    //   773: aload 92
    //   775: invokevirtual 170	java/lang/Long:longValue	()J
    //   778: lcmp
    //   779: ifeq +3527 -> 4306
    //   782: aload_0
    //   783: invokevirtual 419	com/google/android/gms/measurement/internal/zzfl:zzjt	()Lcom/google/android/gms/measurement/internal/zzt;
    //   786: aload_1
    //   787: aload 149
    //   789: invokevirtual 509	com/google/android/gms/measurement/internal/zzt:zza	(Ljava/lang/String;Ljava/lang/Long;)Landroid/util/Pair;
    //   792: astore 160
    //   794: aload 160
    //   796: ifnull +11 -> 807
    //   799: aload 160
    //   801: getfield 515	android/util/Pair:first	Ljava/lang/Object;
    //   804: ifnonnull +23 -> 827
    //   807: aload_0
    //   808: invokevirtual 76	com/google/android/gms/measurement/internal/zzcr:zzgt	()Lcom/google/android/gms/measurement/internal/zzas;
    //   811: invokevirtual 504	com/google/android/gms/measurement/internal/zzas:zzjg	()Lcom/google/android/gms/measurement/internal/zzau;
    //   814: ldc_w 517
    //   817: aload 159
    //   819: aload 149
    //   821: invokevirtual 143	com/google/android/gms/measurement/internal/zzau:zze	(Ljava/lang/String;Ljava/lang/Object;Ljava/lang/Object;)V
    //   824: goto -84 -> 740
    //   827: aload 160
    //   829: getfield 515	android/util/Pair:first	Ljava/lang/Object;
    //   832: checkcast 473	com/google/android/gms/internal/measurement/zzft
    //   835: astore 161
    //   837: aload 160
    //   839: getfield 520	android/util/Pair:second	Ljava/lang/Object;
    //   842: checkcast 161	java/lang/Long
    //   845: invokevirtual 170	java/lang/Long:longValue	()J
    //   848: lstore 90
    //   850: aload_0
    //   851: invokevirtual 492	com/google/android/gms/measurement/internal/zzfl:zzjr	()Lcom/google/android/gms/measurement/internal/zzft;
    //   854: pop
    //   855: aload 161
    //   857: ldc_w 494
    //   860: invokestatic 497	com/google/android/gms/measurement/internal/zzft:zzb	(Lcom/google/android/gms/internal/measurement/zzft;Ljava/lang/String;)Ljava/lang/Object;
    //   863: checkcast 161	java/lang/Long
    //   866: astore 163
    //   868: aload 161
    //   870: astore 89
    //   872: lload 90
    //   874: lconst_1
    //   875: lsub
    //   876: lstore 164
    //   878: lload 164
    //   880: lconst_0
    //   881: lcmp
    //   882: ifgt +157 -> 1039
    //   885: aload_0
    //   886: invokevirtual 419	com/google/android/gms/measurement/internal/zzfl:zzjt	()Lcom/google/android/gms/measurement/internal/zzt;
    //   889: astore 180
    //   891: aload 180
    //   893: invokevirtual 523	com/google/android/gms/measurement/internal/zzcr:zzaf	()V
    //   896: aload 180
    //   898: invokevirtual 76	com/google/android/gms/measurement/internal/zzcr:zzgt	()Lcom/google/android/gms/measurement/internal/zzas;
    //   901: invokevirtual 205	com/google/android/gms/measurement/internal/zzas:zzjo	()Lcom/google/android/gms/measurement/internal/zzau;
    //   904: ldc_w 525
    //   907: aload_1
    //   908: invokevirtual 100	com/google/android/gms/measurement/internal/zzau:zzg	(Ljava/lang/String;Ljava/lang/Object;)V
    //   911: aload 180
    //   913: invokevirtual 529	com/google/android/gms/measurement/internal/zzt:getWritableDatabase	()Landroid/database/sqlite/SQLiteDatabase;
    //   916: ldc_w 531
    //   919: iconst_1
    //   920: anewarray 182	java/lang/String
    //   923: dup
    //   924: iconst_0
    //   925: aload_1
    //   926: aastore
    //   927: invokevirtual 537	android/database/sqlite/SQLiteDatabase:execSQL	(Ljava/lang/String;[Ljava/lang/Object;)V
    //   930: aload 89
    //   932: getfield 478	com/google/android/gms/internal/measurement/zzft:zzaxc	[Lcom/google/android/gms/internal/measurement/zzfu;
    //   935: arraylength
    //   936: aload 98
    //   938: arraylength
    //   939: iadd
    //   940: anewarray 111	com/google/android/gms/internal/measurement/zzfu
    //   943: astore 167
    //   945: iconst_0
    //   946: istore 168
    //   948: aload 89
    //   950: getfield 478	com/google/android/gms/internal/measurement/zzft:zzaxc	[Lcom/google/android/gms/internal/measurement/zzfu;
    //   953: astore 169
    //   955: aload 169
    //   957: arraylength
    //   958: istore 170
    //   960: iconst_0
    //   961: istore 171
    //   963: iload 171
    //   965: iload 170
    //   967: if_icmpge +90 -> 1057
    //   970: aload 169
    //   972: iload 171
    //   974: aaload
    //   975: astore 177
    //   977: aload_0
    //   978: invokevirtual 492	com/google/android/gms/measurement/internal/zzfl:zzjr	()Lcom/google/android/gms/measurement/internal/zzft;
    //   981: pop
    //   982: aload 96
    //   984: aload 177
    //   986: getfield 114	com/google/android/gms/internal/measurement/zzfu:name	Ljava/lang/String;
    //   989: invokestatic 540	com/google/android/gms/measurement/internal/zzft:zza	(Lcom/google/android/gms/internal/measurement/zzft;Ljava/lang/String;)Lcom/google/android/gms/internal/measurement/zzfu;
    //   992: ifnonnull +3381 -> 4373
    //   995: iload 168
    //   997: iconst_1
    //   998: iadd
    //   999: istore 179
    //   1001: aload 167
    //   1003: iload 168
    //   1005: aload 177
    //   1007: aastore
    //   1008: iinc 171 1
    //   1011: iload 179
    //   1013: istore 168
    //   1015: goto -52 -> 963
    //   1018: astore 181
    //   1020: aload 180
    //   1022: invokevirtual 76	com/google/android/gms/measurement/internal/zzcr:zzgt	()Lcom/google/android/gms/measurement/internal/zzas;
    //   1025: invokevirtual 504	com/google/android/gms/measurement/internal/zzas:zzjg	()Lcom/google/android/gms/measurement/internal/zzau;
    //   1028: ldc_w 542
    //   1031: aload 181
    //   1033: invokevirtual 100	com/google/android/gms/measurement/internal/zzau:zzg	(Ljava/lang/String;Ljava/lang/Object;)V
    //   1036: goto -106 -> 930
    //   1039: aload_0
    //   1040: invokevirtual 419	com/google/android/gms/measurement/internal/zzfl:zzjt	()Lcom/google/android/gms/measurement/internal/zzt;
    //   1043: aload_1
    //   1044: aload 149
    //   1046: lload 164
    //   1048: aload 89
    //   1050: invokevirtual 545	com/google/android/gms/measurement/internal/zzt:zza	(Ljava/lang/String;Ljava/lang/Long;JLcom/google/android/gms/internal/measurement/zzft;)Z
    //   1053: pop
    //   1054: goto -124 -> 930
    //   1057: iload 168
    //   1059: ifle +323 -> 1382
    //   1062: aload 98
    //   1064: arraylength
    //   1065: istore 172
    //   1067: iconst_0
    //   1068: istore 173
    //   1070: iload 173
    //   1072: iload 172
    //   1074: if_icmpge +33 -> 1107
    //   1077: aload 98
    //   1079: iload 173
    //   1081: aaload
    //   1082: astore 175
    //   1084: iload 168
    //   1086: iconst_1
    //   1087: iadd
    //   1088: istore 176
    //   1090: aload 167
    //   1092: iload 168
    //   1094: aload 175
    //   1096: aastore
    //   1097: iinc 173 1
    //   1100: iload 176
    //   1102: istore 168
    //   1104: goto -34 -> 1070
    //   1107: iload 168
    //   1109: aload 167
    //   1111: arraylength
    //   1112: if_icmpne +255 -> 1367
    //   1115: aload 167
    //   1117: astore 174
    //   1119: aload 174
    //   1121: astore 99
    //   1123: aload 159
    //   1125: astore 100
    //   1127: aload 163
    //   1129: astore 101
    //   1131: lload 164
    //   1133: lstore 102
    //   1135: aload 89
    //   1137: astore 104
    //   1139: aload_0
    //   1140: invokevirtual 419	com/google/android/gms/measurement/internal/zzfl:zzjt	()Lcom/google/android/gms/measurement/internal/zzt;
    //   1143: aload_1
    //   1144: aload 96
    //   1146: getfield 474	com/google/android/gms/internal/measurement/zzft:name	Ljava/lang/String;
    //   1149: invokevirtual 548	com/google/android/gms/measurement/internal/zzt:zzg	(Ljava/lang/String;Ljava/lang/String;)Lcom/google/android/gms/measurement/internal/zzac;
    //   1152: astore 105
    //   1154: aload 105
    //   1156: ifnonnull +395 -> 1551
    //   1159: aload_0
    //   1160: invokevirtual 76	com/google/android/gms/measurement/internal/zzcr:zzgt	()Lcom/google/android/gms/measurement/internal/zzas;
    //   1163: invokevirtual 82	com/google/android/gms/measurement/internal/zzas:zzjj	()Lcom/google/android/gms/measurement/internal/zzau;
    //   1166: ldc_w 550
    //   1169: aload_1
    //   1170: invokestatic 554	com/google/android/gms/measurement/internal/zzas:zzbw	(Ljava/lang/String;)Ljava/lang/Object;
    //   1173: aload_0
    //   1174: invokevirtual 88	com/google/android/gms/measurement/internal/zzcr:zzgq	()Lcom/google/android/gms/measurement/internal/zzaq;
    //   1177: aload 100
    //   1179: invokevirtual 94	com/google/android/gms/measurement/internal/zzaq:zzbt	(Ljava/lang/String;)Ljava/lang/String;
    //   1182: invokevirtual 143	com/google/android/gms/measurement/internal/zzau:zze	(Ljava/lang/String;Ljava/lang/Object;Ljava/lang/Object;)V
    //   1185: new 556	com/google/android/gms/measurement/internal/zzac
    //   1188: dup
    //   1189: aload_1
    //   1190: aload 96
    //   1192: getfield 474	com/google/android/gms/internal/measurement/zzft:name	Ljava/lang/String;
    //   1195: lconst_1
    //   1196: lconst_1
    //   1197: aload 96
    //   1199: getfield 559	com/google/android/gms/internal/measurement/zzft:zzaxd	Ljava/lang/Long;
    //   1202: invokevirtual 170	java/lang/Long:longValue	()J
    //   1205: lconst_0
    //   1206: aconst_null
    //   1207: aconst_null
    //   1208: aconst_null
    //   1209: aconst_null
    //   1210: invokespecial 562	com/google/android/gms/measurement/internal/zzac:<init>	(Ljava/lang/String;Ljava/lang/String;JJJJLjava/lang/Long;Ljava/lang/Long;Ljava/lang/Long;Ljava/lang/Boolean;)V
    //   1213: astore 106
    //   1215: aload_0
    //   1216: invokevirtual 419	com/google/android/gms/measurement/internal/zzfl:zzjt	()Lcom/google/android/gms/measurement/internal/zzt;
    //   1219: aload 106
    //   1221: invokevirtual 565	com/google/android/gms/measurement/internal/zzt:zza	(Lcom/google/android/gms/measurement/internal/zzac;)V
    //   1224: aload 106
    //   1226: getfield 569	com/google/android/gms/measurement/internal/zzac:zzahv	J
    //   1229: lstore 107
    //   1231: aload 93
    //   1233: aload 100
    //   1235: invokeinterface 159 2 0
    //   1240: checkcast 123	java/util/Map
    //   1243: astore 109
    //   1245: aload 109
    //   1247: ifnonnull +3119 -> 4366
    //   1250: aload_0
    //   1251: invokevirtual 419	com/google/android/gms/measurement/internal/zzfl:zzjt	()Lcom/google/android/gms/measurement/internal/zzt;
    //   1254: aload_1
    //   1255: aload 100
    //   1257: invokevirtual 573	com/google/android/gms/measurement/internal/zzt:zzl	(Ljava/lang/String;Ljava/lang/String;)Ljava/util/Map;
    //   1260: astore 146
    //   1262: aload 146
    //   1264: ifnonnull +12 -> 1276
    //   1267: new 108	android/support/v4/util/ArrayMap
    //   1270: dup
    //   1271: invokespecial 109	android/support/v4/util/ArrayMap:<init>	()V
    //   1274: astore 146
    //   1276: aload 93
    //   1278: aload 100
    //   1280: aload 146
    //   1282: invokeinterface 127 3 0
    //   1287: pop
    //   1288: aload 146
    //   1290: astore 110
    //   1292: aload 110
    //   1294: invokeinterface 376 1 0
    //   1299: invokeinterface 380 1 0
    //   1304: astore 111
    //   1306: aload 111
    //   1308: invokeinterface 385 1 0
    //   1313: ifeq +3038 -> 4351
    //   1316: aload 111
    //   1318: invokeinterface 389 1 0
    //   1323: checkcast 303	java/lang/Integer
    //   1326: invokevirtual 306	java/lang/Integer:intValue	()I
    //   1329: istore 112
    //   1331: aload 5
    //   1333: iload 112
    //   1335: invokestatic 362	java/lang/Integer:valueOf	(I)Ljava/lang/Integer;
    //   1338: invokeinterface 117 2 0
    //   1343: ifeq +274 -> 1617
    //   1346: aload_0
    //   1347: invokevirtual 76	com/google/android/gms/measurement/internal/zzcr:zzgt	()Lcom/google/android/gms/measurement/internal/zzas;
    //   1350: invokevirtual 205	com/google/android/gms/measurement/internal/zzas:zzjo	()Lcom/google/android/gms/measurement/internal/zzau;
    //   1353: ldc_w 575
    //   1356: iload 112
    //   1358: invokestatic 362	java/lang/Integer:valueOf	(I)Ljava/lang/Integer;
    //   1361: invokevirtual 100	com/google/android/gms/measurement/internal/zzau:zzg	(Ljava/lang/String;Ljava/lang/Object;)V
    //   1364: goto -58 -> 1306
    //   1367: aload 167
    //   1369: iload 168
    //   1371: invokestatic 579	java/util/Arrays:copyOf	([Ljava/lang/Object;I)[Ljava/lang/Object;
    //   1374: checkcast 580	[Lcom/google/android/gms/internal/measurement/zzfu;
    //   1377: astore 174
    //   1379: goto -260 -> 1119
    //   1382: aload_0
    //   1383: invokevirtual 76	com/google/android/gms/measurement/internal/zzcr:zzgt	()Lcom/google/android/gms/measurement/internal/zzas;
    //   1386: invokevirtual 82	com/google/android/gms/measurement/internal/zzas:zzjj	()Lcom/google/android/gms/measurement/internal/zzau;
    //   1389: ldc_w 582
    //   1392: aload 159
    //   1394: invokevirtual 100	com/google/android/gms/measurement/internal/zzau:zzg	(Ljava/lang/String;Ljava/lang/Object;)V
    //   1397: aload 98
    //   1399: astore 99
    //   1401: aload 159
    //   1403: astore 100
    //   1405: aload 163
    //   1407: astore 101
    //   1409: lload 164
    //   1411: lstore 102
    //   1413: aload 89
    //   1415: astore 104
    //   1417: goto -278 -> 1139
    //   1420: iload 150
    //   1422: ifeq +2861 -> 4283
    //   1425: aload_0
    //   1426: invokevirtual 492	com/google/android/gms/measurement/internal/zzfl:zzjr	()Lcom/google/android/gms/measurement/internal/zzft;
    //   1429: pop
    //   1430: lconst_0
    //   1431: invokestatic 367	java/lang/Long:valueOf	(J)Ljava/lang/Long;
    //   1434: astore 153
    //   1436: aload 96
    //   1438: ldc_w 584
    //   1441: invokestatic 497	com/google/android/gms/measurement/internal/zzft:zzb	(Lcom/google/android/gms/internal/measurement/zzft;Ljava/lang/String;)Ljava/lang/Object;
    //   1444: astore 154
    //   1446: aload 154
    //   1448: ifnonnull +58 -> 1506
    //   1451: aload 153
    //   1453: checkcast 161	java/lang/Long
    //   1456: invokevirtual 170	java/lang/Long:longValue	()J
    //   1459: lstore 155
    //   1461: lload 155
    //   1463: lconst_0
    //   1464: lcmp
    //   1465: ifgt +48 -> 1513
    //   1468: aload_0
    //   1469: invokevirtual 76	com/google/android/gms/measurement/internal/zzcr:zzgt	()Lcom/google/android/gms/measurement/internal/zzas;
    //   1472: invokevirtual 82	com/google/android/gms/measurement/internal/zzas:zzjj	()Lcom/google/android/gms/measurement/internal/zzau;
    //   1475: ldc_w 586
    //   1478: aload 97
    //   1480: invokevirtual 100	com/google/android/gms/measurement/internal/zzau:zzg	(Ljava/lang/String;Ljava/lang/Object;)V
    //   1483: aload 98
    //   1485: astore 99
    //   1487: aload 97
    //   1489: astore 100
    //   1491: aload 149
    //   1493: astore 101
    //   1495: lload 155
    //   1497: lstore 102
    //   1499: aload 96
    //   1501: astore 104
    //   1503: goto -364 -> 1139
    //   1506: aload 154
    //   1508: astore 153
    //   1510: goto -59 -> 1451
    //   1513: aload_0
    //   1514: invokevirtual 419	com/google/android/gms/measurement/internal/zzfl:zzjt	()Lcom/google/android/gms/measurement/internal/zzt;
    //   1517: aload_1
    //   1518: aload 149
    //   1520: lload 155
    //   1522: aload 96
    //   1524: invokevirtual 545	com/google/android/gms/measurement/internal/zzt:zza	(Ljava/lang/String;Ljava/lang/Long;JLcom/google/android/gms/internal/measurement/zzft;)Z
    //   1527: pop
    //   1528: aload 98
    //   1530: astore 99
    //   1532: aload 97
    //   1534: astore 100
    //   1536: aload 149
    //   1538: astore 101
    //   1540: lload 155
    //   1542: lstore 102
    //   1544: aload 96
    //   1546: astore 104
    //   1548: goto -409 -> 1139
    //   1551: new 556	com/google/android/gms/measurement/internal/zzac
    //   1554: dup
    //   1555: aload 105
    //   1557: getfield 589	com/google/android/gms/measurement/internal/zzac:zztt	Ljava/lang/String;
    //   1560: aload 105
    //   1562: getfield 590	com/google/android/gms/measurement/internal/zzac:name	Ljava/lang/String;
    //   1565: lconst_1
    //   1566: aload 105
    //   1568: getfield 569	com/google/android/gms/measurement/internal/zzac:zzahv	J
    //   1571: ladd
    //   1572: lconst_1
    //   1573: aload 105
    //   1575: getfield 593	com/google/android/gms/measurement/internal/zzac:zzahw	J
    //   1578: ladd
    //   1579: aload 105
    //   1581: getfield 596	com/google/android/gms/measurement/internal/zzac:zzahx	J
    //   1584: aload 105
    //   1586: getfield 599	com/google/android/gms/measurement/internal/zzac:zzahy	J
    //   1589: aload 105
    //   1591: getfield 602	com/google/android/gms/measurement/internal/zzac:zzahz	Ljava/lang/Long;
    //   1594: aload 105
    //   1596: getfield 605	com/google/android/gms/measurement/internal/zzac:zzaia	Ljava/lang/Long;
    //   1599: aload 105
    //   1601: getfield 608	com/google/android/gms/measurement/internal/zzac:zzaib	Ljava/lang/Long;
    //   1604: aload 105
    //   1606: getfield 611	com/google/android/gms/measurement/internal/zzac:zzaic	Ljava/lang/Boolean;
    //   1609: invokespecial 562	com/google/android/gms/measurement/internal/zzac:<init>	(Ljava/lang/String;Ljava/lang/String;JJJJLjava/lang/Long;Ljava/lang/Long;Ljava/lang/Long;Ljava/lang/Boolean;)V
    //   1612: astore 106
    //   1614: goto -399 -> 1215
    //   1617: aload 6
    //   1619: iload 112
    //   1621: invokestatic 362	java/lang/Integer:valueOf	(I)Ljava/lang/Integer;
    //   1624: invokeinterface 159 2 0
    //   1629: checkcast 454	com/google/android/gms/internal/measurement/zzfr
    //   1632: astore 113
    //   1634: aload 7
    //   1636: iload 112
    //   1638: invokestatic 362	java/lang/Integer:valueOf	(I)Ljava/lang/Integer;
    //   1641: invokeinterface 159 2 0
    //   1646: checkcast 429	java/util/BitSet
    //   1649: astore 114
    //   1651: aload 8
    //   1653: iload 112
    //   1655: invokestatic 362	java/lang/Integer:valueOf	(I)Ljava/lang/Integer;
    //   1658: invokeinterface 159 2 0
    //   1663: checkcast 429	java/util/BitSet
    //   1666: astore 115
    //   1668: aconst_null
    //   1669: astore 116
    //   1671: aconst_null
    //   1672: astore 117
    //   1674: iload 11
    //   1676: ifeq +45 -> 1721
    //   1679: aload 9
    //   1681: iload 112
    //   1683: invokestatic 362	java/lang/Integer:valueOf	(I)Ljava/lang/Integer;
    //   1686: invokeinterface 159 2 0
    //   1691: checkcast 123	java/util/Map
    //   1694: astore 144
    //   1696: aload 10
    //   1698: iload 112
    //   1700: invokestatic 362	java/lang/Integer:valueOf	(I)Ljava/lang/Integer;
    //   1703: invokeinterface 159 2 0
    //   1708: checkcast 123	java/util/Map
    //   1711: astore 145
    //   1713: aload 144
    //   1715: astore 117
    //   1717: aload 145
    //   1719: astore 116
    //   1721: aload 113
    //   1723: ifnonnull +2609 -> 4332
    //   1726: new 454	com/google/android/gms/internal/measurement/zzfr
    //   1729: dup
    //   1730: invokespecial 455	com/google/android/gms/internal/measurement/zzfr:<init>	()V
    //   1733: astore 118
    //   1735: aload 6
    //   1737: iload 112
    //   1739: invokestatic 362	java/lang/Integer:valueOf	(I)Ljava/lang/Integer;
    //   1742: aload 118
    //   1744: invokeinterface 127 3 0
    //   1749: pop
    //   1750: aload 118
    //   1752: iconst_1
    //   1753: invokestatic 49	java/lang/Boolean:valueOf	(Z)Ljava/lang/Boolean;
    //   1756: putfield 458	com/google/android/gms/internal/measurement/zzfr:zzawx	Ljava/lang/Boolean;
    //   1759: new 429	java/util/BitSet
    //   1762: dup
    //   1763: invokespecial 434	java/util/BitSet:<init>	()V
    //   1766: astore 120
    //   1768: aload 7
    //   1770: iload 112
    //   1772: invokestatic 362	java/lang/Integer:valueOf	(I)Ljava/lang/Integer;
    //   1775: aload 120
    //   1777: invokeinterface 127 3 0
    //   1782: pop
    //   1783: new 429	java/util/BitSet
    //   1786: dup
    //   1787: invokespecial 434	java/util/BitSet:<init>	()V
    //   1790: astore 122
    //   1792: aload 8
    //   1794: iload 112
    //   1796: invokestatic 362	java/lang/Integer:valueOf	(I)Ljava/lang/Integer;
    //   1799: aload 122
    //   1801: invokeinterface 127 3 0
    //   1806: pop
    //   1807: iload 11
    //   1809: ifeq +2504 -> 4313
    //   1812: new 108	android/support/v4/util/ArrayMap
    //   1815: dup
    //   1816: invokespecial 109	android/support/v4/util/ArrayMap:<init>	()V
    //   1819: astore 124
    //   1821: aload 9
    //   1823: iload 112
    //   1825: invokestatic 362	java/lang/Integer:valueOf	(I)Ljava/lang/Integer;
    //   1828: aload 124
    //   1830: invokeinterface 127 3 0
    //   1835: pop
    //   1836: new 108	android/support/v4/util/ArrayMap
    //   1839: dup
    //   1840: invokespecial 109	android/support/v4/util/ArrayMap:<init>	()V
    //   1843: astore 126
    //   1845: aload 10
    //   1847: iload 112
    //   1849: invokestatic 362	java/lang/Integer:valueOf	(I)Ljava/lang/Integer;
    //   1852: aload 126
    //   1854: invokeinterface 127 3 0
    //   1859: pop
    //   1860: aload 126
    //   1862: astore 128
    //   1864: aload 122
    //   1866: astore 129
    //   1868: aload 120
    //   1870: astore 130
    //   1872: aload 124
    //   1874: astore 131
    //   1876: aload 110
    //   1878: iload 112
    //   1880: invokestatic 362	java/lang/Integer:valueOf	(I)Ljava/lang/Integer;
    //   1883: invokeinterface 159 2 0
    //   1888: checkcast 246	java/util/List
    //   1891: invokeinterface 612 1 0
    //   1896: astore 132
    //   1898: aload 132
    //   1900: invokeinterface 385 1 0
    //   1905: ifeq -599 -> 1306
    //   1908: aload 132
    //   1910: invokeinterface 389 1 0
    //   1915: checkcast 33	com/google/android/gms/internal/measurement/zzfj
    //   1918: astore 133
    //   1920: aload_0
    //   1921: invokevirtual 76	com/google/android/gms/measurement/internal/zzcr:zzgt	()Lcom/google/android/gms/measurement/internal/zzas;
    //   1924: iconst_2
    //   1925: invokevirtual 616	com/google/android/gms/measurement/internal/zzas:isLoggable	(I)Z
    //   1928: ifeq +60 -> 1988
    //   1931: aload_0
    //   1932: invokevirtual 76	com/google/android/gms/measurement/internal/zzcr:zzgt	()Lcom/google/android/gms/measurement/internal/zzas;
    //   1935: invokevirtual 205	com/google/android/gms/measurement/internal/zzas:zzjo	()Lcom/google/android/gms/measurement/internal/zzau;
    //   1938: ldc_w 618
    //   1941: iload 112
    //   1943: invokestatic 362	java/lang/Integer:valueOf	(I)Ljava/lang/Integer;
    //   1946: aload 133
    //   1948: getfield 621	com/google/android/gms/internal/measurement/zzfj:zzavm	Ljava/lang/Integer;
    //   1951: aload_0
    //   1952: invokevirtual 88	com/google/android/gms/measurement/internal/zzcr:zzgq	()Lcom/google/android/gms/measurement/internal/zzaq;
    //   1955: aload 133
    //   1957: getfield 624	com/google/android/gms/internal/measurement/zzfj:zzavn	Ljava/lang/String;
    //   1960: invokevirtual 94	com/google/android/gms/measurement/internal/zzaq:zzbt	(Ljava/lang/String;)Ljava/lang/String;
    //   1963: invokevirtual 627	com/google/android/gms/measurement/internal/zzau:zzd	(Ljava/lang/String;Ljava/lang/Object;Ljava/lang/Object;Ljava/lang/Object;)V
    //   1966: aload_0
    //   1967: invokevirtual 76	com/google/android/gms/measurement/internal/zzcr:zzgt	()Lcom/google/android/gms/measurement/internal/zzas;
    //   1970: invokevirtual 205	com/google/android/gms/measurement/internal/zzas:zzjo	()Lcom/google/android/gms/measurement/internal/zzau;
    //   1973: ldc_w 629
    //   1976: aload_0
    //   1977: invokevirtual 492	com/google/android/gms/measurement/internal/zzfl:zzjr	()Lcom/google/android/gms/measurement/internal/zzft;
    //   1980: aload 133
    //   1982: invokevirtual 632	com/google/android/gms/measurement/internal/zzft:zza	(Lcom/google/android/gms/internal/measurement/zzfj;)Ljava/lang/String;
    //   1985: invokevirtual 100	com/google/android/gms/measurement/internal/zzau:zzg	(Ljava/lang/String;Ljava/lang/Object;)V
    //   1988: aload 133
    //   1990: getfield 621	com/google/android/gms/internal/measurement/zzfj:zzavm	Ljava/lang/Integer;
    //   1993: ifnull +17 -> 2010
    //   1996: aload 133
    //   1998: getfield 621	com/google/android/gms/internal/measurement/zzfj:zzavm	Ljava/lang/Integer;
    //   2001: invokevirtual 306	java/lang/Integer:intValue	()I
    //   2004: sipush 256
    //   2007: if_icmple +31 -> 2038
    //   2010: aload_0
    //   2011: invokevirtual 76	com/google/android/gms/measurement/internal/zzcr:zzgt	()Lcom/google/android/gms/measurement/internal/zzas;
    //   2014: invokevirtual 82	com/google/android/gms/measurement/internal/zzas:zzjj	()Lcom/google/android/gms/measurement/internal/zzau;
    //   2017: ldc_w 634
    //   2020: aload_1
    //   2021: invokestatic 554	com/google/android/gms/measurement/internal/zzas:zzbw	(Ljava/lang/String;)Ljava/lang/Object;
    //   2024: aload 133
    //   2026: getfield 621	com/google/android/gms/internal/measurement/zzfj:zzavm	Ljava/lang/Integer;
    //   2029: invokestatic 637	java/lang/String:valueOf	(Ljava/lang/Object;)Ljava/lang/String;
    //   2032: invokevirtual 143	com/google/android/gms/measurement/internal/zzau:zze	(Ljava/lang/String;Ljava/lang/Object;Ljava/lang/Object;)V
    //   2035: goto -137 -> 1898
    //   2038: iload 11
    //   2040: ifeq +297 -> 2337
    //   2043: aload 133
    //   2045: ifnull +104 -> 2149
    //   2048: aload 133
    //   2050: getfield 640	com/google/android/gms/internal/measurement/zzfj:zzavj	Ljava/lang/Boolean;
    //   2053: ifnull +96 -> 2149
    //   2056: aload 133
    //   2058: getfield 640	com/google/android/gms/internal/measurement/zzfj:zzavj	Ljava/lang/Boolean;
    //   2061: invokevirtual 45	java/lang/Boolean:booleanValue	()Z
    //   2064: ifeq +85 -> 2149
    //   2067: iconst_1
    //   2068: istore 138
    //   2070: aload 133
    //   2072: ifnull +83 -> 2155
    //   2075: aload 133
    //   2077: getfield 643	com/google/android/gms/internal/measurement/zzfj:zzavk	Ljava/lang/Boolean;
    //   2080: ifnull +75 -> 2155
    //   2083: aload 133
    //   2085: getfield 643	com/google/android/gms/internal/measurement/zzfj:zzavk	Ljava/lang/Boolean;
    //   2088: invokevirtual 45	java/lang/Boolean:booleanValue	()Z
    //   2091: ifeq +64 -> 2155
    //   2094: iconst_1
    //   2095: istore 139
    //   2097: aload 130
    //   2099: aload 133
    //   2101: getfield 621	com/google/android/gms/internal/measurement/zzfj:zzavm	Ljava/lang/Integer;
    //   2104: invokevirtual 306	java/lang/Integer:intValue	()I
    //   2107: invokevirtual 645	java/util/BitSet:get	(I)Z
    //   2110: ifeq +51 -> 2161
    //   2113: iload 138
    //   2115: ifne +46 -> 2161
    //   2118: iload 139
    //   2120: ifne +41 -> 2161
    //   2123: aload_0
    //   2124: invokevirtual 76	com/google/android/gms/measurement/internal/zzcr:zzgt	()Lcom/google/android/gms/measurement/internal/zzas;
    //   2127: invokevirtual 205	com/google/android/gms/measurement/internal/zzas:zzjo	()Lcom/google/android/gms/measurement/internal/zzau;
    //   2130: ldc_w 647
    //   2133: iload 112
    //   2135: invokestatic 362	java/lang/Integer:valueOf	(I)Ljava/lang/Integer;
    //   2138: aload 133
    //   2140: getfield 621	com/google/android/gms/internal/measurement/zzfj:zzavm	Ljava/lang/Integer;
    //   2143: invokevirtual 143	com/google/android/gms/measurement/internal/zzau:zze	(Ljava/lang/String;Ljava/lang/Object;Ljava/lang/Object;)V
    //   2146: goto -248 -> 1898
    //   2149: iconst_0
    //   2150: istore 138
    //   2152: goto -82 -> 2070
    //   2155: iconst_0
    //   2156: istore 139
    //   2158: goto -61 -> 2097
    //   2161: aload_0
    //   2162: aload 133
    //   2164: aload 100
    //   2166: aload 99
    //   2168: lload 107
    //   2170: invokespecial 649	com/google/android/gms/measurement/internal/zzm:zza	(Lcom/google/android/gms/internal/measurement/zzfj;Ljava/lang/String;[Lcom/google/android/gms/internal/measurement/zzfu;J)Ljava/lang/Boolean;
    //   2173: astore 140
    //   2175: aload_0
    //   2176: invokevirtual 76	com/google/android/gms/measurement/internal/zzcr:zzgt	()Lcom/google/android/gms/measurement/internal/zzas;
    //   2179: invokevirtual 205	com/google/android/gms/measurement/internal/zzas:zzjo	()Lcom/google/android/gms/measurement/internal/zzau;
    //   2182: astore 141
    //   2184: aload 140
    //   2186: ifnonnull +39 -> 2225
    //   2189: ldc_w 651
    //   2192: astore 142
    //   2194: aload 141
    //   2196: ldc_w 653
    //   2199: aload 142
    //   2201: invokevirtual 100	com/google/android/gms/measurement/internal/zzau:zzg	(Ljava/lang/String;Ljava/lang/Object;)V
    //   2204: aload 140
    //   2206: ifnonnull +26 -> 2232
    //   2209: aload 5
    //   2211: iload 112
    //   2213: invokestatic 362	java/lang/Integer:valueOf	(I)Ljava/lang/Integer;
    //   2216: invokeinterface 106 2 0
    //   2221: pop
    //   2222: goto -324 -> 1898
    //   2225: aload 140
    //   2227: astore 142
    //   2229: goto -35 -> 2194
    //   2232: aload 129
    //   2234: aload 133
    //   2236: getfield 621	com/google/android/gms/internal/measurement/zzfj:zzavm	Ljava/lang/Integer;
    //   2239: invokevirtual 306	java/lang/Integer:intValue	()I
    //   2242: invokevirtual 446	java/util/BitSet:set	(I)V
    //   2245: aload 140
    //   2247: invokevirtual 45	java/lang/Boolean:booleanValue	()Z
    //   2250: ifeq -352 -> 1898
    //   2253: aload 130
    //   2255: aload 133
    //   2257: getfield 621	com/google/android/gms/internal/measurement/zzfj:zzavm	Ljava/lang/Integer;
    //   2260: invokevirtual 306	java/lang/Integer:intValue	()I
    //   2263: invokevirtual 446	java/util/BitSet:set	(I)V
    //   2266: iload 138
    //   2268: ifne +8 -> 2276
    //   2271: iload 139
    //   2273: ifeq -375 -> 1898
    //   2276: aload 96
    //   2278: getfield 559	com/google/android/gms/internal/measurement/zzft:zzaxd	Ljava/lang/Long;
    //   2281: ifnull -383 -> 1898
    //   2284: iload 139
    //   2286: ifeq +27 -> 2313
    //   2289: aload 128
    //   2291: aload 133
    //   2293: getfield 621	com/google/android/gms/internal/measurement/zzfj:zzavm	Ljava/lang/Integer;
    //   2296: invokevirtual 306	java/lang/Integer:intValue	()I
    //   2299: aload 96
    //   2301: getfield 559	com/google/android/gms/internal/measurement/zzft:zzaxd	Ljava/lang/Long;
    //   2304: invokevirtual 170	java/lang/Long:longValue	()J
    //   2307: invokestatic 655	com/google/android/gms/measurement/internal/zzm:zzb	(Ljava/util/Map;IJ)V
    //   2310: goto -412 -> 1898
    //   2313: aload 131
    //   2315: aload 133
    //   2317: getfield 621	com/google/android/gms/internal/measurement/zzfj:zzavm	Ljava/lang/Integer;
    //   2320: invokevirtual 306	java/lang/Integer:intValue	()I
    //   2323: aload 96
    //   2325: getfield 559	com/google/android/gms/internal/measurement/zzft:zzaxd	Ljava/lang/Long;
    //   2328: invokevirtual 170	java/lang/Long:longValue	()J
    //   2331: invokestatic 657	com/google/android/gms/measurement/internal/zzm:zza	(Ljava/util/Map;IJ)V
    //   2334: goto -436 -> 1898
    //   2337: aload 130
    //   2339: aload 133
    //   2341: getfield 621	com/google/android/gms/internal/measurement/zzfj:zzavm	Ljava/lang/Integer;
    //   2344: invokevirtual 306	java/lang/Integer:intValue	()I
    //   2347: invokevirtual 645	java/util/BitSet:get	(I)Z
    //   2350: ifeq +29 -> 2379
    //   2353: aload_0
    //   2354: invokevirtual 76	com/google/android/gms/measurement/internal/zzcr:zzgt	()Lcom/google/android/gms/measurement/internal/zzas;
    //   2357: invokevirtual 205	com/google/android/gms/measurement/internal/zzas:zzjo	()Lcom/google/android/gms/measurement/internal/zzau;
    //   2360: ldc_w 659
    //   2363: iload 112
    //   2365: invokestatic 362	java/lang/Integer:valueOf	(I)Ljava/lang/Integer;
    //   2368: aload 133
    //   2370: getfield 621	com/google/android/gms/internal/measurement/zzfj:zzavm	Ljava/lang/Integer;
    //   2373: invokevirtual 143	com/google/android/gms/measurement/internal/zzau:zze	(Ljava/lang/String;Ljava/lang/Object;Ljava/lang/Object;)V
    //   2376: goto -478 -> 1898
    //   2379: aload_0
    //   2380: aload 133
    //   2382: aload 100
    //   2384: aload 99
    //   2386: lload 107
    //   2388: invokespecial 649	com/google/android/gms/measurement/internal/zzm:zza	(Lcom/google/android/gms/internal/measurement/zzfj;Ljava/lang/String;[Lcom/google/android/gms/internal/measurement/zzfu;J)Ljava/lang/Boolean;
    //   2391: astore 134
    //   2393: aload_0
    //   2394: invokevirtual 76	com/google/android/gms/measurement/internal/zzcr:zzgt	()Lcom/google/android/gms/measurement/internal/zzas;
    //   2397: invokevirtual 205	com/google/android/gms/measurement/internal/zzas:zzjo	()Lcom/google/android/gms/measurement/internal/zzau;
    //   2400: astore 135
    //   2402: aload 134
    //   2404: ifnonnull +39 -> 2443
    //   2407: ldc_w 651
    //   2410: astore 136
    //   2412: aload 135
    //   2414: ldc_w 653
    //   2417: aload 136
    //   2419: invokevirtual 100	com/google/android/gms/measurement/internal/zzau:zzg	(Ljava/lang/String;Ljava/lang/Object;)V
    //   2422: aload 134
    //   2424: ifnonnull +26 -> 2450
    //   2427: aload 5
    //   2429: iload 112
    //   2431: invokestatic 362	java/lang/Integer:valueOf	(I)Ljava/lang/Integer;
    //   2434: invokeinterface 106 2 0
    //   2439: pop
    //   2440: goto -542 -> 1898
    //   2443: aload 134
    //   2445: astore 136
    //   2447: goto -35 -> 2412
    //   2450: aload 129
    //   2452: aload 133
    //   2454: getfield 621	com/google/android/gms/internal/measurement/zzfj:zzavm	Ljava/lang/Integer;
    //   2457: invokevirtual 306	java/lang/Integer:intValue	()I
    //   2460: invokevirtual 446	java/util/BitSet:set	(I)V
    //   2463: aload 134
    //   2465: invokevirtual 45	java/lang/Boolean:booleanValue	()Z
    //   2468: ifeq -570 -> 1898
    //   2471: aload 130
    //   2473: aload 133
    //   2475: getfield 621	com/google/android/gms/internal/measurement/zzfj:zzavm	Ljava/lang/Integer;
    //   2478: invokevirtual 306	java/lang/Integer:intValue	()I
    //   2481: invokevirtual 446	java/util/BitSet:set	(I)V
    //   2484: goto -586 -> 1898
    //   2487: aload_3
    //   2488: ifnull +1063 -> 3551
    //   2491: new 108	android/support/v4/util/ArrayMap
    //   2494: dup
    //   2495: invokespecial 109	android/support/v4/util/ArrayMap:<init>	()V
    //   2498: astore 13
    //   2500: aload_3
    //   2501: arraylength
    //   2502: istore 14
    //   2504: iconst_0
    //   2505: istore 15
    //   2507: iload 15
    //   2509: iload 14
    //   2511: if_icmpge +1040 -> 3551
    //   2514: aload_3
    //   2515: iload 15
    //   2517: aaload
    //   2518: astore 47
    //   2520: aload 13
    //   2522: aload 47
    //   2524: getfield 221	com/google/android/gms/internal/measurement/zzfz:name	Ljava/lang/String;
    //   2527: invokeinterface 159 2 0
    //   2532: checkcast 123	java/util/Map
    //   2535: astore 48
    //   2537: aload 48
    //   2539: ifnonnull +1737 -> 4276
    //   2542: aload_0
    //   2543: invokevirtual 419	com/google/android/gms/measurement/internal/zzfl:zzjt	()Lcom/google/android/gms/measurement/internal/zzt;
    //   2546: aload_1
    //   2547: aload 47
    //   2549: getfield 221	com/google/android/gms/internal/measurement/zzfz:name	Ljava/lang/String;
    //   2552: invokevirtual 662	com/google/android/gms/measurement/internal/zzt:zzm	(Ljava/lang/String;Ljava/lang/String;)Ljava/util/Map;
    //   2555: astore 87
    //   2557: aload 87
    //   2559: ifnonnull +12 -> 2571
    //   2562: new 108	android/support/v4/util/ArrayMap
    //   2565: dup
    //   2566: invokespecial 109	android/support/v4/util/ArrayMap:<init>	()V
    //   2569: astore 87
    //   2571: aload 13
    //   2573: aload 47
    //   2575: getfield 221	com/google/android/gms/internal/measurement/zzfz:name	Ljava/lang/String;
    //   2578: aload 87
    //   2580: invokeinterface 127 3 0
    //   2585: pop
    //   2586: aload 87
    //   2588: astore 49
    //   2590: aload 49
    //   2592: invokeinterface 376 1 0
    //   2597: invokeinterface 380 1 0
    //   2602: astore 50
    //   2604: aload 50
    //   2606: invokeinterface 385 1 0
    //   2611: ifeq +934 -> 3545
    //   2614: aload 50
    //   2616: invokeinterface 389 1 0
    //   2621: checkcast 303	java/lang/Integer
    //   2624: invokevirtual 306	java/lang/Integer:intValue	()I
    //   2627: istore 51
    //   2629: aload 5
    //   2631: iload 51
    //   2633: invokestatic 362	java/lang/Integer:valueOf	(I)Ljava/lang/Integer;
    //   2636: invokeinterface 117 2 0
    //   2641: ifeq +24 -> 2665
    //   2644: aload_0
    //   2645: invokevirtual 76	com/google/android/gms/measurement/internal/zzcr:zzgt	()Lcom/google/android/gms/measurement/internal/zzas;
    //   2648: invokevirtual 205	com/google/android/gms/measurement/internal/zzas:zzjo	()Lcom/google/android/gms/measurement/internal/zzau;
    //   2651: ldc_w 575
    //   2654: iload 51
    //   2656: invokestatic 362	java/lang/Integer:valueOf	(I)Ljava/lang/Integer;
    //   2659: invokevirtual 100	com/google/android/gms/measurement/internal/zzau:zzg	(Ljava/lang/String;Ljava/lang/Object;)V
    //   2662: goto -58 -> 2604
    //   2665: aload 6
    //   2667: iload 51
    //   2669: invokestatic 362	java/lang/Integer:valueOf	(I)Ljava/lang/Integer;
    //   2672: invokeinterface 159 2 0
    //   2677: checkcast 454	com/google/android/gms/internal/measurement/zzfr
    //   2680: astore 52
    //   2682: aload 7
    //   2684: iload 51
    //   2686: invokestatic 362	java/lang/Integer:valueOf	(I)Ljava/lang/Integer;
    //   2689: invokeinterface 159 2 0
    //   2694: checkcast 429	java/util/BitSet
    //   2697: astore 53
    //   2699: aload 8
    //   2701: iload 51
    //   2703: invokestatic 362	java/lang/Integer:valueOf	(I)Ljava/lang/Integer;
    //   2706: invokeinterface 159 2 0
    //   2711: checkcast 429	java/util/BitSet
    //   2714: astore 54
    //   2716: aconst_null
    //   2717: astore 55
    //   2719: aconst_null
    //   2720: astore 56
    //   2722: iload 11
    //   2724: ifeq +45 -> 2769
    //   2727: aload 9
    //   2729: iload 51
    //   2731: invokestatic 362	java/lang/Integer:valueOf	(I)Ljava/lang/Integer;
    //   2734: invokeinterface 159 2 0
    //   2739: checkcast 123	java/util/Map
    //   2742: astore 85
    //   2744: aload 10
    //   2746: iload 51
    //   2748: invokestatic 362	java/lang/Integer:valueOf	(I)Ljava/lang/Integer;
    //   2751: invokeinterface 159 2 0
    //   2756: checkcast 123	java/util/Map
    //   2759: astore 86
    //   2761: aload 85
    //   2763: astore 56
    //   2765: aload 86
    //   2767: astore 55
    //   2769: aload 52
    //   2771: ifnonnull +1482 -> 4253
    //   2774: new 454	com/google/android/gms/internal/measurement/zzfr
    //   2777: dup
    //   2778: invokespecial 455	com/google/android/gms/internal/measurement/zzfr:<init>	()V
    //   2781: astore 57
    //   2783: aload 6
    //   2785: iload 51
    //   2787: invokestatic 362	java/lang/Integer:valueOf	(I)Ljava/lang/Integer;
    //   2790: aload 57
    //   2792: invokeinterface 127 3 0
    //   2797: pop
    //   2798: aload 57
    //   2800: iconst_1
    //   2801: invokestatic 49	java/lang/Boolean:valueOf	(Z)Ljava/lang/Boolean;
    //   2804: putfield 458	com/google/android/gms/internal/measurement/zzfr:zzawx	Ljava/lang/Boolean;
    //   2807: new 429	java/util/BitSet
    //   2810: dup
    //   2811: invokespecial 434	java/util/BitSet:<init>	()V
    //   2814: astore 59
    //   2816: aload 7
    //   2818: iload 51
    //   2820: invokestatic 362	java/lang/Integer:valueOf	(I)Ljava/lang/Integer;
    //   2823: aload 59
    //   2825: invokeinterface 127 3 0
    //   2830: pop
    //   2831: new 429	java/util/BitSet
    //   2834: dup
    //   2835: invokespecial 434	java/util/BitSet:<init>	()V
    //   2838: astore 61
    //   2840: aload 8
    //   2842: iload 51
    //   2844: invokestatic 362	java/lang/Integer:valueOf	(I)Ljava/lang/Integer;
    //   2847: aload 61
    //   2849: invokeinterface 127 3 0
    //   2854: pop
    //   2855: iload 11
    //   2857: ifeq +1377 -> 4234
    //   2860: new 108	android/support/v4/util/ArrayMap
    //   2863: dup
    //   2864: invokespecial 109	android/support/v4/util/ArrayMap:<init>	()V
    //   2867: astore 63
    //   2869: aload 9
    //   2871: iload 51
    //   2873: invokestatic 362	java/lang/Integer:valueOf	(I)Ljava/lang/Integer;
    //   2876: aload 63
    //   2878: invokeinterface 127 3 0
    //   2883: pop
    //   2884: new 108	android/support/v4/util/ArrayMap
    //   2887: dup
    //   2888: invokespecial 109	android/support/v4/util/ArrayMap:<init>	()V
    //   2891: astore 65
    //   2893: aload 10
    //   2895: iload 51
    //   2897: invokestatic 362	java/lang/Integer:valueOf	(I)Ljava/lang/Integer;
    //   2900: aload 65
    //   2902: invokeinterface 127 3 0
    //   2907: pop
    //   2908: aload 61
    //   2910: astore 67
    //   2912: aload 59
    //   2914: astore 68
    //   2916: aload 63
    //   2918: astore 69
    //   2920: aload 65
    //   2922: astore 70
    //   2924: aload 49
    //   2926: iload 51
    //   2928: invokestatic 362	java/lang/Integer:valueOf	(I)Ljava/lang/Integer;
    //   2931: invokeinterface 159 2 0
    //   2936: checkcast 246	java/util/List
    //   2939: invokeinterface 612 1 0
    //   2944: astore 71
    //   2946: aload 71
    //   2948: invokeinterface 385 1 0
    //   2953: ifeq -349 -> 2604
    //   2956: aload 71
    //   2958: invokeinterface 389 1 0
    //   2963: checkcast 212	com/google/android/gms/internal/measurement/zzfm
    //   2966: astore 72
    //   2968: aload_0
    //   2969: invokevirtual 76	com/google/android/gms/measurement/internal/zzcr:zzgt	()Lcom/google/android/gms/measurement/internal/zzas;
    //   2972: iconst_2
    //   2973: invokevirtual 616	com/google/android/gms/measurement/internal/zzas:isLoggable	(I)Z
    //   2976: ifeq +60 -> 3036
    //   2979: aload_0
    //   2980: invokevirtual 76	com/google/android/gms/measurement/internal/zzcr:zzgt	()Lcom/google/android/gms/measurement/internal/zzas;
    //   2983: invokevirtual 205	com/google/android/gms/measurement/internal/zzas:zzjo	()Lcom/google/android/gms/measurement/internal/zzau;
    //   2986: ldc_w 664
    //   2989: iload 51
    //   2991: invokestatic 362	java/lang/Integer:valueOf	(I)Ljava/lang/Integer;
    //   2994: aload 72
    //   2996: getfield 665	com/google/android/gms/internal/measurement/zzfm:zzavm	Ljava/lang/Integer;
    //   2999: aload_0
    //   3000: invokevirtual 88	com/google/android/gms/measurement/internal/zzcr:zzgq	()Lcom/google/android/gms/measurement/internal/zzaq;
    //   3003: aload 72
    //   3005: getfield 668	com/google/android/gms/internal/measurement/zzfm:zzawc	Ljava/lang/String;
    //   3008: invokevirtual 224	com/google/android/gms/measurement/internal/zzaq:zzbv	(Ljava/lang/String;)Ljava/lang/String;
    //   3011: invokevirtual 627	com/google/android/gms/measurement/internal/zzau:zzd	(Ljava/lang/String;Ljava/lang/Object;Ljava/lang/Object;Ljava/lang/Object;)V
    //   3014: aload_0
    //   3015: invokevirtual 76	com/google/android/gms/measurement/internal/zzcr:zzgt	()Lcom/google/android/gms/measurement/internal/zzas;
    //   3018: invokevirtual 205	com/google/android/gms/measurement/internal/zzas:zzjo	()Lcom/google/android/gms/measurement/internal/zzau;
    //   3021: ldc_w 629
    //   3024: aload_0
    //   3025: invokevirtual 492	com/google/android/gms/measurement/internal/zzfl:zzjr	()Lcom/google/android/gms/measurement/internal/zzft;
    //   3028: aload 72
    //   3030: invokevirtual 671	com/google/android/gms/measurement/internal/zzft:zza	(Lcom/google/android/gms/internal/measurement/zzfm;)Ljava/lang/String;
    //   3033: invokevirtual 100	com/google/android/gms/measurement/internal/zzau:zzg	(Ljava/lang/String;Ljava/lang/Object;)V
    //   3036: aload 72
    //   3038: getfield 665	com/google/android/gms/internal/measurement/zzfm:zzavm	Ljava/lang/Integer;
    //   3041: ifnull +17 -> 3058
    //   3044: aload 72
    //   3046: getfield 665	com/google/android/gms/internal/measurement/zzfm:zzavm	Ljava/lang/Integer;
    //   3049: invokevirtual 306	java/lang/Integer:intValue	()I
    //   3052: sipush 256
    //   3055: if_icmple +44 -> 3099
    //   3058: aload_0
    //   3059: invokevirtual 76	com/google/android/gms/measurement/internal/zzcr:zzgt	()Lcom/google/android/gms/measurement/internal/zzas;
    //   3062: invokevirtual 82	com/google/android/gms/measurement/internal/zzas:zzjj	()Lcom/google/android/gms/measurement/internal/zzau;
    //   3065: ldc_w 673
    //   3068: aload_1
    //   3069: invokestatic 554	com/google/android/gms/measurement/internal/zzas:zzbw	(Ljava/lang/String;)Ljava/lang/Object;
    //   3072: aload 72
    //   3074: getfield 665	com/google/android/gms/internal/measurement/zzfm:zzavm	Ljava/lang/Integer;
    //   3077: invokestatic 637	java/lang/String:valueOf	(Ljava/lang/Object;)Ljava/lang/String;
    //   3080: invokevirtual 143	com/google/android/gms/measurement/internal/zzau:zze	(Ljava/lang/String;Ljava/lang/Object;Ljava/lang/Object;)V
    //   3083: aload 5
    //   3085: iload 51
    //   3087: invokestatic 362	java/lang/Integer:valueOf	(I)Ljava/lang/Integer;
    //   3090: invokeinterface 106 2 0
    //   3095: pop
    //   3096: goto -492 -> 2604
    //   3099: iload 11
    //   3101: ifeq +298 -> 3399
    //   3104: aload 72
    //   3106: ifnull +104 -> 3210
    //   3109: aload 72
    //   3111: getfield 674	com/google/android/gms/internal/measurement/zzfm:zzavj	Ljava/lang/Boolean;
    //   3114: ifnull +96 -> 3210
    //   3117: aload 72
    //   3119: getfield 674	com/google/android/gms/internal/measurement/zzfm:zzavj	Ljava/lang/Boolean;
    //   3122: invokevirtual 45	java/lang/Boolean:booleanValue	()Z
    //   3125: ifeq +85 -> 3210
    //   3128: iconst_1
    //   3129: istore 78
    //   3131: aload 72
    //   3133: ifnull +83 -> 3216
    //   3136: aload 72
    //   3138: getfield 675	com/google/android/gms/internal/measurement/zzfm:zzavk	Ljava/lang/Boolean;
    //   3141: ifnull +75 -> 3216
    //   3144: aload 72
    //   3146: getfield 675	com/google/android/gms/internal/measurement/zzfm:zzavk	Ljava/lang/Boolean;
    //   3149: invokevirtual 45	java/lang/Boolean:booleanValue	()Z
    //   3152: ifeq +64 -> 3216
    //   3155: iconst_1
    //   3156: istore 79
    //   3158: aload 68
    //   3160: aload 72
    //   3162: getfield 665	com/google/android/gms/internal/measurement/zzfm:zzavm	Ljava/lang/Integer;
    //   3165: invokevirtual 306	java/lang/Integer:intValue	()I
    //   3168: invokevirtual 645	java/util/BitSet:get	(I)Z
    //   3171: ifeq +51 -> 3222
    //   3174: iload 78
    //   3176: ifne +46 -> 3222
    //   3179: iload 79
    //   3181: ifne +41 -> 3222
    //   3184: aload_0
    //   3185: invokevirtual 76	com/google/android/gms/measurement/internal/zzcr:zzgt	()Lcom/google/android/gms/measurement/internal/zzas;
    //   3188: invokevirtual 205	com/google/android/gms/measurement/internal/zzas:zzjo	()Lcom/google/android/gms/measurement/internal/zzau;
    //   3191: ldc_w 677
    //   3194: iload 51
    //   3196: invokestatic 362	java/lang/Integer:valueOf	(I)Ljava/lang/Integer;
    //   3199: aload 72
    //   3201: getfield 665	com/google/android/gms/internal/measurement/zzfm:zzavm	Ljava/lang/Integer;
    //   3204: invokevirtual 143	com/google/android/gms/measurement/internal/zzau:zze	(Ljava/lang/String;Ljava/lang/Object;Ljava/lang/Object;)V
    //   3207: goto -261 -> 2946
    //   3210: iconst_0
    //   3211: istore 78
    //   3213: goto -82 -> 3131
    //   3216: iconst_0
    //   3217: istore 79
    //   3219: goto -61 -> 3158
    //   3222: aload_0
    //   3223: aload 72
    //   3225: aload 47
    //   3227: invokespecial 679	com/google/android/gms/measurement/internal/zzm:zza	(Lcom/google/android/gms/internal/measurement/zzfm;Lcom/google/android/gms/internal/measurement/zzfz;)Ljava/lang/Boolean;
    //   3230: astore 80
    //   3232: aload_0
    //   3233: invokevirtual 76	com/google/android/gms/measurement/internal/zzcr:zzgt	()Lcom/google/android/gms/measurement/internal/zzas;
    //   3236: invokevirtual 205	com/google/android/gms/measurement/internal/zzas:zzjo	()Lcom/google/android/gms/measurement/internal/zzau;
    //   3239: astore 81
    //   3241: aload 80
    //   3243: ifnonnull +39 -> 3282
    //   3246: ldc_w 651
    //   3249: astore 82
    //   3251: aload 81
    //   3253: ldc_w 681
    //   3256: aload 82
    //   3258: invokevirtual 100	com/google/android/gms/measurement/internal/zzau:zzg	(Ljava/lang/String;Ljava/lang/Object;)V
    //   3261: aload 80
    //   3263: ifnonnull +26 -> 3289
    //   3266: aload 5
    //   3268: iload 51
    //   3270: invokestatic 362	java/lang/Integer:valueOf	(I)Ljava/lang/Integer;
    //   3273: invokeinterface 106 2 0
    //   3278: pop
    //   3279: goto -333 -> 2946
    //   3282: aload 80
    //   3284: astore 82
    //   3286: goto -35 -> 3251
    //   3289: aload 67
    //   3291: aload 72
    //   3293: getfield 665	com/google/android/gms/internal/measurement/zzfm:zzavm	Ljava/lang/Integer;
    //   3296: invokevirtual 306	java/lang/Integer:intValue	()I
    //   3299: invokevirtual 446	java/util/BitSet:set	(I)V
    //   3302: aload 68
    //   3304: aload 72
    //   3306: getfield 665	com/google/android/gms/internal/measurement/zzfm:zzavm	Ljava/lang/Integer;
    //   3309: invokevirtual 306	java/lang/Integer:intValue	()I
    //   3312: aload 80
    //   3314: invokevirtual 45	java/lang/Boolean:booleanValue	()Z
    //   3317: invokevirtual 684	java/util/BitSet:set	(IZ)V
    //   3320: aload 80
    //   3322: invokevirtual 45	java/lang/Boolean:booleanValue	()Z
    //   3325: ifeq -379 -> 2946
    //   3328: iload 78
    //   3330: ifne +8 -> 3338
    //   3333: iload 79
    //   3335: ifeq -389 -> 2946
    //   3338: aload 47
    //   3340: getfield 687	com/google/android/gms/internal/measurement/zzfz:zzayw	Ljava/lang/Long;
    //   3343: ifnull -397 -> 2946
    //   3346: iload 79
    //   3348: ifeq +27 -> 3375
    //   3351: aload 70
    //   3353: aload 72
    //   3355: getfield 665	com/google/android/gms/internal/measurement/zzfm:zzavm	Ljava/lang/Integer;
    //   3358: invokevirtual 306	java/lang/Integer:intValue	()I
    //   3361: aload 47
    //   3363: getfield 687	com/google/android/gms/internal/measurement/zzfz:zzayw	Ljava/lang/Long;
    //   3366: invokevirtual 170	java/lang/Long:longValue	()J
    //   3369: invokestatic 655	com/google/android/gms/measurement/internal/zzm:zzb	(Ljava/util/Map;IJ)V
    //   3372: goto -426 -> 2946
    //   3375: aload 69
    //   3377: aload 72
    //   3379: getfield 665	com/google/android/gms/internal/measurement/zzfm:zzavm	Ljava/lang/Integer;
    //   3382: invokevirtual 306	java/lang/Integer:intValue	()I
    //   3385: aload 47
    //   3387: getfield 687	com/google/android/gms/internal/measurement/zzfz:zzayw	Ljava/lang/Long;
    //   3390: invokevirtual 170	java/lang/Long:longValue	()J
    //   3393: invokestatic 657	com/google/android/gms/measurement/internal/zzm:zza	(Ljava/util/Map;IJ)V
    //   3396: goto -450 -> 2946
    //   3399: aload 68
    //   3401: aload 72
    //   3403: getfield 665	com/google/android/gms/internal/measurement/zzfm:zzavm	Ljava/lang/Integer;
    //   3406: invokevirtual 306	java/lang/Integer:intValue	()I
    //   3409: invokevirtual 645	java/util/BitSet:get	(I)Z
    //   3412: ifeq +29 -> 3441
    //   3415: aload_0
    //   3416: invokevirtual 76	com/google/android/gms/measurement/internal/zzcr:zzgt	()Lcom/google/android/gms/measurement/internal/zzas;
    //   3419: invokevirtual 205	com/google/android/gms/measurement/internal/zzas:zzjo	()Lcom/google/android/gms/measurement/internal/zzau;
    //   3422: ldc_w 689
    //   3425: iload 51
    //   3427: invokestatic 362	java/lang/Integer:valueOf	(I)Ljava/lang/Integer;
    //   3430: aload 72
    //   3432: getfield 665	com/google/android/gms/internal/measurement/zzfm:zzavm	Ljava/lang/Integer;
    //   3435: invokevirtual 143	com/google/android/gms/measurement/internal/zzau:zze	(Ljava/lang/String;Ljava/lang/Object;Ljava/lang/Object;)V
    //   3438: goto -492 -> 2946
    //   3441: aload_0
    //   3442: aload 72
    //   3444: aload 47
    //   3446: invokespecial 679	com/google/android/gms/measurement/internal/zzm:zza	(Lcom/google/android/gms/internal/measurement/zzfm;Lcom/google/android/gms/internal/measurement/zzfz;)Ljava/lang/Boolean;
    //   3449: astore 74
    //   3451: aload_0
    //   3452: invokevirtual 76	com/google/android/gms/measurement/internal/zzcr:zzgt	()Lcom/google/android/gms/measurement/internal/zzas;
    //   3455: invokevirtual 205	com/google/android/gms/measurement/internal/zzas:zzjo	()Lcom/google/android/gms/measurement/internal/zzau;
    //   3458: astore 75
    //   3460: aload 74
    //   3462: ifnonnull +39 -> 3501
    //   3465: ldc_w 651
    //   3468: astore 76
    //   3470: aload 75
    //   3472: ldc_w 681
    //   3475: aload 76
    //   3477: invokevirtual 100	com/google/android/gms/measurement/internal/zzau:zzg	(Ljava/lang/String;Ljava/lang/Object;)V
    //   3480: aload 74
    //   3482: ifnonnull +26 -> 3508
    //   3485: aload 5
    //   3487: iload 51
    //   3489: invokestatic 362	java/lang/Integer:valueOf	(I)Ljava/lang/Integer;
    //   3492: invokeinterface 106 2 0
    //   3497: pop
    //   3498: goto -552 -> 2946
    //   3501: aload 74
    //   3503: astore 76
    //   3505: goto -35 -> 3470
    //   3508: aload 67
    //   3510: aload 72
    //   3512: getfield 665	com/google/android/gms/internal/measurement/zzfm:zzavm	Ljava/lang/Integer;
    //   3515: invokevirtual 306	java/lang/Integer:intValue	()I
    //   3518: invokevirtual 446	java/util/BitSet:set	(I)V
    //   3521: aload 74
    //   3523: invokevirtual 45	java/lang/Boolean:booleanValue	()Z
    //   3526: ifeq -580 -> 2946
    //   3529: aload 68
    //   3531: aload 72
    //   3533: getfield 665	com/google/android/gms/internal/measurement/zzfm:zzavm	Ljava/lang/Integer;
    //   3536: invokevirtual 306	java/lang/Integer:intValue	()I
    //   3539: invokevirtual 446	java/util/BitSet:set	(I)V
    //   3542: goto -596 -> 2946
    //   3545: iinc 15 1
    //   3548: goto -1041 -> 2507
    //   3551: aload 7
    //   3553: invokeinterface 370 1 0
    //   3558: anewarray 454	com/google/android/gms/internal/measurement/zzfr
    //   3561: astore 16
    //   3563: aload 7
    //   3565: invokeinterface 376 1 0
    //   3570: invokeinterface 380 1 0
    //   3575: astore 17
    //   3577: iconst_0
    //   3578: istore 18
    //   3580: aload 17
    //   3582: invokeinterface 385 1 0
    //   3587: ifeq +629 -> 4216
    //   3590: aload 17
    //   3592: invokeinterface 389 1 0
    //   3597: checkcast 303	java/lang/Integer
    //   3600: invokevirtual 306	java/lang/Integer:intValue	()I
    //   3603: istore 19
    //   3605: aload 5
    //   3607: iload 19
    //   3609: invokestatic 362	java/lang/Integer:valueOf	(I)Ljava/lang/Integer;
    //   3612: invokeinterface 117 2 0
    //   3617: ifne -37 -> 3580
    //   3620: aload 6
    //   3622: iload 19
    //   3624: invokestatic 362	java/lang/Integer:valueOf	(I)Ljava/lang/Integer;
    //   3627: invokeinterface 159 2 0
    //   3632: checkcast 454	com/google/android/gms/internal/measurement/zzfr
    //   3635: astore 20
    //   3637: aload 20
    //   3639: ifnonnull +588 -> 4227
    //   3642: new 454	com/google/android/gms/internal/measurement/zzfr
    //   3645: dup
    //   3646: invokespecial 455	com/google/android/gms/internal/measurement/zzfr:<init>	()V
    //   3649: astore 21
    //   3651: iload 18
    //   3653: iconst_1
    //   3654: iadd
    //   3655: istore 22
    //   3657: aload 16
    //   3659: iload 18
    //   3661: aload 21
    //   3663: aastore
    //   3664: aload 21
    //   3666: iload 19
    //   3668: invokestatic 362	java/lang/Integer:valueOf	(I)Ljava/lang/Integer;
    //   3671: putfield 692	com/google/android/gms/internal/measurement/zzfr:zzavg	Ljava/lang/Integer;
    //   3674: aload 21
    //   3676: new 427	com/google/android/gms/internal/measurement/zzfx
    //   3679: dup
    //   3680: invokespecial 463	com/google/android/gms/internal/measurement/zzfx:<init>	()V
    //   3683: putfield 466	com/google/android/gms/internal/measurement/zzfr:zzawv	Lcom/google/android/gms/internal/measurement/zzfx;
    //   3686: aload 21
    //   3688: getfield 466	com/google/android/gms/internal/measurement/zzfr:zzawv	Lcom/google/android/gms/internal/measurement/zzfx;
    //   3691: aload 7
    //   3693: iload 19
    //   3695: invokestatic 362	java/lang/Integer:valueOf	(I)Ljava/lang/Integer;
    //   3698: invokeinterface 159 2 0
    //   3703: checkcast 429	java/util/BitSet
    //   3706: invokestatic 469	com/google/android/gms/measurement/internal/zzft:zza	(Ljava/util/BitSet;)[J
    //   3709: putfield 449	com/google/android/gms/internal/measurement/zzfx:zzayq	[J
    //   3712: aload 21
    //   3714: getfield 466	com/google/android/gms/internal/measurement/zzfr:zzawv	Lcom/google/android/gms/internal/measurement/zzfx;
    //   3717: aload 8
    //   3719: iload 19
    //   3721: invokestatic 362	java/lang/Integer:valueOf	(I)Ljava/lang/Integer;
    //   3724: invokeinterface 159 2 0
    //   3729: checkcast 429	java/util/BitSet
    //   3732: invokestatic 469	com/google/android/gms/measurement/internal/zzft:zza	(Ljava/util/BitSet;)[J
    //   3735: putfield 438	com/google/android/gms/internal/measurement/zzfx:zzayp	[J
    //   3738: iload 11
    //   3740: ifeq +71 -> 3811
    //   3743: aload 21
    //   3745: getfield 466	com/google/android/gms/internal/measurement/zzfr:zzawv	Lcom/google/android/gms/internal/measurement/zzfx;
    //   3748: aload 9
    //   3750: iload 19
    //   3752: invokestatic 362	java/lang/Integer:valueOf	(I)Ljava/lang/Integer;
    //   3755: invokeinterface 159 2 0
    //   3760: checkcast 123	java/util/Map
    //   3763: invokestatic 471	com/google/android/gms/measurement/internal/zzm:zzb	(Ljava/util/Map;)[Lcom/google/android/gms/internal/measurement/zzfs;
    //   3766: putfield 433	com/google/android/gms/internal/measurement/zzfx:zzayr	[Lcom/google/android/gms/internal/measurement/zzfs;
    //   3769: aload 21
    //   3771: getfield 466	com/google/android/gms/internal/measurement/zzfr:zzawv	Lcom/google/android/gms/internal/measurement/zzfx;
    //   3774: astore 32
    //   3776: aload 10
    //   3778: iload 19
    //   3780: invokestatic 362	java/lang/Integer:valueOf	(I)Ljava/lang/Integer;
    //   3783: invokeinterface 159 2 0
    //   3788: checkcast 123	java/util/Map
    //   3791: astore 33
    //   3793: aload 33
    //   3795: ifnonnull +170 -> 3965
    //   3798: iconst_0
    //   3799: anewarray 694	com/google/android/gms/internal/measurement/zzfy
    //   3802: astore 34
    //   3804: aload 32
    //   3806: aload 34
    //   3808: putfield 698	com/google/android/gms/internal/measurement/zzfx:zzays	[Lcom/google/android/gms/internal/measurement/zzfy;
    //   3811: aload_0
    //   3812: invokevirtual 419	com/google/android/gms/measurement/internal/zzfl:zzjt	()Lcom/google/android/gms/measurement/internal/zzt;
    //   3815: astore 23
    //   3817: aload 21
    //   3819: getfield 466	com/google/android/gms/internal/measurement/zzfr:zzawv	Lcom/google/android/gms/internal/measurement/zzfx;
    //   3822: astore 24
    //   3824: aload 23
    //   3826: invokevirtual 701	com/google/android/gms/measurement/internal/zzfm:zzcl	()V
    //   3829: aload 23
    //   3831: invokevirtual 523	com/google/android/gms/measurement/internal/zzcr:zzaf	()V
    //   3834: aload_1
    //   3835: invokestatic 404	com/google/android/gms/common/internal/Preconditions:checkNotEmpty	(Ljava/lang/String;)Ljava/lang/String;
    //   3838: pop
    //   3839: aload 24
    //   3841: invokestatic 295	com/google/android/gms/common/internal/Preconditions:checkNotNull	(Ljava/lang/Object;)Ljava/lang/Object;
    //   3844: pop
    //   3845: aload 24
    //   3847: invokevirtual 706	com/google/android/gms/internal/measurement/zzyi:zzvx	()I
    //   3850: newarray byte
    //   3852: astore 28
    //   3854: aload 28
    //   3856: iconst_0
    //   3857: aload 28
    //   3859: arraylength
    //   3860: invokestatic 712	com/google/android/gms/internal/measurement/zzya:zzk	([BII)Lcom/google/android/gms/internal/measurement/zzya;
    //   3863: astore 29
    //   3865: aload 24
    //   3867: aload 29
    //   3869: invokevirtual 715	com/google/android/gms/internal/measurement/zzyi:zza	(Lcom/google/android/gms/internal/measurement/zzya;)V
    //   3872: aload 29
    //   3874: invokevirtual 718	com/google/android/gms/internal/measurement/zzya:zzza	()V
    //   3877: new 720	android/content/ContentValues
    //   3880: dup
    //   3881: invokespecial 721	android/content/ContentValues:<init>	()V
    //   3884: astore 30
    //   3886: aload 30
    //   3888: ldc_w 723
    //   3891: aload_1
    //   3892: invokevirtual 726	android/content/ContentValues:put	(Ljava/lang/String;Ljava/lang/String;)V
    //   3895: aload 30
    //   3897: ldc_w 728
    //   3900: iload 19
    //   3902: invokestatic 362	java/lang/Integer:valueOf	(I)Ljava/lang/Integer;
    //   3905: invokevirtual 731	android/content/ContentValues:put	(Ljava/lang/String;Ljava/lang/Integer;)V
    //   3908: aload 30
    //   3910: ldc_w 733
    //   3913: aload 28
    //   3915: invokevirtual 736	android/content/ContentValues:put	(Ljava/lang/String;[B)V
    //   3918: aload 23
    //   3920: invokevirtual 529	com/google/android/gms/measurement/internal/zzt:getWritableDatabase	()Landroid/database/sqlite/SQLiteDatabase;
    //   3923: ldc_w 738
    //   3926: aconst_null
    //   3927: aload 30
    //   3929: iconst_5
    //   3930: invokevirtual 742	android/database/sqlite/SQLiteDatabase:insertWithOnConflict	(Ljava/lang/String;Ljava/lang/String;Landroid/content/ContentValues;I)J
    //   3933: ldc2_w 743
    //   3936: lcmp
    //   3937: ifne +21 -> 3958
    //   3940: aload 23
    //   3942: invokevirtual 76	com/google/android/gms/measurement/internal/zzcr:zzgt	()Lcom/google/android/gms/measurement/internal/zzas;
    //   3945: invokevirtual 504	com/google/android/gms/measurement/internal/zzas:zzjg	()Lcom/google/android/gms/measurement/internal/zzau;
    //   3948: ldc_w 746
    //   3951: aload_1
    //   3952: invokestatic 554	com/google/android/gms/measurement/internal/zzas:zzbw	(Ljava/lang/String;)Ljava/lang/Object;
    //   3955: invokevirtual 100	com/google/android/gms/measurement/internal/zzau:zzg	(Ljava/lang/String;Ljava/lang/Object;)V
    //   3958: iload 22
    //   3960: istore 18
    //   3962: goto -382 -> 3580
    //   3965: aload 33
    //   3967: invokeinterface 370 1 0
    //   3972: anewarray 694	com/google/android/gms/internal/measurement/zzfy
    //   3975: astore 35
    //   3977: aload 33
    //   3979: invokeinterface 376 1 0
    //   3984: invokeinterface 380 1 0
    //   3989: astore 36
    //   3991: iconst_0
    //   3992: istore 37
    //   3994: aload 36
    //   3996: invokeinterface 385 1 0
    //   4001: ifeq +150 -> 4151
    //   4004: aload 36
    //   4006: invokeinterface 389 1 0
    //   4011: checkcast 303	java/lang/Integer
    //   4014: astore 38
    //   4016: new 694	com/google/android/gms/internal/measurement/zzfy
    //   4019: dup
    //   4020: invokespecial 747	com/google/android/gms/internal/measurement/zzfy:<init>	()V
    //   4023: astore 39
    //   4025: aload 39
    //   4027: aload 38
    //   4029: putfield 748	com/google/android/gms/internal/measurement/zzfy:zzawz	Ljava/lang/Integer;
    //   4032: aload 33
    //   4034: aload 38
    //   4036: invokeinterface 159 2 0
    //   4041: checkcast 246	java/util/List
    //   4044: astore 40
    //   4046: aload 40
    //   4048: ifnull +83 -> 4131
    //   4051: aload 40
    //   4053: invokestatic 754	java/util/Collections:sort	(Ljava/util/List;)V
    //   4056: aload 40
    //   4058: invokeinterface 250 1 0
    //   4063: newarray long
    //   4065: astore 42
    //   4067: iconst_0
    //   4068: istore 43
    //   4070: aload 40
    //   4072: invokeinterface 612 1 0
    //   4077: astore 44
    //   4079: aload 44
    //   4081: invokeinterface 385 1 0
    //   4086: ifeq +38 -> 4124
    //   4089: aload 44
    //   4091: invokeinterface 389 1 0
    //   4096: checkcast 161	java/lang/Long
    //   4099: astore 45
    //   4101: iload 43
    //   4103: iconst_1
    //   4104: iadd
    //   4105: istore 46
    //   4107: aload 42
    //   4109: iload 43
    //   4111: aload 45
    //   4113: invokevirtual 170	java/lang/Long:longValue	()J
    //   4116: lastore
    //   4117: iload 46
    //   4119: istore 43
    //   4121: goto -42 -> 4079
    //   4124: aload 39
    //   4126: aload 42
    //   4128: putfield 757	com/google/android/gms/internal/measurement/zzfy:zzayu	[J
    //   4131: iload 37
    //   4133: iconst_1
    //   4134: iadd
    //   4135: istore 41
    //   4137: aload 35
    //   4139: iload 37
    //   4141: aload 39
    //   4143: aastore
    //   4144: iload 41
    //   4146: istore 37
    //   4148: goto -154 -> 3994
    //   4151: aload 35
    //   4153: astore 34
    //   4155: goto -351 -> 3804
    //   4158: astore 27
    //   4160: aload 23
    //   4162: invokevirtual 76	com/google/android/gms/measurement/internal/zzcr:zzgt	()Lcom/google/android/gms/measurement/internal/zzas;
    //   4165: invokevirtual 504	com/google/android/gms/measurement/internal/zzas:zzjg	()Lcom/google/android/gms/measurement/internal/zzau;
    //   4168: ldc_w 759
    //   4171: aload_1
    //   4172: invokestatic 554	com/google/android/gms/measurement/internal/zzas:zzbw	(Ljava/lang/String;)Ljava/lang/Object;
    //   4175: aload 27
    //   4177: invokevirtual 143	com/google/android/gms/measurement/internal/zzau:zze	(Ljava/lang/String;Ljava/lang/Object;Ljava/lang/Object;)V
    //   4180: iload 22
    //   4182: istore 18
    //   4184: goto -604 -> 3580
    //   4187: astore 31
    //   4189: aload 23
    //   4191: invokevirtual 76	com/google/android/gms/measurement/internal/zzcr:zzgt	()Lcom/google/android/gms/measurement/internal/zzas;
    //   4194: invokevirtual 504	com/google/android/gms/measurement/internal/zzas:zzjg	()Lcom/google/android/gms/measurement/internal/zzau;
    //   4197: ldc_w 761
    //   4200: aload_1
    //   4201: invokestatic 554	com/google/android/gms/measurement/internal/zzas:zzbw	(Ljava/lang/String;)Ljava/lang/Object;
    //   4204: aload 31
    //   4206: invokevirtual 143	com/google/android/gms/measurement/internal/zzau:zze	(Ljava/lang/String;Ljava/lang/Object;Ljava/lang/Object;)V
    //   4209: iload 22
    //   4211: istore 18
    //   4213: goto -633 -> 3580
    //   4216: aload 16
    //   4218: iload 18
    //   4220: invokestatic 579	java/util/Arrays:copyOf	([Ljava/lang/Object;I)[Ljava/lang/Object;
    //   4223: checkcast 763	[Lcom/google/android/gms/internal/measurement/zzfr;
    //   4226: areturn
    //   4227: aload 20
    //   4229: astore 21
    //   4231: goto -580 -> 3651
    //   4234: aload 55
    //   4236: astore 70
    //   4238: aload 61
    //   4240: astore 67
    //   4242: aload 56
    //   4244: astore 69
    //   4246: aload 59
    //   4248: astore 68
    //   4250: goto -1326 -> 2924
    //   4253: aload 55
    //   4255: astore 84
    //   4257: aload 54
    //   4259: astore 67
    //   4261: aload 56
    //   4263: astore 69
    //   4265: aload 53
    //   4267: astore 68
    //   4269: aload 84
    //   4271: astore 70
    //   4273: goto -1349 -> 2924
    //   4276: aload 48
    //   4278: astore 49
    //   4280: goto -1690 -> 2590
    //   4283: aload 98
    //   4285: astore 99
    //   4287: aload 97
    //   4289: astore 100
    //   4291: aload 92
    //   4293: astore 101
    //   4295: lload 90
    //   4297: lstore 102
    //   4299: aload 89
    //   4301: astore 104
    //   4303: goto -3164 -> 1139
    //   4306: aload 92
    //   4308: astore 163
    //   4310: goto -3438 -> 872
    //   4313: aload 122
    //   4315: astore 129
    //   4317: aload 120
    //   4319: astore 130
    //   4321: aload 117
    //   4323: astore 131
    //   4325: aload 116
    //   4327: astore 128
    //   4329: goto -2453 -> 1876
    //   4332: aload 117
    //   4334: astore 131
    //   4336: aload 115
    //   4338: astore 129
    //   4340: aload 114
    //   4342: astore 130
    //   4344: aload 116
    //   4346: astore 128
    //   4348: goto -2472 -> 1876
    //   4351: aload 101
    //   4353: astore 92
    //   4355: lload 102
    //   4357: lstore 90
    //   4359: aload 104
    //   4361: astore 89
    //   4363: goto -3623 -> 740
    //   4366: aload 109
    //   4368: astore 110
    //   4370: goto -3078 -> 1292
    //   4373: iload 168
    //   4375: istore 179
    //   4377: goto -3369 -> 1008
    //   4380: aconst_null
    //   4381: astore 189
    //   4383: goto -4163 -> 220
    //
    // Exception table:
    //   from	to	target	type
    //   911	930	1018	android/database/sqlite/SQLiteException
    //   3845	3877	4158	java/io/IOException
    //   3918	3958	4187	android/database/sqlite/SQLiteException
  }

  protected final boolean zzgy()
  {
    return false;
  }
}

/* Location:           E:\Study\Tools\apktool2_2\dex2jar-0.0.9.15\classes_viber_2_dex2jar.jar
 * Qualified Name:     com.google.android.gms.measurement.internal.zzm
 * JD-Core Version:    0.6.2
 */