package com.google.android.gms.measurement.internal;

import android.content.ContentValues;
import android.content.Context;
import android.database.Cursor;
import android.database.sqlite.SQLiteDatabase;
import android.database.sqlite.SQLiteException;
import android.text.TextUtils;
import com.google.android.gms.common.internal.Preconditions;
import com.google.android.gms.common.util.Clock;
import com.google.android.gms.common.util.VisibleForTesting;
import com.google.android.gms.internal.measurement.zzfj;
import com.google.android.gms.internal.measurement.zzya;
import com.google.android.gms.internal.measurement.zzyi;
import java.io.File;
import java.io.IOException;
import java.util.ArrayList;
import java.util.List;

final class zzt extends zzfm
{
  private static final String[] zzagz = { "last_bundled_timestamp", "ALTER TABLE events ADD COLUMN last_bundled_timestamp INTEGER;", "last_bundled_day", "ALTER TABLE events ADD COLUMN last_bundled_day INTEGER;", "last_sampled_complex_event_id", "ALTER TABLE events ADD COLUMN last_sampled_complex_event_id INTEGER;", "last_sampling_rate", "ALTER TABLE events ADD COLUMN last_sampling_rate INTEGER;", "last_exempt_from_sampling", "ALTER TABLE events ADD COLUMN last_exempt_from_sampling INTEGER;" };
  private static final String[] zzaha = { "origin", "ALTER TABLE user_attributes ADD COLUMN origin TEXT;" };
  private static final String[] zzahb = { "app_version", "ALTER TABLE apps ADD COLUMN app_version TEXT;", "app_store", "ALTER TABLE apps ADD COLUMN app_store TEXT;", "gmp_version", "ALTER TABLE apps ADD COLUMN gmp_version INTEGER;", "dev_cert_hash", "ALTER TABLE apps ADD COLUMN dev_cert_hash INTEGER;", "measurement_enabled", "ALTER TABLE apps ADD COLUMN measurement_enabled INTEGER;", "last_bundle_start_timestamp", "ALTER TABLE apps ADD COLUMN last_bundle_start_timestamp INTEGER;", "day", "ALTER TABLE apps ADD COLUMN day INTEGER;", "daily_public_events_count", "ALTER TABLE apps ADD COLUMN daily_public_events_count INTEGER;", "daily_events_count", "ALTER TABLE apps ADD COLUMN daily_events_count INTEGER;", "daily_conversions_count", "ALTER TABLE apps ADD COLUMN daily_conversions_count INTEGER;", "remote_config", "ALTER TABLE apps ADD COLUMN remote_config BLOB;", "config_fetched_time", "ALTER TABLE apps ADD COLUMN config_fetched_time INTEGER;", "failed_config_fetch_time", "ALTER TABLE apps ADD COLUMN failed_config_fetch_time INTEGER;", "app_version_int", "ALTER TABLE apps ADD COLUMN app_version_int INTEGER;", "firebase_instance_id", "ALTER TABLE apps ADD COLUMN firebase_instance_id TEXT;", "daily_error_events_count", "ALTER TABLE apps ADD COLUMN daily_error_events_count INTEGER;", "daily_realtime_events_count", "ALTER TABLE apps ADD COLUMN daily_realtime_events_count INTEGER;", "health_monitor_sample", "ALTER TABLE apps ADD COLUMN health_monitor_sample TEXT;", "android_id", "ALTER TABLE apps ADD COLUMN android_id INTEGER;", "adid_reporting_enabled", "ALTER TABLE apps ADD COLUMN adid_reporting_enabled INTEGER;", "ssaid_reporting_enabled", "ALTER TABLE apps ADD COLUMN ssaid_reporting_enabled INTEGER;", "admob_app_id", "ALTER TABLE apps ADD COLUMN admob_app_id TEXT;", "linked_admob_app_id", "ALTER TABLE apps ADD COLUMN linked_admob_app_id TEXT;" };
  private static final String[] zzahc = { "realtime", "ALTER TABLE raw_events ADD COLUMN realtime INTEGER;" };
  private static final String[] zzahd = { "has_realtime", "ALTER TABLE queue ADD COLUMN has_realtime INTEGER;", "retry_count", "ALTER TABLE queue ADD COLUMN retry_count INTEGER;" };
  private static final String[] zzahe = { "previous_install_count", "ALTER TABLE app2 ADD COLUMN previous_install_count INTEGER;" };
  private final zzw zzahf = new zzw(this, getContext(), "google_app_measurement.db");
  private final zzfi zzahg = new zzfi(zzbx());

  zzt(zzfn paramzzfn)
  {
    super(paramzzfn);
  }

  private final long zza(String paramString, String[] paramArrayOfString)
  {
    SQLiteDatabase localSQLiteDatabase = getWritableDatabase();
    Cursor localCursor = null;
    try
    {
      localCursor = localSQLiteDatabase.rawQuery(paramString, paramArrayOfString);
      if (localCursor.moveToFirst())
      {
        long l = localCursor.getLong(0);
        return l;
      }
      throw new SQLiteException("Database returned empty set");
    }
    catch (SQLiteException localSQLiteException)
    {
      zzgt().zzjg().zze("Database error", paramString, localSQLiteException);
      throw localSQLiteException;
    }
    finally
    {
      if (localCursor != null)
        localCursor.close();
    }
  }

  private final long zza(String paramString, String[] paramArrayOfString, long paramLong)
  {
    SQLiteDatabase localSQLiteDatabase = getWritableDatabase();
    Cursor localCursor = null;
    try
    {
      localCursor = localSQLiteDatabase.rawQuery(paramString, paramArrayOfString);
      if (localCursor.moveToFirst())
      {
        long l = localCursor.getLong(0);
        paramLong = l;
        return paramLong;
      }
      return paramLong;
    }
    catch (SQLiteException localSQLiteException)
    {
      zzgt().zzjg().zze("Database error", paramString, localSQLiteException);
      throw localSQLiteException;
    }
    finally
    {
      if (localCursor != null)
        localCursor.close();
    }
  }

  @VisibleForTesting
  private final Object zza(Cursor paramCursor, int paramInt)
  {
    int i = paramCursor.getType(paramInt);
    switch (i)
    {
    default:
      zzgt().zzjg().zzg("Loaded invalid unknown value type, ignoring it", Integer.valueOf(i));
      return null;
    case 0:
      zzgt().zzjg().zzby("Loaded invalid null value from database");
      return null;
    case 1:
      return Long.valueOf(paramCursor.getLong(paramInt));
    case 2:
      return Double.valueOf(paramCursor.getDouble(paramInt));
    case 3:
      return paramCursor.getString(paramInt);
    case 4:
    }
    zzgt().zzjg().zzby("Loaded invalid blob type value, ignoring it");
    return null;
  }

  private static void zza(ContentValues paramContentValues, String paramString, Object paramObject)
  {
    Preconditions.checkNotEmpty(paramString);
    Preconditions.checkNotNull(paramObject);
    if ((paramObject instanceof String))
    {
      paramContentValues.put(paramString, (String)paramObject);
      return;
    }
    if ((paramObject instanceof Long))
    {
      paramContentValues.put(paramString, (Long)paramObject);
      return;
    }
    if ((paramObject instanceof Double))
    {
      paramContentValues.put(paramString, (Double)paramObject);
      return;
    }
    throw new IllegalArgumentException("Invalid value type");
  }

  // ERROR //
  private final boolean zza(String paramString, int paramInt, zzfj paramzzfj)
  {
    // Byte code:
    //   0: aload_0
    //   1: invokevirtual 322	com/google/android/gms/measurement/internal/zzfm:zzcl	()V
    //   4: aload_0
    //   5: invokevirtual 325	com/google/android/gms/measurement/internal/zzcr:zzaf	()V
    //   8: aload_1
    //   9: invokestatic 295	com/google/android/gms/common/internal/Preconditions:checkNotEmpty	(Ljava/lang/String;)Ljava/lang/String;
    //   12: pop
    //   13: aload_3
    //   14: invokestatic 299	com/google/android/gms/common/internal/Preconditions:checkNotNull	(Ljava/lang/Object;)Ljava/lang/Object;
    //   17: pop
    //   18: aload_3
    //   19: getfield 331	com/google/android/gms/internal/measurement/zzfj:zzavn	Ljava/lang/String;
    //   22: invokestatic 337	android/text/TextUtils:isEmpty	(Ljava/lang/CharSequence;)Z
    //   25: ifeq +33 -> 58
    //   28: aload_0
    //   29: invokevirtual 229	com/google/android/gms/measurement/internal/zzcr:zzgt	()Lcom/google/android/gms/measurement/internal/zzas;
    //   32: invokevirtual 340	com/google/android/gms/measurement/internal/zzas:zzjj	()Lcom/google/android/gms/measurement/internal/zzau;
    //   35: ldc_w 342
    //   38: aload_1
    //   39: invokestatic 346	com/google/android/gms/measurement/internal/zzas:zzbw	(Ljava/lang/String;)Ljava/lang/Object;
    //   42: iload_2
    //   43: invokestatic 259	java/lang/Integer:valueOf	(I)Ljava/lang/Integer;
    //   46: aload_3
    //   47: getfield 350	com/google/android/gms/internal/measurement/zzfj:zzavm	Ljava/lang/Integer;
    //   50: invokestatic 353	java/lang/String:valueOf	(Ljava/lang/Object;)Ljava/lang/String;
    //   53: invokevirtual 357	com/google/android/gms/measurement/internal/zzau:zzd	(Ljava/lang/String;Ljava/lang/Object;Ljava/lang/Object;Ljava/lang/Object;)V
    //   56: iconst_0
    //   57: ireturn
    //   58: aload_3
    //   59: invokevirtual 363	com/google/android/gms/internal/measurement/zzyi:zzvx	()I
    //   62: newarray byte
    //   64: astore 7
    //   66: aload 7
    //   68: iconst_0
    //   69: aload 7
    //   71: arraylength
    //   72: invokestatic 369	com/google/android/gms/internal/measurement/zzya:zzk	([BII)Lcom/google/android/gms/internal/measurement/zzya;
    //   75: astore 8
    //   77: aload_3
    //   78: aload 8
    //   80: invokevirtual 372	com/google/android/gms/internal/measurement/zzyi:zza	(Lcom/google/android/gms/internal/measurement/zzya;)V
    //   83: aload 8
    //   85: invokevirtual 375	com/google/android/gms/internal/measurement/zzya:zzza	()V
    //   88: new 301	android/content/ContentValues
    //   91: dup
    //   92: invokespecial 377	android/content/ContentValues:<init>	()V
    //   95: astore 9
    //   97: aload 9
    //   99: ldc_w 379
    //   102: aload_1
    //   103: invokevirtual 305	android/content/ContentValues:put	(Ljava/lang/String;Ljava/lang/String;)V
    //   106: aload 9
    //   108: ldc_w 381
    //   111: iload_2
    //   112: invokestatic 259	java/lang/Integer:valueOf	(I)Ljava/lang/Integer;
    //   115: invokevirtual 384	android/content/ContentValues:put	(Ljava/lang/String;Ljava/lang/Integer;)V
    //   118: aload 9
    //   120: ldc_w 386
    //   123: aload_3
    //   124: getfield 350	com/google/android/gms/internal/measurement/zzfj:zzavm	Ljava/lang/Integer;
    //   127: invokevirtual 384	android/content/ContentValues:put	(Ljava/lang/String;Ljava/lang/Integer;)V
    //   130: aload 9
    //   132: ldc_w 388
    //   135: aload_3
    //   136: getfield 331	com/google/android/gms/internal/measurement/zzfj:zzavn	Ljava/lang/String;
    //   139: invokevirtual 305	android/content/ContentValues:put	(Ljava/lang/String;Ljava/lang/String;)V
    //   142: aload 9
    //   144: ldc_w 390
    //   147: aload 7
    //   149: invokevirtual 393	android/content/ContentValues:put	(Ljava/lang/String;[B)V
    //   152: aload_0
    //   153: invokevirtual 201	com/google/android/gms/measurement/internal/zzt:getWritableDatabase	()Landroid/database/sqlite/SQLiteDatabase;
    //   156: ldc_w 395
    //   159: aconst_null
    //   160: aload 9
    //   162: iconst_5
    //   163: invokevirtual 399	android/database/sqlite/SQLiteDatabase:insertWithOnConflict	(Ljava/lang/String;Ljava/lang/String;Landroid/content/ContentValues;I)J
    //   166: ldc2_w 400
    //   169: lcmp
    //   170: ifne +20 -> 190
    //   173: aload_0
    //   174: invokevirtual 229	com/google/android/gms/measurement/internal/zzcr:zzgt	()Lcom/google/android/gms/measurement/internal/zzas;
    //   177: invokevirtual 235	com/google/android/gms/measurement/internal/zzas:zzjg	()Lcom/google/android/gms/measurement/internal/zzau;
    //   180: ldc_w 403
    //   183: aload_1
    //   184: invokestatic 346	com/google/android/gms/measurement/internal/zzas:zzbw	(Ljava/lang/String;)Ljava/lang/Object;
    //   187: invokevirtual 263	com/google/android/gms/measurement/internal/zzau:zzg	(Ljava/lang/String;Ljava/lang/Object;)V
    //   190: iconst_1
    //   191: ireturn
    //   192: astore 6
    //   194: aload_0
    //   195: invokevirtual 229	com/google/android/gms/measurement/internal/zzcr:zzgt	()Lcom/google/android/gms/measurement/internal/zzas;
    //   198: invokevirtual 235	com/google/android/gms/measurement/internal/zzas:zzjg	()Lcom/google/android/gms/measurement/internal/zzau;
    //   201: ldc_w 405
    //   204: aload_1
    //   205: invokestatic 346	com/google/android/gms/measurement/internal/zzas:zzbw	(Ljava/lang/String;)Ljava/lang/Object;
    //   208: aload 6
    //   210: invokevirtual 243	com/google/android/gms/measurement/internal/zzau:zze	(Ljava/lang/String;Ljava/lang/Object;Ljava/lang/Object;)V
    //   213: iconst_0
    //   214: ireturn
    //   215: astore 10
    //   217: aload_0
    //   218: invokevirtual 229	com/google/android/gms/measurement/internal/zzcr:zzgt	()Lcom/google/android/gms/measurement/internal/zzas;
    //   221: invokevirtual 235	com/google/android/gms/measurement/internal/zzas:zzjg	()Lcom/google/android/gms/measurement/internal/zzau;
    //   224: ldc_w 407
    //   227: aload_1
    //   228: invokestatic 346	com/google/android/gms/measurement/internal/zzas:zzbw	(Ljava/lang/String;)Ljava/lang/Object;
    //   231: aload 10
    //   233: invokevirtual 243	com/google/android/gms/measurement/internal/zzau:zze	(Ljava/lang/String;Ljava/lang/Object;Ljava/lang/Object;)V
    //   236: iconst_0
    //   237: ireturn
    //
    // Exception table:
    //   from	to	target	type
    //   58	88	192	java/io/IOException
    //   152	190	215	android/database/sqlite/SQLiteException
  }

  private final boolean zza(String paramString, int paramInt, com.google.android.gms.internal.measurement.zzfm paramzzfm)
  {
    zzcl();
    zzaf();
    Preconditions.checkNotEmpty(paramString);
    Preconditions.checkNotNull(paramzzfm);
    if (TextUtils.isEmpty(paramzzfm.zzawc))
    {
      zzgt().zzjj().zzd("Property filter had no property name. Audience definition ignored. appId, audienceId, filterId", zzas.zzbw(paramString), Integer.valueOf(paramInt), String.valueOf(paramzzfm.zzavm));
      return false;
    }
    try
    {
      byte[] arrayOfByte = new byte[paramzzfm.zzvx()];
      zzya localzzya = zzya.zzk(arrayOfByte, 0, arrayOfByte.length);
      paramzzfm.zza(localzzya);
      localzzya.zzza();
      ContentValues localContentValues = new ContentValues();
      localContentValues.put("app_id", paramString);
      localContentValues.put("audience_id", Integer.valueOf(paramInt));
      localContentValues.put("filter_id", paramzzfm.zzavm);
      localContentValues.put("property_name", paramzzfm.zzawc);
      localContentValues.put("data", arrayOfByte);
      try
      {
        if (getWritableDatabase().insertWithOnConflict("property_filters", null, localContentValues, 5) == -1L)
        {
          zzgt().zzjg().zzg("Failed to insert property filter (got -1). appId", zzas.zzbw(paramString));
          return false;
        }
      }
      catch (SQLiteException localSQLiteException)
      {
        zzgt().zzjg().zze("Error storing property filter. appId", zzas.zzbw(paramString), localSQLiteException);
        return false;
      }
    }
    catch (IOException localIOException)
    {
      zzgt().zzjg().zze("Configuration loss. Failed to serialize property filter. appId", zzas.zzbw(paramString), localIOException);
      return false;
    }
    return true;
  }

  private final boolean zza(String paramString, List<Integer> paramList)
  {
    Preconditions.checkNotEmpty(paramString);
    zzcl();
    zzaf();
    SQLiteDatabase localSQLiteDatabase = getWritableDatabase();
    label164: String str3;
    String[] arrayOfString;
    do
    {
      int i;
      try
      {
        long l = zza("select count(1) from audience_filter_values where app_id=?", new String[] { paramString });
        i = Math.max(0, Math.min(2000, zzgv().zzb(paramString, zzai.zzajz)));
        if (l <= i)
          return false;
      }
      catch (SQLiteException localSQLiteException)
      {
        zzgt().zzjg().zze("Database error querying filters. appId", zzas.zzbw(paramString), localSQLiteException);
        return false;
      }
      ArrayList localArrayList = new ArrayList();
      for (int j = 0; ; j++)
      {
        if (j >= paramList.size())
          break label164;
        Integer localInteger = (Integer)paramList.get(j);
        if ((localInteger == null) || (!(localInteger instanceof Integer)))
          break;
        localArrayList.add(Integer.toString(localInteger.intValue()));
      }
      String str1 = TextUtils.join(",", localArrayList);
      String str2 = 2 + String.valueOf(str1).length() + "(" + str1 + ")";
      str3 = 140 + String.valueOf(str2).length() + "audience_id in (select audience_id from audience_filter_values where app_id=? and audience_id not in " + str2 + " order by rowid desc limit -1 offset ?)";
      arrayOfString = new String[2];
      arrayOfString[0] = paramString;
      arrayOfString[1] = Integer.toString(i);
    }
    while (localSQLiteDatabase.delete("audience_filter_values", str3, arrayOfString) <= 0);
    return true;
  }

  private final boolean zzip()
  {
    return getContext().getDatabasePath("google_app_measurement.db").exists();
  }

  public final void beginTransaction()
  {
    zzcl();
    getWritableDatabase().beginTransaction();
  }

  public final void endTransaction()
  {
    zzcl();
    getWritableDatabase().endTransaction();
  }

  @VisibleForTesting
  final SQLiteDatabase getWritableDatabase()
  {
    zzaf();
    try
    {
      SQLiteDatabase localSQLiteDatabase = this.zzahf.getWritableDatabase();
      return localSQLiteDatabase;
    }
    catch (SQLiteException localSQLiteException)
    {
      zzgt().zzjj().zzg("Error opening database", localSQLiteException);
      throw localSQLiteException;
    }
  }

  public final void setTransactionSuccessful()
  {
    zzcl();
    getWritableDatabase().setTransactionSuccessful();
  }

  // ERROR //
  public final long zza(com.google.android.gms.internal.measurement.zzfw paramzzfw)
    throws IOException
  {
    // Byte code:
    //   0: aload_0
    //   1: invokevirtual 325	com/google/android/gms/measurement/internal/zzcr:zzaf	()V
    //   4: aload_0
    //   5: invokevirtual 322	com/google/android/gms/measurement/internal/zzfm:zzcl	()V
    //   8: aload_1
    //   9: invokestatic 299	com/google/android/gms/common/internal/Preconditions:checkNotNull	(Ljava/lang/Object;)Ljava/lang/Object;
    //   12: pop
    //   13: aload_1
    //   14: getfield 552	com/google/android/gms/internal/measurement/zzfw:zztt	Ljava/lang/String;
    //   17: invokestatic 295	com/google/android/gms/common/internal/Preconditions:checkNotEmpty	(Ljava/lang/String;)Ljava/lang/String;
    //   20: pop
    //   21: aload_1
    //   22: invokevirtual 363	com/google/android/gms/internal/measurement/zzyi:zzvx	()I
    //   25: newarray byte
    //   27: astore 5
    //   29: aload 5
    //   31: iconst_0
    //   32: aload 5
    //   34: arraylength
    //   35: invokestatic 369	com/google/android/gms/internal/measurement/zzya:zzk	([BII)Lcom/google/android/gms/internal/measurement/zzya;
    //   38: astore 6
    //   40: aload_1
    //   41: aload 6
    //   43: invokevirtual 372	com/google/android/gms/internal/measurement/zzyi:zza	(Lcom/google/android/gms/internal/measurement/zzya;)V
    //   46: aload 6
    //   48: invokevirtual 375	com/google/android/gms/internal/measurement/zzya:zzza	()V
    //   51: aload_0
    //   52: invokevirtual 558	com/google/android/gms/measurement/internal/zzfl:zzjr	()Lcom/google/android/gms/measurement/internal/zzft;
    //   55: astore 7
    //   57: aload 5
    //   59: invokestatic 299	com/google/android/gms/common/internal/Preconditions:checkNotNull	(Ljava/lang/Object;)Ljava/lang/Object;
    //   62: pop
    //   63: aload 7
    //   65: invokevirtual 562	com/google/android/gms/measurement/internal/zzcr:zzgr	()Lcom/google/android/gms/measurement/internal/zzfx;
    //   68: invokevirtual 325	com/google/android/gms/measurement/internal/zzcr:zzaf	()V
    //   71: invokestatic 568	com/google/android/gms/measurement/internal/zzfx:getMessageDigest	()Ljava/security/MessageDigest;
    //   74: astore 9
    //   76: aload 9
    //   78: ifnonnull +109 -> 187
    //   81: aload 7
    //   83: invokevirtual 229	com/google/android/gms/measurement/internal/zzcr:zzgt	()Lcom/google/android/gms/measurement/internal/zzas;
    //   86: invokevirtual 235	com/google/android/gms/measurement/internal/zzas:zzjg	()Lcom/google/android/gms/measurement/internal/zzau;
    //   89: ldc_w 570
    //   92: invokevirtual 268	com/google/android/gms/measurement/internal/zzau:zzby	(Ljava/lang/String;)V
    //   95: lconst_0
    //   96: lstore 10
    //   98: new 301	android/content/ContentValues
    //   101: dup
    //   102: invokespecial 377	android/content/ContentValues:<init>	()V
    //   105: astore 12
    //   107: aload 12
    //   109: ldc_w 379
    //   112: aload_1
    //   113: getfield 552	com/google/android/gms/internal/measurement/zzfw:zztt	Ljava/lang/String;
    //   116: invokevirtual 305	android/content/ContentValues:put	(Ljava/lang/String;Ljava/lang/String;)V
    //   119: aload 12
    //   121: ldc_w 572
    //   124: lload 10
    //   126: invokestatic 273	java/lang/Long:valueOf	(J)Ljava/lang/Long;
    //   129: invokevirtual 308	android/content/ContentValues:put	(Ljava/lang/String;Ljava/lang/Long;)V
    //   132: aload 12
    //   134: ldc_w 574
    //   137: aload 5
    //   139: invokevirtual 393	android/content/ContentValues:put	(Ljava/lang/String;[B)V
    //   142: aload_0
    //   143: invokevirtual 201	com/google/android/gms/measurement/internal/zzt:getWritableDatabase	()Landroid/database/sqlite/SQLiteDatabase;
    //   146: ldc_w 576
    //   149: aconst_null
    //   150: aload 12
    //   152: iconst_4
    //   153: invokevirtual 399	android/database/sqlite/SQLiteDatabase:insertWithOnConflict	(Ljava/lang/String;Ljava/lang/String;Landroid/content/ContentValues;I)J
    //   156: pop2
    //   157: lload 10
    //   159: lreturn
    //   160: astore 4
    //   162: aload_0
    //   163: invokevirtual 229	com/google/android/gms/measurement/internal/zzcr:zzgt	()Lcom/google/android/gms/measurement/internal/zzas;
    //   166: invokevirtual 235	com/google/android/gms/measurement/internal/zzas:zzjg	()Lcom/google/android/gms/measurement/internal/zzau;
    //   169: ldc_w 578
    //   172: aload_1
    //   173: getfield 552	com/google/android/gms/internal/measurement/zzfw:zztt	Ljava/lang/String;
    //   176: invokestatic 346	com/google/android/gms/measurement/internal/zzas:zzbw	(Ljava/lang/String;)Ljava/lang/Object;
    //   179: aload 4
    //   181: invokevirtual 243	com/google/android/gms/measurement/internal/zzau:zze	(Ljava/lang/String;Ljava/lang/Object;Ljava/lang/Object;)V
    //   184: aload 4
    //   186: athrow
    //   187: aload 9
    //   189: aload 5
    //   191: invokevirtual 584	java/security/MessageDigest:digest	([B)[B
    //   194: invokestatic 588	com/google/android/gms/measurement/internal/zzfx:zzc	([B)J
    //   197: lstore 10
    //   199: goto -101 -> 98
    //   202: astore 13
    //   204: aload_0
    //   205: invokevirtual 229	com/google/android/gms/measurement/internal/zzcr:zzgt	()Lcom/google/android/gms/measurement/internal/zzas;
    //   208: invokevirtual 235	com/google/android/gms/measurement/internal/zzas:zzjg	()Lcom/google/android/gms/measurement/internal/zzau;
    //   211: ldc_w 590
    //   214: aload_1
    //   215: getfield 552	com/google/android/gms/internal/measurement/zzfw:zztt	Ljava/lang/String;
    //   218: invokestatic 346	com/google/android/gms/measurement/internal/zzas:zzbw	(Ljava/lang/String;)Ljava/lang/Object;
    //   221: aload 13
    //   223: invokevirtual 243	com/google/android/gms/measurement/internal/zzau:zze	(Ljava/lang/String;Ljava/lang/Object;Ljava/lang/Object;)V
    //   226: aload 13
    //   228: athrow
    //
    // Exception table:
    //   from	to	target	type
    //   21	51	160	java/io/IOException
    //   142	157	202	android/database/sqlite/SQLiteException
  }

  // ERROR //
  public final android.util.Pair<com.google.android.gms.internal.measurement.zzft, Long> zza(String paramString, Long paramLong)
  {
    // Byte code:
    //   0: aload_0
    //   1: invokevirtual 325	com/google/android/gms/measurement/internal/zzcr:zzaf	()V
    //   4: aload_0
    //   5: invokevirtual 322	com/google/android/gms/measurement/internal/zzfm:zzcl	()V
    //   8: aload_0
    //   9: invokevirtual 201	com/google/android/gms/measurement/internal/zzt:getWritableDatabase	()Landroid/database/sqlite/SQLiteDatabase;
    //   12: astore 8
    //   14: iconst_2
    //   15: anewarray 19	java/lang/String
    //   18: astore 9
    //   20: aload 9
    //   22: iconst_0
    //   23: aload_1
    //   24: aastore
    //   25: aload 9
    //   27: iconst_1
    //   28: aload_2
    //   29: invokestatic 353	java/lang/String:valueOf	(Ljava/lang/Object;)Ljava/lang/String;
    //   32: aastore
    //   33: aload 8
    //   35: ldc_w 593
    //   38: aload 9
    //   40: invokevirtual 207	android/database/sqlite/SQLiteDatabase:rawQuery	(Ljava/lang/String;[Ljava/lang/String;)Landroid/database/Cursor;
    //   43: astore 10
    //   45: aload 10
    //   47: astore 4
    //   49: aload 4
    //   51: invokeinterface 213 1 0
    //   56: ifne +34 -> 90
    //   59: aload_0
    //   60: invokevirtual 229	com/google/android/gms/measurement/internal/zzcr:zzgt	()Lcom/google/android/gms/measurement/internal/zzas;
    //   63: invokevirtual 596	com/google/android/gms/measurement/internal/zzas:zzjo	()Lcom/google/android/gms/measurement/internal/zzau;
    //   66: ldc_w 598
    //   69: invokevirtual 268	com/google/android/gms/measurement/internal/zzau:zzby	(Ljava/lang/String;)V
    //   72: aconst_null
    //   73: astore 7
    //   75: aload 4
    //   77: ifnull +10 -> 87
    //   80: aload 4
    //   82: invokeinterface 220 1 0
    //   87: aload 7
    //   89: areturn
    //   90: aload 4
    //   92: iconst_0
    //   93: invokeinterface 602 2 0
    //   98: astore 11
    //   100: aload 4
    //   102: iconst_1
    //   103: invokeinterface 217 2 0
    //   108: invokestatic 273	java/lang/Long:valueOf	(J)Ljava/lang/Long;
    //   111: astore 12
    //   113: aload 11
    //   115: iconst_0
    //   116: aload 11
    //   118: arraylength
    //   119: invokestatic 608	com/google/android/gms/internal/measurement/zzxz:zzj	([BII)Lcom/google/android/gms/internal/measurement/zzxz;
    //   122: astore 13
    //   124: new 610	com/google/android/gms/internal/measurement/zzft
    //   127: dup
    //   128: invokespecial 611	com/google/android/gms/internal/measurement/zzft:<init>	()V
    //   131: astore 14
    //   133: aload 14
    //   135: aload 13
    //   137: invokevirtual 614	com/google/android/gms/internal/measurement/zzyi:zza	(Lcom/google/android/gms/internal/measurement/zzxz;)Lcom/google/android/gms/internal/measurement/zzyi;
    //   140: pop
    //   141: aload 14
    //   143: aload 12
    //   145: invokestatic 620	android/util/Pair:create	(Ljava/lang/Object;Ljava/lang/Object;)Landroid/util/Pair;
    //   148: astore 17
    //   150: aload 17
    //   152: astore 7
    //   154: aload 4
    //   156: ifnull -69 -> 87
    //   159: aload 4
    //   161: invokeinterface 220 1 0
    //   166: aload 7
    //   168: areturn
    //   169: astore 15
    //   171: aload_0
    //   172: invokevirtual 229	com/google/android/gms/measurement/internal/zzcr:zzgt	()Lcom/google/android/gms/measurement/internal/zzas;
    //   175: invokevirtual 235	com/google/android/gms/measurement/internal/zzas:zzjg	()Lcom/google/android/gms/measurement/internal/zzau;
    //   178: ldc_w 622
    //   181: aload_1
    //   182: invokestatic 346	com/google/android/gms/measurement/internal/zzas:zzbw	(Ljava/lang/String;)Ljava/lang/Object;
    //   185: aload_2
    //   186: aload 15
    //   188: invokevirtual 357	com/google/android/gms/measurement/internal/zzau:zzd	(Ljava/lang/String;Ljava/lang/Object;Ljava/lang/Object;Ljava/lang/Object;)V
    //   191: aconst_null
    //   192: astore 7
    //   194: aload 4
    //   196: ifnull -109 -> 87
    //   199: aload 4
    //   201: invokeinterface 220 1 0
    //   206: aconst_null
    //   207: areturn
    //   208: astore 6
    //   210: aconst_null
    //   211: astore 4
    //   213: aload_0
    //   214: invokevirtual 229	com/google/android/gms/measurement/internal/zzcr:zzgt	()Lcom/google/android/gms/measurement/internal/zzas;
    //   217: invokevirtual 235	com/google/android/gms/measurement/internal/zzas:zzjg	()Lcom/google/android/gms/measurement/internal/zzau;
    //   220: ldc_w 624
    //   223: aload 6
    //   225: invokevirtual 263	com/google/android/gms/measurement/internal/zzau:zzg	(Ljava/lang/String;Ljava/lang/Object;)V
    //   228: aconst_null
    //   229: astore 7
    //   231: aload 4
    //   233: ifnull -146 -> 87
    //   236: aload 4
    //   238: invokeinterface 220 1 0
    //   243: aconst_null
    //   244: areturn
    //   245: astore_3
    //   246: aconst_null
    //   247: astore 4
    //   249: aload_3
    //   250: astore 5
    //   252: aload 4
    //   254: ifnull +10 -> 264
    //   257: aload 4
    //   259: invokeinterface 220 1 0
    //   264: aload 5
    //   266: athrow
    //   267: astore 5
    //   269: goto -17 -> 252
    //   272: astore 6
    //   274: goto -61 -> 213
    //
    // Exception table:
    //   from	to	target	type
    //   133	141	169	java/io/IOException
    //   8	45	208	android/database/sqlite/SQLiteException
    //   8	45	245	finally
    //   49	72	267	finally
    //   90	133	267	finally
    //   133	141	267	finally
    //   141	150	267	finally
    //   171	191	267	finally
    //   213	228	267	finally
    //   49	72	272	android/database/sqlite/SQLiteException
    //   90	133	272	android/database/sqlite/SQLiteException
    //   133	141	272	android/database/sqlite/SQLiteException
    //   141	150	272	android/database/sqlite/SQLiteException
    //   171	191	272	android/database/sqlite/SQLiteException
  }

  // ERROR //
  public final zzu zza(long paramLong, String paramString, boolean paramBoolean1, boolean paramBoolean2, boolean paramBoolean3, boolean paramBoolean4, boolean paramBoolean5)
  {
    // Byte code:
    //   0: aload_3
    //   1: invokestatic 295	com/google/android/gms/common/internal/Preconditions:checkNotEmpty	(Ljava/lang/String;)Ljava/lang/String;
    //   4: pop
    //   5: aload_0
    //   6: invokevirtual 325	com/google/android/gms/measurement/internal/zzcr:zzaf	()V
    //   9: aload_0
    //   10: invokevirtual 322	com/google/android/gms/measurement/internal/zzfm:zzcl	()V
    //   13: iconst_1
    //   14: anewarray 19	java/lang/String
    //   17: dup
    //   18: iconst_0
    //   19: aload_3
    //   20: aastore
    //   21: astore 10
    //   23: new 627	com/google/android/gms/measurement/internal/zzu
    //   26: dup
    //   27: invokespecial 628	com/google/android/gms/measurement/internal/zzu:<init>	()V
    //   30: astore 11
    //   32: aload_0
    //   33: invokevirtual 201	com/google/android/gms/measurement/internal/zzt:getWritableDatabase	()Landroid/database/sqlite/SQLiteDatabase;
    //   36: astore 15
    //   38: aload 15
    //   40: ldc_w 630
    //   43: bipush 6
    //   45: anewarray 19	java/lang/String
    //   48: dup
    //   49: iconst_0
    //   50: ldc 73
    //   52: aastore
    //   53: dup
    //   54: iconst_1
    //   55: ldc 81
    //   57: aastore
    //   58: dup
    //   59: iconst_2
    //   60: ldc 77
    //   62: aastore
    //   63: dup
    //   64: iconst_3
    //   65: ldc 85
    //   67: aastore
    //   68: dup
    //   69: iconst_4
    //   70: ldc 109
    //   72: aastore
    //   73: dup
    //   74: iconst_5
    //   75: ldc 113
    //   77: aastore
    //   78: ldc_w 632
    //   81: iconst_1
    //   82: anewarray 19	java/lang/String
    //   85: dup
    //   86: iconst_0
    //   87: aload_3
    //   88: aastore
    //   89: aconst_null
    //   90: aconst_null
    //   91: aconst_null
    //   92: invokevirtual 636	android/database/sqlite/SQLiteDatabase:query	(Ljava/lang/String;[Ljava/lang/String;Ljava/lang/String;[Ljava/lang/String;Ljava/lang/String;Ljava/lang/String;Ljava/lang/String;)Landroid/database/Cursor;
    //   95: astore 16
    //   97: aload 16
    //   99: astore 13
    //   101: aload 13
    //   103: invokeinterface 213 1 0
    //   108: ifne +35 -> 143
    //   111: aload_0
    //   112: invokevirtual 229	com/google/android/gms/measurement/internal/zzcr:zzgt	()Lcom/google/android/gms/measurement/internal/zzas;
    //   115: invokevirtual 340	com/google/android/gms/measurement/internal/zzas:zzjj	()Lcom/google/android/gms/measurement/internal/zzau;
    //   118: ldc_w 638
    //   121: aload_3
    //   122: invokestatic 346	com/google/android/gms/measurement/internal/zzas:zzbw	(Ljava/lang/String;)Ljava/lang/Object;
    //   125: invokevirtual 263	com/google/android/gms/measurement/internal/zzau:zzg	(Ljava/lang/String;Ljava/lang/Object;)V
    //   128: aload 13
    //   130: ifnull +10 -> 140
    //   133: aload 13
    //   135: invokeinterface 220 1 0
    //   140: aload 11
    //   142: areturn
    //   143: aload 13
    //   145: iconst_0
    //   146: invokeinterface 217 2 0
    //   151: lload_1
    //   152: lcmp
    //   153: ifne +68 -> 221
    //   156: aload 11
    //   158: aload 13
    //   160: iconst_1
    //   161: invokeinterface 217 2 0
    //   166: putfield 642	com/google/android/gms/measurement/internal/zzu:zzahi	J
    //   169: aload 11
    //   171: aload 13
    //   173: iconst_2
    //   174: invokeinterface 217 2 0
    //   179: putfield 645	com/google/android/gms/measurement/internal/zzu:zzahh	J
    //   182: aload 11
    //   184: aload 13
    //   186: iconst_3
    //   187: invokeinterface 217 2 0
    //   192: putfield 648	com/google/android/gms/measurement/internal/zzu:zzahj	J
    //   195: aload 11
    //   197: aload 13
    //   199: iconst_4
    //   200: invokeinterface 217 2 0
    //   205: putfield 651	com/google/android/gms/measurement/internal/zzu:zzahk	J
    //   208: aload 11
    //   210: aload 13
    //   212: iconst_5
    //   213: invokeinterface 217 2 0
    //   218: putfield 654	com/google/android/gms/measurement/internal/zzu:zzahl	J
    //   221: iload 4
    //   223: ifeq +15 -> 238
    //   226: aload 11
    //   228: lconst_1
    //   229: aload 11
    //   231: getfield 642	com/google/android/gms/measurement/internal/zzu:zzahi	J
    //   234: ladd
    //   235: putfield 642	com/google/android/gms/measurement/internal/zzu:zzahi	J
    //   238: iload 5
    //   240: ifeq +15 -> 255
    //   243: aload 11
    //   245: lconst_1
    //   246: aload 11
    //   248: getfield 645	com/google/android/gms/measurement/internal/zzu:zzahh	J
    //   251: ladd
    //   252: putfield 645	com/google/android/gms/measurement/internal/zzu:zzahh	J
    //   255: iload 6
    //   257: ifeq +15 -> 272
    //   260: aload 11
    //   262: lconst_1
    //   263: aload 11
    //   265: getfield 648	com/google/android/gms/measurement/internal/zzu:zzahj	J
    //   268: ladd
    //   269: putfield 648	com/google/android/gms/measurement/internal/zzu:zzahj	J
    //   272: iload 7
    //   274: ifeq +15 -> 289
    //   277: aload 11
    //   279: lconst_1
    //   280: aload 11
    //   282: getfield 651	com/google/android/gms/measurement/internal/zzu:zzahk	J
    //   285: ladd
    //   286: putfield 651	com/google/android/gms/measurement/internal/zzu:zzahk	J
    //   289: iload 8
    //   291: ifeq +15 -> 306
    //   294: aload 11
    //   296: lconst_1
    //   297: aload 11
    //   299: getfield 654	com/google/android/gms/measurement/internal/zzu:zzahl	J
    //   302: ladd
    //   303: putfield 654	com/google/android/gms/measurement/internal/zzu:zzahl	J
    //   306: new 301	android/content/ContentValues
    //   309: dup
    //   310: invokespecial 377	android/content/ContentValues:<init>	()V
    //   313: astore 17
    //   315: aload 17
    //   317: ldc 73
    //   319: lload_1
    //   320: invokestatic 273	java/lang/Long:valueOf	(J)Ljava/lang/Long;
    //   323: invokevirtual 308	android/content/ContentValues:put	(Ljava/lang/String;Ljava/lang/Long;)V
    //   326: aload 17
    //   328: ldc 77
    //   330: aload 11
    //   332: getfield 645	com/google/android/gms/measurement/internal/zzu:zzahh	J
    //   335: invokestatic 273	java/lang/Long:valueOf	(J)Ljava/lang/Long;
    //   338: invokevirtual 308	android/content/ContentValues:put	(Ljava/lang/String;Ljava/lang/Long;)V
    //   341: aload 17
    //   343: ldc 81
    //   345: aload 11
    //   347: getfield 642	com/google/android/gms/measurement/internal/zzu:zzahi	J
    //   350: invokestatic 273	java/lang/Long:valueOf	(J)Ljava/lang/Long;
    //   353: invokevirtual 308	android/content/ContentValues:put	(Ljava/lang/String;Ljava/lang/Long;)V
    //   356: aload 17
    //   358: ldc 85
    //   360: aload 11
    //   362: getfield 648	com/google/android/gms/measurement/internal/zzu:zzahj	J
    //   365: invokestatic 273	java/lang/Long:valueOf	(J)Ljava/lang/Long;
    //   368: invokevirtual 308	android/content/ContentValues:put	(Ljava/lang/String;Ljava/lang/Long;)V
    //   371: aload 17
    //   373: ldc 109
    //   375: aload 11
    //   377: getfield 651	com/google/android/gms/measurement/internal/zzu:zzahk	J
    //   380: invokestatic 273	java/lang/Long:valueOf	(J)Ljava/lang/Long;
    //   383: invokevirtual 308	android/content/ContentValues:put	(Ljava/lang/String;Ljava/lang/Long;)V
    //   386: aload 17
    //   388: ldc 113
    //   390: aload 11
    //   392: getfield 654	com/google/android/gms/measurement/internal/zzu:zzahl	J
    //   395: invokestatic 273	java/lang/Long:valueOf	(J)Ljava/lang/Long;
    //   398: invokevirtual 308	android/content/ContentValues:put	(Ljava/lang/String;Ljava/lang/Long;)V
    //   401: aload 15
    //   403: ldc_w 630
    //   406: aload 17
    //   408: ldc_w 632
    //   411: aload 10
    //   413: invokevirtual 658	android/database/sqlite/SQLiteDatabase:update	(Ljava/lang/String;Landroid/content/ContentValues;Ljava/lang/String;[Ljava/lang/String;)I
    //   416: pop
    //   417: aload 13
    //   419: ifnull +10 -> 429
    //   422: aload 13
    //   424: invokeinterface 220 1 0
    //   429: aload 11
    //   431: areturn
    //   432: astore 14
    //   434: aconst_null
    //   435: astore 13
    //   437: aload_0
    //   438: invokevirtual 229	com/google/android/gms/measurement/internal/zzcr:zzgt	()Lcom/google/android/gms/measurement/internal/zzas;
    //   441: invokevirtual 235	com/google/android/gms/measurement/internal/zzas:zzjg	()Lcom/google/android/gms/measurement/internal/zzau;
    //   444: ldc_w 660
    //   447: aload_3
    //   448: invokestatic 346	com/google/android/gms/measurement/internal/zzas:zzbw	(Ljava/lang/String;)Ljava/lang/Object;
    //   451: aload 14
    //   453: invokevirtual 243	com/google/android/gms/measurement/internal/zzau:zze	(Ljava/lang/String;Ljava/lang/Object;Ljava/lang/Object;)V
    //   456: aload 13
    //   458: ifnull +10 -> 468
    //   461: aload 13
    //   463: invokeinterface 220 1 0
    //   468: aload 11
    //   470: areturn
    //   471: astore 12
    //   473: aconst_null
    //   474: astore 13
    //   476: aload 13
    //   478: ifnull +10 -> 488
    //   481: aload 13
    //   483: invokeinterface 220 1 0
    //   488: aload 12
    //   490: athrow
    //   491: astore 12
    //   493: goto -17 -> 476
    //   496: astore 14
    //   498: goto -61 -> 437
    //
    // Exception table:
    //   from	to	target	type
    //   32	97	432	android/database/sqlite/SQLiteException
    //   32	97	471	finally
    //   101	128	491	finally
    //   143	221	491	finally
    //   226	238	491	finally
    //   243	255	491	finally
    //   260	272	491	finally
    //   277	289	491	finally
    //   294	306	491	finally
    //   306	417	491	finally
    //   437	456	491	finally
    //   101	128	496	android/database/sqlite/SQLiteException
    //   143	221	496	android/database/sqlite/SQLiteException
    //   226	238	496	android/database/sqlite/SQLiteException
    //   243	255	496	android/database/sqlite/SQLiteException
    //   260	272	496	android/database/sqlite/SQLiteException
    //   277	289	496	android/database/sqlite/SQLiteException
    //   294	306	496	android/database/sqlite/SQLiteException
    //   306	417	496	android/database/sqlite/SQLiteException
  }

  public final void zza(zzac paramzzac)
  {
    Preconditions.checkNotNull(paramzzac);
    zzaf();
    zzcl();
    ContentValues localContentValues = new ContentValues();
    localContentValues.put("app_id", paramzzac.zztt);
    localContentValues.put("name", paramzzac.name);
    localContentValues.put("lifetime_count", Long.valueOf(paramzzac.zzahv));
    localContentValues.put("current_bundle_count", Long.valueOf(paramzzac.zzahw));
    localContentValues.put("last_fire_timestamp", Long.valueOf(paramzzac.zzahx));
    localContentValues.put("last_bundled_timestamp", Long.valueOf(paramzzac.zzahy));
    localContentValues.put("last_bundled_day", paramzzac.zzahz);
    localContentValues.put("last_sampled_complex_event_id", paramzzac.zzaia);
    localContentValues.put("last_sampling_rate", paramzzac.zzaib);
    Boolean localBoolean = paramzzac.zzaic;
    Long localLong = null;
    if (localBoolean != null)
    {
      boolean bool = paramzzac.zzaic.booleanValue();
      localLong = null;
      if (bool)
        localLong = Long.valueOf(1L);
    }
    localContentValues.put("last_exempt_from_sampling", localLong);
    try
    {
      if (getWritableDatabase().insertWithOnConflict("events", null, localContentValues, 5) == -1L)
        zzgt().zzjg().zzg("Failed to insert/update event aggregates (got -1). appId", zzas.zzbw(paramzzac.zztt));
      return;
    }
    catch (SQLiteException localSQLiteException)
    {
      zzgt().zzjg().zze("Error storing event aggregates. appId", zzas.zzbw(paramzzac.zztt), localSQLiteException);
    }
  }

  public final void zza(zzg paramzzg)
  {
    Preconditions.checkNotNull(paramzzg);
    zzaf();
    zzcl();
    ContentValues localContentValues = new ContentValues();
    localContentValues.put("app_id", paramzzg.zzal());
    localContentValues.put("app_instance_id", paramzzg.getAppInstanceId());
    localContentValues.put("gmp_app_id", paramzzg.getGmpAppId());
    localContentValues.put("resettable_device_id_hash", paramzzg.zzhc());
    localContentValues.put("last_bundle_index", Long.valueOf(paramzzg.zzhj()));
    localContentValues.put("last_bundle_start_timestamp", Long.valueOf(paramzzg.zzhd()));
    localContentValues.put("last_bundle_end_timestamp", Long.valueOf(paramzzg.zzhe()));
    localContentValues.put("app_version", paramzzg.zzak());
    localContentValues.put("app_store", paramzzg.zzhg());
    localContentValues.put("gmp_version", Long.valueOf(paramzzg.zzhh()));
    localContentValues.put("dev_cert_hash", Long.valueOf(paramzzg.zzhi()));
    localContentValues.put("measurement_enabled", Boolean.valueOf(paramzzg.isMeasurementEnabled()));
    localContentValues.put("day", Long.valueOf(paramzzg.zzhn()));
    localContentValues.put("daily_public_events_count", Long.valueOf(paramzzg.zzho()));
    localContentValues.put("daily_events_count", Long.valueOf(paramzzg.zzhp()));
    localContentValues.put("daily_conversions_count", Long.valueOf(paramzzg.zzhq()));
    localContentValues.put("config_fetched_time", Long.valueOf(paramzzg.zzhk()));
    localContentValues.put("failed_config_fetch_time", Long.valueOf(paramzzg.zzhl()));
    localContentValues.put("app_version_int", Long.valueOf(paramzzg.zzhf()));
    localContentValues.put("firebase_instance_id", paramzzg.getFirebaseInstanceId());
    localContentValues.put("daily_error_events_count", Long.valueOf(paramzzg.zzhs()));
    localContentValues.put("daily_realtime_events_count", Long.valueOf(paramzzg.zzhr()));
    localContentValues.put("health_monitor_sample", paramzzg.zzht());
    localContentValues.put("android_id", Long.valueOf(paramzzg.zzhv()));
    localContentValues.put("adid_reporting_enabled", Boolean.valueOf(paramzzg.zzhw()));
    localContentValues.put("ssaid_reporting_enabled", Boolean.valueOf(paramzzg.zzhx()));
    localContentValues.put("admob_app_id", paramzzg.zzhb());
    try
    {
      SQLiteDatabase localSQLiteDatabase = getWritableDatabase();
      String[] arrayOfString = new String[1];
      arrayOfString[0] = paramzzg.zzal();
      if ((localSQLiteDatabase.update("apps", localContentValues, "app_id = ?", arrayOfString) == 0L) && (localSQLiteDatabase.insertWithOnConflict("apps", null, localContentValues, 5) == -1L))
        zzgt().zzjg().zzg("Failed to insert/update app (got -1). appId", zzas.zzbw(paramzzg.zzal()));
      return;
    }
    catch (SQLiteException localSQLiteException)
    {
      zzgt().zzjg().zze("Error storing app. appId", zzas.zzbw(paramzzg.zzal()), localSQLiteException);
    }
  }

  final void zza(String paramString, com.google.android.gms.internal.measurement.zzfi[] paramArrayOfzzfi)
  {
    int i = 0;
    zzcl();
    zzaf();
    Preconditions.checkNotEmpty(paramString);
    Preconditions.checkNotNull(paramArrayOfzzfi);
    SQLiteDatabase localSQLiteDatabase1 = getWritableDatabase();
    localSQLiteDatabase1.beginTransaction();
    int k;
    com.google.android.gms.internal.measurement.zzfi localzzfi;
    int m;
    while (true)
    {
      int i1;
      try
      {
        zzcl();
        zzaf();
        Preconditions.checkNotEmpty(paramString);
        SQLiteDatabase localSQLiteDatabase2 = getWritableDatabase();
        localSQLiteDatabase2.delete("property_filters", "app_id=?", new String[] { paramString });
        localSQLiteDatabase2.delete("event_filters", "app_id=?", new String[] { paramString });
        int j = paramArrayOfzzfi.length;
        k = 0;
        if (k >= j)
          break label497;
        localzzfi = paramArrayOfzzfi[k];
        zzcl();
        zzaf();
        Preconditions.checkNotEmpty(paramString);
        Preconditions.checkNotNull(localzzfi);
        Preconditions.checkNotNull(localzzfi.zzavi);
        Preconditions.checkNotNull(localzzfi.zzavh);
        if (localzzfi.zzavg == null)
        {
          zzgt().zzjj().zzg("Audience with no ID. appId", zzas.zzbw(paramString));
        }
        else
        {
          m = localzzfi.zzavg.intValue();
          zzfj[] arrayOfzzfj1 = localzzfi.zzavi;
          int n = arrayOfzzfj1.length;
          i1 = 0;
          if (i1 < n)
            if (arrayOfzzfj1[i1].zzavm == null)
              zzgt().zzjj().zze("Event filter with no ID. Audience definition ignored. appId, audienceId", zzas.zzbw(paramString), localzzfi.zzavg);
        }
      }
      finally
      {
        localSQLiteDatabase1.endTransaction();
      }
      i1++;
    }
    com.google.android.gms.internal.measurement.zzfm[] arrayOfzzfm1 = localzzfi.zzavh;
    int i2 = arrayOfzzfm1.length;
    int i3 = 0;
    label274: int i5;
    label332: int i6;
    label357: com.google.android.gms.internal.measurement.zzfm[] arrayOfzzfm2;
    int i7;
    if (i3 < i2)
    {
      if (arrayOfzzfm1[i3].zzavm != null)
        break label567;
      zzgt().zzjj().zze("Property filter with no ID. Audience definition ignored. appId, audienceId", zzas.zzbw(paramString), localzzfi.zzavg);
    }
    else
    {
      zzfj[] arrayOfzzfj2 = localzzfi.zzavi;
      int i4 = arrayOfzzfj2.length;
      i5 = 0;
      if (i5 < i4)
      {
        if (zza(paramString, m, arrayOfzzfj2[i5]))
          break label573;
        i6 = 0;
        if (i6 != 0)
        {
          arrayOfzzfm2 = localzzfi.zzavh;
          i7 = arrayOfzzfm2.length;
        }
      }
    }
    for (int i8 = 0; ; i8++)
      if (i8 < i7)
      {
        if (!zza(paramString, m, arrayOfzzfm2[i8]))
          i6 = 0;
      }
      else
      {
        if (i6 == 0)
        {
          zzcl();
          zzaf();
          Preconditions.checkNotEmpty(paramString);
          SQLiteDatabase localSQLiteDatabase3 = getWritableDatabase();
          String[] arrayOfString1 = new String[2];
          arrayOfString1[0] = paramString;
          arrayOfString1[1] = String.valueOf(m);
          localSQLiteDatabase3.delete("property_filters", "app_id=? and audience_id=?", arrayOfString1);
          String[] arrayOfString2 = new String[2];
          arrayOfString2[0] = paramString;
          arrayOfString2[1] = String.valueOf(m);
          localSQLiteDatabase3.delete("event_filters", "app_id=? and audience_id=?", arrayOfString2);
          break label561;
          label497: ArrayList localArrayList = new ArrayList();
          int i9 = paramArrayOfzzfi.length;
          while (i < i9)
          {
            localArrayList.add(paramArrayOfzzfi[i].zzavg);
            i++;
          }
          zza(paramString, localArrayList);
          localSQLiteDatabase1.setTransactionSuccessful();
          localSQLiteDatabase1.endTransaction();
          return;
          i6 = 1;
          break label357;
        }
        label561: k++;
        break;
        label567: i3++;
        break label274;
        label573: i5++;
        break label332;
      }
  }

  // ERROR //
  public final boolean zza(com.google.android.gms.internal.measurement.zzfw paramzzfw, boolean paramBoolean)
  {
    // Byte code:
    //   0: aload_0
    //   1: invokevirtual 325	com/google/android/gms/measurement/internal/zzcr:zzaf	()V
    //   4: aload_0
    //   5: invokevirtual 322	com/google/android/gms/measurement/internal/zzfm:zzcl	()V
    //   8: aload_1
    //   9: invokestatic 299	com/google/android/gms/common/internal/Preconditions:checkNotNull	(Ljava/lang/Object;)Ljava/lang/Object;
    //   12: pop
    //   13: aload_1
    //   14: getfield 552	com/google/android/gms/internal/measurement/zzfw:zztt	Ljava/lang/String;
    //   17: invokestatic 295	com/google/android/gms/common/internal/Preconditions:checkNotEmpty	(Ljava/lang/String;)Ljava/lang/String;
    //   20: pop
    //   21: aload_1
    //   22: getfield 852	com/google/android/gms/internal/measurement/zzfw:zzaxo	Ljava/lang/Long;
    //   25: invokestatic 299	com/google/android/gms/common/internal/Preconditions:checkNotNull	(Ljava/lang/Object;)Ljava/lang/Object;
    //   28: pop
    //   29: aload_0
    //   30: invokevirtual 855	com/google/android/gms/measurement/internal/zzt:zzij	()V
    //   33: aload_0
    //   34: invokevirtual 175	com/google/android/gms/measurement/internal/zzcr:zzbx	()Lcom/google/android/gms/common/util/Clock;
    //   37: invokeinterface 860 1 0
    //   42: lstore 6
    //   44: aload_1
    //   45: getfield 852	com/google/android/gms/internal/measurement/zzfw:zzaxo	Ljava/lang/Long;
    //   48: invokevirtual 863	java/lang/Long:longValue	()J
    //   51: lload 6
    //   53: invokestatic 866	com/google/android/gms/measurement/internal/zzq:zzib	()J
    //   56: lsub
    //   57: lcmp
    //   58: iflt +20 -> 78
    //   61: aload_1
    //   62: getfield 852	com/google/android/gms/internal/measurement/zzfw:zzaxo	Ljava/lang/Long;
    //   65: invokevirtual 863	java/lang/Long:longValue	()J
    //   68: lload 6
    //   70: invokestatic 866	com/google/android/gms/measurement/internal/zzq:zzib	()J
    //   73: ladd
    //   74: lcmp
    //   75: ifle +32 -> 107
    //   78: aload_0
    //   79: invokevirtual 229	com/google/android/gms/measurement/internal/zzcr:zzgt	()Lcom/google/android/gms/measurement/internal/zzas;
    //   82: invokevirtual 340	com/google/android/gms/measurement/internal/zzas:zzjj	()Lcom/google/android/gms/measurement/internal/zzau;
    //   85: ldc_w 868
    //   88: aload_1
    //   89: getfield 552	com/google/android/gms/internal/measurement/zzfw:zztt	Ljava/lang/String;
    //   92: invokestatic 346	com/google/android/gms/measurement/internal/zzas:zzbw	(Ljava/lang/String;)Ljava/lang/Object;
    //   95: lload 6
    //   97: invokestatic 273	java/lang/Long:valueOf	(J)Ljava/lang/Long;
    //   100: aload_1
    //   101: getfield 852	com/google/android/gms/internal/measurement/zzfw:zzaxo	Ljava/lang/Long;
    //   104: invokevirtual 357	com/google/android/gms/measurement/internal/zzau:zzd	(Ljava/lang/String;Ljava/lang/Object;Ljava/lang/Object;Ljava/lang/Object;)V
    //   107: aload_1
    //   108: invokevirtual 363	com/google/android/gms/internal/measurement/zzyi:zzvx	()I
    //   111: newarray byte
    //   113: astore 9
    //   115: aload 9
    //   117: iconst_0
    //   118: aload 9
    //   120: arraylength
    //   121: invokestatic 369	com/google/android/gms/internal/measurement/zzya:zzk	([BII)Lcom/google/android/gms/internal/measurement/zzya;
    //   124: astore 10
    //   126: aload_1
    //   127: aload 10
    //   129: invokevirtual 372	com/google/android/gms/internal/measurement/zzyi:zza	(Lcom/google/android/gms/internal/measurement/zzya;)V
    //   132: aload 10
    //   134: invokevirtual 375	com/google/android/gms/internal/measurement/zzya:zzza	()V
    //   137: aload_0
    //   138: invokevirtual 558	com/google/android/gms/measurement/internal/zzfl:zzjr	()Lcom/google/android/gms/measurement/internal/zzft;
    //   141: aload 9
    //   143: invokevirtual 872	com/google/android/gms/measurement/internal/zzft:zzb	([B)[B
    //   146: astore 11
    //   148: aload_0
    //   149: invokevirtual 229	com/google/android/gms/measurement/internal/zzcr:zzgt	()Lcom/google/android/gms/measurement/internal/zzas;
    //   152: invokevirtual 596	com/google/android/gms/measurement/internal/zzas:zzjo	()Lcom/google/android/gms/measurement/internal/zzau;
    //   155: ldc_w 874
    //   158: aload 11
    //   160: arraylength
    //   161: invokestatic 259	java/lang/Integer:valueOf	(I)Ljava/lang/Integer;
    //   164: invokevirtual 263	com/google/android/gms/measurement/internal/zzau:zzg	(Ljava/lang/String;Ljava/lang/Object;)V
    //   167: new 301	android/content/ContentValues
    //   170: dup
    //   171: invokespecial 377	android/content/ContentValues:<init>	()V
    //   174: astore 12
    //   176: aload 12
    //   178: ldc_w 379
    //   181: aload_1
    //   182: getfield 552	com/google/android/gms/internal/measurement/zzfw:zztt	Ljava/lang/String;
    //   185: invokevirtual 305	android/content/ContentValues:put	(Ljava/lang/String;Ljava/lang/String;)V
    //   188: aload 12
    //   190: ldc_w 876
    //   193: aload_1
    //   194: getfield 852	com/google/android/gms/internal/measurement/zzfw:zzaxo	Ljava/lang/Long;
    //   197: invokevirtual 308	android/content/ContentValues:put	(Ljava/lang/String;Ljava/lang/Long;)V
    //   200: aload 12
    //   202: ldc_w 390
    //   205: aload 11
    //   207: invokevirtual 393	android/content/ContentValues:put	(Ljava/lang/String;[B)V
    //   210: iload_2
    //   211: ifeq +104 -> 315
    //   214: iconst_1
    //   215: istore 13
    //   217: aload 12
    //   219: ldc 149
    //   221: iload 13
    //   223: invokestatic 259	java/lang/Integer:valueOf	(I)Ljava/lang/Integer;
    //   226: invokevirtual 384	android/content/ContentValues:put	(Ljava/lang/String;Ljava/lang/Integer;)V
    //   229: aload_1
    //   230: getfield 879	com/google/android/gms/internal/measurement/zzfw:zzayl	Ljava/lang/Integer;
    //   233: ifnull +14 -> 247
    //   236: aload 12
    //   238: ldc 153
    //   240: aload_1
    //   241: getfield 879	com/google/android/gms/internal/measurement/zzfw:zzayl	Ljava/lang/Integer;
    //   244: invokevirtual 384	android/content/ContentValues:put	(Ljava/lang/String;Ljava/lang/Integer;)V
    //   247: aload_0
    //   248: invokevirtual 201	com/google/android/gms/measurement/internal/zzt:getWritableDatabase	()Landroid/database/sqlite/SQLiteDatabase;
    //   251: ldc_w 881
    //   254: aconst_null
    //   255: aload 12
    //   257: invokevirtual 885	android/database/sqlite/SQLiteDatabase:insert	(Ljava/lang/String;Ljava/lang/String;Landroid/content/ContentValues;)J
    //   260: ldc2_w 400
    //   263: lcmp
    //   264: ifne +83 -> 347
    //   267: aload_0
    //   268: invokevirtual 229	com/google/android/gms/measurement/internal/zzcr:zzgt	()Lcom/google/android/gms/measurement/internal/zzas;
    //   271: invokevirtual 235	com/google/android/gms/measurement/internal/zzas:zzjg	()Lcom/google/android/gms/measurement/internal/zzau;
    //   274: ldc_w 887
    //   277: aload_1
    //   278: getfield 552	com/google/android/gms/internal/measurement/zzfw:zztt	Ljava/lang/String;
    //   281: invokestatic 346	com/google/android/gms/measurement/internal/zzas:zzbw	(Ljava/lang/String;)Ljava/lang/Object;
    //   284: invokevirtual 263	com/google/android/gms/measurement/internal/zzau:zzg	(Ljava/lang/String;Ljava/lang/Object;)V
    //   287: iconst_0
    //   288: ireturn
    //   289: astore 8
    //   291: aload_0
    //   292: invokevirtual 229	com/google/android/gms/measurement/internal/zzcr:zzgt	()Lcom/google/android/gms/measurement/internal/zzas;
    //   295: invokevirtual 235	com/google/android/gms/measurement/internal/zzas:zzjg	()Lcom/google/android/gms/measurement/internal/zzau;
    //   298: ldc_w 889
    //   301: aload_1
    //   302: getfield 552	com/google/android/gms/internal/measurement/zzfw:zztt	Ljava/lang/String;
    //   305: invokestatic 346	com/google/android/gms/measurement/internal/zzas:zzbw	(Ljava/lang/String;)Ljava/lang/Object;
    //   308: aload 8
    //   310: invokevirtual 243	com/google/android/gms/measurement/internal/zzau:zze	(Ljava/lang/String;Ljava/lang/Object;Ljava/lang/Object;)V
    //   313: iconst_0
    //   314: ireturn
    //   315: iconst_0
    //   316: istore 13
    //   318: goto -101 -> 217
    //   321: astore 14
    //   323: aload_0
    //   324: invokevirtual 229	com/google/android/gms/measurement/internal/zzcr:zzgt	()Lcom/google/android/gms/measurement/internal/zzas;
    //   327: invokevirtual 235	com/google/android/gms/measurement/internal/zzas:zzjg	()Lcom/google/android/gms/measurement/internal/zzau;
    //   330: ldc_w 891
    //   333: aload_1
    //   334: getfield 552	com/google/android/gms/internal/measurement/zzfw:zztt	Ljava/lang/String;
    //   337: invokestatic 346	com/google/android/gms/measurement/internal/zzas:zzbw	(Ljava/lang/String;)Ljava/lang/Object;
    //   340: aload 14
    //   342: invokevirtual 243	com/google/android/gms/measurement/internal/zzau:zze	(Ljava/lang/String;Ljava/lang/Object;Ljava/lang/Object;)V
    //   345: iconst_0
    //   346: ireturn
    //   347: iconst_1
    //   348: ireturn
    //
    // Exception table:
    //   from	to	target	type
    //   107	148	289	java/io/IOException
    //   247	287	321	android/database/sqlite/SQLiteException
  }

  // ERROR //
  public final boolean zza(zzab paramzzab, long paramLong, boolean paramBoolean)
  {
    // Byte code:
    //   0: aload_0
    //   1: invokevirtual 325	com/google/android/gms/measurement/internal/zzcr:zzaf	()V
    //   4: aload_0
    //   5: invokevirtual 322	com/google/android/gms/measurement/internal/zzfm:zzcl	()V
    //   8: aload_1
    //   9: invokestatic 299	com/google/android/gms/common/internal/Preconditions:checkNotNull	(Ljava/lang/Object;)Ljava/lang/Object;
    //   12: pop
    //   13: aload_1
    //   14: getfield 895	com/google/android/gms/measurement/internal/zzab:zztt	Ljava/lang/String;
    //   17: invokestatic 295	com/google/android/gms/common/internal/Preconditions:checkNotEmpty	(Ljava/lang/String;)Ljava/lang/String;
    //   20: pop
    //   21: new 610	com/google/android/gms/internal/measurement/zzft
    //   24: dup
    //   25: invokespecial 611	com/google/android/gms/internal/measurement/zzft:<init>	()V
    //   28: astore 7
    //   30: aload 7
    //   32: aload_1
    //   33: getfield 898	com/google/android/gms/measurement/internal/zzab:zzaht	J
    //   36: invokestatic 273	java/lang/Long:valueOf	(J)Ljava/lang/Long;
    //   39: putfield 901	com/google/android/gms/internal/measurement/zzft:zzaxe	Ljava/lang/Long;
    //   42: aload 7
    //   44: aload_1
    //   45: getfield 905	com/google/android/gms/measurement/internal/zzab:zzahu	Lcom/google/android/gms/measurement/internal/zzad;
    //   48: invokevirtual 908	com/google/android/gms/measurement/internal/zzad:size	()I
    //   51: anewarray 910	com/google/android/gms/internal/measurement/zzfu
    //   54: putfield 914	com/google/android/gms/internal/measurement/zzft:zzaxc	[Lcom/google/android/gms/internal/measurement/zzfu;
    //   57: aload_1
    //   58: getfield 905	com/google/android/gms/measurement/internal/zzab:zzahu	Lcom/google/android/gms/measurement/internal/zzad;
    //   61: invokevirtual 918	com/google/android/gms/measurement/internal/zzad:iterator	()Ljava/util/Iterator;
    //   64: astore 8
    //   66: iconst_0
    //   67: istore 9
    //   69: aload 8
    //   71: invokeinterface 923 1 0
    //   76: ifeq +80 -> 156
    //   79: aload 8
    //   81: invokeinterface 927 1 0
    //   86: checkcast 19	java/lang/String
    //   89: astore 16
    //   91: new 910	com/google/android/gms/internal/measurement/zzfu
    //   94: dup
    //   95: invokespecial 928	com/google/android/gms/internal/measurement/zzfu:<init>	()V
    //   98: astore 17
    //   100: aload 7
    //   102: getfield 914	com/google/android/gms/internal/measurement/zzft:zzaxc	[Lcom/google/android/gms/internal/measurement/zzfu;
    //   105: astore 18
    //   107: iload 9
    //   109: iconst_1
    //   110: iadd
    //   111: istore 19
    //   113: aload 18
    //   115: iload 9
    //   117: aload 17
    //   119: aastore
    //   120: aload 17
    //   122: aload 16
    //   124: putfield 929	com/google/android/gms/internal/measurement/zzfu:name	Ljava/lang/String;
    //   127: aload_1
    //   128: getfield 905	com/google/android/gms/measurement/internal/zzab:zzahu	Lcom/google/android/gms/measurement/internal/zzad;
    //   131: aload 16
    //   133: invokevirtual 931	com/google/android/gms/measurement/internal/zzad:get	(Ljava/lang/String;)Ljava/lang/Object;
    //   136: astore 20
    //   138: aload_0
    //   139: invokevirtual 558	com/google/android/gms/measurement/internal/zzfl:zzjr	()Lcom/google/android/gms/measurement/internal/zzft;
    //   142: aload 17
    //   144: aload 20
    //   146: invokevirtual 934	com/google/android/gms/measurement/internal/zzft:zza	(Lcom/google/android/gms/internal/measurement/zzfu;Ljava/lang/Object;)V
    //   149: iload 19
    //   151: istore 9
    //   153: goto -84 -> 69
    //   156: aload 7
    //   158: invokevirtual 363	com/google/android/gms/internal/measurement/zzyi:zzvx	()I
    //   161: newarray byte
    //   163: astore 11
    //   165: aload 11
    //   167: iconst_0
    //   168: aload 11
    //   170: arraylength
    //   171: invokestatic 369	com/google/android/gms/internal/measurement/zzya:zzk	([BII)Lcom/google/android/gms/internal/measurement/zzya;
    //   174: astore 12
    //   176: aload 7
    //   178: aload 12
    //   180: invokevirtual 372	com/google/android/gms/internal/measurement/zzyi:zza	(Lcom/google/android/gms/internal/measurement/zzya;)V
    //   183: aload 12
    //   185: invokevirtual 375	com/google/android/gms/internal/measurement/zzya:zzza	()V
    //   188: aload_0
    //   189: invokevirtual 229	com/google/android/gms/measurement/internal/zzcr:zzgt	()Lcom/google/android/gms/measurement/internal/zzas;
    //   192: invokevirtual 596	com/google/android/gms/measurement/internal/zzas:zzjo	()Lcom/google/android/gms/measurement/internal/zzau;
    //   195: ldc_w 936
    //   198: aload_0
    //   199: invokevirtual 940	com/google/android/gms/measurement/internal/zzcr:zzgq	()Lcom/google/android/gms/measurement/internal/zzaq;
    //   202: aload_1
    //   203: getfield 941	com/google/android/gms/measurement/internal/zzab:name	Ljava/lang/String;
    //   206: invokevirtual 946	com/google/android/gms/measurement/internal/zzaq:zzbt	(Ljava/lang/String;)Ljava/lang/String;
    //   209: aload 11
    //   211: arraylength
    //   212: invokestatic 259	java/lang/Integer:valueOf	(I)Ljava/lang/Integer;
    //   215: invokevirtual 243	com/google/android/gms/measurement/internal/zzau:zze	(Ljava/lang/String;Ljava/lang/Object;Ljava/lang/Object;)V
    //   218: new 301	android/content/ContentValues
    //   221: dup
    //   222: invokespecial 377	android/content/ContentValues:<init>	()V
    //   225: astore 13
    //   227: aload 13
    //   229: ldc_w 379
    //   232: aload_1
    //   233: getfield 895	com/google/android/gms/measurement/internal/zzab:zztt	Ljava/lang/String;
    //   236: invokevirtual 305	android/content/ContentValues:put	(Ljava/lang/String;Ljava/lang/String;)V
    //   239: aload 13
    //   241: ldc_w 666
    //   244: aload_1
    //   245: getfield 941	com/google/android/gms/measurement/internal/zzab:name	Ljava/lang/String;
    //   248: invokevirtual 305	android/content/ContentValues:put	(Ljava/lang/String;Ljava/lang/String;)V
    //   251: aload 13
    //   253: ldc_w 948
    //   256: aload_1
    //   257: getfield 950	com/google/android/gms/measurement/internal/zzab:timestamp	J
    //   260: invokestatic 273	java/lang/Long:valueOf	(J)Ljava/lang/Long;
    //   263: invokevirtual 308	android/content/ContentValues:put	(Ljava/lang/String;Ljava/lang/Long;)V
    //   266: aload 13
    //   268: ldc_w 572
    //   271: lload_2
    //   272: invokestatic 273	java/lang/Long:valueOf	(J)Ljava/lang/Long;
    //   275: invokevirtual 308	android/content/ContentValues:put	(Ljava/lang/String;Ljava/lang/Long;)V
    //   278: aload 13
    //   280: ldc_w 390
    //   283: aload 11
    //   285: invokevirtual 393	android/content/ContentValues:put	(Ljava/lang/String;[B)V
    //   288: iload 4
    //   290: ifeq +86 -> 376
    //   293: iconst_1
    //   294: istore 14
    //   296: aload 13
    //   298: ldc 143
    //   300: iload 14
    //   302: invokestatic 259	java/lang/Integer:valueOf	(I)Ljava/lang/Integer;
    //   305: invokevirtual 384	android/content/ContentValues:put	(Ljava/lang/String;Ljava/lang/Integer;)V
    //   308: aload_0
    //   309: invokevirtual 201	com/google/android/gms/measurement/internal/zzt:getWritableDatabase	()Landroid/database/sqlite/SQLiteDatabase;
    //   312: ldc_w 952
    //   315: aconst_null
    //   316: aload 13
    //   318: invokevirtual 885	android/database/sqlite/SQLiteDatabase:insert	(Ljava/lang/String;Ljava/lang/String;Landroid/content/ContentValues;)J
    //   321: ldc2_w 400
    //   324: lcmp
    //   325: ifne +83 -> 408
    //   328: aload_0
    //   329: invokevirtual 229	com/google/android/gms/measurement/internal/zzcr:zzgt	()Lcom/google/android/gms/measurement/internal/zzas;
    //   332: invokevirtual 235	com/google/android/gms/measurement/internal/zzas:zzjg	()Lcom/google/android/gms/measurement/internal/zzau;
    //   335: ldc_w 954
    //   338: aload_1
    //   339: getfield 895	com/google/android/gms/measurement/internal/zzab:zztt	Ljava/lang/String;
    //   342: invokestatic 346	com/google/android/gms/measurement/internal/zzas:zzbw	(Ljava/lang/String;)Ljava/lang/Object;
    //   345: invokevirtual 263	com/google/android/gms/measurement/internal/zzau:zzg	(Ljava/lang/String;Ljava/lang/Object;)V
    //   348: iconst_0
    //   349: ireturn
    //   350: astore 10
    //   352: aload_0
    //   353: invokevirtual 229	com/google/android/gms/measurement/internal/zzcr:zzgt	()Lcom/google/android/gms/measurement/internal/zzas;
    //   356: invokevirtual 235	com/google/android/gms/measurement/internal/zzas:zzjg	()Lcom/google/android/gms/measurement/internal/zzau;
    //   359: ldc_w 956
    //   362: aload_1
    //   363: getfield 895	com/google/android/gms/measurement/internal/zzab:zztt	Ljava/lang/String;
    //   366: invokestatic 346	com/google/android/gms/measurement/internal/zzas:zzbw	(Ljava/lang/String;)Ljava/lang/Object;
    //   369: aload 10
    //   371: invokevirtual 243	com/google/android/gms/measurement/internal/zzau:zze	(Ljava/lang/String;Ljava/lang/Object;Ljava/lang/Object;)V
    //   374: iconst_0
    //   375: ireturn
    //   376: iconst_0
    //   377: istore 14
    //   379: goto -83 -> 296
    //   382: astore 15
    //   384: aload_0
    //   385: invokevirtual 229	com/google/android/gms/measurement/internal/zzcr:zzgt	()Lcom/google/android/gms/measurement/internal/zzas;
    //   388: invokevirtual 235	com/google/android/gms/measurement/internal/zzas:zzjg	()Lcom/google/android/gms/measurement/internal/zzau;
    //   391: ldc_w 958
    //   394: aload_1
    //   395: getfield 895	com/google/android/gms/measurement/internal/zzab:zztt	Ljava/lang/String;
    //   398: invokestatic 346	com/google/android/gms/measurement/internal/zzas:zzbw	(Ljava/lang/String;)Ljava/lang/Object;
    //   401: aload 15
    //   403: invokevirtual 243	com/google/android/gms/measurement/internal/zzau:zze	(Ljava/lang/String;Ljava/lang/Object;Ljava/lang/Object;)V
    //   406: iconst_0
    //   407: ireturn
    //   408: iconst_1
    //   409: ireturn
    //
    // Exception table:
    //   from	to	target	type
    //   156	188	350	java/io/IOException
    //   308	348	382	android/database/sqlite/SQLiteException
  }

  public final boolean zza(zzfw paramzzfw)
  {
    Preconditions.checkNotNull(paramzzfw);
    zzaf();
    zzcl();
    if (zzi(paramzzfw.zztt, paramzzfw.name) == null)
      if (zzfx.zzct(paramzzfw.name))
      {
        String[] arrayOfString2 = new String[1];
        arrayOfString2[0] = paramzzfw.zztt;
        if (zza("select count(1) from user_attributes where app_id=? and name not like '!_%' escape '!'", arrayOfString2) < 25L);
      }
      else
      {
        String[] arrayOfString1;
        do
        {
          return false;
          arrayOfString1 = new String[2];
          arrayOfString1[0] = paramzzfw.zztt;
          arrayOfString1[1] = paramzzfw.origin;
        }
        while (zza("select count(1) from user_attributes where app_id=? and origin=? AND name like '!_%' escape '!'", arrayOfString1) >= 25L);
      }
    ContentValues localContentValues = new ContentValues();
    localContentValues.put("app_id", paramzzfw.zztt);
    localContentValues.put("origin", paramzzfw.origin);
    localContentValues.put("name", paramzzfw.name);
    localContentValues.put("set_timestamp", Long.valueOf(paramzzfw.zzaum));
    zza(localContentValues, "value", paramzzfw.value);
    try
    {
      if (getWritableDatabase().insertWithOnConflict("user_attributes", null, localContentValues, 5) == -1L)
        zzgt().zzjg().zzg("Failed to insert/update user property (got -1). appId", zzas.zzbw(paramzzfw.zztt));
      return true;
    }
    catch (SQLiteException localSQLiteException)
    {
      while (true)
        zzgt().zzjg().zze("Error storing user property. appId", zzas.zzbw(paramzzfw.zztt), localSQLiteException);
    }
  }

  public final boolean zza(zzo paramzzo)
  {
    Preconditions.checkNotNull(paramzzo);
    zzaf();
    zzcl();
    if (zzi(paramzzo.packageName, paramzzo.zzags.name) == null)
    {
      String[] arrayOfString = new String[1];
      arrayOfString[0] = paramzzo.packageName;
      if (zza("SELECT COUNT(1) FROM conditional_properties WHERE app_id=?", arrayOfString) >= 1000L)
        return false;
    }
    ContentValues localContentValues = new ContentValues();
    localContentValues.put("app_id", paramzzo.packageName);
    localContentValues.put("origin", paramzzo.origin);
    localContentValues.put("name", paramzzo.zzags.name);
    zza(localContentValues, "value", paramzzo.zzags.getValue());
    localContentValues.put("active", Boolean.valueOf(paramzzo.active));
    localContentValues.put("trigger_event_name", paramzzo.triggerEventName);
    localContentValues.put("trigger_timeout", Long.valueOf(paramzzo.triggerTimeout));
    zzgr();
    localContentValues.put("timed_out_event", zzfx.zza(paramzzo.zzagt));
    localContentValues.put("creation_timestamp", Long.valueOf(paramzzo.creationTimestamp));
    zzgr();
    localContentValues.put("triggered_event", zzfx.zza(paramzzo.zzagu));
    localContentValues.put("triggered_timestamp", Long.valueOf(paramzzo.zzags.zzaum));
    localContentValues.put("time_to_live", Long.valueOf(paramzzo.timeToLive));
    zzgr();
    localContentValues.put("expired_event", zzfx.zza(paramzzo.zzagv));
    try
    {
      if (getWritableDatabase().insertWithOnConflict("conditional_properties", null, localContentValues, 5) == -1L)
        zzgt().zzjg().zzg("Failed to insert/update conditional user property (got -1)", zzas.zzbw(paramzzo.packageName));
      return true;
    }
    catch (SQLiteException localSQLiteException)
    {
      while (true)
        zzgt().zzjg().zze("Error storing conditional user property", zzas.zzbw(paramzzo.packageName), localSQLiteException);
    }
  }

  // ERROR //
  public final boolean zza(String paramString, Long paramLong, long paramLong1, com.google.android.gms.internal.measurement.zzft paramzzft)
  {
    // Byte code:
    //   0: aload_0
    //   1: invokevirtual 325	com/google/android/gms/measurement/internal/zzcr:zzaf	()V
    //   4: aload_0
    //   5: invokevirtual 322	com/google/android/gms/measurement/internal/zzfm:zzcl	()V
    //   8: aload 5
    //   10: invokestatic 299	com/google/android/gms/common/internal/Preconditions:checkNotNull	(Ljava/lang/Object;)Ljava/lang/Object;
    //   13: pop
    //   14: aload_1
    //   15: invokestatic 295	com/google/android/gms/common/internal/Preconditions:checkNotEmpty	(Ljava/lang/String;)Ljava/lang/String;
    //   18: pop
    //   19: aload_2
    //   20: invokestatic 299	com/google/android/gms/common/internal/Preconditions:checkNotNull	(Ljava/lang/Object;)Ljava/lang/Object;
    //   23: pop
    //   24: aload 5
    //   26: invokevirtual 363	com/google/android/gms/internal/measurement/zzyi:zzvx	()I
    //   29: newarray byte
    //   31: astore 10
    //   33: aload 10
    //   35: iconst_0
    //   36: aload 10
    //   38: arraylength
    //   39: invokestatic 369	com/google/android/gms/internal/measurement/zzya:zzk	([BII)Lcom/google/android/gms/internal/measurement/zzya;
    //   42: astore 11
    //   44: aload 5
    //   46: aload 11
    //   48: invokevirtual 372	com/google/android/gms/internal/measurement/zzyi:zza	(Lcom/google/android/gms/internal/measurement/zzya;)V
    //   51: aload 11
    //   53: invokevirtual 375	com/google/android/gms/internal/measurement/zzya:zzza	()V
    //   56: aload_0
    //   57: invokevirtual 229	com/google/android/gms/measurement/internal/zzcr:zzgt	()Lcom/google/android/gms/measurement/internal/zzas;
    //   60: invokevirtual 596	com/google/android/gms/measurement/internal/zzas:zzjo	()Lcom/google/android/gms/measurement/internal/zzau;
    //   63: ldc_w 1074
    //   66: aload_0
    //   67: invokevirtual 940	com/google/android/gms/measurement/internal/zzcr:zzgq	()Lcom/google/android/gms/measurement/internal/zzaq;
    //   70: aload_1
    //   71: invokevirtual 946	com/google/android/gms/measurement/internal/zzaq:zzbt	(Ljava/lang/String;)Ljava/lang/String;
    //   74: aload 10
    //   76: arraylength
    //   77: invokestatic 259	java/lang/Integer:valueOf	(I)Ljava/lang/Integer;
    //   80: invokevirtual 243	com/google/android/gms/measurement/internal/zzau:zze	(Ljava/lang/String;Ljava/lang/Object;Ljava/lang/Object;)V
    //   83: new 301	android/content/ContentValues
    //   86: dup
    //   87: invokespecial 377	android/content/ContentValues:<init>	()V
    //   90: astore 12
    //   92: aload 12
    //   94: ldc_w 379
    //   97: aload_1
    //   98: invokevirtual 305	android/content/ContentValues:put	(Ljava/lang/String;Ljava/lang/String;)V
    //   101: aload 12
    //   103: ldc_w 1076
    //   106: aload_2
    //   107: invokevirtual 308	android/content/ContentValues:put	(Ljava/lang/String;Ljava/lang/Long;)V
    //   110: aload 12
    //   112: ldc_w 1078
    //   115: lload_3
    //   116: invokestatic 273	java/lang/Long:valueOf	(J)Ljava/lang/Long;
    //   119: invokevirtual 308	android/content/ContentValues:put	(Ljava/lang/String;Ljava/lang/Long;)V
    //   122: aload 12
    //   124: ldc_w 1080
    //   127: aload 10
    //   129: invokevirtual 393	android/content/ContentValues:put	(Ljava/lang/String;[B)V
    //   132: aload_0
    //   133: invokevirtual 201	com/google/android/gms/measurement/internal/zzt:getWritableDatabase	()Landroid/database/sqlite/SQLiteDatabase;
    //   136: ldc_w 1082
    //   139: aconst_null
    //   140: aload 12
    //   142: iconst_5
    //   143: invokevirtual 399	android/database/sqlite/SQLiteDatabase:insertWithOnConflict	(Ljava/lang/String;Ljava/lang/String;Landroid/content/ContentValues;I)J
    //   146: ldc2_w 400
    //   149: lcmp
    //   150: ifne +69 -> 219
    //   153: aload_0
    //   154: invokevirtual 229	com/google/android/gms/measurement/internal/zzcr:zzgt	()Lcom/google/android/gms/measurement/internal/zzas;
    //   157: invokevirtual 235	com/google/android/gms/measurement/internal/zzas:zzjg	()Lcom/google/android/gms/measurement/internal/zzau;
    //   160: ldc_w 1084
    //   163: aload_1
    //   164: invokestatic 346	com/google/android/gms/measurement/internal/zzas:zzbw	(Ljava/lang/String;)Ljava/lang/Object;
    //   167: invokevirtual 263	com/google/android/gms/measurement/internal/zzau:zzg	(Ljava/lang/String;Ljava/lang/Object;)V
    //   170: iconst_0
    //   171: ireturn
    //   172: astore 9
    //   174: aload_0
    //   175: invokevirtual 229	com/google/android/gms/measurement/internal/zzcr:zzgt	()Lcom/google/android/gms/measurement/internal/zzas;
    //   178: invokevirtual 235	com/google/android/gms/measurement/internal/zzas:zzjg	()Lcom/google/android/gms/measurement/internal/zzau;
    //   181: ldc_w 1086
    //   184: aload_1
    //   185: invokestatic 346	com/google/android/gms/measurement/internal/zzas:zzbw	(Ljava/lang/String;)Ljava/lang/Object;
    //   188: aload_2
    //   189: aload 9
    //   191: invokevirtual 357	com/google/android/gms/measurement/internal/zzau:zzd	(Ljava/lang/String;Ljava/lang/Object;Ljava/lang/Object;Ljava/lang/Object;)V
    //   194: iconst_0
    //   195: ireturn
    //   196: astore 13
    //   198: aload_0
    //   199: invokevirtual 229	com/google/android/gms/measurement/internal/zzcr:zzgt	()Lcom/google/android/gms/measurement/internal/zzas;
    //   202: invokevirtual 235	com/google/android/gms/measurement/internal/zzas:zzjg	()Lcom/google/android/gms/measurement/internal/zzau;
    //   205: ldc_w 1088
    //   208: aload_1
    //   209: invokestatic 346	com/google/android/gms/measurement/internal/zzas:zzbw	(Ljava/lang/String;)Ljava/lang/Object;
    //   212: aload 13
    //   214: invokevirtual 243	com/google/android/gms/measurement/internal/zzau:zze	(Ljava/lang/String;Ljava/lang/Object;Ljava/lang/Object;)V
    //   217: iconst_0
    //   218: ireturn
    //   219: iconst_1
    //   220: ireturn
    //
    // Exception table:
    //   from	to	target	type
    //   24	56	172	java/io/IOException
    //   132	170	196	android/database/sqlite/SQLiteException
  }

  // ERROR //
  public final String zzad(long paramLong)
  {
    // Byte code:
    //   0: aload_0
    //   1: invokevirtual 325	com/google/android/gms/measurement/internal/zzcr:zzaf	()V
    //   4: aload_0
    //   5: invokevirtual 322	com/google/android/gms/measurement/internal/zzfm:zzcl	()V
    //   8: aload_0
    //   9: invokevirtual 201	com/google/android/gms/measurement/internal/zzt:getWritableDatabase	()Landroid/database/sqlite/SQLiteDatabase;
    //   12: astore 8
    //   14: iconst_1
    //   15: anewarray 19	java/lang/String
    //   18: astore 9
    //   20: aload 9
    //   22: iconst_0
    //   23: lload_1
    //   24: invokestatic 1092	java/lang/String:valueOf	(J)Ljava/lang/String;
    //   27: aastore
    //   28: aload 8
    //   30: ldc_w 1094
    //   33: aload 9
    //   35: invokevirtual 207	android/database/sqlite/SQLiteDatabase:rawQuery	(Ljava/lang/String;[Ljava/lang/String;)Landroid/database/Cursor;
    //   38: astore 10
    //   40: aload 10
    //   42: astore 4
    //   44: aload 4
    //   46: invokeinterface 213 1 0
    //   51: ifne +34 -> 85
    //   54: aload_0
    //   55: invokevirtual 229	com/google/android/gms/measurement/internal/zzcr:zzgt	()Lcom/google/android/gms/measurement/internal/zzas;
    //   58: invokevirtual 596	com/google/android/gms/measurement/internal/zzas:zzjo	()Lcom/google/android/gms/measurement/internal/zzau;
    //   61: ldc_w 1096
    //   64: invokevirtual 268	com/google/android/gms/measurement/internal/zzau:zzby	(Ljava/lang/String;)V
    //   67: aconst_null
    //   68: astore 7
    //   70: aload 4
    //   72: ifnull +10 -> 82
    //   75: aload 4
    //   77: invokeinterface 220 1 0
    //   82: aload 7
    //   84: areturn
    //   85: aload 4
    //   87: iconst_0
    //   88: invokeinterface 286 2 0
    //   93: astore 11
    //   95: aload 11
    //   97: astore 7
    //   99: aload 4
    //   101: ifnull -19 -> 82
    //   104: aload 4
    //   106: invokeinterface 220 1 0
    //   111: aload 7
    //   113: areturn
    //   114: astore 6
    //   116: aconst_null
    //   117: astore 4
    //   119: aload_0
    //   120: invokevirtual 229	com/google/android/gms/measurement/internal/zzcr:zzgt	()Lcom/google/android/gms/measurement/internal/zzas;
    //   123: invokevirtual 235	com/google/android/gms/measurement/internal/zzas:zzjg	()Lcom/google/android/gms/measurement/internal/zzau;
    //   126: ldc_w 1098
    //   129: aload 6
    //   131: invokevirtual 263	com/google/android/gms/measurement/internal/zzau:zzg	(Ljava/lang/String;Ljava/lang/Object;)V
    //   134: aconst_null
    //   135: astore 7
    //   137: aload 4
    //   139: ifnull -57 -> 82
    //   142: aload 4
    //   144: invokeinterface 220 1 0
    //   149: aconst_null
    //   150: areturn
    //   151: astore_3
    //   152: aconst_null
    //   153: astore 4
    //   155: aload_3
    //   156: astore 5
    //   158: aload 4
    //   160: ifnull +10 -> 170
    //   163: aload 4
    //   165: invokeinterface 220 1 0
    //   170: aload 5
    //   172: athrow
    //   173: astore 5
    //   175: goto -17 -> 158
    //   178: astore 6
    //   180: goto -61 -> 119
    //
    // Exception table:
    //   from	to	target	type
    //   8	40	114	android/database/sqlite/SQLiteException
    //   8	40	151	finally
    //   44	67	173	finally
    //   85	95	173	finally
    //   119	134	173	finally
    //   44	67	178	android/database/sqlite/SQLiteException
    //   85	95	178	android/database/sqlite/SQLiteException
  }

  // ERROR //
  public final List<android.util.Pair<com.google.android.gms.internal.measurement.zzfw, Long>> zzb(String paramString, int paramInt1, int paramInt2)
  {
    // Byte code:
    //   0: iconst_1
    //   1: istore 4
    //   3: aload_0
    //   4: invokevirtual 325	com/google/android/gms/measurement/internal/zzcr:zzaf	()V
    //   7: aload_0
    //   8: invokevirtual 322	com/google/android/gms/measurement/internal/zzfm:zzcl	()V
    //   11: iload_2
    //   12: ifle +117 -> 129
    //   15: iload 4
    //   17: istore 5
    //   19: iload 5
    //   21: invokestatic 1103	com/google/android/gms/common/internal/Preconditions:checkArgument	(Z)V
    //   24: iload_3
    //   25: ifle +110 -> 135
    //   28: iload 4
    //   30: invokestatic 1103	com/google/android/gms/common/internal/Preconditions:checkArgument	(Z)V
    //   33: aload_1
    //   34: invokestatic 295	com/google/android/gms/common/internal/Preconditions:checkNotEmpty	(Ljava/lang/String;)Ljava/lang/String;
    //   37: pop
    //   38: aload_0
    //   39: invokevirtual 201	com/google/android/gms/measurement/internal/zzt:getWritableDatabase	()Landroid/database/sqlite/SQLiteDatabase;
    //   42: ldc_w 881
    //   45: iconst_3
    //   46: anewarray 19	java/lang/String
    //   49: dup
    //   50: iconst_0
    //   51: ldc_w 1105
    //   54: aastore
    //   55: dup
    //   56: iconst_1
    //   57: ldc_w 390
    //   60: aastore
    //   61: dup
    //   62: iconst_2
    //   63: ldc 153
    //   65: aastore
    //   66: ldc_w 632
    //   69: iconst_1
    //   70: anewarray 19	java/lang/String
    //   73: dup
    //   74: iconst_0
    //   75: aload_1
    //   76: aastore
    //   77: aconst_null
    //   78: aconst_null
    //   79: ldc_w 1105
    //   82: iload_2
    //   83: invokestatic 844	java/lang/String:valueOf	(I)Ljava/lang/String;
    //   86: invokevirtual 1108	android/database/sqlite/SQLiteDatabase:query	(Ljava/lang/String;[Ljava/lang/String;Ljava/lang/String;[Ljava/lang/String;Ljava/lang/String;Ljava/lang/String;Ljava/lang/String;Ljava/lang/String;)Landroid/database/Cursor;
    //   89: astore 13
    //   91: aload 13
    //   93: astore 8
    //   95: aload 8
    //   97: invokeinterface 213 1 0
    //   102: ifne +39 -> 141
    //   105: invokestatic 1114	java/util/Collections:emptyList	()Ljava/util/List;
    //   108: astore 27
    //   110: aload 27
    //   112: astore 12
    //   114: aload 8
    //   116: ifnull +10 -> 126
    //   119: aload 8
    //   121: invokeinterface 220 1 0
    //   126: aload 12
    //   128: areturn
    //   129: iconst_0
    //   130: istore 5
    //   132: goto -113 -> 19
    //   135: iconst_0
    //   136: istore 4
    //   138: goto -110 -> 28
    //   141: new 460	java/util/ArrayList
    //   144: dup
    //   145: invokespecial 461	java/util/ArrayList:<init>	()V
    //   148: astore 12
    //   150: iconst_0
    //   151: istore 14
    //   153: aload 8
    //   155: iconst_0
    //   156: invokeinterface 217 2 0
    //   161: lstore 15
    //   163: aload 8
    //   165: iconst_1
    //   166: invokeinterface 602 2 0
    //   171: astore 20
    //   173: aload_0
    //   174: invokevirtual 558	com/google/android/gms/measurement/internal/zzfl:zzjr	()Lcom/google/android/gms/measurement/internal/zzft;
    //   177: aload 20
    //   179: invokevirtual 1116	com/google/android/gms/measurement/internal/zzft:zza	([B)[B
    //   182: astore 21
    //   184: aload 12
    //   186: invokeinterface 1118 1 0
    //   191: ifne +13 -> 204
    //   194: iload 14
    //   196: aload 21
    //   198: arraylength
    //   199: iadd
    //   200: iload_3
    //   201: if_icmpgt +104 -> 305
    //   204: aload 21
    //   206: iconst_0
    //   207: aload 21
    //   209: arraylength
    //   210: invokestatic 608	com/google/android/gms/internal/measurement/zzxz:zzj	([BII)Lcom/google/android/gms/internal/measurement/zzxz;
    //   213: astore 22
    //   215: new 549	com/google/android/gms/internal/measurement/zzfw
    //   218: dup
    //   219: invokespecial 1119	com/google/android/gms/internal/measurement/zzfw:<init>	()V
    //   222: astore 23
    //   224: aload 23
    //   226: aload 22
    //   228: invokevirtual 614	com/google/android/gms/internal/measurement/zzyi:zza	(Lcom/google/android/gms/internal/measurement/zzxz;)Lcom/google/android/gms/internal/measurement/zzyi;
    //   231: pop
    //   232: aload 8
    //   234: iconst_2
    //   235: invokeinterface 1123 2 0
    //   240: ifne +19 -> 259
    //   243: aload 23
    //   245: aload 8
    //   247: iconst_2
    //   248: invokeinterface 1126 2 0
    //   253: invokestatic 259	java/lang/Integer:valueOf	(I)Ljava/lang/Integer;
    //   256: putfield 879	com/google/android/gms/internal/measurement/zzfw:zzayl	Ljava/lang/Integer;
    //   259: iload 14
    //   261: aload 21
    //   263: arraylength
    //   264: iadd
    //   265: istore 18
    //   267: aload 12
    //   269: aload 23
    //   271: lload 15
    //   273: invokestatic 273	java/lang/Long:valueOf	(J)Ljava/lang/Long;
    //   276: invokestatic 620	android/util/Pair:create	(Ljava/lang/Object;Ljava/lang/Object;)Landroid/util/Pair;
    //   279: invokeinterface 480 2 0
    //   284: pop
    //   285: aload 8
    //   287: invokeinterface 1129 1 0
    //   292: istore 19
    //   294: iload 19
    //   296: ifeq +9 -> 305
    //   299: iload 18
    //   301: iload_3
    //   302: if_icmple +165 -> 467
    //   305: aload 8
    //   307: ifnull -181 -> 126
    //   310: aload 8
    //   312: invokeinterface 220 1 0
    //   317: aload 12
    //   319: areturn
    //   320: astore 17
    //   322: aload_0
    //   323: invokevirtual 229	com/google/android/gms/measurement/internal/zzcr:zzgt	()Lcom/google/android/gms/measurement/internal/zzas;
    //   326: invokevirtual 235	com/google/android/gms/measurement/internal/zzas:zzjg	()Lcom/google/android/gms/measurement/internal/zzau;
    //   329: ldc_w 1131
    //   332: aload_1
    //   333: invokestatic 346	com/google/android/gms/measurement/internal/zzas:zzbw	(Ljava/lang/String;)Ljava/lang/Object;
    //   336: aload 17
    //   338: invokevirtual 243	com/google/android/gms/measurement/internal/zzau:zze	(Ljava/lang/String;Ljava/lang/Object;Ljava/lang/Object;)V
    //   341: iload 14
    //   343: istore 18
    //   345: goto -60 -> 285
    //   348: astore 24
    //   350: aload_0
    //   351: invokevirtual 229	com/google/android/gms/measurement/internal/zzcr:zzgt	()Lcom/google/android/gms/measurement/internal/zzas;
    //   354: invokevirtual 235	com/google/android/gms/measurement/internal/zzas:zzjg	()Lcom/google/android/gms/measurement/internal/zzau;
    //   357: ldc_w 1133
    //   360: aload_1
    //   361: invokestatic 346	com/google/android/gms/measurement/internal/zzas:zzbw	(Ljava/lang/String;)Ljava/lang/Object;
    //   364: aload 24
    //   366: invokevirtual 243	com/google/android/gms/measurement/internal/zzau:zze	(Ljava/lang/String;Ljava/lang/Object;Ljava/lang/Object;)V
    //   369: iload 14
    //   371: istore 18
    //   373: goto -88 -> 285
    //   376: astore 9
    //   378: aconst_null
    //   379: astore 10
    //   381: aload_0
    //   382: invokevirtual 229	com/google/android/gms/measurement/internal/zzcr:zzgt	()Lcom/google/android/gms/measurement/internal/zzas;
    //   385: invokevirtual 235	com/google/android/gms/measurement/internal/zzas:zzjg	()Lcom/google/android/gms/measurement/internal/zzau;
    //   388: ldc_w 1135
    //   391: aload_1
    //   392: invokestatic 346	com/google/android/gms/measurement/internal/zzas:zzbw	(Ljava/lang/String;)Ljava/lang/Object;
    //   395: aload 9
    //   397: invokevirtual 243	com/google/android/gms/measurement/internal/zzau:zze	(Ljava/lang/String;Ljava/lang/Object;Ljava/lang/Object;)V
    //   400: invokestatic 1114	java/util/Collections:emptyList	()Ljava/util/List;
    //   403: astore 11
    //   405: aload 11
    //   407: astore 12
    //   409: aload 10
    //   411: ifnull -285 -> 126
    //   414: aload 10
    //   416: invokeinterface 220 1 0
    //   421: aload 12
    //   423: areturn
    //   424: astore 7
    //   426: aconst_null
    //   427: astore 8
    //   429: aload 8
    //   431: ifnull +10 -> 441
    //   434: aload 8
    //   436: invokeinterface 220 1 0
    //   441: aload 7
    //   443: athrow
    //   444: astore 7
    //   446: goto -17 -> 429
    //   449: astore 7
    //   451: aload 10
    //   453: astore 8
    //   455: goto -26 -> 429
    //   458: astore 9
    //   460: aload 8
    //   462: astore 10
    //   464: goto -83 -> 381
    //   467: iload 18
    //   469: istore 14
    //   471: goto -318 -> 153
    //
    // Exception table:
    //   from	to	target	type
    //   163	184	320	java/io/IOException
    //   224	232	348	java/io/IOException
    //   38	91	376	android/database/sqlite/SQLiteException
    //   38	91	424	finally
    //   95	110	444	finally
    //   141	150	444	finally
    //   153	163	444	finally
    //   163	184	444	finally
    //   184	204	444	finally
    //   204	224	444	finally
    //   224	232	444	finally
    //   232	259	444	finally
    //   259	285	444	finally
    //   285	294	444	finally
    //   322	341	444	finally
    //   350	369	444	finally
    //   381	405	449	finally
    //   95	110	458	android/database/sqlite/SQLiteException
    //   141	150	458	android/database/sqlite/SQLiteException
    //   153	163	458	android/database/sqlite/SQLiteException
    //   163	184	458	android/database/sqlite/SQLiteException
    //   184	204	458	android/database/sqlite/SQLiteException
    //   204	224	458	android/database/sqlite/SQLiteException
    //   224	232	458	android/database/sqlite/SQLiteException
    //   232	259	458	android/database/sqlite/SQLiteException
    //   259	285	458	android/database/sqlite/SQLiteException
    //   285	294	458	android/database/sqlite/SQLiteException
    //   322	341	458	android/database/sqlite/SQLiteException
    //   350	369	458	android/database/sqlite/SQLiteException
  }

  // ERROR //
  public final List<zzfw> zzb(String paramString1, String paramString2, String paramString3)
  {
    // Byte code:
    //   0: aconst_null
    //   1: astore 4
    //   3: aload_1
    //   4: invokestatic 295	com/google/android/gms/common/internal/Preconditions:checkNotEmpty	(Ljava/lang/String;)Ljava/lang/String;
    //   7: pop
    //   8: aload_0
    //   9: invokevirtual 325	com/google/android/gms/measurement/internal/zzcr:zzaf	()V
    //   12: aload_0
    //   13: invokevirtual 322	com/google/android/gms/measurement/internal/zzfm:zzcl	()V
    //   16: new 460	java/util/ArrayList
    //   19: dup
    //   20: invokespecial 461	java/util/ArrayList:<init>	()V
    //   23: astore 6
    //   25: new 460	java/util/ArrayList
    //   28: dup
    //   29: iconst_3
    //   30: invokespecial 1137	java/util/ArrayList:<init>	(I)V
    //   33: astore 7
    //   35: aload 7
    //   37: aload_1
    //   38: invokeinterface 480 2 0
    //   43: pop
    //   44: new 488	java/lang/StringBuilder
    //   47: dup
    //   48: ldc_w 632
    //   51: invokespecial 1138	java/lang/StringBuilder:<init>	(Ljava/lang/String;)V
    //   54: astore 12
    //   56: aload_2
    //   57: invokestatic 337	android/text/TextUtils:isEmpty	(Ljava/lang/CharSequence;)Z
    //   60: ifne +21 -> 81
    //   63: aload 7
    //   65: aload_2
    //   66: invokeinterface 480 2 0
    //   71: pop
    //   72: aload 12
    //   74: ldc_w 1140
    //   77: invokevirtual 500	java/lang/StringBuilder:append	(Ljava/lang/String;)Ljava/lang/StringBuilder;
    //   80: pop
    //   81: aload_3
    //   82: invokestatic 337	android/text/TextUtils:isEmpty	(Ljava/lang/CharSequence;)Z
    //   85: ifne +30 -> 115
    //   88: aload 7
    //   90: aload_3
    //   91: invokestatic 353	java/lang/String:valueOf	(Ljava/lang/Object;)Ljava/lang/String;
    //   94: ldc_w 1142
    //   97: invokevirtual 1145	java/lang/String:concat	(Ljava/lang/String;)Ljava/lang/String;
    //   100: invokeinterface 480 2 0
    //   105: pop
    //   106: aload 12
    //   108: ldc_w 1147
    //   111: invokevirtual 500	java/lang/StringBuilder:append	(Ljava/lang/String;)Ljava/lang/StringBuilder;
    //   114: pop
    //   115: aload 7
    //   117: aload 7
    //   119: invokeinterface 466 1 0
    //   124: anewarray 19	java/lang/String
    //   127: invokeinterface 1151 2 0
    //   132: checkcast 1152	[Ljava/lang/String;
    //   135: astore 13
    //   137: aload_0
    //   138: invokevirtual 201	com/google/android/gms/measurement/internal/zzt:getWritableDatabase	()Landroid/database/sqlite/SQLiteDatabase;
    //   141: ldc_w 993
    //   144: iconst_4
    //   145: anewarray 19	java/lang/String
    //   148: dup
    //   149: iconst_0
    //   150: ldc_w 666
    //   153: aastore
    //   154: dup
    //   155: iconst_1
    //   156: ldc_w 981
    //   159: aastore
    //   160: dup
    //   161: iconst_2
    //   162: ldc_w 986
    //   165: aastore
    //   166: dup
    //   167: iconst_3
    //   168: ldc 43
    //   170: aastore
    //   171: aload 12
    //   173: invokevirtual 505	java/lang/StringBuilder:toString	()Ljava/lang/String;
    //   176: aload 13
    //   178: aconst_null
    //   179: aconst_null
    //   180: ldc_w 1105
    //   183: ldc_w 1154
    //   186: invokevirtual 1108	android/database/sqlite/SQLiteDatabase:query	(Ljava/lang/String;[Ljava/lang/String;Ljava/lang/String;[Ljava/lang/String;Ljava/lang/String;Ljava/lang/String;Ljava/lang/String;Ljava/lang/String;)Landroid/database/Cursor;
    //   189: astore 14
    //   191: aload 14
    //   193: invokeinterface 213 1 0
    //   198: istore 15
    //   200: iload 15
    //   202: ifne +21 -> 223
    //   205: aload 14
    //   207: ifnull +10 -> 217
    //   210: aload 14
    //   212: invokeinterface 220 1 0
    //   217: aload 6
    //   219: areturn
    //   220: aload 20
    //   222: astore_2
    //   223: aload 6
    //   225: invokeinterface 466 1 0
    //   230: sipush 1000
    //   233: if_icmplt +37 -> 270
    //   236: aload_0
    //   237: invokevirtual 229	com/google/android/gms/measurement/internal/zzcr:zzgt	()Lcom/google/android/gms/measurement/internal/zzas;
    //   240: invokevirtual 235	com/google/android/gms/measurement/internal/zzas:zzjg	()Lcom/google/android/gms/measurement/internal/zzau;
    //   243: ldc_w 1156
    //   246: sipush 1000
    //   249: invokestatic 259	java/lang/Integer:valueOf	(I)Ljava/lang/Integer;
    //   252: invokevirtual 263	com/google/android/gms/measurement/internal/zzau:zzg	(Ljava/lang/String;Ljava/lang/Object;)V
    //   255: aload 14
    //   257: ifnull +10 -> 267
    //   260: aload 14
    //   262: invokeinterface 220 1 0
    //   267: aload 6
    //   269: areturn
    //   270: aload 14
    //   272: iconst_0
    //   273: invokeinterface 286 2 0
    //   278: astore 16
    //   280: aload 14
    //   282: iconst_1
    //   283: invokeinterface 217 2 0
    //   288: lstore 17
    //   290: aload_0
    //   291: aload 14
    //   293: iconst_2
    //   294: invokespecial 1158	com/google/android/gms/measurement/internal/zzt:zza	(Landroid/database/Cursor;I)Ljava/lang/Object;
    //   297: astore 19
    //   299: aload 14
    //   301: iconst_3
    //   302: invokeinterface 286 2 0
    //   307: astore 20
    //   309: aload 19
    //   311: ifnonnull +36 -> 347
    //   314: aload_0
    //   315: invokevirtual 229	com/google/android/gms/measurement/internal/zzcr:zzgt	()Lcom/google/android/gms/measurement/internal/zzas;
    //   318: invokevirtual 235	com/google/android/gms/measurement/internal/zzas:zzjg	()Lcom/google/android/gms/measurement/internal/zzau;
    //   321: ldc_w 1160
    //   324: aload_1
    //   325: invokestatic 346	com/google/android/gms/measurement/internal/zzas:zzbw	(Ljava/lang/String;)Ljava/lang/Object;
    //   328: aload 20
    //   330: aload_3
    //   331: invokevirtual 357	com/google/android/gms/measurement/internal/zzau:zzd	(Ljava/lang/String;Ljava/lang/Object;Ljava/lang/Object;Ljava/lang/Object;)V
    //   334: aload 14
    //   336: invokeinterface 1129 1 0
    //   341: ifne -121 -> 220
    //   344: goto -89 -> 255
    //   347: aload 6
    //   349: new 961	com/google/android/gms/measurement/internal/zzfw
    //   352: dup
    //   353: aload_1
    //   354: aload 20
    //   356: aload 16
    //   358: lload 17
    //   360: aload 19
    //   362: invokespecial 1163	com/google/android/gms/measurement/internal/zzfw:<init>	(Ljava/lang/String;Ljava/lang/String;Ljava/lang/String;JLjava/lang/Object;)V
    //   365: invokeinterface 480 2 0
    //   370: pop
    //   371: goto -37 -> 334
    //   374: astore 8
    //   376: aload 14
    //   378: astore 9
    //   380: aload 20
    //   382: astore_2
    //   383: aload_0
    //   384: invokevirtual 229	com/google/android/gms/measurement/internal/zzcr:zzgt	()Lcom/google/android/gms/measurement/internal/zzas;
    //   387: invokevirtual 235	com/google/android/gms/measurement/internal/zzas:zzjg	()Lcom/google/android/gms/measurement/internal/zzau;
    //   390: ldc_w 1165
    //   393: aload_1
    //   394: invokestatic 346	com/google/android/gms/measurement/internal/zzas:zzbw	(Ljava/lang/String;)Ljava/lang/Object;
    //   397: aload_2
    //   398: aload 8
    //   400: invokevirtual 357	com/google/android/gms/measurement/internal/zzau:zzd	(Ljava/lang/String;Ljava/lang/Object;Ljava/lang/Object;Ljava/lang/Object;)V
    //   403: aload 9
    //   405: ifnull +10 -> 415
    //   408: aload 9
    //   410: invokeinterface 220 1 0
    //   415: aconst_null
    //   416: areturn
    //   417: astore 10
    //   419: aload 4
    //   421: ifnull +10 -> 431
    //   424: aload 4
    //   426: invokeinterface 220 1 0
    //   431: aload 10
    //   433: athrow
    //   434: astore 10
    //   436: aload 14
    //   438: astore 4
    //   440: goto -21 -> 419
    //   443: astore 10
    //   445: aload 9
    //   447: astore 4
    //   449: goto -30 -> 419
    //   452: astore 8
    //   454: aconst_null
    //   455: astore 9
    //   457: goto -74 -> 383
    //   460: astore 8
    //   462: aload 14
    //   464: astore 9
    //   466: goto -83 -> 383
    //
    // Exception table:
    //   from	to	target	type
    //   314	334	374	android/database/sqlite/SQLiteException
    //   334	344	374	android/database/sqlite/SQLiteException
    //   347	371	374	android/database/sqlite/SQLiteException
    //   25	81	417	finally
    //   81	115	417	finally
    //   115	191	417	finally
    //   191	200	434	finally
    //   223	255	434	finally
    //   270	309	434	finally
    //   314	334	434	finally
    //   334	344	434	finally
    //   347	371	434	finally
    //   383	403	443	finally
    //   25	81	452	android/database/sqlite/SQLiteException
    //   81	115	452	android/database/sqlite/SQLiteException
    //   115	191	452	android/database/sqlite/SQLiteException
    //   191	200	460	android/database/sqlite/SQLiteException
    //   223	255	460	android/database/sqlite/SQLiteException
    //   270	309	460	android/database/sqlite/SQLiteException
  }

  // ERROR //
  public final List<zzo> zzb(String paramString, String[] paramArrayOfString)
  {
    // Byte code:
    //   0: aload_0
    //   1: invokevirtual 325	com/google/android/gms/measurement/internal/zzcr:zzaf	()V
    //   4: aload_0
    //   5: invokevirtual 322	com/google/android/gms/measurement/internal/zzfm:zzcl	()V
    //   8: new 460	java/util/ArrayList
    //   11: dup
    //   12: invokespecial 461	java/util/ArrayList:<init>	()V
    //   15: astore_3
    //   16: aload_0
    //   17: invokevirtual 201	com/google/android/gms/measurement/internal/zzt:getWritableDatabase	()Landroid/database/sqlite/SQLiteDatabase;
    //   20: ldc_w 1067
    //   23: bipush 13
    //   25: anewarray 19	java/lang/String
    //   28: dup
    //   29: iconst_0
    //   30: ldc_w 379
    //   33: aastore
    //   34: dup
    //   35: iconst_1
    //   36: ldc 43
    //   38: aastore
    //   39: dup
    //   40: iconst_2
    //   41: ldc_w 666
    //   44: aastore
    //   45: dup
    //   46: iconst_3
    //   47: ldc_w 986
    //   50: aastore
    //   51: dup
    //   52: iconst_4
    //   53: ldc_w 1020
    //   56: aastore
    //   57: dup
    //   58: iconst_5
    //   59: ldc_w 1025
    //   62: aastore
    //   63: dup
    //   64: bipush 6
    //   66: ldc_w 1030
    //   69: aastore
    //   70: dup
    //   71: bipush 7
    //   73: ldc_w 1035
    //   76: aastore
    //   77: dup
    //   78: bipush 8
    //   80: ldc_w 1044
    //   83: aastore
    //   84: dup
    //   85: bipush 9
    //   87: ldc_w 1049
    //   90: aastore
    //   91: dup
    //   92: bipush 10
    //   94: ldc_w 1054
    //   97: aastore
    //   98: dup
    //   99: bipush 11
    //   101: ldc_w 1057
    //   104: aastore
    //   105: dup
    //   106: bipush 12
    //   108: ldc_w 1062
    //   111: aastore
    //   112: aload_1
    //   113: aload_2
    //   114: aconst_null
    //   115: aconst_null
    //   116: ldc_w 1105
    //   119: ldc_w 1154
    //   122: invokevirtual 1108	android/database/sqlite/SQLiteDatabase:query	(Ljava/lang/String;[Ljava/lang/String;Ljava/lang/String;[Ljava/lang/String;Ljava/lang/String;Ljava/lang/String;Ljava/lang/String;Ljava/lang/String;)Landroid/database/Cursor;
    //   125: astore 10
    //   127: aload 10
    //   129: astore 5
    //   131: aload 5
    //   133: invokeinterface 213 1 0
    //   138: istore 11
    //   140: iload 11
    //   142: ifne +21 -> 163
    //   145: aload 5
    //   147: ifnull +10 -> 157
    //   150: aload 5
    //   152: invokeinterface 220 1 0
    //   157: aload_3
    //   158: astore 9
    //   160: aload 9
    //   162: areturn
    //   163: aload_3
    //   164: invokeinterface 466 1 0
    //   169: sipush 1000
    //   172: if_icmplt +36 -> 208
    //   175: aload_0
    //   176: invokevirtual 229	com/google/android/gms/measurement/internal/zzcr:zzgt	()Lcom/google/android/gms/measurement/internal/zzas;
    //   179: invokevirtual 235	com/google/android/gms/measurement/internal/zzas:zzjg	()Lcom/google/android/gms/measurement/internal/zzau;
    //   182: ldc_w 1168
    //   185: sipush 1000
    //   188: invokestatic 259	java/lang/Integer:valueOf	(I)Ljava/lang/Integer;
    //   191: invokevirtual 263	com/google/android/gms/measurement/internal/zzau:zzg	(Ljava/lang/String;Ljava/lang/Object;)V
    //   194: aload 5
    //   196: ifnull +10 -> 206
    //   199: aload 5
    //   201: invokeinterface 220 1 0
    //   206: aload_3
    //   207: areturn
    //   208: aload 5
    //   210: iconst_0
    //   211: invokeinterface 286 2 0
    //   216: astore 12
    //   218: aload 5
    //   220: iconst_1
    //   221: invokeinterface 286 2 0
    //   226: astore 13
    //   228: aload 5
    //   230: iconst_2
    //   231: invokeinterface 286 2 0
    //   236: astore 14
    //   238: aload_0
    //   239: aload 5
    //   241: iconst_3
    //   242: invokespecial 1158	com/google/android/gms/measurement/internal/zzt:zza	(Landroid/database/Cursor;I)Ljava/lang/Object;
    //   245: astore 15
    //   247: aload 5
    //   249: iconst_4
    //   250: invokeinterface 1126 2 0
    //   255: ifeq +198 -> 453
    //   258: iconst_1
    //   259: istore 16
    //   261: aload 5
    //   263: iconst_5
    //   264: invokeinterface 286 2 0
    //   269: astore 17
    //   271: aload 5
    //   273: bipush 6
    //   275: invokeinterface 217 2 0
    //   280: lstore 18
    //   282: aload_0
    //   283: invokevirtual 558	com/google/android/gms/measurement/internal/zzfl:zzjr	()Lcom/google/android/gms/measurement/internal/zzft;
    //   286: aload 5
    //   288: bipush 7
    //   290: invokeinterface 602 2 0
    //   295: getstatic 1174	com/google/android/gms/measurement/internal/zzag:CREATOR	Landroid/os/Parcelable$Creator;
    //   298: invokevirtual 1177	com/google/android/gms/measurement/internal/zzft:zza	([BLandroid/os/Parcelable$Creator;)Landroid/os/Parcelable;
    //   301: checkcast 1170	com/google/android/gms/measurement/internal/zzag
    //   304: astore 20
    //   306: aload 5
    //   308: bipush 8
    //   310: invokeinterface 217 2 0
    //   315: lstore 21
    //   317: aload_0
    //   318: invokevirtual 558	com/google/android/gms/measurement/internal/zzfl:zzjr	()Lcom/google/android/gms/measurement/internal/zzft;
    //   321: aload 5
    //   323: bipush 9
    //   325: invokeinterface 602 2 0
    //   330: getstatic 1174	com/google/android/gms/measurement/internal/zzag:CREATOR	Landroid/os/Parcelable$Creator;
    //   333: invokevirtual 1177	com/google/android/gms/measurement/internal/zzft:zza	([BLandroid/os/Parcelable$Creator;)Landroid/os/Parcelable;
    //   336: checkcast 1170	com/google/android/gms/measurement/internal/zzag
    //   339: astore 23
    //   341: aload 5
    //   343: bipush 10
    //   345: invokeinterface 217 2 0
    //   350: lstore 24
    //   352: aload 5
    //   354: bipush 11
    //   356: invokeinterface 217 2 0
    //   361: lstore 26
    //   363: aload_0
    //   364: invokevirtual 558	com/google/android/gms/measurement/internal/zzfl:zzjr	()Lcom/google/android/gms/measurement/internal/zzft;
    //   367: aload 5
    //   369: bipush 12
    //   371: invokeinterface 602 2 0
    //   376: getstatic 1174	com/google/android/gms/measurement/internal/zzag:CREATOR	Landroid/os/Parcelable$Creator;
    //   379: invokevirtual 1177	com/google/android/gms/measurement/internal/zzft:zza	([BLandroid/os/Parcelable$Creator;)Landroid/os/Parcelable;
    //   382: checkcast 1170	com/google/android/gms/measurement/internal/zzag
    //   385: astore 28
    //   387: aload_3
    //   388: new 1000	com/google/android/gms/measurement/internal/zzo
    //   391: dup
    //   392: aload 12
    //   394: aload 13
    //   396: new 1009	com/google/android/gms/measurement/internal/zzfu
    //   399: dup
    //   400: aload 14
    //   402: lload 24
    //   404: aload 15
    //   406: aload 13
    //   408: invokespecial 1180	com/google/android/gms/measurement/internal/zzfu:<init>	(Ljava/lang/String;JLjava/lang/Object;Ljava/lang/String;)V
    //   411: lload 21
    //   413: iload 16
    //   415: aload 17
    //   417: aload 20
    //   419: lload 18
    //   421: aload 23
    //   423: lload 26
    //   425: aload 28
    //   427: invokespecial 1183	com/google/android/gms/measurement/internal/zzo:<init>	(Ljava/lang/String;Ljava/lang/String;Lcom/google/android/gms/measurement/internal/zzfu;JZLjava/lang/String;Lcom/google/android/gms/measurement/internal/zzag;JLcom/google/android/gms/measurement/internal/zzag;JLcom/google/android/gms/measurement/internal/zzag;)V
    //   430: invokeinterface 480 2 0
    //   435: pop
    //   436: aload 5
    //   438: invokeinterface 1129 1 0
    //   443: istore 30
    //   445: iload 30
    //   447: ifne -284 -> 163
    //   450: goto -256 -> 194
    //   453: iconst_0
    //   454: istore 16
    //   456: goto -195 -> 261
    //   459: astore 6
    //   461: aconst_null
    //   462: astore 7
    //   464: aload_0
    //   465: invokevirtual 229	com/google/android/gms/measurement/internal/zzcr:zzgt	()Lcom/google/android/gms/measurement/internal/zzas;
    //   468: invokevirtual 235	com/google/android/gms/measurement/internal/zzas:zzjg	()Lcom/google/android/gms/measurement/internal/zzau;
    //   471: ldc_w 1185
    //   474: aload 6
    //   476: invokevirtual 263	com/google/android/gms/measurement/internal/zzau:zzg	(Ljava/lang/String;Ljava/lang/Object;)V
    //   479: invokestatic 1114	java/util/Collections:emptyList	()Ljava/util/List;
    //   482: astore 8
    //   484: aload 8
    //   486: astore 9
    //   488: aload 7
    //   490: ifnull -330 -> 160
    //   493: aload 7
    //   495: invokeinterface 220 1 0
    //   500: aload 9
    //   502: areturn
    //   503: astore 4
    //   505: aconst_null
    //   506: astore 5
    //   508: aload 5
    //   510: ifnull +10 -> 520
    //   513: aload 5
    //   515: invokeinterface 220 1 0
    //   520: aload 4
    //   522: athrow
    //   523: astore 4
    //   525: goto -17 -> 508
    //   528: astore 4
    //   530: aload 7
    //   532: astore 5
    //   534: goto -26 -> 508
    //   537: astore 6
    //   539: aload 5
    //   541: astore 7
    //   543: goto -79 -> 464
    //
    // Exception table:
    //   from	to	target	type
    //   16	127	459	android/database/sqlite/SQLiteException
    //   16	127	503	finally
    //   131	140	523	finally
    //   163	194	523	finally
    //   208	258	523	finally
    //   261	445	523	finally
    //   464	484	528	finally
    //   131	140	537	android/database/sqlite/SQLiteException
    //   163	194	537	android/database/sqlite/SQLiteException
    //   208	258	537	android/database/sqlite/SQLiteException
    //   261	445	537	android/database/sqlite/SQLiteException
  }

  // ERROR //
  public final List<zzfw> zzbl(String paramString)
  {
    // Byte code:
    //   0: aconst_null
    //   1: astore_2
    //   2: aload_1
    //   3: invokestatic 295	com/google/android/gms/common/internal/Preconditions:checkNotEmpty	(Ljava/lang/String;)Ljava/lang/String;
    //   6: pop
    //   7: aload_0
    //   8: invokevirtual 325	com/google/android/gms/measurement/internal/zzcr:zzaf	()V
    //   11: aload_0
    //   12: invokevirtual 322	com/google/android/gms/measurement/internal/zzfm:zzcl	()V
    //   15: new 460	java/util/ArrayList
    //   18: dup
    //   19: invokespecial 461	java/util/ArrayList:<init>	()V
    //   22: astore 4
    //   24: aload_0
    //   25: invokevirtual 201	com/google/android/gms/measurement/internal/zzt:getWritableDatabase	()Landroid/database/sqlite/SQLiteDatabase;
    //   28: ldc_w 993
    //   31: iconst_4
    //   32: anewarray 19	java/lang/String
    //   35: dup
    //   36: iconst_0
    //   37: ldc_w 666
    //   40: aastore
    //   41: dup
    //   42: iconst_1
    //   43: ldc 43
    //   45: aastore
    //   46: dup
    //   47: iconst_2
    //   48: ldc_w 981
    //   51: aastore
    //   52: dup
    //   53: iconst_3
    //   54: ldc_w 986
    //   57: aastore
    //   58: ldc_w 632
    //   61: iconst_1
    //   62: anewarray 19	java/lang/String
    //   65: dup
    //   66: iconst_0
    //   67: aload_1
    //   68: aastore
    //   69: aconst_null
    //   70: aconst_null
    //   71: ldc_w 1105
    //   74: ldc_w 1189
    //   77: invokevirtual 1108	android/database/sqlite/SQLiteDatabase:query	(Ljava/lang/String;[Ljava/lang/String;Ljava/lang/String;[Ljava/lang/String;Ljava/lang/String;Ljava/lang/String;Ljava/lang/String;Ljava/lang/String;)Landroid/database/Cursor;
    //   80: astore 8
    //   82: aload 8
    //   84: invokeinterface 213 1 0
    //   89: istore 9
    //   91: iload 9
    //   93: ifne +18 -> 111
    //   96: aload 8
    //   98: ifnull +10 -> 108
    //   101: aload 8
    //   103: invokeinterface 220 1 0
    //   108: aload 4
    //   110: areturn
    //   111: aload 8
    //   113: iconst_0
    //   114: invokeinterface 286 2 0
    //   119: astore 10
    //   121: aload 8
    //   123: iconst_1
    //   124: invokeinterface 286 2 0
    //   129: astore 11
    //   131: aload 11
    //   133: ifnonnull +8 -> 141
    //   136: ldc_w 1191
    //   139: astore 11
    //   141: aload 8
    //   143: iconst_2
    //   144: invokeinterface 217 2 0
    //   149: lstore 12
    //   151: aload_0
    //   152: aload 8
    //   154: iconst_3
    //   155: invokespecial 1158	com/google/android/gms/measurement/internal/zzt:zza	(Landroid/database/Cursor;I)Ljava/lang/Object;
    //   158: astore 14
    //   160: aload 14
    //   162: ifnonnull +49 -> 211
    //   165: aload_0
    //   166: invokevirtual 229	com/google/android/gms/measurement/internal/zzcr:zzgt	()Lcom/google/android/gms/measurement/internal/zzas;
    //   169: invokevirtual 235	com/google/android/gms/measurement/internal/zzas:zzjg	()Lcom/google/android/gms/measurement/internal/zzau;
    //   172: ldc_w 1193
    //   175: aload_1
    //   176: invokestatic 346	com/google/android/gms/measurement/internal/zzas:zzbw	(Ljava/lang/String;)Ljava/lang/Object;
    //   179: invokevirtual 263	com/google/android/gms/measurement/internal/zzau:zzg	(Ljava/lang/String;Ljava/lang/Object;)V
    //   182: aload 8
    //   184: invokeinterface 1129 1 0
    //   189: istore 15
    //   191: iload 15
    //   193: ifne -82 -> 111
    //   196: aload 8
    //   198: ifnull +10 -> 208
    //   201: aload 8
    //   203: invokeinterface 220 1 0
    //   208: aload 4
    //   210: areturn
    //   211: aload 4
    //   213: new 961	com/google/android/gms/measurement/internal/zzfw
    //   216: dup
    //   217: aload_1
    //   218: aload 11
    //   220: aload 10
    //   222: lload 12
    //   224: aload 14
    //   226: invokespecial 1163	com/google/android/gms/measurement/internal/zzfw:<init>	(Ljava/lang/String;Ljava/lang/String;Ljava/lang/String;JLjava/lang/Object;)V
    //   229: invokeinterface 480 2 0
    //   234: pop
    //   235: goto -53 -> 182
    //   238: astore 5
    //   240: aload 8
    //   242: astore 6
    //   244: aload_0
    //   245: invokevirtual 229	com/google/android/gms/measurement/internal/zzcr:zzgt	()Lcom/google/android/gms/measurement/internal/zzas;
    //   248: invokevirtual 235	com/google/android/gms/measurement/internal/zzas:zzjg	()Lcom/google/android/gms/measurement/internal/zzau;
    //   251: ldc_w 1195
    //   254: aload_1
    //   255: invokestatic 346	com/google/android/gms/measurement/internal/zzas:zzbw	(Ljava/lang/String;)Ljava/lang/Object;
    //   258: aload 5
    //   260: invokevirtual 243	com/google/android/gms/measurement/internal/zzau:zze	(Ljava/lang/String;Ljava/lang/Object;Ljava/lang/Object;)V
    //   263: aload 6
    //   265: ifnull +10 -> 275
    //   268: aload 6
    //   270: invokeinterface 220 1 0
    //   275: aconst_null
    //   276: areturn
    //   277: astore 7
    //   279: aload_2
    //   280: ifnull +9 -> 289
    //   283: aload_2
    //   284: invokeinterface 220 1 0
    //   289: aload 7
    //   291: athrow
    //   292: astore 7
    //   294: aload 8
    //   296: astore_2
    //   297: goto -18 -> 279
    //   300: astore 7
    //   302: aload 6
    //   304: astore_2
    //   305: goto -26 -> 279
    //   308: astore 5
    //   310: aconst_null
    //   311: astore 6
    //   313: goto -69 -> 244
    //
    // Exception table:
    //   from	to	target	type
    //   82	91	238	android/database/sqlite/SQLiteException
    //   111	131	238	android/database/sqlite/SQLiteException
    //   141	160	238	android/database/sqlite/SQLiteException
    //   165	182	238	android/database/sqlite/SQLiteException
    //   182	191	238	android/database/sqlite/SQLiteException
    //   211	235	238	android/database/sqlite/SQLiteException
    //   24	82	277	finally
    //   82	91	292	finally
    //   111	131	292	finally
    //   141	160	292	finally
    //   165	182	292	finally
    //   182	191	292	finally
    //   211	235	292	finally
    //   244	263	300	finally
    //   24	82	308	android/database/sqlite/SQLiteException
  }

  // ERROR //
  public final zzg zzbm(String paramString)
  {
    // Byte code:
    //   0: aload_1
    //   1: invokestatic 295	com/google/android/gms/common/internal/Preconditions:checkNotEmpty	(Ljava/lang/String;)Ljava/lang/String;
    //   4: pop
    //   5: aload_0
    //   6: invokevirtual 325	com/google/android/gms/measurement/internal/zzcr:zzaf	()V
    //   9: aload_0
    //   10: invokevirtual 322	com/google/android/gms/measurement/internal/zzfm:zzcl	()V
    //   13: aload_0
    //   14: invokevirtual 201	com/google/android/gms/measurement/internal/zzt:getWritableDatabase	()Landroid/database/sqlite/SQLiteDatabase;
    //   17: ldc_w 630
    //   20: bipush 26
    //   22: anewarray 19	java/lang/String
    //   25: dup
    //   26: iconst_0
    //   27: ldc_w 719
    //   30: aastore
    //   31: dup
    //   32: iconst_1
    //   33: ldc_w 724
    //   36: aastore
    //   37: dup
    //   38: iconst_2
    //   39: ldc_w 729
    //   42: aastore
    //   43: dup
    //   44: iconst_3
    //   45: ldc_w 734
    //   48: aastore
    //   49: dup
    //   50: iconst_4
    //   51: ldc 69
    //   53: aastore
    //   54: dup
    //   55: iconst_5
    //   56: ldc_w 743
    //   59: aastore
    //   60: dup
    //   61: bipush 6
    //   63: ldc 49
    //   65: aastore
    //   66: dup
    //   67: bipush 7
    //   69: ldc 53
    //   71: aastore
    //   72: dup
    //   73: bipush 8
    //   75: ldc 57
    //   77: aastore
    //   78: dup
    //   79: bipush 9
    //   81: ldc 61
    //   83: aastore
    //   84: dup
    //   85: bipush 10
    //   87: ldc 65
    //   89: aastore
    //   90: dup
    //   91: bipush 11
    //   93: ldc 73
    //   95: aastore
    //   96: dup
    //   97: bipush 12
    //   99: ldc 77
    //   101: aastore
    //   102: dup
    //   103: bipush 13
    //   105: ldc 81
    //   107: aastore
    //   108: dup
    //   109: bipush 14
    //   111: ldc 85
    //   113: aastore
    //   114: dup
    //   115: bipush 15
    //   117: ldc 93
    //   119: aastore
    //   120: dup
    //   121: bipush 16
    //   123: ldc 97
    //   125: aastore
    //   126: dup
    //   127: bipush 17
    //   129: ldc 101
    //   131: aastore
    //   132: dup
    //   133: bipush 18
    //   135: ldc 105
    //   137: aastore
    //   138: dup
    //   139: bipush 19
    //   141: ldc 109
    //   143: aastore
    //   144: dup
    //   145: bipush 20
    //   147: ldc 113
    //   149: aastore
    //   150: dup
    //   151: bipush 21
    //   153: ldc 117
    //   155: aastore
    //   156: dup
    //   157: bipush 22
    //   159: ldc 121
    //   161: aastore
    //   162: dup
    //   163: bipush 23
    //   165: ldc 125
    //   167: aastore
    //   168: dup
    //   169: bipush 24
    //   171: ldc 129
    //   173: aastore
    //   174: dup
    //   175: bipush 25
    //   177: ldc 133
    //   179: aastore
    //   180: ldc_w 632
    //   183: iconst_1
    //   184: anewarray 19	java/lang/String
    //   187: dup
    //   188: iconst_0
    //   189: aload_1
    //   190: aastore
    //   191: aconst_null
    //   192: aconst_null
    //   193: aconst_null
    //   194: invokevirtual 636	android/database/sqlite/SQLiteDatabase:query	(Ljava/lang/String;[Ljava/lang/String;Ljava/lang/String;[Ljava/lang/String;Ljava/lang/String;Ljava/lang/String;Ljava/lang/String;)Landroid/database/Cursor;
    //   197: astore 6
    //   199: aload 6
    //   201: astore 4
    //   203: aload 4
    //   205: invokeinterface 213 1 0
    //   210: istore 7
    //   212: iload 7
    //   214: ifne +21 -> 235
    //   217: aload 4
    //   219: ifnull +10 -> 229
    //   222: aload 4
    //   224: invokeinterface 220 1 0
    //   229: aconst_null
    //   230: astore 8
    //   232: aload 8
    //   234: areturn
    //   235: new 714	com/google/android/gms/measurement/internal/zzg
    //   238: dup
    //   239: aload_0
    //   240: getfield 1201	com/google/android/gms/measurement/internal/zzt:zzamx	Lcom/google/android/gms/measurement/internal/zzfn;
    //   243: invokevirtual 1207	com/google/android/gms/measurement/internal/zzfn:zzmh	()Lcom/google/android/gms/measurement/internal/zzbw;
    //   246: aload_1
    //   247: invokespecial 1210	com/google/android/gms/measurement/internal/zzg:<init>	(Lcom/google/android/gms/measurement/internal/zzbw;Ljava/lang/String;)V
    //   250: astore 8
    //   252: aload 8
    //   254: aload 4
    //   256: iconst_0
    //   257: invokeinterface 286 2 0
    //   262: invokevirtual 1213	com/google/android/gms/measurement/internal/zzg:zzaj	(Ljava/lang/String;)V
    //   265: aload 8
    //   267: aload 4
    //   269: iconst_1
    //   270: invokeinterface 286 2 0
    //   275: invokevirtual 1215	com/google/android/gms/measurement/internal/zzg:zzak	(Ljava/lang/String;)V
    //   278: aload 8
    //   280: aload 4
    //   282: iconst_2
    //   283: invokeinterface 286 2 0
    //   288: invokevirtual 1218	com/google/android/gms/measurement/internal/zzg:zzam	(Ljava/lang/String;)V
    //   291: aload 8
    //   293: aload 4
    //   295: iconst_3
    //   296: invokeinterface 217 2 0
    //   301: invokevirtual 1222	com/google/android/gms/measurement/internal/zzg:zzt	(J)V
    //   304: aload 8
    //   306: aload 4
    //   308: iconst_4
    //   309: invokeinterface 217 2 0
    //   314: invokevirtual 1225	com/google/android/gms/measurement/internal/zzg:zzo	(J)V
    //   317: aload 8
    //   319: aload 4
    //   321: iconst_5
    //   322: invokeinterface 217 2 0
    //   327: invokevirtual 1228	com/google/android/gms/measurement/internal/zzg:zzp	(J)V
    //   330: aload 8
    //   332: aload 4
    //   334: bipush 6
    //   336: invokeinterface 286 2 0
    //   341: invokevirtual 1231	com/google/android/gms/measurement/internal/zzg:setAppVersion	(Ljava/lang/String;)V
    //   344: aload 8
    //   346: aload 4
    //   348: bipush 7
    //   350: invokeinterface 286 2 0
    //   355: invokevirtual 1234	com/google/android/gms/measurement/internal/zzg:zzao	(Ljava/lang/String;)V
    //   358: aload 8
    //   360: aload 4
    //   362: bipush 8
    //   364: invokeinterface 217 2 0
    //   369: invokevirtual 1237	com/google/android/gms/measurement/internal/zzg:zzr	(J)V
    //   372: aload 8
    //   374: aload 4
    //   376: bipush 9
    //   378: invokeinterface 217 2 0
    //   383: invokevirtual 1240	com/google/android/gms/measurement/internal/zzg:zzs	(J)V
    //   386: aload 4
    //   388: bipush 10
    //   390: invokeinterface 1123 2 0
    //   395: ifne +456 -> 851
    //   398: aload 4
    //   400: bipush 10
    //   402: invokeinterface 1126 2 0
    //   407: ifeq +328 -> 735
    //   410: goto +441 -> 851
    //   413: aload 8
    //   415: iload 9
    //   417: invokevirtual 1243	com/google/android/gms/measurement/internal/zzg:setMeasurementEnabled	(Z)V
    //   420: aload 8
    //   422: aload 4
    //   424: bipush 11
    //   426: invokeinterface 217 2 0
    //   431: invokevirtual 1246	com/google/android/gms/measurement/internal/zzg:zzw	(J)V
    //   434: aload 8
    //   436: aload 4
    //   438: bipush 12
    //   440: invokeinterface 217 2 0
    //   445: invokevirtual 1249	com/google/android/gms/measurement/internal/zzg:zzx	(J)V
    //   448: aload 8
    //   450: aload 4
    //   452: bipush 13
    //   454: invokeinterface 217 2 0
    //   459: invokevirtual 1252	com/google/android/gms/measurement/internal/zzg:zzy	(J)V
    //   462: aload 8
    //   464: aload 4
    //   466: bipush 14
    //   468: invokeinterface 217 2 0
    //   473: invokevirtual 1255	com/google/android/gms/measurement/internal/zzg:zzz	(J)V
    //   476: aload 8
    //   478: aload 4
    //   480: bipush 15
    //   482: invokeinterface 217 2 0
    //   487: invokevirtual 1258	com/google/android/gms/measurement/internal/zzg:zzu	(J)V
    //   490: aload 8
    //   492: aload 4
    //   494: bipush 16
    //   496: invokeinterface 217 2 0
    //   501: invokevirtual 1261	com/google/android/gms/measurement/internal/zzg:zzv	(J)V
    //   504: aload 4
    //   506: bipush 17
    //   508: invokeinterface 1123 2 0
    //   513: ifeq +228 -> 741
    //   516: ldc2_w 1262
    //   519: lstore 10
    //   521: aload 8
    //   523: lload 10
    //   525: invokevirtual 1266	com/google/android/gms/measurement/internal/zzg:zzq	(J)V
    //   528: aload 8
    //   530: aload 4
    //   532: bipush 18
    //   534: invokeinterface 286 2 0
    //   539: invokevirtual 1269	com/google/android/gms/measurement/internal/zzg:zzan	(Ljava/lang/String;)V
    //   542: aload 8
    //   544: aload 4
    //   546: bipush 19
    //   548: invokeinterface 217 2 0
    //   553: invokevirtual 1272	com/google/android/gms/measurement/internal/zzg:zzab	(J)V
    //   556: aload 8
    //   558: aload 4
    //   560: bipush 20
    //   562: invokeinterface 217 2 0
    //   567: invokevirtual 1275	com/google/android/gms/measurement/internal/zzg:zzaa	(J)V
    //   570: aload 8
    //   572: aload 4
    //   574: bipush 21
    //   576: invokeinterface 286 2 0
    //   581: invokevirtual 1278	com/google/android/gms/measurement/internal/zzg:zzap	(Ljava/lang/String;)V
    //   584: aload 4
    //   586: bipush 22
    //   588: invokeinterface 1123 2 0
    //   593: ifeq +163 -> 756
    //   596: lconst_0
    //   597: lstore 12
    //   599: aload 8
    //   601: lload 12
    //   603: invokevirtual 1281	com/google/android/gms/measurement/internal/zzg:zzac	(J)V
    //   606: aload 4
    //   608: bipush 23
    //   610: invokeinterface 1123 2 0
    //   615: ifne +242 -> 857
    //   618: aload 4
    //   620: bipush 23
    //   622: invokeinterface 1126 2 0
    //   627: ifeq +147 -> 774
    //   630: goto +227 -> 857
    //   633: aload 8
    //   635: iload 14
    //   637: invokevirtual 1283	com/google/android/gms/measurement/internal/zzg:zze	(Z)V
    //   640: aload 4
    //   642: bipush 24
    //   644: invokeinterface 1123 2 0
    //   649: ifne +214 -> 863
    //   652: aload 4
    //   654: bipush 24
    //   656: invokeinterface 1126 2 0
    //   661: ifeq +119 -> 780
    //   664: goto +199 -> 863
    //   667: aload 8
    //   669: iload 15
    //   671: invokevirtual 1286	com/google/android/gms/measurement/internal/zzg:zzf	(Z)V
    //   674: aload 8
    //   676: aload 4
    //   678: bipush 25
    //   680: invokeinterface 286 2 0
    //   685: invokevirtual 1288	com/google/android/gms/measurement/internal/zzg:zzal	(Ljava/lang/String;)V
    //   688: aload 8
    //   690: invokevirtual 1291	com/google/android/gms/measurement/internal/zzg:zzha	()V
    //   693: aload 4
    //   695: invokeinterface 1129 1 0
    //   700: ifeq +20 -> 720
    //   703: aload_0
    //   704: invokevirtual 229	com/google/android/gms/measurement/internal/zzcr:zzgt	()Lcom/google/android/gms/measurement/internal/zzas;
    //   707: invokevirtual 235	com/google/android/gms/measurement/internal/zzas:zzjg	()Lcom/google/android/gms/measurement/internal/zzau;
    //   710: ldc_w 1293
    //   713: aload_1
    //   714: invokestatic 346	com/google/android/gms/measurement/internal/zzas:zzbw	(Ljava/lang/String;)Ljava/lang/Object;
    //   717: invokevirtual 263	com/google/android/gms/measurement/internal/zzau:zzg	(Ljava/lang/String;Ljava/lang/Object;)V
    //   720: aload 4
    //   722: ifnull -490 -> 232
    //   725: aload 4
    //   727: invokeinterface 220 1 0
    //   732: aload 8
    //   734: areturn
    //   735: iconst_0
    //   736: istore 9
    //   738: goto -325 -> 413
    //   741: aload 4
    //   743: bipush 17
    //   745: invokeinterface 1126 2 0
    //   750: i2l
    //   751: lstore 10
    //   753: goto -232 -> 521
    //   756: aload 4
    //   758: bipush 22
    //   760: invokeinterface 217 2 0
    //   765: lstore 16
    //   767: lload 16
    //   769: lstore 12
    //   771: goto -172 -> 599
    //   774: iconst_0
    //   775: istore 14
    //   777: goto -144 -> 633
    //   780: iconst_0
    //   781: istore 15
    //   783: goto -116 -> 667
    //   786: astore 5
    //   788: aconst_null
    //   789: astore 4
    //   791: aload_0
    //   792: invokevirtual 229	com/google/android/gms/measurement/internal/zzcr:zzgt	()Lcom/google/android/gms/measurement/internal/zzas;
    //   795: invokevirtual 235	com/google/android/gms/measurement/internal/zzas:zzjg	()Lcom/google/android/gms/measurement/internal/zzau;
    //   798: ldc_w 1295
    //   801: aload_1
    //   802: invokestatic 346	com/google/android/gms/measurement/internal/zzas:zzbw	(Ljava/lang/String;)Ljava/lang/Object;
    //   805: aload 5
    //   807: invokevirtual 243	com/google/android/gms/measurement/internal/zzau:zze	(Ljava/lang/String;Ljava/lang/Object;Ljava/lang/Object;)V
    //   810: aload 4
    //   812: ifnull +10 -> 822
    //   815: aload 4
    //   817: invokeinterface 220 1 0
    //   822: aconst_null
    //   823: areturn
    //   824: astore_3
    //   825: aconst_null
    //   826: astore 4
    //   828: aload 4
    //   830: ifnull +10 -> 840
    //   833: aload 4
    //   835: invokeinterface 220 1 0
    //   840: aload_3
    //   841: athrow
    //   842: astore_3
    //   843: goto -15 -> 828
    //   846: astore 5
    //   848: goto -57 -> 791
    //   851: iconst_1
    //   852: istore 9
    //   854: goto -441 -> 413
    //   857: iconst_1
    //   858: istore 14
    //   860: goto -227 -> 633
    //   863: iconst_1
    //   864: istore 15
    //   866: goto -199 -> 667
    //
    // Exception table:
    //   from	to	target	type
    //   13	199	786	android/database/sqlite/SQLiteException
    //   13	199	824	finally
    //   203	212	842	finally
    //   235	410	842	finally
    //   413	516	842	finally
    //   521	596	842	finally
    //   599	630	842	finally
    //   633	664	842	finally
    //   667	720	842	finally
    //   741	753	842	finally
    //   756	767	842	finally
    //   791	810	842	finally
    //   203	212	846	android/database/sqlite/SQLiteException
    //   235	410	846	android/database/sqlite/SQLiteException
    //   413	516	846	android/database/sqlite/SQLiteException
    //   521	596	846	android/database/sqlite/SQLiteException
    //   599	630	846	android/database/sqlite/SQLiteException
    //   633	664	846	android/database/sqlite/SQLiteException
    //   667	720	846	android/database/sqlite/SQLiteException
    //   741	753	846	android/database/sqlite/SQLiteException
    //   756	767	846	android/database/sqlite/SQLiteException
  }

  public final long zzbn(String paramString)
  {
    Preconditions.checkNotEmpty(paramString);
    zzaf();
    zzcl();
    try
    {
      int i = getWritableDatabase().delete("raw_events", "rowid in (select rowid from raw_events where app_id=? order by rowid desc limit -1 offset ?)", new String[] { paramString, String.valueOf(Math.max(0, Math.min(1000000, zzgv().zzb(paramString, zzai.zzajj)))) });
      return i;
    }
    catch (SQLiteException localSQLiteException)
    {
      zzgt().zzjg().zze("Error deleting over the limit events. appId", zzas.zzbw(paramString), localSQLiteException);
    }
    return 0L;
  }

  // ERROR //
  public final byte[] zzbo(String paramString)
  {
    // Byte code:
    //   0: aload_1
    //   1: invokestatic 295	com/google/android/gms/common/internal/Preconditions:checkNotEmpty	(Ljava/lang/String;)Ljava/lang/String;
    //   4: pop
    //   5: aload_0
    //   6: invokevirtual 325	com/google/android/gms/measurement/internal/zzcr:zzaf	()V
    //   9: aload_0
    //   10: invokevirtual 322	com/google/android/gms/measurement/internal/zzfm:zzcl	()V
    //   13: aload_0
    //   14: invokevirtual 201	com/google/android/gms/measurement/internal/zzt:getWritableDatabase	()Landroid/database/sqlite/SQLiteDatabase;
    //   17: ldc_w 630
    //   20: iconst_1
    //   21: anewarray 19	java/lang/String
    //   24: dup
    //   25: iconst_0
    //   26: ldc 89
    //   28: aastore
    //   29: ldc_w 632
    //   32: iconst_1
    //   33: anewarray 19	java/lang/String
    //   36: dup
    //   37: iconst_0
    //   38: aload_1
    //   39: aastore
    //   40: aconst_null
    //   41: aconst_null
    //   42: aconst_null
    //   43: invokevirtual 636	android/database/sqlite/SQLiteDatabase:query	(Ljava/lang/String;[Ljava/lang/String;Ljava/lang/String;[Ljava/lang/String;Ljava/lang/String;Ljava/lang/String;Ljava/lang/String;)Landroid/database/Cursor;
    //   46: astore 6
    //   48: aload 6
    //   50: astore 4
    //   52: aload 4
    //   54: invokeinterface 213 1 0
    //   59: istore 7
    //   61: iload 7
    //   63: ifne +21 -> 84
    //   66: aload 4
    //   68: ifnull +10 -> 78
    //   71: aload 4
    //   73: invokeinterface 220 1 0
    //   78: aconst_null
    //   79: astore 8
    //   81: aload 8
    //   83: areturn
    //   84: aload 4
    //   86: iconst_0
    //   87: invokeinterface 602 2 0
    //   92: astore 8
    //   94: aload 4
    //   96: invokeinterface 1129 1 0
    //   101: ifeq +20 -> 121
    //   104: aload_0
    //   105: invokevirtual 229	com/google/android/gms/measurement/internal/zzcr:zzgt	()Lcom/google/android/gms/measurement/internal/zzas;
    //   108: invokevirtual 235	com/google/android/gms/measurement/internal/zzas:zzjg	()Lcom/google/android/gms/measurement/internal/zzau;
    //   111: ldc_w 1309
    //   114: aload_1
    //   115: invokestatic 346	com/google/android/gms/measurement/internal/zzas:zzbw	(Ljava/lang/String;)Ljava/lang/Object;
    //   118: invokevirtual 263	com/google/android/gms/measurement/internal/zzau:zzg	(Ljava/lang/String;Ljava/lang/Object;)V
    //   121: aload 4
    //   123: ifnull -42 -> 81
    //   126: aload 4
    //   128: invokeinterface 220 1 0
    //   133: aload 8
    //   135: areturn
    //   136: astore 5
    //   138: aconst_null
    //   139: astore 4
    //   141: aload_0
    //   142: invokevirtual 229	com/google/android/gms/measurement/internal/zzcr:zzgt	()Lcom/google/android/gms/measurement/internal/zzas;
    //   145: invokevirtual 235	com/google/android/gms/measurement/internal/zzas:zzjg	()Lcom/google/android/gms/measurement/internal/zzau;
    //   148: ldc_w 1311
    //   151: aload_1
    //   152: invokestatic 346	com/google/android/gms/measurement/internal/zzas:zzbw	(Ljava/lang/String;)Ljava/lang/Object;
    //   155: aload 5
    //   157: invokevirtual 243	com/google/android/gms/measurement/internal/zzau:zze	(Ljava/lang/String;Ljava/lang/Object;Ljava/lang/Object;)V
    //   160: aload 4
    //   162: ifnull +10 -> 172
    //   165: aload 4
    //   167: invokeinterface 220 1 0
    //   172: aconst_null
    //   173: areturn
    //   174: astore_3
    //   175: aconst_null
    //   176: astore 4
    //   178: aload 4
    //   180: ifnull +10 -> 190
    //   183: aload 4
    //   185: invokeinterface 220 1 0
    //   190: aload_3
    //   191: athrow
    //   192: astore_3
    //   193: goto -15 -> 178
    //   196: astore 5
    //   198: goto -57 -> 141
    //
    // Exception table:
    //   from	to	target	type
    //   13	48	136	android/database/sqlite/SQLiteException
    //   13	48	174	finally
    //   52	61	192	finally
    //   84	121	192	finally
    //   141	160	192	finally
    //   52	61	196	android/database/sqlite/SQLiteException
    //   84	121	196	android/database/sqlite/SQLiteException
  }

  // ERROR //
  final java.util.Map<Integer, com.google.android.gms.internal.measurement.zzfx> zzbp(String paramString)
  {
    // Byte code:
    //   0: aload_0
    //   1: invokevirtual 322	com/google/android/gms/measurement/internal/zzfm:zzcl	()V
    //   4: aload_0
    //   5: invokevirtual 325	com/google/android/gms/measurement/internal/zzcr:zzaf	()V
    //   8: aload_1
    //   9: invokestatic 295	com/google/android/gms/common/internal/Preconditions:checkNotEmpty	(Ljava/lang/String;)Ljava/lang/String;
    //   12: pop
    //   13: aload_0
    //   14: invokevirtual 201	com/google/android/gms/measurement/internal/zzt:getWritableDatabase	()Landroid/database/sqlite/SQLiteDatabase;
    //   17: astore_3
    //   18: aload_3
    //   19: ldc_w 511
    //   22: iconst_2
    //   23: anewarray 19	java/lang/String
    //   26: dup
    //   27: iconst_0
    //   28: ldc_w 381
    //   31: aastore
    //   32: dup
    //   33: iconst_1
    //   34: ldc_w 1315
    //   37: aastore
    //   38: ldc_w 632
    //   41: iconst_1
    //   42: anewarray 19	java/lang/String
    //   45: dup
    //   46: iconst_0
    //   47: aload_1
    //   48: aastore
    //   49: aconst_null
    //   50: aconst_null
    //   51: aconst_null
    //   52: invokevirtual 636	android/database/sqlite/SQLiteDatabase:query	(Ljava/lang/String;[Ljava/lang/String;Ljava/lang/String;[Ljava/lang/String;Ljava/lang/String;Ljava/lang/String;Ljava/lang/String;)Landroid/database/Cursor;
    //   55: astore 7
    //   57: aload 7
    //   59: astore 5
    //   61: aload 5
    //   63: invokeinterface 213 1 0
    //   68: istore 8
    //   70: iload 8
    //   72: ifne +21 -> 93
    //   75: aload 5
    //   77: ifnull +10 -> 87
    //   80: aload 5
    //   82: invokeinterface 220 1 0
    //   87: aconst_null
    //   88: astore 9
    //   90: aload 9
    //   92: areturn
    //   93: new 1317	android/support/v4/util/ArrayMap
    //   96: dup
    //   97: invokespecial 1318	android/support/v4/util/ArrayMap:<init>	()V
    //   100: astore 9
    //   102: aload 5
    //   104: iconst_0
    //   105: invokeinterface 1126 2 0
    //   110: istore 10
    //   112: aload 5
    //   114: iconst_1
    //   115: invokeinterface 602 2 0
    //   120: astore 11
    //   122: aload 11
    //   124: iconst_0
    //   125: aload 11
    //   127: arraylength
    //   128: invokestatic 608	com/google/android/gms/internal/measurement/zzxz:zzj	([BII)Lcom/google/android/gms/internal/measurement/zzxz;
    //   131: astore 12
    //   133: new 1320	com/google/android/gms/internal/measurement/zzfx
    //   136: dup
    //   137: invokespecial 1321	com/google/android/gms/internal/measurement/zzfx:<init>	()V
    //   140: astore 13
    //   142: aload 13
    //   144: aload 12
    //   146: invokevirtual 614	com/google/android/gms/internal/measurement/zzyi:zza	(Lcom/google/android/gms/internal/measurement/zzxz;)Lcom/google/android/gms/internal/measurement/zzyi;
    //   149: pop
    //   150: aload 9
    //   152: iload 10
    //   154: invokestatic 259	java/lang/Integer:valueOf	(I)Ljava/lang/Integer;
    //   157: aload 13
    //   159: invokeinterface 1326 3 0
    //   164: pop
    //   165: aload 5
    //   167: invokeinterface 1129 1 0
    //   172: istore 15
    //   174: iload 15
    //   176: ifne -74 -> 102
    //   179: aload 5
    //   181: ifnull -91 -> 90
    //   184: aload 5
    //   186: invokeinterface 220 1 0
    //   191: aload 9
    //   193: areturn
    //   194: astore 14
    //   196: aload_0
    //   197: invokevirtual 229	com/google/android/gms/measurement/internal/zzcr:zzgt	()Lcom/google/android/gms/measurement/internal/zzas;
    //   200: invokevirtual 235	com/google/android/gms/measurement/internal/zzas:zzjg	()Lcom/google/android/gms/measurement/internal/zzau;
    //   203: ldc_w 1328
    //   206: aload_1
    //   207: invokestatic 346	com/google/android/gms/measurement/internal/zzas:zzbw	(Ljava/lang/String;)Ljava/lang/Object;
    //   210: iload 10
    //   212: invokestatic 259	java/lang/Integer:valueOf	(I)Ljava/lang/Integer;
    //   215: aload 14
    //   217: invokevirtual 357	com/google/android/gms/measurement/internal/zzau:zzd	(Ljava/lang/String;Ljava/lang/Object;Ljava/lang/Object;Ljava/lang/Object;)V
    //   220: goto -55 -> 165
    //   223: astore 4
    //   225: aload_0
    //   226: invokevirtual 229	com/google/android/gms/measurement/internal/zzcr:zzgt	()Lcom/google/android/gms/measurement/internal/zzas;
    //   229: invokevirtual 235	com/google/android/gms/measurement/internal/zzas:zzjg	()Lcom/google/android/gms/measurement/internal/zzau;
    //   232: ldc_w 1330
    //   235: aload_1
    //   236: invokestatic 346	com/google/android/gms/measurement/internal/zzas:zzbw	(Ljava/lang/String;)Ljava/lang/Object;
    //   239: aload 4
    //   241: invokevirtual 243	com/google/android/gms/measurement/internal/zzau:zze	(Ljava/lang/String;Ljava/lang/Object;Ljava/lang/Object;)V
    //   244: aload 5
    //   246: ifnull +10 -> 256
    //   249: aload 5
    //   251: invokeinterface 220 1 0
    //   256: aconst_null
    //   257: areturn
    //   258: astore 6
    //   260: aconst_null
    //   261: astore 5
    //   263: aload 5
    //   265: ifnull +10 -> 275
    //   268: aload 5
    //   270: invokeinterface 220 1 0
    //   275: aload 6
    //   277: athrow
    //   278: astore 6
    //   280: goto -17 -> 263
    //   283: astore 4
    //   285: aconst_null
    //   286: astore 5
    //   288: goto -63 -> 225
    //
    // Exception table:
    //   from	to	target	type
    //   142	150	194	java/io/IOException
    //   61	70	223	android/database/sqlite/SQLiteException
    //   93	102	223	android/database/sqlite/SQLiteException
    //   102	142	223	android/database/sqlite/SQLiteException
    //   142	150	223	android/database/sqlite/SQLiteException
    //   150	165	223	android/database/sqlite/SQLiteException
    //   165	174	223	android/database/sqlite/SQLiteException
    //   196	220	223	android/database/sqlite/SQLiteException
    //   18	57	258	finally
    //   61	70	278	finally
    //   93	102	278	finally
    //   102	142	278	finally
    //   142	150	278	finally
    //   150	165	278	finally
    //   165	174	278	finally
    //   196	220	278	finally
    //   225	244	278	finally
    //   18	57	283	android/database/sqlite/SQLiteException
  }

  public final long zzbq(String paramString)
  {
    Preconditions.checkNotEmpty(paramString);
    return zza("select count(1) from events where app_id=? and name not like '!_%' escape '!'", new String[] { paramString }, 0L);
  }

  public final List<zzo> zzc(String paramString1, String paramString2, String paramString3)
  {
    Preconditions.checkNotEmpty(paramString1);
    zzaf();
    zzcl();
    ArrayList localArrayList = new ArrayList(3);
    localArrayList.add(paramString1);
    StringBuilder localStringBuilder = new StringBuilder("app_id=?");
    if (!TextUtils.isEmpty(paramString2))
    {
      localArrayList.add(paramString2);
      localStringBuilder.append(" and origin=?");
    }
    if (!TextUtils.isEmpty(paramString3))
    {
      localArrayList.add(String.valueOf(paramString3).concat("*"));
      localStringBuilder.append(" and name glob ?");
    }
    String[] arrayOfString = (String[])localArrayList.toArray(new String[localArrayList.size()]);
    return zzb(localStringBuilder.toString(), arrayOfString);
  }

  @VisibleForTesting
  final void zzc(List<Long> paramList)
  {
    zzaf();
    zzcl();
    Preconditions.checkNotNull(paramList);
    Preconditions.checkNotZero(paramList.size());
    if (!zzip())
      return;
    String str1 = TextUtils.join(",", paramList);
    String str2 = 2 + String.valueOf(str1).length() + "(" + str1 + ")";
    if (zza(80 + String.valueOf(str2).length() + "SELECT COUNT(1) FROM queue WHERE rowid IN " + str2 + " AND retry_count =  2147483647 LIMIT 1", null) > 0L)
      zzgt().zzjj().zzby("The number of upload retries exceeds the limit. Will remain unchanged.");
    try
    {
      getWritableDatabase().execSQL(127 + String.valueOf(str2).length() + "UPDATE queue SET retry_count = IFNULL(retry_count, 0) + 1 WHERE rowid IN " + str2 + " AND (retry_count IS NULL OR retry_count < 2147483647)");
      return;
    }
    catch (SQLiteException localSQLiteException)
    {
      zzgt().zzjg().zzg("Error incrementing retry count. error", localSQLiteException);
    }
  }

  // ERROR //
  public final zzac zzg(String paramString1, String paramString2)
  {
    // Byte code:
    //   0: aload_1
    //   1: invokestatic 295	com/google/android/gms/common/internal/Preconditions:checkNotEmpty	(Ljava/lang/String;)Ljava/lang/String;
    //   4: pop
    //   5: aload_2
    //   6: invokestatic 295	com/google/android/gms/common/internal/Preconditions:checkNotEmpty	(Ljava/lang/String;)Ljava/lang/String;
    //   9: pop
    //   10: aload_0
    //   11: invokevirtual 325	com/google/android/gms/measurement/internal/zzcr:zzaf	()V
    //   14: aload_0
    //   15: invokevirtual 322	com/google/android/gms/measurement/internal/zzfm:zzcl	()V
    //   18: aload_0
    //   19: invokevirtual 201	com/google/android/gms/measurement/internal/zzt:getWritableDatabase	()Landroid/database/sqlite/SQLiteDatabase;
    //   22: ldc_w 707
    //   25: bipush 8
    //   27: anewarray 19	java/lang/String
    //   30: dup
    //   31: iconst_0
    //   32: ldc_w 670
    //   35: aastore
    //   36: dup
    //   37: iconst_1
    //   38: ldc_w 675
    //   41: aastore
    //   42: dup
    //   43: iconst_2
    //   44: ldc_w 680
    //   47: aastore
    //   48: dup
    //   49: iconst_3
    //   50: ldc 21
    //   52: aastore
    //   53: dup
    //   54: iconst_4
    //   55: ldc 25
    //   57: aastore
    //   58: dup
    //   59: iconst_5
    //   60: ldc 29
    //   62: aastore
    //   63: dup
    //   64: bipush 6
    //   66: ldc 33
    //   68: aastore
    //   69: dup
    //   70: bipush 7
    //   72: ldc 37
    //   74: aastore
    //   75: ldc_w 1361
    //   78: iconst_2
    //   79: anewarray 19	java/lang/String
    //   82: dup
    //   83: iconst_0
    //   84: aload_1
    //   85: aastore
    //   86: dup
    //   87: iconst_1
    //   88: aload_2
    //   89: aastore
    //   90: aconst_null
    //   91: aconst_null
    //   92: aconst_null
    //   93: invokevirtual 636	android/database/sqlite/SQLiteDatabase:query	(Ljava/lang/String;[Ljava/lang/String;Ljava/lang/String;[Ljava/lang/String;Ljava/lang/String;Ljava/lang/String;Ljava/lang/String;)Landroid/database/Cursor;
    //   96: astore 9
    //   98: aload 9
    //   100: astore 6
    //   102: aload 6
    //   104: invokeinterface 213 1 0
    //   109: istore 10
    //   111: iload 10
    //   113: ifne +21 -> 134
    //   116: aload 6
    //   118: ifnull +10 -> 128
    //   121: aload 6
    //   123: invokeinterface 220 1 0
    //   128: aconst_null
    //   129: astore 25
    //   131: aload 25
    //   133: areturn
    //   134: aload 6
    //   136: iconst_0
    //   137: invokeinterface 217 2 0
    //   142: lstore 11
    //   144: aload 6
    //   146: iconst_1
    //   147: invokeinterface 217 2 0
    //   152: lstore 13
    //   154: aload 6
    //   156: iconst_2
    //   157: invokeinterface 217 2 0
    //   162: lstore 15
    //   164: aload 6
    //   166: iconst_3
    //   167: invokeinterface 1123 2 0
    //   172: ifeq +161 -> 333
    //   175: lconst_0
    //   176: lstore 17
    //   178: aload 6
    //   180: iconst_4
    //   181: invokeinterface 1123 2 0
    //   186: ifeq +160 -> 346
    //   189: aconst_null
    //   190: astore 19
    //   192: aload 6
    //   194: iconst_5
    //   195: invokeinterface 1123 2 0
    //   200: ifeq +162 -> 362
    //   203: aconst_null
    //   204: astore 20
    //   206: aload 6
    //   208: bipush 6
    //   210: invokeinterface 1123 2 0
    //   215: ifeq +163 -> 378
    //   218: aconst_null
    //   219: astore 21
    //   221: aload 6
    //   223: bipush 7
    //   225: invokeinterface 1123 2 0
    //   230: istore 22
    //   232: aconst_null
    //   233: astore 23
    //   235: iload 22
    //   237: ifne +27 -> 264
    //   240: aload 6
    //   242: bipush 7
    //   244: invokeinterface 217 2 0
    //   249: lconst_1
    //   250: lcmp
    //   251: ifne +148 -> 399
    //   254: iconst_1
    //   255: istore 24
    //   257: iload 24
    //   259: invokestatic 764	java/lang/Boolean:valueOf	(Z)Ljava/lang/Boolean;
    //   262: astore 23
    //   264: new 663	com/google/android/gms/measurement/internal/zzac
    //   267: dup
    //   268: aload_1
    //   269: aload_2
    //   270: lload 11
    //   272: lload 13
    //   274: lload 15
    //   276: lload 17
    //   278: aload 19
    //   280: aload 20
    //   282: aload 21
    //   284: aload 23
    //   286: invokespecial 1364	com/google/android/gms/measurement/internal/zzac:<init>	(Ljava/lang/String;Ljava/lang/String;JJJJLjava/lang/Long;Ljava/lang/Long;Ljava/lang/Long;Ljava/lang/Boolean;)V
    //   289: astore 25
    //   291: aload 6
    //   293: invokeinterface 1129 1 0
    //   298: ifeq +20 -> 318
    //   301: aload_0
    //   302: invokevirtual 229	com/google/android/gms/measurement/internal/zzcr:zzgt	()Lcom/google/android/gms/measurement/internal/zzas;
    //   305: invokevirtual 235	com/google/android/gms/measurement/internal/zzas:zzjg	()Lcom/google/android/gms/measurement/internal/zzau;
    //   308: ldc_w 1366
    //   311: aload_1
    //   312: invokestatic 346	com/google/android/gms/measurement/internal/zzas:zzbw	(Ljava/lang/String;)Ljava/lang/Object;
    //   315: invokevirtual 263	com/google/android/gms/measurement/internal/zzau:zzg	(Ljava/lang/String;Ljava/lang/Object;)V
    //   318: aload 6
    //   320: ifnull -189 -> 131
    //   323: aload 6
    //   325: invokeinterface 220 1 0
    //   330: aload 25
    //   332: areturn
    //   333: aload 6
    //   335: iconst_3
    //   336: invokeinterface 217 2 0
    //   341: lstore 17
    //   343: goto -165 -> 178
    //   346: aload 6
    //   348: iconst_4
    //   349: invokeinterface 217 2 0
    //   354: invokestatic 273	java/lang/Long:valueOf	(J)Ljava/lang/Long;
    //   357: astore 19
    //   359: goto -167 -> 192
    //   362: aload 6
    //   364: iconst_5
    //   365: invokeinterface 217 2 0
    //   370: invokestatic 273	java/lang/Long:valueOf	(J)Ljava/lang/Long;
    //   373: astore 20
    //   375: goto -169 -> 206
    //   378: aload 6
    //   380: bipush 6
    //   382: invokeinterface 217 2 0
    //   387: invokestatic 273	java/lang/Long:valueOf	(J)Ljava/lang/Long;
    //   390: astore 26
    //   392: aload 26
    //   394: astore 21
    //   396: goto -175 -> 221
    //   399: iconst_0
    //   400: istore 24
    //   402: goto -145 -> 257
    //   405: astore 7
    //   407: aconst_null
    //   408: astore 8
    //   410: aload_0
    //   411: invokevirtual 229	com/google/android/gms/measurement/internal/zzcr:zzgt	()Lcom/google/android/gms/measurement/internal/zzas;
    //   414: invokevirtual 235	com/google/android/gms/measurement/internal/zzas:zzjg	()Lcom/google/android/gms/measurement/internal/zzau;
    //   417: ldc_w 1368
    //   420: aload_1
    //   421: invokestatic 346	com/google/android/gms/measurement/internal/zzas:zzbw	(Ljava/lang/String;)Ljava/lang/Object;
    //   424: aload_0
    //   425: invokevirtual 940	com/google/android/gms/measurement/internal/zzcr:zzgq	()Lcom/google/android/gms/measurement/internal/zzaq;
    //   428: aload_2
    //   429: invokevirtual 946	com/google/android/gms/measurement/internal/zzaq:zzbt	(Ljava/lang/String;)Ljava/lang/String;
    //   432: aload 7
    //   434: invokevirtual 357	com/google/android/gms/measurement/internal/zzau:zzd	(Ljava/lang/String;Ljava/lang/Object;Ljava/lang/Object;Ljava/lang/Object;)V
    //   437: aload 8
    //   439: ifnull +10 -> 449
    //   442: aload 8
    //   444: invokeinterface 220 1 0
    //   449: aconst_null
    //   450: areturn
    //   451: astore 5
    //   453: aconst_null
    //   454: astore 6
    //   456: aload 6
    //   458: ifnull +10 -> 468
    //   461: aload 6
    //   463: invokeinterface 220 1 0
    //   468: aload 5
    //   470: athrow
    //   471: astore 5
    //   473: goto -17 -> 456
    //   476: astore 5
    //   478: aload 8
    //   480: astore 6
    //   482: goto -26 -> 456
    //   485: astore 7
    //   487: aload 6
    //   489: astore 8
    //   491: goto -81 -> 410
    //
    // Exception table:
    //   from	to	target	type
    //   18	98	405	android/database/sqlite/SQLiteException
    //   18	98	451	finally
    //   102	111	471	finally
    //   134	175	471	finally
    //   178	189	471	finally
    //   192	203	471	finally
    //   206	218	471	finally
    //   221	232	471	finally
    //   240	254	471	finally
    //   257	264	471	finally
    //   264	318	471	finally
    //   333	343	471	finally
    //   346	359	471	finally
    //   362	375	471	finally
    //   378	392	471	finally
    //   410	437	476	finally
    //   102	111	485	android/database/sqlite/SQLiteException
    //   134	175	485	android/database/sqlite/SQLiteException
    //   178	189	485	android/database/sqlite/SQLiteException
    //   192	203	485	android/database/sqlite/SQLiteException
    //   206	218	485	android/database/sqlite/SQLiteException
    //   221	232	485	android/database/sqlite/SQLiteException
    //   240	254	485	android/database/sqlite/SQLiteException
    //   257	264	485	android/database/sqlite/SQLiteException
    //   264	318	485	android/database/sqlite/SQLiteException
    //   333	343	485	android/database/sqlite/SQLiteException
    //   346	359	485	android/database/sqlite/SQLiteException
    //   362	375	485	android/database/sqlite/SQLiteException
    //   378	392	485	android/database/sqlite/SQLiteException
  }

  protected final boolean zzgy()
  {
    return false;
  }

  public final void zzh(String paramString1, String paramString2)
  {
    Preconditions.checkNotEmpty(paramString1);
    Preconditions.checkNotEmpty(paramString2);
    zzaf();
    zzcl();
    try
    {
      int i = getWritableDatabase().delete("user_attributes", "app_id=? and name=?", new String[] { paramString1, paramString2 });
      zzgt().zzjo().zzg("Deleted user attribute rows", Integer.valueOf(i));
      return;
    }
    catch (SQLiteException localSQLiteException)
    {
      zzgt().zzjg().zzd("Error deleting user attribute. appId", zzas.zzbw(paramString1), zzgq().zzbv(paramString2), localSQLiteException);
    }
  }

  // ERROR //
  public final zzfw zzi(String paramString1, String paramString2)
  {
    // Byte code:
    //   0: aconst_null
    //   1: astore_3
    //   2: aload_1
    //   3: invokestatic 295	com/google/android/gms/common/internal/Preconditions:checkNotEmpty	(Ljava/lang/String;)Ljava/lang/String;
    //   6: pop
    //   7: aload_2
    //   8: invokestatic 295	com/google/android/gms/common/internal/Preconditions:checkNotEmpty	(Ljava/lang/String;)Ljava/lang/String;
    //   11: pop
    //   12: aload_0
    //   13: invokevirtual 325	com/google/android/gms/measurement/internal/zzcr:zzaf	()V
    //   16: aload_0
    //   17: invokevirtual 322	com/google/android/gms/measurement/internal/zzfm:zzcl	()V
    //   20: aload_0
    //   21: invokevirtual 201	com/google/android/gms/measurement/internal/zzt:getWritableDatabase	()Landroid/database/sqlite/SQLiteDatabase;
    //   24: ldc_w 993
    //   27: iconst_3
    //   28: anewarray 19	java/lang/String
    //   31: dup
    //   32: iconst_0
    //   33: ldc_w 981
    //   36: aastore
    //   37: dup
    //   38: iconst_1
    //   39: ldc_w 986
    //   42: aastore
    //   43: dup
    //   44: iconst_2
    //   45: ldc 43
    //   47: aastore
    //   48: ldc_w 1361
    //   51: iconst_2
    //   52: anewarray 19	java/lang/String
    //   55: dup
    //   56: iconst_0
    //   57: aload_1
    //   58: aastore
    //   59: dup
    //   60: iconst_1
    //   61: aload_2
    //   62: aastore
    //   63: aconst_null
    //   64: aconst_null
    //   65: aconst_null
    //   66: invokevirtual 636	android/database/sqlite/SQLiteDatabase:query	(Ljava/lang/String;[Ljava/lang/String;Ljava/lang/String;[Ljava/lang/String;Ljava/lang/String;Ljava/lang/String;Ljava/lang/String;)Landroid/database/Cursor;
    //   69: astore 9
    //   71: aload 9
    //   73: invokeinterface 213 1 0
    //   78: istore 10
    //   80: iload 10
    //   82: ifne +21 -> 103
    //   85: aload 9
    //   87: ifnull +10 -> 97
    //   90: aload 9
    //   92: invokeinterface 220 1 0
    //   97: aconst_null
    //   98: astore 14
    //   100: aload 14
    //   102: areturn
    //   103: aload 9
    //   105: iconst_0
    //   106: invokeinterface 217 2 0
    //   111: lstore 11
    //   113: aload_0
    //   114: aload 9
    //   116: iconst_1
    //   117: invokespecial 1158	com/google/android/gms/measurement/internal/zzt:zza	(Landroid/database/Cursor;I)Ljava/lang/Object;
    //   120: astore 13
    //   122: new 961	com/google/android/gms/measurement/internal/zzfw
    //   125: dup
    //   126: aload_1
    //   127: aload 9
    //   129: iconst_2
    //   130: invokeinterface 286 2 0
    //   135: aload_2
    //   136: lload 11
    //   138: aload 13
    //   140: invokespecial 1163	com/google/android/gms/measurement/internal/zzfw:<init>	(Ljava/lang/String;Ljava/lang/String;Ljava/lang/String;JLjava/lang/Object;)V
    //   143: astore 14
    //   145: aload 9
    //   147: invokeinterface 1129 1 0
    //   152: ifeq +20 -> 172
    //   155: aload_0
    //   156: invokevirtual 229	com/google/android/gms/measurement/internal/zzcr:zzgt	()Lcom/google/android/gms/measurement/internal/zzas;
    //   159: invokevirtual 235	com/google/android/gms/measurement/internal/zzas:zzjg	()Lcom/google/android/gms/measurement/internal/zzau;
    //   162: ldc_w 1379
    //   165: aload_1
    //   166: invokestatic 346	com/google/android/gms/measurement/internal/zzas:zzbw	(Ljava/lang/String;)Ljava/lang/Object;
    //   169: invokevirtual 263	com/google/android/gms/measurement/internal/zzau:zzg	(Ljava/lang/String;Ljava/lang/Object;)V
    //   172: aload 9
    //   174: ifnull -74 -> 100
    //   177: aload 9
    //   179: invokeinterface 220 1 0
    //   184: aload 14
    //   186: areturn
    //   187: astore 7
    //   189: aconst_null
    //   190: astore 8
    //   192: aload_0
    //   193: invokevirtual 229	com/google/android/gms/measurement/internal/zzcr:zzgt	()Lcom/google/android/gms/measurement/internal/zzas;
    //   196: invokevirtual 235	com/google/android/gms/measurement/internal/zzas:zzjg	()Lcom/google/android/gms/measurement/internal/zzau;
    //   199: ldc_w 1381
    //   202: aload_1
    //   203: invokestatic 346	com/google/android/gms/measurement/internal/zzas:zzbw	(Ljava/lang/String;)Ljava/lang/Object;
    //   206: aload_0
    //   207: invokevirtual 940	com/google/android/gms/measurement/internal/zzcr:zzgq	()Lcom/google/android/gms/measurement/internal/zzaq;
    //   210: aload_2
    //   211: invokevirtual 1377	com/google/android/gms/measurement/internal/zzaq:zzbv	(Ljava/lang/String;)Ljava/lang/String;
    //   214: aload 7
    //   216: invokevirtual 357	com/google/android/gms/measurement/internal/zzau:zzd	(Ljava/lang/String;Ljava/lang/Object;Ljava/lang/Object;Ljava/lang/Object;)V
    //   219: aload 8
    //   221: ifnull +10 -> 231
    //   224: aload 8
    //   226: invokeinterface 220 1 0
    //   231: aconst_null
    //   232: areturn
    //   233: astore 6
    //   235: aload_3
    //   236: ifnull +9 -> 245
    //   239: aload_3
    //   240: invokeinterface 220 1 0
    //   245: aload 6
    //   247: athrow
    //   248: astore 6
    //   250: aload 9
    //   252: astore_3
    //   253: goto -18 -> 235
    //   256: astore 6
    //   258: aload 8
    //   260: astore_3
    //   261: goto -26 -> 235
    //   264: astore 7
    //   266: aload 9
    //   268: astore 8
    //   270: goto -78 -> 192
    //
    // Exception table:
    //   from	to	target	type
    //   20	71	187	android/database/sqlite/SQLiteException
    //   20	71	233	finally
    //   71	80	248	finally
    //   103	172	248	finally
    //   192	219	256	finally
    //   71	80	264	android/database/sqlite/SQLiteException
    //   103	172	264	android/database/sqlite/SQLiteException
  }

  // ERROR //
  public final String zzih()
  {
    // Byte code:
    //   0: aload_0
    //   1: invokevirtual 201	com/google/android/gms/measurement/internal/zzt:getWritableDatabase	()Landroid/database/sqlite/SQLiteDatabase;
    //   4: astore_1
    //   5: aload_1
    //   6: ldc_w 1384
    //   9: aconst_null
    //   10: invokevirtual 207	android/database/sqlite/SQLiteDatabase:rawQuery	(Ljava/lang/String;[Ljava/lang/String;)Landroid/database/Cursor;
    //   13: astore 7
    //   15: aload 7
    //   17: astore_3
    //   18: aload_3
    //   19: invokeinterface 213 1 0
    //   24: ifeq +29 -> 53
    //   27: aload_3
    //   28: iconst_0
    //   29: invokeinterface 286 2 0
    //   34: astore 8
    //   36: aload 8
    //   38: astore 6
    //   40: aload_3
    //   41: ifnull +9 -> 50
    //   44: aload_3
    //   45: invokeinterface 220 1 0
    //   50: aload 6
    //   52: areturn
    //   53: aconst_null
    //   54: astore 6
    //   56: aload_3
    //   57: ifnull -7 -> 50
    //   60: aload_3
    //   61: invokeinterface 220 1 0
    //   66: aconst_null
    //   67: areturn
    //   68: astore 5
    //   70: aconst_null
    //   71: astore_3
    //   72: aload_0
    //   73: invokevirtual 229	com/google/android/gms/measurement/internal/zzcr:zzgt	()Lcom/google/android/gms/measurement/internal/zzas;
    //   76: invokevirtual 235	com/google/android/gms/measurement/internal/zzas:zzjg	()Lcom/google/android/gms/measurement/internal/zzau;
    //   79: ldc_w 1386
    //   82: aload 5
    //   84: invokevirtual 263	com/google/android/gms/measurement/internal/zzau:zzg	(Ljava/lang/String;Ljava/lang/Object;)V
    //   87: aconst_null
    //   88: astore 6
    //   90: aload_3
    //   91: ifnull -41 -> 50
    //   94: aload_3
    //   95: invokeinterface 220 1 0
    //   100: aconst_null
    //   101: areturn
    //   102: astore_2
    //   103: aconst_null
    //   104: astore_3
    //   105: aload_2
    //   106: astore 4
    //   108: aload_3
    //   109: ifnull +9 -> 118
    //   112: aload_3
    //   113: invokeinterface 220 1 0
    //   118: aload 4
    //   120: athrow
    //   121: astore 4
    //   123: goto -15 -> 108
    //   126: astore 5
    //   128: goto -56 -> 72
    //
    // Exception table:
    //   from	to	target	type
    //   5	15	68	android/database/sqlite/SQLiteException
    //   5	15	102	finally
    //   18	36	121	finally
    //   72	87	121	finally
    //   18	36	126	android/database/sqlite/SQLiteException
  }

  public final boolean zzii()
  {
    return zza("select count(1) > 0 from queue where has_realtime = 1", null) != 0L;
  }

  final void zzij()
  {
    zzaf();
    zzcl();
    if (!zzip());
    int i;
    do
    {
      do
      {
        long l1;
        long l2;
        do
        {
          return;
          l1 = zzgu().zzanf.get();
          l2 = zzbx().elapsedRealtime();
        }
        while (Math.abs(l2 - l1) <= ((Long)zzai.zzajs.get()).longValue());
        zzgu().zzanf.set(l2);
        zzaf();
        zzcl();
      }
      while (!zzip());
      SQLiteDatabase localSQLiteDatabase = getWritableDatabase();
      String[] arrayOfString = new String[2];
      arrayOfString[0] = String.valueOf(zzbx().currentTimeMillis());
      arrayOfString[1] = String.valueOf(zzq.zzib());
      i = localSQLiteDatabase.delete("queue", "abs(bundle_end_timestamp - ?) > cast(? as integer)", arrayOfString);
    }
    while (i <= 0);
    zzgt().zzjo().zzg("Deleted stale rows. rowsDeleted", Integer.valueOf(i));
  }

  public final long zzik()
  {
    return zza("select max(bundle_end_timestamp) from queue", null, 0L);
  }

  public final long zzil()
  {
    return zza("select max(timestamp) from raw_events", null, 0L);
  }

  public final boolean zzim()
  {
    return zza("select count(1) > 0 from raw_events", null) != 0L;
  }

  public final boolean zzin()
  {
    return zza("select count(1) > 0 from raw_events where realtime = 1", null) != 0L;
  }

  public final long zzio()
  {
    long l1 = -1L;
    Cursor localCursor = null;
    try
    {
      localCursor = getWritableDatabase().rawQuery("select rowid from raw_events order by rowid desc limit 1;", null);
      boolean bool = localCursor.moveToFirst();
      if (!bool)
        return l1;
      long l2 = localCursor.getLong(0);
      l1 = l2;
      return l1;
    }
    catch (SQLiteException localSQLiteException)
    {
      zzgt().zzjg().zzg("Error querying raw events", localSQLiteException);
      return l1;
    }
    finally
    {
      if (localCursor != null)
        localCursor.close();
    }
  }

  // ERROR //
  public final zzo zzj(String paramString1, String paramString2)
  {
    // Byte code:
    //   0: aload_1
    //   1: invokestatic 295	com/google/android/gms/common/internal/Preconditions:checkNotEmpty	(Ljava/lang/String;)Ljava/lang/String;
    //   4: pop
    //   5: aload_2
    //   6: invokestatic 295	com/google/android/gms/common/internal/Preconditions:checkNotEmpty	(Ljava/lang/String;)Ljava/lang/String;
    //   9: pop
    //   10: aload_0
    //   11: invokevirtual 325	com/google/android/gms/measurement/internal/zzcr:zzaf	()V
    //   14: aload_0
    //   15: invokevirtual 322	com/google/android/gms/measurement/internal/zzfm:zzcl	()V
    //   18: aload_0
    //   19: invokevirtual 201	com/google/android/gms/measurement/internal/zzt:getWritableDatabase	()Landroid/database/sqlite/SQLiteDatabase;
    //   22: ldc_w 1067
    //   25: bipush 11
    //   27: anewarray 19	java/lang/String
    //   30: dup
    //   31: iconst_0
    //   32: ldc 43
    //   34: aastore
    //   35: dup
    //   36: iconst_1
    //   37: ldc_w 986
    //   40: aastore
    //   41: dup
    //   42: iconst_2
    //   43: ldc_w 1020
    //   46: aastore
    //   47: dup
    //   48: iconst_3
    //   49: ldc_w 1025
    //   52: aastore
    //   53: dup
    //   54: iconst_4
    //   55: ldc_w 1030
    //   58: aastore
    //   59: dup
    //   60: iconst_5
    //   61: ldc_w 1035
    //   64: aastore
    //   65: dup
    //   66: bipush 6
    //   68: ldc_w 1044
    //   71: aastore
    //   72: dup
    //   73: bipush 7
    //   75: ldc_w 1049
    //   78: aastore
    //   79: dup
    //   80: bipush 8
    //   82: ldc_w 1054
    //   85: aastore
    //   86: dup
    //   87: bipush 9
    //   89: ldc_w 1057
    //   92: aastore
    //   93: dup
    //   94: bipush 10
    //   96: ldc_w 1062
    //   99: aastore
    //   100: ldc_w 1361
    //   103: iconst_2
    //   104: anewarray 19	java/lang/String
    //   107: dup
    //   108: iconst_0
    //   109: aload_1
    //   110: aastore
    //   111: dup
    //   112: iconst_1
    //   113: aload_2
    //   114: aastore
    //   115: aconst_null
    //   116: aconst_null
    //   117: aconst_null
    //   118: invokevirtual 636	android/database/sqlite/SQLiteDatabase:query	(Ljava/lang/String;[Ljava/lang/String;Ljava/lang/String;[Ljava/lang/String;Ljava/lang/String;Ljava/lang/String;Ljava/lang/String;)Landroid/database/Cursor;
    //   121: astore 9
    //   123: aload 9
    //   125: astore 6
    //   127: aload 6
    //   129: invokeinterface 213 1 0
    //   134: istore 10
    //   136: iload 10
    //   138: ifne +21 -> 159
    //   141: aload 6
    //   143: ifnull +10 -> 153
    //   146: aload 6
    //   148: invokeinterface 220 1 0
    //   153: aconst_null
    //   154: astore 26
    //   156: aload 26
    //   158: areturn
    //   159: aload 6
    //   161: iconst_0
    //   162: invokeinterface 286 2 0
    //   167: astore 11
    //   169: aload_0
    //   170: aload 6
    //   172: iconst_1
    //   173: invokespecial 1158	com/google/android/gms/measurement/internal/zzt:zza	(Landroid/database/Cursor;I)Ljava/lang/Object;
    //   176: astore 12
    //   178: aload 6
    //   180: iconst_2
    //   181: invokeinterface 1126 2 0
    //   186: ifeq +222 -> 408
    //   189: iconst_1
    //   190: istore 13
    //   192: aload 6
    //   194: iconst_3
    //   195: invokeinterface 286 2 0
    //   200: astore 14
    //   202: aload 6
    //   204: iconst_4
    //   205: invokeinterface 217 2 0
    //   210: lstore 15
    //   212: aload_0
    //   213: invokevirtual 558	com/google/android/gms/measurement/internal/zzfl:zzjr	()Lcom/google/android/gms/measurement/internal/zzft;
    //   216: aload 6
    //   218: iconst_5
    //   219: invokeinterface 602 2 0
    //   224: getstatic 1174	com/google/android/gms/measurement/internal/zzag:CREATOR	Landroid/os/Parcelable$Creator;
    //   227: invokevirtual 1177	com/google/android/gms/measurement/internal/zzft:zza	([BLandroid/os/Parcelable$Creator;)Landroid/os/Parcelable;
    //   230: checkcast 1170	com/google/android/gms/measurement/internal/zzag
    //   233: astore 17
    //   235: aload 6
    //   237: bipush 6
    //   239: invokeinterface 217 2 0
    //   244: lstore 18
    //   246: aload_0
    //   247: invokevirtual 558	com/google/android/gms/measurement/internal/zzfl:zzjr	()Lcom/google/android/gms/measurement/internal/zzft;
    //   250: aload 6
    //   252: bipush 7
    //   254: invokeinterface 602 2 0
    //   259: getstatic 1174	com/google/android/gms/measurement/internal/zzag:CREATOR	Landroid/os/Parcelable$Creator;
    //   262: invokevirtual 1177	com/google/android/gms/measurement/internal/zzft:zza	([BLandroid/os/Parcelable$Creator;)Landroid/os/Parcelable;
    //   265: checkcast 1170	com/google/android/gms/measurement/internal/zzag
    //   268: astore 20
    //   270: aload 6
    //   272: bipush 8
    //   274: invokeinterface 217 2 0
    //   279: lstore 21
    //   281: aload 6
    //   283: bipush 9
    //   285: invokeinterface 217 2 0
    //   290: lstore 23
    //   292: aload_0
    //   293: invokevirtual 558	com/google/android/gms/measurement/internal/zzfl:zzjr	()Lcom/google/android/gms/measurement/internal/zzft;
    //   296: aload 6
    //   298: bipush 10
    //   300: invokeinterface 602 2 0
    //   305: getstatic 1174	com/google/android/gms/measurement/internal/zzag:CREATOR	Landroid/os/Parcelable$Creator;
    //   308: invokevirtual 1177	com/google/android/gms/measurement/internal/zzft:zza	([BLandroid/os/Parcelable$Creator;)Landroid/os/Parcelable;
    //   311: checkcast 1170	com/google/android/gms/measurement/internal/zzag
    //   314: astore 25
    //   316: new 1000	com/google/android/gms/measurement/internal/zzo
    //   319: dup
    //   320: aload_1
    //   321: aload 11
    //   323: new 1009	com/google/android/gms/measurement/internal/zzfu
    //   326: dup
    //   327: aload_2
    //   328: lload 21
    //   330: aload 12
    //   332: aload 11
    //   334: invokespecial 1180	com/google/android/gms/measurement/internal/zzfu:<init>	(Ljava/lang/String;JLjava/lang/Object;Ljava/lang/String;)V
    //   337: lload 18
    //   339: iload 13
    //   341: aload 14
    //   343: aload 17
    //   345: lload 15
    //   347: aload 20
    //   349: lload 23
    //   351: aload 25
    //   353: invokespecial 1183	com/google/android/gms/measurement/internal/zzo:<init>	(Ljava/lang/String;Ljava/lang/String;Lcom/google/android/gms/measurement/internal/zzfu;JZLjava/lang/String;Lcom/google/android/gms/measurement/internal/zzag;JLcom/google/android/gms/measurement/internal/zzag;JLcom/google/android/gms/measurement/internal/zzag;)V
    //   356: astore 26
    //   358: aload 6
    //   360: invokeinterface 1129 1 0
    //   365: ifeq +28 -> 393
    //   368: aload_0
    //   369: invokevirtual 229	com/google/android/gms/measurement/internal/zzcr:zzgt	()Lcom/google/android/gms/measurement/internal/zzas;
    //   372: invokevirtual 235	com/google/android/gms/measurement/internal/zzas:zzjg	()Lcom/google/android/gms/measurement/internal/zzau;
    //   375: ldc_w 1444
    //   378: aload_1
    //   379: invokestatic 346	com/google/android/gms/measurement/internal/zzas:zzbw	(Ljava/lang/String;)Ljava/lang/Object;
    //   382: aload_0
    //   383: invokevirtual 940	com/google/android/gms/measurement/internal/zzcr:zzgq	()Lcom/google/android/gms/measurement/internal/zzaq;
    //   386: aload_2
    //   387: invokevirtual 1377	com/google/android/gms/measurement/internal/zzaq:zzbv	(Ljava/lang/String;)Ljava/lang/String;
    //   390: invokevirtual 243	com/google/android/gms/measurement/internal/zzau:zze	(Ljava/lang/String;Ljava/lang/Object;Ljava/lang/Object;)V
    //   393: aload 6
    //   395: ifnull -239 -> 156
    //   398: aload 6
    //   400: invokeinterface 220 1 0
    //   405: aload 26
    //   407: areturn
    //   408: iconst_0
    //   409: istore 13
    //   411: goto -219 -> 192
    //   414: astore 7
    //   416: aconst_null
    //   417: astore 8
    //   419: aload_0
    //   420: invokevirtual 229	com/google/android/gms/measurement/internal/zzcr:zzgt	()Lcom/google/android/gms/measurement/internal/zzas;
    //   423: invokevirtual 235	com/google/android/gms/measurement/internal/zzas:zzjg	()Lcom/google/android/gms/measurement/internal/zzau;
    //   426: ldc_w 1446
    //   429: aload_1
    //   430: invokestatic 346	com/google/android/gms/measurement/internal/zzas:zzbw	(Ljava/lang/String;)Ljava/lang/Object;
    //   433: aload_0
    //   434: invokevirtual 940	com/google/android/gms/measurement/internal/zzcr:zzgq	()Lcom/google/android/gms/measurement/internal/zzaq;
    //   437: aload_2
    //   438: invokevirtual 1377	com/google/android/gms/measurement/internal/zzaq:zzbv	(Ljava/lang/String;)Ljava/lang/String;
    //   441: aload 7
    //   443: invokevirtual 357	com/google/android/gms/measurement/internal/zzau:zzd	(Ljava/lang/String;Ljava/lang/Object;Ljava/lang/Object;Ljava/lang/Object;)V
    //   446: aload 8
    //   448: ifnull +10 -> 458
    //   451: aload 8
    //   453: invokeinterface 220 1 0
    //   458: aconst_null
    //   459: areturn
    //   460: astore 5
    //   462: aconst_null
    //   463: astore 6
    //   465: aload 6
    //   467: ifnull +10 -> 477
    //   470: aload 6
    //   472: invokeinterface 220 1 0
    //   477: aload 5
    //   479: athrow
    //   480: astore 5
    //   482: goto -17 -> 465
    //   485: astore 5
    //   487: aload 8
    //   489: astore 6
    //   491: goto -26 -> 465
    //   494: astore 7
    //   496: aload 6
    //   498: astore 8
    //   500: goto -81 -> 419
    //
    // Exception table:
    //   from	to	target	type
    //   18	123	414	android/database/sqlite/SQLiteException
    //   18	123	460	finally
    //   127	136	480	finally
    //   159	189	480	finally
    //   192	393	480	finally
    //   419	446	485	finally
    //   127	136	494	android/database/sqlite/SQLiteException
    //   159	189	494	android/database/sqlite/SQLiteException
    //   192	393	494	android/database/sqlite/SQLiteException
  }

  public final int zzk(String paramString1, String paramString2)
  {
    Preconditions.checkNotEmpty(paramString1);
    Preconditions.checkNotEmpty(paramString2);
    zzaf();
    zzcl();
    try
    {
      int i = getWritableDatabase().delete("conditional_properties", "app_id=? and name=?", new String[] { paramString1, paramString2 });
      return i;
    }
    catch (SQLiteException localSQLiteException)
    {
      zzgt().zzjg().zzd("Error deleting conditional property", zzas.zzbw(paramString1), zzgq().zzbv(paramString2), localSQLiteException);
    }
    return 0;
  }

  // ERROR //
  final java.util.Map<Integer, List<zzfj>> zzl(String paramString1, String paramString2)
  {
    // Byte code:
    //   0: aload_0
    //   1: invokevirtual 322	com/google/android/gms/measurement/internal/zzfm:zzcl	()V
    //   4: aload_0
    //   5: invokevirtual 325	com/google/android/gms/measurement/internal/zzcr:zzaf	()V
    //   8: aload_1
    //   9: invokestatic 295	com/google/android/gms/common/internal/Preconditions:checkNotEmpty	(Ljava/lang/String;)Ljava/lang/String;
    //   12: pop
    //   13: aload_2
    //   14: invokestatic 295	com/google/android/gms/common/internal/Preconditions:checkNotEmpty	(Ljava/lang/String;)Ljava/lang/String;
    //   17: pop
    //   18: new 1317	android/support/v4/util/ArrayMap
    //   21: dup
    //   22: invokespecial 1318	android/support/v4/util/ArrayMap:<init>	()V
    //   25: astore 5
    //   27: aload_0
    //   28: invokevirtual 201	com/google/android/gms/measurement/internal/zzt:getWritableDatabase	()Landroid/database/sqlite/SQLiteDatabase;
    //   31: astore 6
    //   33: aload 6
    //   35: ldc_w 395
    //   38: iconst_2
    //   39: anewarray 19	java/lang/String
    //   42: dup
    //   43: iconst_0
    //   44: ldc_w 381
    //   47: aastore
    //   48: dup
    //   49: iconst_1
    //   50: ldc_w 390
    //   53: aastore
    //   54: ldc_w 1453
    //   57: iconst_2
    //   58: anewarray 19	java/lang/String
    //   61: dup
    //   62: iconst_0
    //   63: aload_1
    //   64: aastore
    //   65: dup
    //   66: iconst_1
    //   67: aload_2
    //   68: aastore
    //   69: aconst_null
    //   70: aconst_null
    //   71: aconst_null
    //   72: invokevirtual 636	android/database/sqlite/SQLiteDatabase:query	(Ljava/lang/String;[Ljava/lang/String;Ljava/lang/String;[Ljava/lang/String;Ljava/lang/String;Ljava/lang/String;Ljava/lang/String;)Landroid/database/Cursor;
    //   75: astore 10
    //   77: aload 10
    //   79: astore 8
    //   81: aload 8
    //   83: invokeinterface 213 1 0
    //   88: ifne +23 -> 111
    //   91: invokestatic 1457	java/util/Collections:emptyMap	()Ljava/util/Map;
    //   94: astore 21
    //   96: aload 8
    //   98: ifnull +10 -> 108
    //   101: aload 8
    //   103: invokeinterface 220 1 0
    //   108: aload 21
    //   110: areturn
    //   111: aload 8
    //   113: iconst_1
    //   114: invokeinterface 602 2 0
    //   119: astore 11
    //   121: aload 11
    //   123: iconst_0
    //   124: aload 11
    //   126: arraylength
    //   127: invokestatic 608	com/google/android/gms/internal/measurement/zzxz:zzj	([BII)Lcom/google/android/gms/internal/measurement/zzxz;
    //   130: astore 12
    //   132: new 327	com/google/android/gms/internal/measurement/zzfj
    //   135: dup
    //   136: invokespecial 1458	com/google/android/gms/internal/measurement/zzfj:<init>	()V
    //   139: astore 13
    //   141: aload 13
    //   143: aload 12
    //   145: invokevirtual 614	com/google/android/gms/internal/measurement/zzyi:zza	(Lcom/google/android/gms/internal/measurement/zzxz;)Lcom/google/android/gms/internal/measurement/zzyi;
    //   148: pop
    //   149: aload 8
    //   151: iconst_0
    //   152: invokeinterface 1126 2 0
    //   157: istore 17
    //   159: aload 5
    //   161: iload 17
    //   163: invokestatic 259	java/lang/Integer:valueOf	(I)Ljava/lang/Integer;
    //   166: invokeinterface 1460 2 0
    //   171: checkcast 463	java/util/List
    //   174: astore 18
    //   176: aload 18
    //   178: ifnonnull +27 -> 205
    //   181: new 460	java/util/ArrayList
    //   184: dup
    //   185: invokespecial 461	java/util/ArrayList:<init>	()V
    //   188: astore 18
    //   190: aload 5
    //   192: iload 17
    //   194: invokestatic 259	java/lang/Integer:valueOf	(I)Ljava/lang/Integer;
    //   197: aload 18
    //   199: invokeinterface 1326 3 0
    //   204: pop
    //   205: aload 18
    //   207: aload 13
    //   209: invokeinterface 480 2 0
    //   214: pop
    //   215: aload 8
    //   217: invokeinterface 1129 1 0
    //   222: istore 15
    //   224: iload 15
    //   226: ifne -115 -> 111
    //   229: aload 8
    //   231: ifnull +10 -> 241
    //   234: aload 8
    //   236: invokeinterface 220 1 0
    //   241: aload 5
    //   243: areturn
    //   244: astore 14
    //   246: aload_0
    //   247: invokevirtual 229	com/google/android/gms/measurement/internal/zzcr:zzgt	()Lcom/google/android/gms/measurement/internal/zzas;
    //   250: invokevirtual 235	com/google/android/gms/measurement/internal/zzas:zzjg	()Lcom/google/android/gms/measurement/internal/zzau;
    //   253: ldc_w 1462
    //   256: aload_1
    //   257: invokestatic 346	com/google/android/gms/measurement/internal/zzas:zzbw	(Ljava/lang/String;)Ljava/lang/Object;
    //   260: aload 14
    //   262: invokevirtual 243	com/google/android/gms/measurement/internal/zzau:zze	(Ljava/lang/String;Ljava/lang/Object;Ljava/lang/Object;)V
    //   265: goto -50 -> 215
    //   268: astore 7
    //   270: aload_0
    //   271: invokevirtual 229	com/google/android/gms/measurement/internal/zzcr:zzgt	()Lcom/google/android/gms/measurement/internal/zzas;
    //   274: invokevirtual 235	com/google/android/gms/measurement/internal/zzas:zzjg	()Lcom/google/android/gms/measurement/internal/zzau;
    //   277: ldc_w 458
    //   280: aload_1
    //   281: invokestatic 346	com/google/android/gms/measurement/internal/zzas:zzbw	(Ljava/lang/String;)Ljava/lang/Object;
    //   284: aload 7
    //   286: invokevirtual 243	com/google/android/gms/measurement/internal/zzau:zze	(Ljava/lang/String;Ljava/lang/Object;Ljava/lang/Object;)V
    //   289: aload 8
    //   291: ifnull +10 -> 301
    //   294: aload 8
    //   296: invokeinterface 220 1 0
    //   301: aconst_null
    //   302: areturn
    //   303: astore 9
    //   305: aconst_null
    //   306: astore 8
    //   308: aload 8
    //   310: ifnull +10 -> 320
    //   313: aload 8
    //   315: invokeinterface 220 1 0
    //   320: aload 9
    //   322: athrow
    //   323: astore 9
    //   325: goto -17 -> 308
    //   328: astore 7
    //   330: aconst_null
    //   331: astore 8
    //   333: goto -63 -> 270
    //
    // Exception table:
    //   from	to	target	type
    //   141	149	244	java/io/IOException
    //   81	96	268	android/database/sqlite/SQLiteException
    //   111	141	268	android/database/sqlite/SQLiteException
    //   141	149	268	android/database/sqlite/SQLiteException
    //   149	176	268	android/database/sqlite/SQLiteException
    //   181	205	268	android/database/sqlite/SQLiteException
    //   205	215	268	android/database/sqlite/SQLiteException
    //   215	224	268	android/database/sqlite/SQLiteException
    //   246	265	268	android/database/sqlite/SQLiteException
    //   33	77	303	finally
    //   81	96	323	finally
    //   111	141	323	finally
    //   141	149	323	finally
    //   149	176	323	finally
    //   181	205	323	finally
    //   205	215	323	finally
    //   215	224	323	finally
    //   246	265	323	finally
    //   270	289	323	finally
    //   33	77	328	android/database/sqlite/SQLiteException
  }

  // ERROR //
  final java.util.Map<Integer, List<com.google.android.gms.internal.measurement.zzfm>> zzm(String paramString1, String paramString2)
  {
    // Byte code:
    //   0: aload_0
    //   1: invokevirtual 322	com/google/android/gms/measurement/internal/zzfm:zzcl	()V
    //   4: aload_0
    //   5: invokevirtual 325	com/google/android/gms/measurement/internal/zzcr:zzaf	()V
    //   8: aload_1
    //   9: invokestatic 295	com/google/android/gms/common/internal/Preconditions:checkNotEmpty	(Ljava/lang/String;)Ljava/lang/String;
    //   12: pop
    //   13: aload_2
    //   14: invokestatic 295	com/google/android/gms/common/internal/Preconditions:checkNotEmpty	(Ljava/lang/String;)Ljava/lang/String;
    //   17: pop
    //   18: new 1317	android/support/v4/util/ArrayMap
    //   21: dup
    //   22: invokespecial 1318	android/support/v4/util/ArrayMap:<init>	()V
    //   25: astore 5
    //   27: aload_0
    //   28: invokevirtual 201	com/google/android/gms/measurement/internal/zzt:getWritableDatabase	()Landroid/database/sqlite/SQLiteDatabase;
    //   31: astore 6
    //   33: aload 6
    //   35: ldc_w 420
    //   38: iconst_2
    //   39: anewarray 19	java/lang/String
    //   42: dup
    //   43: iconst_0
    //   44: ldc_w 381
    //   47: aastore
    //   48: dup
    //   49: iconst_1
    //   50: ldc_w 390
    //   53: aastore
    //   54: ldc_w 1465
    //   57: iconst_2
    //   58: anewarray 19	java/lang/String
    //   61: dup
    //   62: iconst_0
    //   63: aload_1
    //   64: aastore
    //   65: dup
    //   66: iconst_1
    //   67: aload_2
    //   68: aastore
    //   69: aconst_null
    //   70: aconst_null
    //   71: aconst_null
    //   72: invokevirtual 636	android/database/sqlite/SQLiteDatabase:query	(Ljava/lang/String;[Ljava/lang/String;Ljava/lang/String;[Ljava/lang/String;Ljava/lang/String;Ljava/lang/String;Ljava/lang/String;)Landroid/database/Cursor;
    //   75: astore 10
    //   77: aload 10
    //   79: astore 8
    //   81: aload 8
    //   83: invokeinterface 213 1 0
    //   88: ifne +23 -> 111
    //   91: invokestatic 1457	java/util/Collections:emptyMap	()Ljava/util/Map;
    //   94: astore 21
    //   96: aload 8
    //   98: ifnull +10 -> 108
    //   101: aload 8
    //   103: invokeinterface 220 1 0
    //   108: aload 21
    //   110: areturn
    //   111: aload 8
    //   113: iconst_1
    //   114: invokeinterface 602 2 0
    //   119: astore 11
    //   121: aload 11
    //   123: iconst_0
    //   124: aload 11
    //   126: arraylength
    //   127: invokestatic 608	com/google/android/gms/internal/measurement/zzxz:zzj	([BII)Lcom/google/android/gms/internal/measurement/zzxz;
    //   130: astore 12
    //   132: new 410	com/google/android/gms/internal/measurement/zzfm
    //   135: dup
    //   136: invokespecial 1466	com/google/android/gms/internal/measurement/zzfm:<init>	()V
    //   139: astore 13
    //   141: aload 13
    //   143: aload 12
    //   145: invokevirtual 614	com/google/android/gms/internal/measurement/zzyi:zza	(Lcom/google/android/gms/internal/measurement/zzxz;)Lcom/google/android/gms/internal/measurement/zzyi;
    //   148: pop
    //   149: aload 8
    //   151: iconst_0
    //   152: invokeinterface 1126 2 0
    //   157: istore 17
    //   159: aload 5
    //   161: iload 17
    //   163: invokestatic 259	java/lang/Integer:valueOf	(I)Ljava/lang/Integer;
    //   166: invokeinterface 1460 2 0
    //   171: checkcast 463	java/util/List
    //   174: astore 18
    //   176: aload 18
    //   178: ifnonnull +27 -> 205
    //   181: new 460	java/util/ArrayList
    //   184: dup
    //   185: invokespecial 461	java/util/ArrayList:<init>	()V
    //   188: astore 18
    //   190: aload 5
    //   192: iload 17
    //   194: invokestatic 259	java/lang/Integer:valueOf	(I)Ljava/lang/Integer;
    //   197: aload 18
    //   199: invokeinterface 1326 3 0
    //   204: pop
    //   205: aload 18
    //   207: aload 13
    //   209: invokeinterface 480 2 0
    //   214: pop
    //   215: aload 8
    //   217: invokeinterface 1129 1 0
    //   222: istore 15
    //   224: iload 15
    //   226: ifne -115 -> 111
    //   229: aload 8
    //   231: ifnull +10 -> 241
    //   234: aload 8
    //   236: invokeinterface 220 1 0
    //   241: aload 5
    //   243: areturn
    //   244: astore 14
    //   246: aload_0
    //   247: invokevirtual 229	com/google/android/gms/measurement/internal/zzcr:zzgt	()Lcom/google/android/gms/measurement/internal/zzas;
    //   250: invokevirtual 235	com/google/android/gms/measurement/internal/zzas:zzjg	()Lcom/google/android/gms/measurement/internal/zzau;
    //   253: ldc_w 1468
    //   256: aload_1
    //   257: invokestatic 346	com/google/android/gms/measurement/internal/zzas:zzbw	(Ljava/lang/String;)Ljava/lang/Object;
    //   260: aload 14
    //   262: invokevirtual 243	com/google/android/gms/measurement/internal/zzau:zze	(Ljava/lang/String;Ljava/lang/Object;Ljava/lang/Object;)V
    //   265: goto -50 -> 215
    //   268: astore 7
    //   270: aload_0
    //   271: invokevirtual 229	com/google/android/gms/measurement/internal/zzcr:zzgt	()Lcom/google/android/gms/measurement/internal/zzas;
    //   274: invokevirtual 235	com/google/android/gms/measurement/internal/zzas:zzjg	()Lcom/google/android/gms/measurement/internal/zzau;
    //   277: ldc_w 458
    //   280: aload_1
    //   281: invokestatic 346	com/google/android/gms/measurement/internal/zzas:zzbw	(Ljava/lang/String;)Ljava/lang/Object;
    //   284: aload 7
    //   286: invokevirtual 243	com/google/android/gms/measurement/internal/zzau:zze	(Ljava/lang/String;Ljava/lang/Object;Ljava/lang/Object;)V
    //   289: aload 8
    //   291: ifnull +10 -> 301
    //   294: aload 8
    //   296: invokeinterface 220 1 0
    //   301: aconst_null
    //   302: areturn
    //   303: astore 9
    //   305: aconst_null
    //   306: astore 8
    //   308: aload 8
    //   310: ifnull +10 -> 320
    //   313: aload 8
    //   315: invokeinterface 220 1 0
    //   320: aload 9
    //   322: athrow
    //   323: astore 9
    //   325: goto -17 -> 308
    //   328: astore 7
    //   330: aconst_null
    //   331: astore 8
    //   333: goto -63 -> 270
    //
    // Exception table:
    //   from	to	target	type
    //   141	149	244	java/io/IOException
    //   81	96	268	android/database/sqlite/SQLiteException
    //   111	141	268	android/database/sqlite/SQLiteException
    //   141	149	268	android/database/sqlite/SQLiteException
    //   149	176	268	android/database/sqlite/SQLiteException
    //   181	205	268	android/database/sqlite/SQLiteException
    //   205	215	268	android/database/sqlite/SQLiteException
    //   215	224	268	android/database/sqlite/SQLiteException
    //   246	265	268	android/database/sqlite/SQLiteException
    //   33	77	303	finally
    //   81	96	323	finally
    //   111	141	323	finally
    //   141	149	323	finally
    //   149	176	323	finally
    //   181	205	323	finally
    //   205	215	323	finally
    //   215	224	323	finally
    //   246	265	323	finally
    //   270	289	323	finally
    //   33	77	328	android/database/sqlite/SQLiteException
  }

  // ERROR //
  @VisibleForTesting
  protected final long zzn(String paramString1, String paramString2)
  {
    // Byte code:
    //   0: aload_1
    //   1: invokestatic 295	com/google/android/gms/common/internal/Preconditions:checkNotEmpty	(Ljava/lang/String;)Ljava/lang/String;
    //   4: pop
    //   5: aload_2
    //   6: invokestatic 295	com/google/android/gms/common/internal/Preconditions:checkNotEmpty	(Ljava/lang/String;)Ljava/lang/String;
    //   9: pop
    //   10: aload_0
    //   11: invokevirtual 325	com/google/android/gms/measurement/internal/zzcr:zzaf	()V
    //   14: aload_0
    //   15: invokevirtual 322	com/google/android/gms/measurement/internal/zzfm:zzcl	()V
    //   18: aload_0
    //   19: invokevirtual 201	com/google/android/gms/measurement/internal/zzt:getWritableDatabase	()Landroid/database/sqlite/SQLiteDatabase;
    //   22: astore 5
    //   24: aload 5
    //   26: invokevirtual 537	android/database/sqlite/SQLiteDatabase:beginTransaction	()V
    //   29: aload_0
    //   30: new 488	java/lang/StringBuilder
    //   33: dup
    //   34: bipush 32
    //   36: aload_2
    //   37: invokestatic 353	java/lang/String:valueOf	(Ljava/lang/Object;)Ljava/lang/String;
    //   40: invokevirtual 491	java/lang/String:length	()I
    //   43: iadd
    //   44: invokespecial 494	java/lang/StringBuilder:<init>	(I)V
    //   47: ldc_w 1472
    //   50: invokevirtual 500	java/lang/StringBuilder:append	(Ljava/lang/String;)Ljava/lang/StringBuilder;
    //   53: aload_2
    //   54: invokevirtual 500	java/lang/StringBuilder:append	(Ljava/lang/String;)Ljava/lang/StringBuilder;
    //   57: ldc_w 1474
    //   60: invokevirtual 500	java/lang/StringBuilder:append	(Ljava/lang/String;)Ljava/lang/StringBuilder;
    //   63: invokevirtual 505	java/lang/StringBuilder:toString	()Ljava/lang/String;
    //   66: iconst_1
    //   67: anewarray 19	java/lang/String
    //   70: dup
    //   71: iconst_0
    //   72: aload_1
    //   73: aastore
    //   74: ldc2_w 400
    //   77: invokespecial 1335	com/google/android/gms/measurement/internal/zzt:zza	(Ljava/lang/String;[Ljava/lang/String;J)J
    //   80: lstore 9
    //   82: lload 9
    //   84: ldc2_w 400
    //   87: lcmp
    //   88: ifne +93 -> 181
    //   91: new 301	android/content/ContentValues
    //   94: dup
    //   95: invokespecial 377	android/content/ContentValues:<init>	()V
    //   98: astore 11
    //   100: aload 11
    //   102: ldc_w 379
    //   105: aload_1
    //   106: invokevirtual 305	android/content/ContentValues:put	(Ljava/lang/String;Ljava/lang/String;)V
    //   109: aload 11
    //   111: ldc_w 1476
    //   114: iconst_0
    //   115: invokestatic 259	java/lang/Integer:valueOf	(I)Ljava/lang/Integer;
    //   118: invokevirtual 384	android/content/ContentValues:put	(Ljava/lang/String;Ljava/lang/Integer;)V
    //   121: aload 11
    //   123: ldc 159
    //   125: iconst_0
    //   126: invokestatic 259	java/lang/Integer:valueOf	(I)Ljava/lang/Integer;
    //   129: invokevirtual 384	android/content/ContentValues:put	(Ljava/lang/String;Ljava/lang/Integer;)V
    //   132: aload 5
    //   134: ldc_w 1478
    //   137: aconst_null
    //   138: aload 11
    //   140: iconst_5
    //   141: invokevirtual 399	android/database/sqlite/SQLiteDatabase:insertWithOnConflict	(Ljava/lang/String;Ljava/lang/String;Landroid/content/ContentValues;I)J
    //   144: ldc2_w 400
    //   147: lcmp
    //   148: ifne +30 -> 178
    //   151: aload_0
    //   152: invokevirtual 229	com/google/android/gms/measurement/internal/zzcr:zzgt	()Lcom/google/android/gms/measurement/internal/zzas;
    //   155: invokevirtual 235	com/google/android/gms/measurement/internal/zzas:zzjg	()Lcom/google/android/gms/measurement/internal/zzau;
    //   158: ldc_w 1480
    //   161: aload_1
    //   162: invokestatic 346	com/google/android/gms/measurement/internal/zzas:zzbw	(Ljava/lang/String;)Ljava/lang/Object;
    //   165: aload_2
    //   166: invokevirtual 243	com/google/android/gms/measurement/internal/zzau:zze	(Ljava/lang/String;Ljava/lang/Object;Ljava/lang/Object;)V
    //   169: aload 5
    //   171: invokevirtual 540	android/database/sqlite/SQLiteDatabase:endTransaction	()V
    //   174: ldc2_w 400
    //   177: lreturn
    //   178: lconst_0
    //   179: lstore 9
    //   181: new 301	android/content/ContentValues
    //   184: dup
    //   185: invokespecial 377	android/content/ContentValues:<init>	()V
    //   188: astore 12
    //   190: aload 12
    //   192: ldc_w 379
    //   195: aload_1
    //   196: invokevirtual 305	android/content/ContentValues:put	(Ljava/lang/String;Ljava/lang/String;)V
    //   199: aload 12
    //   201: aload_2
    //   202: lconst_1
    //   203: lload 9
    //   205: ladd
    //   206: invokestatic 273	java/lang/Long:valueOf	(J)Ljava/lang/Long;
    //   209: invokevirtual 308	android/content/ContentValues:put	(Ljava/lang/String;Ljava/lang/Long;)V
    //   212: aload 5
    //   214: ldc_w 1478
    //   217: aload 12
    //   219: ldc_w 814
    //   222: iconst_1
    //   223: anewarray 19	java/lang/String
    //   226: dup
    //   227: iconst_0
    //   228: aload_1
    //   229: aastore
    //   230: invokevirtual 658	android/database/sqlite/SQLiteDatabase:update	(Ljava/lang/String;Landroid/content/ContentValues;Ljava/lang/String;[Ljava/lang/String;)I
    //   233: i2l
    //   234: lconst_0
    //   235: lcmp
    //   236: ifne +30 -> 266
    //   239: aload_0
    //   240: invokevirtual 229	com/google/android/gms/measurement/internal/zzcr:zzgt	()Lcom/google/android/gms/measurement/internal/zzas;
    //   243: invokevirtual 235	com/google/android/gms/measurement/internal/zzas:zzjg	()Lcom/google/android/gms/measurement/internal/zzau;
    //   246: ldc_w 1482
    //   249: aload_1
    //   250: invokestatic 346	com/google/android/gms/measurement/internal/zzas:zzbw	(Ljava/lang/String;)Ljava/lang/Object;
    //   253: aload_2
    //   254: invokevirtual 243	com/google/android/gms/measurement/internal/zzau:zze	(Ljava/lang/String;Ljava/lang/Object;Ljava/lang/Object;)V
    //   257: aload 5
    //   259: invokevirtual 540	android/database/sqlite/SQLiteDatabase:endTransaction	()V
    //   262: ldc2_w 400
    //   265: lreturn
    //   266: aload 5
    //   268: invokevirtual 546	android/database/sqlite/SQLiteDatabase:setTransactionSuccessful	()V
    //   271: aload 5
    //   273: invokevirtual 540	android/database/sqlite/SQLiteDatabase:endTransaction	()V
    //   276: lload 9
    //   278: lreturn
    //   279: astore 7
    //   281: aload 7
    //   283: astore 8
    //   285: lconst_0
    //   286: lstore 9
    //   288: aload_0
    //   289: invokevirtual 229	com/google/android/gms/measurement/internal/zzcr:zzgt	()Lcom/google/android/gms/measurement/internal/zzas;
    //   292: invokevirtual 235	com/google/android/gms/measurement/internal/zzas:zzjg	()Lcom/google/android/gms/measurement/internal/zzau;
    //   295: ldc_w 1484
    //   298: aload_1
    //   299: invokestatic 346	com/google/android/gms/measurement/internal/zzas:zzbw	(Ljava/lang/String;)Ljava/lang/Object;
    //   302: aload_2
    //   303: aload 8
    //   305: invokevirtual 357	com/google/android/gms/measurement/internal/zzau:zzd	(Ljava/lang/String;Ljava/lang/Object;Ljava/lang/Object;Ljava/lang/Object;)V
    //   308: aload 5
    //   310: invokevirtual 540	android/database/sqlite/SQLiteDatabase:endTransaction	()V
    //   313: lload 9
    //   315: lreturn
    //   316: astore 6
    //   318: aload 5
    //   320: invokevirtual 540	android/database/sqlite/SQLiteDatabase:endTransaction	()V
    //   323: aload 6
    //   325: athrow
    //   326: astore 8
    //   328: goto -40 -> 288
    //
    // Exception table:
    //   from	to	target	type
    //   29	82	279	android/database/sqlite/SQLiteException
    //   91	169	279	android/database/sqlite/SQLiteException
    //   29	82	316	finally
    //   91	169	316	finally
    //   181	257	316	finally
    //   266	271	316	finally
    //   288	308	316	finally
    //   181	257	326	android/database/sqlite/SQLiteException
    //   266	271	326	android/database/sqlite/SQLiteException
  }
}

/* Location:           E:\Study\Tools\apktool2_2\dex2jar-0.0.9.15\classes_viber_2_dex2jar.jar
 * Qualified Name:     com.google.android.gms.measurement.internal.zzt
 * JD-Core Version:    0.6.2
 */