package com.my.target;

public class ac
{
  // ERROR //
  java.lang.String a(java.net.HttpCookie paramHttpCookie)
  {
    // Byte code:
    //   0: new 18	org/json/JSONObject
    //   3: dup
    //   4: invokespecial 19	org/json/JSONObject:<init>	()V
    //   7: astore_2
    //   8: aload_2
    //   9: ldc 21
    //   11: aload_1
    //   12: invokevirtual 27	java/net/HttpCookie:getName	()Ljava/lang/String;
    //   15: invokevirtual 31	org/json/JSONObject:putOpt	(Ljava/lang/String;Ljava/lang/Object;)Lorg/json/JSONObject;
    //   18: pop
    //   19: aload_2
    //   20: ldc 33
    //   22: aload_1
    //   23: invokevirtual 36	java/net/HttpCookie:getValue	()Ljava/lang/String;
    //   26: invokevirtual 31	org/json/JSONObject:putOpt	(Ljava/lang/String;Ljava/lang/Object;)Lorg/json/JSONObject;
    //   29: pop
    //   30: aload_2
    //   31: ldc 38
    //   33: aload_1
    //   34: invokevirtual 41	java/net/HttpCookie:getComment	()Ljava/lang/String;
    //   37: invokevirtual 31	org/json/JSONObject:putOpt	(Ljava/lang/String;Ljava/lang/Object;)Lorg/json/JSONObject;
    //   40: pop
    //   41: aload_2
    //   42: ldc 43
    //   44: aload_1
    //   45: invokevirtual 46	java/net/HttpCookie:getCommentURL	()Ljava/lang/String;
    //   48: invokevirtual 31	org/json/JSONObject:putOpt	(Ljava/lang/String;Ljava/lang/Object;)Lorg/json/JSONObject;
    //   51: pop
    //   52: aload_2
    //   53: ldc 48
    //   55: aload_1
    //   56: invokevirtual 51	java/net/HttpCookie:getDomain	()Ljava/lang/String;
    //   59: invokevirtual 31	org/json/JSONObject:putOpt	(Ljava/lang/String;Ljava/lang/Object;)Lorg/json/JSONObject;
    //   62: pop
    //   63: aload_2
    //   64: ldc 53
    //   66: aload_1
    //   67: invokevirtual 57	java/net/HttpCookie:getMaxAge	()J
    //   70: invokestatic 63	java/lang/Long:valueOf	(J)Ljava/lang/Long;
    //   73: invokevirtual 31	org/json/JSONObject:putOpt	(Ljava/lang/String;Ljava/lang/Object;)Lorg/json/JSONObject;
    //   76: pop
    //   77: aload_2
    //   78: ldc 65
    //   80: aload_1
    //   81: invokevirtual 68	java/net/HttpCookie:getPath	()Ljava/lang/String;
    //   84: invokevirtual 31	org/json/JSONObject:putOpt	(Ljava/lang/String;Ljava/lang/Object;)Lorg/json/JSONObject;
    //   87: pop
    //   88: aload_2
    //   89: ldc 70
    //   91: aload_1
    //   92: invokevirtual 73	java/net/HttpCookie:getPortlist	()Ljava/lang/String;
    //   95: invokevirtual 31	org/json/JSONObject:putOpt	(Ljava/lang/String;Ljava/lang/Object;)Lorg/json/JSONObject;
    //   98: pop
    //   99: aload_2
    //   100: ldc 75
    //   102: aload_1
    //   103: invokevirtual 79	java/net/HttpCookie:getVersion	()I
    //   106: invokestatic 84	java/lang/Integer:valueOf	(I)Ljava/lang/Integer;
    //   109: invokevirtual 31	org/json/JSONObject:putOpt	(Ljava/lang/String;Ljava/lang/Object;)Lorg/json/JSONObject;
    //   112: pop
    //   113: aload_2
    //   114: ldc 86
    //   116: aload_1
    //   117: invokevirtual 90	java/net/HttpCookie:getSecure	()Z
    //   120: invokestatic 95	java/lang/Boolean:valueOf	(Z)Ljava/lang/Boolean;
    //   123: invokevirtual 31	org/json/JSONObject:putOpt	(Ljava/lang/String;Ljava/lang/Object;)Lorg/json/JSONObject;
    //   126: pop
    //   127: aload_2
    //   128: ldc 97
    //   130: aload_1
    //   131: invokevirtual 100	java/net/HttpCookie:getDiscard	()Z
    //   134: invokestatic 95	java/lang/Boolean:valueOf	(Z)Ljava/lang/Boolean;
    //   137: invokevirtual 31	org/json/JSONObject:putOpt	(Ljava/lang/String;Ljava/lang/Object;)Lorg/json/JSONObject;
    //   140: pop
    //   141: getstatic 106	android/os/Build$VERSION:SDK_INT	I
    //   144: bipush 24
    //   146: if_icmplt +26 -> 172
    //   149: aload_2
    //   150: ldc 108
    //   152: aload_1
    //   153: invokevirtual 111	java/net/HttpCookie:isHttpOnly	()Z
    //   156: invokestatic 95	java/lang/Boolean:valueOf	(Z)Ljava/lang/Boolean;
    //   159: invokevirtual 31	org/json/JSONObject:putOpt	(Ljava/lang/String;Ljava/lang/Object;)Lorg/json/JSONObject;
    //   162: pop
    //   163: aload_2
    //   164: invokevirtual 114	org/json/JSONObject:toString	()Ljava/lang/String;
    //   167: astore 16
    //   169: aload 16
    //   171: areturn
    //   172: aload_1
    //   173: invokevirtual 118	java/lang/Object:getClass	()Ljava/lang/Class;
    //   176: ldc 108
    //   178: invokevirtual 124	java/lang/Class:getDeclaredField	(Ljava/lang/String;)Ljava/lang/reflect/Field;
    //   181: astore 18
    //   183: aload 18
    //   185: iconst_1
    //   186: invokevirtual 130	java/lang/reflect/Field:setAccessible	(Z)V
    //   189: aload_2
    //   190: ldc 108
    //   192: aload 18
    //   194: aload_1
    //   195: invokevirtual 134	java/lang/reflect/Field:get	(Ljava/lang/Object;)Ljava/lang/Object;
    //   198: invokevirtual 31	org/json/JSONObject:putOpt	(Ljava/lang/String;Ljava/lang/Object;)Lorg/json/JSONObject;
    //   201: pop
    //   202: goto -39 -> 163
    //   205: astore 17
    //   207: goto -44 -> 163
    //   210: astore_3
    //   211: new 136	java/lang/StringBuilder
    //   214: dup
    //   215: invokespecial 137	java/lang/StringBuilder:<init>	()V
    //   218: ldc 139
    //   220: invokevirtual 143	java/lang/StringBuilder:append	(Ljava/lang/String;)Ljava/lang/StringBuilder;
    //   223: aload_3
    //   224: invokevirtual 146	org/json/JSONException:getMessage	()Ljava/lang/String;
    //   227: invokevirtual 143	java/lang/StringBuilder:append	(Ljava/lang/String;)Ljava/lang/StringBuilder;
    //   230: invokevirtual 147	java/lang/StringBuilder:toString	()Ljava/lang/String;
    //   233: invokestatic 152	com/my/target/dp:a	(Ljava/lang/String;)V
    //   236: aconst_null
    //   237: areturn
    //   238: astore 15
    //   240: goto -77 -> 163
    //
    // Exception table:
    //   from	to	target	type
    //   172	202	205	java/lang/NoSuchFieldException
    //   8	163	210	org/json/JSONException
    //   163	169	210	org/json/JSONException
    //   172	202	210	org/json/JSONException
    //   172	202	238	java/lang/IllegalAccessException
  }

  // ERROR //
  java.net.HttpCookie a(java.lang.String paramString)
  {
    // Byte code:
    //   0: new 18	org/json/JSONObject
    //   3: dup
    //   4: aload_1
    //   5: invokespecial 155	org/json/JSONObject:<init>	(Ljava/lang/String;)V
    //   8: astore_2
    //   9: new 23	java/net/HttpCookie
    //   12: dup
    //   13: aload_2
    //   14: ldc 21
    //   16: invokevirtual 159	org/json/JSONObject:getString	(Ljava/lang/String;)Ljava/lang/String;
    //   19: aload_2
    //   20: ldc 33
    //   22: invokevirtual 159	org/json/JSONObject:getString	(Ljava/lang/String;)Ljava/lang/String;
    //   25: invokespecial 162	java/net/HttpCookie:<init>	(Ljava/lang/String;Ljava/lang/String;)V
    //   28: astore_3
    //   29: aload_3
    //   30: aload_2
    //   31: ldc 38
    //   33: invokevirtual 159	org/json/JSONObject:getString	(Ljava/lang/String;)Ljava/lang/String;
    //   36: invokevirtual 165	java/net/HttpCookie:setComment	(Ljava/lang/String;)V
    //   39: aload_3
    //   40: aload_2
    //   41: ldc 43
    //   43: invokevirtual 159	org/json/JSONObject:getString	(Ljava/lang/String;)Ljava/lang/String;
    //   46: invokevirtual 168	java/net/HttpCookie:setCommentURL	(Ljava/lang/String;)V
    //   49: aload_3
    //   50: aload_2
    //   51: ldc 48
    //   53: invokevirtual 159	org/json/JSONObject:getString	(Ljava/lang/String;)Ljava/lang/String;
    //   56: invokevirtual 171	java/net/HttpCookie:setDomain	(Ljava/lang/String;)V
    //   59: aload_3
    //   60: aload_2
    //   61: ldc 53
    //   63: invokevirtual 175	org/json/JSONObject:getInt	(Ljava/lang/String;)I
    //   66: i2l
    //   67: invokevirtual 179	java/net/HttpCookie:setMaxAge	(J)V
    //   70: aload_3
    //   71: aload_2
    //   72: ldc 65
    //   74: invokevirtual 159	org/json/JSONObject:getString	(Ljava/lang/String;)Ljava/lang/String;
    //   77: invokevirtual 182	java/net/HttpCookie:setPath	(Ljava/lang/String;)V
    //   80: aload_3
    //   81: aload_2
    //   82: ldc 70
    //   84: invokevirtual 159	org/json/JSONObject:getString	(Ljava/lang/String;)Ljava/lang/String;
    //   87: invokevirtual 185	java/net/HttpCookie:setPortlist	(Ljava/lang/String;)V
    //   90: aload_3
    //   91: aload_2
    //   92: ldc 75
    //   94: invokevirtual 175	org/json/JSONObject:getInt	(Ljava/lang/String;)I
    //   97: invokevirtual 189	java/net/HttpCookie:setVersion	(I)V
    //   100: aload_3
    //   101: aload_2
    //   102: ldc 86
    //   104: invokevirtual 193	org/json/JSONObject:getBoolean	(Ljava/lang/String;)Z
    //   107: invokevirtual 196	java/net/HttpCookie:setSecure	(Z)V
    //   110: aload_3
    //   111: aload_2
    //   112: ldc 97
    //   114: invokevirtual 193	org/json/JSONObject:getBoolean	(Ljava/lang/String;)Z
    //   117: invokevirtual 199	java/net/HttpCookie:setDiscard	(Z)V
    //   120: getstatic 106	android/os/Build$VERSION:SDK_INT	I
    //   123: bipush 24
    //   125: if_icmplt +15 -> 140
    //   128: aload_3
    //   129: aload_2
    //   130: ldc 108
    //   132: invokevirtual 193	org/json/JSONObject:getBoolean	(Ljava/lang/String;)Z
    //   135: invokevirtual 202	java/net/HttpCookie:setHttpOnly	(Z)V
    //   138: aload_3
    //   139: areturn
    //   140: aload_3
    //   141: invokevirtual 118	java/lang/Object:getClass	()Ljava/lang/Class;
    //   144: ldc 108
    //   146: invokevirtual 124	java/lang/Class:getDeclaredField	(Ljava/lang/String;)Ljava/lang/reflect/Field;
    //   149: astore 7
    //   151: aload 7
    //   153: iconst_1
    //   154: invokevirtual 130	java/lang/reflect/Field:setAccessible	(Z)V
    //   157: aload 7
    //   159: aload_3
    //   160: aload_2
    //   161: ldc 108
    //   163: invokevirtual 193	org/json/JSONObject:getBoolean	(Ljava/lang/String;)Z
    //   166: invokestatic 95	java/lang/Boolean:valueOf	(Z)Ljava/lang/Boolean;
    //   169: invokevirtual 206	java/lang/reflect/Field:set	(Ljava/lang/Object;Ljava/lang/Object;)V
    //   172: aload_3
    //   173: areturn
    //   174: astore 6
    //   176: aload_3
    //   177: areturn
    //   178: astore 8
    //   180: aconst_null
    //   181: astore_3
    //   182: aload 8
    //   184: astore 4
    //   186: new 136	java/lang/StringBuilder
    //   189: dup
    //   190: invokespecial 137	java/lang/StringBuilder:<init>	()V
    //   193: ldc 208
    //   195: invokevirtual 143	java/lang/StringBuilder:append	(Ljava/lang/String;)Ljava/lang/StringBuilder;
    //   198: aload 4
    //   200: invokevirtual 146	org/json/JSONException:getMessage	()Ljava/lang/String;
    //   203: invokevirtual 143	java/lang/StringBuilder:append	(Ljava/lang/String;)Ljava/lang/StringBuilder;
    //   206: invokevirtual 147	java/lang/StringBuilder:toString	()Ljava/lang/String;
    //   209: invokestatic 152	com/my/target/dp:a	(Ljava/lang/String;)V
    //   212: aload_3
    //   213: areturn
    //   214: astore 4
    //   216: goto -30 -> 186
    //   219: astore 5
    //   221: aload_3
    //   222: areturn
    //
    // Exception table:
    //   from	to	target	type
    //   140	172	174	java/lang/NoSuchFieldException
    //   0	29	178	org/json/JSONException
    //   29	138	214	org/json/JSONException
    //   140	172	214	org/json/JSONException
    //   140	172	219	java/lang/IllegalAccessException
  }
}

/* Location:           E:\Study\Tools\apktool2_2\dex2jar-0.0.9.15\classes_viber_2_dex2jar.jar
 * Qualified Name:     com.my.target.ac
 * JD-Core Version:    0.6.2
 */