package com.google.a.a.b.b;

import com.google.a.a.c.t;
import com.google.a.a.c.t.a;

public class b extends t
{
  private final transient a a;

  public b(t.a parama, a parama1)
  {
    super(parama);
    this.a = parama1;
  }

  // ERROR //
  public static b a(com.google.a.a.d.c paramc, com.google.a.a.c.s params)
  {
    // Byte code:
    //   0: new 18	com/google/a/a/c/t$a
    //   3: dup
    //   4: aload_1
    //   5: invokevirtual 24	com/google/a/a/c/s:d	()I
    //   8: aload_1
    //   9: invokevirtual 28	com/google/a/a/c/s:e	()Ljava/lang/String;
    //   12: aload_1
    //   13: invokevirtual 32	com/google/a/a/c/s:b	()Lcom/google/a/a/c/m;
    //   16: invokespecial 35	com/google/a/a/c/t$a:<init>	(ILjava/lang/String;Lcom/google/a/a/c/m;)V
    //   19: astore_2
    //   20: aload_0
    //   21: invokestatic 40	com/google/a/a/f/z:a	(Ljava/lang/Object;)Ljava/lang/Object;
    //   24: pop
    //   25: aload_1
    //   26: invokevirtual 44	com/google/a/a/c/s:c	()Z
    //   29: ifne +286 -> 315
    //   32: ldc 46
    //   34: aload_1
    //   35: invokevirtual 48	com/google/a/a/c/s:a	()Ljava/lang/String;
    //   38: invokestatic 53	com/google/a/a/c/o:b	(Ljava/lang/String;Ljava/lang/String;)Z
    //   41: ifeq +274 -> 315
    //   44: aload_1
    //   45: invokevirtual 57	com/google/a/a/c/s:g	()Ljava/io/InputStream;
    //   48: astore 13
    //   50: aload 13
    //   52: ifnull +263 -> 315
    //   55: aload_0
    //   56: aload_1
    //   57: invokevirtual 57	com/google/a/a/c/s:g	()Ljava/io/InputStream;
    //   60: invokevirtual 62	com/google/a/a/d/c:a	(Ljava/io/InputStream;)Lcom/google/a/a/d/f;
    //   63: astore 22
    //   65: aload 22
    //   67: astore 15
    //   69: aload 15
    //   71: invokevirtual 67	com/google/a/a/d/f:d	()Lcom/google/a/a/d/i;
    //   74: astore 24
    //   76: aload 24
    //   78: ifnonnull +10 -> 88
    //   81: aload 15
    //   83: invokevirtual 69	com/google/a/a/d/f:c	()Lcom/google/a/a/d/i;
    //   86: astore 24
    //   88: aload 24
    //   90: ifnull +316 -> 406
    //   93: aload 15
    //   95: ldc 71
    //   97: invokevirtual 74	com/google/a/a/d/f:a	(Ljava/lang/String;)V
    //   100: aload 15
    //   102: invokevirtual 67	com/google/a/a/d/f:d	()Lcom/google/a/a/d/i;
    //   105: getstatic 79	com/google/a/a/d/i:d	Lcom/google/a/a/d/i;
    //   108: if_acmpeq +298 -> 406
    //   111: aload 15
    //   113: ldc 81
    //   115: invokevirtual 84	com/google/a/a/d/f:a	(Ljava/lang/Class;)Ljava/lang/Object;
    //   118: checkcast 81	com/google/a/a/b/b/a
    //   121: astore 20
    //   123: aload 20
    //   125: invokevirtual 86	com/google/a/a/b/b/a:d	()Ljava/lang/String;
    //   128: astore 25
    //   130: aload 20
    //   132: astore 7
    //   134: aload 25
    //   136: astore 6
    //   138: aload 15
    //   140: ifnonnull +63 -> 203
    //   143: aload_1
    //   144: invokevirtual 90	com/google/a/a/c/s:h	()V
    //   147: aload_1
    //   148: invokestatic 93	com/google/a/a/c/t:a	(Lcom/google/a/a/c/s;)Ljava/lang/StringBuilder;
    //   151: astore 8
    //   153: aload 6
    //   155: invokestatic 98	com/google/a/a/f/ae:a	(Ljava/lang/String;)Z
    //   158: ifne +24 -> 182
    //   161: aload 8
    //   163: getstatic 103	com/google/a/a/f/ad:a	Ljava/lang/String;
    //   166: invokevirtual 109	java/lang/StringBuilder:append	(Ljava/lang/String;)Ljava/lang/StringBuilder;
    //   169: aload 6
    //   171: invokevirtual 109	java/lang/StringBuilder:append	(Ljava/lang/String;)Ljava/lang/StringBuilder;
    //   174: pop
    //   175: aload_2
    //   176: aload 6
    //   178: invokevirtual 112	com/google/a/a/c/t$a:c	(Ljava/lang/String;)Lcom/google/a/a/c/t$a;
    //   181: pop
    //   182: aload_2
    //   183: aload 8
    //   185: invokevirtual 115	java/lang/StringBuilder:toString	()Ljava/lang/String;
    //   188: invokevirtual 117	com/google/a/a/c/t$a:a	(Ljava/lang/String;)Lcom/google/a/a/c/t$a;
    //   191: pop
    //   192: new 2	com/google/a/a/b/b/b
    //   195: dup
    //   196: aload_2
    //   197: aload 7
    //   199: invokespecial 119	com/google/a/a/b/b/b:<init>	(Lcom/google/a/a/c/t$a;Lcom/google/a/a/b/b/a;)V
    //   202: areturn
    //   203: aload 7
    //   205: ifnonnull -58 -> 147
    //   208: aload 15
    //   210: invokevirtual 121	com/google/a/a/d/f:b	()V
    //   213: goto -66 -> 147
    //   216: astore 5
    //   218: aload 5
    //   220: invokevirtual 124	java/io/IOException:printStackTrace	()V
    //   223: goto -76 -> 147
    //   226: astore 18
    //   228: aload 18
    //   230: astore 19
    //   232: aconst_null
    //   233: astore 15
    //   235: aconst_null
    //   236: astore 20
    //   238: aload 19
    //   240: invokevirtual 124	java/io/IOException:printStackTrace	()V
    //   243: aload 15
    //   245: ifnonnull +17 -> 262
    //   248: aload_1
    //   249: invokevirtual 90	com/google/a/a/c/s:h	()V
    //   252: aload 20
    //   254: astore 7
    //   256: aconst_null
    //   257: astore 6
    //   259: goto -112 -> 147
    //   262: aload 20
    //   264: ifnonnull +132 -> 396
    //   267: aload 15
    //   269: invokevirtual 121	com/google/a/a/d/f:b	()V
    //   272: aload 20
    //   274: astore 7
    //   276: aconst_null
    //   277: astore 6
    //   279: goto -132 -> 147
    //   282: astore 14
    //   284: aconst_null
    //   285: astore 15
    //   287: aconst_null
    //   288: astore 16
    //   290: aload 15
    //   292: ifnonnull +10 -> 302
    //   295: aload_1
    //   296: invokevirtual 90	com/google/a/a/c/s:h	()V
    //   299: aload 14
    //   301: athrow
    //   302: aload 16
    //   304: ifnonnull -5 -> 299
    //   307: aload 15
    //   309: invokevirtual 121	com/google/a/a/d/f:b	()V
    //   312: goto -13 -> 299
    //   315: aload_1
    //   316: invokevirtual 127	com/google/a/a/c/s:j	()Ljava/lang/String;
    //   319: astore 12
    //   321: aload 12
    //   323: astore 6
    //   325: aconst_null
    //   326: astore 7
    //   328: goto -181 -> 147
    //   331: astore 4
    //   333: aload 4
    //   335: astore 5
    //   337: aconst_null
    //   338: astore 6
    //   340: aconst_null
    //   341: astore 7
    //   343: goto -125 -> 218
    //   346: astore 5
    //   348: aload 20
    //   350: astore 7
    //   352: aconst_null
    //   353: astore 6
    //   355: goto -137 -> 218
    //   358: astore 14
    //   360: aconst_null
    //   361: astore 16
    //   363: goto -73 -> 290
    //   366: astore 21
    //   368: aload 20
    //   370: astore 16
    //   372: aload 21
    //   374: astore 14
    //   376: goto -86 -> 290
    //   379: astore 23
    //   381: aload 23
    //   383: astore 19
    //   385: aconst_null
    //   386: astore 20
    //   388: goto -150 -> 238
    //   391: astore 19
    //   393: goto -155 -> 238
    //   396: aload 20
    //   398: astore 7
    //   400: aconst_null
    //   401: astore 6
    //   403: goto -256 -> 147
    //   406: aconst_null
    //   407: astore 6
    //   409: aconst_null
    //   410: astore 7
    //   412: goto -274 -> 138
    //   415: astore 17
    //   417: aload 16
    //   419: astore 7
    //   421: aload 17
    //   423: astore 5
    //   425: aconst_null
    //   426: astore 6
    //   428: goto -210 -> 218
    //
    // Exception table:
    //   from	to	target	type
    //   143	147	216	java/io/IOException
    //   208	213	216	java/io/IOException
    //   55	65	226	java/io/IOException
    //   55	65	282	finally
    //   25	50	331	java/io/IOException
    //   315	321	331	java/io/IOException
    //   248	252	346	java/io/IOException
    //   267	272	346	java/io/IOException
    //   69	76	358	finally
    //   81	88	358	finally
    //   93	123	358	finally
    //   123	130	366	finally
    //   238	243	366	finally
    //   69	76	379	java/io/IOException
    //   81	88	379	java/io/IOException
    //   93	123	379	java/io/IOException
    //   123	130	391	java/io/IOException
    //   295	299	415	java/io/IOException
    //   299	302	415	java/io/IOException
    //   307	312	415	java/io/IOException
  }
}

/* Location:           E:\Study\Tools\apktool2_2\dex2jar-0.0.9.15\classes_viber_dex2jar.jar
 * Qualified Name:     com.google.a.a.b.b.b
 * JD-Core Version:    0.6.2
 */