package com.google.e.a;

import com.google.e.l;

public final class b
  implements l
{
  // ERROR //
  public com.google.e.n a(com.google.e.c paramc, java.util.Map<com.google.e.e, ?> paramMap)
    throws com.google.e.j, com.google.e.g
  {
    // Byte code:
    //   0: aconst_null
    //   1: astore_3
    //   2: new 18	com/google/e/a/b/a
    //   5: dup
    //   6: aload_1
    //   7: invokevirtual 24	com/google/e/c:c	()Lcom/google/e/c/b;
    //   10: invokespecial 27	com/google/e/a/b/a:<init>	(Lcom/google/e/c/b;)V
    //   13: astore 4
    //   15: aload 4
    //   17: iconst_0
    //   18: invokevirtual 30	com/google/e/a/b/a:a	(Z)Lcom/google/e/a/a;
    //   21: astore 22
    //   23: aload 22
    //   25: invokevirtual 36	com/google/e/a/a:e	()[Lcom/google/e/p;
    //   28: astore 23
    //   30: aload 23
    //   32: astore 6
    //   34: new 38	com/google/e/a/a/a
    //   37: dup
    //   38: invokespecial 39	com/google/e/a/a/a:<init>	()V
    //   41: aload 22
    //   43: invokevirtual 42	com/google/e/a/a/a:a	(Lcom/google/e/a/a;)Lcom/google/e/c/e;
    //   46: astore 24
    //   48: aload 24
    //   50: astore 7
    //   52: aconst_null
    //   53: astore 8
    //   55: aload 7
    //   57: ifnonnull +235 -> 292
    //   60: aload 4
    //   62: iconst_1
    //   63: invokevirtual 30	com/google/e/a/b/a:a	(Z)Lcom/google/e/a/a;
    //   66: astore 18
    //   68: aload 18
    //   70: invokevirtual 36	com/google/e/a/a:e	()[Lcom/google/e/p;
    //   73: astore 19
    //   75: new 38	com/google/e/a/a/a
    //   78: dup
    //   79: invokespecial 39	com/google/e/a/a/a:<init>	()V
    //   82: aload 18
    //   84: invokevirtual 42	com/google/e/a/a/a:a	(Lcom/google/e/a/a;)Lcom/google/e/c/e;
    //   87: astore 20
    //   89: aload 20
    //   91: astore 9
    //   93: aload 19
    //   95: astore 10
    //   97: aload_2
    //   98: ifnull +108 -> 206
    //   101: aload_2
    //   102: getstatic 48	com/google/e/e:j	Lcom/google/e/e;
    //   105: invokeinterface 54 2 0
    //   110: checkcast 56	com/google/e/q
    //   113: astore 14
    //   115: aload 14
    //   117: ifnull +89 -> 206
    //   120: aload 10
    //   122: arraylength
    //   123: istore 15
    //   125: iconst_0
    //   126: istore 16
    //   128: iload 16
    //   130: iload 15
    //   132: if_icmpge +74 -> 206
    //   135: aload 14
    //   137: aload 10
    //   139: iload 16
    //   141: aaload
    //   142: invokeinterface 59 2 0
    //   147: iinc 16 1
    //   150: goto -22 -> 128
    //   153: astore 21
    //   155: aconst_null
    //   156: astore 6
    //   158: aload 21
    //   160: astore 8
    //   162: aconst_null
    //   163: astore 7
    //   165: aconst_null
    //   166: astore_3
    //   167: goto -112 -> 55
    //   170: astore 5
    //   172: aconst_null
    //   173: astore 6
    //   175: aload 5
    //   177: astore_3
    //   178: aconst_null
    //   179: astore 7
    //   181: aconst_null
    //   182: astore 8
    //   184: goto -129 -> 55
    //   187: astore 17
    //   189: aload 8
    //   191: ifnull +6 -> 197
    //   194: aload 8
    //   196: athrow
    //   197: aload_3
    //   198: ifnull +5 -> 203
    //   201: aload_3
    //   202: athrow
    //   203: aload 17
    //   205: athrow
    //   206: new 61	com/google/e/n
    //   209: dup
    //   210: aload 9
    //   212: invokevirtual 67	com/google/e/c/e:b	()Ljava/lang/String;
    //   215: aload 9
    //   217: invokevirtual 70	com/google/e/c/e:a	()[B
    //   220: aload 10
    //   222: getstatic 75	com/google/e/a:a	Lcom/google/e/a;
    //   225: invokespecial 78	com/google/e/n:<init>	(Ljava/lang/String;[B[Lcom/google/e/p;Lcom/google/e/a;)V
    //   228: astore 11
    //   230: aload 9
    //   232: invokevirtual 81	com/google/e/c/e:c	()Ljava/util/List;
    //   235: astore 12
    //   237: aload 12
    //   239: ifnull +13 -> 252
    //   242: aload 11
    //   244: getstatic 86	com/google/e/o:c	Lcom/google/e/o;
    //   247: aload 12
    //   249: invokevirtual 89	com/google/e/n:a	(Lcom/google/e/o;Ljava/lang/Object;)V
    //   252: aload 9
    //   254: invokevirtual 92	com/google/e/c/e:d	()Ljava/lang/String;
    //   257: astore 13
    //   259: aload 13
    //   261: ifnull +13 -> 274
    //   264: aload 11
    //   266: getstatic 94	com/google/e/o:d	Lcom/google/e/o;
    //   269: aload 13
    //   271: invokevirtual 89	com/google/e/n:a	(Lcom/google/e/o;Ljava/lang/Object;)V
    //   274: aload 11
    //   276: areturn
    //   277: astore 17
    //   279: goto -90 -> 189
    //   282: astore 5
    //   284: goto -109 -> 175
    //   287: astore 21
    //   289: goto -131 -> 158
    //   292: aload 7
    //   294: astore 9
    //   296: aload 6
    //   298: astore 10
    //   300: goto -203 -> 97
    //
    // Exception table:
    //   from	to	target	type
    //   15	30	153	com/google/e/j
    //   15	30	170	com/google/e/g
    //   60	89	187	com/google/e/j
    //   60	89	277	com/google/e/g
    //   34	48	282	com/google/e/g
    //   34	48	287	com/google/e/j
  }

  public void a()
  {
  }
}

/* Location:           E:\Study\Tools\apktool2_2\dex2jar-0.0.9.15\classes_viber_2_dex2jar.jar
 * Qualified Name:     com.google.e.a.b
 * JD-Core Version:    0.6.2
 */